Workbook

Sheet Start Here
B2: Beverage Competitor Intelligence
B3: What's selling in energy, sparkling water and functional drinks on Amazon.ca, who wins, why, and where the open gaps are.
B5: 125 | C5: 102 | D5: 2,927 | E5: 50%
B6: product lines | C6: brands | D6: SKUs mapped | E6: are sugar free
B8: 📊 See the category | D8: 💡 Read the insights
B9: Big picture dashboard: KPIs, category charts and the headline takeaways at a glance. | D9: The 'so what': top findings, flavour whitespace, a positioning map and an opportunity shortlist.
B14: 🥤 Add live prices | D14: 📖 How it's built
B15: Turn estimates into decision grade data. Follow the simple capture steps, drop a file, done. | D15: Plain language methodology, the honesty model, scoring, and a clickable index of all tabs.
B20: What you can trust
B21: ✓ Retrieved | C21: 47 of 125 lines have nutrition retrieved and cited in the Enrichment Log. Sort or filter column P1 on any master tab to see exactly which.
B22: ◻ Recalled | C22: 60 lines were confirmed in a batch from recall rather than a retrieval. Marked to confirm, not sourced.
B23: ✗ No source | C23: 18 lines carry no enrichment entry at all. These are the weakest rows in the file.
B24: ◻ Pending | C24: Live prices, ratings and Subscribe & Save are left blank until captured, never guessed.
B25: ⚙ Advanced | C25: Every number is reproducible code, machine checked by an automated integrity test, and built in CI.
B27: Updated 2026-10-31 · tip: every tab is one click away from the index on the “How it's built” page.

Sheet README & Methodology
B2: Amazon.ca Beverage, Competitor Intelligence Master File
B3: Build date: 2026-10-31 | v3 Enterprise | 2927 SKUs from 125 product lines / 102 brands
B5: Table of Contents (click to jump)
B6: 1. Start Here | C6: Plain language home page, the simplest way in.
B7: 2. README & Methodology | C7: Honesty model, scoring, scope, and this index.
B8: 3. Executive Dashboard | C8: KPIs, charts and the top key findings at a glance.
B9: 4. Strategic Insights | C9: Synthesized findings, flavour whitespace, positioning map, opportunity shortlist.
B10: 5. Data Dictionary | C10: Every field defined, meaning, source class, fill status.
B11: 6. M1 Sparkling Electrolyte | C11: SKU level master: sparkling electrolyte / functional sparkling.
B12: 7. M2 Electrolyte RTD | C12: SKU level master: electrolyte beverages (RTD).
B13: 8. M3 Functional Beverage | C13: SKU level master: functional beverages (still/sparkling).
B14: 9. M4 Caffeine & Energy | C14: SKU level master: caffeine & energy beverages.
B15: 10. M5 Sparkling Water & Soda | C15: SKU level master: sparkling water & soda.
B16: 11. Brand Roll up | C16: Per brand SKU counts, avg nutrition and scores.
B17: 12. Category Benchmarks | C17: Per category averages, ranges and sugar free counts.
... B28: 23. Sources | C28: Source classes and references behind the stable attributes.
B30: CRITICAL, READ FIRST
B31: Data access limitation | C31: Generated with NO live access to Amazon (HTTP 403 on search, product, and brand pages). The file therefore contains NO live prices, Subscribe & Save terms, coupons, ratings, review counts, badges, ranks, or URLs. Those cells are intentionally BLANK and amber highlighted, they are NOT fabricated.
B32: SKU model, how the rows are built | C32: The Master tabs are SKU level. Because each flavour x pack size is a separate ASIN on Amazon, every product LINE is exploded into individual SKU rows (line x flavour x pack). These are DERIVED / CANDIDATE SKUs to verify against live listings, NOT confirmed ASINs. Flavour lists are representative not exhaustive, and some specific flavour+pack combinations may not exist exactly as shown. The live catalogue cannot be enumerated without Amazon access; this expansion approximates its shape.
B33: What IS filled (and its confidence) | C33: Stable attributes, brand, SKU, format/size, typical pack, flavours, caffeine/sodium/potassium/sugar/calories, sweetener, claims, positioning, plus an honest velocity ESTIMATE, filled from manufacturer + secondary sources. Treat all as APPROXIMATE and verify on the live label. Nutrition is per single serving and varies by flavour.
B34: What is BLANK (capture live) | C34: Fields 6, 9 to 14, 23 to 26, 30 and helper H2. All amber. Filled by a live capture pass (see 'Live Capture Protocol' tab).
B35: Built in automation | C35: Fields 7,8,11,14 are LIVE FORMULAS. Enter price (F), pack (E), S&S % as decimal (J, e.g. 0.15) and coupon value (H2); per unit, per 100 mL, S&S price and stacked floor compute instantly and the red row flag clears.
B36: NEW v2, computed analytics | C36: Columns C1 to C7 on every Master tab: Caffeine/100 mL, Sugar/100 mL, Sodium/100 mL, Sugar Free flag, Health Score, Functional Score, all live formulas off the nutrition you can already see.
B37: Health Score (0 to 100) model | C37: Formula: MAX of 0 and MIN of 100 and (100 minus sugar times 2.5 minus calories times 0.12 plus 12 when sugar is 1 g or under). Higher is lighter and cleaner. Transparent and editable; based on APPROXIMATE nutrition.
B38: Functional Score (0 to 100) model | C38: Sodium (>=100=20, >=30=10) + Potassium (>=100=20) + Caffeine (>=150=20, >=50=12, else 5) + Low sugar bonus (<=1 g=15). Higher = more 'functional' payload. A heuristic, not a medical claim.
B39: Stacking model (field 14) | C39: Lowest Effective is (Price less Coupon) times (1 less the S&S percentage). Assumes coupon + subscription stack on one order (usual Amazon behaviour); confirm per listing.
B40: Velocity estimate (field 27) | C40: Bands are ESTIMATES from brand prominence/category position because live review counts/BSR were not accessible. Re derive from real #Ratings + BSR once captured. Never a unit count.
B41: Scope rules | C41: RTD only. Powders, drink mix packets, tablets EXCLUDED (Liquid I.V., Nuun, LMNT, Cure powder, Cirkul). One PRIMARY category per product; overlaps noted.
B42: Cross tab linkage | C42: Pricing & Promo and Subscription tabs are LIVE LINKED to the Master tabs, fill a price once and those tabs update automatically.
... B46: Automated integrity test | C46: 'nothing fabricated' is machine enforced, not just promised: test_competitor_intel.py asserts every commercial cell is blank, every computed column is a formula, nutrition is in range, SKU counts reconcile across tabs, and all TOC links + Enrichment Log citations resolve. It runs automatically at the end of every build and the build fails if any check fails. Run it any time with: python3 test_competitor_intel.py

Sheet Executive Dashboard
B2: Executive Dashboard
B3: Amazon.ca ready to drink beverage field | 2026-10-31 | ESTIMATE and secondary data, see README
B5: 2927 | C5: 125 | D5: 102 | E5: 5 | F5: 12.9 | G5: =(COUNT('M1 Sparkling Electrolyte'!F2:F255)+COUNT('M2 Electrolyte RTD'!F2:F405)+COUNT('M3 Functional Beverage'!F2:F556)+COUNT('M4 Caffeine & Energy'!F2:F816)+COUNT('M5 Sparkling Water & Soda'!F2:F900))/2927
B6: SKUs | C6: Product lines | D6: Brands | E6: Categories | F6: Avg sugar (g) per line | G6: Price capture %
B19: Category direction (outside data, not computed from this file)
B20: Segment | C20: Dollar growth | D20: Volume growth | E20: Base period | F20: Geography | G20: Source
B21: Sports and hydration <<< Organika's lane | C21: +1.8% | D21: -0.2% | E21: 52 weeks to 19 Apr 2026 | F21: US multi outlet | G21: Circana via Beverage Industry 2026
B22: Energy | C22: +13.7% | D22: +12.0% | E22: LTM to 9 Aug 2026 | F22: US off premise | G22: Circana via Capstone Partners 8 Oct 2026
B23: Sparkling water, non flavoured | C23: +8.1% | D23: +5.8% | E23: 52 weeks to 19 Apr 2026 | F23: US multi outlet | G23: Circana via Beverage Industry 2026
B24: Prebiotic and gut soda | C24: declining | D24: declining | E24: H1 2026 | F24: US retail | G24: Beverage Digest 5 Aug 2026
B25: Cola, full sugar | C25: -8% | D25: not stated | E25: 2025 | F25: US | G25: Mintel via Beverage Industry 2026
B26: Cola, diet and zero | C26: +11.8% | D26: not stated | E26: 2025 | F26: US | G26: Mintel via Beverage Industry 2026
B27: Sparkling water, prior period | C27: +11.6% | D27: not stated | E27: 52 weeks to 10 Aug 2025 | F27: US multi outlet | G27: Circana via Beverage Industry 2026, the comparison period for the row above
B28: Canada, all segments | C28: no data held | D28: no data held | E28: n/a | F28: Canada | G28: None held. Owner Louis, by 30 Nov 2026: commission a NielsenIQ Canada or Circana Canada pull. Until then every rate above is a US proxy.
B29: Read this before any whitespace on the Strategic Insights tab. Organika's own lane grows 1.8% in dollars with volume going backwards, so a gap found there has to be won from a named competitor, not from category growth. Sparkling water growth slowed from 11.6% to 8.1% across the two 52 week periods. The two energy reads sit on different bases and channel definitions and are not averaged. Every rate in this block is US and none of it is ecommerce. Treat it as direction only, never as a level, and never quote one as a Canadian or an Amazon figure.
B32: Key findings (full synthesis on the 'Strategic Insights' tab)
B33: • Field scope | C33: 124 competitor lines across 101 brands and 5 ready to drink categories, plus the Organika benchmark line, 2927 SKU permutations in total. Nutrition provenance is carried per line in column P1: 47 of 125 lines retrieved and cited, 60 recalled and batch confirmed, 18 with no enrichment entry. Commercial fields await live capture.
B34: • Zero sugar is now the default, not the exception | C34: 62 of 125 lines (50%) are sugar free (≤1 g). Most sugar free category: Sparkling electrolyte / functional sparkling (90%); least: Functional beverage (still/sparkling) (35%). 26 lines still carry ≥30 g sugar, a shrinking, vulnerable segment.
B35: • Natural zero sweeteners, as a snapshot not a trend | C35: 7 lines are natural zero only (stevia or monk fruit) and 5 more blend natural with artificial, against 29 artificial only. This is the composition of the lines sampled, not a direction of travel: one cross section cannot show share moving. Outside benchmark: sucralose still leads sweetener new product development while monk fruit concentrate grows fastest (Innova via Food Ingredients First, 11 Feb 2026). EFSA reaffirmed the sucralose ADI in Feb 2026, so the shift is clean label, not safety.
B36: • Energy caffeine has bifurcated | C36: 12 of 37 energy lines (32%) now dose ≥200 mg caffeine. Read against Canadian law rather than as free positioning: Health Canada caps a single serve container at 180 mg and 400 mg per litre, and treats any container that cannot be resealed as single serve at any size. The size at which a resealable container stops being single serve is NOT settled in this file: Health Canada's proposed approach says 591 mL, its Category Specific Guidance says 750 mL, and that guidance is archived and superseded by the Supplemented Foods Regulations. Do not quote a resealable threshold externally without checking the current regulation. Every line above 180 mg is therefore a US formulation or not a compliant Canadian single serve, and this file cannot yet tell which. One carve out: the ceiling governs caffeinated energy drinks sold as foods, and an energy shot is normally licensed in Canada as a natural health product instead, so a flagged shot is a question rather than a breach. That carve out covers exactly one flagged line, 5-hour Energy Shot, and the classification is not confirmed here: look the product up in Health Canada's Licensed Natural Health Products Database before treating it as settled. US demand for that tier is not flattening: energy grew 13.7% in dollars LTM to 9 Aug 2026 (Circana via Capstone).
B67: Chart data (computed from stable attributes)
B68: Category | C68: # SKUs | D68: Avg sugar (g) per line | E68: Avg caffeine (mg) per line
B69: Sparkling electrolyte / functional sparkling | C69: 254 | D69: 0.8 | E69: 34.9
B70: Electrolyte beverage (RTD) | C70: 404 | D70: 9.5 | E70: 0
B71: Functional beverage (still/sparkling) | C71: 555 | D71: 6.5 | E71: 5.5
B72: Caffeine & energy beverage | C72: 815 | D72: 19.1 | E72: 154.6
B73: Sparkling water & soda | C73: 899 | D73: 15.2 | E73: 10.8
B75: Sweetener class | C75: # Products
B76: Caloric only | C76: 41
B77: Non caloric only | C77: 41
B78: None / unsweetened | C78: 23
B79: Blend (caloric + non caloric) | C79: 16
B80: Other | C80: 4

Sheet Strategic Insights
B2: Strategic Insights & Opportunity Whitespace
B3: Synthesis of verified STABLE attributes | 2026-10-31 | every figure computed from the data set, not asserted
B5: A. What the lines in this file show (computed from this file)
B6: Field scope | C6: 124 competitor lines across 101 brands and 5 ready to drink categories, plus the Organika benchmark line, 2927 SKU permutations in total. Nutrition provenance is carried per line in column P1: 47 of 125 lines retrieved and cited, 60 recalled and batch confirmed, 18 with no enrichment entry. Commercial fields await live capture.
B7: Zero sugar is now the default, not the exception | C7: 62 of 125 lines (50%) are sugar free (≤1 g). Most sugar free category: Sparkling electrolyte / functional sparkling (90%); least: Functional beverage (still/sparkling) (35%). 26 lines still carry ≥30 g sugar, a shrinking, vulnerable segment.
B8: Natural zero sweeteners, as a snapshot not a trend | C8: 7 lines are natural zero only (stevia or monk fruit) and 5 more blend natural with artificial, against 29 artificial only. This is the composition of the lines sampled, not a direction of travel: one cross section cannot show share moving. Outside benchmark: sucralose still leads sweetener new product development while monk fruit concentrate grows fastest (Innova via Food Ingredients First, 11 Feb 2026). EFSA reaffirmed the sucralose ADI in Feb 2026, so the shift is clean label, not safety.
B9: Energy caffeine has bifurcated | C9: 12 of 37 energy lines (32%) now dose ≥200 mg caffeine. Read against Canadian law rather than as free positioning: Health Canada caps a single serve container at 180 mg and 400 mg per litre, and treats any container that cannot be resealed as single serve at any size. The size at which a resealable container stops being single serve is NOT settled in this file: Health Canada's proposed approach says 591 mL, its Category Specific Guidance says 750 mL, and that guidance is archived and superseded by the Supplemented Foods Regulations. Do not quote a resealable threshold externally without checking the current regulation. Every line above 180 mg is therefore a US formulation or not a compliant Canadian single serve, and this file cannot yet tell which. One carve out: the ceiling governs caffeinated energy drinks sold as foods, and an energy shot is normally licensed in Canada as a natural health product instead, so a flagged shot is a question rather than a breach. That carve out covers exactly one flagged line, 5-hour Energy Shot, and the classification is not confirmed here: look the product up in Health Canada's Licensed Natural Health Products Database before treating it as settled. US demand for that tier is not flattening: energy grew 13.7% in dollars LTM to 9 Aug 2026 (Circana via Capstone).
B10: Flavour whitespace concentrated in a few families | C10: Least served flavour families across the field: Cola/Root Beer (4 brands); Coconut (9 brands); Ginger (11 brands). These are the clearest line extension gaps for a challenger brand (see Flavour Whitespace matrix below).
B11: Functional + electrolyte crossover is the structural growth vector | C11: Categories 1 to 3 (functional/electrolyte sparkling) skew sugar free with added minerals/vitamins; they are where premium price and Subscribe & Save retention concentrate once live pricing is captured.
B13: B. Flavour whitespace, # distinct brands offering each family, by category (low = opportunity)
B14: Flavour family | C14: Sparkling electrolyte / functional sparkling | D14: Electrolyte beverage (RTD) | E14: Functional beverage (still/sparkling) | F14: Caffeine & energy beverage | G14: Sparkling water & soda | H14: All
B15: Cola/Root Beer | C15: 0 | D15: 0 | E15: 2 | F15: 2 | G15: 1 | H15: 4
B16: Citrus (Lem/Lime) | C16: 9 | D16: 5 | E16: 12 | F16: 11 | G16: 19 | H16: 54
B17: Orange/Mango | C17: 3 | D17: 6 | E17: 14 | F17: 12 | G17: 12 | H17: 47
B18: Berry/Rasp | C18: 8 | D18: 11 | E18: 18 | F18: 18 | G18: 13 | H18: 67
B19: Cherry | C19: 4 | D19: 4 | E19: 8 | F19: 2 | G19: 14 | H19: 32
B20: Grape | C20: 0 | D20: 5 | E20: 2 | F20: 1 | G20: 5 | H20: 13
B21: Watermelon | C21: 2 | D21: 6 | E21: 4 | F21: 7 | G21: 5 | H21: 23
B22: Peach | C22: 1 | D22: 5 | E22: 5 | F22: 9 | G22: 4 | H22: 24
B23: Tropical/Pineapple | C23: 3 | D23: 5 | E23: 8 | F23: 11 | G23: 6 | H23: 32
B24: Grapefruit | C24: 3 | D24: 0 | E24: 2 | F24: 1 | G24: 8 | H24: 14
B25: Coconut | C25: 2 | D25: 2 | E25: 4 | F25: 0 | G25: 1 | H25: 9
B26: Ginger | C26: 1 | D26: 0 | E26: 9 | F26: 1 | G26: 1 | H26: 11
... B28: Original/Plain | C28: 2 | D28: 4 | E28: 4 | F28: 8 | G28: 21 | H28: 38
B29: Opportunity heat, red = 0 brands (clear whitespace in that category) · amber = 1 to 2 brands (thinly served).
B31: C. Nutrition positioning by category
B32: Category | C32: Lines | D32: % sugar free | E32: Median sugar (g) | F32: Caffeine range (mg) | G32: Positioning read
B33: Sparkling electrolyte / functional sparkling | C33: 10 | D33: 90% | E33: 0 | F33: 0 to 120 | G33: Premium clean tier; sugar free + minerals is table stakes.
B34: Electrolyte beverage (RTD) | C34: 21 | D34: 38% | E34: 3 | F34: 0 | G34: Performance hydration; sodium/potassium load is the differentiator.
B35: Functional beverage (still/sparkling) | C35: 20 | D35: 35% | E35: 5.5 | F35: 0 to 55 | G35: Benefit led (gut/adaptogen/vitamin); sugar varies widely, clean label gap exists.
B36: Caffeine & energy beverage | C36: 37 | D36: 43% | E36: 14 | F36: 18 to 300 | G36: Caffeine defined; dose tier + sweetener choice decide the shelf.
B37: Sparkling water & soda | C37: 37 | D37: 59% | E37: 0 | F37: 0 to 69 | G37: Split between zero everything seltzer and full sugar legacy soda.
B39: D. Sweetener strategy mix (count of lines)
B40: Sweetener strategy | C40: # lines | D40: % of field
B41: Caloric (sugar) | C41: 41 | D41: 33%
B42: Zero (artificial) | C42: 29 | D42: 23%
B43: Unsweetened | C43: 23 | D43: 18%
B44: Caloric + sweetener blend | C44: 16 | D44: 13%
B45: Zero (natural: stevia/monk) | C45: 7 | D45: 6%
B46: Zero (natural + artificial) | C46: 5 | D46: 4%
B47: Other | C47: 4 | D47: 3%
B49: E. What I recommend (analyst judgement, not computed. Everything above this rule is data; everything below is a call.)
B50: 1. Natural zero line extension into thin flavour families (Cola/Root Beer, Coconut, Ginger), combines the thinnest flavour families in this file with the sweetener wedge Innova reports growing fastest in new product development (via Food Ingredients First, 11 Feb 2026). This file cannot itself show share moving.
B51: 2. Dose to whichever Canadian limit binds first, not to 180 mg. Two ceilings apply at once and the lower one wins: 180 mg per single serve container, and 400 mg per litre. In a 355 mL can, the size of the Organika benchmark, 400 mg per litre binds and the legal maximum is 142 mg, not 180. In a 473 mL can it is 189 mg, so there 180 mg binds. Pair whatever dose binds with stevia or monk fruit to avoid the artificial sweetener objection.
B52: 3. Clean label functional (Cat 3): median sugar is the widest ranging, a genuinely low sugar gut/adaptogen entry stands out against sugary incumbents.
B53: 4. Premium sparkling electrolyte (Cat 1) is where Subscribe & Save retention + price premium concentrate; prioritize live price capture here first to validate margin headroom.
B54: 5. Defensive watch: high sugar legacy lines (≥30 g) are the segment most exposed to the zero sugar shift, track their promo cadence once commercial capture is live.
B56: All findings derive from verified STABLE attributes (nutrition/flavour/sweetener/positioning). They do NOT depend on live commercial data; price/velocity dependent conclusions are flagged as pending live capture.
B58: F. Competitive positioning map, sugar vs caffeine (per 100 mL), one series per category | T58: Scatter source data, kept visible so the chart plots
B59: Bottom left = light/low stim waters & seltzers · right = sugary · top = high caffeine energy. Sparse regions = positioning whitespace. | T59: 1) sugar/100mL | U59: 1) caf/100mL | V59: 2) sugar/100mL | W59: 2) caf/100mL | X59: 3) sugar/100mL | Y59: 3) caf/100mL | Z59: 4) sugar/100mL | AA59: 4) caf/100mL | AB59: 5) sugar/100mL | AC59: 5) caf/100mL
T60: 0 | U60: 0 | V60: 5.75 | W60: 0 | X60: 1.13 | Y60: 0 | Z60: 10.8 | AA60: 32 | AB60: 0.56 | AC60: 0
T61: 0 | U61: 0 | V61: 0 | W61: 0 | X61: 1.41 | Y61: 0 | Z61: 0 | AA61: 32 | AB61: 0 | AC61: 0
T62: 0 | U62: 14.6 | V62: 5.92 | W62: 0 | X62: 2.54 | Y62: 0 | Z62: 11.42 | AA62: 33.8 | AB62: 0 | AC62: 0
T63: 0 | U63: 21.4 | V63: 0 | W63: 0 | X63: 1.69 | Y63: 0 | Z63: 0 | AA63: 31.7 | AB63: 0 | AC63: 0
T64: 0 | U64: 0 | V64: 6.13 | W64: 0 | X64: 1.69 | Y64: 0 | Z64: 0 | AA64: 56.3 | AB64: 0 | AC64: 0
T65: 0 | U65: 4.2 | V65: 0.63 | W65: 0 | X65: 2.5 | Y65: 2.9 | Z65: 0 | AA65: 57.1 | AB65: 0 | AC65: 0
T66: 0 | U66: 0 | V66: 0.4 | W66: 0 | X66: 1.48 | Y66: 3.2 | Z66: 0 | AA66: 56.3 | AB66: 4.85 | AC66: 0
T67: 0 | U67: 33.8 | V67: 0.38 | W67: 0 | X67: 0 | Y67: 4 | Z67: 0 | AA67: 42.3 | AB67: 0 | AC67: 0
T68: 2.25 | U68: 0 | V68: 0 | W68: 0 | X68: 0.28 | Y68: 0 | Z68: 0 | AA68: 63.4 | AB68: 0 | AC68: 0
T69: 0 | U69: 14.8 | V69: 0 | W69: 0 | X69: 0.2 | Y69: 0 | Z69: 0 | AA69: 56.3 | AB69: 0 | AC69: 0
V70: 2.5 | W70: 0 | X70: 4.57 | Y70: 0 | Z70: 0 | AA70: 63.4 | AB70: 0 | AC70: 0
V71: 2.03 | W71: 0 | X71: 0 | Y71: 0 | Z71: 6.55 | AA71: 33.8 | AB71: 0 | AC71: 8.5
V72: 3.33 | W72: 0 | X72: 0.19 | Y72: 10.4 | Z72: 8.4 | AA72: 40 | AB72: 0 | AC72: 0
V73: 3.84 | W73: 0 | X73: 0 | Y73: 0 | Z73: 6.11 | AA73: 32.8 | AB73: 0 | AC73: 0
V74: 0 | W74: 0 | X74: 1.69 | Y74: 0 | Z74: 11.42 | AA74: 33.8 | AB74: 10.99 | AC74: 9.6
V75: 0 | W75: 0 | X75: 0.28 | Y75: 0 | Z75: 6.31 | AA75: 30.4 | AB75: 0 | AC75: 0
V76: 0 | W76: 0 | X76: 1.14 | Y76: 0 | Z76: 0 | AA76: 42.3 | AB76: 0 | AC76: 0
V77: 0 | W77: 0 | X77: 2.42 | Y77: 3.6 | Z77: 0 | AA77: 33.8 | AB77: 11.55 | AC77: 10.7
V78: 1.18 | W78: 0 | X78: 1.88 | Y78: 0 | Z78: 0 | AA78: 33.8 | AB78: 0 | AC78: 19.4
V79: 0.85 | W79: 0 | X79: 4 | Y79: 0 | Z79: 12.26 | AA79: 33.8 | AB79: 0 | AC79: 9.9
V80: 2.22 | W80: 0 | Z80: 11.21 | AA80: 33.8 | AB80: 0 | AC80: 9.6
Z81: 12.26 | AA81: 30 | AB81: 0 | AC81: 13
Z82: 0 | AA82: 350.9 | AB82: 10.7 | AC82: 0
Z83: 7.88 | AA83: 45 | AB83: 0 | AC83: 0
Z84: 10.8 | AA84: 32 | AB84: 12.39 | AC84: 0
Z85: 0 | AA85: 63.4 | AB85: 10.7 | AC85: 0
Z86: 0 | AA86: 38.1 | AB86: 12.96 | AC86: 15.2
Z87: 0 | AA87: 63.4 | AB87: 11.27 | AC87: 11.5
Z88: 7.21 | AA88: 3.2 | AB88: 10.14 | AC88: 0
Z89: 5.85 | AA89: 12.8 | AB89: 9.3 | AC89: 0
Z90: 6.4 | AA90: 8.2 | AB90: 12.96 | AC90: 0
Z91: 4.91 | AA91: 3 | AB91: 13.8 | AC91: 0
Z92: 4.44 | AA92: 8.9 | AB92: 0 | AC92: 0
... Z96: 11.03 | AA96: 32 | AB96: 0 | AC96: 0

Sheet Data Dictionary
A1: Field # | B1: Field name | C1: Definition / how to read it | D1: Source class | E1: Status in this file
A2: 1 | B2: Brand | C2: Manufacturer/brand name. | D2: Stable | E2: Filled (approx)
A3: 2 | B3: Product Line / SKU Name | C3: Exact product/line name; confirm spelling. | D3: Stable | E3: Filled (approx)
A4: 3 | B4: Category | C4: One of five scope categories (primary). | D4: Assigned | E4: Filled
A5: 4 | B5: Format & Size | C5: Container type + single unit size. | D5: Stable | E5: Filled (approx)
A6: 5 | B6: Pack Count | C6: Units per multipack (typical). | D6: Stable | E6: Filled (typical)
A7: 6 | B7: One Time Price (CAD) | C7: List one time price. | D7: LIVE Amazon.ca | E7: BLANK, capture
A8: 7 | B8: Price / Unit (CAD) | C8: Price divided by pack count. | D8: Calculated | E8: Auto
A9: 8 | B9: Price / 100 mL (CAD) | C9: Price divided by total volume, times 100. | D9: Calculated | E9: Auto
A10: 9 | B10: S&S Offered (Y/N) | C10: Subscribe & Save offered? | D10: LIVE Amazon.ca | E10: BLANK, capture
A11: 10 | B11: S&S Discount % | C11: Enter decimal (0.15=15%). | D11: LIVE Amazon.ca | E11: BLANK, capture
A12: 11 | B12: S&S Price After Discount | C12: Price less the Subscribe and Save percentage. | D12: Calculated | E12: Auto
... A47: P3 | B47: Row Flag | C47: Flags unverified rows. | D47: Meta | E47: Filled

Sheet M1 Sparkling Electrolyte
A1: 1. Brand | B1: 2. Product Line / SKU Name | C1: 3. Category | D1: 4. Format & Size | E1: 5. Pack Count | F1: 6. One Time Price (CAD) | G1: 7. Price / Unit (CAD) | H1: 8. Price / 100 mL (CAD) | I1: 9. S&S Offered (Y/N) | J1: 10. S&S Discount % | K1: 11. S&S Price After Disc. | L1: 12. Coupon on Listing (Y/N + value) | M1: 13. Promotion Text | N1: 14. Lowest Effective Price (stacked) | O1: 15. All Flavours in Listing | P1: 16. Caffeine / Serving (mg) | Q1: 17. Sodium / Serving (mg) | R1: 18. Potassium / Serving (mg) | S1: 19. Sugar / Serving (g) | T1: 20. Calories / Serving | U1: 21. Sweetener Type | V1: 22. Key Functional Claims | W1: 23. Star Rating | X1: 24. Number of Ratings | Y1: 25. Amazon Badge | Z1: 26. Bestseller Rank in Category | AA1: 27a. Est. Weekly Velocity (band) | AB1: 27b. Velocity Signal Used | AC1: 28. Biggest Selling Message | AD1: 29. Why a Shopper Chooses This | AE1: 30. Direct Product URL | AF1: C1. Caffeine /100 mL (mg) | AG1: C2. Sugar /100 mL (g) | AH1: C3. Sodium /100 mL (mg) | AI1: C4. Sugar Free? (<=1 g) | AJ1: C5. Health Score (0 to 100) | AK1: C6. Functional Score (0 to 100) | AL1: H1. Unit Vol (mL) [calc helper] | AM1: H2. Coupon Value (CAD) [calc helper] | AN1: C7. Over Health Canada caffeine ceiling (180 mg per container or 400 mg per litre)? | AO1: 31. Supplemented Food Facts table (Y/N) | AP1: 32. Caution Identifier (Y/N/not required) | AQ1: 33. Bilingual EN and FR panel (Y/N) | AR1: P1. Attribute Provenance | AS1: P2. Commercial Field Status | AT1: P3. Row Flag
A2: Organika | B2: Organika Sparkling Electrolyte (BENCHMARK) | Raspberry | single 355mL | C2: 1) Sparkling electrolyte / functional sparkling | D2: 355 mL can | E2: 1 | G2: =IF(AND(ISNUMBER($F2),ISNUMBER($E2),$E2<>0),$F2/$E2,"") | H2: =IF(AND(ISNUMBER($F2),ISNUMBER($AL2),ISNUMBER($E2),($AL2*$E2)<>0),$F2/($AL2*$E2)*100,"") | K2: =IF(AND(ISNUMBER($F2),ISNUMBER($J2)),$F2*(1-$J2),"") | N2: =IF(ISNUMBER($F2),($F2-IF(ISNUMBER($AM2),$AM2,0))*(1-IF(ISNUMBER($J2),$J2,0)),"") | O2: Raspberry | P2: 0 | Q2: Split not published, 290 mg combined | R2: Split not published, 290 mg combined | S2: 0 | T2: 10 | U2: Not named on launch materials; no artificial sweeteners claimed | V2: BENCHMARK, Organika's own line. 290 mg combined electrolytes per 355 mL can from magnesium glycinate, potassium and sodium, plus Fibersol prebiotic fibre. Zero sugar, no caffeine, 10 calories. Launched August 2026. The per mineral split is not published: sodium and potassium carry no number on purpose, because only the combined figure is published. They are the single highest value cells to fill from the can, and until they are filled this line's Functional Score is understated by up to 40 points. | AA2: n/a | AB2: Benchmark line, not a competitor. No velocity estimated. | AC2: Organika's own sparkling electrolyte, read every competitor against this row | AD2: This is the row to beat, not a shopper choice. | AF2: =IF(AND(ISNUMBER($P2),ISNUMBER($AL2),$AL2<>0),ROUND($P2/$AL2*100,1),"") | AG2: =IF(AND(ISNUMBER($S2),ISNUMBER($AL2),$AL2<>0),ROUND($S2/$AL2*100,2),"") | AH2: =IF(AND(ISNUMBER($Q2),ISNUMBER($AL2),$AL2<>0),ROUND($Q2/$AL2*100,1),"") | AI2: =IF(ISNUMBER($S2),IF($S2<=1,"Yes","No"),"n/a") | AJ2: =IF(ISNUMBER($S2),ROUND(MAX(0,MIN(100,100-$S2*2.5-IF(ISNUMBER($T2),$T2,0)*0.12+IF($S2<=1,12,0))),0),"") | AK2: =IF(ISNUMBER($Q2),IF($Q2>=100,20,IF($Q2>=30,10,0)),0)+IF(ISNUMBER($R2),IF($R2>=100,20,0),0)+IF(ISNUMBER($P2),IF($P2>=150,20,IF($P2>=50,12,5)),0)+IF(ISNUMBER($S2),IF($S2<=1,15,0),0) | AL2: 355 | AN2: =IF(AND(ISNUMBER($P2),ISNUMBER($AL2),$AL2<>0),IF(OR($P2>180,$P2/$AL2*1000>400),"Over ceiling, confirm SKU","Within"),"n/a") | AR2: No enrichment entry, to confirm | AS2: BLANK -> requires live Amazon.ca capture | AT2: Unverified commercial data
A3: Organika | B3: Organika Sparkling Electrolyte (BENCHMARK) | Raspberry | 4 pack 355mL | C3: 1) Sparkling electrolyte / functional sparkling | D3: 355 mL can | E3: 4 | G3: =IF(AND(ISNUMBER($F3),ISNUMBER($E3),$E3<>0),$F3/$E3,"") | H3: =IF(AND(ISNUMBER($F3),ISNUMBER($AL3),ISNUMBER($E3),($AL3*$E3)<>0),$F3/($AL3*$E3)*100,"") | K3: =IF(AND(ISNUMBER($F3),ISNUMBER($J3)),$F3*(1-$J3),"") | N3: =IF(ISNUMBER($F3),($F3-IF(ISNUMBER($AM3),$AM3,0))*(1-IF(ISNUMBER($J3),$J3,0)),"") | O3: Raspberry | P3: 0 | Q3: Split not published, 290 mg combined | R3: Split not published, 290 mg combined | S3: 0 | T3: 10 | U3: Not named on launch materials; no artificial sweeteners claimed | V3: BENCHMARK, Organika's own line. 290 mg combined electrolytes per 355 mL can from magnesium glycinate, potassium and sodium, plus Fibersol prebiotic fibre. Zero sugar, no caffeine, 10 calories. Launched August 2026. The per mineral split is not published: sodium and potassium carry no number on purpose, because only the combined figure is published. They are the single highest value cells to fill from the can, and until they are filled this line's Functional Score is understated by up to 40 points. | AA3: n/a | AB3: Benchmark line, not a competitor. No velocity estimated. | AC3: Organika's own sparkling electrolyte, read every competitor against this row | AD3: This is the row to beat, not a shopper choice. | AF3: =IF(AND(ISNUMBER($P3),ISNUMBER($AL3),$AL3<>0),ROUND($P3/$AL3*100,1),"") | AG3: =IF(AND(ISNUMBER($S3),ISNUMBER($AL3),$AL3<>0),ROUND($S3/$AL3*100,2),"") | AH3: =IF(AND(ISNUMBER($Q3),ISNUMBER($AL3),$AL3<>0),ROUND($Q3/$AL3*100,1),"") | AI3: =IF(ISNUMBER($S3),IF($S3<=1,"Yes","No"),"n/a") | AJ3: =IF(ISNUMBER($S3),ROUND(MAX(0,MIN(100,100-$S3*2.5-IF(ISNUMBER($T3),$T3,0)*0.12+IF($S3<=1,12,0))),0),"") | AK3: =IF(ISNUMBER($Q3),IF($Q3>=100,20,IF($Q3>=30,10,0)),0)+IF(ISNUMBER($R3),IF($R3>=100,20,0),0)+IF(ISNUMBER($P3),IF($P3>=150,20,IF($P3>=50,12,5)),0)+IF(ISNUMBER($S3),IF($S3<=1,15,0),0) | AL3: 355 | AN3: =IF(AND(ISNUMBER($P3),ISNUMBER($AL3),$AL3<>0),IF(OR($P3>180,$P3/$AL3*1000>400),"Over ceiling, confirm SKU","Within"),"n/a") | AR3: No enrichment entry, to confirm | AS3: BLANK -> requires live Amazon.ca capture | AT3: Unverified commercial data
A4: Organika | B4: Organika Sparkling Electrolyte (BENCHMARK) | Lime Lemon | single 355mL | C4: 1) Sparkling electrolyte / functional sparkling | D4: 355 mL can | E4: 1 | G4: =IF(AND(ISNUMBER($F4),ISNUMBER($E4),$E4<>0),$F4/$E4,"") | H4: =IF(AND(ISNUMBER($F4),ISNUMBER($AL4),ISNUMBER($E4),($AL4*$E4)<>0),$F4/($AL4*$E4)*100,"") | K4: =IF(AND(ISNUMBER($F4),ISNUMBER($J4)),$F4*(1-$J4),"") | N4: =IF(ISNUMBER($F4),($F4-IF(ISNUMBER($AM4),$AM4,0))*(1-IF(ISNUMBER($J4),$J4,0)),"") | O4: Lime Lemon | P4: 0 | Q4: Split not published, 290 mg combined | R4: Split not published, 290 mg combined | S4: 0 | T4: 10 | U4: Not named on launch materials; no artificial sweeteners claimed | V4: BENCHMARK, Organika's own line. 290 mg combined electrolytes per 355 mL can from magnesium glycinate, potassium and sodium, plus Fibersol prebiotic fibre. Zero sugar, no caffeine, 10 calories. Launched August 2026. The per mineral split is not published: sodium and potassium carry no number on purpose, because only the combined figure is published. They are the single highest value cells to fill from the can, and until they are filled this line's Functional Score is understated by up to 40 points. | AA4: n/a | AB4: Benchmark line, not a competitor. No velocity estimated. | AC4: Organika's own sparkling electrolyte, read every competitor against this row | AD4: This is the row to beat, not a shopper choice. | AF4: =IF(AND(ISNUMBER($P4),ISNUMBER($AL4),$AL4<>0),ROUND($P4/$AL4*100,1),"") | AG4: =IF(AND(ISNUMBER($S4),ISNUMBER($AL4),$AL4<>0),ROUND($S4/$AL4*100,2),"") | AH4: =IF(AND(ISNUMBER($Q4),ISNUMBER($AL4),$AL4<>0),ROUND($Q4/$AL4*100,1),"") | AI4: =IF(ISNUMBER($S4),IF($S4<=1,"Yes","No"),"n/a") | AJ4: =IF(ISNUMBER($S4),ROUND(MAX(0,MIN(100,100-$S4*2.5-IF(ISNUMBER($T4),$T4,0)*0.12+IF($S4<=1,12,0))),0),"") | AK4: =IF(ISNUMBER($Q4),IF($Q4>=100,20,IF($Q4>=30,10,0)),0)+IF(ISNUMBER($R4),IF($R4>=100,20,0),0)+IF(ISNUMBER($P4),IF($P4>=150,20,IF($P4>=50,12,5)),0)+IF(ISNUMBER($S4),IF($S4<=1,15,0),0) | AL4: 355 | AN4: =IF(AND(ISNUMBER($P4),ISNUMBER($AL4),$AL4<>0),IF(OR($P4>180,$P4/$AL4*1000>400),"Over ceiling, confirm SKU","Within"),"n/a") | AR4: No enrichment entry, to confirm | AS4: BLANK -> requires live Amazon.ca capture | AT4: Unverified commercial data
A5: Organika | B5: Organika Sparkling Electrolyte (BENCHMARK) | Lime Lemon | 4 pack 355mL | C5: 1) Sparkling electrolyte / functional sparkling | D5: 355 mL can | E5: 4 | G5: =IF(AND(ISNUMBER($F5),ISNUMBER($E5),$E5<>0),$F5/$E5,"") | H5: =IF(AND(ISNUMBER($F5),ISNUMBER($AL5),ISNUMBER($E5),($AL5*$E5)<>0),$F5/($AL5*$E5)*100,"") | K5: =IF(AND(ISNUMBER($F5),ISNUMBER($J5)),$F5*(1-$J5),"") | N5: =IF(ISNUMBER($F5),($F5-IF(ISNUMBER($AM5),$AM5,0))*(1-IF(ISNUMBER($J5),$J5,0)),"") | O5: Lime Lemon | P5: 0 | Q5: Split not published, 290 mg combined | R5: Split not published, 290 mg combined | S5: 0 | T5: 10 | U5: Not named on launch materials; no artificial sweeteners claimed | V5: BENCHMARK, Organika's own line. 290 mg combined electrolytes per 355 mL can from magnesium glycinate, potassium and sodium, plus Fibersol prebiotic fibre. Zero sugar, no caffeine, 10 calories. Launched August 2026. The per mineral split is not published: sodium and potassium carry no number on purpose, because only the combined figure is published. They are the single highest value cells to fill from the can, and until they are filled this line's Functional Score is understated by up to 40 points. | AA5: n/a | AB5: Benchmark line, not a competitor. No velocity estimated. | AC5: Organika's own sparkling electrolyte, read every competitor against this row | AD5: This is the row to beat, not a shopper choice. | AF5: =IF(AND(ISNUMBER($P5),ISNUMBER($AL5),$AL5<>0),ROUND($P5/$AL5*100,1),"") | AG5: =IF(AND(ISNUMBER($S5),ISNUMBER($AL5),$AL5<>0),ROUND($S5/$AL5*100,2),"") | AH5: =IF(AND(ISNUMBER($Q5),ISNUMBER($AL5),$AL5<>0),ROUND($Q5/$AL5*100,1),"") | AI5: =IF(ISNUMBER($S5),IF($S5<=1,"Yes","No"),"n/a") | AJ5: =IF(ISNUMBER($S5),ROUND(MAX(0,MIN(100,100-$S5*2.5-IF(ISNUMBER($T5),$T5,0)*0.12+IF($S5<=1,12,0))),0),"") | AK5: =IF(ISNUMBER($Q5),IF($Q5>=100,20,IF($Q5>=30,10,0)),0)+IF(ISNUMBER($R5),IF($R5>=100,20,0),0)+IF(ISNUMBER($P5),IF($P5>=150,20,IF($P5>=50,12,5)),0)+IF(ISNUMBER($S5),IF($S5<=1,15,0),0) | AL5: 355 | AN5: =IF(AND(ISNUMBER($P5),ISNUMBER($AL5),$AL5<>0),IF(OR($P5>180,$P5/$AL5*1000>400),"Over ceiling, confirm SKU","Within"),"n/a") | AR5: No enrichment entry, to confirm | AS5: BLANK -> requires live Amazon.ca capture | AT5: Unverified commercial data
A6: Organika | B6: Organika Sparkling Electrolyte (BENCHMARK) | Passion Fruit Pineapple | single 355mL | C6: 1) Sparkling electrolyte / functional sparkling | D6: 355 mL can | E6: 1 | G6: =IF(AND(ISNUMBER($F6),ISNUMBER($E6),$E6<>0),$F6/$E6,"") | H6: =IF(AND(ISNUMBER($F6),ISNUMBER($AL6),ISNUMBER($E6),($AL6*$E6)<>0),$F6/($AL6*$E6)*100,"") | K6: =IF(AND(ISNUMBER($F6),ISNUMBER($J6)),$F6*(1-$J6),"") | N6: =IF(ISNUMBER($F6),($F6-IF(ISNUMBER($AM6),$AM6,0))*(1-IF(ISNUMBER($J6),$J6,0)),"") | O6: Passion Fruit Pineapple | P6: 0 | Q6: Split not published, 290 mg combined | R6: Split not published, 290 mg combined | S6: 0 | T6: 10 | U6: Not named on launch materials; no artificial sweeteners claimed | V6: BENCHMARK, Organika's own line. 290 mg combined electrolytes per 355 mL can from magnesium glycinate, potassium and sodium, plus Fibersol prebiotic fibre. Zero sugar, no caffeine, 10 calories. Launched August 2026. The per mineral split is not published: sodium and potassium carry no number on purpose, because only the combined figure is published. They are the single highest value cells to fill from the can, and until they are filled this line's Functional Score is understated by up to 40 points. | AA6: n/a | AB6: Benchmark line, not a competitor. No velocity estimated. | AC6: Organika's own sparkling electrolyte, read every competitor against this row | AD6: This is the row to beat, not a shopper choice. | AF6: =IF(AND(ISNUMBER($P6),ISNUMBER($AL6),$AL6<>0),ROUND($P6/$AL6*100,1),"") | AG6: =IF(AND(ISNUMBER($S6),ISNUMBER($AL6),$AL6<>0),ROUND($S6/$AL6*100,2),"") | AH6: =IF(AND(ISNUMBER($Q6),ISNUMBER($AL6),$AL6<>0),ROUND($Q6/$AL6*100,1),"") | AI6: =IF(ISNUMBER($S6),IF($S6<=1,"Yes","No"),"n/a") | AJ6: =IF(ISNUMBER($S6),ROUND(MAX(0,MIN(100,100-$S6*2.5-IF(ISNUMBER($T6),$T6,0)*0.12+IF($S6<=1,12,0))),0),"") | AK6: =IF(ISNUMBER($Q6),IF($Q6>=100,20,IF($Q6>=30,10,0)),0)+IF(ISNUMBER($R6),IF($R6>=100,20,0),0)+IF(ISNUMBER($P6),IF($P6>=150,20,IF($P6>=50,12,5)),0)+IF(ISNUMBER($S6),IF($S6<=1,15,0),0) | AL6: 355 | AN6: =IF(AND(ISNUMBER($P6),ISNUMBER($AL6),$AL6<>0),IF(OR($P6>180,$P6/$AL6*1000>400),"Over ceiling, confirm SKU","Within"),"n/a") | AR6: No enrichment entry, to confirm | AS6: BLANK -> requires live Amazon.ca capture | AT6: Unverified commercial data
A7: Organika | B7: Organika Sparkling Electrolyte (BENCHMARK) | Passion Fruit Pineapple | 4 pack 355mL | C7: 1) Sparkling electrolyte / functional sparkling | D7: 355 mL can | E7: 4 | G7: =IF(AND(ISNUMBER($F7),ISNUMBER($E7),$E7<>0),$F7/$E7,"") | H7: =IF(AND(ISNUMBER($F7),ISNUMBER($AL7),ISNUMBER($E7),($AL7*$E7)<>0),$F7/($AL7*$E7)*100,"") | K7: =IF(AND(ISNUMBER($F7),ISNUMBER($J7)),$F7*(1-$J7),"") | N7: =IF(ISNUMBER($F7),($F7-IF(ISNUMBER($AM7),$AM7,0))*(1-IF(ISNUMBER($J7),$J7,0)),"") | O7: Passion Fruit Pineapple | P7: 0 | Q7: Split not published, 290 mg combined | R7: Split not published, 290 mg combined | S7: 0 | T7: 10 | U7: Not named on launch materials; no artificial sweeteners claimed | V7: BENCHMARK, Organika's own line. 290 mg combined electrolytes per 355 mL can from magnesium glycinate, potassium and sodium, plus Fibersol prebiotic fibre. Zero sugar, no caffeine, 10 calories. Launched August 2026. The per mineral split is not published: sodium and potassium carry no number on purpose, because only the combined figure is published. They are the single highest value cells to fill from the can, and until they are filled this line's Functional Score is understated by up to 40 points. | AA7: n/a | AB7: Benchmark line, not a competitor. No velocity estimated. | AC7: Organika's own sparkling electrolyte, read every competitor against this row | AD7: This is the row to beat, not a shopper choice. | AF7: =IF(AND(ISNUMBER($P7),ISNUMBER($AL7),$AL7<>0),ROUND($P7/$AL7*100,1),"") | AG7: =IF(AND(ISNUMBER($S7),ISNUMBER($AL7),$AL7<>0),ROUND($S7/$AL7*100,2),"") | AH7: =IF(AND(ISNUMBER($Q7),ISNUMBER($AL7),$AL7<>0),ROUND($Q7/$AL7*100,1),"") | AI7: =IF(ISNUMBER($S7),IF($S7<=1,"Yes","No"),"n/a") | AJ7: =IF(ISNUMBER($S7),ROUND(MAX(0,MIN(100,100-$S7*2.5-IF(ISNUMBER($T7),$T7,0)*0.12+IF($S7<=1,12,0))),0),"") | AK7: =IF(ISNUMBER($Q7),IF($Q7>=100,20,IF($Q7>=30,10,0)),0)+IF(ISNUMBER($R7),IF($R7>=100,20,0),0)+IF(ISNUMBER($P7),IF($P7>=150,20,IF($P7>=50,12,5)),0)+IF(ISNUMBER($S7),IF($S7<=1,15,0),0) | AL7: 355 | AN7: =IF(AND(ISNUMBER($P7),ISNUMBER($AL7),$AL7<>0),IF(OR($P7>180,$P7/$AL7*1000>400),"Over ceiling, confirm SKU","Within"),"n/a") | AR7: No enrichment entry, to confirm | AS7: BLANK -> requires live Amazon.ca capture | AT7: Unverified commercial data
A8: Sparkling Ice | B8: Sparkling Ice (+ Antioxidants & Vitamins) | Black Raspberry | single 503mL | C8: 1) Sparkling electrolyte / functional sparkling | D8: 503 mL bottle | E8: 1 | G8: =IF(AND(ISNUMBER($F8),ISNUMBER($E8),$E8<>0),$F8/$E8,"") | H8: =IF(AND(ISNUMBER($F8),ISNUMBER($AL8),ISNUMBER($E8),($AL8*$E8)<>0),$F8/($AL8*$E8)*100,"") | K8: =IF(AND(ISNUMBER($F8),ISNUMBER($J8)),$F8*(1-$J8),"") | N8: =IF(ISNUMBER($F8),($F8-IF(ISNUMBER($AM8),$AM8,0))*(1-IF(ISNUMBER($J8),$J8,0)),"") | O8: Black Raspberry | P8: 0 | Q8: 0 | R8: 30 | S8: 0 | T8: 5 | U8: Sucralose | V8: Zero sugar, vitamins A/D/B, antioxidants (green tea), bold flavour | AA8: High | AB8: Mass market functional sparkling; strong shelf share | AC8: Bold zero sugar sparkling with added vitamins | AD8: Big flavour and added vitamins at zero sugar. | AF8: =IF(AND(ISNUMBER($P8),ISNUMBER($AL8),$AL8<>0),ROUND($P8/$AL8*100,1),"") | AG8: =IF(AND(ISNUMBER($S8),ISNUMBER($AL8),$AL8<>0),ROUND($S8/$AL8*100,2),"") | AH8: =IF(AND(ISNUMBER($Q8),ISNUMBER($AL8),$AL8<>0),ROUND($Q8/$AL8*100,1),"") | AI8: =IF(ISNUMBER($S8),IF($S8<=1,"Yes","No"),"n/a") | AJ8: =IF(ISNUMBER($S8),ROUND(MAX(0,MIN(100,100-$S8*2.5-IF(ISNUMBER($T8),$T8,0)*0.12+IF($S8<=1,12,0))),0),"") | AK8: =IF(ISNUMBER($Q8),IF($Q8>=100,20,IF($Q8>=30,10,0)),0)+IF(ISNUMBER($R8),IF($R8>=100,20,0),0)+IF(ISNUMBER($P8),IF($P8>=150,20,IF($P8>=50,12,5)),0)+IF(ISNUMBER($S8),IF($S8<=1,15,0),0) | AL8: 503 | AN8: =IF(AND(ISNUMBER($P8),ISNUMBER($AL8),$AL8<>0),IF(OR($P8>180,$P8/$AL8*1000>400),"Over ceiling, confirm SKU","Within"),"n/a") | AR8: Retrieved and cited, see Enrichment Log | AS8: BLANK -> requires live Amazon.ca capture | AT8: Unverified commercial data
A9: Sparkling Ice | B9: Sparkling Ice (+ Antioxidants & Vitamins) | Black Raspberry | 8 pack 503mL | C9: 1) Sparkling electrolyte / functional sparkling | D9: 503 mL bottle | E9: 8 | G9: =IF(AND(ISNUMBER($F9),ISNUMBER($E9),$E9<>0),$F9/$E9,"") | H9: =IF(AND(ISNUMBER($F9),ISNUMBER($AL9),ISNUMBER($E9),($AL9*$E9)<>0),$F9/($AL9*$E9)*100,"") | K9: =IF(AND(ISNUMBER($F9),ISNUMBER($J9)),$F9*(1-$J9),"") | N9: =IF(ISNUMBER($F9),($F9-IF(ISNUMBER($AM9),$AM9,0))*(1-IF(ISNUMBER($J9),$J9,0)),"") | O9: Black Raspberry | P9: 0 | Q9: 0 | R9: 30 | S9: 0 | T9: 5 | U9: Sucralose | V9: Zero sugar, vitamins A/D/B, antioxidants (green tea), bold flavour | AA9: High | AB9: Mass market functional sparkling; strong shelf share | AC9: Bold zero sugar sparkling with added vitamins | AD9: Big flavour and added vitamins at zero sugar. | AF9: =IF(AND(ISNUMBER($P9),ISNUMBER($AL9),$AL9<>0),ROUND($P9/$AL9*100,1),"") | AG9: =IF(AND(ISNUMBER($S9),ISNUMBER($AL9),$AL9<>0),ROUND($S9/$AL9*100,2),"") | AH9: =IF(AND(ISNUMBER($Q9),ISNUMBER($AL9),$AL9<>0),ROUND($Q9/$AL9*100,1),"") | AI9: =IF(ISNUMBER($S9),IF($S9<=1,"Yes","No"),"n/a") | AJ9: =IF(ISNUMBER($S9),ROUND(MAX(0,MIN(100,100-$S9*2.5-IF(ISNUMBER($T9),$T9,0)*0.12+IF($S9<=1,12,0))),0),"") | AK9: =IF(ISNUMBER($Q9),IF($Q9>=100,20,IF($Q9>=30,10,0)),0)+IF(ISNUMBER($R9),IF($R9>=100,20,0),0)+IF(ISNUMBER($P9),IF($P9>=150,20,IF($P9>=50,12,5)),0)+IF(ISNUMBER($S9),IF($S9<=1,15,0),0) | AL9: 503 | AN9: =IF(AND(ISNUMBER($P9),ISNUMBER($AL9),$AL9<>0),IF(OR($P9>180,$P9/$AL9*1000>400),"Over ceiling, confirm SKU","Within"),"n/a") | AR9: Retrieved and cited, see Enrichment Log | AS9: BLANK -> requires live Amazon.ca capture | AT9: Unverified commercial data
A10: Sparkling Ice | B10: Sparkling Ice (+ Antioxidants & Vitamins) | Black Raspberry | 12 pack 503mL | C10: 1) Sparkling electrolyte / functional sparkling | D10: 503 mL bottle | E10: 12 | G10: =IF(AND(ISNUMBER($F10),ISNUMBER($E10),$E10<>0),$F10/$E10,"") | H10: =IF(AND(ISNUMBER($F10),ISNUMBER($AL10),ISNUMBER($E10),($AL10*$E10)<>0),$F10/($AL10*$E10)*100,"") | K10: =IF(AND(ISNUMBER($F10),ISNUMBER($J10)),$F10*(1-$J10),"") | N10: =IF(ISNUMBER($F10),($F10-IF(ISNUMBER($AM10),$AM10,0))*(1-IF(ISNUMBER($J10),$J10,0)),"") | O10: Black Raspberry | P10: 0 | Q10: 0 | R10: 30 | S10: 0 | T10: 5 | U10: Sucralose | V10: Zero sugar, vitamins A/D/B, antioxidants (green tea), bold flavour | AA10: High | AB10: Mass market functional sparkling; strong shelf share | AC10: Bold zero sugar sparkling with added vitamins | AD10: Big flavour and added vitamins at zero sugar. | AF10: =IF(AND(ISNUMBER($P10),ISNUMBER($AL10),$AL10<>0),ROUND($P10/$AL10*100,1),"") | AG10: =IF(AND(ISNUMBER($S10),ISNUMBER($AL10),$AL10<>0),ROUND($S10/$AL10*100,2),"") | AH10: =IF(AND(ISNUMBER($Q10),ISNUMBER($AL10),$AL10<>0),ROUND($Q10/$AL10*100,1),"") | AI10: =IF(ISNUMBER($S10),IF($S10<=1,"Yes","No"),"n/a") | AJ10: =IF(ISNUMBER($S10),ROUND(MAX(0,MIN(100,100-$S10*2.5-IF(ISNUMBER($T10),$T10,0)*0.12+IF($S10<=1,12,0))),0),"") | AK10: =IF(ISNUMBER($Q10),IF($Q10>=100,20,IF($Q10>=30,10,0)),0)+IF(ISNUMBER($R10),IF($R10>=100,20,0),0)+IF(ISNUMBER($P10),IF($P10>=150,20,IF($P10>=50,12,5)),0)+IF(ISNUMBER($S10),IF($S10<=1,15,0),0) | AL10: 503 | AN10: =IF(AND(ISNUMBER($P10),ISNUMBER($AL10),$AL10<>0),IF(OR($P10>180,$P10/$AL10*1000>400),"Over ceiling, confirm SKU","Within"),"n/a") | AR10: Retrieved and cited, see Enrichment Log | AS10: BLANK -> requires live Amazon.ca capture | AT10: Unverified commercial data
A11: Sparkling Ice | B11: Sparkling Ice (+ Antioxidants & Vitamins) | Black Raspberry | 18 pack 503mL | C11: 1) Sparkling electrolyte / functional sparkling | D11: 503 mL bottle | E11: 18 | G11: =IF(AND(ISNUMBER($F11),ISNUMBER($E11),$E11<>0),$F11/$E11,"") | H11: =IF(AND(ISNUMBER($F11),ISNUMBER($AL11),ISNUMBER($E11),($AL11*$E11)<>0),$F11/($AL11*$E11)*100,"") | K11: =IF(AND(ISNUMBER($F11),ISNUMBER($J11)),$F11*(1-$J11),"") | N11: =IF(ISNUMBER($F11),($F11-IF(ISNUMBER($AM11),$AM11,0))*(1-IF(ISNUMBER($J11),$J11,0)),"") | O11: Black Raspberry | P11: 0 | Q11: 0 | R11: 30 | S11: 0 | T11: 5 | U11: Sucralose | V11: Zero sugar, vitamins A/D/B, antioxidants (green tea), bold flavour | AA11: High | AB11: Mass market functional sparkling; strong shelf share | AC11: Bold zero sugar sparkling with added vitamins | AD11: Big flavour and added vitamins at zero sugar. | AF11: =IF(AND(ISNUMBER($P11),ISNUMBER($AL11),$AL11<>0),ROUND($P11/$AL11*100,1),"") | AG11: =IF(AND(ISNUMBER($S11),ISNUMBER($AL11),$AL11<>0),ROUND($S11/$AL11*100,2),"") | AH11: =IF(AND(ISNUMBER($Q11),ISNUMBER($AL11),$AL11<>0),ROUND($Q11/$AL11*100,1),"") | AI11: =IF(ISNUMBER($S11),IF($S11<=1,"Yes","No"),"n/a") | AJ11: =IF(ISNUMBER($S11),ROUND(MAX(0,MIN(100,100-$S11*2.5-IF(ISNUMBER($T11),$T11,0)*0.12+IF($S11<=1,12,0))),0),"") | AK11: =IF(ISNUMBER($Q11),IF($Q11>=100,20,IF($Q11>=30,10,0)),0)+IF(ISNUMBER($R11),IF($R11>=100,20,0),0)+IF(ISNUMBER($P11),IF($P11>=150,20,IF($P11>=50,12,5)),0)+IF(ISNUMBER($S11),IF($S11<=1,15,0),0) | AL11: 503 | AN11: =IF(AND(ISNUMBER($P11),ISNUMBER($AL11),$AL11<>0),IF(OR($P11>180,$P11/$AL11*1000>400),"Over ceiling, confirm SKU","Within"),"n/a") | AR11: Retrieved and cited, see Enrichment Log | AS11: BLANK -> requires live Amazon.ca capture | AT11: Unverified commercial data
A12: Sparkling Ice | B12: Sparkling Ice (+ Antioxidants & Vitamins) | Black Raspberry | 24 pack 503mL | C12: 1) Sparkling electrolyte / functional sparkling | D12: 503 mL bottle | E12: 24 | G12: =IF(AND(ISNUMBER($F12),ISNUMBER($E12),$E12<>0),$F12/$E12,"") | H12: =IF(AND(ISNUMBER($F12),ISNUMBER($AL12),ISNUMBER($E12),($AL12*$E12)<>0),$F12/($AL12*$E12)*100,"") | K12: =IF(AND(ISNUMBER($F12),ISNUMBER($J12)),$F12*(1-$J12),"") | N12: =IF(ISNUMBER($F12),($F12-IF(ISNUMBER($AM12),$AM12,0))*(1-IF(ISNUMBER($J12),$J12,0)),"") | O12: Black Raspberry | P12: 0 | Q12: 0 | R12: 30 | S12: 0 | T12: 5 | U12: Sucralose | V12: Zero sugar, vitamins A/D/B, antioxidants (green tea), bold flavour | AA12: High | AB12: Mass market functional sparkling; strong shelf share | AC12: Bold zero sugar sparkling with added vitamins | AD12: Big flavour and added vitamins at zero sugar. | AF12: =IF(AND(ISNUMBER($P12),ISNUMBER($AL12),$AL12<>0),ROUND($P12/$AL12*100,1),"") | AG12: =IF(AND(ISNUMBER($S12),ISNUMBER($AL12),$AL12<>0),ROUND($S12/$AL12*100,2),"") | AH12: =IF(AND(ISNUMBER($Q12),ISNUMBER($AL12),$AL12<>0),ROUND($Q12/$AL12*100,1),"") | AI12: =IF(ISNUMBER($S12),IF($S12<=1,"Yes","No"),"n/a") | AJ12: =IF(ISNUMBER($S12),ROUND(MAX(0,MIN(100,100-$S12*2.5-IF(ISNUMBER($T12),$T12,0)*0.12+IF($S12<=1,12,0))),0),"") | AK12: =IF(ISNUMBER($Q12),IF($Q12>=100,20,IF($Q12>=30,10,0)),0)+IF(ISNUMBER($R12),IF($R12>=100,20,0),0)+IF(ISNUMBER($P12),IF($P12>=150,20,IF($P12>=50,12,5)),0)+IF(ISNUMBER($S12),IF($S12<=1,15,0),0) | AL12: 503 | AN12: =IF(AND(ISNUMBER($P12),ISNUMBER($AL12),$AL12<>0),IF(OR($P12>180,$P12/$AL12*1000>400),"Over ceiling, confirm SKU","Within"),"n/a") | AR12: Retrieved and cited, see Enrichment Log | AS12: BLANK -> requires live Amazon.ca capture | AT12: Unverified commercial data
A13: Sparkling Ice | B13: Sparkling Ice (+ Antioxidants & Vitamins) | Cherry Limeade | single 503mL | C13: 1) Sparkling electrolyte / functional sparkling | D13: 503 mL bottle | E13: 1 | G13: =IF(AND(ISNUMBER($F13),ISNUMBER($E13),$E13<>0),$F13/$E13,"") | H13: =IF(AND(ISNUMBER($F13),ISNUMBER($AL13),ISNUMBER($E13),($AL13*$E13)<>0),$F13/($AL13*$E13)*100,"") | K13: =IF(AND(ISNUMBER($F13),ISNUMBER($J13)),$F13*(1-$J13),"") | N13: =IF(ISNUMBER($F13),($F13-IF(ISNUMBER($AM13),$AM13,0))*(1-IF(ISNUMBER($J13),$J13,0)),"") | O13: Cherry Limeade | P13: 0 | Q13: 0 | R13: 30 | S13: 0 | T13: 5 | U13: Sucralose | V13: Zero sugar, vitamins A/D/B, antioxidants (green tea), bold flavour | AA13: High | AB13: Mass market functional sparkling; strong shelf share | AC13: Bold zero sugar sparkling with added vitamins | AD13: Big flavour and added vitamins at zero sugar. | AF13: =IF(AND(ISNUMBER($P13),ISNUMBER($AL13),$AL13<>0),ROUND($P13/$AL13*100,1),"") | AG13: =IF(AND(ISNUMBER($S13),ISNUMBER($AL13),$AL13<>0),ROUND($S13/$AL13*100,2),"") | AH13: =IF(AND(ISNUMBER($Q13),ISNUMBER($AL13),$AL13<>0),ROUND($Q13/$AL13*100,1),"") | AI13: =IF(ISNUMBER($S13),IF($S13<=1,"Yes","No"),"n/a") | AJ13: =IF(ISNUMBER($S13),ROUND(MAX(0,MIN(100,100-$S13*2.5-IF(ISNUMBER($T13),$T13,0)*0.12+IF($S13<=1,12,0))),0),"") | AK13: =IF(ISNUMBER($Q13),IF($Q13>=100,20,IF($Q13>=30,10,0)),0)+IF(ISNUMBER($R13),IF($R13>=100,20,0),0)+IF(ISNUMBER($P13),IF($P13>=150,20,IF($P13>=50,12,5)),0)+IF(ISNUMBER($S13),IF($S13<=1,15,0),0) | AL13: 503 | AN13: =IF(AND(ISNUMBER($P13),ISNUMBER($AL13),$AL13<>0),IF(OR($P13>180,$P13/$AL13*1000>400),"Over ceiling, confirm SKU","Within"),"n/a") | AR13: Retrieved and cited, see Enrichment Log | AS13: BLANK -> requires live Amazon.ca capture | AT13: Unverified commercial data
A14: Sparkling Ice | B14: Sparkling Ice (+ Antioxidants & Vitamins) | Cherry Limeade | 8 pack 503mL | C14: 1) Sparkling electrolyte / functional sparkling | D14: 503 mL bottle | E14: 8 | G14: =IF(AND(ISNUMBER($F14),ISNUMBER($E14),$E14<>0),$F14/$E14,"") | H14: =IF(AND(ISNUMBER($F14),ISNUMBER($AL14),ISNUMBER($E14),($AL14*$E14)<>0),$F14/($AL14*$E14)*100,"") | K14: =IF(AND(ISNUMBER($F14),ISNUMBER($J14)),$F14*(1-$J14),"") | N14: =IF(ISNUMBER($F14),($F14-IF(ISNUMBER($AM14),$AM14,0))*(1-IF(ISNUMBER($J14),$J14,0)),"") | O14: Cherry Limeade | P14: 0 | Q14: 0 | R14: 30 | S14: 0 | T14: 5 | U14: Sucralose | V14: Zero sugar, vitamins A/D/B, antioxidants (green tea), bold flavour | AA14: High | AB14: Mass market functional sparkling; strong shelf share | AC14: Bold zero sugar sparkling with added vitamins | AD14: Big flavour and added vitamins at zero sugar. | AF14: =IF(AND(ISNUMBER($P14),ISNUMBER($AL14),$AL14<>0),ROUND($P14/$AL14*100,1),"") | AG14: =IF(AND(ISNUMBER($S14),ISNUMBER($AL14),$AL14<>0),ROUND($S14/$AL14*100,2),"") | AH14: =IF(AND(ISNUMBER($Q14),ISNUMBER($AL14),$AL14<>0),ROUND($Q14/$AL14*100,1),"") | AI14: =IF(ISNUMBER($S14),IF($S14<=1,"Yes","No"),"n/a") | AJ14: =IF(ISNUMBER($S14),ROUND(MAX(0,MIN(100,100-$S14*2.5-IF(ISNUMBER($T14),$T14,0)*0.12+IF($S14<=1,12,0))),0),"") | AK14: =IF(ISNUMBER($Q14),IF($Q14>=100,20,IF($Q14>=30,10,0)),0)+IF(ISNUMBER($R14),IF($R14>=100,20,0),0)+IF(ISNUMBER($P14),IF($P14>=150,20,IF($P14>=50,12,5)),0)+IF(ISNUMBER($S14),IF($S14<=1,15,0),0) | AL14: 503 | AN14: =IF(AND(ISNUMBER($P14),ISNUMBER($AL14),$AL14<>0),IF(OR($P14>180,$P14/$AL14*1000>400),"Over ceiling, confirm SKU","Within"),"n/a") | AR14: Retrieved and cited, see Enrichment Log | AS14: BLANK -> requires live Amazon.ca capture | AT14: Unverified commercial data
A15: Sparkling Ice | B15: Sparkling Ice (+ Antioxidants & Vitamins) | Cherry Limeade | 12 pack 503mL | C15: 1) Sparkling electrolyte / functional sparkling | D15: 503 mL bottle | E15: 12 | G15: =IF(AND(ISNUMBER($F15),ISNUMBER($E15),$E15<>0),$F15/$E15,"") | H15: =IF(AND(ISNUMBER($F15),ISNUMBER($AL15),ISNUMBER($E15),($AL15*$E15)<>0),$F15/($AL15*$E15)*100,"") | K15: =IF(AND(ISNUMBER($F15),ISNUMBER($J15)),$F15*(1-$J15),"") | N15: =IF(ISNUMBER($F15),($F15-IF(ISNUMBER($AM15),$AM15,0))*(1-IF(ISNUMBER($J15),$J15,0)),"") | O15: Cherry Limeade | P15: 0 | Q15: 0 | R15: 30 | S15: 0 | T15: 5 | U15: Sucralose | V15: Zero sugar, vitamins A/D/B, antioxidants (green tea), bold flavour | AA15: High | AB15: Mass market functional sparkling; strong shelf share | AC15: Bold zero sugar sparkling with added vitamins | AD15: Big flavour and added vitamins at zero sugar. | AF15: =IF(AND(ISNUMBER($P15),ISNUMBER($AL15),$AL15<>0),ROUND($P15/$AL15*100,1),"") | AG15: =IF(AND(ISNUMBER($S15),ISNUMBER($AL15),$AL15<>0),ROUND($S15/$AL15*100,2),"") | AH15: =IF(AND(ISNUMBER($Q15),ISNUMBER($AL15),$AL15<>0),ROUND($Q15/$AL15*100,1),"") | AI15: =IF(ISNUMBER($S15),IF($S15<=1,"Yes","No"),"n/a") | AJ15: =IF(ISNUMBER($S15),ROUND(MAX(0,MIN(100,100-$S15*2.5-IF(ISNUMBER($T15),$T15,0)*0.12+IF($S15<=1,12,0))),0),"") | AK15: =IF(ISNUMBER($Q15),IF($Q15>=100,20,IF($Q15>=30,10,0)),0)+IF(ISNUMBER($R15),IF($R15>=100,20,0),0)+IF(ISNUMBER($P15),IF($P15>=150,20,IF($P15>=50,12,5)),0)+IF(ISNUMBER($S15),IF($S15<=1,15,0),0) | AL15: 503 | AN15: =IF(AND(ISNUMBER($P15),ISNUMBER($AL15),$AL15<>0),IF(OR($P15>180,$P15/$AL15*1000>400),"Over ceiling, confirm SKU","Within"),"n/a") | AR15: Retrieved and cited, see Enrichment Log | AS15: BLANK -> requires live Amazon.ca capture | AT15: Unverified commercial data
A16: Sparkling Ice | B16: Sparkling Ice (+ Antioxidants & Vitamins) | Cherry Limeade | 18 pack 503mL | C16: 1) Sparkling electrolyte / functional sparkling | D16: 503 mL bottle | E16: 18 | G16: =IF(AND(ISNUMBER($F16),ISNUMBER($E16),$E16<>0),$F16/$E16,"") | H16: =IF(AND(ISNUMBER($F16),ISNUMBER($AL16),ISNUMBER($E16),($AL16*$E16)<>0),$F16/($AL16*$E16)*100,"") | K16: =IF(AND(ISNUMBER($F16),ISNUMBER($J16)),$F16*(1-$J16),"") | N16: =IF(ISNUMBER($F16),($F16-IF(ISNUMBER($AM16),$AM16,0))*(1-IF(ISNUMBER($J16),$J16,0)),"") | O16: Cherry Limeade | P16: 0 | Q16: 0 | R16: 30 | S16: 0 | T16: 5 | U16: Sucralose | V16: Zero sugar, vitamins A/D/B, antioxidants (green tea), bold flavour | AA16: High | AB16: Mass market functional sparkling; strong shelf share | AC16: Bold zero sugar sparkling with added vitamins | AD16: Big flavour and added vitamins at zero sugar. | AF16: =IF(AND(ISNUMBER($P16),ISNUMBER($AL16),$AL16<>0),ROUND($P16/$AL16*100,1),"") | AG16: =IF(AND(ISNUMBER($S16),ISNUMBER($AL16),$AL16<>0),ROUND($S16/$AL16*100,2),"") | AH16: =IF(AND(ISNUMBER($Q16),ISNUMBER($AL16),$AL16<>0),ROUND($Q16/$AL16*100,1),"") | AI16: =IF(ISNUMBER($S16),IF($S16<=1,"Yes","No"),"n/a") | AJ16: =IF(ISNUMBER($S16),ROUND(MAX(0,MIN(100,100-$S16*2.5-IF(ISNUMBER($T16),$T16,0)*0.12+IF($S16<=1,12,0))),0),"") | AK16: =IF(ISNUMBER($Q16),IF($Q16>=100,20,IF($Q16>=30,10,0)),0)+IF(ISNUMBER($R16),IF($R16>=100,20,0),0)+IF(ISNUMBER($P16),IF($P16>=150,20,IF($P16>=50,12,5)),0)+IF(ISNUMBER($S16),IF($S16<=1,15,0),0) | AL16: 503 | AN16: =IF(AND(ISNUMBER($P16),ISNUMBER($AL16),$AL16<>0),IF(OR($P16>180,$P16/$AL16*1000>400),"Over ceiling, confirm SKU","Within"),"n/a") | AR16: Retrieved and cited, see Enrichment Log | AS16: BLANK -> requires live Amazon.ca capture | AT16: Unverified commercial data
A17: Sparkling Ice | B17: Sparkling Ice (+ Antioxidants & Vitamins) | Cherry Limeade | 24 pack 503mL | C17: 1) Sparkling electrolyte / functional sparkling | D17: 503 mL bottle | E17: 24 | G17: =IF(AND(ISNUMBER($F17),ISNUMBER($E17),$E17<>0),$F17/$E17,"") | H17: =IF(AND(ISNUMBER($F17),ISNUMBER($AL17),ISNUMBER($E17),($AL17*$E17)<>0),$F17/($AL17*$E17)*100,"") | K17: =IF(AND(ISNUMBER($F17),ISNUMBER($J17)),$F17*(1-$J17),"") | N17: =IF(ISNUMBER($F17),($F17-IF(ISNUMBER($AM17),$AM17,0))*(1-IF(ISNUMBER($J17),$J17,0)),"") | O17: Cherry Limeade | P17: 0 | Q17: 0 | R17: 30 | S17: 0 | T17: 5 | U17: Sucralose | V17: Zero sugar, vitamins A/D/B, antioxidants (green tea), bold flavour | AA17: High | AB17: Mass market functional sparkling; strong shelf share | AC17: Bold zero sugar sparkling with added vitamins | AD17: Big flavour and added vitamins at zero sugar. | AF17: =IF(AND(ISNUMBER($P17),ISNUMBER($AL17),$AL17<>0),ROUND($P17/$AL17*100,1),"") | AG17: =IF(AND(ISNUMBER($S17),ISNUMBER($AL17),$AL17<>0),ROUND($S17/$AL17*100,2),"") | AH17: =IF(AND(ISNUMBER($Q17),ISNUMBER($AL17),$AL17<>0),ROUND($Q17/$AL17*100,1),"") | AI17: =IF(ISNUMBER($S17),IF($S17<=1,"Yes","No"),"n/a") | AJ17: =IF(ISNUMBER($S17),ROUND(MAX(0,MIN(100,100-$S17*2.5-IF(ISNUMBER($T17),$T17,0)*0.12+IF($S17<=1,12,0))),0),"") | AK17: =IF(ISNUMBER($Q17),IF($Q17>=100,20,IF($Q17>=30,10,0)),0)+IF(ISNUMBER($R17),IF($R17>=100,20,0),0)+IF(ISNUMBER($P17),IF($P17>=150,20,IF($P17>=50,12,5)),0)+IF(ISNUMBER($S17),IF($S17<=1,15,0),0) | AL17: 503 | AN17: =IF(AND(ISNUMBER($P17),ISNUMBER($AL17),$AL17<>0),IF(OR($P17>180,$P17/$AL17*1000>400),"Over ceiling, confirm SKU","Within"),"n/a") | AR17: Retrieved and cited, see Enrichment Log | AS17: BLANK -> requires live Amazon.ca capture | AT17: Unverified commercial data
A18: Sparkling Ice | B18: Sparkling Ice (+ Antioxidants & Vitamins) | Orange Mango | single 503mL | C18: 1) Sparkling electrolyte / functional sparkling | D18: 503 mL bottle | E18: 1 | G18: =IF(AND(ISNUMBER($F18),ISNUMBER($E18),$E18<>0),$F18/$E18,"") | H18: =IF(AND(ISNUMBER($F18),ISNUMBER($AL18),ISNUMBER($E18),($AL18*$E18)<>0),$F18/($AL18*$E18)*100,"") | K18: =IF(AND(ISNUMBER($F18),ISNUMBER($J18)),$F18*(1-$J18),"") | N18: =IF(ISNUMBER($F18),($F18-IF(ISNUMBER($AM18),$AM18,0))*(1-IF(ISNUMBER($J18),$J18,0)),"") | O18: Orange Mango | P18: 0 | Q18: 0 | R18: 30 | S18: 0 | T18: 5 | U18: Sucralose | V18: Zero sugar, vitamins A/D/B, antioxidants (green tea), bold flavour | AA18: High | AB18: Mass market functional sparkling; strong shelf share | AC18: Bold zero sugar sparkling with added vitamins | AD18: Big flavour and added vitamins at zero sugar. | AF18: =IF(AND(ISNUMBER($P18),ISNUMBER($AL18),$AL18<>0),ROUND($P18/$AL18*100,1),"") | AG18: =IF(AND(ISNUMBER($S18),ISNUMBER($AL18),$AL18<>0),ROUND($S18/$AL18*100,2),"") | AH18: =IF(AND(ISNUMBER($Q18),ISNUMBER($AL18),$AL18<>0),ROUND($Q18/$AL18*100,1),"") | AI18: =IF(ISNUMBER($S18),IF($S18<=1,"Yes","No"),"n/a") | AJ18: =IF(ISNUMBER($S18),ROUND(MAX(0,MIN(100,100-$S18*2.5-IF(ISNUMBER($T18),$T18,0)*0.12+IF($S18<=1,12,0))),0),"") | AK18: =IF(ISNUMBER($Q18),IF($Q18>=100,20,IF($Q18>=30,10,0)),0)+IF(ISNUMBER($R18),IF($R18>=100,20,0),0)+IF(ISNUMBER($P18),IF($P18>=150,20,IF($P18>=50,12,5)),0)+IF(ISNUMBER($S18),IF($S18<=1,15,0),0) | AL18: 503 | AN18: =IF(AND(ISNUMBER($P18),ISNUMBER($AL18),$AL18<>0),IF(OR($P18>180,$P18/$AL18*1000>400),"Over ceiling, confirm SKU","Within"),"n/a") | AR18: Retrieved and cited, see Enrichment Log | AS18: BLANK -> requires live Amazon.ca capture | AT18: Unverified commercial data
A19: Sparkling Ice | B19: Sparkling Ice (+ Antioxidants & Vitamins) | Orange Mango | 8 pack 503mL | C19: 1) Sparkling electrolyte / functional sparkling | D19: 503 mL bottle | E19: 8 | G19: =IF(AND(ISNUMBER($F19),ISNUMBER($E19),$E19<>0),$F19/$E19,"") | H19: =IF(AND(ISNUMBER($F19),ISNUMBER($AL19),ISNUMBER($E19),($AL19*$E19)<>0),$F19/($AL19*$E19)*100,"") | K19: =IF(AND(ISNUMBER($F19),ISNUMBER($J19)),$F19*(1-$J19),"") | N19: =IF(ISNUMBER($F19),($F19-IF(ISNUMBER($AM19),$AM19,0))*(1-IF(ISNUMBER($J19),$J19,0)),"") | O19: Orange Mango | P19: 0 | Q19: 0 | R19: 30 | S19: 0 | T19: 5 | U19: Sucralose | V19: Zero sugar, vitamins A/D/B, antioxidants (green tea), bold flavour | AA19: High | AB19: Mass market functional sparkling; strong shelf share | AC19: Bold zero sugar sparkling with added vitamins | AD19: Big flavour and added vitamins at zero sugar. | AF19: =IF(AND(ISNUMBER($P19),ISNUMBER($AL19),$AL19<>0),ROUND($P19/$AL19*100,1),"") | AG19: =IF(AND(ISNUMBER($S19),ISNUMBER($AL19),$AL19<>0),ROUND($S19/$AL19*100,2),"") | AH19: =IF(AND(ISNUMBER($Q19),ISNUMBER($AL19),$AL19<>0),ROUND($Q19/$AL19*100,1),"") | AI19: =IF(ISNUMBER($S19),IF($S19<=1,"Yes","No"),"n/a") | AJ19: =IF(ISNUMBER($S19),ROUND(MAX(0,MIN(100,100-$S19*2.5-IF(ISNUMBER($T19),$T19,0)*0.12+IF($S19<=1,12,0))),0),"") | AK19: =IF(ISNUMBER($Q19),IF($Q19>=100,20,IF($Q19>=30,10,0)),0)+IF(ISNUMBER($R19),IF($R19>=100,20,0),0)+IF(ISNUMBER($P19),IF($P19>=150,20,IF($P19>=50,12,5)),0)+IF(ISNUMBER($S19),IF($S19<=1,15,0),0) | AL19: 503 | AN19: =IF(AND(ISNUMBER($P19),ISNUMBER($AL19),$AL19<>0),IF(OR($P19>180,$P19/$AL19*1000>400),"Over ceiling, confirm SKU","Within"),"n/a") | AR19: Retrieved and cited, see Enrichment Log | AS19: BLANK -> requires live Amazon.ca capture | AT19: Unverified commercial data
... A37: Sparkling Ice | B37: Sparkling Ice (+ Antioxidants & Vitamins) | Classic Lemonade | 24 pack 503mL | C37: 1) Sparkling electrolyte / functional sparkling | D37: 503 mL bottle | E37: 24 | G37: =IF(AND(ISNUMBER($F37),ISNUMBER($E37),$E37<>0),$F37/$E37,"") | H37: =IF(AND(ISNUMBER($F37),ISNUMBER($AL37),ISNUMBER($E37),($AL37*$E37)<>0),$F37/($AL37*$E37)*100,"") | K37: =IF(AND(ISNUMBER($F37),ISNUMBER($J37)),$F37*(1-$J37),"") | N37: =IF(ISNUMBER($F37),($F37-IF(ISNUMBER($AM37),$AM37,0))*(1-IF(ISNUMBER($J37),$J37,0)),"") | O37: Classic Lemonade | P37: 0 | Q37: 0 | R37: 30 | S37: 0 | T37: 5 | U37: Sucralose | V37: Zero sugar, vitamins A/D/B, antioxidants (green tea), bold flavour | AA37: High | AB37: Mass market functional sparkling; strong shelf share | AC37: Bold zero sugar sparkling with added vitamins | AD37: Big flavour and added vitamins at zero sugar. | AF37: =IF(AND(ISNUMBER($P37),ISNUMBER($AL37),$AL37<>0),ROUND($P37/$AL37*100,1),"") | AG37: =IF(AND(ISNUMBER($S37),ISNUMBER($AL37),$AL37<>0),ROUND($S37/$AL37*100,2),"") | AH37: =IF(AND(ISNUMBER($Q37),ISNUMBER($AL37),$AL37<>0),ROUND($Q37/$AL37*100,1),"") | AI37: =IF(ISNUMBER($S37),IF($S37<=1,"Yes","No"),"n/a") | AJ37: =IF(ISNUMBER($S37),ROUND(MAX(0,MIN(100,100-$S37*2.5-IF(ISNUMBER($T37),$T37,0)*0.12+IF($S37<=1,12,0))),0),"") | AK37: =IF(ISNUMBER($Q37),IF($Q37>=100,20,IF($Q37>=30,10,0)),0)+IF(ISNUMBER($R37),IF($R37>=100,20,0),0)+IF(ISNUMBER($P37),IF($P37>=150,20,IF($P37>=50,12,5)),0)+IF(ISNUMBER($S37),IF($S37<=1,15,0),0) | AL37: 503 | AN37: =IF(AND(ISNUMBER($P37),ISNUMBER($AL37),$AL37<>0),IF(OR($P37>180,$P37/$AL37*1000>400),"Over ceiling, confirm SKU","Within"),"n/a") | AR37: Retrieved and cited, see Enrichment Log | AS37: BLANK -> requires live Amazon.ca capture | AT37: Unverified commercial data
A38: BUBBL'R | B38: BUBBL'R Antioxidant Sparkling Water | Blackberribrilliance | single 473mL | C38: 1) Sparkling electrolyte / functional sparkling | D38: 473 mL can | E38: 1 | G38: =IF(AND(ISNUMBER($F38),ISNUMBER($E38),$E38<>0),$F38/$E38,"") | H38: =IF(AND(ISNUMBER($F38),ISNUMBER($AL38),ISNUMBER($E38),($AL38*$E38)<>0),$F38/($AL38*$E38)*100,"") | K38: =IF(AND(ISNUMBER($F38),ISNUMBER($J38)),$F38*(1-$J38),"") | N38: =IF(ISNUMBER($F38),($F38-IF(ISNUMBER($AM38),$AM38,0))*(1-IF(ISNUMBER($J38),$J38,0)),"") | O38: Blackberribrilliance | P38: 69 | Q38: 15 | R38: Not listed | S38: 0 | T38: 10 | U38: Erythritol + stevia | V38: Natural caffeine (69 mg), antioxidants, B vitamins, zero sugar | AA38: Medium | AB38: Mid caffeine functional sparkling; growing | AC38: Sparkling water with a light caffeine + antioxidant lift | AD38: Light natural caffeine and antioxidants without an energy drink dose. | AF38: =IF(AND(ISNUMBER($P38),ISNUMBER($AL38),$AL38<>0),ROUND($P38/$AL38*100,1),"") | AG38: =IF(AND(ISNUMBER($S38),ISNUMBER($AL38),$AL38<>0),ROUND($S38/$AL38*100,2),"") | AH38: =IF(AND(ISNUMBER($Q38),ISNUMBER($AL38),$AL38<>0),ROUND($Q38/$AL38*100,1),"") | AI38: =IF(ISNUMBER($S38),IF($S38<=1,"Yes","No"),"n/a") | AJ38: =IF(ISNUMBER($S38),ROUND(MAX(0,MIN(100,100-$S38*2.5-IF(ISNUMBER($T38),$T38,0)*0.12+IF($S38<=1,12,0))),0),"") | AK38: =IF(ISNUMBER($Q38),IF($Q38>=100,20,IF($Q38>=30,10,0)),0)+IF(ISNUMBER($R38),IF($R38>=100,20,0),0)+IF(ISNUMBER($P38),IF($P38>=150,20,IF($P38>=50,12,5)),0)+IF(ISNUMBER($S38),IF($S38<=1,15,0),0) | AL38: 473 | AN38: =IF(AND(ISNUMBER($P38),ISNUMBER($AL38),$AL38<>0),IF(OR($P38>180,$P38/$AL38*1000>400),"Over ceiling, confirm SKU","Within"),"n/a") | AR38: Recalled, batch confirmed, to confirm | AS38: BLANK -> requires live Amazon.ca capture | AT38: Unverified commercial data
A39: BUBBL'R | B39: BUBBL'R Antioxidant Sparkling Water | Blackberribrilliance | 8 pack 473mL | C39: 1) Sparkling electrolyte / functional sparkling | D39: 473 mL can | E39: 8 | G39: =IF(AND(ISNUMBER($F39),ISNUMBER($E39),$E39<>0),$F39/$E39,"") | H39: =IF(AND(ISNUMBER($F39),ISNUMBER($AL39),ISNUMBER($E39),($AL39*$E39)<>0),$F39/($AL39*$E39)*100,"") | K39: =IF(AND(ISNUMBER($F39),ISNUMBER($J39)),$F39*(1-$J39),"") | N39: =IF(ISNUMBER($F39),($F39-IF(ISNUMBER($AM39),$AM39,0))*(1-IF(ISNUMBER($J39),$J39,0)),"") | O39: Blackberribrilliance | P39: 69 | Q39: 15 | R39: Not listed | S39: 0 | T39: 10 | U39: Erythritol + stevia | V39: Natural caffeine (69 mg), antioxidants, B vitamins, zero sugar | AA39: Medium | AB39: Mid caffeine functional sparkling; growing | AC39: Sparkling water with a light caffeine + antioxidant lift | AD39: Light natural caffeine and antioxidants without an energy drink dose. | AF39: =IF(AND(ISNUMBER($P39),ISNUMBER($AL39),$AL39<>0),ROUND($P39/$AL39*100,1),"") | AG39: =IF(AND(ISNUMBER($S39),ISNUMBER($AL39),$AL39<>0),ROUND($S39/$AL39*100,2),"") | AH39: =IF(AND(ISNUMBER($Q39),ISNUMBER($AL39),$AL39<>0),ROUND($Q39/$AL39*100,1),"") | AI39: =IF(ISNUMBER($S39),IF($S39<=1,"Yes","No"),"n/a") | AJ39: =IF(ISNUMBER($S39),ROUND(MAX(0,MIN(100,100-$S39*2.5-IF(ISNUMBER($T39),$T39,0)*0.12+IF($S39<=1,12,0))),0),"") | AK39: =IF(ISNUMBER($Q39),IF($Q39>=100,20,IF($Q39>=30,10,0)),0)+IF(ISNUMBER($R39),IF($R39>=100,20,0),0)+IF(ISNUMBER($P39),IF($P39>=150,20,IF($P39>=50,12,5)),0)+IF(ISNUMBER($S39),IF($S39<=1,15,0),0) | AL39: 473 | AN39: =IF(AND(ISNUMBER($P39),ISNUMBER($AL39),$AL39<>0),IF(OR($P39>180,$P39/$AL39*1000>400),"Over ceiling, confirm SKU","Within"),"n/a") | AR39: Recalled, batch confirmed, to confirm | AS39: BLANK -> requires live Amazon.ca capture | AT39: Unverified commercial data
A40: BUBBL'R | B40: BUBBL'R Antioxidant Sparkling Water | Blackberribrilliance | 12 pack 473mL | C40: 1) Sparkling electrolyte / functional sparkling | D40: 473 mL can | E40: 12 | G40: =IF(AND(ISNUMBER($F40),ISNUMBER($E40),$E40<>0),$F40/$E40,"") | H40: =IF(AND(ISNUMBER($F40),ISNUMBER($AL40),ISNUMBER($E40),($AL40*$E40)<>0),$F40/($AL40*$E40)*100,"") | K40: =IF(AND(ISNUMBER($F40),ISNUMBER($J40)),$F40*(1-$J40),"") | N40: =IF(ISNUMBER($F40),($F40-IF(ISNUMBER($AM40),$AM40,0))*(1-IF(ISNUMBER($J40),$J40,0)),"") | O40: Blackberribrilliance | P40: 69 | Q40: 15 | R40: Not listed | S40: 0 | T40: 10 | U40: Erythritol + stevia | V40: Natural caffeine (69 mg), antioxidants, B vitamins, zero sugar | AA40: Medium | AB40: Mid caffeine functional sparkling; growing | AC40: Sparkling water with a light caffeine + antioxidant lift | AD40: Light natural caffeine and antioxidants without an energy drink dose. | AF40: =IF(AND(ISNUMBER($P40),ISNUMBER($AL40),$AL40<>0),ROUND($P40/$AL40*100,1),"") | AG40: =IF(AND(ISNUMBER($S40),ISNUMBER($AL40),$AL40<>0),ROUND($S40/$AL40*100,2),"") | AH40: =IF(AND(ISNUMBER($Q40),ISNUMBER($AL40),$AL40<>0),ROUND($Q40/$AL40*100,1),"") | AI40: =IF(ISNUMBER($S40),IF($S40<=1,"Yes","No"),"n/a") | AJ40: =IF(ISNUMBER($S40),ROUND(MAX(0,MIN(100,100-$S40*2.5-IF(ISNUMBER($T40),$T40,0)*0.12+IF($S40<=1,12,0))),0),"") | AK40: =IF(ISNUMBER($Q40),IF($Q40>=100,20,IF($Q40>=30,10,0)),0)+IF(ISNUMBER($R40),IF($R40>=100,20,0),0)+IF(ISNUMBER($P40),IF($P40>=150,20,IF($P40>=50,12,5)),0)+IF(ISNUMBER($S40),IF($S40<=1,15,0),0) | AL40: 473 | AN40: =IF(AND(ISNUMBER($P40),ISNUMBER($AL40),$AL40<>0),IF(OR($P40>180,$P40/$AL40*1000>400),"Over ceiling, confirm SKU","Within"),"n/a") | AR40: Recalled, batch confirmed, to confirm | AS40: BLANK -> requires live Amazon.ca capture | AT40: Unverified commercial data
A41: BUBBL'R | B41: BUBBL'R Antioxidant Sparkling Water | Blackberribrilliance | 18 pack 473mL | C41: 1) Sparkling electrolyte / functional sparkling | D41: 473 mL can | E41: 18 | G41: =IF(AND(ISNUMBER($F41),ISNUMBER($E41),$E41<>0),$F41/$E41,"") | H41: =IF(AND(ISNUMBER($F41),ISNUMBER($AL41),ISNUMBER($E41),($AL41*$E41)<>0),$F41/($AL41*$E41)*100,"") | K41: =IF(AND(ISNUMBER($F41),ISNUMBER($J41)),$F41*(1-$J41),"") | N41: =IF(ISNUMBER($F41),($F41-IF(ISNUMBER($AM41),$AM41,0))*(1-IF(ISNUMBER($J41),$J41,0)),"") | O41: Blackberribrilliance | P41: 69 | Q41: 15 | R41: Not listed | S41: 0 | T41: 10 | U41: Erythritol + stevia | V41: Natural caffeine (69 mg), antioxidants, B vitamins, zero sugar | AA41: Medium | AB41: Mid caffeine functional sparkling; growing | AC41: Sparkling water with a light caffeine + antioxidant lift | AD41: Light natural caffeine and antioxidants without an energy drink dose. | AF41: =IF(AND(ISNUMBER($P41),ISNUMBER($AL41),$AL41<>0),ROUND($P41/$AL41*100,1),"") | AG41: =IF(AND(ISNUMBER($S41),ISNUMBER($AL41),$AL41<>0),ROUND($S41/$AL41*100,2),"") | AH41: =IF(AND(ISNUMBER($Q41),ISNUMBER($AL41),$AL41<>0),ROUND($Q41/$AL41*100,1),"") | AI41: =IF(ISNUMBER($S41),IF($S41<=1,"Yes","No"),"n/a") | AJ41: =IF(ISNUMBER($S41),ROUND(MAX(0,MIN(100,100-$S41*2.5-IF(ISNUMBER($T41),$T41,0)*0.12+IF($S41<=1,12,0))),0),"") | AK41: =IF(ISNUMBER($Q41),IF($Q41>=100,20,IF($Q41>=30,10,0)),0)+IF(ISNUMBER($R41),IF($R41>=100,20,0),0)+IF(ISNUMBER($P41),IF($P41>=150,20,IF($P41>=50,12,5)),0)+IF(ISNUMBER($S41),IF($S41<=1,15,0),0) | AL41: 473 | AN41: =IF(AND(ISNUMBER($P41),ISNUMBER($AL41),$AL41<>0),IF(OR($P41>180,$P41/$AL41*1000>400),"Over ceiling, confirm SKU","Within"),"n/a") | AR41: Recalled, batch confirmed, to confirm | AS41: BLANK -> requires live Amazon.ca capture | AT41: Unverified commercial data
A42: BUBBL'R | B42: BUBBL'R Antioxidant Sparkling Water | Blackberribrilliance | 24 pack 473mL | C42: 1) Sparkling electrolyte / functional sparkling | D42: 473 mL can | E42: 24 | G42: =IF(AND(ISNUMBER($F42),ISNUMBER($E42),$E42<>0),$F42/$E42,"") | H42: =IF(AND(ISNUMBER($F42),ISNUMBER($AL42),ISNUMBER($E42),($AL42*$E42)<>0),$F42/($AL42*$E42)*100,"") | K42: =IF(AND(ISNUMBER($F42),ISNUMBER($J42)),$F42*(1-$J42),"") | N42: =IF(ISNUMBER($F42),($F42-IF(ISNUMBER($AM42),$AM42,0))*(1-IF(ISNUMBER($J42),$J42,0)),"") | O42: Blackberribrilliance | P42: 69 | Q42: 15 | R42: Not listed | S42: 0 | T42: 10 | U42: Erythritol + stevia | V42: Natural caffeine (69 mg), antioxidants, B vitamins, zero sugar | AA42: Medium | AB42: Mid caffeine functional sparkling; growing | AC42: Sparkling water with a light caffeine + antioxidant lift | AD42: Light natural caffeine and antioxidants without an energy drink dose. | AF42: =IF(AND(ISNUMBER($P42),ISNUMBER($AL42),$AL42<>0),ROUND($P42/$AL42*100,1),"") | AG42: =IF(AND(ISNUMBER($S42),ISNUMBER($AL42),$AL42<>0),ROUND($S42/$AL42*100,2),"") | AH42: =IF(AND(ISNUMBER($Q42),ISNUMBER($AL42),$AL42<>0),ROUND($Q42/$AL42*100,1),"") | AI42: =IF(ISNUMBER($S42),IF($S42<=1,"Yes","No"),"n/a") | AJ42: =IF(ISNUMBER($S42),ROUND(MAX(0,MIN(100,100-$S42*2.5-IF(ISNUMBER($T42),$T42,0)*0.12+IF($S42<=1,12,0))),0),"") | AK42: =IF(ISNUMBER($Q42),IF($Q42>=100,20,IF($Q42>=30,10,0)),0)+IF(ISNUMBER($R42),IF($R42>=100,20,0),0)+IF(ISNUMBER($P42),IF($P42>=150,20,IF($P42>=50,12,5)),0)+IF(ISNUMBER($S42),IF($S42<=1,15,0),0) | AL42: 473 | AN42: =IF(AND(ISNUMBER($P42),ISNUMBER($AL42),$AL42<>0),IF(OR($P42>180,$P42/$AL42*1000>400),"Over ceiling, confirm SKU","Within"),"n/a") | AR42: Recalled, batch confirmed, to confirm | AS42: BLANK -> requires live Amazon.ca capture | AT42: Unverified commercial data
A43: BUBBL'R | B43: BUBBL'R Antioxidant Sparkling Water | Strawbeary Lemonade | single 473mL | C43: 1) Sparkling electrolyte / functional sparkling | D43: 473 mL can | E43: 1 | G43: =IF(AND(ISNUMBER($F43),ISNUMBER($E43),$E43<>0),$F43/$E43,"") | H43: =IF(AND(ISNUMBER($F43),ISNUMBER($AL43),ISNUMBER($E43),($AL43*$E43)<>0),$F43/($AL43*$E43)*100,"") | K43: =IF(AND(ISNUMBER($F43),ISNUMBER($J43)),$F43*(1-$J43),"") | N43: =IF(ISNUMBER($F43),($F43-IF(ISNUMBER($AM43),$AM43,0))*(1-IF(ISNUMBER($J43),$J43,0)),"") | O43: Strawbeary Lemonade | P43: 69 | Q43: 15 | R43: Not listed | S43: 0 | T43: 10 | U43: Erythritol + stevia | V43: Natural caffeine (69 mg), antioxidants, B vitamins, zero sugar | AA43: Medium | AB43: Mid caffeine functional sparkling; growing | AC43: Sparkling water with a light caffeine + antioxidant lift | AD43: Light natural caffeine and antioxidants without an energy drink dose. | AF43: =IF(AND(ISNUMBER($P43),ISNUMBER($AL43),$AL43<>0),ROUND($P43/$AL43*100,1),"") | AG43: =IF(AND(ISNUMBER($S43),ISNUMBER($AL43),$AL43<>0),ROUND($S43/$AL43*100,2),"") | AH43: =IF(AND(ISNUMBER($Q43),ISNUMBER($AL43),$AL43<>0),ROUND($Q43/$AL43*100,1),"") | AI43: =IF(ISNUMBER($S43),IF($S43<=1,"Yes","No"),"n/a") | AJ43: =IF(ISNUMBER($S43),ROUND(MAX(0,MIN(100,100-$S43*2.5-IF(ISNUMBER($T43),$T43,0)*0.12+IF($S43<=1,12,0))),0),"") | AK43: =IF(ISNUMBER($Q43),IF($Q43>=100,20,IF($Q43>=30,10,0)),0)+IF(ISNUMBER($R43),IF($R43>=100,20,0),0)+IF(ISNUMBER($P43),IF($P43>=150,20,IF($P43>=50,12,5)),0)+IF(ISNUMBER($S43),IF($S43<=1,15,0),0) | AL43: 473 | AN43: =IF(AND(ISNUMBER($P43),ISNUMBER($AL43),$AL43<>0),IF(OR($P43>180,$P43/$AL43*1000>400),"Over ceiling, confirm SKU","Within"),"n/a") | AR43: Recalled, batch confirmed, to confirm | AS43: BLANK -> requires live Amazon.ca capture | AT43: Unverified commercial data
A44: BUBBL'R | B44: BUBBL'R Antioxidant Sparkling Water | Strawbeary Lemonade | 8 pack 473mL | C44: 1) Sparkling electrolyte / functional sparkling | D44: 473 mL can | E44: 8 | G44: =IF(AND(ISNUMBER($F44),ISNUMBER($E44),$E44<>0),$F44/$E44,"") | H44: =IF(AND(ISNUMBER($F44),ISNUMBER($AL44),ISNUMBER($E44),($AL44*$E44)<>0),$F44/($AL44*$E44)*100,"") | K44: =IF(AND(ISNUMBER($F44),ISNUMBER($J44)),$F44*(1-$J44),"") | N44: =IF(ISNUMBER($F44),($F44-IF(ISNUMBER($AM44),$AM44,0))*(1-IF(ISNUMBER($J44),$J44,0)),"") | O44: Strawbeary Lemonade | P44: 69 | Q44: 15 | R44: Not listed | S44: 0 | T44: 10 | U44: Erythritol + stevia | V44: Natural caffeine (69 mg), antioxidants, B vitamins, zero sugar | AA44: Medium | AB44: Mid caffeine functional sparkling; growing | AC44: Sparkling water with a light caffeine + antioxidant lift | AD44: Light natural caffeine and antioxidants without an energy drink dose. | AF44: =IF(AND(ISNUMBER($P44),ISNUMBER($AL44),$AL44<>0),ROUND($P44/$AL44*100,1),"") | AG44: =IF(AND(ISNUMBER($S44),ISNUMBER($AL44),$AL44<>0),ROUND($S44/$AL44*100,2),"") | AH44: =IF(AND(ISNUMBER($Q44),ISNUMBER($AL44),$AL44<>0),ROUND($Q44/$AL44*100,1),"") | AI44: =IF(ISNUMBER($S44),IF($S44<=1,"Yes","No"),"n/a") | AJ44: =IF(ISNUMBER($S44),ROUND(MAX(0,MIN(100,100-$S44*2.5-IF(ISNUMBER($T44),$T44,0)*0.12+IF($S44<=1,12,0))),0),"") | AK44: =IF(ISNUMBER($Q44),IF($Q44>=100,20,IF($Q44>=30,10,0)),0)+IF(ISNUMBER($R44),IF($R44>=100,20,0),0)+IF(ISNUMBER($P44),IF($P44>=150,20,IF($P44>=50,12,5)),0)+IF(ISNUMBER($S44),IF($S44<=1,15,0),0) | AL44: 473 | AN44: =IF(AND(ISNUMBER($P44),ISNUMBER($AL44),$AL44<>0),IF(OR($P44>180,$P44/$AL44*1000>400),"Over ceiling, confirm SKU","Within"),"n/a") | AR44: Recalled, batch confirmed, to confirm | AS44: BLANK -> requires live Amazon.ca capture | AT44: Unverified commercial data
A45: BUBBL'R | B45: BUBBL'R Antioxidant Sparkling Water | Strawbeary Lemonade | 12 pack 473mL | C45: 1) Sparkling electrolyte / functional sparkling | D45: 473 mL can | E45: 12 | G45: =IF(AND(ISNUMBER($F45),ISNUMBER($E45),$E45<>0),$F45/$E45,"") | H45: =IF(AND(ISNUMBER($F45),ISNUMBER($AL45),ISNUMBER($E45),($AL45*$E45)<>0),$F45/($AL45*$E45)*100,"") | K45: =IF(AND(ISNUMBER($F45),ISNUMBER($J45)),$F45*(1-$J45),"") | N45: =IF(ISNUMBER($F45),($F45-IF(ISNUMBER($AM45),$AM45,0))*(1-IF(ISNUMBER($J45),$J45,0)),"") | O45: Strawbeary Lemonade | P45: 69 | Q45: 15 | R45: Not listed | S45: 0 | T45: 10 | U45: Erythritol + stevia | V45: Natural caffeine (69 mg), antioxidants, B vitamins, zero sugar | AA45: Medium | AB45: Mid caffeine functional sparkling; growing | AC45: Sparkling water with a light caffeine + antioxidant lift | AD45: Light natural caffeine and antioxidants without an energy drink dose. | AF45: =IF(AND(ISNUMBER($P45),ISNUMBER($AL45),$AL45<>0),ROUND($P45/$AL45*100,1),"") | AG45: =IF(AND(ISNUMBER($S45),ISNUMBER($AL45),$AL45<>0),ROUND($S45/$AL45*100,2),"") | AH45: =IF(AND(ISNUMBER($Q45),ISNUMBER($AL45),$AL45<>0),ROUND($Q45/$AL45*100,1),"") | AI45: =IF(ISNUMBER($S45),IF($S45<=1,"Yes","No"),"n/a") | AJ45: =IF(ISNUMBER($S45),ROUND(MAX(0,MIN(100,100-$S45*2.5-IF(ISNUMBER($T45),$T45,0)*0.12+IF($S45<=1,12,0))),0),"") | AK45: =IF(ISNUMBER($Q45),IF($Q45>=100,20,IF($Q45>=30,10,0)),0)+IF(ISNUMBER($R45),IF($R45>=100,20,0),0)+IF(ISNUMBER($P45),IF($P45>=150,20,IF($P45>=50,12,5)),0)+IF(ISNUMBER($S45),IF($S45<=1,15,0),0) | AL45: 473 | AN45: =IF(AND(ISNUMBER($P45),ISNUMBER($AL45),$AL45<>0),IF(OR($P45>180,$P45/$AL45*1000>400),"Over ceiling, confirm SKU","Within"),"n/a") | AR45: Recalled, batch confirmed, to confirm | AS45: BLANK -> requires live Amazon.ca capture | AT45: Unverified commercial data
A46: BUBBL'R | B46: BUBBL'R Antioxidant Sparkling Water | Strawbeary Lemonade | 18 pack 473mL | C46: 1) Sparkling electrolyte / functional sparkling | D46: 473 mL can | E46: 18 | G46: =IF(AND(ISNUMBER($F46),ISNUMBER($E46),$E46<>0),$F46/$E46,"") | H46: =IF(AND(ISNUMBER($F46),ISNUMBER($AL46),ISNUMBER($E46),($AL46*$E46)<>0),$F46/($AL46*$E46)*100,"") | K46: =IF(AND(ISNUMBER($F46),ISNUMBER($J46)),$F46*(1-$J46),"") | N46: =IF(ISNUMBER($F46),($F46-IF(ISNUMBER($AM46),$AM46,0))*(1-IF(ISNUMBER($J46),$J46,0)),"") | O46: Strawbeary Lemonade | P46: 69 | Q46: 15 | R46: Not listed | S46: 0 | T46: 10 | U46: Erythritol + stevia | V46: Natural caffeine (69 mg), antioxidants, B vitamins, zero sugar | AA46: Medium | AB46: Mid caffeine functional sparkling; growing | AC46: Sparkling water with a light caffeine + antioxidant lift | AD46: Light natural caffeine and antioxidants without an energy drink dose. | AF46: =IF(AND(ISNUMBER($P46),ISNUMBER($AL46),$AL46<>0),ROUND($P46/$AL46*100,1),"") | AG46: =IF(AND(ISNUMBER($S46),ISNUMBER($AL46),$AL46<>0),ROUND($S46/$AL46*100,2),"") | AH46: =IF(AND(ISNUMBER($Q46),ISNUMBER($AL46),$AL46<>0),ROUND($Q46/$AL46*100,1),"") | AI46: =IF(ISNUMBER($S46),IF($S46<=1,"Yes","No"),"n/a") | AJ46: =IF(ISNUMBER($S46),ROUND(MAX(0,MIN(100,100-$S46*2.5-IF(ISNUMBER($T46),$T46,0)*0.12+IF($S46<=1,12,0))),0),"") | AK46: =IF(ISNUMBER($Q46),IF($Q46>=100,20,IF($Q46>=30,10,0)),0)+IF(ISNUMBER($R46),IF($R46>=100,20,0),0)+IF(ISNUMBER($P46),IF($P46>=150,20,IF($P46>=50,12,5)),0)+IF(ISNUMBER($S46),IF($S46<=1,15,0),0) | AL46: 473 | AN46: =IF(AND(ISNUMBER($P46),ISNUMBER($AL46),$AL46<>0),IF(OR($P46>180,$P46/$AL46*1000>400),"Over ceiling, confirm SKU","Within"),"n/a") | AR46: Recalled, batch confirmed, to confirm | AS46: BLANK -> requires live Amazon.ca capture | AT46: Unverified commercial data
A47: BUBBL'R | B47: BUBBL'R Antioxidant Sparkling Water | Strawbeary Lemonade | 24 pack 473mL | C47: 1) Sparkling electrolyte / functional sparkling | D47: 473 mL can | E47: 24 | G47: =IF(AND(ISNUMBER($F47),ISNUMBER($E47),$E47<>0),$F47/$E47,"") | H47: =IF(AND(ISNUMBER($F47),ISNUMBER($AL47),ISNUMBER($E47),($AL47*$E47)<>0),$F47/($AL47*$E47)*100,"") | K47: =IF(AND(ISNUMBER($F47),ISNUMBER($J47)),$F47*(1-$J47),"") | N47: =IF(ISNUMBER($F47),($F47-IF(ISNUMBER($AM47),$AM47,0))*(1-IF(ISNUMBER($J47),$J47,0)),"") | O47: Strawbeary Lemonade | P47: 69 | Q47: 15 | R47: Not listed | S47: 0 | T47: 10 | U47: Erythritol + stevia | V47: Natural caffeine (69 mg), antioxidants, B vitamins, zero sugar | AA47: Medium | AB47: Mid caffeine functional sparkling; growing | AC47: Sparkling water with a light caffeine + antioxidant lift | AD47: Light natural caffeine and antioxidants without an energy drink dose. | AF47: =IF(AND(ISNUMBER($P47),ISNUMBER($AL47),$AL47<>0),ROUND($P47/$AL47*100,1),"") | AG47: =IF(AND(ISNUMBER($S47),ISNUMBER($AL47),$AL47<>0),ROUND($S47/$AL47*100,2),"") | AH47: =IF(AND(ISNUMBER($Q47),ISNUMBER($AL47),$AL47<>0),ROUND($Q47/$AL47*100,1),"") | AI47: =IF(ISNUMBER($S47),IF($S47<=1,"Yes","No"),"n/a") | AJ47: =IF(ISNUMBER($S47),ROUND(MAX(0,MIN(100,100-$S47*2.5-IF(ISNUMBER($T47),$T47,0)*0.12+IF($S47<=1,12,0))),0),"") | AK47: =IF(ISNUMBER($Q47),IF($Q47>=100,20,IF($Q47>=30,10,0)),0)+IF(ISNUMBER($R47),IF($R47>=100,20,0),0)+IF(ISNUMBER($P47),IF($P47>=150,20,IF($P47>=50,12,5)),0)+IF(ISNUMBER($S47),IF($S47<=1,15,0),0) | AL47: 473 | AN47: =IF(AND(ISNUMBER($P47),ISNUMBER($AL47),$AL47<>0),IF(OR($P47>180,$P47/$AL47*1000>400),"Over ceiling, confirm SKU","Within"),"n/a") | AR47: Recalled, batch confirmed, to confirm | AS47: BLANK -> requires live Amazon.ca capture | AT47: Unverified commercial data
A48: BUBBL'R | B48: BUBBL'R Antioxidant Sparkling Water | Tropic'b'r | single 473mL | C48: 1) Sparkling electrolyte / functional sparkling | D48: 473 mL can | E48: 1 | G48: =IF(AND(ISNUMBER($F48),ISNUMBER($E48),$E48<>0),$F48/$E48,"") | H48: =IF(AND(ISNUMBER($F48),ISNUMBER($AL48),ISNUMBER($E48),($AL48*$E48)<>0),$F48/($AL48*$E48)*100,"") | K48: =IF(AND(ISNUMBER($F48),ISNUMBER($J48)),$F48*(1-$J48),"") | N48: =IF(ISNUMBER($F48),($F48-IF(ISNUMBER($AM48),$AM48,0))*(1-IF(ISNUMBER($J48),$J48,0)),"") | O48: Tropic'b'r | P48: 69 | Q48: 15 | R48: Not listed | S48: 0 | T48: 10 | U48: Erythritol + stevia | V48: Natural caffeine (69 mg), antioxidants, B vitamins, zero sugar | AA48: Medium | AB48: Mid caffeine functional sparkling; growing | AC48: Sparkling water with a light caffeine + antioxidant lift | AD48: Light natural caffeine and antioxidants without an energy drink dose. | AF48: =IF(AND(ISNUMBER($P48),ISNUMBER($AL48),$AL48<>0),ROUND($P48/$AL48*100,1),"") | AG48: =IF(AND(ISNUMBER($S48),ISNUMBER($AL48),$AL48<>0),ROUND($S48/$AL48*100,2),"") | AH48: =IF(AND(ISNUMBER($Q48),ISNUMBER($AL48),$AL48<>0),ROUND($Q48/$AL48*100,1),"") | AI48: =IF(ISNUMBER($S48),IF($S48<=1,"Yes","No"),"n/a") | AJ48: =IF(ISNUMBER($S48),ROUND(MAX(0,MIN(100,100-$S48*2.5-IF(ISNUMBER($T48),$T48,0)*0.12+IF($S48<=1,12,0))),0),"") | AK48: =IF(ISNUMBER($Q48),IF($Q48>=100,20,IF($Q48>=30,10,0)),0)+IF(ISNUMBER($R48),IF($R48>=100,20,0),0)+IF(ISNUMBER($P48),IF($P48>=150,20,IF($P48>=50,12,5)),0)+IF(ISNUMBER($S48),IF($S48<=1,15,0),0) | AL48: 473 | AN48: =IF(AND(ISNUMBER($P48),ISNUMBER($AL48),$AL48<>0),IF(OR($P48>180,$P48/$AL48*1000>400),"Over ceiling, confirm SKU","Within"),"n/a") | AR48: Recalled, batch confirmed, to confirm | AS48: BLANK -> requires live Amazon.ca capture | AT48: Unverified commercial data
A49: BUBBL'R | B49: BUBBL'R Antioxidant Sparkling Water | Tropic'b'r | 8 pack 473mL | C49: 1) Sparkling electrolyte / functional sparkling | D49: 473 mL can | E49: 8 | G49: =IF(AND(ISNUMBER($F49),ISNUMBER($E49),$E49<>0),$F49/$E49,"") | H49: =IF(AND(ISNUMBER($F49),ISNUMBER($AL49),ISNUMBER($E49),($AL49*$E49)<>0),$F49/($AL49*$E49)*100,"") | K49: =IF(AND(ISNUMBER($F49),ISNUMBER($J49)),$F49*(1-$J49),"") | N49: =IF(ISNUMBER($F49),($F49-IF(ISNUMBER($AM49),$AM49,0))*(1-IF(ISNUMBER($J49),$J49,0)),"") | O49: Tropic'b'r | P49: 69 | Q49: 15 | R49: Not listed | S49: 0 | T49: 10 | U49: Erythritol + stevia | V49: Natural caffeine (69 mg), antioxidants, B vitamins, zero sugar | AA49: Medium | AB49: Mid caffeine functional sparkling; growing | AC49: Sparkling water with a light caffeine + antioxidant lift | AD49: Light natural caffeine and antioxidants without an energy drink dose. | AF49: =IF(AND(ISNUMBER($P49),ISNUMBER($AL49),$AL49<>0),ROUND($P49/$AL49*100,1),"") | AG49: =IF(AND(ISNUMBER($S49),ISNUMBER($AL49),$AL49<>0),ROUND($S49/$AL49*100,2),"") | AH49: =IF(AND(ISNUMBER($Q49),ISNUMBER($AL49),$AL49<>0),ROUND($Q49/$AL49*100,1),"") | AI49: =IF(ISNUMBER($S49),IF($S49<=1,"Yes","No"),"n/a") | AJ49: =IF(ISNUMBER($S49),ROUND(MAX(0,MIN(100,100-$S49*2.5-IF(ISNUMBER($T49),$T49,0)*0.12+IF($S49<=1,12,0))),0),"") | AK49: =IF(ISNUMBER($Q49),IF($Q49>=100,20,IF($Q49>=30,10,0)),0)+IF(ISNUMBER($R49),IF($R49>=100,20,0),0)+IF(ISNUMBER($P49),IF($P49>=150,20,IF($P49>=50,12,5)),0)+IF(ISNUMBER($S49),IF($S49<=1,15,0),0) | AL49: 473 | AN49: =IF(AND(ISNUMBER($P49),ISNUMBER($AL49),$AL49<>0),IF(OR($P49>180,$P49/$AL49*1000>400),"Over ceiling, confirm SKU","Within"),"n/a") | AR49: Recalled, batch confirmed, to confirm | AS49: BLANK -> requires live Amazon.ca capture | AT49: Unverified commercial data
... A152: Sound | B152: Sound Sparkling Water (Tea/Botanical) | Cucumber + Mint Green Tea | 24 pack 355mL | C152: 1) Sparkling electrolyte / functional sparkling | D152: 355 mL can | E152: 24 | G152: =IF(AND(ISNUMBER($F152),ISNUMBER($E152),$E152<>0),$F152/$E152,"") | H152: =IF(AND(ISNUMBER($F152),ISNUMBER($AL152),ISNUMBER($E152),($AL152*$E152)<>0),$F152/($AL152*$E152)*100,"") | K152: =IF(AND(ISNUMBER($F152),ISNUMBER($J152)),$F152*(1-$J152),"") | N152: =IF(ISNUMBER($F152),($F152-IF(ISNUMBER($AM152),$AM152,0))*(1-IF(ISNUMBER($J152),$J152,0)),"") | O152: Cucumber + Mint Green Tea | P152: 15 | Q152: 0 | R152: Not listed | S152: 0 | T152: 0 | U152: None (unsweetened) | V152: Real brewed tea/botanicals, unsweetened, zero sugar/calorie | AA152: Low | AB152: Emerging unsweetened botanical niche | AC152: Unsweetened sparkling brewed tea and botanicals | AD152: Genuinely unsweetened with real tea/botanical character. | AF152: =IF(AND(ISNUMBER($P152),ISNUMBER($AL152),$AL152<>0),ROUND($P152/$AL152*100,1),"") | AG152: =IF(AND(ISNUMBER($S152),ISNUMBER($AL152),$AL152<>0),ROUND($S152/$AL152*100,2),"") | AH152: =IF(AND(ISNUMBER($Q152),ISNUMBER($AL152),$AL152<>0),ROUND($Q152/$AL152*100,1),"") | AI152: =IF(ISNUMBER($S152),IF($S152<=1,"Yes","No"),"n/a") | AJ152: =IF(ISNUMBER($S152),ROUND(MAX(0,MIN(100,100-$S152*2.5-IF(ISNUMBER($T152),$T152,0)*0.12+IF($S152<=1,12,0))),0),"") | AK152: =IF(ISNUMBER($Q152),IF($Q152>=100,20,IF($Q152>=30,10,0)),0)+IF(ISNUMBER($R152),IF($R152>=100,20,0),0)+IF(ISNUMBER($P152),IF($P152>=150,20,IF($P152>=50,12,5)),0)+IF(ISNUMBER($S152),IF($S152<=1,15,0),0) | AL152: 355 | AN152: =IF(AND(ISNUMBER($P152),ISNUMBER($AL152),$AL152<>0),IF(OR($P152>180,$P152/$AL152*1000>400),"Over ceiling, confirm SKU","Within"),"n/a") | AR152: Recalled, batch confirmed, to confirm | AS152: BLANK -> requires live Amazon.ca capture | AT152: Unverified commercial data
A153: Halo Sport | B153: Halo Sport Sparkling Electrolyte Water | Lemon Lime | single 355mL | C153: 1) Sparkling electrolyte / functional sparkling | D153: 355 mL can | E153: 1 | G153: =IF(AND(ISNUMBER($F153),ISNUMBER($E153),$E153<>0),$F153/$E153,"") | H153: =IF(AND(ISNUMBER($F153),ISNUMBER($AL153),ISNUMBER($E153),($AL153*$E153)<>0),$F153/($AL153*$E153)*100,"") | K153: =IF(AND(ISNUMBER($F153),ISNUMBER($J153)),$F153*(1-$J153),"") | N153: =IF(ISNUMBER($F153),($F153-IF(ISNUMBER($AM153),$AM153,0))*(1-IF(ISNUMBER($J153),$J153,0)),"") | O153: Lemon Lime | P153: 0 | Q153: 110 | R153: 40 | S153: 0 | T153: 5 | U153: Stevia | V153: Sparkling electrolytes, zero sugar, light hydration | AA153: Low | AB153: Small emerging sparkling electrolyte entrant | AC153: Sparkling, lightly mineralled hydration | AD153: Electrolytes in a fizzy, zero sugar format. | AF153: =IF(AND(ISNUMBER($P153),ISNUMBER($AL153),$AL153<>0),ROUND($P153/$AL153*100,1),"") | AG153: =IF(AND(ISNUMBER($S153),ISNUMBER($AL153),$AL153<>0),ROUND($S153/$AL153*100,2),"") | AH153: =IF(AND(ISNUMBER($Q153),ISNUMBER($AL153),$AL153<>0),ROUND($Q153/$AL153*100,1),"") | AI153: =IF(ISNUMBER($S153),IF($S153<=1,"Yes","No"),"n/a") | AJ153: =IF(ISNUMBER($S153),ROUND(MAX(0,MIN(100,100-$S153*2.5-IF(ISNUMBER($T153),$T153,0)*0.12+IF($S153<=1,12,0))),0),"") | AK153: =IF(ISNUMBER($Q153),IF($Q153>=100,20,IF($Q153>=30,10,0)),0)+IF(ISNUMBER($R153),IF($R153>=100,20,0),0)+IF(ISNUMBER($P153),IF($P153>=150,20,IF($P153>=50,12,5)),0)+IF(ISNUMBER($S153),IF($S153<=1,15,0),0) | AL153: 355 | AN153: =IF(AND(ISNUMBER($P153),ISNUMBER($AL153),$AL153<>0),IF(OR($P153>180,$P153/$AL153*1000>400),"Over ceiling, confirm SKU","Within"),"n/a") | AR153: Recalled, batch confirmed, to confirm | AS153: BLANK -> requires live Amazon.ca capture | AT153: Unverified commercial data
A154: Halo Sport | B154: Halo Sport Sparkling Electrolyte Water | Lemon Lime | 8 pack 355mL | C154: 1) Sparkling electrolyte / functional sparkling | D154: 355 mL can | E154: 8 | G154: =IF(AND(ISNUMBER($F154),ISNUMBER($E154),$E154<>0),$F154/$E154,"") | H154: =IF(AND(ISNUMBER($F154),ISNUMBER($AL154),ISNUMBER($E154),($AL154*$E154)<>0),$F154/($AL154*$E154)*100,"") | K154: =IF(AND(ISNUMBER($F154),ISNUMBER($J154)),$F154*(1-$J154),"") | N154: =IF(ISNUMBER($F154),($F154-IF(ISNUMBER($AM154),$AM154,0))*(1-IF(ISNUMBER($J154),$J154,0)),"") | O154: Lemon Lime | P154: 0 | Q154: 110 | R154: 40 | S154: 0 | T154: 5 | U154: Stevia | V154: Sparkling electrolytes, zero sugar, light hydration | AA154: Low | AB154: Small emerging sparkling electrolyte entrant | AC154: Sparkling, lightly mineralled hydration | AD154: Electrolytes in a fizzy, zero sugar format. | AF154: =IF(AND(ISNUMBER($P154),ISNUMBER($AL154),$AL154<>0),ROUND($P154/$AL154*100,1),"") | AG154: =IF(AND(ISNUMBER($S154),ISNUMBER($AL154),$AL154<>0),ROUND($S154/$AL154*100,2),"") | AH154: =IF(AND(ISNUMBER($Q154),ISNUMBER($AL154),$AL154<>0),ROUND($Q154/$AL154*100,1),"") | AI154: =IF(ISNUMBER($S154),IF($S154<=1,"Yes","No"),"n/a") | AJ154: =IF(ISNUMBER($S154),ROUND(MAX(0,MIN(100,100-$S154*2.5-IF(ISNUMBER($T154),$T154,0)*0.12+IF($S154<=1,12,0))),0),"") | AK154: =IF(ISNUMBER($Q154),IF($Q154>=100,20,IF($Q154>=30,10,0)),0)+IF(ISNUMBER($R154),IF($R154>=100,20,0),0)+IF(ISNUMBER($P154),IF($P154>=150,20,IF($P154>=50,12,5)),0)+IF(ISNUMBER($S154),IF($S154<=1,15,0),0) | AL154: 355 | AN154: =IF(AND(ISNUMBER($P154),ISNUMBER($AL154),$AL154<>0),IF(OR($P154>180,$P154/$AL154*1000>400),"Over ceiling, confirm SKU","Within"),"n/a") | AR154: Recalled, batch confirmed, to confirm | AS154: BLANK -> requires live Amazon.ca capture | AT154: Unverified commercial data
A155: Halo Sport | B155: Halo Sport Sparkling Electrolyte Water | Lemon Lime | 12 pack 355mL | C155: 1) Sparkling electrolyte / functional sparkling | D155: 355 mL can | E155: 12 | G155: =IF(AND(ISNUMBER($F155),ISNUMBER($E155),$E155<>0),$F155/$E155,"") | H155: =IF(AND(ISNUMBER($F155),ISNUMBER($AL155),ISNUMBER($E155),($AL155*$E155)<>0),$F155/($AL155*$E155)*100,"") | K155: =IF(AND(ISNUMBER($F155),ISNUMBER($J155)),$F155*(1-$J155),"") | N155: =IF(ISNUMBER($F155),($F155-IF(ISNUMBER($AM155),$AM155,0))*(1-IF(ISNUMBER($J155),$J155,0)),"") | O155: Lemon Lime | P155: 0 | Q155: 110 | R155: 40 | S155: 0 | T155: 5 | U155: Stevia | V155: Sparkling electrolytes, zero sugar, light hydration | AA155: Low | AB155: Small emerging sparkling electrolyte entrant | AC155: Sparkling, lightly mineralled hydration | AD155: Electrolytes in a fizzy, zero sugar format. | AF155: =IF(AND(ISNUMBER($P155),ISNUMBER($AL155),$AL155<>0),ROUND($P155/$AL155*100,1),"") | AG155: =IF(AND(ISNUMBER($S155),ISNUMBER($AL155),$AL155<>0),ROUND($S155/$AL155*100,2),"") | AH155: =IF(AND(ISNUMBER($Q155),ISNUMBER($AL155),$AL155<>0),ROUND($Q155/$AL155*100,1),"") | AI155: =IF(ISNUMBER($S155),IF($S155<=1,"Yes","No"),"n/a") | AJ155: =IF(ISNUMBER($S155),ROUND(MAX(0,MIN(100,100-$S155*2.5-IF(ISNUMBER($T155),$T155,0)*0.12+IF($S155<=1,12,0))),0),"") | AK155: =IF(ISNUMBER($Q155),IF($Q155>=100,20,IF($Q155>=30,10,0)),0)+IF(ISNUMBER($R155),IF($R155>=100,20,0),0)+IF(ISNUMBER($P155),IF($P155>=150,20,IF($P155>=50,12,5)),0)+IF(ISNUMBER($S155),IF($S155<=1,15,0),0) | AL155: 355 | AN155: =IF(AND(ISNUMBER($P155),ISNUMBER($AL155),$AL155<>0),IF(OR($P155>180,$P155/$AL155*1000>400),"Over ceiling, confirm SKU","Within"),"n/a") | AR155: Recalled, batch confirmed, to confirm | AS155: BLANK -> requires live Amazon.ca capture | AT155: Unverified commercial data
A156: Halo Sport | B156: Halo Sport Sparkling Electrolyte Water | Lemon Lime | 15 pack 355mL | C156: 1) Sparkling electrolyte / functional sparkling | D156: 355 mL can | E156: 15 | G156: =IF(AND(ISNUMBER($F156),ISNUMBER($E156),$E156<>0),$F156/$E156,"") | H156: =IF(AND(ISNUMBER($F156),ISNUMBER($AL156),ISNUMBER($E156),($AL156*$E156)<>0),$F156/($AL156*$E156)*100,"") | K156: =IF(AND(ISNUMBER($F156),ISNUMBER($J156)),$F156*(1-$J156),"") | N156: =IF(ISNUMBER($F156),($F156-IF(ISNUMBER($AM156),$AM156,0))*(1-IF(ISNUMBER($J156),$J156,0)),"") | O156: Lemon Lime | P156: 0 | Q156: 110 | R156: 40 | S156: 0 | T156: 5 | U156: Stevia | V156: Sparkling electrolytes, zero sugar, light hydration | AA156: Low | AB156: Small emerging sparkling electrolyte entrant | AC156: Sparkling, lightly mineralled hydration | AD156: Electrolytes in a fizzy, zero sugar format. | AF156: =IF(AND(ISNUMBER($P156),ISNUMBER($AL156),$AL156<>0),ROUND($P156/$AL156*100,1),"") | AG156: =IF(AND(ISNUMBER($S156),ISNUMBER($AL156),$AL156<>0),ROUND($S156/$AL156*100,2),"") | AH156: =IF(AND(ISNUMBER($Q156),ISNUMBER($AL156),$AL156<>0),ROUND($Q156/$AL156*100,1),"") | AI156: =IF(ISNUMBER($S156),IF($S156<=1,"Yes","No"),"n/a") | AJ156: =IF(ISNUMBER($S156),ROUND(MAX(0,MIN(100,100-$S156*2.5-IF(ISNUMBER($T156),$T156,0)*0.12+IF($S156<=1,12,0))),0),"") | AK156: =IF(ISNUMBER($Q156),IF($Q156>=100,20,IF($Q156>=30,10,0)),0)+IF(ISNUMBER($R156),IF($R156>=100,20,0),0)+IF(ISNUMBER($P156),IF($P156>=150,20,IF($P156>=50,12,5)),0)+IF(ISNUMBER($S156),IF($S156<=1,15,0),0) | AL156: 355 | AN156: =IF(AND(ISNUMBER($P156),ISNUMBER($AL156),$AL156<>0),IF(OR($P156>180,$P156/$AL156*1000>400),"Over ceiling, confirm SKU","Within"),"n/a") | AR156: Recalled, batch confirmed, to confirm | AS156: BLANK -> requires live Amazon.ca capture | AT156: Unverified commercial data
A157: Halo Sport | B157: Halo Sport Sparkling Electrolyte Water | Lemon Lime | 18 pack 355mL | C157: 1) Sparkling electrolyte / functional sparkling | D157: 355 mL can | E157: 18 | G157: =IF(AND(ISNUMBER($F157),ISNUMBER($E157),$E157<>0),$F157/$E157,"") | H157: =IF(AND(ISNUMBER($F157),ISNUMBER($AL157),ISNUMBER($E157),($AL157*$E157)<>0),$F157/($AL157*$E157)*100,"") | K157: =IF(AND(ISNUMBER($F157),ISNUMBER($J157)),$F157*(1-$J157),"") | N157: =IF(ISNUMBER($F157),($F157-IF(ISNUMBER($AM157),$AM157,0))*(1-IF(ISNUMBER($J157),$J157,0)),"") | O157: Lemon Lime | P157: 0 | Q157: 110 | R157: 40 | S157: 0 | T157: 5 | U157: Stevia | V157: Sparkling electrolytes, zero sugar, light hydration | AA157: Low | AB157: Small emerging sparkling electrolyte entrant | AC157: Sparkling, lightly mineralled hydration | AD157: Electrolytes in a fizzy, zero sugar format. | AF157: =IF(AND(ISNUMBER($P157),ISNUMBER($AL157),$AL157<>0),ROUND($P157/$AL157*100,1),"") | AG157: =IF(AND(ISNUMBER($S157),ISNUMBER($AL157),$AL157<>0),ROUND($S157/$AL157*100,2),"") | AH157: =IF(AND(ISNUMBER($Q157),ISNUMBER($AL157),$AL157<>0),ROUND($Q157/$AL157*100,1),"") | AI157: =IF(ISNUMBER($S157),IF($S157<=1,"Yes","No"),"n/a") | AJ157: =IF(ISNUMBER($S157),ROUND(MAX(0,MIN(100,100-$S157*2.5-IF(ISNUMBER($T157),$T157,0)*0.12+IF($S157<=1,12,0))),0),"") | AK157: =IF(ISNUMBER($Q157),IF($Q157>=100,20,IF($Q157>=30,10,0)),0)+IF(ISNUMBER($R157),IF($R157>=100,20,0),0)+IF(ISNUMBER($P157),IF($P157>=150,20,IF($P157>=50,12,5)),0)+IF(ISNUMBER($S157),IF($S157<=1,15,0),0) | AL157: 355 | AN157: =IF(AND(ISNUMBER($P157),ISNUMBER($AL157),$AL157<>0),IF(OR($P157>180,$P157/$AL157*1000>400),"Over ceiling, confirm SKU","Within"),"n/a") | AR157: Recalled, batch confirmed, to confirm | AS157: BLANK -> requires live Amazon.ca capture | AT157: Unverified commercial data
A158: Halo Sport | B158: Halo Sport Sparkling Electrolyte Water | Lemon Lime | 24 pack 355mL | C158: 1) Sparkling electrolyte / functional sparkling | D158: 355 mL can | E158: 24 | G158: =IF(AND(ISNUMBER($F158),ISNUMBER($E158),$E158<>0),$F158/$E158,"") | H158: =IF(AND(ISNUMBER($F158),ISNUMBER($AL158),ISNUMBER($E158),($AL158*$E158)<>0),$F158/($AL158*$E158)*100,"") | K158: =IF(AND(ISNUMBER($F158),ISNUMBER($J158)),$F158*(1-$J158),"") | N158: =IF(ISNUMBER($F158),($F158-IF(ISNUMBER($AM158),$AM158,0))*(1-IF(ISNUMBER($J158),$J158,0)),"") | O158: Lemon Lime | P158: 0 | Q158: 110 | R158: 40 | S158: 0 | T158: 5 | U158: Stevia | V158: Sparkling electrolytes, zero sugar, light hydration | AA158: Low | AB158: Small emerging sparkling electrolyte entrant | AC158: Sparkling, lightly mineralled hydration | AD158: Electrolytes in a fizzy, zero sugar format. | AF158: =IF(AND(ISNUMBER($P158),ISNUMBER($AL158),$AL158<>0),ROUND($P158/$AL158*100,1),"") | AG158: =IF(AND(ISNUMBER($S158),ISNUMBER($AL158),$AL158<>0),ROUND($S158/$AL158*100,2),"") | AH158: =IF(AND(ISNUMBER($Q158),ISNUMBER($AL158),$AL158<>0),ROUND($Q158/$AL158*100,1),"") | AI158: =IF(ISNUMBER($S158),IF($S158<=1,"Yes","No"),"n/a") | AJ158: =IF(ISNUMBER($S158),ROUND(MAX(0,MIN(100,100-$S158*2.5-IF(ISNUMBER($T158),$T158,0)*0.12+IF($S158<=1,12,0))),0),"") | AK158: =IF(ISNUMBER($Q158),IF($Q158>=100,20,IF($Q158>=30,10,0)),0)+IF(ISNUMBER($R158),IF($R158>=100,20,0),0)+IF(ISNUMBER($P158),IF($P158>=150,20,IF($P158>=50,12,5)),0)+IF(ISNUMBER($S158),IF($S158<=1,15,0),0) | AL158: 355 | AN158: =IF(AND(ISNUMBER($P158),ISNUMBER($AL158),$AL158<>0),IF(OR($P158>180,$P158/$AL158*1000>400),"Over ceiling, confirm SKU","Within"),"n/a") | AR158: Recalled, batch confirmed, to confirm | AS158: BLANK -> requires live Amazon.ca capture | AT158: Unverified commercial data
A159: Halo Sport | B159: Halo Sport Sparkling Electrolyte Water | Berry | single 355mL | C159: 1) Sparkling electrolyte / functional sparkling | D159: 355 mL can | E159: 1 | G159: =IF(AND(ISNUMBER($F159),ISNUMBER($E159),$E159<>0),$F159/$E159,"") | H159: =IF(AND(ISNUMBER($F159),ISNUMBER($AL159),ISNUMBER($E159),($AL159*$E159)<>0),$F159/($AL159*$E159)*100,"") | K159: =IF(AND(ISNUMBER($F159),ISNUMBER($J159)),$F159*(1-$J159),"") | N159: =IF(ISNUMBER($F159),($F159-IF(ISNUMBER($AM159),$AM159,0))*(1-IF(ISNUMBER($J159),$J159,0)),"") | O159: Berry | P159: 0 | Q159: 110 | R159: 40 | S159: 0 | T159: 5 | U159: Stevia | V159: Sparkling electrolytes, zero sugar, light hydration | AA159: Low | AB159: Small emerging sparkling electrolyte entrant | AC159: Sparkling, lightly mineralled hydration | AD159: Electrolytes in a fizzy, zero sugar format. | AF159: =IF(AND(ISNUMBER($P159),ISNUMBER($AL159),$AL159<>0),ROUND($P159/$AL159*100,1),"") | AG159: =IF(AND(ISNUMBER($S159),ISNUMBER($AL159),$AL159<>0),ROUND($S159/$AL159*100,2),"") | AH159: =IF(AND(ISNUMBER($Q159),ISNUMBER($AL159),$AL159<>0),ROUND($Q159/$AL159*100,1),"") | AI159: =IF(ISNUMBER($S159),IF($S159<=1,"Yes","No"),"n/a") | AJ159: =IF(ISNUMBER($S159),ROUND(MAX(0,MIN(100,100-$S159*2.5-IF(ISNUMBER($T159),$T159,0)*0.12+IF($S159<=1,12,0))),0),"") | AK159: =IF(ISNUMBER($Q159),IF($Q159>=100,20,IF($Q159>=30,10,0)),0)+IF(ISNUMBER($R159),IF($R159>=100,20,0),0)+IF(ISNUMBER($P159),IF($P159>=150,20,IF($P159>=50,12,5)),0)+IF(ISNUMBER($S159),IF($S159<=1,15,0),0) | AL159: 355 | AN159: =IF(AND(ISNUMBER($P159),ISNUMBER($AL159),$AL159<>0),IF(OR($P159>180,$P159/$AL159*1000>400),"Over ceiling, confirm SKU","Within"),"n/a") | AR159: Recalled, batch confirmed, to confirm | AS159: BLANK -> requires live Amazon.ca capture | AT159: Unverified commercial data
A160: Halo Sport | B160: Halo Sport Sparkling Electrolyte Water | Berry | 8 pack 355mL | C160: 1) Sparkling electrolyte / functional sparkling | D160: 355 mL can | E160: 8 | G160: =IF(AND(ISNUMBER($F160),ISNUMBER($E160),$E160<>0),$F160/$E160,"") | H160: =IF(AND(ISNUMBER($F160),ISNUMBER($AL160),ISNUMBER($E160),($AL160*$E160)<>0),$F160/($AL160*$E160)*100,"") | K160: =IF(AND(ISNUMBER($F160),ISNUMBER($J160)),$F160*(1-$J160),"") | N160: =IF(ISNUMBER($F160),($F160-IF(ISNUMBER($AM160),$AM160,0))*(1-IF(ISNUMBER($J160),$J160,0)),"") | O160: Berry | P160: 0 | Q160: 110 | R160: 40 | S160: 0 | T160: 5 | U160: Stevia | V160: Sparkling electrolytes, zero sugar, light hydration | AA160: Low | AB160: Small emerging sparkling electrolyte entrant | AC160: Sparkling, lightly mineralled hydration | AD160: Electrolytes in a fizzy, zero sugar format. | AF160: =IF(AND(ISNUMBER($P160),ISNUMBER($AL160),$AL160<>0),ROUND($P160/$AL160*100,1),"") | AG160: =IF(AND(ISNUMBER($S160),ISNUMBER($AL160),$AL160<>0),ROUND($S160/$AL160*100,2),"") | AH160: =IF(AND(ISNUMBER($Q160),ISNUMBER($AL160),$AL160<>0),ROUND($Q160/$AL160*100,1),"") | AI160: =IF(ISNUMBER($S160),IF($S160<=1,"Yes","No"),"n/a") | AJ160: =IF(ISNUMBER($S160),ROUND(MAX(0,MIN(100,100-$S160*2.5-IF(ISNUMBER($T160),$T160,0)*0.12+IF($S160<=1,12,0))),0),"") | AK160: =IF(ISNUMBER($Q160),IF($Q160>=100,20,IF($Q160>=30,10,0)),0)+IF(ISNUMBER($R160),IF($R160>=100,20,0),0)+IF(ISNUMBER($P160),IF($P160>=150,20,IF($P160>=50,12,5)),0)+IF(ISNUMBER($S160),IF($S160<=1,15,0),0) | AL160: 355 | AN160: =IF(AND(ISNUMBER($P160),ISNUMBER($AL160),$AL160<>0),IF(OR($P160>180,$P160/$AL160*1000>400),"Over ceiling, confirm SKU","Within"),"n/a") | AR160: Recalled, batch confirmed, to confirm | AS160: BLANK -> requires live Amazon.ca capture | AT160: Unverified commercial data
A161: Halo Sport | B161: Halo Sport Sparkling Electrolyte Water | Berry | 12 pack 355mL | C161: 1) Sparkling electrolyte / functional sparkling | D161: 355 mL can | E161: 12 | G161: =IF(AND(ISNUMBER($F161),ISNUMBER($E161),$E161<>0),$F161/$E161,"") | H161: =IF(AND(ISNUMBER($F161),ISNUMBER($AL161),ISNUMBER($E161),($AL161*$E161)<>0),$F161/($AL161*$E161)*100,"") | K161: =IF(AND(ISNUMBER($F161),ISNUMBER($J161)),$F161*(1-$J161),"") | N161: =IF(ISNUMBER($F161),($F161-IF(ISNUMBER($AM161),$AM161,0))*(1-IF(ISNUMBER($J161),$J161,0)),"") | O161: Berry | P161: 0 | Q161: 110 | R161: 40 | S161: 0 | T161: 5 | U161: Stevia | V161: Sparkling electrolytes, zero sugar, light hydration | AA161: Low | AB161: Small emerging sparkling electrolyte entrant | AC161: Sparkling, lightly mineralled hydration | AD161: Electrolytes in a fizzy, zero sugar format. | AF161: =IF(AND(ISNUMBER($P161),ISNUMBER($AL161),$AL161<>0),ROUND($P161/$AL161*100,1),"") | AG161: =IF(AND(ISNUMBER($S161),ISNUMBER($AL161),$AL161<>0),ROUND($S161/$AL161*100,2),"") | AH161: =IF(AND(ISNUMBER($Q161),ISNUMBER($AL161),$AL161<>0),ROUND($Q161/$AL161*100,1),"") | AI161: =IF(ISNUMBER($S161),IF($S161<=1,"Yes","No"),"n/a") | AJ161: =IF(ISNUMBER($S161),ROUND(MAX(0,MIN(100,100-$S161*2.5-IF(ISNUMBER($T161),$T161,0)*0.12+IF($S161<=1,12,0))),0),"") | AK161: =IF(ISNUMBER($Q161),IF($Q161>=100,20,IF($Q161>=30,10,0)),0)+IF(ISNUMBER($R161),IF($R161>=100,20,0),0)+IF(ISNUMBER($P161),IF($P161>=150,20,IF($P161>=50,12,5)),0)+IF(ISNUMBER($S161),IF($S161<=1,15,0),0) | AL161: 355 | AN161: =IF(AND(ISNUMBER($P161),ISNUMBER($AL161),$AL161<>0),IF(OR($P161>180,$P161/$AL161*1000>400),"Over ceiling, confirm SKU","Within"),"n/a") | AR161: Recalled, batch confirmed, to confirm | AS161: BLANK -> requires live Amazon.ca capture | AT161: Unverified commercial data
A162: Halo Sport | B162: Halo Sport Sparkling Electrolyte Water | Berry | 15 pack 355mL | C162: 1) Sparkling electrolyte / functional sparkling | D162: 355 mL can | E162: 15 | G162: =IF(AND(ISNUMBER($F162),ISNUMBER($E162),$E162<>0),$F162/$E162,"") | H162: =IF(AND(ISNUMBER($F162),ISNUMBER($AL162),ISNUMBER($E162),($AL162*$E162)<>0),$F162/($AL162*$E162)*100,"") | K162: =IF(AND(ISNUMBER($F162),ISNUMBER($J162)),$F162*(1-$J162),"") | N162: =IF(ISNUMBER($F162),($F162-IF(ISNUMBER($AM162),$AM162,0))*(1-IF(ISNUMBER($J162),$J162,0)),"") | O162: Berry | P162: 0 | Q162: 110 | R162: 40 | S162: 0 | T162: 5 | U162: Stevia | V162: Sparkling electrolytes, zero sugar, light hydration | AA162: Low | AB162: Small emerging sparkling electrolyte entrant | AC162: Sparkling, lightly mineralled hydration | AD162: Electrolytes in a fizzy, zero sugar format. | AF162: =IF(AND(ISNUMBER($P162),ISNUMBER($AL162),$AL162<>0),ROUND($P162/$AL162*100,1),"") | AG162: =IF(AND(ISNUMBER($S162),ISNUMBER($AL162),$AL162<>0),ROUND($S162/$AL162*100,2),"") | AH162: =IF(AND(ISNUMBER($Q162),ISNUMBER($AL162),$AL162<>0),ROUND($Q162/$AL162*100,1),"") | AI162: =IF(ISNUMBER($S162),IF($S162<=1,"Yes","No"),"n/a") | AJ162: =IF(ISNUMBER($S162),ROUND(MAX(0,MIN(100,100-$S162*2.5-IF(ISNUMBER($T162),$T162,0)*0.12+IF($S162<=1,12,0))),0),"") | AK162: =IF(ISNUMBER($Q162),IF($Q162>=100,20,IF($Q162>=30,10,0)),0)+IF(ISNUMBER($R162),IF($R162>=100,20,0),0)+IF(ISNUMBER($P162),IF($P162>=150,20,IF($P162>=50,12,5)),0)+IF(ISNUMBER($S162),IF($S162<=1,15,0),0) | AL162: 355 | AN162: =IF(AND(ISNUMBER($P162),ISNUMBER($AL162),$AL162<>0),IF(OR($P162>180,$P162/$AL162*1000>400),"Over ceiling, confirm SKU","Within"),"n/a") | AR162: Recalled, batch confirmed, to confirm | AS162: BLANK -> requires live Amazon.ca capture | AT162: Unverified commercial data
A163: Halo Sport | B163: Halo Sport Sparkling Electrolyte Water | Berry | 18 pack 355mL | C163: 1) Sparkling electrolyte / functional sparkling | D163: 355 mL can | E163: 18 | G163: =IF(AND(ISNUMBER($F163),ISNUMBER($E163),$E163<>0),$F163/$E163,"") | H163: =IF(AND(ISNUMBER($F163),ISNUMBER($AL163),ISNUMBER($E163),($AL163*$E163)<>0),$F163/($AL163*$E163)*100,"") | K163: =IF(AND(ISNUMBER($F163),ISNUMBER($J163)),$F163*(1-$J163),"") | N163: =IF(ISNUMBER($F163),($F163-IF(ISNUMBER($AM163),$AM163,0))*(1-IF(ISNUMBER($J163),$J163,0)),"") | O163: Berry | P163: 0 | Q163: 110 | R163: 40 | S163: 0 | T163: 5 | U163: Stevia | V163: Sparkling electrolytes, zero sugar, light hydration | AA163: Low | AB163: Small emerging sparkling electrolyte entrant | AC163: Sparkling, lightly mineralled hydration | AD163: Electrolytes in a fizzy, zero sugar format. | AF163: =IF(AND(ISNUMBER($P163),ISNUMBER($AL163),$AL163<>0),ROUND($P163/$AL163*100,1),"") | AG163: =IF(AND(ISNUMBER($S163),ISNUMBER($AL163),$AL163<>0),ROUND($S163/$AL163*100,2),"") | AH163: =IF(AND(ISNUMBER($Q163),ISNUMBER($AL163),$AL163<>0),ROUND($Q163/$AL163*100,1),"") | AI163: =IF(ISNUMBER($S163),IF($S163<=1,"Yes","No"),"n/a") | AJ163: =IF(ISNUMBER($S163),ROUND(MAX(0,MIN(100,100-$S163*2.5-IF(ISNUMBER($T163),$T163,0)*0.12+IF($S163<=1,12,0))),0),"") | AK163: =IF(ISNUMBER($Q163),IF($Q163>=100,20,IF($Q163>=30,10,0)),0)+IF(ISNUMBER($R163),IF($R163>=100,20,0),0)+IF(ISNUMBER($P163),IF($P163>=150,20,IF($P163>=50,12,5)),0)+IF(ISNUMBER($S163),IF($S163<=1,15,0),0) | AL163: 355 | AN163: =IF(AND(ISNUMBER($P163),ISNUMBER($AL163),$AL163<>0),IF(OR($P163>180,$P163/$AL163*1000>400),"Over ceiling, confirm SKU","Within"),"n/a") | AR163: Recalled, batch confirmed, to confirm | AS163: BLANK -> requires live Amazon.ca capture | AT163: Unverified commercial data
A164: Halo Sport | B164: Halo Sport Sparkling Electrolyte Water | Berry | 24 pack 355mL | C164: 1) Sparkling electrolyte / functional sparkling | D164: 355 mL can | E164: 24 | G164: =IF(AND(ISNUMBER($F164),ISNUMBER($E164),$E164<>0),$F164/$E164,"") | H164: =IF(AND(ISNUMBER($F164),ISNUMBER($AL164),ISNUMBER($E164),($AL164*$E164)<>0),$F164/($AL164*$E164)*100,"") | K164: =IF(AND(ISNUMBER($F164),ISNUMBER($J164)),$F164*(1-$J164),"") | N164: =IF(ISNUMBER($F164),($F164-IF(ISNUMBER($AM164),$AM164,0))*(1-IF(ISNUMBER($J164),$J164,0)),"") | O164: Berry | P164: 0 | Q164: 110 | R164: 40 | S164: 0 | T164: 5 | U164: Stevia | V164: Sparkling electrolytes, zero sugar, light hydration | AA164: Low | AB164: Small emerging sparkling electrolyte entrant | AC164: Sparkling, lightly mineralled hydration | AD164: Electrolytes in a fizzy, zero sugar format. | AF164: =IF(AND(ISNUMBER($P164),ISNUMBER($AL164),$AL164<>0),ROUND($P164/$AL164*100,1),"") | AG164: =IF(AND(ISNUMBER($S164),ISNUMBER($AL164),$AL164<>0),ROUND($S164/$AL164*100,2),"") | AH164: =IF(AND(ISNUMBER($Q164),ISNUMBER($AL164),$AL164<>0),ROUND($Q164/$AL164*100,1),"") | AI164: =IF(ISNUMBER($S164),IF($S164<=1,"Yes","No"),"n/a") | AJ164: =IF(ISNUMBER($S164),ROUND(MAX(0,MIN(100,100-$S164*2.5-IF(ISNUMBER($T164),$T164,0)*0.12+IF($S164<=1,12,0))),0),"") | AK164: =IF(ISNUMBER($Q164),IF($Q164>=100,20,IF($Q164>=30,10,0)),0)+IF(ISNUMBER($R164),IF($R164>=100,20,0),0)+IF(ISNUMBER($P164),IF($P164>=150,20,IF($P164>=50,12,5)),0)+IF(ISNUMBER($S164),IF($S164<=1,15,0),0) | AL164: 355 | AN164: =IF(AND(ISNUMBER($P164),ISNUMBER($AL164),$AL164<>0),IF(OR($P164>180,$P164/$AL164*1000>400),"Over ceiling, confirm SKU","Within"),"n/a") | AR164: Recalled, batch confirmed, to confirm | AS164: BLANK -> requires live Amazon.ca capture | AT164: Unverified commercial data
... A176: Halo Sport | B176: Halo Sport Sparkling Electrolyte Water | Grapefruit | 24 pack 355mL | C176: 1) Sparkling electrolyte / functional sparkling | D176: 355 mL can | E176: 24 | G176: =IF(AND(ISNUMBER($F176),ISNUMBER($E176),$E176<>0),$F176/$E176,"") | H176: =IF(AND(ISNUMBER($F176),ISNUMBER($AL176),ISNUMBER($E176),($AL176*$E176)<>0),$F176/($AL176*$E176)*100,"") | K176: =IF(AND(ISNUMBER($F176),ISNUMBER($J176)),$F176*(1-$J176),"") | N176: =IF(ISNUMBER($F176),($F176-IF(ISNUMBER($AM176),$AM176,0))*(1-IF(ISNUMBER($J176),$J176,0)),"") | O176: Grapefruit | P176: 0 | Q176: 110 | R176: 40 | S176: 0 | T176: 5 | U176: Stevia | V176: Sparkling electrolytes, zero sugar, light hydration | AA176: Low | AB176: Small emerging sparkling electrolyte entrant | AC176: Sparkling, lightly mineralled hydration | AD176: Electrolytes in a fizzy, zero sugar format. | AF176: =IF(AND(ISNUMBER($P176),ISNUMBER($AL176),$AL176<>0),ROUND($P176/$AL176*100,1),"") | AG176: =IF(AND(ISNUMBER($S176),ISNUMBER($AL176),$AL176<>0),ROUND($S176/$AL176*100,2),"") | AH176: =IF(AND(ISNUMBER($Q176),ISNUMBER($AL176),$AL176<>0),ROUND($Q176/$AL176*100,1),"") | AI176: =IF(ISNUMBER($S176),IF($S176<=1,"Yes","No"),"n/a") | AJ176: =IF(ISNUMBER($S176),ROUND(MAX(0,MIN(100,100-$S176*2.5-IF(ISNUMBER($T176),$T176,0)*0.12+IF($S176<=1,12,0))),0),"") | AK176: =IF(ISNUMBER($Q176),IF($Q176>=100,20,IF($Q176>=30,10,0)),0)+IF(ISNUMBER($R176),IF($R176>=100,20,0),0)+IF(ISNUMBER($P176),IF($P176>=150,20,IF($P176>=50,12,5)),0)+IF(ISNUMBER($S176),IF($S176<=1,15,0),0) | AL176: 355 | AN176: =IF(AND(ISNUMBER($P176),ISNUMBER($AL176),$AL176<>0),IF(OR($P176>180,$P176/$AL176*1000>400),"Over ceiling, confirm SKU","Within"),"n/a") | AR176: Recalled, batch confirmed, to confirm | AS176: BLANK -> requires live Amazon.ca capture | AT176: Unverified commercial data
A177: Gorgie | B177: Gorgie Energy Sparkling Water | Watermelon | single 355mL | C177: 1) Sparkling electrolyte / functional sparkling | D177: 355 mL can | E177: 1 | G177: =IF(AND(ISNUMBER($F177),ISNUMBER($E177),$E177<>0),$F177/$E177,"") | H177: =IF(AND(ISNUMBER($F177),ISNUMBER($AL177),ISNUMBER($E177),($AL177*$E177)<>0),$F177/($AL177*$E177)*100,"") | K177: =IF(AND(ISNUMBER($F177),ISNUMBER($J177)),$F177*(1-$J177),"") | N177: =IF(ISNUMBER($F177),($F177-IF(ISNUMBER($AM177),$AM177,0))*(1-IF(ISNUMBER($J177),$J177,0)),"") | O177: Watermelon | P177: 120 | Q177: 10 | R177: Not listed | S177: 0 | T177: 10 | U177: Stevia | V177: 120 mg natural caffeine, L-theanine, biotin, zero sugar | AA177: Low | AB177: New social driven entrant; small footprint | AC177: A lighter, prettier caffeinated sparkling energy | AD177: Mid dose caffeine with a clean, lifestyle aesthetic. | AF177: =IF(AND(ISNUMBER($P177),ISNUMBER($AL177),$AL177<>0),ROUND($P177/$AL177*100,1),"") | AG177: =IF(AND(ISNUMBER($S177),ISNUMBER($AL177),$AL177<>0),ROUND($S177/$AL177*100,2),"") | AH177: =IF(AND(ISNUMBER($Q177),ISNUMBER($AL177),$AL177<>0),ROUND($Q177/$AL177*100,1),"") | AI177: =IF(ISNUMBER($S177),IF($S177<=1,"Yes","No"),"n/a") | AJ177: =IF(ISNUMBER($S177),ROUND(MAX(0,MIN(100,100-$S177*2.5-IF(ISNUMBER($T177),$T177,0)*0.12+IF($S177<=1,12,0))),0),"") | AK177: =IF(ISNUMBER($Q177),IF($Q177>=100,20,IF($Q177>=30,10,0)),0)+IF(ISNUMBER($R177),IF($R177>=100,20,0),0)+IF(ISNUMBER($P177),IF($P177>=150,20,IF($P177>=50,12,5)),0)+IF(ISNUMBER($S177),IF($S177<=1,15,0),0) | AL177: 355 | AN177: =IF(AND(ISNUMBER($P177),ISNUMBER($AL177),$AL177<>0),IF(OR($P177>180,$P177/$AL177*1000>400),"Over ceiling, confirm SKU","Within"),"n/a") | AR177: Recalled, batch confirmed, to confirm | AS177: BLANK -> requires live Amazon.ca capture | AT177: Unverified commercial data
A178: Gorgie | B178: Gorgie Energy Sparkling Water | Watermelon | 8 pack 355mL | C178: 1) Sparkling electrolyte / functional sparkling | D178: 355 mL can | E178: 8 | G178: =IF(AND(ISNUMBER($F178),ISNUMBER($E178),$E178<>0),$F178/$E178,"") | H178: =IF(AND(ISNUMBER($F178),ISNUMBER($AL178),ISNUMBER($E178),($AL178*$E178)<>0),$F178/($AL178*$E178)*100,"") | K178: =IF(AND(ISNUMBER($F178),ISNUMBER($J178)),$F178*(1-$J178),"") | N178: =IF(ISNUMBER($F178),($F178-IF(ISNUMBER($AM178),$AM178,0))*(1-IF(ISNUMBER($J178),$J178,0)),"") | O178: Watermelon | P178: 120 | Q178: 10 | R178: Not listed | S178: 0 | T178: 10 | U178: Stevia | V178: 120 mg natural caffeine, L-theanine, biotin, zero sugar | AA178: Low | AB178: New social driven entrant; small footprint | AC178: A lighter, prettier caffeinated sparkling energy | AD178: Mid dose caffeine with a clean, lifestyle aesthetic. | AF178: =IF(AND(ISNUMBER($P178),ISNUMBER($AL178),$AL178<>0),ROUND($P178/$AL178*100,1),"") | AG178: =IF(AND(ISNUMBER($S178),ISNUMBER($AL178),$AL178<>0),ROUND($S178/$AL178*100,2),"") | AH178: =IF(AND(ISNUMBER($Q178),ISNUMBER($AL178),$AL178<>0),ROUND($Q178/$AL178*100,1),"") | AI178: =IF(ISNUMBER($S178),IF($S178<=1,"Yes","No"),"n/a") | AJ178: =IF(ISNUMBER($S178),ROUND(MAX(0,MIN(100,100-$S178*2.5-IF(ISNUMBER($T178),$T178,0)*0.12+IF($S178<=1,12,0))),0),"") | AK178: =IF(ISNUMBER($Q178),IF($Q178>=100,20,IF($Q178>=30,10,0)),0)+IF(ISNUMBER($R178),IF($R178>=100,20,0),0)+IF(ISNUMBER($P178),IF($P178>=150,20,IF($P178>=50,12,5)),0)+IF(ISNUMBER($S178),IF($S178<=1,15,0),0) | AL178: 355 | AN178: =IF(AND(ISNUMBER($P178),ISNUMBER($AL178),$AL178<>0),IF(OR($P178>180,$P178/$AL178*1000>400),"Over ceiling, confirm SKU","Within"),"n/a") | AR178: Recalled, batch confirmed, to confirm | AS178: BLANK -> requires live Amazon.ca capture | AT178: Unverified commercial data
A179: Gorgie | B179: Gorgie Energy Sparkling Water | Watermelon | 12 pack 355mL | C179: 1) Sparkling electrolyte / functional sparkling | D179: 355 mL can | E179: 12 | G179: =IF(AND(ISNUMBER($F179),ISNUMBER($E179),$E179<>0),$F179/$E179,"") | H179: =IF(AND(ISNUMBER($F179),ISNUMBER($AL179),ISNUMBER($E179),($AL179*$E179)<>0),$F179/($AL179*$E179)*100,"") | K179: =IF(AND(ISNUMBER($F179),ISNUMBER($J179)),$F179*(1-$J179),"") | N179: =IF(ISNUMBER($F179),($F179-IF(ISNUMBER($AM179),$AM179,0))*(1-IF(ISNUMBER($J179),$J179,0)),"") | O179: Watermelon | P179: 120 | Q179: 10 | R179: Not listed | S179: 0 | T179: 10 | U179: Stevia | V179: 120 mg natural caffeine, L-theanine, biotin, zero sugar | AA179: Low | AB179: New social driven entrant; small footprint | AC179: A lighter, prettier caffeinated sparkling energy | AD179: Mid dose caffeine with a clean, lifestyle aesthetic. | AF179: =IF(AND(ISNUMBER($P179),ISNUMBER($AL179),$AL179<>0),ROUND($P179/$AL179*100,1),"") | AG179: =IF(AND(ISNUMBER($S179),ISNUMBER($AL179),$AL179<>0),ROUND($S179/$AL179*100,2),"") | AH179: =IF(AND(ISNUMBER($Q179),ISNUMBER($AL179),$AL179<>0),ROUND($Q179/$AL179*100,1),"") | AI179: =IF(ISNUMBER($S179),IF($S179<=1,"Yes","No"),"n/a") | AJ179: =IF(ISNUMBER($S179),ROUND(MAX(0,MIN(100,100-$S179*2.5-IF(ISNUMBER($T179),$T179,0)*0.12+IF($S179<=1,12,0))),0),"") | AK179: =IF(ISNUMBER($Q179),IF($Q179>=100,20,IF($Q179>=30,10,0)),0)+IF(ISNUMBER($R179),IF($R179>=100,20,0),0)+IF(ISNUMBER($P179),IF($P179>=150,20,IF($P179>=50,12,5)),0)+IF(ISNUMBER($S179),IF($S179<=1,15,0),0) | AL179: 355 | AN179: =IF(AND(ISNUMBER($P179),ISNUMBER($AL179),$AL179<>0),IF(OR($P179>180,$P179/$AL179*1000>400),"Over ceiling, confirm SKU","Within"),"n/a") | AR179: Recalled, batch confirmed, to confirm | AS179: BLANK -> requires live Amazon.ca capture | AT179: Unverified commercial data
A180: Gorgie | B180: Gorgie Energy Sparkling Water | Watermelon | 15 pack 355mL | C180: 1) Sparkling electrolyte / functional sparkling | D180: 355 mL can | E180: 15 | G180: =IF(AND(ISNUMBER($F180),ISNUMBER($E180),$E180<>0),$F180/$E180,"") | H180: =IF(AND(ISNUMBER($F180),ISNUMBER($AL180),ISNUMBER($E180),($AL180*$E180)<>0),$F180/($AL180*$E180)*100,"") | K180: =IF(AND(ISNUMBER($F180),ISNUMBER($J180)),$F180*(1-$J180),"") | N180: =IF(ISNUMBER($F180),($F180-IF(ISNUMBER($AM180),$AM180,0))*(1-IF(ISNUMBER($J180),$J180,0)),"") | O180: Watermelon | P180: 120 | Q180: 10 | R180: Not listed | S180: 0 | T180: 10 | U180: Stevia | V180: 120 mg natural caffeine, L-theanine, biotin, zero sugar | AA180: Low | AB180: New social driven entrant; small footprint | AC180: A lighter, prettier caffeinated sparkling energy | AD180: Mid dose caffeine with a clean, lifestyle aesthetic. | AF180: =IF(AND(ISNUMBER($P180),ISNUMBER($AL180),$AL180<>0),ROUND($P180/$AL180*100,1),"") | AG180: =IF(AND(ISNUMBER($S180),ISNUMBER($AL180),$AL180<>0),ROUND($S180/$AL180*100,2),"") | AH180: =IF(AND(ISNUMBER($Q180),ISNUMBER($AL180),$AL180<>0),ROUND($Q180/$AL180*100,1),"") | AI180: =IF(ISNUMBER($S180),IF($S180<=1,"Yes","No"),"n/a") | AJ180: =IF(ISNUMBER($S180),ROUND(MAX(0,MIN(100,100-$S180*2.5-IF(ISNUMBER($T180),$T180,0)*0.12+IF($S180<=1,12,0))),0),"") | AK180: =IF(ISNUMBER($Q180),IF($Q180>=100,20,IF($Q180>=30,10,0)),0)+IF(ISNUMBER($R180),IF($R180>=100,20,0),0)+IF(ISNUMBER($P180),IF($P180>=150,20,IF($P180>=50,12,5)),0)+IF(ISNUMBER($S180),IF($S180<=1,15,0),0) | AL180: 355 | AN180: =IF(AND(ISNUMBER($P180),ISNUMBER($AL180),$AL180<>0),IF(OR($P180>180,$P180/$AL180*1000>400),"Over ceiling, confirm SKU","Within"),"n/a") | AR180: Recalled, batch confirmed, to confirm | AS180: BLANK -> requires live Amazon.ca capture | AT180: Unverified commercial data
A181: Gorgie | B181: Gorgie Energy Sparkling Water | Watermelon | 18 pack 355mL | C181: 1) Sparkling electrolyte / functional sparkling | D181: 355 mL can | E181: 18 | G181: =IF(AND(ISNUMBER($F181),ISNUMBER($E181),$E181<>0),$F181/$E181,"") | H181: =IF(AND(ISNUMBER($F181),ISNUMBER($AL181),ISNUMBER($E181),($AL181*$E181)<>0),$F181/($AL181*$E181)*100,"") | K181: =IF(AND(ISNUMBER($F181),ISNUMBER($J181)),$F181*(1-$J181),"") | N181: =IF(ISNUMBER($F181),($F181-IF(ISNUMBER($AM181),$AM181,0))*(1-IF(ISNUMBER($J181),$J181,0)),"") | O181: Watermelon | P181: 120 | Q181: 10 | R181: Not listed | S181: 0 | T181: 10 | U181: Stevia | V181: 120 mg natural caffeine, L-theanine, biotin, zero sugar | AA181: Low | AB181: New social driven entrant; small footprint | AC181: A lighter, prettier caffeinated sparkling energy | AD181: Mid dose caffeine with a clean, lifestyle aesthetic. | AF181: =IF(AND(ISNUMBER($P181),ISNUMBER($AL181),$AL181<>0),ROUND($P181/$AL181*100,1),"") | AG181: =IF(AND(ISNUMBER($S181),ISNUMBER($AL181),$AL181<>0),ROUND($S181/$AL181*100,2),"") | AH181: =IF(AND(ISNUMBER($Q181),ISNUMBER($AL181),$AL181<>0),ROUND($Q181/$AL181*100,1),"") | AI181: =IF(ISNUMBER($S181),IF($S181<=1,"Yes","No"),"n/a") | AJ181: =IF(ISNUMBER($S181),ROUND(MAX(0,MIN(100,100-$S181*2.5-IF(ISNUMBER($T181),$T181,0)*0.12+IF($S181<=1,12,0))),0),"") | AK181: =IF(ISNUMBER($Q181),IF($Q181>=100,20,IF($Q181>=30,10,0)),0)+IF(ISNUMBER($R181),IF($R181>=100,20,0),0)+IF(ISNUMBER($P181),IF($P181>=150,20,IF($P181>=50,12,5)),0)+IF(ISNUMBER($S181),IF($S181<=1,15,0),0) | AL181: 355 | AN181: =IF(AND(ISNUMBER($P181),ISNUMBER($AL181),$AL181<>0),IF(OR($P181>180,$P181/$AL181*1000>400),"Over ceiling, confirm SKU","Within"),"n/a") | AR181: Recalled, batch confirmed, to confirm | AS181: BLANK -> requires live Amazon.ca capture | AT181: Unverified commercial data
A182: Gorgie | B182: Gorgie Energy Sparkling Water | Watermelon | 24 pack 355mL | C182: 1) Sparkling electrolyte / functional sparkling | D182: 355 mL can | E182: 24 | G182: =IF(AND(ISNUMBER($F182),ISNUMBER($E182),$E182<>0),$F182/$E182,"") | H182: =IF(AND(ISNUMBER($F182),ISNUMBER($AL182),ISNUMBER($E182),($AL182*$E182)<>0),$F182/($AL182*$E182)*100,"") | K182: =IF(AND(ISNUMBER($F182),ISNUMBER($J182)),$F182*(1-$J182),"") | N182: =IF(ISNUMBER($F182),($F182-IF(ISNUMBER($AM182),$AM182,0))*(1-IF(ISNUMBER($J182),$J182,0)),"") | O182: Watermelon | P182: 120 | Q182: 10 | R182: Not listed | S182: 0 | T182: 10 | U182: Stevia | V182: 120 mg natural caffeine, L-theanine, biotin, zero sugar | AA182: Low | AB182: New social driven entrant; small footprint | AC182: A lighter, prettier caffeinated sparkling energy | AD182: Mid dose caffeine with a clean, lifestyle aesthetic. | AF182: =IF(AND(ISNUMBER($P182),ISNUMBER($AL182),$AL182<>0),ROUND($P182/$AL182*100,1),"") | AG182: =IF(AND(ISNUMBER($S182),ISNUMBER($AL182),$AL182<>0),ROUND($S182/$AL182*100,2),"") | AH182: =IF(AND(ISNUMBER($Q182),ISNUMBER($AL182),$AL182<>0),ROUND($Q182/$AL182*100,1),"") | AI182: =IF(ISNUMBER($S182),IF($S182<=1,"Yes","No"),"n/a") | AJ182: =IF(ISNUMBER($S182),ROUND(MAX(0,MIN(100,100-$S182*2.5-IF(ISNUMBER($T182),$T182,0)*0.12+IF($S182<=1,12,0))),0),"") | AK182: =IF(ISNUMBER($Q182),IF($Q182>=100,20,IF($Q182>=30,10,0)),0)+IF(ISNUMBER($R182),IF($R182>=100,20,0),0)+IF(ISNUMBER($P182),IF($P182>=150,20,IF($P182>=50,12,5)),0)+IF(ISNUMBER($S182),IF($S182<=1,15,0),0) | AL182: 355 | AN182: =IF(AND(ISNUMBER($P182),ISNUMBER($AL182),$AL182<>0),IF(OR($P182>180,$P182/$AL182*1000>400),"Over ceiling, confirm SKU","Within"),"n/a") | AR182: Recalled, batch confirmed, to confirm | AS182: BLANK -> requires live Amazon.ca capture | AT182: Unverified commercial data
A183: Gorgie | B183: Gorgie Energy Sparkling Water | Tropical | single 355mL | C183: 1) Sparkling electrolyte / functional sparkling | D183: 355 mL can | E183: 1 | G183: =IF(AND(ISNUMBER($F183),ISNUMBER($E183),$E183<>0),$F183/$E183,"") | H183: =IF(AND(ISNUMBER($F183),ISNUMBER($AL183),ISNUMBER($E183),($AL183*$E183)<>0),$F183/($AL183*$E183)*100,"") | K183: =IF(AND(ISNUMBER($F183),ISNUMBER($J183)),$F183*(1-$J183),"") | N183: =IF(ISNUMBER($F183),($F183-IF(ISNUMBER($AM183),$AM183,0))*(1-IF(ISNUMBER($J183),$J183,0)),"") | O183: Tropical | P183: 120 | Q183: 10 | R183: Not listed | S183: 0 | T183: 10 | U183: Stevia | V183: 120 mg natural caffeine, L-theanine, biotin, zero sugar | AA183: Low | AB183: New social driven entrant; small footprint | AC183: A lighter, prettier caffeinated sparkling energy | AD183: Mid dose caffeine with a clean, lifestyle aesthetic. | AF183: =IF(AND(ISNUMBER($P183),ISNUMBER($AL183),$AL183<>0),ROUND($P183/$AL183*100,1),"") | AG183: =IF(AND(ISNUMBER($S183),ISNUMBER($AL183),$AL183<>0),ROUND($S183/$AL183*100,2),"") | AH183: =IF(AND(ISNUMBER($Q183),ISNUMBER($AL183),$AL183<>0),ROUND($Q183/$AL183*100,1),"") | AI183: =IF(ISNUMBER($S183),IF($S183<=1,"Yes","No"),"n/a") | AJ183: =IF(ISNUMBER($S183),ROUND(MAX(0,MIN(100,100-$S183*2.5-IF(ISNUMBER($T183),$T183,0)*0.12+IF($S183<=1,12,0))),0),"") | AK183: =IF(ISNUMBER($Q183),IF($Q183>=100,20,IF($Q183>=30,10,0)),0)+IF(ISNUMBER($R183),IF($R183>=100,20,0),0)+IF(ISNUMBER($P183),IF($P183>=150,20,IF($P183>=50,12,5)),0)+IF(ISNUMBER($S183),IF($S183<=1,15,0),0) | AL183: 355 | AN183: =IF(AND(ISNUMBER($P183),ISNUMBER($AL183),$AL183<>0),IF(OR($P183>180,$P183/$AL183*1000>400),"Over ceiling, confirm SKU","Within"),"n/a") | AR183: Recalled, batch confirmed, to confirm | AS183: BLANK -> requires live Amazon.ca capture | AT183: Unverified commercial data
A184: Gorgie | B184: Gorgie Energy Sparkling Water | Tropical | 8 pack 355mL | C184: 1) Sparkling electrolyte / functional sparkling | D184: 355 mL can | E184: 8 | G184: =IF(AND(ISNUMBER($F184),ISNUMBER($E184),$E184<>0),$F184/$E184,"") | H184: =IF(AND(ISNUMBER($F184),ISNUMBER($AL184),ISNUMBER($E184),($AL184*$E184)<>0),$F184/($AL184*$E184)*100,"") | K184: =IF(AND(ISNUMBER($F184),ISNUMBER($J184)),$F184*(1-$J184),"") | N184: =IF(ISNUMBER($F184),($F184-IF(ISNUMBER($AM184),$AM184,0))*(1-IF(ISNUMBER($J184),$J184,0)),"") | O184: Tropical | P184: 120 | Q184: 10 | R184: Not listed | S184: 0 | T184: 10 | U184: Stevia | V184: 120 mg natural caffeine, L-theanine, biotin, zero sugar | AA184: Low | AB184: New social driven entrant; small footprint | AC184: A lighter, prettier caffeinated sparkling energy | AD184: Mid dose caffeine with a clean, lifestyle aesthetic. | AF184: =IF(AND(ISNUMBER($P184),ISNUMBER($AL184),$AL184<>0),ROUND($P184/$AL184*100,1),"") | AG184: =IF(AND(ISNUMBER($S184),ISNUMBER($AL184),$AL184<>0),ROUND($S184/$AL184*100,2),"") | AH184: =IF(AND(ISNUMBER($Q184),ISNUMBER($AL184),$AL184<>0),ROUND($Q184/$AL184*100,1),"") | AI184: =IF(ISNUMBER($S184),IF($S184<=1,"Yes","No"),"n/a") | AJ184: =IF(ISNUMBER($S184),ROUND(MAX(0,MIN(100,100-$S184*2.5-IF(ISNUMBER($T184),$T184,0)*0.12+IF($S184<=1,12,0))),0),"") | AK184: =IF(ISNUMBER($Q184),IF($Q184>=100,20,IF($Q184>=30,10,0)),0)+IF(ISNUMBER($R184),IF($R184>=100,20,0),0)+IF(ISNUMBER($P184),IF($P184>=150,20,IF($P184>=50,12,5)),0)+IF(ISNUMBER($S184),IF($S184<=1,15,0),0) | AL184: 355 | AN184: =IF(AND(ISNUMBER($P184),ISNUMBER($AL184),$AL184<>0),IF(OR($P184>180,$P184/$AL184*1000>400),"Over ceiling, confirm SKU","Within"),"n/a") | AR184: Recalled, batch confirmed, to confirm | AS184: BLANK -> requires live Amazon.ca capture | AT184: Unverified commercial data
A185: Gorgie | B185: Gorgie Energy Sparkling Water | Tropical | 12 pack 355mL | C185: 1) Sparkling electrolyte / functional sparkling | D185: 355 mL can | E185: 12 | G185: =IF(AND(ISNUMBER($F185),ISNUMBER($E185),$E185<>0),$F185/$E185,"") | H185: =IF(AND(ISNUMBER($F185),ISNUMBER($AL185),ISNUMBER($E185),($AL185*$E185)<>0),$F185/($AL185*$E185)*100,"") | K185: =IF(AND(ISNUMBER($F185),ISNUMBER($J185)),$F185*(1-$J185),"") | N185: =IF(ISNUMBER($F185),($F185-IF(ISNUMBER($AM185),$AM185,0))*(1-IF(ISNUMBER($J185),$J185,0)),"") | O185: Tropical | P185: 120 | Q185: 10 | R185: Not listed | S185: 0 | T185: 10 | U185: Stevia | V185: 120 mg natural caffeine, L-theanine, biotin, zero sugar | AA185: Low | AB185: New social driven entrant; small footprint | AC185: A lighter, prettier caffeinated sparkling energy | AD185: Mid dose caffeine with a clean, lifestyle aesthetic. | AF185: =IF(AND(ISNUMBER($P185),ISNUMBER($AL185),$AL185<>0),ROUND($P185/$AL185*100,1),"") | AG185: =IF(AND(ISNUMBER($S185),ISNUMBER($AL185),$AL185<>0),ROUND($S185/$AL185*100,2),"") | AH185: =IF(AND(ISNUMBER($Q185),ISNUMBER($AL185),$AL185<>0),ROUND($Q185/$AL185*100,1),"") | AI185: =IF(ISNUMBER($S185),IF($S185<=1,"Yes","No"),"n/a") | AJ185: =IF(ISNUMBER($S185),ROUND(MAX(0,MIN(100,100-$S185*2.5-IF(ISNUMBER($T185),$T185,0)*0.12+IF($S185<=1,12,0))),0),"") | AK185: =IF(ISNUMBER($Q185),IF($Q185>=100,20,IF($Q185>=30,10,0)),0)+IF(ISNUMBER($R185),IF($R185>=100,20,0),0)+IF(ISNUMBER($P185),IF($P185>=150,20,IF($P185>=50,12,5)),0)+IF(ISNUMBER($S185),IF($S185<=1,15,0),0) | AL185: 355 | AN185: =IF(AND(ISNUMBER($P185),ISNUMBER($AL185),$AL185<>0),IF(OR($P185>180,$P185/$AL185*1000>400),"Over ceiling, confirm SKU","Within"),"n/a") | AR185: Recalled, batch confirmed, to confirm | AS185: BLANK -> requires live Amazon.ca capture | AT185: Unverified commercial data
A186: Gorgie | B186: Gorgie Energy Sparkling Water | Tropical | 15 pack 355mL | C186: 1) Sparkling electrolyte / functional sparkling | D186: 355 mL can | E186: 15 | G186: =IF(AND(ISNUMBER($F186),ISNUMBER($E186),$E186<>0),$F186/$E186,"") | H186: =IF(AND(ISNUMBER($F186),ISNUMBER($AL186),ISNUMBER($E186),($AL186*$E186)<>0),$F186/($AL186*$E186)*100,"") | K186: =IF(AND(ISNUMBER($F186),ISNUMBER($J186)),$F186*(1-$J186),"") | N186: =IF(ISNUMBER($F186),($F186-IF(ISNUMBER($AM186),$AM186,0))*(1-IF(ISNUMBER($J186),$J186,0)),"") | O186: Tropical | P186: 120 | Q186: 10 | R186: Not listed | S186: 0 | T186: 10 | U186: Stevia | V186: 120 mg natural caffeine, L-theanine, biotin, zero sugar | AA186: Low | AB186: New social driven entrant; small footprint | AC186: A lighter, prettier caffeinated sparkling energy | AD186: Mid dose caffeine with a clean, lifestyle aesthetic. | AF186: =IF(AND(ISNUMBER($P186),ISNUMBER($AL186),$AL186<>0),ROUND($P186/$AL186*100,1),"") | AG186: =IF(AND(ISNUMBER($S186),ISNUMBER($AL186),$AL186<>0),ROUND($S186/$AL186*100,2),"") | AH186: =IF(AND(ISNUMBER($Q186),ISNUMBER($AL186),$AL186<>0),ROUND($Q186/$AL186*100,1),"") | AI186: =IF(ISNUMBER($S186),IF($S186<=1,"Yes","No"),"n/a") | AJ186: =IF(ISNUMBER($S186),ROUND(MAX(0,MIN(100,100-$S186*2.5-IF(ISNUMBER($T186),$T186,0)*0.12+IF($S186<=1,12,0))),0),"") | AK186: =IF(ISNUMBER($Q186),IF($Q186>=100,20,IF($Q186>=30,10,0)),0)+IF(ISNUMBER($R186),IF($R186>=100,20,0),0)+IF(ISNUMBER($P186),IF($P186>=150,20,IF($P186>=50,12,5)),0)+IF(ISNUMBER($S186),IF($S186<=1,15,0),0) | AL186: 355 | AN186: =IF(AND(ISNUMBER($P186),ISNUMBER($AL186),$AL186<>0),IF(OR($P186>180,$P186/$AL186*1000>400),"Over ceiling, confirm SKU","Within"),"n/a") | AR186: Recalled, batch confirmed, to confirm | AS186: BLANK -> requires live Amazon.ca capture | AT186: Unverified commercial data
A187: Gorgie | B187: Gorgie Energy Sparkling Water | Tropical | 18 pack 355mL | C187: 1) Sparkling electrolyte / functional sparkling | D187: 355 mL can | E187: 18 | G187: =IF(AND(ISNUMBER($F187),ISNUMBER($E187),$E187<>0),$F187/$E187,"") | H187: =IF(AND(ISNUMBER($F187),ISNUMBER($AL187),ISNUMBER($E187),($AL187*$E187)<>0),$F187/($AL187*$E187)*100,"") | K187: =IF(AND(ISNUMBER($F187),ISNUMBER($J187)),$F187*(1-$J187),"") | N187: =IF(ISNUMBER($F187),($F187-IF(ISNUMBER($AM187),$AM187,0))*(1-IF(ISNUMBER($J187),$J187,0)),"") | O187: Tropical | P187: 120 | Q187: 10 | R187: Not listed | S187: 0 | T187: 10 | U187: Stevia | V187: 120 mg natural caffeine, L-theanine, biotin, zero sugar | AA187: Low | AB187: New social driven entrant; small footprint | AC187: A lighter, prettier caffeinated sparkling energy | AD187: Mid dose caffeine with a clean, lifestyle aesthetic. | AF187: =IF(AND(ISNUMBER($P187),ISNUMBER($AL187),$AL187<>0),ROUND($P187/$AL187*100,1),"") | AG187: =IF(AND(ISNUMBER($S187),ISNUMBER($AL187),$AL187<>0),ROUND($S187/$AL187*100,2),"") | AH187: =IF(AND(ISNUMBER($Q187),ISNUMBER($AL187),$AL187<>0),ROUND($Q187/$AL187*100,1),"") | AI187: =IF(ISNUMBER($S187),IF($S187<=1,"Yes","No"),"n/a") | AJ187: =IF(ISNUMBER($S187),ROUND(MAX(0,MIN(100,100-$S187*2.5-IF(ISNUMBER($T187),$T187,0)*0.12+IF($S187<=1,12,0))),0),"") | AK187: =IF(ISNUMBER($Q187),IF($Q187>=100,20,IF($Q187>=30,10,0)),0)+IF(ISNUMBER($R187),IF($R187>=100,20,0),0)+IF(ISNUMBER($P187),IF($P187>=150,20,IF($P187>=50,12,5)),0)+IF(ISNUMBER($S187),IF($S187<=1,15,0),0) | AL187: 355 | AN187: =IF(AND(ISNUMBER($P187),ISNUMBER($AL187),$AL187<>0),IF(OR($P187>180,$P187/$AL187*1000>400),"Over ceiling, confirm SKU","Within"),"n/a") | AR187: Recalled, batch confirmed, to confirm | AS187: BLANK -> requires live Amazon.ca capture | AT187: Unverified commercial data
A188: Gorgie | B188: Gorgie Energy Sparkling Water | Tropical | 24 pack 355mL | C188: 1) Sparkling electrolyte / functional sparkling | D188: 355 mL can | E188: 24 | G188: =IF(AND(ISNUMBER($F188),ISNUMBER($E188),$E188<>0),$F188/$E188,"") | H188: =IF(AND(ISNUMBER($F188),ISNUMBER($AL188),ISNUMBER($E188),($AL188*$E188)<>0),$F188/($AL188*$E188)*100,"") | K188: =IF(AND(ISNUMBER($F188),ISNUMBER($J188)),$F188*(1-$J188),"") | N188: =IF(ISNUMBER($F188),($F188-IF(ISNUMBER($AM188),$AM188,0))*(1-IF(ISNUMBER($J188),$J188,0)),"") | O188: Tropical | P188: 120 | Q188: 10 | R188: Not listed | S188: 0 | T188: 10 | U188: Stevia | V188: 120 mg natural caffeine, L-theanine, biotin, zero sugar | AA188: Low | AB188: New social driven entrant; small footprint | AC188: A lighter, prettier caffeinated sparkling energy | AD188: Mid dose caffeine with a clean, lifestyle aesthetic. | AF188: =IF(AND(ISNUMBER($P188),ISNUMBER($AL188),$AL188<>0),ROUND($P188/$AL188*100,1),"") | AG188: =IF(AND(ISNUMBER($S188),ISNUMBER($AL188),$AL188<>0),ROUND($S188/$AL188*100,2),"") | AH188: =IF(AND(ISNUMBER($Q188),ISNUMBER($AL188),$AL188<>0),ROUND($Q188/$AL188*100,1),"") | AI188: =IF(ISNUMBER($S188),IF($S188<=1,"Yes","No"),"n/a") | AJ188: =IF(ISNUMBER($S188),ROUND(MAX(0,MIN(100,100-$S188*2.5-IF(ISNUMBER($T188),$T188,0)*0.12+IF($S188<=1,12,0))),0),"") | AK188: =IF(ISNUMBER($Q188),IF($Q188>=100,20,IF($Q188>=30,10,0)),0)+IF(ISNUMBER($R188),IF($R188>=100,20,0),0)+IF(ISNUMBER($P188),IF($P188>=150,20,IF($P188>=50,12,5)),0)+IF(ISNUMBER($S188),IF($S188<=1,15,0),0) | AL188: 355 | AN188: =IF(AND(ISNUMBER($P188),ISNUMBER($AL188),$AL188<>0),IF(OR($P188>180,$P188/$AL188*1000>400),"Over ceiling, confirm SKU","Within"),"n/a") | AR188: Recalled, batch confirmed, to confirm | AS188: BLANK -> requires live Amazon.ca capture | AT188: Unverified commercial data
... A255: Sparkling Ice | B255: Sparkling Ice +Caffeine | Triple Citrus | 24 pack 473mL | C255: 1) Sparkling electrolyte / functional sparkling | D255: 473 mL can | E255: 24 | G255: =IF(AND(ISNUMBER($F255),ISNUMBER($E255),$E255<>0),$F255/$E255,"") | H255: =IF(AND(ISNUMBER($F255),ISNUMBER($AL255),ISNUMBER($E255),($AL255*$E255)<>0),$F255/($AL255*$E255)*100,"") | K255: =IF(AND(ISNUMBER($F255),ISNUMBER($J255)),$F255*(1-$J255),"") | N255: =IF(ISNUMBER($F255),($F255-IF(ISNUMBER($AM255),$AM255,0))*(1-IF(ISNUMBER($J255),$J255,0)),"") | O255: Triple Citrus | P255: 70 | Q255: 25 | R255: Not listed | S255: 0 | T255: 5 | U255: Sucralose | V255: 70 mg caffeine, vitamins, antioxidants, zero sugar | AA255: Medium | AB255: Caffeinated line of mass sparkling brand | AC255: Zero sugar sparkling with a caffeine boost | AD255: Light caffeine plus vitamins, zero sugar. | AF255: =IF(AND(ISNUMBER($P255),ISNUMBER($AL255),$AL255<>0),ROUND($P255/$AL255*100,1),"") | AG255: =IF(AND(ISNUMBER($S255),ISNUMBER($AL255),$AL255<>0),ROUND($S255/$AL255*100,2),"") | AH255: =IF(AND(ISNUMBER($Q255),ISNUMBER($AL255),$AL255<>0),ROUND($Q255/$AL255*100,1),"") | AI255: =IF(ISNUMBER($S255),IF($S255<=1,"Yes","No"),"n/a") | AJ255: =IF(ISNUMBER($S255),ROUND(MAX(0,MIN(100,100-$S255*2.5-IF(ISNUMBER($T255),$T255,0)*0.12+IF($S255<=1,12,0))),0),"") | AK255: =IF(ISNUMBER($Q255),IF($Q255>=100,20,IF($Q255>=30,10,0)),0)+IF(ISNUMBER($R255),IF($R255>=100,20,0),0)+IF(ISNUMBER($P255),IF($P255>=150,20,IF($P255>=50,12,5)),0)+IF(ISNUMBER($S255),IF($S255<=1,15,0),0) | AL255: 473 | AN255: =IF(AND(ISNUMBER($P255),ISNUMBER($AL255),$AL255<>0),IF(OR($P255>180,$P255/$AL255*1000>400),"Over ceiling, confirm SKU","Within"),"n/a") | AR255: Retrieved and cited, see Enrichment Log | AS255: BLANK -> requires live Amazon.ca capture | AT255: Unverified commercial data

Sheet M2 Electrolyte RTD
A1: 1. Brand | B1: 2. Product Line / SKU Name | C1: 3. Category | D1: 4. Format & Size | E1: 5. Pack Count | F1: 6. One Time Price (CAD) | G1: 7. Price / Unit (CAD) | H1: 8. Price / 100 mL (CAD) | I1: 9. S&S Offered (Y/N) | J1: 10. S&S Discount % | K1: 11. S&S Price After Disc. | L1: 12. Coupon on Listing (Y/N + value) | M1: 13. Promotion Text | N1: 14. Lowest Effective Price (stacked) | O1: 15. All Flavours in Listing | P1: 16. Caffeine / Serving (mg) | Q1: 17. Sodium / Serving (mg) | R1: 18. Potassium / Serving (mg) | S1: 19. Sugar / Serving (g) | T1: 20. Calories / Serving | U1: 21. Sweetener Type | V1: 22. Key Functional Claims | W1: 23. Star Rating | X1: 24. Number of Ratings | Y1: 25. Amazon Badge | Z1: 26. Bestseller Rank in Category | AA1: 27a. Est. Weekly Velocity (band) | AB1: 27b. Velocity Signal Used | AC1: 28. Biggest Selling Message | AD1: 29. Why a Shopper Chooses This | AE1: 30. Direct Product URL | AF1: C1. Caffeine /100 mL (mg) | AG1: C2. Sugar /100 mL (g) | AH1: C3. Sodium /100 mL (mg) | AI1: C4. Sugar Free? (<=1 g) | AJ1: C5. Health Score (0 to 100) | AK1: C6. Functional Score (0 to 100) | AL1: H1. Unit Vol (mL) [calc helper] | AM1: H2. Coupon Value (CAD) [calc helper] | AN1: C7. Over Health Canada caffeine ceiling (180 mg per container or 400 mg per litre)? | AO1: 31. Supplemented Food Facts table (Y/N) | AP1: 32. Caution Identifier (Y/N/not required) | AQ1: 33. Bilingual EN and FR panel (Y/N) | AR1: P1. Attribute Provenance | AS1: P2. Commercial Field Status | AT1: P3. Row Flag
A2: Gatorade | B2: Gatorade Thirst Quencher | Cool Blue | single 591mL | C2: 2) Electrolyte beverage (RTD) | D2: 591 mL bottle | E2: 1 | G2: =IF(AND(ISNUMBER($F2),ISNUMBER($E2),$E2<>0),$F2/$E2,"") | H2: =IF(AND(ISNUMBER($F2),ISNUMBER($AL2),ISNUMBER($E2),($AL2*$E2)<>0),$F2/($AL2*$E2)*100,"") | K2: =IF(AND(ISNUMBER($F2),ISNUMBER($J2)),$F2*(1-$J2),"") | N2: =IF(ISNUMBER($F2),($F2-IF(ISNUMBER($AM2),$AM2,0))*(1-IF(ISNUMBER($J2),$J2,0)),"") | O2: Cool Blue | P2: 0 | Q2: 270 | R2: 75 | S2: 34 | T2: 140 | U2: Sugar + dextrose | V2: Rehydrate, replenish electrolytes, sports performance | AA2: Very High | AB2: Category defining sports drink; mass repeat purchase | AC2: The original sports hydration standard | AD2: Sodium led rehydration with unmatched brand trust. | AF2: =IF(AND(ISNUMBER($P2),ISNUMBER($AL2),$AL2<>0),ROUND($P2/$AL2*100,1),"") | AG2: =IF(AND(ISNUMBER($S2),ISNUMBER($AL2),$AL2<>0),ROUND($S2/$AL2*100,2),"") | AH2: =IF(AND(ISNUMBER($Q2),ISNUMBER($AL2),$AL2<>0),ROUND($Q2/$AL2*100,1),"") | AI2: =IF(ISNUMBER($S2),IF($S2<=1,"Yes","No"),"n/a") | AJ2: =IF(ISNUMBER($S2),ROUND(MAX(0,MIN(100,100-$S2*2.5-IF(ISNUMBER($T2),$T2,0)*0.12+IF($S2<=1,12,0))),0),"") | AK2: =IF(ISNUMBER($Q2),IF($Q2>=100,20,IF($Q2>=30,10,0)),0)+IF(ISNUMBER($R2),IF($R2>=100,20,0),0)+IF(ISNUMBER($P2),IF($P2>=150,20,IF($P2>=50,12,5)),0)+IF(ISNUMBER($S2),IF($S2<=1,15,0),0) | AL2: 591 | AN2: =IF(AND(ISNUMBER($P2),ISNUMBER($AL2),$AL2<>0),IF(OR($P2>180,$P2/$AL2*1000>400),"Over ceiling, confirm SKU","Within"),"n/a") | AR2: Retrieved and cited, see Enrichment Log | AS2: BLANK -> requires live Amazon.ca capture | AT2: Unverified commercial data
A3: Gatorade | B3: Gatorade Thirst Quencher | Cool Blue | 6 pack 591mL | C3: 2) Electrolyte beverage (RTD) | D3: 591 mL bottle | E3: 6 | G3: =IF(AND(ISNUMBER($F3),ISNUMBER($E3),$E3<>0),$F3/$E3,"") | H3: =IF(AND(ISNUMBER($F3),ISNUMBER($AL3),ISNUMBER($E3),($AL3*$E3)<>0),$F3/($AL3*$E3)*100,"") | K3: =IF(AND(ISNUMBER($F3),ISNUMBER($J3)),$F3*(1-$J3),"") | N3: =IF(ISNUMBER($F3),($F3-IF(ISNUMBER($AM3),$AM3,0))*(1-IF(ISNUMBER($J3),$J3,0)),"") | O3: Cool Blue | P3: 0 | Q3: 270 | R3: 75 | S3: 34 | T3: 140 | U3: Sugar + dextrose | V3: Rehydrate, replenish electrolytes, sports performance | AA3: Very High | AB3: Category defining sports drink; mass repeat purchase | AC3: The original sports hydration standard | AD3: Sodium led rehydration with unmatched brand trust. | AF3: =IF(AND(ISNUMBER($P3),ISNUMBER($AL3),$AL3<>0),ROUND($P3/$AL3*100,1),"") | AG3: =IF(AND(ISNUMBER($S3),ISNUMBER($AL3),$AL3<>0),ROUND($S3/$AL3*100,2),"") | AH3: =IF(AND(ISNUMBER($Q3),ISNUMBER($AL3),$AL3<>0),ROUND($Q3/$AL3*100,1),"") | AI3: =IF(ISNUMBER($S3),IF($S3<=1,"Yes","No"),"n/a") | AJ3: =IF(ISNUMBER($S3),ROUND(MAX(0,MIN(100,100-$S3*2.5-IF(ISNUMBER($T3),$T3,0)*0.12+IF($S3<=1,12,0))),0),"") | AK3: =IF(ISNUMBER($Q3),IF($Q3>=100,20,IF($Q3>=30,10,0)),0)+IF(ISNUMBER($R3),IF($R3>=100,20,0),0)+IF(ISNUMBER($P3),IF($P3>=150,20,IF($P3>=50,12,5)),0)+IF(ISNUMBER($S3),IF($S3<=1,15,0),0) | AL3: 591 | AN3: =IF(AND(ISNUMBER($P3),ISNUMBER($AL3),$AL3<>0),IF(OR($P3>180,$P3/$AL3*1000>400),"Over ceiling, confirm SKU","Within"),"n/a") | AR3: Retrieved and cited, see Enrichment Log | AS3: BLANK -> requires live Amazon.ca capture | AT3: Unverified commercial data
A4: Gatorade | B4: Gatorade Thirst Quencher | Cool Blue | 12 pack 591mL | C4: 2) Electrolyte beverage (RTD) | D4: 591 mL bottle | E4: 12 | G4: =IF(AND(ISNUMBER($F4),ISNUMBER($E4),$E4<>0),$F4/$E4,"") | H4: =IF(AND(ISNUMBER($F4),ISNUMBER($AL4),ISNUMBER($E4),($AL4*$E4)<>0),$F4/($AL4*$E4)*100,"") | K4: =IF(AND(ISNUMBER($F4),ISNUMBER($J4)),$F4*(1-$J4),"") | N4: =IF(ISNUMBER($F4),($F4-IF(ISNUMBER($AM4),$AM4,0))*(1-IF(ISNUMBER($J4),$J4,0)),"") | O4: Cool Blue | P4: 0 | Q4: 270 | R4: 75 | S4: 34 | T4: 140 | U4: Sugar + dextrose | V4: Rehydrate, replenish electrolytes, sports performance | AA4: Very High | AB4: Category defining sports drink; mass repeat purchase | AC4: The original sports hydration standard | AD4: Sodium led rehydration with unmatched brand trust. | AF4: =IF(AND(ISNUMBER($P4),ISNUMBER($AL4),$AL4<>0),ROUND($P4/$AL4*100,1),"") | AG4: =IF(AND(ISNUMBER($S4),ISNUMBER($AL4),$AL4<>0),ROUND($S4/$AL4*100,2),"") | AH4: =IF(AND(ISNUMBER($Q4),ISNUMBER($AL4),$AL4<>0),ROUND($Q4/$AL4*100,1),"") | AI4: =IF(ISNUMBER($S4),IF($S4<=1,"Yes","No"),"n/a") | AJ4: =IF(ISNUMBER($S4),ROUND(MAX(0,MIN(100,100-$S4*2.5-IF(ISNUMBER($T4),$T4,0)*0.12+IF($S4<=1,12,0))),0),"") | AK4: =IF(ISNUMBER($Q4),IF($Q4>=100,20,IF($Q4>=30,10,0)),0)+IF(ISNUMBER($R4),IF($R4>=100,20,0),0)+IF(ISNUMBER($P4),IF($P4>=150,20,IF($P4>=50,12,5)),0)+IF(ISNUMBER($S4),IF($S4<=1,15,0),0) | AL4: 591 | AN4: =IF(AND(ISNUMBER($P4),ISNUMBER($AL4),$AL4<>0),IF(OR($P4>180,$P4/$AL4*1000>400),"Over ceiling, confirm SKU","Within"),"n/a") | AR4: Retrieved and cited, see Enrichment Log | AS4: BLANK -> requires live Amazon.ca capture | AT4: Unverified commercial data
A5: Gatorade | B5: Gatorade Thirst Quencher | Cool Blue | 24 pack 591mL | C5: 2) Electrolyte beverage (RTD) | D5: 591 mL bottle | E5: 24 | G5: =IF(AND(ISNUMBER($F5),ISNUMBER($E5),$E5<>0),$F5/$E5,"") | H5: =IF(AND(ISNUMBER($F5),ISNUMBER($AL5),ISNUMBER($E5),($AL5*$E5)<>0),$F5/($AL5*$E5)*100,"") | K5: =IF(AND(ISNUMBER($F5),ISNUMBER($J5)),$F5*(1-$J5),"") | N5: =IF(ISNUMBER($F5),($F5-IF(ISNUMBER($AM5),$AM5,0))*(1-IF(ISNUMBER($J5),$J5,0)),"") | O5: Cool Blue | P5: 0 | Q5: 270 | R5: 75 | S5: 34 | T5: 140 | U5: Sugar + dextrose | V5: Rehydrate, replenish electrolytes, sports performance | AA5: Very High | AB5: Category defining sports drink; mass repeat purchase | AC5: The original sports hydration standard | AD5: Sodium led rehydration with unmatched brand trust. | AF5: =IF(AND(ISNUMBER($P5),ISNUMBER($AL5),$AL5<>0),ROUND($P5/$AL5*100,1),"") | AG5: =IF(AND(ISNUMBER($S5),ISNUMBER($AL5),$AL5<>0),ROUND($S5/$AL5*100,2),"") | AH5: =IF(AND(ISNUMBER($Q5),ISNUMBER($AL5),$AL5<>0),ROUND($Q5/$AL5*100,1),"") | AI5: =IF(ISNUMBER($S5),IF($S5<=1,"Yes","No"),"n/a") | AJ5: =IF(ISNUMBER($S5),ROUND(MAX(0,MIN(100,100-$S5*2.5-IF(ISNUMBER($T5),$T5,0)*0.12+IF($S5<=1,12,0))),0),"") | AK5: =IF(ISNUMBER($Q5),IF($Q5>=100,20,IF($Q5>=30,10,0)),0)+IF(ISNUMBER($R5),IF($R5>=100,20,0),0)+IF(ISNUMBER($P5),IF($P5>=150,20,IF($P5>=50,12,5)),0)+IF(ISNUMBER($S5),IF($S5<=1,15,0),0) | AL5: 591 | AN5: =IF(AND(ISNUMBER($P5),ISNUMBER($AL5),$AL5<>0),IF(OR($P5>180,$P5/$AL5*1000>400),"Over ceiling, confirm SKU","Within"),"n/a") | AR5: Retrieved and cited, see Enrichment Log | AS5: BLANK -> requires live Amazon.ca capture | AT5: Unverified commercial data
A6: Gatorade | B6: Gatorade Thirst Quencher | Fruit Punch | single 591mL | C6: 2) Electrolyte beverage (RTD) | D6: 591 mL bottle | E6: 1 | G6: =IF(AND(ISNUMBER($F6),ISNUMBER($E6),$E6<>0),$F6/$E6,"") | H6: =IF(AND(ISNUMBER($F6),ISNUMBER($AL6),ISNUMBER($E6),($AL6*$E6)<>0),$F6/($AL6*$E6)*100,"") | K6: =IF(AND(ISNUMBER($F6),ISNUMBER($J6)),$F6*(1-$J6),"") | N6: =IF(ISNUMBER($F6),($F6-IF(ISNUMBER($AM6),$AM6,0))*(1-IF(ISNUMBER($J6),$J6,0)),"") | O6: Fruit Punch | P6: 0 | Q6: 270 | R6: 75 | S6: 34 | T6: 140 | U6: Sugar + dextrose | V6: Rehydrate, replenish electrolytes, sports performance | AA6: Very High | AB6: Category defining sports drink; mass repeat purchase | AC6: The original sports hydration standard | AD6: Sodium led rehydration with unmatched brand trust. | AF6: =IF(AND(ISNUMBER($P6),ISNUMBER($AL6),$AL6<>0),ROUND($P6/$AL6*100,1),"") | AG6: =IF(AND(ISNUMBER($S6),ISNUMBER($AL6),$AL6<>0),ROUND($S6/$AL6*100,2),"") | AH6: =IF(AND(ISNUMBER($Q6),ISNUMBER($AL6),$AL6<>0),ROUND($Q6/$AL6*100,1),"") | AI6: =IF(ISNUMBER($S6),IF($S6<=1,"Yes","No"),"n/a") | AJ6: =IF(ISNUMBER($S6),ROUND(MAX(0,MIN(100,100-$S6*2.5-IF(ISNUMBER($T6),$T6,0)*0.12+IF($S6<=1,12,0))),0),"") | AK6: =IF(ISNUMBER($Q6),IF($Q6>=100,20,IF($Q6>=30,10,0)),0)+IF(ISNUMBER($R6),IF($R6>=100,20,0),0)+IF(ISNUMBER($P6),IF($P6>=150,20,IF($P6>=50,12,5)),0)+IF(ISNUMBER($S6),IF($S6<=1,15,0),0) | AL6: 591 | AN6: =IF(AND(ISNUMBER($P6),ISNUMBER($AL6),$AL6<>0),IF(OR($P6>180,$P6/$AL6*1000>400),"Over ceiling, confirm SKU","Within"),"n/a") | AR6: Retrieved and cited, see Enrichment Log | AS6: BLANK -> requires live Amazon.ca capture | AT6: Unverified commercial data
A7: Gatorade | B7: Gatorade Thirst Quencher | Fruit Punch | 6 pack 591mL | C7: 2) Electrolyte beverage (RTD) | D7: 591 mL bottle | E7: 6 | G7: =IF(AND(ISNUMBER($F7),ISNUMBER($E7),$E7<>0),$F7/$E7,"") | H7: =IF(AND(ISNUMBER($F7),ISNUMBER($AL7),ISNUMBER($E7),($AL7*$E7)<>0),$F7/($AL7*$E7)*100,"") | K7: =IF(AND(ISNUMBER($F7),ISNUMBER($J7)),$F7*(1-$J7),"") | N7: =IF(ISNUMBER($F7),($F7-IF(ISNUMBER($AM7),$AM7,0))*(1-IF(ISNUMBER($J7),$J7,0)),"") | O7: Fruit Punch | P7: 0 | Q7: 270 | R7: 75 | S7: 34 | T7: 140 | U7: Sugar + dextrose | V7: Rehydrate, replenish electrolytes, sports performance | AA7: Very High | AB7: Category defining sports drink; mass repeat purchase | AC7: The original sports hydration standard | AD7: Sodium led rehydration with unmatched brand trust. | AF7: =IF(AND(ISNUMBER($P7),ISNUMBER($AL7),$AL7<>0),ROUND($P7/$AL7*100,1),"") | AG7: =IF(AND(ISNUMBER($S7),ISNUMBER($AL7),$AL7<>0),ROUND($S7/$AL7*100,2),"") | AH7: =IF(AND(ISNUMBER($Q7),ISNUMBER($AL7),$AL7<>0),ROUND($Q7/$AL7*100,1),"") | AI7: =IF(ISNUMBER($S7),IF($S7<=1,"Yes","No"),"n/a") | AJ7: =IF(ISNUMBER($S7),ROUND(MAX(0,MIN(100,100-$S7*2.5-IF(ISNUMBER($T7),$T7,0)*0.12+IF($S7<=1,12,0))),0),"") | AK7: =IF(ISNUMBER($Q7),IF($Q7>=100,20,IF($Q7>=30,10,0)),0)+IF(ISNUMBER($R7),IF($R7>=100,20,0),0)+IF(ISNUMBER($P7),IF($P7>=150,20,IF($P7>=50,12,5)),0)+IF(ISNUMBER($S7),IF($S7<=1,15,0),0) | AL7: 591 | AN7: =IF(AND(ISNUMBER($P7),ISNUMBER($AL7),$AL7<>0),IF(OR($P7>180,$P7/$AL7*1000>400),"Over ceiling, confirm SKU","Within"),"n/a") | AR7: Retrieved and cited, see Enrichment Log | AS7: BLANK -> requires live Amazon.ca capture | AT7: Unverified commercial data
A8: Gatorade | B8: Gatorade Thirst Quencher | Fruit Punch | 12 pack 591mL | C8: 2) Electrolyte beverage (RTD) | D8: 591 mL bottle | E8: 12 | G8: =IF(AND(ISNUMBER($F8),ISNUMBER($E8),$E8<>0),$F8/$E8,"") | H8: =IF(AND(ISNUMBER($F8),ISNUMBER($AL8),ISNUMBER($E8),($AL8*$E8)<>0),$F8/($AL8*$E8)*100,"") | K8: =IF(AND(ISNUMBER($F8),ISNUMBER($J8)),$F8*(1-$J8),"") | N8: =IF(ISNUMBER($F8),($F8-IF(ISNUMBER($AM8),$AM8,0))*(1-IF(ISNUMBER($J8),$J8,0)),"") | O8: Fruit Punch | P8: 0 | Q8: 270 | R8: 75 | S8: 34 | T8: 140 | U8: Sugar + dextrose | V8: Rehydrate, replenish electrolytes, sports performance | AA8: Very High | AB8: Category defining sports drink; mass repeat purchase | AC8: The original sports hydration standard | AD8: Sodium led rehydration with unmatched brand trust. | AF8: =IF(AND(ISNUMBER($P8),ISNUMBER($AL8),$AL8<>0),ROUND($P8/$AL8*100,1),"") | AG8: =IF(AND(ISNUMBER($S8),ISNUMBER($AL8),$AL8<>0),ROUND($S8/$AL8*100,2),"") | AH8: =IF(AND(ISNUMBER($Q8),ISNUMBER($AL8),$AL8<>0),ROUND($Q8/$AL8*100,1),"") | AI8: =IF(ISNUMBER($S8),IF($S8<=1,"Yes","No"),"n/a") | AJ8: =IF(ISNUMBER($S8),ROUND(MAX(0,MIN(100,100-$S8*2.5-IF(ISNUMBER($T8),$T8,0)*0.12+IF($S8<=1,12,0))),0),"") | AK8: =IF(ISNUMBER($Q8),IF($Q8>=100,20,IF($Q8>=30,10,0)),0)+IF(ISNUMBER($R8),IF($R8>=100,20,0),0)+IF(ISNUMBER($P8),IF($P8>=150,20,IF($P8>=50,12,5)),0)+IF(ISNUMBER($S8),IF($S8<=1,15,0),0) | AL8: 591 | AN8: =IF(AND(ISNUMBER($P8),ISNUMBER($AL8),$AL8<>0),IF(OR($P8>180,$P8/$AL8*1000>400),"Over ceiling, confirm SKU","Within"),"n/a") | AR8: Retrieved and cited, see Enrichment Log | AS8: BLANK -> requires live Amazon.ca capture | AT8: Unverified commercial data
A9: Gatorade | B9: Gatorade Thirst Quencher | Fruit Punch | 24 pack 591mL | C9: 2) Electrolyte beverage (RTD) | D9: 591 mL bottle | E9: 24 | G9: =IF(AND(ISNUMBER($F9),ISNUMBER($E9),$E9<>0),$F9/$E9,"") | H9: =IF(AND(ISNUMBER($F9),ISNUMBER($AL9),ISNUMBER($E9),($AL9*$E9)<>0),$F9/($AL9*$E9)*100,"") | K9: =IF(AND(ISNUMBER($F9),ISNUMBER($J9)),$F9*(1-$J9),"") | N9: =IF(ISNUMBER($F9),($F9-IF(ISNUMBER($AM9),$AM9,0))*(1-IF(ISNUMBER($J9),$J9,0)),"") | O9: Fruit Punch | P9: 0 | Q9: 270 | R9: 75 | S9: 34 | T9: 140 | U9: Sugar + dextrose | V9: Rehydrate, replenish electrolytes, sports performance | AA9: Very High | AB9: Category defining sports drink; mass repeat purchase | AC9: The original sports hydration standard | AD9: Sodium led rehydration with unmatched brand trust. | AF9: =IF(AND(ISNUMBER($P9),ISNUMBER($AL9),$AL9<>0),ROUND($P9/$AL9*100,1),"") | AG9: =IF(AND(ISNUMBER($S9),ISNUMBER($AL9),$AL9<>0),ROUND($S9/$AL9*100,2),"") | AH9: =IF(AND(ISNUMBER($Q9),ISNUMBER($AL9),$AL9<>0),ROUND($Q9/$AL9*100,1),"") | AI9: =IF(ISNUMBER($S9),IF($S9<=1,"Yes","No"),"n/a") | AJ9: =IF(ISNUMBER($S9),ROUND(MAX(0,MIN(100,100-$S9*2.5-IF(ISNUMBER($T9),$T9,0)*0.12+IF($S9<=1,12,0))),0),"") | AK9: =IF(ISNUMBER($Q9),IF($Q9>=100,20,IF($Q9>=30,10,0)),0)+IF(ISNUMBER($R9),IF($R9>=100,20,0),0)+IF(ISNUMBER($P9),IF($P9>=150,20,IF($P9>=50,12,5)),0)+IF(ISNUMBER($S9),IF($S9<=1,15,0),0) | AL9: 591 | AN9: =IF(AND(ISNUMBER($P9),ISNUMBER($AL9),$AL9<>0),IF(OR($P9>180,$P9/$AL9*1000>400),"Over ceiling, confirm SKU","Within"),"n/a") | AR9: Retrieved and cited, see Enrichment Log | AS9: BLANK -> requires live Amazon.ca capture | AT9: Unverified commercial data
A10: Gatorade | B10: Gatorade Thirst Quencher | Glacier Freeze | single 591mL | C10: 2) Electrolyte beverage (RTD) | D10: 591 mL bottle | E10: 1 | G10: =IF(AND(ISNUMBER($F10),ISNUMBER($E10),$E10<>0),$F10/$E10,"") | H10: =IF(AND(ISNUMBER($F10),ISNUMBER($AL10),ISNUMBER($E10),($AL10*$E10)<>0),$F10/($AL10*$E10)*100,"") | K10: =IF(AND(ISNUMBER($F10),ISNUMBER($J10)),$F10*(1-$J10),"") | N10: =IF(ISNUMBER($F10),($F10-IF(ISNUMBER($AM10),$AM10,0))*(1-IF(ISNUMBER($J10),$J10,0)),"") | O10: Glacier Freeze | P10: 0 | Q10: 270 | R10: 75 | S10: 34 | T10: 140 | U10: Sugar + dextrose | V10: Rehydrate, replenish electrolytes, sports performance | AA10: Very High | AB10: Category defining sports drink; mass repeat purchase | AC10: The original sports hydration standard | AD10: Sodium led rehydration with unmatched brand trust. | AF10: =IF(AND(ISNUMBER($P10),ISNUMBER($AL10),$AL10<>0),ROUND($P10/$AL10*100,1),"") | AG10: =IF(AND(ISNUMBER($S10),ISNUMBER($AL10),$AL10<>0),ROUND($S10/$AL10*100,2),"") | AH10: =IF(AND(ISNUMBER($Q10),ISNUMBER($AL10),$AL10<>0),ROUND($Q10/$AL10*100,1),"") | AI10: =IF(ISNUMBER($S10),IF($S10<=1,"Yes","No"),"n/a") | AJ10: =IF(ISNUMBER($S10),ROUND(MAX(0,MIN(100,100-$S10*2.5-IF(ISNUMBER($T10),$T10,0)*0.12+IF($S10<=1,12,0))),0),"") | AK10: =IF(ISNUMBER($Q10),IF($Q10>=100,20,IF($Q10>=30,10,0)),0)+IF(ISNUMBER($R10),IF($R10>=100,20,0),0)+IF(ISNUMBER($P10),IF($P10>=150,20,IF($P10>=50,12,5)),0)+IF(ISNUMBER($S10),IF($S10<=1,15,0),0) | AL10: 591 | AN10: =IF(AND(ISNUMBER($P10),ISNUMBER($AL10),$AL10<>0),IF(OR($P10>180,$P10/$AL10*1000>400),"Over ceiling, confirm SKU","Within"),"n/a") | AR10: Retrieved and cited, see Enrichment Log | AS10: BLANK -> requires live Amazon.ca capture | AT10: Unverified commercial data
A11: Gatorade | B11: Gatorade Thirst Quencher | Glacier Freeze | 6 pack 591mL | C11: 2) Electrolyte beverage (RTD) | D11: 591 mL bottle | E11: 6 | G11: =IF(AND(ISNUMBER($F11),ISNUMBER($E11),$E11<>0),$F11/$E11,"") | H11: =IF(AND(ISNUMBER($F11),ISNUMBER($AL11),ISNUMBER($E11),($AL11*$E11)<>0),$F11/($AL11*$E11)*100,"") | K11: =IF(AND(ISNUMBER($F11),ISNUMBER($J11)),$F11*(1-$J11),"") | N11: =IF(ISNUMBER($F11),($F11-IF(ISNUMBER($AM11),$AM11,0))*(1-IF(ISNUMBER($J11),$J11,0)),"") | O11: Glacier Freeze | P11: 0 | Q11: 270 | R11: 75 | S11: 34 | T11: 140 | U11: Sugar + dextrose | V11: Rehydrate, replenish electrolytes, sports performance | AA11: Very High | AB11: Category defining sports drink; mass repeat purchase | AC11: The original sports hydration standard | AD11: Sodium led rehydration with unmatched brand trust. | AF11: =IF(AND(ISNUMBER($P11),ISNUMBER($AL11),$AL11<>0),ROUND($P11/$AL11*100,1),"") | AG11: =IF(AND(ISNUMBER($S11),ISNUMBER($AL11),$AL11<>0),ROUND($S11/$AL11*100,2),"") | AH11: =IF(AND(ISNUMBER($Q11),ISNUMBER($AL11),$AL11<>0),ROUND($Q11/$AL11*100,1),"") | AI11: =IF(ISNUMBER($S11),IF($S11<=1,"Yes","No"),"n/a") | AJ11: =IF(ISNUMBER($S11),ROUND(MAX(0,MIN(100,100-$S11*2.5-IF(ISNUMBER($T11),$T11,0)*0.12+IF($S11<=1,12,0))),0),"") | AK11: =IF(ISNUMBER($Q11),IF($Q11>=100,20,IF($Q11>=30,10,0)),0)+IF(ISNUMBER($R11),IF($R11>=100,20,0),0)+IF(ISNUMBER($P11),IF($P11>=150,20,IF($P11>=50,12,5)),0)+IF(ISNUMBER($S11),IF($S11<=1,15,0),0) | AL11: 591 | AN11: =IF(AND(ISNUMBER($P11),ISNUMBER($AL11),$AL11<>0),IF(OR($P11>180,$P11/$AL11*1000>400),"Over ceiling, confirm SKU","Within"),"n/a") | AR11: Retrieved and cited, see Enrichment Log | AS11: BLANK -> requires live Amazon.ca capture | AT11: Unverified commercial data
A12: Gatorade | B12: Gatorade Thirst Quencher | Glacier Freeze | 12 pack 591mL | C12: 2) Electrolyte beverage (RTD) | D12: 591 mL bottle | E12: 12 | G12: =IF(AND(ISNUMBER($F12),ISNUMBER($E12),$E12<>0),$F12/$E12,"") | H12: =IF(AND(ISNUMBER($F12),ISNUMBER($AL12),ISNUMBER($E12),($AL12*$E12)<>0),$F12/($AL12*$E12)*100,"") | K12: =IF(AND(ISNUMBER($F12),ISNUMBER($J12)),$F12*(1-$J12),"") | N12: =IF(ISNUMBER($F12),($F12-IF(ISNUMBER($AM12),$AM12,0))*(1-IF(ISNUMBER($J12),$J12,0)),"") | O12: Glacier Freeze | P12: 0 | Q12: 270 | R12: 75 | S12: 34 | T12: 140 | U12: Sugar + dextrose | V12: Rehydrate, replenish electrolytes, sports performance | AA12: Very High | AB12: Category defining sports drink; mass repeat purchase | AC12: The original sports hydration standard | AD12: Sodium led rehydration with unmatched brand trust. | AF12: =IF(AND(ISNUMBER($P12),ISNUMBER($AL12),$AL12<>0),ROUND($P12/$AL12*100,1),"") | AG12: =IF(AND(ISNUMBER($S12),ISNUMBER($AL12),$AL12<>0),ROUND($S12/$AL12*100,2),"") | AH12: =IF(AND(ISNUMBER($Q12),ISNUMBER($AL12),$AL12<>0),ROUND($Q12/$AL12*100,1),"") | AI12: =IF(ISNUMBER($S12),IF($S12<=1,"Yes","No"),"n/a") | AJ12: =IF(ISNUMBER($S12),ROUND(MAX(0,MIN(100,100-$S12*2.5-IF(ISNUMBER($T12),$T12,0)*0.12+IF($S12<=1,12,0))),0),"") | AK12: =IF(ISNUMBER($Q12),IF($Q12>=100,20,IF($Q12>=30,10,0)),0)+IF(ISNUMBER($R12),IF($R12>=100,20,0),0)+IF(ISNUMBER($P12),IF($P12>=150,20,IF($P12>=50,12,5)),0)+IF(ISNUMBER($S12),IF($S12<=1,15,0),0) | AL12: 591 | AN12: =IF(AND(ISNUMBER($P12),ISNUMBER($AL12),$AL12<>0),IF(OR($P12>180,$P12/$AL12*1000>400),"Over ceiling, confirm SKU","Within"),"n/a") | AR12: Retrieved and cited, see Enrichment Log | AS12: BLANK -> requires live Amazon.ca capture | AT12: Unverified commercial data
A13: Gatorade | B13: Gatorade Thirst Quencher | Glacier Freeze | 24 pack 591mL | C13: 2) Electrolyte beverage (RTD) | D13: 591 mL bottle | E13: 24 | G13: =IF(AND(ISNUMBER($F13),ISNUMBER($E13),$E13<>0),$F13/$E13,"") | H13: =IF(AND(ISNUMBER($F13),ISNUMBER($AL13),ISNUMBER($E13),($AL13*$E13)<>0),$F13/($AL13*$E13)*100,"") | K13: =IF(AND(ISNUMBER($F13),ISNUMBER($J13)),$F13*(1-$J13),"") | N13: =IF(ISNUMBER($F13),($F13-IF(ISNUMBER($AM13),$AM13,0))*(1-IF(ISNUMBER($J13),$J13,0)),"") | O13: Glacier Freeze | P13: 0 | Q13: 270 | R13: 75 | S13: 34 | T13: 140 | U13: Sugar + dextrose | V13: Rehydrate, replenish electrolytes, sports performance | AA13: Very High | AB13: Category defining sports drink; mass repeat purchase | AC13: The original sports hydration standard | AD13: Sodium led rehydration with unmatched brand trust. | AF13: =IF(AND(ISNUMBER($P13),ISNUMBER($AL13),$AL13<>0),ROUND($P13/$AL13*100,1),"") | AG13: =IF(AND(ISNUMBER($S13),ISNUMBER($AL13),$AL13<>0),ROUND($S13/$AL13*100,2),"") | AH13: =IF(AND(ISNUMBER($Q13),ISNUMBER($AL13),$AL13<>0),ROUND($Q13/$AL13*100,1),"") | AI13: =IF(ISNUMBER($S13),IF($S13<=1,"Yes","No"),"n/a") | AJ13: =IF(ISNUMBER($S13),ROUND(MAX(0,MIN(100,100-$S13*2.5-IF(ISNUMBER($T13),$T13,0)*0.12+IF($S13<=1,12,0))),0),"") | AK13: =IF(ISNUMBER($Q13),IF($Q13>=100,20,IF($Q13>=30,10,0)),0)+IF(ISNUMBER($R13),IF($R13>=100,20,0),0)+IF(ISNUMBER($P13),IF($P13>=150,20,IF($P13>=50,12,5)),0)+IF(ISNUMBER($S13),IF($S13<=1,15,0),0) | AL13: 591 | AN13: =IF(AND(ISNUMBER($P13),ISNUMBER($AL13),$AL13<>0),IF(OR($P13>180,$P13/$AL13*1000>400),"Over ceiling, confirm SKU","Within"),"n/a") | AR13: Retrieved and cited, see Enrichment Log | AS13: BLANK -> requires live Amazon.ca capture | AT13: Unverified commercial data
... A345: Propel | B345: Propel Electrolyte Water | Black Cherry | 24 pack 591mL | C345: 2) Electrolyte beverage (RTD) | D345: 591 mL bottle | E345: 24 | G345: =IF(AND(ISNUMBER($F345),ISNUMBER($E345),$E345<>0),$F345/$E345,"") | H345: =IF(AND(ISNUMBER($F345),ISNUMBER($AL345),ISNUMBER($E345),($AL345*$E345)<>0),$F345/($AL345*$E345)*100,"") | K345: =IF(AND(ISNUMBER($F345),ISNUMBER($J345)),$F345*(1-$J345),"") | N345: =IF(ISNUMBER($F345),($F345-IF(ISNUMBER($AM345),$AM345,0))*(1-IF(ISNUMBER($J345),$J345,0)),"") | O345: Black Cherry | P345: 0 | Q345: 150 | R345: 40 | S345: 0 | T345: 5 | U345: Sucralose + acesulfame-K | V345: Electrolytes + vitamins, zero sugar, fitness water | AA345: High | AB345: Leading zero sugar electrolyte water (Gatorade family) | AC345: Zero sugar workout water with electrolytes | AD345: Light electrolyte water for everyday workouts. | AF345: =IF(AND(ISNUMBER($P345),ISNUMBER($AL345),$AL345<>0),ROUND($P345/$AL345*100,1),"") | AG345: =IF(AND(ISNUMBER($S345),ISNUMBER($AL345),$AL345<>0),ROUND($S345/$AL345*100,2),"") | AH345: =IF(AND(ISNUMBER($Q345),ISNUMBER($AL345),$AL345<>0),ROUND($Q345/$AL345*100,1),"") | AI345: =IF(ISNUMBER($S345),IF($S345<=1,"Yes","No"),"n/a") | AJ345: =IF(ISNUMBER($S345),ROUND(MAX(0,MIN(100,100-$S345*2.5-IF(ISNUMBER($T345),$T345,0)*0.12+IF($S345<=1,12,0))),0),"") | AK345: =IF(ISNUMBER($Q345),IF($Q345>=100,20,IF($Q345>=30,10,0)),0)+IF(ISNUMBER($R345),IF($R345>=100,20,0),0)+IF(ISNUMBER($P345),IF($P345>=150,20,IF($P345>=50,12,5)),0)+IF(ISNUMBER($S345),IF($S345<=1,15,0),0) | AL345: 591 | AN345: =IF(AND(ISNUMBER($P345),ISNUMBER($AL345),$AL345<>0),IF(OR($P345>180,$P345/$AL345*1000>400),"Over ceiling, confirm SKU","Within"),"n/a") | AR345: Recalled, batch confirmed, to confirm | AS345: BLANK -> requires live Amazon.ca capture | AT345: Unverified commercial data
A346: Essentia | B346: Essentia Ionized Alkaline Water | Original (pH 9.5) | 8 pack 1L | C346: 2) Electrolyte beverage (RTD) | D346: 1 L bottle | E346: 8 | G346: =IF(AND(ISNUMBER($F346),ISNUMBER($E346),$E346<>0),$F346/$E346,"") | H346: =IF(AND(ISNUMBER($F346),ISNUMBER($AL346),ISNUMBER($E346),($AL346*$E346)<>0),$F346/($AL346*$E346)*100,"") | K346: =IF(AND(ISNUMBER($F346),ISNUMBER($J346)),$F346*(1-$J346),"") | N346: =IF(ISNUMBER($F346),($F346-IF(ISNUMBER($AM346),$AM346,0))*(1-IF(ISNUMBER($J346),$J346,0)),"") | O346: Original (pH 9.5) | P346: 0 | Q346: 10 | R346: Not listed | S346: 0 | T346: 0 | U346: None | V346: Ionized alkaline pH 9.5, electrolytes for taste, hydration | AA346: High | AB346: Leading premium alkaline water | AC346: Smooth alkaline ionized water | AD346: Alkaline water believers; smooth taste. | AF346: =IF(AND(ISNUMBER($P346),ISNUMBER($AL346),$AL346<>0),ROUND($P346/$AL346*100,1),"") | AG346: =IF(AND(ISNUMBER($S346),ISNUMBER($AL346),$AL346<>0),ROUND($S346/$AL346*100,2),"") | AH346: =IF(AND(ISNUMBER($Q346),ISNUMBER($AL346),$AL346<>0),ROUND($Q346/$AL346*100,1),"") | AI346: =IF(ISNUMBER($S346),IF($S346<=1,"Yes","No"),"n/a") | AJ346: =IF(ISNUMBER($S346),ROUND(MAX(0,MIN(100,100-$S346*2.5-IF(ISNUMBER($T346),$T346,0)*0.12+IF($S346<=1,12,0))),0),"") | AK346: =IF(ISNUMBER($Q346),IF($Q346>=100,20,IF($Q346>=30,10,0)),0)+IF(ISNUMBER($R346),IF($R346>=100,20,0),0)+IF(ISNUMBER($P346),IF($P346>=150,20,IF($P346>=50,12,5)),0)+IF(ISNUMBER($S346),IF($S346<=1,15,0),0) | AL346: 1000 | AN346: =IF(AND(ISNUMBER($P346),ISNUMBER($AL346),$AL346<>0),IF(OR($P346>180,$P346/$AL346*1000>400),"Over ceiling, confirm SKU","Within"),"n/a") | AR346: Recalled, batch confirmed, to confirm | AS346: BLANK -> requires live Amazon.ca capture | AT346: Unverified commercial data
A347: Essentia | B347: Essentia Ionized Alkaline Water | Original (pH 9.5) | 12 pack 1L | C347: 2) Electrolyte beverage (RTD) | D347: 1 L bottle | E347: 12 | G347: =IF(AND(ISNUMBER($F347),ISNUMBER($E347),$E347<>0),$F347/$E347,"") | H347: =IF(AND(ISNUMBER($F347),ISNUMBER($AL347),ISNUMBER($E347),($AL347*$E347)<>0),$F347/($AL347*$E347)*100,"") | K347: =IF(AND(ISNUMBER($F347),ISNUMBER($J347)),$F347*(1-$J347),"") | N347: =IF(ISNUMBER($F347),($F347-IF(ISNUMBER($AM347),$AM347,0))*(1-IF(ISNUMBER($J347),$J347,0)),"") | O347: Original (pH 9.5) | P347: 0 | Q347: 10 | R347: Not listed | S347: 0 | T347: 0 | U347: None | V347: Ionized alkaline pH 9.5, electrolytes for taste, hydration | AA347: High | AB347: Leading premium alkaline water | AC347: Smooth alkaline ionized water | AD347: Alkaline water believers; smooth taste. | AF347: =IF(AND(ISNUMBER($P347),ISNUMBER($AL347),$AL347<>0),ROUND($P347/$AL347*100,1),"") | AG347: =IF(AND(ISNUMBER($S347),ISNUMBER($AL347),$AL347<>0),ROUND($S347/$AL347*100,2),"") | AH347: =IF(AND(ISNUMBER($Q347),ISNUMBER($AL347),$AL347<>0),ROUND($Q347/$AL347*100,1),"") | AI347: =IF(ISNUMBER($S347),IF($S347<=1,"Yes","No"),"n/a") | AJ347: =IF(ISNUMBER($S347),ROUND(MAX(0,MIN(100,100-$S347*2.5-IF(ISNUMBER($T347),$T347,0)*0.12+IF($S347<=1,12,0))),0),"") | AK347: =IF(ISNUMBER($Q347),IF($Q347>=100,20,IF($Q347>=30,10,0)),0)+IF(ISNUMBER($R347),IF($R347>=100,20,0),0)+IF(ISNUMBER($P347),IF($P347>=150,20,IF($P347>=50,12,5)),0)+IF(ISNUMBER($S347),IF($S347<=1,15,0),0) | AL347: 1000 | AN347: =IF(AND(ISNUMBER($P347),ISNUMBER($AL347),$AL347<>0),IF(OR($P347>180,$P347/$AL347*1000>400),"Over ceiling, confirm SKU","Within"),"n/a") | AR347: Recalled, batch confirmed, to confirm | AS347: BLANK -> requires live Amazon.ca capture | AT347: Unverified commercial data
A348: Essentia | B348: Essentia Ionized Alkaline Water | Original (pH 9.5) | 24 pack 1L | C348: 2) Electrolyte beverage (RTD) | D348: 1 L bottle | E348: 24 | G348: =IF(AND(ISNUMBER($F348),ISNUMBER($E348),$E348<>0),$F348/$E348,"") | H348: =IF(AND(ISNUMBER($F348),ISNUMBER($AL348),ISNUMBER($E348),($AL348*$E348)<>0),$F348/($AL348*$E348)*100,"") | K348: =IF(AND(ISNUMBER($F348),ISNUMBER($J348)),$F348*(1-$J348),"") | N348: =IF(ISNUMBER($F348),($F348-IF(ISNUMBER($AM348),$AM348,0))*(1-IF(ISNUMBER($J348),$J348,0)),"") | O348: Original (pH 9.5) | P348: 0 | Q348: 10 | R348: Not listed | S348: 0 | T348: 0 | U348: None | V348: Ionized alkaline pH 9.5, electrolytes for taste, hydration | AA348: High | AB348: Leading premium alkaline water | AC348: Smooth alkaline ionized water | AD348: Alkaline water believers; smooth taste. | AF348: =IF(AND(ISNUMBER($P348),ISNUMBER($AL348),$AL348<>0),ROUND($P348/$AL348*100,1),"") | AG348: =IF(AND(ISNUMBER($S348),ISNUMBER($AL348),$AL348<>0),ROUND($S348/$AL348*100,2),"") | AH348: =IF(AND(ISNUMBER($Q348),ISNUMBER($AL348),$AL348<>0),ROUND($Q348/$AL348*100,1),"") | AI348: =IF(ISNUMBER($S348),IF($S348<=1,"Yes","No"),"n/a") | AJ348: =IF(ISNUMBER($S348),ROUND(MAX(0,MIN(100,100-$S348*2.5-IF(ISNUMBER($T348),$T348,0)*0.12+IF($S348<=1,12,0))),0),"") | AK348: =IF(ISNUMBER($Q348),IF($Q348>=100,20,IF($Q348>=30,10,0)),0)+IF(ISNUMBER($R348),IF($R348>=100,20,0),0)+IF(ISNUMBER($P348),IF($P348>=150,20,IF($P348>=50,12,5)),0)+IF(ISNUMBER($S348),IF($S348<=1,15,0),0) | AL348: 1000 | AN348: =IF(AND(ISNUMBER($P348),ISNUMBER($AL348),$AL348<>0),IF(OR($P348>180,$P348/$AL348*1000>400),"Over ceiling, confirm SKU","Within"),"n/a") | AR348: Recalled, batch confirmed, to confirm | AS348: BLANK -> requires live Amazon.ca capture | AT348: Unverified commercial data
A349: Smartwater | B349: Smartwater Alkaline | Alkaline pH 9+ | 8 pack 1L | C349: 2) Electrolyte beverage (RTD) | D349: 1 L bottle | E349: 8 | G349: =IF(AND(ISNUMBER($F349),ISNUMBER($E349),$E349<>0),$F349/$E349,"") | H349: =IF(AND(ISNUMBER($F349),ISNUMBER($AL349),ISNUMBER($E349),($AL349*$E349)<>0),$F349/($AL349*$E349)*100,"") | K349: =IF(AND(ISNUMBER($F349),ISNUMBER($J349)),$F349*(1-$J349),"") | N349: =IF(ISNUMBER($F349),($F349-IF(ISNUMBER($AM349),$AM349,0))*(1-IF(ISNUMBER($J349),$J349,0)),"") | O349: Alkaline pH 9+ | P349: 0 | Q349: 0 | R349: Not listed | S349: 0 | T349: 0 | U349: None | V349: Vapor distilled, added electrolytes / alkaline variant | AA349: High | AB349: Premium water brand | AC349: Premium distilled water | AD349: Brand trust and clean taste. | AF349: =IF(AND(ISNUMBER($P349),ISNUMBER($AL349),$AL349<>0),ROUND($P349/$AL349*100,1),"") | AG349: =IF(AND(ISNUMBER($S349),ISNUMBER($AL349),$AL349<>0),ROUND($S349/$AL349*100,2),"") | AH349: =IF(AND(ISNUMBER($Q349),ISNUMBER($AL349),$AL349<>0),ROUND($Q349/$AL349*100,1),"") | AI349: =IF(ISNUMBER($S349),IF($S349<=1,"Yes","No"),"n/a") | AJ349: =IF(ISNUMBER($S349),ROUND(MAX(0,MIN(100,100-$S349*2.5-IF(ISNUMBER($T349),$T349,0)*0.12+IF($S349<=1,12,0))),0),"") | AK349: =IF(ISNUMBER($Q349),IF($Q349>=100,20,IF($Q349>=30,10,0)),0)+IF(ISNUMBER($R349),IF($R349>=100,20,0),0)+IF(ISNUMBER($P349),IF($P349>=150,20,IF($P349>=50,12,5)),0)+IF(ISNUMBER($S349),IF($S349<=1,15,0),0) | AL349: 1000 | AN349: =IF(AND(ISNUMBER($P349),ISNUMBER($AL349),$AL349<>0),IF(OR($P349>180,$P349/$AL349*1000>400),"Over ceiling, confirm SKU","Within"),"n/a") | AR349: Recalled, batch confirmed, to confirm | AS349: BLANK -> requires live Amazon.ca capture | AT349: Unverified commercial data
A350: Smartwater | B350: Smartwater Alkaline | Alkaline pH 9+ | 12 pack 1L | C350: 2) Electrolyte beverage (RTD) | D350: 1 L bottle | E350: 12 | G350: =IF(AND(ISNUMBER($F350),ISNUMBER($E350),$E350<>0),$F350/$E350,"") | H350: =IF(AND(ISNUMBER($F350),ISNUMBER($AL350),ISNUMBER($E350),($AL350*$E350)<>0),$F350/($AL350*$E350)*100,"") | K350: =IF(AND(ISNUMBER($F350),ISNUMBER($J350)),$F350*(1-$J350),"") | N350: =IF(ISNUMBER($F350),($F350-IF(ISNUMBER($AM350),$AM350,0))*(1-IF(ISNUMBER($J350),$J350,0)),"") | O350: Alkaline pH 9+ | P350: 0 | Q350: 0 | R350: Not listed | S350: 0 | T350: 0 | U350: None | V350: Vapor distilled, added electrolytes / alkaline variant | AA350: High | AB350: Premium water brand | AC350: Premium distilled water | AD350: Brand trust and clean taste. | AF350: =IF(AND(ISNUMBER($P350),ISNUMBER($AL350),$AL350<>0),ROUND($P350/$AL350*100,1),"") | AG350: =IF(AND(ISNUMBER($S350),ISNUMBER($AL350),$AL350<>0),ROUND($S350/$AL350*100,2),"") | AH350: =IF(AND(ISNUMBER($Q350),ISNUMBER($AL350),$AL350<>0),ROUND($Q350/$AL350*100,1),"") | AI350: =IF(ISNUMBER($S350),IF($S350<=1,"Yes","No"),"n/a") | AJ350: =IF(ISNUMBER($S350),ROUND(MAX(0,MIN(100,100-$S350*2.5-IF(ISNUMBER($T350),$T350,0)*0.12+IF($S350<=1,12,0))),0),"") | AK350: =IF(ISNUMBER($Q350),IF($Q350>=100,20,IF($Q350>=30,10,0)),0)+IF(ISNUMBER($R350),IF($R350>=100,20,0),0)+IF(ISNUMBER($P350),IF($P350>=150,20,IF($P350>=50,12,5)),0)+IF(ISNUMBER($S350),IF($S350<=1,15,0),0) | AL350: 1000 | AN350: =IF(AND(ISNUMBER($P350),ISNUMBER($AL350),$AL350<>0),IF(OR($P350>180,$P350/$AL350*1000>400),"Over ceiling, confirm SKU","Within"),"n/a") | AR350: Recalled, batch confirmed, to confirm | AS350: BLANK -> requires live Amazon.ca capture | AT350: Unverified commercial data
A351: Smartwater | B351: Smartwater Alkaline | Alkaline pH 9+ | 24 pack 1L | C351: 2) Electrolyte beverage (RTD) | D351: 1 L bottle | E351: 24 | G351: =IF(AND(ISNUMBER($F351),ISNUMBER($E351),$E351<>0),$F351/$E351,"") | H351: =IF(AND(ISNUMBER($F351),ISNUMBER($AL351),ISNUMBER($E351),($AL351*$E351)<>0),$F351/($AL351*$E351)*100,"") | K351: =IF(AND(ISNUMBER($F351),ISNUMBER($J351)),$F351*(1-$J351),"") | N351: =IF(ISNUMBER($F351),($F351-IF(ISNUMBER($AM351),$AM351,0))*(1-IF(ISNUMBER($J351),$J351,0)),"") | O351: Alkaline pH 9+ | P351: 0 | Q351: 0 | R351: Not listed | S351: 0 | T351: 0 | U351: None | V351: Vapor distilled, added electrolytes / alkaline variant | AA351: High | AB351: Premium water brand | AC351: Premium distilled water | AD351: Brand trust and clean taste. | AF351: =IF(AND(ISNUMBER($P351),ISNUMBER($AL351),$AL351<>0),ROUND($P351/$AL351*100,1),"") | AG351: =IF(AND(ISNUMBER($S351),ISNUMBER($AL351),$AL351<>0),ROUND($S351/$AL351*100,2),"") | AH351: =IF(AND(ISNUMBER($Q351),ISNUMBER($AL351),$AL351<>0),ROUND($Q351/$AL351*100,1),"") | AI351: =IF(ISNUMBER($S351),IF($S351<=1,"Yes","No"),"n/a") | AJ351: =IF(ISNUMBER($S351),ROUND(MAX(0,MIN(100,100-$S351*2.5-IF(ISNUMBER($T351),$T351,0)*0.12+IF($S351<=1,12,0))),0),"") | AK351: =IF(ISNUMBER($Q351),IF($Q351>=100,20,IF($Q351>=30,10,0)),0)+IF(ISNUMBER($R351),IF($R351>=100,20,0),0)+IF(ISNUMBER($P351),IF($P351>=150,20,IF($P351>=50,12,5)),0)+IF(ISNUMBER($S351),IF($S351<=1,15,0),0) | AL351: 1000 | AN351: =IF(AND(ISNUMBER($P351),ISNUMBER($AL351),$AL351<>0),IF(OR($P351>180,$P351/$AL351*1000>400),"Over ceiling, confirm SKU","Within"),"n/a") | AR351: Recalled, batch confirmed, to confirm | AS351: BLANK -> requires live Amazon.ca capture | AT351: Unverified commercial data
A352: Smartwater | B352: Smartwater Alkaline | Original | 8 pack 1L | C352: 2) Electrolyte beverage (RTD) | D352: 1 L bottle | E352: 8 | G352: =IF(AND(ISNUMBER($F352),ISNUMBER($E352),$E352<>0),$F352/$E352,"") | H352: =IF(AND(ISNUMBER($F352),ISNUMBER($AL352),ISNUMBER($E352),($AL352*$E352)<>0),$F352/($AL352*$E352)*100,"") | K352: =IF(AND(ISNUMBER($F352),ISNUMBER($J352)),$F352*(1-$J352),"") | N352: =IF(ISNUMBER($F352),($F352-IF(ISNUMBER($AM352),$AM352,0))*(1-IF(ISNUMBER($J352),$J352,0)),"") | O352: Original | P352: 0 | Q352: 0 | R352: Not listed | S352: 0 | T352: 0 | U352: None | V352: Vapor distilled, added electrolytes / alkaline variant | AA352: High | AB352: Premium water brand | AC352: Premium distilled water | AD352: Brand trust and clean taste. | AF352: =IF(AND(ISNUMBER($P352),ISNUMBER($AL352),$AL352<>0),ROUND($P352/$AL352*100,1),"") | AG352: =IF(AND(ISNUMBER($S352),ISNUMBER($AL352),$AL352<>0),ROUND($S352/$AL352*100,2),"") | AH352: =IF(AND(ISNUMBER($Q352),ISNUMBER($AL352),$AL352<>0),ROUND($Q352/$AL352*100,1),"") | AI352: =IF(ISNUMBER($S352),IF($S352<=1,"Yes","No"),"n/a") | AJ352: =IF(ISNUMBER($S352),ROUND(MAX(0,MIN(100,100-$S352*2.5-IF(ISNUMBER($T352),$T352,0)*0.12+IF($S352<=1,12,0))),0),"") | AK352: =IF(ISNUMBER($Q352),IF($Q352>=100,20,IF($Q352>=30,10,0)),0)+IF(ISNUMBER($R352),IF($R352>=100,20,0),0)+IF(ISNUMBER($P352),IF($P352>=150,20,IF($P352>=50,12,5)),0)+IF(ISNUMBER($S352),IF($S352<=1,15,0),0) | AL352: 1000 | AN352: =IF(AND(ISNUMBER($P352),ISNUMBER($AL352),$AL352<>0),IF(OR($P352>180,$P352/$AL352*1000>400),"Over ceiling, confirm SKU","Within"),"n/a") | AR352: Recalled, batch confirmed, to confirm | AS352: BLANK -> requires live Amazon.ca capture | AT352: Unverified commercial data
A353: Smartwater | B353: Smartwater Alkaline | Original | 12 pack 1L | C353: 2) Electrolyte beverage (RTD) | D353: 1 L bottle | E353: 12 | G353: =IF(AND(ISNUMBER($F353),ISNUMBER($E353),$E353<>0),$F353/$E353,"") | H353: =IF(AND(ISNUMBER($F353),ISNUMBER($AL353),ISNUMBER($E353),($AL353*$E353)<>0),$F353/($AL353*$E353)*100,"") | K353: =IF(AND(ISNUMBER($F353),ISNUMBER($J353)),$F353*(1-$J353),"") | N353: =IF(ISNUMBER($F353),($F353-IF(ISNUMBER($AM353),$AM353,0))*(1-IF(ISNUMBER($J353),$J353,0)),"") | O353: Original | P353: 0 | Q353: 0 | R353: Not listed | S353: 0 | T353: 0 | U353: None | V353: Vapor distilled, added electrolytes / alkaline variant | AA353: High | AB353: Premium water brand | AC353: Premium distilled water | AD353: Brand trust and clean taste. | AF353: =IF(AND(ISNUMBER($P353),ISNUMBER($AL353),$AL353<>0),ROUND($P353/$AL353*100,1),"") | AG353: =IF(AND(ISNUMBER($S353),ISNUMBER($AL353),$AL353<>0),ROUND($S353/$AL353*100,2),"") | AH353: =IF(AND(ISNUMBER($Q353),ISNUMBER($AL353),$AL353<>0),ROUND($Q353/$AL353*100,1),"") | AI353: =IF(ISNUMBER($S353),IF($S353<=1,"Yes","No"),"n/a") | AJ353: =IF(ISNUMBER($S353),ROUND(MAX(0,MIN(100,100-$S353*2.5-IF(ISNUMBER($T353),$T353,0)*0.12+IF($S353<=1,12,0))),0),"") | AK353: =IF(ISNUMBER($Q353),IF($Q353>=100,20,IF($Q353>=30,10,0)),0)+IF(ISNUMBER($R353),IF($R353>=100,20,0),0)+IF(ISNUMBER($P353),IF($P353>=150,20,IF($P353>=50,12,5)),0)+IF(ISNUMBER($S353),IF($S353<=1,15,0),0) | AL353: 1000 | AN353: =IF(AND(ISNUMBER($P353),ISNUMBER($AL353),$AL353<>0),IF(OR($P353>180,$P353/$AL353*1000>400),"Over ceiling, confirm SKU","Within"),"n/a") | AR353: Recalled, batch confirmed, to confirm | AS353: BLANK -> requires live Amazon.ca capture | AT353: Unverified commercial data
A354: Smartwater | B354: Smartwater Alkaline | Original | 24 pack 1L | C354: 2) Electrolyte beverage (RTD) | D354: 1 L bottle | E354: 24 | G354: =IF(AND(ISNUMBER($F354),ISNUMBER($E354),$E354<>0),$F354/$E354,"") | H354: =IF(AND(ISNUMBER($F354),ISNUMBER($AL354),ISNUMBER($E354),($AL354*$E354)<>0),$F354/($AL354*$E354)*100,"") | K354: =IF(AND(ISNUMBER($F354),ISNUMBER($J354)),$F354*(1-$J354),"") | N354: =IF(ISNUMBER($F354),($F354-IF(ISNUMBER($AM354),$AM354,0))*(1-IF(ISNUMBER($J354),$J354,0)),"") | O354: Original | P354: 0 | Q354: 0 | R354: Not listed | S354: 0 | T354: 0 | U354: None | V354: Vapor distilled, added electrolytes / alkaline variant | AA354: High | AB354: Premium water brand | AC354: Premium distilled water | AD354: Brand trust and clean taste. | AF354: =IF(AND(ISNUMBER($P354),ISNUMBER($AL354),$AL354<>0),ROUND($P354/$AL354*100,1),"") | AG354: =IF(AND(ISNUMBER($S354),ISNUMBER($AL354),$AL354<>0),ROUND($S354/$AL354*100,2),"") | AH354: =IF(AND(ISNUMBER($Q354),ISNUMBER($AL354),$AL354<>0),ROUND($Q354/$AL354*100,1),"") | AI354: =IF(ISNUMBER($S354),IF($S354<=1,"Yes","No"),"n/a") | AJ354: =IF(ISNUMBER($S354),ROUND(MAX(0,MIN(100,100-$S354*2.5-IF(ISNUMBER($T354),$T354,0)*0.12+IF($S354<=1,12,0))),0),"") | AK354: =IF(ISNUMBER($Q354),IF($Q354>=100,20,IF($Q354>=30,10,0)),0)+IF(ISNUMBER($R354),IF($R354>=100,20,0),0)+IF(ISNUMBER($P354),IF($P354>=150,20,IF($P354>=50,12,5)),0)+IF(ISNUMBER($S354),IF($S354<=1,15,0),0) | AL354: 1000 | AN354: =IF(AND(ISNUMBER($P354),ISNUMBER($AL354),$AL354<>0),IF(OR($P354>180,$P354/$AL354*1000>400),"Over ceiling, confirm SKU","Within"),"n/a") | AR354: Recalled, batch confirmed, to confirm | AS354: BLANK -> requires live Amazon.ca capture | AT354: Unverified commercial data
A355: Gatorade | B355: Gatorade G2 Low Sugar | Glacier Freeze | single 591mL | C355: 2) Electrolyte beverage (RTD) | D355: 591 mL bottle | E355: 1 | G355: =IF(AND(ISNUMBER($F355),ISNUMBER($E355),$E355<>0),$F355/$E355,"") | H355: =IF(AND(ISNUMBER($F355),ISNUMBER($AL355),ISNUMBER($E355),($AL355*$E355)<>0),$F355/($AL355*$E355)*100,"") | K355: =IF(AND(ISNUMBER($F355),ISNUMBER($J355)),$F355*(1-$J355),"") | N355: =IF(ISNUMBER($F355),($F355-IF(ISNUMBER($AM355),$AM355,0))*(1-IF(ISNUMBER($J355),$J355,0)),"") | O355: Glacier Freeze | P355: 0 | Q355: 270 | R355: 75 | S355: 7 | T355: 30 | U355: Sugar + sucralose | V355: Same electrolytes, lower sugar | AA355: Medium | AB355: Reduced sugar Gatorade | AC355: Lower sugar Gatorade electrolytes | AD355: Electrolytes with much less sugar. | AF355: =IF(AND(ISNUMBER($P355),ISNUMBER($AL355),$AL355<>0),ROUND($P355/$AL355*100,1),"") | AG355: =IF(AND(ISNUMBER($S355),ISNUMBER($AL355),$AL355<>0),ROUND($S355/$AL355*100,2),"") | AH355: =IF(AND(ISNUMBER($Q355),ISNUMBER($AL355),$AL355<>0),ROUND($Q355/$AL355*100,1),"") | AI355: =IF(ISNUMBER($S355),IF($S355<=1,"Yes","No"),"n/a") | AJ355: =IF(ISNUMBER($S355),ROUND(MAX(0,MIN(100,100-$S355*2.5-IF(ISNUMBER($T355),$T355,0)*0.12+IF($S355<=1,12,0))),0),"") | AK355: =IF(ISNUMBER($Q355),IF($Q355>=100,20,IF($Q355>=30,10,0)),0)+IF(ISNUMBER($R355),IF($R355>=100,20,0),0)+IF(ISNUMBER($P355),IF($P355>=150,20,IF($P355>=50,12,5)),0)+IF(ISNUMBER($S355),IF($S355<=1,15,0),0) | AL355: 591 | AN355: =IF(AND(ISNUMBER($P355),ISNUMBER($AL355),$AL355<>0),IF(OR($P355>180,$P355/$AL355*1000>400),"Over ceiling, confirm SKU","Within"),"n/a") | AR355: Recalled, batch confirmed, to confirm | AS355: BLANK -> requires live Amazon.ca capture | AT355: Unverified commercial data
A356: Gatorade | B356: Gatorade G2 Low Sugar | Glacier Freeze | 6 pack 591mL | C356: 2) Electrolyte beverage (RTD) | D356: 591 mL bottle | E356: 6 | G356: =IF(AND(ISNUMBER($F356),ISNUMBER($E356),$E356<>0),$F356/$E356,"") | H356: =IF(AND(ISNUMBER($F356),ISNUMBER($AL356),ISNUMBER($E356),($AL356*$E356)<>0),$F356/($AL356*$E356)*100,"") | K356: =IF(AND(ISNUMBER($F356),ISNUMBER($J356)),$F356*(1-$J356),"") | N356: =IF(ISNUMBER($F356),($F356-IF(ISNUMBER($AM356),$AM356,0))*(1-IF(ISNUMBER($J356),$J356,0)),"") | O356: Glacier Freeze | P356: 0 | Q356: 270 | R356: 75 | S356: 7 | T356: 30 | U356: Sugar + sucralose | V356: Same electrolytes, lower sugar | AA356: Medium | AB356: Reduced sugar Gatorade | AC356: Lower sugar Gatorade electrolytes | AD356: Electrolytes with much less sugar. | AF356: =IF(AND(ISNUMBER($P356),ISNUMBER($AL356),$AL356<>0),ROUND($P356/$AL356*100,1),"") | AG356: =IF(AND(ISNUMBER($S356),ISNUMBER($AL356),$AL356<>0),ROUND($S356/$AL356*100,2),"") | AH356: =IF(AND(ISNUMBER($Q356),ISNUMBER($AL356),$AL356<>0),ROUND($Q356/$AL356*100,1),"") | AI356: =IF(ISNUMBER($S356),IF($S356<=1,"Yes","No"),"n/a") | AJ356: =IF(ISNUMBER($S356),ROUND(MAX(0,MIN(100,100-$S356*2.5-IF(ISNUMBER($T356),$T356,0)*0.12+IF($S356<=1,12,0))),0),"") | AK356: =IF(ISNUMBER($Q356),IF($Q356>=100,20,IF($Q356>=30,10,0)),0)+IF(ISNUMBER($R356),IF($R356>=100,20,0),0)+IF(ISNUMBER($P356),IF($P356>=150,20,IF($P356>=50,12,5)),0)+IF(ISNUMBER($S356),IF($S356<=1,15,0),0) | AL356: 591 | AN356: =IF(AND(ISNUMBER($P356),ISNUMBER($AL356),$AL356<>0),IF(OR($P356>180,$P356/$AL356*1000>400),"Over ceiling, confirm SKU","Within"),"n/a") | AR356: Recalled, batch confirmed, to confirm | AS356: BLANK -> requires live Amazon.ca capture | AT356: Unverified commercial data
A357: Gatorade | B357: Gatorade G2 Low Sugar | Glacier Freeze | 12 pack 591mL | C357: 2) Electrolyte beverage (RTD) | D357: 591 mL bottle | E357: 12 | G357: =IF(AND(ISNUMBER($F357),ISNUMBER($E357),$E357<>0),$F357/$E357,"") | H357: =IF(AND(ISNUMBER($F357),ISNUMBER($AL357),ISNUMBER($E357),($AL357*$E357)<>0),$F357/($AL357*$E357)*100,"") | K357: =IF(AND(ISNUMBER($F357),ISNUMBER($J357)),$F357*(1-$J357),"") | N357: =IF(ISNUMBER($F357),($F357-IF(ISNUMBER($AM357),$AM357,0))*(1-IF(ISNUMBER($J357),$J357,0)),"") | O357: Glacier Freeze | P357: 0 | Q357: 270 | R357: 75 | S357: 7 | T357: 30 | U357: Sugar + sucralose | V357: Same electrolytes, lower sugar | AA357: Medium | AB357: Reduced sugar Gatorade | AC357: Lower sugar Gatorade electrolytes | AD357: Electrolytes with much less sugar. | AF357: =IF(AND(ISNUMBER($P357),ISNUMBER($AL357),$AL357<>0),ROUND($P357/$AL357*100,1),"") | AG357: =IF(AND(ISNUMBER($S357),ISNUMBER($AL357),$AL357<>0),ROUND($S357/$AL357*100,2),"") | AH357: =IF(AND(ISNUMBER($Q357),ISNUMBER($AL357),$AL357<>0),ROUND($Q357/$AL357*100,1),"") | AI357: =IF(ISNUMBER($S357),IF($S357<=1,"Yes","No"),"n/a") | AJ357: =IF(ISNUMBER($S357),ROUND(MAX(0,MIN(100,100-$S357*2.5-IF(ISNUMBER($T357),$T357,0)*0.12+IF($S357<=1,12,0))),0),"") | AK357: =IF(ISNUMBER($Q357),IF($Q357>=100,20,IF($Q357>=30,10,0)),0)+IF(ISNUMBER($R357),IF($R357>=100,20,0),0)+IF(ISNUMBER($P357),IF($P357>=150,20,IF($P357>=50,12,5)),0)+IF(ISNUMBER($S357),IF($S357<=1,15,0),0) | AL357: 591 | AN357: =IF(AND(ISNUMBER($P357),ISNUMBER($AL357),$AL357<>0),IF(OR($P357>180,$P357/$AL357*1000>400),"Over ceiling, confirm SKU","Within"),"n/a") | AR357: Recalled, batch confirmed, to confirm | AS357: BLANK -> requires live Amazon.ca capture | AT357: Unverified commercial data
A358: Gatorade | B358: Gatorade G2 Low Sugar | Glacier Freeze | 24 pack 591mL | C358: 2) Electrolyte beverage (RTD) | D358: 591 mL bottle | E358: 24 | G358: =IF(AND(ISNUMBER($F358),ISNUMBER($E358),$E358<>0),$F358/$E358,"") | H358: =IF(AND(ISNUMBER($F358),ISNUMBER($AL358),ISNUMBER($E358),($AL358*$E358)<>0),$F358/($AL358*$E358)*100,"") | K358: =IF(AND(ISNUMBER($F358),ISNUMBER($J358)),$F358*(1-$J358),"") | N358: =IF(ISNUMBER($F358),($F358-IF(ISNUMBER($AM358),$AM358,0))*(1-IF(ISNUMBER($J358),$J358,0)),"") | O358: Glacier Freeze | P358: 0 | Q358: 270 | R358: 75 | S358: 7 | T358: 30 | U358: Sugar + sucralose | V358: Same electrolytes, lower sugar | AA358: Medium | AB358: Reduced sugar Gatorade | AC358: Lower sugar Gatorade electrolytes | AD358: Electrolytes with much less sugar. | AF358: =IF(AND(ISNUMBER($P358),ISNUMBER($AL358),$AL358<>0),ROUND($P358/$AL358*100,1),"") | AG358: =IF(AND(ISNUMBER($S358),ISNUMBER($AL358),$AL358<>0),ROUND($S358/$AL358*100,2),"") | AH358: =IF(AND(ISNUMBER($Q358),ISNUMBER($AL358),$AL358<>0),ROUND($Q358/$AL358*100,1),"") | AI358: =IF(ISNUMBER($S358),IF($S358<=1,"Yes","No"),"n/a") | AJ358: =IF(ISNUMBER($S358),ROUND(MAX(0,MIN(100,100-$S358*2.5-IF(ISNUMBER($T358),$T358,0)*0.12+IF($S358<=1,12,0))),0),"") | AK358: =IF(ISNUMBER($Q358),IF($Q358>=100,20,IF($Q358>=30,10,0)),0)+IF(ISNUMBER($R358),IF($R358>=100,20,0),0)+IF(ISNUMBER($P358),IF($P358>=150,20,IF($P358>=50,12,5)),0)+IF(ISNUMBER($S358),IF($S358<=1,15,0),0) | AL358: 591 | AN358: =IF(AND(ISNUMBER($P358),ISNUMBER($AL358),$AL358<>0),IF(OR($P358>180,$P358/$AL358*1000>400),"Over ceiling, confirm SKU","Within"),"n/a") | AR358: Recalled, batch confirmed, to confirm | AS358: BLANK -> requires live Amazon.ca capture | AT358: Unverified commercial data
A359: Gatorade | B359: Gatorade G2 Low Sugar | Fruit Punch | single 591mL | C359: 2) Electrolyte beverage (RTD) | D359: 591 mL bottle | E359: 1 | G359: =IF(AND(ISNUMBER($F359),ISNUMBER($E359),$E359<>0),$F359/$E359,"") | H359: =IF(AND(ISNUMBER($F359),ISNUMBER($AL359),ISNUMBER($E359),($AL359*$E359)<>0),$F359/($AL359*$E359)*100,"") | K359: =IF(AND(ISNUMBER($F359),ISNUMBER($J359)),$F359*(1-$J359),"") | N359: =IF(ISNUMBER($F359),($F359-IF(ISNUMBER($AM359),$AM359,0))*(1-IF(ISNUMBER($J359),$J359,0)),"") | O359: Fruit Punch | P359: 0 | Q359: 270 | R359: 75 | S359: 7 | T359: 30 | U359: Sugar + sucralose | V359: Same electrolytes, lower sugar | AA359: Medium | AB359: Reduced sugar Gatorade | AC359: Lower sugar Gatorade electrolytes | AD359: Electrolytes with much less sugar. | AF359: =IF(AND(ISNUMBER($P359),ISNUMBER($AL359),$AL359<>0),ROUND($P359/$AL359*100,1),"") | AG359: =IF(AND(ISNUMBER($S359),ISNUMBER($AL359),$AL359<>0),ROUND($S359/$AL359*100,2),"") | AH359: =IF(AND(ISNUMBER($Q359),ISNUMBER($AL359),$AL359<>0),ROUND($Q359/$AL359*100,1),"") | AI359: =IF(ISNUMBER($S359),IF($S359<=1,"Yes","No"),"n/a") | AJ359: =IF(ISNUMBER($S359),ROUND(MAX(0,MIN(100,100-$S359*2.5-IF(ISNUMBER($T359),$T359,0)*0.12+IF($S359<=1,12,0))),0),"") | AK359: =IF(ISNUMBER($Q359),IF($Q359>=100,20,IF($Q359>=30,10,0)),0)+IF(ISNUMBER($R359),IF($R359>=100,20,0),0)+IF(ISNUMBER($P359),IF($P359>=150,20,IF($P359>=50,12,5)),0)+IF(ISNUMBER($S359),IF($S359<=1,15,0),0) | AL359: 591 | AN359: =IF(AND(ISNUMBER($P359),ISNUMBER($AL359),$AL359<>0),IF(OR($P359>180,$P359/$AL359*1000>400),"Over ceiling, confirm SKU","Within"),"n/a") | AR359: Recalled, batch confirmed, to confirm | AS359: BLANK -> requires live Amazon.ca capture | AT359: Unverified commercial data
A360: Gatorade | B360: Gatorade G2 Low Sugar | Fruit Punch | 6 pack 591mL | C360: 2) Electrolyte beverage (RTD) | D360: 591 mL bottle | E360: 6 | G360: =IF(AND(ISNUMBER($F360),ISNUMBER($E360),$E360<>0),$F360/$E360,"") | H360: =IF(AND(ISNUMBER($F360),ISNUMBER($AL360),ISNUMBER($E360),($AL360*$E360)<>0),$F360/($AL360*$E360)*100,"") | K360: =IF(AND(ISNUMBER($F360),ISNUMBER($J360)),$F360*(1-$J360),"") | N360: =IF(ISNUMBER($F360),($F360-IF(ISNUMBER($AM360),$AM360,0))*(1-IF(ISNUMBER($J360),$J360,0)),"") | O360: Fruit Punch | P360: 0 | Q360: 270 | R360: 75 | S360: 7 | T360: 30 | U360: Sugar + sucralose | V360: Same electrolytes, lower sugar | AA360: Medium | AB360: Reduced sugar Gatorade | AC360: Lower sugar Gatorade electrolytes | AD360: Electrolytes with much less sugar. | AF360: =IF(AND(ISNUMBER($P360),ISNUMBER($AL360),$AL360<>0),ROUND($P360/$AL360*100,1),"") | AG360: =IF(AND(ISNUMBER($S360),ISNUMBER($AL360),$AL360<>0),ROUND($S360/$AL360*100,2),"") | AH360: =IF(AND(ISNUMBER($Q360),ISNUMBER($AL360),$AL360<>0),ROUND($Q360/$AL360*100,1),"") | AI360: =IF(ISNUMBER($S360),IF($S360<=1,"Yes","No"),"n/a") | AJ360: =IF(ISNUMBER($S360),ROUND(MAX(0,MIN(100,100-$S360*2.5-IF(ISNUMBER($T360),$T360,0)*0.12+IF($S360<=1,12,0))),0),"") | AK360: =IF(ISNUMBER($Q360),IF($Q360>=100,20,IF($Q360>=30,10,0)),0)+IF(ISNUMBER($R360),IF($R360>=100,20,0),0)+IF(ISNUMBER($P360),IF($P360>=150,20,IF($P360>=50,12,5)),0)+IF(ISNUMBER($S360),IF($S360<=1,15,0),0) | AL360: 591 | AN360: =IF(AND(ISNUMBER($P360),ISNUMBER($AL360),$AL360<>0),IF(OR($P360>180,$P360/$AL360*1000>400),"Over ceiling, confirm SKU","Within"),"n/a") | AR360: Recalled, batch confirmed, to confirm | AS360: BLANK -> requires live Amazon.ca capture | AT360: Unverified commercial data
A361: Gatorade | B361: Gatorade G2 Low Sugar | Fruit Punch | 12 pack 591mL | C361: 2) Electrolyte beverage (RTD) | D361: 591 mL bottle | E361: 12 | G361: =IF(AND(ISNUMBER($F361),ISNUMBER($E361),$E361<>0),$F361/$E361,"") | H361: =IF(AND(ISNUMBER($F361),ISNUMBER($AL361),ISNUMBER($E361),($AL361*$E361)<>0),$F361/($AL361*$E361)*100,"") | K361: =IF(AND(ISNUMBER($F361),ISNUMBER($J361)),$F361*(1-$J361),"") | N361: =IF(ISNUMBER($F361),($F361-IF(ISNUMBER($AM361),$AM361,0))*(1-IF(ISNUMBER($J361),$J361,0)),"") | O361: Fruit Punch | P361: 0 | Q361: 270 | R361: 75 | S361: 7 | T361: 30 | U361: Sugar + sucralose | V361: Same electrolytes, lower sugar | AA361: Medium | AB361: Reduced sugar Gatorade | AC361: Lower sugar Gatorade electrolytes | AD361: Electrolytes with much less sugar. | AF361: =IF(AND(ISNUMBER($P361),ISNUMBER($AL361),$AL361<>0),ROUND($P361/$AL361*100,1),"") | AG361: =IF(AND(ISNUMBER($S361),ISNUMBER($AL361),$AL361<>0),ROUND($S361/$AL361*100,2),"") | AH361: =IF(AND(ISNUMBER($Q361),ISNUMBER($AL361),$AL361<>0),ROUND($Q361/$AL361*100,1),"") | AI361: =IF(ISNUMBER($S361),IF($S361<=1,"Yes","No"),"n/a") | AJ361: =IF(ISNUMBER($S361),ROUND(MAX(0,MIN(100,100-$S361*2.5-IF(ISNUMBER($T361),$T361,0)*0.12+IF($S361<=1,12,0))),0),"") | AK361: =IF(ISNUMBER($Q361),IF($Q361>=100,20,IF($Q361>=30,10,0)),0)+IF(ISNUMBER($R361),IF($R361>=100,20,0),0)+IF(ISNUMBER($P361),IF($P361>=150,20,IF($P361>=50,12,5)),0)+IF(ISNUMBER($S361),IF($S361<=1,15,0),0) | AL361: 591 | AN361: =IF(AND(ISNUMBER($P361),ISNUMBER($AL361),$AL361<>0),IF(OR($P361>180,$P361/$AL361*1000>400),"Over ceiling, confirm SKU","Within"),"n/a") | AR361: Recalled, batch confirmed, to confirm | AS361: BLANK -> requires live Amazon.ca capture | AT361: Unverified commercial data
A362: Gatorade | B362: Gatorade G2 Low Sugar | Fruit Punch | 24 pack 591mL | C362: 2) Electrolyte beverage (RTD) | D362: 591 mL bottle | E362: 24 | G362: =IF(AND(ISNUMBER($F362),ISNUMBER($E362),$E362<>0),$F362/$E362,"") | H362: =IF(AND(ISNUMBER($F362),ISNUMBER($AL362),ISNUMBER($E362),($AL362*$E362)<>0),$F362/($AL362*$E362)*100,"") | K362: =IF(AND(ISNUMBER($F362),ISNUMBER($J362)),$F362*(1-$J362),"") | N362: =IF(ISNUMBER($F362),($F362-IF(ISNUMBER($AM362),$AM362,0))*(1-IF(ISNUMBER($J362),$J362,0)),"") | O362: Fruit Punch | P362: 0 | Q362: 270 | R362: 75 | S362: 7 | T362: 30 | U362: Sugar + sucralose | V362: Same electrolytes, lower sugar | AA362: Medium | AB362: Reduced sugar Gatorade | AC362: Lower sugar Gatorade electrolytes | AD362: Electrolytes with much less sugar. | AF362: =IF(AND(ISNUMBER($P362),ISNUMBER($AL362),$AL362<>0),ROUND($P362/$AL362*100,1),"") | AG362: =IF(AND(ISNUMBER($S362),ISNUMBER($AL362),$AL362<>0),ROUND($S362/$AL362*100,2),"") | AH362: =IF(AND(ISNUMBER($Q362),ISNUMBER($AL362),$AL362<>0),ROUND($Q362/$AL362*100,1),"") | AI362: =IF(ISNUMBER($S362),IF($S362<=1,"Yes","No"),"n/a") | AJ362: =IF(ISNUMBER($S362),ROUND(MAX(0,MIN(100,100-$S362*2.5-IF(ISNUMBER($T362),$T362,0)*0.12+IF($S362<=1,12,0))),0),"") | AK362: =IF(ISNUMBER($Q362),IF($Q362>=100,20,IF($Q362>=30,10,0)),0)+IF(ISNUMBER($R362),IF($R362>=100,20,0),0)+IF(ISNUMBER($P362),IF($P362>=150,20,IF($P362>=50,12,5)),0)+IF(ISNUMBER($S362),IF($S362<=1,15,0),0) | AL362: 591 | AN362: =IF(AND(ISNUMBER($P362),ISNUMBER($AL362),$AL362<>0),IF(OR($P362>180,$P362/$AL362*1000>400),"Over ceiling, confirm SKU","Within"),"n/a") | AR362: Recalled, batch confirmed, to confirm | AS362: BLANK -> requires live Amazon.ca capture | AT362: Unverified commercial data
A363: Gatorade | B363: Gatorade G2 Low Sugar | Grape | single 591mL | C363: 2) Electrolyte beverage (RTD) | D363: 591 mL bottle | E363: 1 | G363: =IF(AND(ISNUMBER($F363),ISNUMBER($E363),$E363<>0),$F363/$E363,"") | H363: =IF(AND(ISNUMBER($F363),ISNUMBER($AL363),ISNUMBER($E363),($AL363*$E363)<>0),$F363/($AL363*$E363)*100,"") | K363: =IF(AND(ISNUMBER($F363),ISNUMBER($J363)),$F363*(1-$J363),"") | N363: =IF(ISNUMBER($F363),($F363-IF(ISNUMBER($AM363),$AM363,0))*(1-IF(ISNUMBER($J363),$J363,0)),"") | O363: Grape | P363: 0 | Q363: 270 | R363: 75 | S363: 7 | T363: 30 | U363: Sugar + sucralose | V363: Same electrolytes, lower sugar | AA363: Medium | AB363: Reduced sugar Gatorade | AC363: Lower sugar Gatorade electrolytes | AD363: Electrolytes with much less sugar. | AF363: =IF(AND(ISNUMBER($P363),ISNUMBER($AL363),$AL363<>0),ROUND($P363/$AL363*100,1),"") | AG363: =IF(AND(ISNUMBER($S363),ISNUMBER($AL363),$AL363<>0),ROUND($S363/$AL363*100,2),"") | AH363: =IF(AND(ISNUMBER($Q363),ISNUMBER($AL363),$AL363<>0),ROUND($Q363/$AL363*100,1),"") | AI363: =IF(ISNUMBER($S363),IF($S363<=1,"Yes","No"),"n/a") | AJ363: =IF(ISNUMBER($S363),ROUND(MAX(0,MIN(100,100-$S363*2.5-IF(ISNUMBER($T363),$T363,0)*0.12+IF($S363<=1,12,0))),0),"") | AK363: =IF(ISNUMBER($Q363),IF($Q363>=100,20,IF($Q363>=30,10,0)),0)+IF(ISNUMBER($R363),IF($R363>=100,20,0),0)+IF(ISNUMBER($P363),IF($P363>=150,20,IF($P363>=50,12,5)),0)+IF(ISNUMBER($S363),IF($S363<=1,15,0),0) | AL363: 591 | AN363: =IF(AND(ISNUMBER($P363),ISNUMBER($AL363),$AL363<>0),IF(OR($P363>180,$P363/$AL363*1000>400),"Over ceiling, confirm SKU","Within"),"n/a") | AR363: Recalled, batch confirmed, to confirm | AS363: BLANK -> requires live Amazon.ca capture | AT363: Unverified commercial data
A364: Gatorade | B364: Gatorade G2 Low Sugar | Grape | 6 pack 591mL | C364: 2) Electrolyte beverage (RTD) | D364: 591 mL bottle | E364: 6 | G364: =IF(AND(ISNUMBER($F364),ISNUMBER($E364),$E364<>0),$F364/$E364,"") | H364: =IF(AND(ISNUMBER($F364),ISNUMBER($AL364),ISNUMBER($E364),($AL364*$E364)<>0),$F364/($AL364*$E364)*100,"") | K364: =IF(AND(ISNUMBER($F364),ISNUMBER($J364)),$F364*(1-$J364),"") | N364: =IF(ISNUMBER($F364),($F364-IF(ISNUMBER($AM364),$AM364,0))*(1-IF(ISNUMBER($J364),$J364,0)),"") | O364: Grape | P364: 0 | Q364: 270 | R364: 75 | S364: 7 | T364: 30 | U364: Sugar + sucralose | V364: Same electrolytes, lower sugar | AA364: Medium | AB364: Reduced sugar Gatorade | AC364: Lower sugar Gatorade electrolytes | AD364: Electrolytes with much less sugar. | AF364: =IF(AND(ISNUMBER($P364),ISNUMBER($AL364),$AL364<>0),ROUND($P364/$AL364*100,1),"") | AG364: =IF(AND(ISNUMBER($S364),ISNUMBER($AL364),$AL364<>0),ROUND($S364/$AL364*100,2),"") | AH364: =IF(AND(ISNUMBER($Q364),ISNUMBER($AL364),$AL364<>0),ROUND($Q364/$AL364*100,1),"") | AI364: =IF(ISNUMBER($S364),IF($S364<=1,"Yes","No"),"n/a") | AJ364: =IF(ISNUMBER($S364),ROUND(MAX(0,MIN(100,100-$S364*2.5-IF(ISNUMBER($T364),$T364,0)*0.12+IF($S364<=1,12,0))),0),"") | AK364: =IF(ISNUMBER($Q364),IF($Q364>=100,20,IF($Q364>=30,10,0)),0)+IF(ISNUMBER($R364),IF($R364>=100,20,0),0)+IF(ISNUMBER($P364),IF($P364>=150,20,IF($P364>=50,12,5)),0)+IF(ISNUMBER($S364),IF($S364<=1,15,0),0) | AL364: 591 | AN364: =IF(AND(ISNUMBER($P364),ISNUMBER($AL364),$AL364<>0),IF(OR($P364>180,$P364/$AL364*1000>400),"Over ceiling, confirm SKU","Within"),"n/a") | AR364: Recalled, batch confirmed, to confirm | AS364: BLANK -> requires live Amazon.ca capture | AT364: Unverified commercial data
A365: Gatorade | B365: Gatorade G2 Low Sugar | Grape | 12 pack 591mL | C365: 2) Electrolyte beverage (RTD) | D365: 591 mL bottle | E365: 12 | G365: =IF(AND(ISNUMBER($F365),ISNUMBER($E365),$E365<>0),$F365/$E365,"") | H365: =IF(AND(ISNUMBER($F365),ISNUMBER($AL365),ISNUMBER($E365),($AL365*$E365)<>0),$F365/($AL365*$E365)*100,"") | K365: =IF(AND(ISNUMBER($F365),ISNUMBER($J365)),$F365*(1-$J365),"") | N365: =IF(ISNUMBER($F365),($F365-IF(ISNUMBER($AM365),$AM365,0))*(1-IF(ISNUMBER($J365),$J365,0)),"") | O365: Grape | P365: 0 | Q365: 270 | R365: 75 | S365: 7 | T365: 30 | U365: Sugar + sucralose | V365: Same electrolytes, lower sugar | AA365: Medium | AB365: Reduced sugar Gatorade | AC365: Lower sugar Gatorade electrolytes | AD365: Electrolytes with much less sugar. | AF365: =IF(AND(ISNUMBER($P365),ISNUMBER($AL365),$AL365<>0),ROUND($P365/$AL365*100,1),"") | AG365: =IF(AND(ISNUMBER($S365),ISNUMBER($AL365),$AL365<>0),ROUND($S365/$AL365*100,2),"") | AH365: =IF(AND(ISNUMBER($Q365),ISNUMBER($AL365),$AL365<>0),ROUND($Q365/$AL365*100,1),"") | AI365: =IF(ISNUMBER($S365),IF($S365<=1,"Yes","No"),"n/a") | AJ365: =IF(ISNUMBER($S365),ROUND(MAX(0,MIN(100,100-$S365*2.5-IF(ISNUMBER($T365),$T365,0)*0.12+IF($S365<=1,12,0))),0),"") | AK365: =IF(ISNUMBER($Q365),IF($Q365>=100,20,IF($Q365>=30,10,0)),0)+IF(ISNUMBER($R365),IF($R365>=100,20,0),0)+IF(ISNUMBER($P365),IF($P365>=150,20,IF($P365>=50,12,5)),0)+IF(ISNUMBER($S365),IF($S365<=1,15,0),0) | AL365: 591 | AN365: =IF(AND(ISNUMBER($P365),ISNUMBER($AL365),$AL365<>0),IF(OR($P365>180,$P365/$AL365*1000>400),"Over ceiling, confirm SKU","Within"),"n/a") | AR365: Recalled, batch confirmed, to confirm | AS365: BLANK -> requires live Amazon.ca capture | AT365: Unverified commercial data
A366: Gatorade | B366: Gatorade G2 Low Sugar | Grape | 24 pack 591mL | C366: 2) Electrolyte beverage (RTD) | D366: 591 mL bottle | E366: 24 | G366: =IF(AND(ISNUMBER($F366),ISNUMBER($E366),$E366<>0),$F366/$E366,"") | H366: =IF(AND(ISNUMBER($F366),ISNUMBER($AL366),ISNUMBER($E366),($AL366*$E366)<>0),$F366/($AL366*$E366)*100,"") | K366: =IF(AND(ISNUMBER($F366),ISNUMBER($J366)),$F366*(1-$J366),"") | N366: =IF(ISNUMBER($F366),($F366-IF(ISNUMBER($AM366),$AM366,0))*(1-IF(ISNUMBER($J366),$J366,0)),"") | O366: Grape | P366: 0 | Q366: 270 | R366: 75 | S366: 7 | T366: 30 | U366: Sugar + sucralose | V366: Same electrolytes, lower sugar | AA366: Medium | AB366: Reduced sugar Gatorade | AC366: Lower sugar Gatorade electrolytes | AD366: Electrolytes with much less sugar. | AF366: =IF(AND(ISNUMBER($P366),ISNUMBER($AL366),$AL366<>0),ROUND($P366/$AL366*100,1),"") | AG366: =IF(AND(ISNUMBER($S366),ISNUMBER($AL366),$AL366<>0),ROUND($S366/$AL366*100,2),"") | AH366: =IF(AND(ISNUMBER($Q366),ISNUMBER($AL366),$AL366<>0),ROUND($Q366/$AL366*100,1),"") | AI366: =IF(ISNUMBER($S366),IF($S366<=1,"Yes","No"),"n/a") | AJ366: =IF(ISNUMBER($S366),ROUND(MAX(0,MIN(100,100-$S366*2.5-IF(ISNUMBER($T366),$T366,0)*0.12+IF($S366<=1,12,0))),0),"") | AK366: =IF(ISNUMBER($Q366),IF($Q366>=100,20,IF($Q366>=30,10,0)),0)+IF(ISNUMBER($R366),IF($R366>=100,20,0),0)+IF(ISNUMBER($P366),IF($P366>=150,20,IF($P366>=50,12,5)),0)+IF(ISNUMBER($S366),IF($S366<=1,15,0),0) | AL366: 591 | AN366: =IF(AND(ISNUMBER($P366),ISNUMBER($AL366),$AL366<>0),IF(OR($P366>180,$P366/$AL366*1000>400),"Over ceiling, confirm SKU","Within"),"n/a") | AR366: Recalled, batch confirmed, to confirm | AS366: BLANK -> requires live Amazon.ca capture | AT366: Unverified commercial data
... A405: Pedialyte | B405: Pedialyte Sport | Cherry | 24 pack 495mL | C405: 2) Electrolyte beverage (RTD) | D405: 495 mL bottle | E405: 24 | G405: =IF(AND(ISNUMBER($F405),ISNUMBER($E405),$E405<>0),$F405/$E405,"") | H405: =IF(AND(ISNUMBER($F405),ISNUMBER($AL405),ISNUMBER($E405),($AL405*$E405)<>0),$F405/($AL405*$E405)*100,"") | K405: =IF(AND(ISNUMBER($F405),ISNUMBER($J405)),$F405*(1-$J405),"") | N405: =IF(ISNUMBER($F405),($F405-IF(ISNUMBER($AM405),$AM405,0))*(1-IF(ISNUMBER($J405),$J405,0)),"") | O405: Cherry | P405: 0 | Q405: 490 | R405: 350 | S405: 11 | T405: 45 | U405: Sugar + sucralose | V405: High electrolyte rapid rehydration for athletes | AA405: Medium | AB405: Sport line of clinical brand | AC405: Clinical grade sport rehydration | AD405: Medical brand electrolytes for sport. | AF405: =IF(AND(ISNUMBER($P405),ISNUMBER($AL405),$AL405<>0),ROUND($P405/$AL405*100,1),"") | AG405: =IF(AND(ISNUMBER($S405),ISNUMBER($AL405),$AL405<>0),ROUND($S405/$AL405*100,2),"") | AH405: =IF(AND(ISNUMBER($Q405),ISNUMBER($AL405),$AL405<>0),ROUND($Q405/$AL405*100,1),"") | AI405: =IF(ISNUMBER($S405),IF($S405<=1,"Yes","No"),"n/a") | AJ405: =IF(ISNUMBER($S405),ROUND(MAX(0,MIN(100,100-$S405*2.5-IF(ISNUMBER($T405),$T405,0)*0.12+IF($S405<=1,12,0))),0),"") | AK405: =IF(ISNUMBER($Q405),IF($Q405>=100,20,IF($Q405>=30,10,0)),0)+IF(ISNUMBER($R405),IF($R405>=100,20,0),0)+IF(ISNUMBER($P405),IF($P405>=150,20,IF($P405>=50,12,5)),0)+IF(ISNUMBER($S405),IF($S405<=1,15,0),0) | AL405: 495 | AN405: =IF(AND(ISNUMBER($P405),ISNUMBER($AL405),$AL405<>0),IF(OR($P405>180,$P405/$AL405*1000>400),"Over ceiling, confirm SKU","Within"),"n/a") | AR405: Retrieved and cited, see Enrichment Log | AS405: BLANK -> requires live Amazon.ca capture | AT405: Unverified commercial data

Sheet M3 Functional Beverage
A1: 1. Brand | B1: 2. Product Line / SKU Name | C1: 3. Category | D1: 4. Format & Size | E1: 5. Pack Count | F1: 6. One Time Price (CAD) | G1: 7. Price / Unit (CAD) | H1: 8. Price / 100 mL (CAD) | I1: 9. S&S Offered (Y/N) | J1: 10. S&S Discount % | K1: 11. S&S Price After Disc. | L1: 12. Coupon on Listing (Y/N + value) | M1: 13. Promotion Text | N1: 14. Lowest Effective Price (stacked) | O1: 15. All Flavours in Listing | P1: 16. Caffeine / Serving (mg) | Q1: 17. Sodium / Serving (mg) | R1: 18. Potassium / Serving (mg) | S1: 19. Sugar / Serving (g) | T1: 20. Calories / Serving | U1: 21. Sweetener Type | V1: 22. Key Functional Claims | W1: 23. Star Rating | X1: 24. Number of Ratings | Y1: 25. Amazon Badge | Z1: 26. Bestseller Rank in Category | AA1: 27a. Est. Weekly Velocity (band) | AB1: 27b. Velocity Signal Used | AC1: 28. Biggest Selling Message | AD1: 29. Why a Shopper Chooses This | AE1: 30. Direct Product URL | AF1: C1. Caffeine /100 mL (mg) | AG1: C2. Sugar /100 mL (g) | AH1: C3. Sodium /100 mL (mg) | AI1: C4. Sugar Free? (<=1 g) | AJ1: C5. Health Score (0 to 100) | AK1: C6. Functional Score (0 to 100) | AL1: H1. Unit Vol (mL) [calc helper] | AM1: H2. Coupon Value (CAD) [calc helper] | AN1: C7. Over Health Canada caffeine ceiling (180 mg per container or 400 mg per litre)? | AO1: 31. Supplemented Food Facts table (Y/N) | AP1: 32. Caution Identifier (Y/N/not required) | AQ1: 33. Bilingual EN and FR panel (Y/N) | AR1: P1. Attribute Provenance | AS1: P2. Commercial Field Status | AT1: P3. Row Flag
A2: OLIPOP | B2: OLIPOP Prebiotic Soda | Vintage Cola | single 355mL | C2: 3) Functional beverage (still/sparkling) | D2: 355 mL can | E2: 1 | G2: =IF(AND(ISNUMBER($F2),ISNUMBER($E2),$E2<>0),$F2/$E2,"") | H2: =IF(AND(ISNUMBER($F2),ISNUMBER($AL2),ISNUMBER($E2),($AL2*$E2)<>0),$F2/($AL2*$E2)*100,"") | K2: =IF(AND(ISNUMBER($F2),ISNUMBER($J2)),$F2*(1-$J2),"") | N2: =IF(ISNUMBER($F2),($F2-IF(ISNUMBER($AM2),$AM2,0))*(1-IF(ISNUMBER($J2),$J2,0)),"") | O2: Vintage Cola | P2: 0 | Q2: 30 | R2: Not listed | S2: 4 | T2: 45 | U2: Stevia + cassava syrup | V2: 9 g prebiotic fiber, gut/digestive health, low sugar (Vintage/Cherry Cola & Doctor Goodwin ~50 mg caffeine, Ridge Rush ~60 mg; other flavours caffeine free) | AA2: Very High | AB2: Category leading prebiotic soda; viral DTC + retail | AC2: Soda nostalgia that's actually good for your gut | AD2: Classic soda taste with 9 g fiber and almost no sugar. | AF2: =IF(AND(ISNUMBER($P2),ISNUMBER($AL2),$AL2<>0),ROUND($P2/$AL2*100,1),"") | AG2: =IF(AND(ISNUMBER($S2),ISNUMBER($AL2),$AL2<>0),ROUND($S2/$AL2*100,2),"") | AH2: =IF(AND(ISNUMBER($Q2),ISNUMBER($AL2),$AL2<>0),ROUND($Q2/$AL2*100,1),"") | AI2: =IF(ISNUMBER($S2),IF($S2<=1,"Yes","No"),"n/a") | AJ2: =IF(ISNUMBER($S2),ROUND(MAX(0,MIN(100,100-$S2*2.5-IF(ISNUMBER($T2),$T2,0)*0.12+IF($S2<=1,12,0))),0),"") | AK2: =IF(ISNUMBER($Q2),IF($Q2>=100,20,IF($Q2>=30,10,0)),0)+IF(ISNUMBER($R2),IF($R2>=100,20,0),0)+IF(ISNUMBER($P2),IF($P2>=150,20,IF($P2>=50,12,5)),0)+IF(ISNUMBER($S2),IF($S2<=1,15,0),0) | AL2: 355 | AN2: =IF(AND(ISNUMBER($P2),ISNUMBER($AL2),$AL2<>0),IF(OR($P2>180,$P2/$AL2*1000>400),"Over ceiling, confirm SKU","Within"),"n/a") | AR2: Retrieved and cited, see Enrichment Log | AS2: BLANK -> requires live Amazon.ca capture | AT2: Unverified commercial data
A3: OLIPOP | B3: OLIPOP Prebiotic Soda | Vintage Cola | 8 pack 355mL | C3: 3) Functional beverage (still/sparkling) | D3: 355 mL can | E3: 8 | G3: =IF(AND(ISNUMBER($F3),ISNUMBER($E3),$E3<>0),$F3/$E3,"") | H3: =IF(AND(ISNUMBER($F3),ISNUMBER($AL3),ISNUMBER($E3),($AL3*$E3)<>0),$F3/($AL3*$E3)*100,"") | K3: =IF(AND(ISNUMBER($F3),ISNUMBER($J3)),$F3*(1-$J3),"") | N3: =IF(ISNUMBER($F3),($F3-IF(ISNUMBER($AM3),$AM3,0))*(1-IF(ISNUMBER($J3),$J3,0)),"") | O3: Vintage Cola | P3: 0 | Q3: 30 | R3: Not listed | S3: 4 | T3: 45 | U3: Stevia + cassava syrup | V3: 9 g prebiotic fiber, gut/digestive health, low sugar (Vintage/Cherry Cola & Doctor Goodwin ~50 mg caffeine, Ridge Rush ~60 mg; other flavours caffeine free) | AA3: Very High | AB3: Category leading prebiotic soda; viral DTC + retail | AC3: Soda nostalgia that's actually good for your gut | AD3: Classic soda taste with 9 g fiber and almost no sugar. | AF3: =IF(AND(ISNUMBER($P3),ISNUMBER($AL3),$AL3<>0),ROUND($P3/$AL3*100,1),"") | AG3: =IF(AND(ISNUMBER($S3),ISNUMBER($AL3),$AL3<>0),ROUND($S3/$AL3*100,2),"") | AH3: =IF(AND(ISNUMBER($Q3),ISNUMBER($AL3),$AL3<>0),ROUND($Q3/$AL3*100,1),"") | AI3: =IF(ISNUMBER($S3),IF($S3<=1,"Yes","No"),"n/a") | AJ3: =IF(ISNUMBER($S3),ROUND(MAX(0,MIN(100,100-$S3*2.5-IF(ISNUMBER($T3),$T3,0)*0.12+IF($S3<=1,12,0))),0),"") | AK3: =IF(ISNUMBER($Q3),IF($Q3>=100,20,IF($Q3>=30,10,0)),0)+IF(ISNUMBER($R3),IF($R3>=100,20,0),0)+IF(ISNUMBER($P3),IF($P3>=150,20,IF($P3>=50,12,5)),0)+IF(ISNUMBER($S3),IF($S3<=1,15,0),0) | AL3: 355 | AN3: =IF(AND(ISNUMBER($P3),ISNUMBER($AL3),$AL3<>0),IF(OR($P3>180,$P3/$AL3*1000>400),"Over ceiling, confirm SKU","Within"),"n/a") | AR3: Retrieved and cited, see Enrichment Log | AS3: BLANK -> requires live Amazon.ca capture | AT3: Unverified commercial data
