Workbook
Name StartDate: Inputs!$C$20
Name WHs: Inputs!$C$21
Name Period: Inputs!$C$22
Name Price: Inputs!$C$25
Name Cost: Inputs!$C$26
Name BaseUnits: Inputs!$C$32
Name DemoCost: Inputs!$C$37
Name EndCapCost: Inputs!$C$41
Name FenceCost: Inputs!$C$42
Name AdvertCost: Inputs!$C$43
Name TPDPct: Inputs!$C$44
Name MdPct: Inputs!$C$45

Sheet README
B2: Costco UK — D93 Portfolio ROI Model
B3: v7.0 · Currency dropdown on every tab
B5: HOW TO USE
B7: 1. Display Currency. Every tab has its own dropdown (GBP / USD / CAD / EUR)
B8: at the top. Switching the dropdown on a tab converts every money cell on
B9: that tab and updates the column headers with the right symbol.
B11: 2. FX rates live in one place — the FX Rate Table on the Inputs sheet.
B12: Edit any rate there and every tab updates.
B14: 3. Tabs are INDEPENDENT. Set them all to the same currency for a consistent
B15: pitch deck view, or set them differently if you want to compare. Summary
B16: automatically adjusts its pull from Forecast if the two tabs disagree.
B18: 4. Inputs themselves stay in GBP — the source of truth for the brand's
... B31: Grey: Reference / structure

Sheet Inputs
B2: INPUTS & ASSUMPTIONS — change any yellow cell
B3: Field | C3: Value | D3: Notes / justification
B5: 1. Display Currency
B6: Display Currency | C6: GBP | D6: Dropdown. Inputs stays in GBP — this selection is informational here. Each display tab has its own currency dropdown that drives that tab.
B7: FX Rate (auto, from table) | C7: =VLOOKUP(C6,B13:D16,3,FALSE) | D7: Reference only — display tabs each look up their own rate.
B8: Currency Symbol (auto) | C8: =VLOOKUP(C6,B13:D16,2,FALSE) | D8: Reference only.
B10: FX Rate Table — edit rates as needed (rate is per 1 GBP)
B12: Code | C12: Symbol | D12: Rate (× GBP)
B13: GBP | C13: £ | D13: 1
B14: USD | C14: $ | D14: 1.27
B15: CAD | C15: C$ | D15: 1.71
B16: EUR | C16: € | D16: 1.17
B18: 2. Product & Distribution
B19: SKU | C19: Bee Propolis Spray 30ml x 2 | D19: Costco UK market test SKU.
B20: Test Start Date (W1) | C20: 46034 | D20: Week-commencing date for W1.
B21: Test Warehouses | C21: 20 | D21: Warehouses in test.
B22: Test Period (Weeks) | C22: 26 | D22: Forecast horizon (26 weeks).
B24: 3. Pricing & Cost (per unit, GBP)
B25: Selling Price (MSRP, £) | C25: 15.99 | D25: Retail per pack.
B26: Cost Price (landed, £) | C26: 7.29 | D26: Brand cost delivered.
B27: Gross Margin per unit (£) | C27: =C25-C26 | D27: Default = SP − Cost.
B28: Gross Margin % | C28: =IFERROR((C25-C26)/C25,0) | D28: Default = GP ÷ SP.
B30: 4. Base Demand (no promo)
B31: Units / Warehouse / Week | C31: 13.79 | D31: Prior 30ml SKU run-rate (500 × 0.8 / 29).
B32: Base Units / Week (all warehouses) | C32: =C31*C21 | D32: Default = per-wh rate × warehouses.
B34: 5. Promo Economics (GBP)
B35: Demo £ / warehouse / week | C35: 199 | D35: Costco demo rate.
B36: Demo cost factor | C36: 1.86 | D36: Overhead multiplier.
B37: Demo Total £ / week | C37: =C35*C21*C36 | D37: Default = rate × wh × factor.
B38: End Cap £ / warehouse / booking | C38: 850 | D38: End cap rental.
B39: End Cap cost factor | C39: 1.86 | D39: Same multiplier.
B40: End Cap booking cycle (weeks) | C40: 2 | D40: Per-week cost = total ÷ this.
B41: End Cap Total £ / week | C41: =C38*C21*C39/C40 | D41: Default = rate × wh × factor ÷ cycle.
B42: Fence £ / week (when active) | C42: 0 | D42: Not currently budgeted.
B43: Advertising £ / week (when active) | C43: 0 | D43: Not currently budgeted.
B44: TPD discount % (of net) | C44: 0.25 | D44: 20% off MSRP ≈ 25% on net.
B45: Markdown discount % | C45: 0.5 | D45: Clearance pricing.
B47: 6. Scenario activity & demand lift
B48: Toggle 1 = promo active, 0 = off. Lift is demand multiplier vs base. Dates auto-fill.
B50: BEST – x2 Demo (Wks 5-6) + TPD
B51: Rationale: Two demo weekends with TPD. Demo lifts ~3x in-week. No end cap, no markdown.
B52: Week | F52: W1 | G52: W2 | H52: W3 | I52: W4 | J52: W5 | K52: W6 | L52: W7 | M52: W8 | N52: W9 | O52: W10 | P52: W11 | Q52: W12 | R52: W13 | S52: W14 | T52: W15 | U52: W16 | V52: W17 | W52: W18 | X52: W19 | Y52: W20 | Z52: W21 | AA52: W22 | AB52: W23 | AC52: W24 | AD52: W25 | AE52: W26
B53: Wk-commencing | F53: =StartDate+7*0 | G53: =StartDate+7*1 | H53: =StartDate+7*2 | I53: =StartDate+7*3 | J53: =StartDate+7*4 | K53: =StartDate+7*5 | L53: =StartDate+7*6 | M53: =StartDate+7*7 | N53: =StartDate+7*8 | O53: =StartDate+7*9 | P53: =StartDate+7*10 | Q53: =StartDate+7*11 | R53: =StartDate+7*12 | S53: =StartDate+7*13 | T53: =StartDate+7*14 | U53: =StartDate+7*15 | V53: =StartDate+7*16 | W53: =StartDate+7*17 | X53: =StartDate+7*18 | Y53: =StartDate+7*19 | Z53: =StartDate+7*20 | AA53: =StartDate+7*21 | AB53: =StartDate+7*22 | AC53: =StartDate+7*23 | AD53: =StartDate+7*24 | AE53: =StartDate+7*25
B54: Demo | F54: 0 | G54: 0 | H54: 0 | I54: 0 | J54: 1 | K54: 1 | L54: 0 | M54: 0 | N54: 0 | O54: 0 | P54: 0 | Q54: 0 | R54: 0 | S54: 0 | T54: 0 | U54: 0 | V54: 0 | W54: 0 | X54: 0 | Y54: 0 | Z54: 0 | AA54: 0 | AB54: 0 | AC54: 0 | AD54: 0 | AE54: 0
B55: End Cap | F55: 0 | G55: 0 | H55: 0 | I55: 0 | J55: 0 | K55: 0 | L55: 0 | M55: 0 | N55: 0 | O55: 0 | P55: 0 | Q55: 0 | R55: 0 | S55: 0 | T55: 0 | U55: 0 | V55: 0 | W55: 0 | X55: 0 | Y55: 0 | Z55: 0 | AA55: 0 | AB55: 0 | AC55: 0 | AD55: 0 | AE55: 0
B56: Fence | F56: 0 | G56: 0 | H56: 0 | I56: 0 | J56: 0 | K56: 0 | L56: 0 | M56: 0 | N56: 0 | O56: 0 | P56: 0 | Q56: 0 | R56: 0 | S56: 0 | T56: 0 | U56: 0 | V56: 0 | W56: 0 | X56: 0 | Y56: 0 | Z56: 0 | AA56: 0 | AB56: 0 | AC56: 0 | AD56: 0 | AE56: 0
B57: TPD | F57: 0 | G57: 0 | H57: 0 | I57: 0 | J57: 1 | K57: 1 | L57: 0 | M57: 0 | N57: 0 | O57: 0 | P57: 0 | Q57: 0 | R57: 0 | S57: 0 | T57: 0 | U57: 0 | V57: 0 | W57: 0 | X57: 0 | Y57: 0 | Z57: 0 | AA57: 0 | AB57: 0 | AC57: 0 | AD57: 0 | AE57: 0
B58: Markdown | F58: 0 | G58: 0 | H58: 0 | I58: 0 | J58: 0 | K58: 0 | L58: 0 | M58: 0 | N58: 0 | O58: 0 | P58: 0 | Q58: 0 | R58: 0 | S58: 0 | T58: 0 | U58: 0 | V58: 0 | W58: 0 | X58: 0 | Y58: 0 | Z58: 0 | AA58: 0 | AB58: 0 | AC58: 0 | AD58: 0 | AE58: 0
B59: Advert | F59: 0 | G59: 0 | H59: 0 | I59: 0 | J59: 0 | K59: 0 | L59: 0 | M59: 0 | N59: 0 | O59: 0 | P59: 0 | Q59: 0 | R59: 0 | S59: 0 | T59: 0 | U59: 0 | V59: 0 | W59: 0 | X59: 0 | Y59: 0 | Z59: 0 | AA59: 0 | AB59: 0 | AC59: 0 | AD59: 0 | AE59: 0
B60: Lift Multiplier (x base) | F60: 1 | G60: 1 | H60: 1 | I60: 1 | J60: 3 | K60: 3 | L60: 1 | M60: 1 | N60: 1 | O60: 1 | P60: 1 | Q60: 1 | R60: 1 | S60: 1 | T60: 1 | U60: 1 | V60: 1 | W60: 1 | X60: 1 | Y60: 1 | Z60: 1 | AA60: 1 | AB60: 1 | AC60: 1 | AD60: 1 | AE60: 1
B62: IDEAL – x2 Demo + End Cap (Wks 5-6) + TPD
B63: Rationale: Demo + end cap + TPD stacked for two weeks. Combined velocity ~3.6x base.
B64: Week | F64: W1 | G64: W2 | H64: W3 | I64: W4 | J64: W5 | K64: W6 | L64: W7 | M64: W8 | N64: W9 | O64: W10 | P64: W11 | Q64: W12 | R64: W13 | S64: W14 | T64: W15 | U64: W16 | V64: W17 | W64: W18 | X64: W19 | Y64: W20 | Z64: W21 | AA64: W22 | AB64: W23 | AC64: W24 | AD64: W25 | AE64: W26
B65: Wk-commencing | F65: =StartDate+7*0 | G65: =StartDate+7*1 | H65: =StartDate+7*2 | I65: =StartDate+7*3 | J65: =StartDate+7*4 | K65: =StartDate+7*5 | L65: =StartDate+7*6 | M65: =StartDate+7*7 | N65: =StartDate+7*8 | O65: =StartDate+7*9 | P65: =StartDate+7*10 | Q65: =StartDate+7*11 | R65: =StartDate+7*12 | S65: =StartDate+7*13 | T65: =StartDate+7*14 | U65: =StartDate+7*15 | V65: =StartDate+7*16 | W65: =StartDate+7*17 | X65: =StartDate+7*18 | Y65: =StartDate+7*19 | Z65: =StartDate+7*20 | AA65: =StartDate+7*21 | AB65: =StartDate+7*22 | AC65: =StartDate+7*23 | AD65: =StartDate+7*24 | AE65: =StartDate+7*25
B66: Demo | F66: 0 | G66: 0 | H66: 0 | I66: 0 | J66: 1 | K66: 1 | L66: 0 | M66: 0 | N66: 0 | O66: 0 | P66: 0 | Q66: 0 | R66: 0 | S66: 0 | T66: 0 | U66: 0 | V66: 0 | W66: 0 | X66: 0 | Y66: 0 | Z66: 0 | AA66: 0 | AB66: 0 | AC66: 0 | AD66: 0 | AE66: 0
B67: End Cap | F67: 0 | G67: 0 | H67: 0 | I67: 0 | J67: 1 | K67: 1 | L67: 0 | M67: 0 | N67: 0 | O67: 0 | P67: 0 | Q67: 0 | R67: 0 | S67: 0 | T67: 0 | U67: 0 | V67: 0 | W67: 0 | X67: 0 | Y67: 0 | Z67: 0 | AA67: 0 | AB67: 0 | AC67: 0 | AD67: 0 | AE67: 0
B68: Fence | F68: 0 | G68: 0 | H68: 0 | I68: 0 | J68: 0 | K68: 0 | L68: 0 | M68: 0 | N68: 0 | O68: 0 | P68: 0 | Q68: 0 | R68: 0 | S68: 0 | T68: 0 | U68: 0 | V68: 0 | W68: 0 | X68: 0 | Y68: 0 | Z68: 0 | AA68: 0 | AB68: 0 | AC68: 0 | AD68: 0 | AE68: 0
B69: TPD | F69: 0 | G69: 0 | H69: 0 | I69: 0 | J69: 1 | K69: 1 | L69: 0 | M69: 0 | N69: 0 | O69: 0 | P69: 0 | Q69: 0 | R69: 0 | S69: 0 | T69: 0 | U69: 0 | V69: 0 | W69: 0 | X69: 0 | Y69: 0 | Z69: 0 | AA69: 0 | AB69: 0 | AC69: 0 | AD69: 0 | AE69: 0
B70: Markdown | F70: 0 | G70: 0 | H70: 0 | I70: 0 | J70: 0 | K70: 0 | L70: 0 | M70: 0 | N70: 0 | O70: 0 | P70: 0 | Q70: 0 | R70: 0 | S70: 0 | T70: 0 | U70: 0 | V70: 0 | W70: 0 | X70: 0 | Y70: 0 | Z70: 0 | AA70: 0 | AB70: 0 | AC70: 0 | AD70: 0 | AE70: 0
B71: Advert | F71: 0 | G71: 0 | H71: 0 | I71: 0 | J71: 0 | K71: 0 | L71: 0 | M71: 0 | N71: 0 | O71: 0 | P71: 0 | Q71: 0 | R71: 0 | S71: 0 | T71: 0 | U71: 0 | V71: 0 | W71: 0 | X71: 0 | Y71: 0 | Z71: 0 | AA71: 0 | AB71: 0 | AC71: 0 | AD71: 0 | AE71: 0
B72: Lift Multiplier (x base) | F72: 1 | G72: 1 | H72: 1 | I72: 1 | J72: 3.6 | K72: 3.6 | L72: 1 | M72: 1 | N72: 1 | O72: 1 | P72: 1 | Q72: 1 | R72: 1 | S72: 1 | T72: 1 | U72: 1 | V72: 1 | W72: 1 | X72: 1 | Y72: 1 | Z72: 1 | AA72: 1 | AB72: 1 | AC72: 1 | AD72: 1 | AE72: 1
B74: WORST – Demo+EndCap+TPD then Markdown (Wks 18-20)
B75: Rationale: Promo plan as IDEAL but residual inventory clears at 50% off over Wks 18-20.
B76: Week | F76: W1 | G76: W2 | H76: W3 | I76: W4 | J76: W5 | K76: W6 | L76: W7 | M76: W8 | N76: W9 | O76: W10 | P76: W11 | Q76: W12 | R76: W13 | S76: W14 | T76: W15 | U76: W16 | V76: W17 | W76: W18 | X76: W19 | Y76: W20 | Z76: W21 | AA76: W22 | AB76: W23 | AC76: W24 | AD76: W25 | AE76: W26
B77: Wk-commencing | F77: =StartDate+7*0 | G77: =StartDate+7*1 | H77: =StartDate+7*2 | I77: =StartDate+7*3 | J77: =StartDate+7*4 | K77: =StartDate+7*5 | L77: =StartDate+7*6 | M77: =StartDate+7*7 | N77: =StartDate+7*8 | O77: =StartDate+7*9 | P77: =StartDate+7*10 | Q77: =StartDate+7*11 | R77: =StartDate+7*12 | S77: =StartDate+7*13 | T77: =StartDate+7*14 | U77: =StartDate+7*15 | V77: =StartDate+7*16 | W77: =StartDate+7*17 | X77: =StartDate+7*18 | Y77: =StartDate+7*19 | Z77: =StartDate+7*20 | AA77: =StartDate+7*21 | AB77: =StartDate+7*22 | AC77: =StartDate+7*23 | AD77: =StartDate+7*24 | AE77: =StartDate+7*25
B78: Demo | F78: 0 | G78: 0 | H78: 0 | I78: 0 | J78: 1 | K78: 1 | L78: 0 | M78: 0 | N78: 0 | O78: 0 | P78: 0 | Q78: 0 | R78: 0 | S78: 0 | T78: 0 | U78: 0 | V78: 0 | W78: 0 | X78: 0 | Y78: 0 | Z78: 0 | AA78: 0 | AB78: 0 | AC78: 0 | AD78: 0 | AE78: 0
B79: End Cap | F79: 0 | G79: 0 | H79: 0 | I79: 0 | J79: 1 | K79: 1 | L79: 0 | M79: 0 | N79: 0 | O79: 0 | P79: 0 | Q79: 0 | R79: 0 | S79: 0 | T79: 0 | U79: 0 | V79: 0 | W79: 0 | X79: 0 | Y79: 0 | Z79: 0 | AA79: 0 | AB79: 0 | AC79: 0 | AD79: 0 | AE79: 0
B80: Fence | F80: 0 | G80: 0 | H80: 0 | I80: 0 | J80: 0 | K80: 0 | L80: 0 | M80: 0 | N80: 0 | O80: 0 | P80: 0 | Q80: 0 | R80: 0 | S80: 0 | T80: 0 | U80: 0 | V80: 0 | W80: 0 | X80: 0 | Y80: 0 | Z80: 0 | AA80: 0 | AB80: 0 | AC80: 0 | AD80: 0 | AE80: 0
B81: TPD | F81: 0 | G81: 0 | H81: 0 | I81: 0 | J81: 1 | K81: 1 | L81: 0 | M81: 0 | N81: 0 | O81: 0 | P81: 0 | Q81: 0 | R81: 0 | S81: 0 | T81: 0 | U81: 0 | V81: 0 | W81: 0 | X81: 0 | Y81: 0 | Z81: 0 | AA81: 0 | AB81: 0 | AC81: 0 | AD81: 0 | AE81: 0
B82: Markdown | F82: 0 | G82: 0 | H82: 0 | I82: 0 | J82: 0 | K82: 0 | L82: 0 | M82: 0 | N82: 0 | O82: 0 | P82: 0 | Q82: 0 | R82: 0 | S82: 0 | T82: 0 | U82: 0 | V82: 0 | W82: 1 | X82: 1 | Y82: 1 | Z82: 0 | AA82: 0 | AB82: 0 | AC82: 0 | AD82: 0 | AE82: 0
B83: Advert | F83: 0 | G83: 0 | H83: 0 | I83: 0 | J83: 0 | K83: 0 | L83: 0 | M83: 0 | N83: 0 | O83: 0 | P83: 0 | Q83: 0 | R83: 0 | S83: 0 | T83: 0 | U83: 0 | V83: 0 | W83: 0 | X83: 0 | Y83: 0 | Z83: 0 | AA83: 0 | AB83: 0 | AC83: 0 | AD83: 0 | AE83: 0
B84: Lift Multiplier (x base) | F84: 1 | G84: 1 | H84: 1 | I84: 1 | J84: 3 | K84: 3 | L84: 1 | M84: 1 | N84: 1 | O84: 1 | P84: 1 | Q84: 1 | R84: 1 | S84: 1 | T84: 1 | U84: 1 | V84: 1 | W84: 1 | X84: 0.3 | Y84: 8.7 | Z84: 1 | AA84: 1 | AB84: 1 | AC84: 1 | AD84: 1 | AE84: 1

Sheet Forecast
B2: ="FORECAST — Weekly P&L by Scenario (Display: "&$G$3&" "&$C$3&")"
B3: Display Currency: | C3: GBP | D3: FX Rate (× GBP): | E3: =VLOOKUP(C3,Inputs!$B$13:$D$16,3,FALSE) | F3: Symbol: | G3: =VLOOKUP(C3,Inputs!$B$13:$D$16,2,FALSE)
B5: BEST – x2 Demo (Wks 5-6) + TPD
B6: Week | F6: W1 | G6: W2 | H6: W3 | I6: W4 | J6: W5 | K6: W6 | L6: W7 | M6: W8 | N6: W9 | O6: W10 | P6: W11 | Q6: W12 | R6: W13 | S6: W14 | T6: W15 | U6: W16 | V6: W17 | W6: W18 | X6: W19 | Y6: W20 | Z6: W21 | AA6: W22 | AB6: W23 | AC6: W24 | AD6: W25 | AE6: W26 | AF6: TOTAL
B7: Wk-commencing | F7: =StartDate+7*0 | G7: =StartDate+7*1 | H7: =StartDate+7*2 | I7: =StartDate+7*3 | J7: =StartDate+7*4 | K7: =StartDate+7*5 | L7: =StartDate+7*6 | M7: =StartDate+7*7 | N7: =StartDate+7*8 | O7: =StartDate+7*9 | P7: =StartDate+7*10 | Q7: =StartDate+7*11 | R7: =StartDate+7*12 | S7: =StartDate+7*13 | T7: =StartDate+7*14 | U7: =StartDate+7*15 | V7: =StartDate+7*16 | W7: =StartDate+7*17 | X7: =StartDate+7*18 | Y7: =StartDate+7*19 | Z7: =StartDate+7*20 | AA7: =StartDate+7*21 | AB7: =StartDate+7*22 | AC7: =StartDate+7*23 | AD7: =StartDate+7*24 | AE7: =StartDate+7*25
B8: POS Units | F8: =ROUND(BaseUnits*Inputs!F60,0) | G8: =ROUND(BaseUnits*Inputs!G60,0) | H8: =ROUND(BaseUnits*Inputs!H60,0) | I8: =ROUND(BaseUnits*Inputs!I60,0) | J8: =ROUND(BaseUnits*Inputs!J60,0) | K8: =ROUND(BaseUnits*Inputs!K60,0) | L8: =ROUND(BaseUnits*Inputs!L60,0) | M8: =ROUND(BaseUnits*Inputs!M60,0) | ... AE8: =ROUND(BaseUnits*Inputs!AE60,0) | AF8: =SUM(F8:AE8)
B9: ="Selling Price ("&$G$3&")" | F9: =Price*$E$3 | G9: =Price*$E$3 | H9: =Price*$E$3 | I9: =Price*$E$3 | J9: =Price*$E$3 | K9: =Price*$E$3 | L9: =Price*$E$3 | M9: =Price*$E$3 | ... AF9: =Price*$E$3
B10: ="Revenue ("&$G$3&")" | F10: =F8*F9 | G10: =G8*G9 | H10: =H8*H9 | I10: =I8*I9 | J10: =J8*J9 | K10: =K8*K9 | L10: =L8*L9 | M10: =M8*M9 | ... AE10: =AE8*AE9 | AF10: =SUM(F10:AE10)
B11: ="Cost Price ("&$G$3&")" | F11: =Cost*$E$3 | G11: =Cost*$E$3 | H11: =Cost*$E$3 | I11: =Cost*$E$3 | J11: =Cost*$E$3 | K11: =Cost*$E$3 | L11: =Cost*$E$3 | M11: =Cost*$E$3 | ... AF11: =Cost*$E$3
B12: ="Raw COGS ("&$G$3&")" | F12: =F8*F11 | G12: =G8*G11 | H12: =H8*H11 | I12: =I8*I11 | J12: =J8*J11 | K12: =K8*K11 | L12: =L8*L11 | M12: =M8*M11 | ... AE12: =AE8*AE11 | AF12: =SUM(F12:AE12)
B13: ="— Demo Spend ("&$G$3&")" | F13: =Inputs!F54*DemoCost*$E$3 | G13: =Inputs!G54*DemoCost*$E$3 | H13: =Inputs!H54*DemoCost*$E$3 | I13: =Inputs!I54*DemoCost*$E$3 | J13: =Inputs!J54*DemoCost*$E$3 | K13: =Inputs!K54*DemoCost*$E$3 | L13: =Inputs!L54*DemoCost*$E$3 | M13: =Inputs!M54*DemoCost*$E$3 | ... AE13: =Inputs!AE54*DemoCost*$E$3 | AF13: =SUM(F13:AE13)
B14: ="— End Cap Spend ("&$G$3&")" | F14: =Inputs!F55*EndCapCost*$E$3 | G14: =Inputs!G55*EndCapCost*$E$3 | H14: =Inputs!H55*EndCapCost*$E$3 | I14: =Inputs!I55*EndCapCost*$E$3 | J14: =Inputs!J55*EndCapCost*$E$3 | K14: =Inputs!K55*EndCapCost*$E$3 | L14: =Inputs!L55*EndCapCost*$E$3 | M14: =Inputs!M55*EndCapCost*$E$3 | ... AE14: =Inputs!AE55*EndCapCost*$E$3 | AF14: =SUM(F14:AE14)
B15: ="— Fence Spend ("&$G$3&")" | F15: =Inputs!F56*FenceCost*$E$3 | G15: =Inputs!G56*FenceCost*$E$3 | H15: =Inputs!H56*FenceCost*$E$3 | I15: =Inputs!I56*FenceCost*$E$3 | J15: =Inputs!J56*FenceCost*$E$3 | K15: =Inputs!K56*FenceCost*$E$3 | L15: =Inputs!L56*FenceCost*$E$3 | M15: =Inputs!M56*FenceCost*$E$3 | ... AE15: =Inputs!AE56*FenceCost*$E$3 | AF15: =SUM(F15:AE15)
B16: ="— TPD Spend ("&$G$3&")" | F16: =Inputs!F57*F8*F9*TPDPct | G16: =Inputs!G57*G8*G9*TPDPct | H16: =Inputs!H57*H8*H9*TPDPct | I16: =Inputs!I57*I8*I9*TPDPct | J16: =Inputs!J57*J8*J9*TPDPct | K16: =Inputs!K57*K8*K9*TPDPct | L16: =Inputs!L57*L8*L9*TPDPct | M16: =Inputs!M57*M8*M9*TPDPct | ... AE16: =Inputs!AE57*AE8*AE9*TPDPct | AF16: =SUM(F16:AE16)
B17: ="— Markdown Spend ("&$G$3&")" | F17: =Inputs!F58*F8*F9*MdPct | G17: =Inputs!G58*G8*G9*MdPct | H17: =Inputs!H58*H8*H9*MdPct | I17: =Inputs!I58*I8*I9*MdPct | J17: =Inputs!J58*J8*J9*MdPct | K17: =Inputs!K58*K8*K9*MdPct | L17: =Inputs!L58*L8*L9*MdPct | M17: =Inputs!M58*M8*M9*MdPct | ... AE17: =Inputs!AE58*AE8*AE9*MdPct | AF17: =SUM(F17:AE17)
B18: ="— Advertising Spend ("&$G$3&")" | F18: =Inputs!F59*AdvertCost*$E$3 | G18: =Inputs!G59*AdvertCost*$E$3 | H18: =Inputs!H59*AdvertCost*$E$3 | I18: =Inputs!I59*AdvertCost*$E$3 | J18: =Inputs!J59*AdvertCost*$E$3 | K18: =Inputs!K59*AdvertCost*$E$3 | L18: =Inputs!L59*AdvertCost*$E$3 | M18: =Inputs!M59*AdvertCost*$E$3 | ... AE18: =Inputs!AE59*AdvertCost*$E$3 | AF18: =SUM(F18:AE18)
B19: ="Total Promo Spend ("&$G$3&")" | F19: =SUM(F13:F18) | G19: =SUM(G13:G18) | H19: =SUM(H13:H18) | I19: =SUM(I13:I18) | J19: =SUM(J13:J18) | K19: =SUM(K13:K18) | L19: =SUM(L13:L18) | M19: =SUM(M13:M18) | ... AE19: =SUM(AE13:AE18) | AF19: =SUM(F19:AE19)
B20: ="Gross Profit ("&$G$3&")" | F20: =F10-F12 | G20: =G10-G12 | H20: =H10-H12 | I20: =I10-I12 | J20: =J10-J12 | K20: =K10-K12 | L20: =L10-L12 | M20: =M10-M12 | ... AE20: =AE10-AE12 | AF20: =SUM(F20:AE20)
B21: ="Net Profit after promo ("&$G$3&")" | F21: =F20-F19 | G21: =G20-G19 | H21: =H20-H19 | I21: =I20-I19 | J21: =J20-J19 | K21: =K20-K19 | L21: =L20-L19 | M21: =M20-M19 | ... AE21: =AE20-AE19 | AF21: =SUM(F21:AE21)
B24: IDEAL – x2 Demo + End Cap (Wks 5-6) + TPD
B25: Week | F25: W1 | G25: W2 | H25: W3 | I25: W4 | J25: W5 | K25: W6 | L25: W7 | M25: W8 | N25: W9 | O25: W10 | P25: W11 | Q25: W12 | R25: W13 | S25: W14 | T25: W15 | U25: W16 | V25: W17 | W25: W18 | X25: W19 | Y25: W20 | Z25: W21 | AA25: W22 | AB25: W23 | AC25: W24 | AD25: W25 | AE25: W26 | AF25: TOTAL
B26: Wk-commencing | F26: =StartDate+7*0 | G26: =StartDate+7*1 | H26: =StartDate+7*2 | I26: =StartDate+7*3 | J26: =StartDate+7*4 | K26: =StartDate+7*5 | L26: =StartDate+7*6 | M26: =StartDate+7*7 | N26: =StartDate+7*8 | O26: =StartDate+7*9 | P26: =StartDate+7*10 | Q26: =StartDate+7*11 | R26: =StartDate+7*12 | S26: =StartDate+7*13 | T26: =StartDate+7*14 | U26: =StartDate+7*15 | V26: =StartDate+7*16 | W26: =StartDate+7*17 | X26: =StartDate+7*18 | Y26: =StartDate+7*19 | Z26: =StartDate+7*20 | AA26: =StartDate+7*21 | AB26: =StartDate+7*22 | AC26: =StartDate+7*23 | AD26: =StartDate+7*24 | AE26: =StartDate+7*25
B27: POS Units | F27: =ROUND(BaseUnits*Inputs!F72,0) | G27: =ROUND(BaseUnits*Inputs!G72,0) | H27: =ROUND(BaseUnits*Inputs!H72,0) | I27: =ROUND(BaseUnits*Inputs!I72,0) | J27: =ROUND(BaseUnits*Inputs!J72,0) | K27: =ROUND(BaseUnits*Inputs!K72,0) | L27: =ROUND(BaseUnits*Inputs!L72,0) | M27: =ROUND(BaseUnits*Inputs!M72,0) | ... AE27: =ROUND(BaseUnits*Inputs!AE72,0) | AF27: =SUM(F27:AE27)
B28: ="Selling Price ("&$G$3&")" | F28: =Price*$E$3 | G28: =Price*$E$3 | H28: =Price*$E$3 | I28: =Price*$E$3 | J28: =Price*$E$3 | K28: =Price*$E$3 | L28: =Price*$E$3 | M28: =Price*$E$3 | ... AF28: =Price*$E$3
B29: ="Revenue ("&$G$3&")" | F29: =F27*F28 | G29: =G27*G28 | H29: =H27*H28 | I29: =I27*I28 | J29: =J27*J28 | K29: =K27*K28 | L29: =L27*L28 | M29: =M27*M28 | ... AE29: =AE27*AE28 | AF29: =SUM(F29:AE29)
B30: ="Cost Price ("&$G$3&")" | F30: =Cost*$E$3 | G30: =Cost*$E$3 | H30: =Cost*$E$3 | I30: =Cost*$E$3 | J30: =Cost*$E$3 | K30: =Cost*$E$3 | L30: =Cost*$E$3 | M30: =Cost*$E$3 | ... AF30: =Cost*$E$3
B31: ="Raw COGS ("&$G$3&")" | F31: =F27*F30 | G31: =G27*G30 | H31: =H27*H30 | I31: =I27*I30 | J31: =J27*J30 | K31: =K27*K30 | L31: =L27*L30 | M31: =M27*M30 | ... AE31: =AE27*AE30 | AF31: =SUM(F31:AE31)
B32: ="— Demo Spend ("&$G$3&")" | F32: =Inputs!F66*DemoCost*$E$3 | G32: =Inputs!G66*DemoCost*$E$3 | H32: =Inputs!H66*DemoCost*$E$3 | I32: =Inputs!I66*DemoCost*$E$3 | J32: =Inputs!J66*DemoCost*$E$3 | K32: =Inputs!K66*DemoCost*$E$3 | L32: =Inputs!L66*DemoCost*$E$3 | M32: =Inputs!M66*DemoCost*$E$3 | ... AE32: =Inputs!AE66*DemoCost*$E$3 | AF32: =SUM(F32:AE32)
B33: ="— End Cap Spend ("&$G$3&")" | F33: =Inputs!F67*EndCapCost*$E$3 | G33: =Inputs!G67*EndCapCost*$E$3 | H33: =Inputs!H67*EndCapCost*$E$3 | I33: =Inputs!I67*EndCapCost*$E$3 | J33: =Inputs!J67*EndCapCost*$E$3 | K33: =Inputs!K67*EndCapCost*$E$3 | L33: =Inputs!L67*EndCapCost*$E$3 | M33: =Inputs!M67*EndCapCost*$E$3 | ... AE33: =Inputs!AE67*EndCapCost*$E$3 | AF33: =SUM(F33:AE33)
B34: ="— Fence Spend ("&$G$3&")" | F34: =Inputs!F68*FenceCost*$E$3 | G34: =Inputs!G68*FenceCost*$E$3 | H34: =Inputs!H68*FenceCost*$E$3 | I34: =Inputs!I68*FenceCost*$E$3 | J34: =Inputs!J68*FenceCost*$E$3 | K34: =Inputs!K68*FenceCost*$E$3 | L34: =Inputs!L68*FenceCost*$E$3 | M34: =Inputs!M68*FenceCost*$E$3 | ... AE34: =Inputs!AE68*FenceCost*$E$3 | AF34: =SUM(F34:AE34)
B35: ="— TPD Spend ("&$G$3&")" | F35: =Inputs!F69*F27*F28*TPDPct | G35: =Inputs!G69*G27*G28*TPDPct | H35: =Inputs!H69*H27*H28*TPDPct | I35: =Inputs!I69*I27*I28*TPDPct | J35: =Inputs!J69*J27*J28*TPDPct | K35: =Inputs!K69*K27*K28*TPDPct | L35: =Inputs!L69*L27*L28*TPDPct | M35: =Inputs!M69*M27*M28*TPDPct | ... AE35: =Inputs!AE69*AE27*AE28*TPDPct | AF35: =SUM(F35:AE35)
B36: ="— Markdown Spend ("&$G$3&")" | F36: =Inputs!F70*F27*F28*MdPct | G36: =Inputs!G70*G27*G28*MdPct | H36: =Inputs!H70*H27*H28*MdPct | I36: =Inputs!I70*I27*I28*MdPct | J36: =Inputs!J70*J27*J28*MdPct | K36: =Inputs!K70*K27*K28*MdPct | L36: =Inputs!L70*L27*L28*MdPct | M36: =Inputs!M70*M27*M28*MdPct | ... AE36: =Inputs!AE70*AE27*AE28*MdPct | AF36: =SUM(F36:AE36)
B37: ="— Advertising Spend ("&$G$3&")" | F37: =Inputs!F71*AdvertCost*$E$3 | G37: =Inputs!G71*AdvertCost*$E$3 | H37: =Inputs!H71*AdvertCost*$E$3 | I37: =Inputs!I71*AdvertCost*$E$3 | J37: =Inputs!J71*AdvertCost*$E$3 | K37: =Inputs!K71*AdvertCost*$E$3 | L37: =Inputs!L71*AdvertCost*$E$3 | M37: =Inputs!M71*AdvertCost*$E$3 | ... AE37: =Inputs!AE71*AdvertCost*$E$3 | AF37: =SUM(F37:AE37)
B38: ="Total Promo Spend ("&$G$3&")" | F38: =SUM(F32:F37) | G38: =SUM(G32:G37) | H38: =SUM(H32:H37) | I38: =SUM(I32:I37) | J38: =SUM(J32:J37) | K38: =SUM(K32:K37) | L38: =SUM(L32:L37) | M38: =SUM(M32:M37) | ... AE38: =SUM(AE32:AE37) | AF38: =SUM(F38:AE38)
B39: ="Gross Profit ("&$G$3&")" | F39: =F29-F31 | G39: =G29-G31 | H39: =H29-H31 | I39: =I29-I31 | J39: =J29-J31 | K39: =K29-K31 | L39: =L29-L31 | M39: =M29-M31 | ... AE39: =AE29-AE31 | AF39: =SUM(F39:AE39)
B40: ="Net Profit after promo ("&$G$3&")" | F40: =F39-F38 | G40: =G39-G38 | H40: =H39-H38 | I40: =I39-I38 | J40: =J39-J38 | K40: =K39-K38 | L40: =L39-L38 | M40: =M39-M38 | ... AE40: =AE39-AE38 | AF40: =SUM(F40:AE40)
B43: WORST – Demo+EndCap+TPD then Markdown (Wks 18-20)
B44: Week | F44: W1 | G44: W2 | H44: W3 | I44: W4 | J44: W5 | K44: W6 | L44: W7 | M44: W8 | N44: W9 | O44: W10 | P44: W11 | Q44: W12 | R44: W13 | S44: W14 | T44: W15 | U44: W16 | V44: W17 | W44: W18 | X44: W19 | Y44: W20 | Z44: W21 | AA44: W22 | AB44: W23 | AC44: W24 | AD44: W25 | AE44: W26 | AF44: TOTAL
B45: Wk-commencing | F45: =StartDate+7*0 | G45: =StartDate+7*1 | H45: =StartDate+7*2 | I45: =StartDate+7*3 | J45: =StartDate+7*4 | K45: =StartDate+7*5 | L45: =StartDate+7*6 | M45: =StartDate+7*7 | N45: =StartDate+7*8 | O45: =StartDate+7*9 | P45: =StartDate+7*10 | Q45: =StartDate+7*11 | R45: =StartDate+7*12 | S45: =StartDate+7*13 | T45: =StartDate+7*14 | U45: =StartDate+7*15 | V45: =StartDate+7*16 | W45: =StartDate+7*17 | X45: =StartDate+7*18 | Y45: =StartDate+7*19 | Z45: =StartDate+7*20 | AA45: =StartDate+7*21 | AB45: =StartDate+7*22 | AC45: =StartDate+7*23 | AD45: =StartDate+7*24 | AE45: =StartDate+7*25
B46: POS Units | F46: =ROUND(BaseUnits*Inputs!F84,0) | G46: =ROUND(BaseUnits*Inputs!G84,0) | H46: =ROUND(BaseUnits*Inputs!H84,0) | I46: =ROUND(BaseUnits*Inputs!I84,0) | J46: =ROUND(BaseUnits*Inputs!J84,0) | K46: =ROUND(BaseUnits*Inputs!K84,0) | L46: =ROUND(BaseUnits*Inputs!L84,0) | M46: =ROUND(BaseUnits*Inputs!M84,0) | ... AE46: =ROUND(BaseUnits*Inputs!AE84,0) | AF46: =SUM(F46:AE46)
B47: ="Selling Price ("&$G$3&")" | F47: =Price*$E$3 | G47: =Price*$E$3 | H47: =Price*$E$3 | I47: =Price*$E$3 | J47: =Price*$E$3 | K47: =Price*$E$3 | L47: =Price*$E$3 | M47: =Price*$E$3 | ... AF47: =Price*$E$3
B48: ="Revenue ("&$G$3&")" | F48: =F46*F47 | G48: =G46*G47 | H48: =H46*H47 | I48: =I46*I47 | J48: =J46*J47 | K48: =K46*K47 | L48: =L46*L47 | M48: =M46*M47 | ... AE48: =AE46*AE47 | AF48: =SUM(F48:AE48)
B49: ="Cost Price ("&$G$3&")" | F49: =Cost*$E$3 | G49: =Cost*$E$3 | H49: =Cost*$E$3 | I49: =Cost*$E$3 | J49: =Cost*$E$3 | K49: =Cost*$E$3 | L49: =Cost*$E$3 | M49: =Cost*$E$3 | ... AF49: =Cost*$E$3
B50: ="Raw COGS ("&$G$3&")" | F50: =F46*F49 | G50: =G46*G49 | H50: =H46*H49 | I50: =I46*I49 | J50: =J46*J49 | K50: =K46*K49 | L50: =L46*L49 | M50: =M46*M49 | ... AE50: =AE46*AE49 | AF50: =SUM(F50:AE50)
B51: ="— Demo Spend ("&$G$3&")" | F51: =Inputs!F78*DemoCost*$E$3 | G51: =Inputs!G78*DemoCost*$E$3 | H51: =Inputs!H78*DemoCost*$E$3 | I51: =Inputs!I78*DemoCost*$E$3 | J51: =Inputs!J78*DemoCost*$E$3 | K51: =Inputs!K78*DemoCost*$E$3 | L51: =Inputs!L78*DemoCost*$E$3 | M51: =Inputs!M78*DemoCost*$E$3 | ... AE51: =Inputs!AE78*DemoCost*$E$3 | AF51: =SUM(F51:AE51)
B52: ="— End Cap Spend ("&$G$3&")" | F52: =Inputs!F79*EndCapCost*$E$3 | G52: =Inputs!G79*EndCapCost*$E$3 | H52: =Inputs!H79*EndCapCost*$E$3 | I52: =Inputs!I79*EndCapCost*$E$3 | J52: =Inputs!J79*EndCapCost*$E$3 | K52: =Inputs!K79*EndCapCost*$E$3 | L52: =Inputs!L79*EndCapCost*$E$3 | M52: =Inputs!M79*EndCapCost*$E$3 | ... AE52: =Inputs!AE79*EndCapCost*$E$3 | AF52: =SUM(F52:AE52)
B53: ="— Fence Spend ("&$G$3&")" | F53: =Inputs!F80*FenceCost*$E$3 | G53: =Inputs!G80*FenceCost*$E$3 | H53: =Inputs!H80*FenceCost*$E$3 | I53: =Inputs!I80*FenceCost*$E$3 | J53: =Inputs!J80*FenceCost*$E$3 | K53: =Inputs!K80*FenceCost*$E$3 | L53: =Inputs!L80*FenceCost*$E$3 | M53: =Inputs!M80*FenceCost*$E$3 | ... AE53: =Inputs!AE80*FenceCost*$E$3 | AF53: =SUM(F53:AE53)
B54: ="— TPD Spend ("&$G$3&")" | F54: =Inputs!F81*F46*F47*TPDPct | G54: =Inputs!G81*G46*G47*TPDPct | H54: =Inputs!H81*H46*H47*TPDPct | I54: =Inputs!I81*I46*I47*TPDPct | J54: =Inputs!J81*J46*J47*TPDPct | K54: =Inputs!K81*K46*K47*TPDPct | L54: =Inputs!L81*L46*L47*TPDPct | M54: =Inputs!M81*M46*M47*TPDPct | ... AE54: =Inputs!AE81*AE46*AE47*TPDPct | AF54: =SUM(F54:AE54)
B55: ="— Markdown Spend ("&$G$3&")" | F55: =Inputs!F82*F46*F47*MdPct | G55: =Inputs!G82*G46*G47*MdPct | H55: =Inputs!H82*H46*H47*MdPct | I55: =Inputs!I82*I46*I47*MdPct | J55: =Inputs!J82*J46*J47*MdPct | K55: =Inputs!K82*K46*K47*MdPct | L55: =Inputs!L82*L46*L47*MdPct | M55: =Inputs!M82*M46*M47*MdPct | ... AE55: =Inputs!AE82*AE46*AE47*MdPct | AF55: =SUM(F55:AE55)
B56: ="— Advertising Spend ("&$G$3&")" | F56: =Inputs!F83*AdvertCost*$E$3 | G56: =Inputs!G83*AdvertCost*$E$3 | H56: =Inputs!H83*AdvertCost*$E$3 | I56: =Inputs!I83*AdvertCost*$E$3 | J56: =Inputs!J83*AdvertCost*$E$3 | K56: =Inputs!K83*AdvertCost*$E$3 | L56: =Inputs!L83*AdvertCost*$E$3 | M56: =Inputs!M83*AdvertCost*$E$3 | ... AE56: =Inputs!AE83*AdvertCost*$E$3 | AF56: =SUM(F56:AE56)
B57: ="Total Promo Spend ("&$G$3&")" | F57: =SUM(F51:F56) | G57: =SUM(G51:G56) | H57: =SUM(H51:H56) | I57: =SUM(I51:I56) | J57: =SUM(J51:J56) | K57: =SUM(K51:K56) | L57: =SUM(L51:L56) | M57: =SUM(M51:M56) | ... AE57: =SUM(AE51:AE56) | AF57: =SUM(F57:AE57)
B58: ="Gross Profit ("&$G$3&")" | F58: =F48-F50 | G58: =G48-G50 | H58: =H48-H50 | I58: =I48-I50 | J58: =J48-J50 | K58: =K48-K50 | L58: =L48-L50 | M58: =M48-M50 | ... AE58: =AE48-AE50 | AF58: =SUM(F58:AE58)
B59: ="Net Profit after promo ("&$G$3&")" | F59: =F58-F57 | G59: =G58-G57 | H59: =H58-H57 | I59: =I58-I57 | J59: =J58-J57 | K59: =K58-K57 | L59: =L58-L57 | M59: =M58-M57 | ... AE59: =AE58-AE57 | AF59: =SUM(F59:AE59)

Sheet Summary
B2: ="ROI SUMMARY — Bee Propolis Scenario Comparison (Display: "&$G$3&" "&$C$3&")"
B3: Display Currency: | C3: GBP | D3: FX Rate (× GBP): | E3: =VLOOKUP(C3,Inputs!$B$13:$D$16,3,FALSE) | F3: Symbol: | G3: =VLOOKUP(C3,Inputs!$B$13:$D$16,2,FALSE)
B4: ="Test window: W1 ("&TEXT(StartDate,"dd-mmm-yyyy")&") → W"&Period&" ("&TEXT(StartDate+7*(Period-1),"dd-mmm-yyyy")&")"
B6: Metric | C6: BEST | D6: IDEAL | E6: WORST
B7: Units Sold | C7: =Forecast!AF8 | D7: =Forecast!AF27 | E7: =Forecast!AF46
B8: ="Revenue ("&$G$3&")" | C8: =Forecast!AF10*($E$3/Forecast!$E$3) | D8: =Forecast!AF29*($E$3/Forecast!$E$3) | E8: =Forecast!AF48*($E$3/Forecast!$E$3)
B9: ="Raw COGS ("&$G$3&")" | C9: =Forecast!AF12*($E$3/Forecast!$E$3) | D9: =Forecast!AF31*($E$3/Forecast!$E$3) | E9: =Forecast!AF50*($E$3/Forecast!$E$3)
B10: ="Gross Profit ("&$G$3&")" | C10: =Forecast!AF20*($E$3/Forecast!$E$3) | D10: =Forecast!AF39*($E$3/Forecast!$E$3) | E10: =Forecast!AF58*($E$3/Forecast!$E$3)
B11: Gross Margin % | C11: =IFERROR(Forecast!AF20/Forecast!AF10,0) | D11: =IFERROR(Forecast!AF39/Forecast!AF29,0) | E11: =IFERROR(Forecast!AF58/Forecast!AF48,0)
B12: ="Demo Spend ("&$G$3&")" | C12: =Forecast!AF13*($E$3/Forecast!$E$3) | D12: =Forecast!AF32*($E$3/Forecast!$E$3) | E12: =Forecast!AF51*($E$3/Forecast!$E$3)
B13: ="End Cap Spend ("&$G$3&")" | C13: =Forecast!AF14*($E$3/Forecast!$E$3) | D13: =Forecast!AF33*($E$3/Forecast!$E$3) | E13: =Forecast!AF52*($E$3/Forecast!$E$3)
B14: ="Fence Spend ("&$G$3&")" | C14: =Forecast!AF15*($E$3/Forecast!$E$3) | D14: =Forecast!AF34*($E$3/Forecast!$E$3) | E14: =Forecast!AF53*($E$3/Forecast!$E$3)
B15: ="TPD Spend ("&$G$3&")" | C15: =Forecast!AF16*($E$3/Forecast!$E$3) | D15: =Forecast!AF35*($E$3/Forecast!$E$3) | E15: =Forecast!AF54*($E$3/Forecast!$E$3)
B16: ="Markdown Spend ("&$G$3&")" | C16: =Forecast!AF17*($E$3/Forecast!$E$3) | D16: =Forecast!AF36*($E$3/Forecast!$E$3) | E16: =Forecast!AF55*($E$3/Forecast!$E$3)
B17: ="Advertising Spend ("&$G$3&")" | C17: =Forecast!AF18*($E$3/Forecast!$E$3) | D17: =Forecast!AF37*($E$3/Forecast!$E$3) | E17: =Forecast!AF56*($E$3/Forecast!$E$3)
B18: ="Total Promo Spend ("&$G$3&")" | C18: =Forecast!AF19*($E$3/Forecast!$E$3) | D18: =Forecast!AF38*($E$3/Forecast!$E$3) | E18: =Forecast!AF57*($E$3/Forecast!$E$3)
B19: ="Net Profit ("&$G$3&")" | C19: =Forecast!AF21*($E$3/Forecast!$E$3) | D19: =Forecast!AF40*($E$3/Forecast!$E$3) | E19: =Forecast!AF59*($E$3/Forecast!$E$3)
B20: Net Margin % | C20: =IFERROR(Forecast!AF21/Forecast!AF10,0) | D20: =IFERROR(Forecast!AF40/Forecast!AF29,0) | E20: =IFERROR(Forecast!AF59/Forecast!AF48,0)
B21: ROI on Promo Spend | C21: =IFERROR(Forecast!AF21/Forecast!AF19,0) | D21: =IFERROR(Forecast!AF40/Forecast!AF38,0) | E21: =IFERROR(Forecast!AF59/Forecast!AF57,0)
B22: Avg Units / WH / Week | C22: =IFERROR(Forecast!AF8/WHs/Period,0) | D22: =IFERROR(Forecast!AF27/WHs/Period,0) | E22: =IFERROR(Forecast!AF46/WHs/Period,0)
B25: Why each scenario?
B26: BEST | C26: Two demo weekends with TPD. Demo lifts ~3x in-week. No end cap, no markdown.
B27: IDEAL | C27: Demo + end cap + TPD stacked for two weeks. Combined velocity ~3.6x base.
B28: WORST | C28: Promo plan as IDEAL but residual inventory clears at 50% off over Wks 18-20.

Sheet Portfolio
B2: ="PORTFOLIO — D93 Pitch SKUs · Annual Y1 Roll-Up (Display: "&$G$3&" "&$C$3&")"
B3: Display Currency: | C3: GBP | D3: FX Rate (× GBP): | E3: =VLOOKUP(C3,Inputs!$B$13:$D$16,3,FALSE) | F3: Symbol: | G3: =VLOOKUP(C3,Inputs!$B$13:$D$16,2,FALSE)
B4: SP / Cost / Promo are entered in the currently-selected display currency. Bee Propolis pre-filled; fill SKUs 2-7 from Asana into the yellow cells. Bottom row blends across SKUs.
B6: # | C6: Code | D6: SKU | E6: Pack | F6: ="SP ("&$G$3&")" | G6: ="Cost ("&$G$3&")" | H6: ="GM/u ("&$G$3&")" | I6: GM % | J6: Y1 Units | K6: ="Revenue ("&$G$3&")" | L6: ="COGS ("&$G$3&")" | M6: ="GP ("&$G$3&")" | N6: ="Promo ("&$G$3&")" | O6: ="Net Profit ("&$G$3&")" | P6: Net % | Q6: ROI % | R6: Rationale / status
B7: 1 | C7: UK-D93-#1 | D7: Bee Propolis Spray 30ml x2 | E7: 30ml x 2 | F7: 15.99 | G7: 7.29 | H7: =IFERROR(F7-G7,0) | I7: =IFERROR((F7-G7)/F7,0) | J7: 17000 | K7: =IFERROR(J7*F7,0) | L7: =IFERROR(J7*G7,0) | M7: =IFERROR(K7-L7,0) | N7: 25000 | O7: =IFERROR(M7-N7,0) | P7: =IFERROR(O7/K7,0) | Q7: =IFERROR(O7/N7,0) | R7: Lead pitch — strong GP%, supported by demo + TPD.
B8: 2 | C8: UK-D93-#2 | D8: Mag 8-in-1 90's/120's | H8: =IFERROR(F8-G8,0) | I8: =IFERROR((F8-G8)/F8,0) | K8: =IFERROR(J8*F8,0) | L8: =IFERROR(J8*G8,0) | M8: =IFERROR(K8-L8,0) | O8: =IFERROR(M8-N8,0) | P8: =IFERROR(O8/K8,0) | Q8: =IFERROR(O8/N8,0)
B9: 3 | C9: UK-D93-#3 | D9: O1 450g | H9: =IFERROR(F9-G9,0) | I9: =IFERROR((F9-G9)/F9,0) | K9: =IFERROR(J9*F9,0) | L9: =IFERROR(J9*G9,0) | M9: =IFERROR(K9-L9,0) | O9: =IFERROR(M9-N9,0) | P9: =IFERROR(O9/K9,0) | Q9: =IFERROR(O9/N9,0)
B10: 4 | C10: UK-D93-#4 | D10: Belli Bliss Raspberry, 450g | H10: =IFERROR(F10-G10,0) | I10: =IFERROR((F10-G10)/F10,0) | K10: =IFERROR(J10*F10,0) | L10: =IFERROR(J10*G10,0) | M10: =IFERROR(K10-L10,0) | O10: =IFERROR(M10-N10,0) | P10: =IFERROR(O10/K10,0) | Q10: =IFERROR(O10/N10,0)
B11: 5 | C11: UK-D93-#5 | D11: Daily Boost | H11: =IFERROR(F11-G11,0) | I11: =IFERROR((F11-G11)/F11,0) | K11: =IFERROR(J11*F11,0) | L11: =IFERROR(J11*G11,0) | M11: =IFERROR(K11-L11,0) | O11: =IFERROR(M11-N11,0) | P11: =IFERROR(O11/K11,0) | Q11: =IFERROR(O11/N11,0)
B12: 6 | C12: UK-D93-#6 | D12: Berberine 90's/120's | H12: =IFERROR(F12-G12,0) | I12: =IFERROR((F12-G12)/F12,0) | K12: =IFERROR(J12*F12,0) | L12: =IFERROR(J12*G12,0) | M12: =IFERROR(K12-L12,0) | O12: =IFERROR(M12-N12,0) | P12: =IFERROR(O12/K12,0) | Q12: =IFERROR(O12/N12,0)
B13: 7 | C13: UK-D93-#7 | D13: L-theanine Capsules 90's/120's | H13: =IFERROR(F13-G13,0) | I13: =IFERROR((F13-G13)/F13,0) | K13: =IFERROR(J13*F13,0) | L13: =IFERROR(J13*G13,0) | M13: =IFERROR(K13-L13,0) | O13: =IFERROR(M13-N13,0) | P13: =IFERROR(O13/K13,0) | Q13: =IFERROR(O13/N13,0)
D14: PORTFOLIO TOTAL / BLENDED | I14: =IFERROR(SUM(M7:M13)/SUM(K7:K13),0) | J14: =SUM(J7:J13) | K14: =SUM(K7:K13) | L14: =SUM(L7:L13) | M14: =SUM(M7:M13) | N14: =SUM(N7:N13) | O14: =SUM(O7:O13) | P14: =IFERROR(O14/K14,0) | Q14: =IFERROR(O14/N14,0) | R14: Blended across SKUs
