Workbook

Sheet README
B2: Costco UK – Bee Propolis Spray 30ml x 2 Pack
B3: Market Test ROI Model – v3.0
B5: HOW TO USE THIS MODEL
B6: INSTRUCTIONS
B8: 1. Open the 'Inputs' sheet. Only the YELLOW cells are editable – everything else is calculated.
B10: 2. Inputs are grouped into four blocks:
B11: • Product & Distribution – SKU, Test Start Date (Week 1), warehouses, test horizon.
B12: • Pricing & Cost – selling price, landed cost (gross margin recalculates automatically).
B13: • Base Demand – organic units sold per warehouse per week with no promo support.
B14: • Promo Economics – cost per warehouse for Demo / End Cap / Fence / Advertising, plus the TPD and Markdown discount %.
B16: 3. OVERRIDES (column D). Any cell with a yellow 'Override (opt.)' next to it can be hand-set: leave blank to use the calculated value, or type a number to force a specific value. This applies to Gross Margin/unit, GM %, Base Units/Week, Demo Total £/Week, and End Cap Total £/Week.
B18: 4. DATES. Set the 'Test Start Date (Week 1)' on Inputs and every week column on every sheet shows the week-commencing date automatically. Change one cell, everything updates.
... B40: Light Blue: Summary KPI

Sheet Inputs
B2: INPUTS & ASSUMPTIONS — change yellow cells only
B3: Field | C3: Value | D3: Override (opt.) | E3: Notes / justification
B5: 1. Product & Distribution
B6: SKU | C6: Bee Propolis Spray 30ml x 2 | E6: Costco UK market test SKU.
B7: Test Start Date (Week 1) | C7: 46034 | E7: Week-commencing date of W1. Every week header on every sheet uses this as the anchor.
B8: Test Warehouses | C8: 20 | E8: Number of Costco UK warehouses included in the market test.
B9: Test Period (Weeks) | C9: 26 | E9: Forecast horizon. Model is built for 26 weeks (W1 through W26).
B11: 2. Pricing & Cost (per unit, £)
B12: Selling Price (MSRP) | C12: 15.99 | E12: Retail price to member per 30ml x 2 pack.
B13: Cost Price (landed) | C13: 7.29 | E13: Brand's cost to Costco delivered to depot.
B14: Gross Margin per unit | C14: =IF(D14="",C12-C13,D14) | E14: Calculated: Selling Price - Cost Price. Override is display-only (Forecast uses SP and Cost directly).
B15: Gross Margin % | C15: =IF(D15="",IFERROR((C12-C13)/C12,0),D15) | E15: Calculated: GP/SP. Healthy supplements benchmark 45-60%. Override is display-only.
B17: 3. Base Demand (no promo support)
B18: Units / Warehouse / Week | C18: 13.79 | E18: Equivalent to original '500 × 0.8 / 29' from prior 30ml SKU test (500 lifetime units × 80% sell-through over a 29-week reference window).
B19: Base Units / Week (all warehouses) | C19: =IF(D19="",C18*$C$8,D19) | E19: Calculated: Per-warehouse rate × number of warehouses. OVERRIDE to set the all-warehouse weekly base directly (flows into Forecast).
B21: 4. Promo Economics
B22: Demo £ / warehouse / week | C22: 199 | E22: Costco UK standard demo rate per warehouse per weekend.
B23: Demo cost factor (overhead × staffing) | C23: 1.86 | E23: Multiplier on raw demo fee to capture staffing, POS print & overhead.
B24: Demo Total £ / week | C24: =IF(D24="",C22*$C$8*C23,D24) | E24: Calculated: rate × warehouses × cost factor. OVERRIDE to set the all-warehouse demo £/week directly.
B25: End Cap £ / warehouse / 2-week cycle | C25: 850 | E25: Costco UK standard end cap rental per warehouse for a 2-week placement.
B26: End Cap cost factor | C26: 1.86 | E26: Same overhead multiplier as demo.
B27: End Cap Total £ / week | C27: =IF(D27="",C25*$C$8*C26/2,D27) | E27: Calculated: rate × warehouses × factor ÷ 2 (booked over 2 weeks). OVERRIDE to set the all-warehouse end-cap £/week directly.
B28: Fence £ / week (when active) | C28: 0 | E28: Optional fence display. Currently not budgeted.
B29: Advertising £ / week (when active) | C29: 0 | E29: External media / coupon insert support. Currently not budgeted.
B30: TPD discount % | C30: 0.25 | E30: Standard TPD: 20% off MSRP. Grossed up by 0.8 retail margin → 25% deduction on net.
B31: Markdown discount % | C31: 0.5 | E31: Clearance pricing in worst-case markdown weeks.
B33: 5. Scenario Activity & Demand Lift (1 = promo active, 0 = off; Lift = demand multiplier vs base; Dates auto-fill)
B35: BEST – x2 Demo (Wks 5-6) + TPD
B36: Rationale: Two national demo weekends combined with a TPD price promo. Demo lifts unit velocity ~3x in-week (Costco benchmark for supplements). No end cap booked, no markdown needed.
B37: Week | F37: W1 | G37: W2 | H37: W3 | I37: W4 | J37: W5 | K37: W6 | L37: W7 | M37: W8 | N37: W9 | O37: W10 | P37: W11 | Q37: W12 | R37: W13 | S37: W14 | T37: W15 | U37: W16 | V37: W17 | W37: W18 | X37: W19 | Y37: W20 | Z37: W21 | AA37: W22 | AB37: W23 | AC37: W24 | AD37: W25 | AE37: W26
B38: Wk-commencing | F38: =Inputs!$C$7+7*0 | G38: =Inputs!$C$7+7*1 | H38: =Inputs!$C$7+7*2 | I38: =Inputs!$C$7+7*3 | J38: =Inputs!$C$7+7*4 | K38: =Inputs!$C$7+7*5 | L38: =Inputs!$C$7+7*6 | M38: =Inputs!$C$7+7*7 | N38: =Inputs!$C$7+7*8 | O38: =Inputs!$C$7+7*9 | P38: =Inputs!$C$7+7*10 | Q38: =Inputs!$C$7+7*11 | R38: =Inputs!$C$7+7*12 | S38: =Inputs!$C$7+7*13 | T38: =Inputs!$C$7+7*14 | U38: =Inputs!$C$7+7*15 | V38: =Inputs!$C$7+7*16 | W38: =Inputs!$C$7+7*17 | X38: =Inputs!$C$7+7*18 | Y38: =Inputs!$C$7+7*19 | Z38: =Inputs!$C$7+7*20 | AA38: =Inputs!$C$7+7*21 | AB38: =Inputs!$C$7+7*22 | AC38: =Inputs!$C$7+7*23 | AD38: =Inputs!$C$7+7*24 | AE38: =Inputs!$C$7+7*25
B39: Demo | F39: 0 | G39: 0 | H39: 0 | I39: 0 | J39: 1 | K39: 1 | L39: 0 | M39: 0 | N39: 0 | O39: 0 | P39: 0 | Q39: 0 | R39: 0 | S39: 0 | T39: 0 | U39: 0 | V39: 0 | W39: 0 | X39: 0 | Y39: 0 | Z39: 0 | AA39: 0 | AB39: 0 | AC39: 0 | AD39: 0 | AE39: 0
B40: End Cap | F40: 0 | G40: 0 | H40: 0 | I40: 0 | J40: 0 | K40: 0 | L40: 0 | M40: 0 | N40: 0 | O40: 0 | P40: 0 | Q40: 0 | R40: 0 | S40: 0 | T40: 0 | U40: 0 | V40: 0 | W40: 0 | X40: 0 | Y40: 0 | Z40: 0 | AA40: 0 | AB40: 0 | AC40: 0 | AD40: 0 | AE40: 0
B41: Fence | F41: 0 | G41: 0 | H41: 0 | I41: 0 | J41: 0 | K41: 0 | L41: 0 | M41: 0 | N41: 0 | O41: 0 | P41: 0 | Q41: 0 | R41: 0 | S41: 0 | T41: 0 | U41: 0 | V41: 0 | W41: 0 | X41: 0 | Y41: 0 | Z41: 0 | AA41: 0 | AB41: 0 | AC41: 0 | AD41: 0 | AE41: 0
B42: TPD | F42: 0 | G42: 0 | H42: 0 | I42: 0 | J42: 1 | K42: 1 | L42: 0 | M42: 0 | N42: 0 | O42: 0 | P42: 0 | Q42: 0 | R42: 0 | S42: 0 | T42: 0 | U42: 0 | V42: 0 | W42: 0 | X42: 0 | Y42: 0 | Z42: 0 | AA42: 0 | AB42: 0 | AC42: 0 | AD42: 0 | AE42: 0
B43: Markdown | F43: 0 | G43: 0 | H43: 0 | I43: 0 | J43: 0 | K43: 0 | L43: 0 | M43: 0 | N43: 0 | O43: 0 | P43: 0 | Q43: 0 | R43: 0 | S43: 0 | T43: 0 | U43: 0 | V43: 0 | W43: 0 | X43: 0 | Y43: 0 | Z43: 0 | AA43: 0 | AB43: 0 | AC43: 0 | AD43: 0 | AE43: 0
B44: Advert | F44: 0 | G44: 0 | H44: 0 | I44: 0 | J44: 0 | K44: 0 | L44: 0 | M44: 0 | N44: 0 | O44: 0 | P44: 0 | Q44: 0 | R44: 0 | S44: 0 | T44: 0 | U44: 0 | V44: 0 | W44: 0 | X44: 0 | Y44: 0 | Z44: 0 | AA44: 0 | AB44: 0 | AC44: 0 | AD44: 0 | AE44: 0
B45: Lift Multiplier (x base) | F45: 1 | G45: 1 | H45: 1 | I45: 1 | J45: 3 | K45: 3 | L45: 1 | M45: 1 | N45: 1 | O45: 1 | P45: 1 | Q45: 1 | R45: 1 | S45: 1 | T45: 1 | U45: 1 | V45: 1 | W45: 1 | X45: 1 | Y45: 1 | Z45: 1 | AA45: 1 | AB45: 1 | AC45: 1 | AD45: 1 | AE45: 1
B47: IDEAL – x2 Demo + End Cap (Wks 5-6) + TPD
B48: Rationale: Full-court press: demo + end cap + TPD all running together for two weeks. Stacking end cap on demo weeks lifts velocity to ~3.6x (incremental ~20% on top of demo-only).
B49: Week | F49: W1 | G49: W2 | H49: W3 | I49: W4 | J49: W5 | K49: W6 | L49: W7 | M49: W8 | N49: W9 | O49: W10 | P49: W11 | Q49: W12 | R49: W13 | S49: W14 | T49: W15 | U49: W16 | V49: W17 | W49: W18 | X49: W19 | Y49: W20 | Z49: W21 | AA49: W22 | AB49: W23 | AC49: W24 | AD49: W25 | AE49: W26
B50: Wk-commencing | F50: =Inputs!$C$7+7*0 | G50: =Inputs!$C$7+7*1 | H50: =Inputs!$C$7+7*2 | I50: =Inputs!$C$7+7*3 | J50: =Inputs!$C$7+7*4 | K50: =Inputs!$C$7+7*5 | L50: =Inputs!$C$7+7*6 | M50: =Inputs!$C$7+7*7 | N50: =Inputs!$C$7+7*8 | O50: =Inputs!$C$7+7*9 | P50: =Inputs!$C$7+7*10 | Q50: =Inputs!$C$7+7*11 | R50: =Inputs!$C$7+7*12 | S50: =Inputs!$C$7+7*13 | T50: =Inputs!$C$7+7*14 | U50: =Inputs!$C$7+7*15 | V50: =Inputs!$C$7+7*16 | W50: =Inputs!$C$7+7*17 | X50: =Inputs!$C$7+7*18 | Y50: =Inputs!$C$7+7*19 | Z50: =Inputs!$C$7+7*20 | AA50: =Inputs!$C$7+7*21 | AB50: =Inputs!$C$7+7*22 | AC50: =Inputs!$C$7+7*23 | AD50: =Inputs!$C$7+7*24 | AE50: =Inputs!$C$7+7*25
B51: Demo | F51: 0 | G51: 0 | H51: 0 | I51: 0 | J51: 1 | K51: 1 | L51: 0 | M51: 0 | N51: 0 | O51: 0 | P51: 0 | Q51: 0 | R51: 0 | S51: 0 | T51: 0 | U51: 0 | V51: 0 | W51: 0 | X51: 0 | Y51: 0 | Z51: 0 | AA51: 0 | AB51: 0 | AC51: 0 | AD51: 0 | AE51: 0
B52: End Cap | F52: 0 | G52: 0 | H52: 0 | I52: 0 | J52: 1 | K52: 1 | L52: 0 | M52: 0 | N52: 0 | O52: 0 | P52: 0 | Q52: 0 | R52: 0 | S52: 0 | T52: 0 | U52: 0 | V52: 0 | W52: 0 | X52: 0 | Y52: 0 | Z52: 0 | AA52: 0 | AB52: 0 | AC52: 0 | AD52: 0 | AE52: 0
B53: Fence | F53: 0 | G53: 0 | H53: 0 | I53: 0 | J53: 0 | K53: 0 | L53: 0 | M53: 0 | N53: 0 | O53: 0 | P53: 0 | Q53: 0 | R53: 0 | S53: 0 | T53: 0 | U53: 0 | V53: 0 | W53: 0 | X53: 0 | Y53: 0 | Z53: 0 | AA53: 0 | AB53: 0 | AC53: 0 | AD53: 0 | AE53: 0
B54: TPD | F54: 0 | G54: 0 | H54: 0 | I54: 0 | J54: 1 | K54: 1 | L54: 0 | M54: 0 | N54: 0 | O54: 0 | P54: 0 | Q54: 0 | R54: 0 | S54: 0 | T54: 0 | U54: 0 | V54: 0 | W54: 0 | X54: 0 | Y54: 0 | Z54: 0 | AA54: 0 | AB54: 0 | AC54: 0 | AD54: 0 | AE54: 0
B55: Markdown | F55: 0 | G55: 0 | H55: 0 | I55: 0 | J55: 0 | K55: 0 | L55: 0 | M55: 0 | N55: 0 | O55: 0 | P55: 0 | Q55: 0 | R55: 0 | S55: 0 | T55: 0 | U55: 0 | V55: 0 | W55: 0 | X55: 0 | Y55: 0 | Z55: 0 | AA55: 0 | AB55: 0 | AC55: 0 | AD55: 0 | AE55: 0
B56: Advert | F56: 0 | G56: 0 | H56: 0 | I56: 0 | J56: 0 | K56: 0 | L56: 0 | M56: 0 | N56: 0 | O56: 0 | P56: 0 | Q56: 0 | R56: 0 | S56: 0 | T56: 0 | U56: 0 | V56: 0 | W56: 0 | X56: 0 | Y56: 0 | Z56: 0 | AA56: 0 | AB56: 0 | AC56: 0 | AD56: 0 | AE56: 0
B57: Lift Multiplier (x base) | F57: 1 | G57: 1 | H57: 1 | I57: 1 | J57: 3.6 | K57: 3.6 | L57: 1 | M57: 1 | N57: 1 | O57: 1 | P57: 1 | Q57: 1 | R57: 1 | S57: 1 | T57: 1 | U57: 1 | V57: 1 | W57: 1 | X57: 1 | Y57: 1 | Z57: 1 | AA57: 1 | AB57: 1 | AC57: 1 | AD57: 1 | AE57: 1
B59: WORST – Demo+EndCap+TPD then Markdown (Wks 18-20)
B60: Rationale: Same launch plan as IDEAL but sell-through stalls after the promo weeks. Residual inventory is cleared via three weeks of 50% markdown (Wks 18-20). Wk 20 spike reflects clearance blow-out (~2,400 units in one week).
B61: Week | F61: W1 | G61: W2 | H61: W3 | I61: W4 | J61: W5 | K61: W6 | L61: W7 | M61: W8 | N61: W9 | O61: W10 | P61: W11 | Q61: W12 | R61: W13 | S61: W14 | T61: W15 | U61: W16 | V61: W17 | W61: W18 | X61: W19 | Y61: W20 | Z61: W21 | AA61: W22 | AB61: W23 | AC61: W24 | AD61: W25 | AE61: W26
B62: Wk-commencing | F62: =Inputs!$C$7+7*0 | G62: =Inputs!$C$7+7*1 | H62: =Inputs!$C$7+7*2 | I62: =Inputs!$C$7+7*3 | J62: =Inputs!$C$7+7*4 | K62: =Inputs!$C$7+7*5 | L62: =Inputs!$C$7+7*6 | M62: =Inputs!$C$7+7*7 | N62: =Inputs!$C$7+7*8 | O62: =Inputs!$C$7+7*9 | P62: =Inputs!$C$7+7*10 | Q62: =Inputs!$C$7+7*11 | R62: =Inputs!$C$7+7*12 | S62: =Inputs!$C$7+7*13 | T62: =Inputs!$C$7+7*14 | U62: =Inputs!$C$7+7*15 | V62: =Inputs!$C$7+7*16 | W62: =Inputs!$C$7+7*17 | X62: =Inputs!$C$7+7*18 | Y62: =Inputs!$C$7+7*19 | Z62: =Inputs!$C$7+7*20 | AA62: =Inputs!$C$7+7*21 | AB62: =Inputs!$C$7+7*22 | AC62: =Inputs!$C$7+7*23 | AD62: =Inputs!$C$7+7*24 | AE62: =Inputs!$C$7+7*25
B63: Demo | F63: 0 | G63: 0 | H63: 0 | I63: 0 | J63: 1 | K63: 1 | L63: 0 | M63: 0 | N63: 0 | O63: 0 | P63: 0 | Q63: 0 | R63: 0 | S63: 0 | T63: 0 | U63: 0 | V63: 0 | W63: 0 | X63: 0 | Y63: 0 | Z63: 0 | AA63: 0 | AB63: 0 | AC63: 0 | AD63: 0 | AE63: 0
B64: End Cap | F64: 0 | G64: 0 | H64: 0 | I64: 0 | J64: 1 | K64: 1 | L64: 0 | M64: 0 | N64: 0 | O64: 0 | P64: 0 | Q64: 0 | R64: 0 | S64: 0 | T64: 0 | U64: 0 | V64: 0 | W64: 0 | X64: 0 | Y64: 0 | Z64: 0 | AA64: 0 | AB64: 0 | AC64: 0 | AD64: 0 | AE64: 0
B65: Fence | F65: 0 | G65: 0 | H65: 0 | I65: 0 | J65: 0 | K65: 0 | L65: 0 | M65: 0 | N65: 0 | O65: 0 | P65: 0 | Q65: 0 | R65: 0 | S65: 0 | T65: 0 | U65: 0 | V65: 0 | W65: 0 | X65: 0 | Y65: 0 | Z65: 0 | AA65: 0 | AB65: 0 | AC65: 0 | AD65: 0 | AE65: 0
B66: TPD | F66: 0 | G66: 0 | H66: 0 | I66: 0 | J66: 1 | K66: 1 | L66: 0 | M66: 0 | N66: 0 | O66: 0 | P66: 0 | Q66: 0 | R66: 0 | S66: 0 | T66: 0 | U66: 0 | V66: 0 | W66: 0 | X66: 0 | Y66: 0 | Z66: 0 | AA66: 0 | AB66: 0 | AC66: 0 | AD66: 0 | AE66: 0
B67: Markdown | F67: 0 | G67: 0 | H67: 0 | I67: 0 | J67: 0 | K67: 0 | L67: 0 | M67: 0 | N67: 0 | O67: 0 | P67: 0 | Q67: 0 | R67: 0 | S67: 0 | T67: 0 | U67: 0 | V67: 0 | W67: 1 | X67: 1 | Y67: 1 | Z67: 0 | AA67: 0 | AB67: 0 | AC67: 0 | AD67: 0 | AE67: 0
B68: Advert | F68: 0 | G68: 0 | H68: 0 | I68: 0 | J68: 0 | K68: 0 | L68: 0 | M68: 0 | N68: 0 | O68: 0 | P68: 0 | Q68: 0 | R68: 0 | S68: 0 | T68: 0 | U68: 0 | V68: 0 | W68: 0 | X68: 0 | Y68: 0 | Z68: 0 | AA68: 0 | AB68: 0 | AC68: 0 | AD68: 0 | AE68: 0
B69: Lift Multiplier (x base) | F69: 1 | G69: 1 | H69: 1 | I69: 1 | J69: 3 | K69: 3 | L69: 1 | M69: 1 | N69: 1 | O69: 1 | P69: 1 | Q69: 1 | R69: 1 | S69: 1 | T69: 1 | U69: 1 | V69: 1 | W69: 1 | X69: 0.3 | Y69: 8.7 | Z69: 1 | AA69: 1 | AB69: 1 | AC69: 1 | AD69: 1 | AE69: 1

Sheet Forecast
B2: FORECAST — Weekly P&L (all values calculated, do not edit)
B4: BEST – x2 Demo (Wks 5-6) + TPD
B5: Week | F5: W1 | G5: W2 | H5: W3 | I5: W4 | J5: W5 | K5: W6 | L5: W7 | M5: W8 | N5: W9 | O5: W10 | P5: W11 | Q5: W12 | R5: W13 | S5: W14 | T5: W15 | U5: W16 | V5: W17 | W5: W18 | X5: W19 | Y5: W20 | Z5: W21 | AA5: W22 | AB5: W23 | AC5: W24 | AD5: W25 | AE5: W26 | AF5: TOTAL
B6: Wk-commencing | F6: =Inputs!$C$7+7*0 | G6: =Inputs!$C$7+7*1 | H6: =Inputs!$C$7+7*2 | I6: =Inputs!$C$7+7*3 | J6: =Inputs!$C$7+7*4 | K6: =Inputs!$C$7+7*5 | L6: =Inputs!$C$7+7*6 | M6: =Inputs!$C$7+7*7 | N6: =Inputs!$C$7+7*8 | O6: =Inputs!$C$7+7*9 | P6: =Inputs!$C$7+7*10 | Q6: =Inputs!$C$7+7*11 | R6: =Inputs!$C$7+7*12 | S6: =Inputs!$C$7+7*13 | T6: =Inputs!$C$7+7*14 | U6: =Inputs!$C$7+7*15 | V6: =Inputs!$C$7+7*16 | W6: =Inputs!$C$7+7*17 | X6: =Inputs!$C$7+7*18 | Y6: =Inputs!$C$7+7*19 | Z6: =Inputs!$C$7+7*20 | AA6: =Inputs!$C$7+7*21 | AB6: =Inputs!$C$7+7*22 | AC6: =Inputs!$C$7+7*23 | AD6: =Inputs!$C$7+7*24 | AE6: =Inputs!$C$7+7*25
B7: POS Units | F7: =ROUND(Inputs!$C$19*Inputs!F45,0) | G7: =ROUND(Inputs!$C$19*Inputs!G45,0) | H7: =ROUND(Inputs!$C$19*Inputs!H45,0) | I7: =ROUND(Inputs!$C$19*Inputs!I45,0) | J7: =ROUND(Inputs!$C$19*Inputs!J45,0) | K7: =ROUND(Inputs!$C$19*Inputs!K45,0) | L7: =ROUND(Inputs!$C$19*Inputs!L45,0) | M7: =ROUND(Inputs!$C$19*Inputs!M45,0) | ... AE7: =ROUND(Inputs!$C$19*Inputs!AE45,0) | AF7: =SUM(F7:AE7)
B8: Selling Price | F8: =Inputs!$C$12 | G8: =Inputs!$C$12 | H8: =Inputs!$C$12 | I8: =Inputs!$C$12 | J8: =Inputs!$C$12 | K8: =Inputs!$C$12 | L8: =Inputs!$C$12 | M8: =Inputs!$C$12 | ... AF8: =Inputs!$C$12
B9: Revenue | F9: =F7*F8 | G9: =G7*G8 | H9: =H7*H8 | I9: =I7*I8 | J9: =J7*J8 | K9: =K7*K8 | L9: =L7*L8 | M9: =M7*M8 | ... AE9: =AE7*AE8 | AF9: =SUM(F9:AE9)
B10: Cost Price | F10: =Inputs!$C$13 | G10: =Inputs!$C$13 | H10: =Inputs!$C$13 | I10: =Inputs!$C$13 | J10: =Inputs!$C$13 | K10: =Inputs!$C$13 | L10: =Inputs!$C$13 | M10: =Inputs!$C$13 | ... AF10: =Inputs!$C$13
B11: Raw COGS | F11: =F7*F10 | G11: =G7*G10 | H11: =H7*H10 | I11: =I7*I10 | J11: =J7*J10 | K11: =K7*K10 | L11: =L7*L10 | M11: =M7*M10 | ... AE11: =AE7*AE10 | AF11: =SUM(F11:AE11)
B12: — Demo Spend | F12: =Inputs!F39*Inputs!$C$24 | G12: =Inputs!G39*Inputs!$C$24 | H12: =Inputs!H39*Inputs!$C$24 | I12: =Inputs!I39*Inputs!$C$24 | J12: =Inputs!J39*Inputs!$C$24 | K12: =Inputs!K39*Inputs!$C$24 | L12: =Inputs!L39*Inputs!$C$24 | M12: =Inputs!M39*Inputs!$C$24 | ... AE12: =Inputs!AE39*Inputs!$C$24 | AF12: =SUM(F12:AE12)
B13: — End Cap Spend | F13: =Inputs!F40*Inputs!$C$27 | G13: =Inputs!G40*Inputs!$C$27 | H13: =Inputs!H40*Inputs!$C$27 | I13: =Inputs!I40*Inputs!$C$27 | J13: =Inputs!J40*Inputs!$C$27 | K13: =Inputs!K40*Inputs!$C$27 | L13: =Inputs!L40*Inputs!$C$27 | M13: =Inputs!M40*Inputs!$C$27 | ... AE13: =Inputs!AE40*Inputs!$C$27 | AF13: =SUM(F13:AE13)
B14: — Fence Spend | F14: =Inputs!F41*Inputs!$C$28 | G14: =Inputs!G41*Inputs!$C$28 | H14: =Inputs!H41*Inputs!$C$28 | I14: =Inputs!I41*Inputs!$C$28 | J14: =Inputs!J41*Inputs!$C$28 | K14: =Inputs!K41*Inputs!$C$28 | L14: =Inputs!L41*Inputs!$C$28 | M14: =Inputs!M41*Inputs!$C$28 | ... AE14: =Inputs!AE41*Inputs!$C$28 | AF14: =SUM(F14:AE14)
B15: — TPD Spend | F15: =Inputs!F42*F7*F8*Inputs!$C$30 | G15: =Inputs!G42*G7*G8*Inputs!$C$30 | H15: =Inputs!H42*H7*H8*Inputs!$C$30 | I15: =Inputs!I42*I7*I8*Inputs!$C$30 | J15: =Inputs!J42*J7*J8*Inputs!$C$30 | K15: =Inputs!K42*K7*K8*Inputs!$C$30 | L15: =Inputs!L42*L7*L8*Inputs!$C$30 | M15: =Inputs!M42*M7*M8*Inputs!$C$30 | ... AE15: =Inputs!AE42*AE7*AE8*Inputs!$C$30 | AF15: =SUM(F15:AE15)
B16: — Markdown Spend | F16: =Inputs!F43*F7*F8*Inputs!$C$31 | G16: =Inputs!G43*G7*G8*Inputs!$C$31 | H16: =Inputs!H43*H7*H8*Inputs!$C$31 | I16: =Inputs!I43*I7*I8*Inputs!$C$31 | J16: =Inputs!J43*J7*J8*Inputs!$C$31 | K16: =Inputs!K43*K7*K8*Inputs!$C$31 | L16: =Inputs!L43*L7*L8*Inputs!$C$31 | M16: =Inputs!M43*M7*M8*Inputs!$C$31 | ... AE16: =Inputs!AE43*AE7*AE8*Inputs!$C$31 | AF16: =SUM(F16:AE16)
B17: — Advertising Spend | F17: =Inputs!F44*Inputs!$C$29 | G17: =Inputs!G44*Inputs!$C$29 | H17: =Inputs!H44*Inputs!$C$29 | I17: =Inputs!I44*Inputs!$C$29 | J17: =Inputs!J44*Inputs!$C$29 | K17: =Inputs!K44*Inputs!$C$29 | L17: =Inputs!L44*Inputs!$C$29 | M17: =Inputs!M44*Inputs!$C$29 | ... AE17: =Inputs!AE44*Inputs!$C$29 | AF17: =SUM(F17:AE17)
B18: Total Promo Spend | F18: =SUM(F12:F17) | G18: =SUM(G12:G17) | H18: =SUM(H12:H17) | I18: =SUM(I12:I17) | J18: =SUM(J12:J17) | K18: =SUM(K12:K17) | L18: =SUM(L12:L17) | M18: =SUM(M12:M17) | ... AE18: =SUM(AE12:AE17) | AF18: =SUM(F18:AE18)
B19: Gross Profit | F19: =F9-F11 | G19: =G9-G11 | H19: =H9-H11 | I19: =I9-I11 | J19: =J9-J11 | K19: =K9-K11 | L19: =L9-L11 | M19: =M9-M11 | ... AE19: =AE9-AE11 | AF19: =SUM(F19:AE19)
B20: Net Profit (after promo) | F20: =F19-F18 | G20: =G19-G18 | H20: =H19-H18 | I20: =I19-I18 | J20: =J19-J18 | K20: =K19-K18 | L20: =L19-L18 | M20: =M19-M18 | ... AE20: =AE19-AE18 | AF20: =SUM(F20:AE20)
B23: IDEAL – x2 Demo + End Cap (Wks 5-6) + TPD
B24: Week | F24: W1 | G24: W2 | H24: W3 | I24: W4 | J24: W5 | K24: W6 | L24: W7 | M24: W8 | N24: W9 | O24: W10 | P24: W11 | Q24: W12 | R24: W13 | S24: W14 | T24: W15 | U24: W16 | V24: W17 | W24: W18 | X24: W19 | Y24: W20 | Z24: W21 | AA24: W22 | AB24: W23 | AC24: W24 | AD24: W25 | AE24: W26 | AF24: TOTAL
B25: Wk-commencing | F25: =Inputs!$C$7+7*0 | G25: =Inputs!$C$7+7*1 | H25: =Inputs!$C$7+7*2 | I25: =Inputs!$C$7+7*3 | J25: =Inputs!$C$7+7*4 | K25: =Inputs!$C$7+7*5 | L25: =Inputs!$C$7+7*6 | M25: =Inputs!$C$7+7*7 | N25: =Inputs!$C$7+7*8 | O25: =Inputs!$C$7+7*9 | P25: =Inputs!$C$7+7*10 | Q25: =Inputs!$C$7+7*11 | R25: =Inputs!$C$7+7*12 | S25: =Inputs!$C$7+7*13 | T25: =Inputs!$C$7+7*14 | U25: =Inputs!$C$7+7*15 | V25: =Inputs!$C$7+7*16 | W25: =Inputs!$C$7+7*17 | X25: =Inputs!$C$7+7*18 | Y25: =Inputs!$C$7+7*19 | Z25: =Inputs!$C$7+7*20 | AA25: =Inputs!$C$7+7*21 | AB25: =Inputs!$C$7+7*22 | AC25: =Inputs!$C$7+7*23 | AD25: =Inputs!$C$7+7*24 | AE25: =Inputs!$C$7+7*25
B26: POS Units | F26: =ROUND(Inputs!$C$19*Inputs!F57,0) | G26: =ROUND(Inputs!$C$19*Inputs!G57,0) | H26: =ROUND(Inputs!$C$19*Inputs!H57,0) | I26: =ROUND(Inputs!$C$19*Inputs!I57,0) | J26: =ROUND(Inputs!$C$19*Inputs!J57,0) | K26: =ROUND(Inputs!$C$19*Inputs!K57,0) | L26: =ROUND(Inputs!$C$19*Inputs!L57,0) | M26: =ROUND(Inputs!$C$19*Inputs!M57,0) | ... AE26: =ROUND(Inputs!$C$19*Inputs!AE57,0) | AF26: =SUM(F26:AE26)
B27: Selling Price | F27: =Inputs!$C$12 | G27: =Inputs!$C$12 | H27: =Inputs!$C$12 | I27: =Inputs!$C$12 | J27: =Inputs!$C$12 | K27: =Inputs!$C$12 | L27: =Inputs!$C$12 | M27: =Inputs!$C$12 | ... AF27: =Inputs!$C$12
B28: Revenue | F28: =F26*F27 | G28: =G26*G27 | H28: =H26*H27 | I28: =I26*I27 | J28: =J26*J27 | K28: =K26*K27 | L28: =L26*L27 | M28: =M26*M27 | ... AE28: =AE26*AE27 | AF28: =SUM(F28:AE28)
B29: Cost Price | F29: =Inputs!$C$13 | G29: =Inputs!$C$13 | H29: =Inputs!$C$13 | I29: =Inputs!$C$13 | J29: =Inputs!$C$13 | K29: =Inputs!$C$13 | L29: =Inputs!$C$13 | M29: =Inputs!$C$13 | ... AF29: =Inputs!$C$13
B30: Raw COGS | F30: =F26*F29 | G30: =G26*G29 | H30: =H26*H29 | I30: =I26*I29 | J30: =J26*J29 | K30: =K26*K29 | L30: =L26*L29 | M30: =M26*M29 | ... AE30: =AE26*AE29 | AF30: =SUM(F30:AE30)
B31: — Demo Spend | F31: =Inputs!F51*Inputs!$C$24 | G31: =Inputs!G51*Inputs!$C$24 | H31: =Inputs!H51*Inputs!$C$24 | I31: =Inputs!I51*Inputs!$C$24 | J31: =Inputs!J51*Inputs!$C$24 | K31: =Inputs!K51*Inputs!$C$24 | L31: =Inputs!L51*Inputs!$C$24 | M31: =Inputs!M51*Inputs!$C$24 | ... AE31: =Inputs!AE51*Inputs!$C$24 | AF31: =SUM(F31:AE31)
B32: — End Cap Spend | F32: =Inputs!F52*Inputs!$C$27 | G32: =Inputs!G52*Inputs!$C$27 | H32: =Inputs!H52*Inputs!$C$27 | I32: =Inputs!I52*Inputs!$C$27 | J32: =Inputs!J52*Inputs!$C$27 | K32: =Inputs!K52*Inputs!$C$27 | L32: =Inputs!L52*Inputs!$C$27 | M32: =Inputs!M52*Inputs!$C$27 | ... AE32: =Inputs!AE52*Inputs!$C$27 | AF32: =SUM(F32:AE32)
B33: — Fence Spend | F33: =Inputs!F53*Inputs!$C$28 | G33: =Inputs!G53*Inputs!$C$28 | H33: =Inputs!H53*Inputs!$C$28 | I33: =Inputs!I53*Inputs!$C$28 | J33: =Inputs!J53*Inputs!$C$28 | K33: =Inputs!K53*Inputs!$C$28 | L33: =Inputs!L53*Inputs!$C$28 | M33: =Inputs!M53*Inputs!$C$28 | ... AE33: =Inputs!AE53*Inputs!$C$28 | AF33: =SUM(F33:AE33)
B34: — TPD Spend | F34: =Inputs!F54*F26*F27*Inputs!$C$30 | G34: =Inputs!G54*G26*G27*Inputs!$C$30 | H34: =Inputs!H54*H26*H27*Inputs!$C$30 | I34: =Inputs!I54*I26*I27*Inputs!$C$30 | J34: =Inputs!J54*J26*J27*Inputs!$C$30 | K34: =Inputs!K54*K26*K27*Inputs!$C$30 | L34: =Inputs!L54*L26*L27*Inputs!$C$30 | M34: =Inputs!M54*M26*M27*Inputs!$C$30 | ... AE34: =Inputs!AE54*AE26*AE27*Inputs!$C$30 | AF34: =SUM(F34:AE34)
B35: — Markdown Spend | F35: =Inputs!F55*F26*F27*Inputs!$C$31 | G35: =Inputs!G55*G26*G27*Inputs!$C$31 | H35: =Inputs!H55*H26*H27*Inputs!$C$31 | I35: =Inputs!I55*I26*I27*Inputs!$C$31 | J35: =Inputs!J55*J26*J27*Inputs!$C$31 | K35: =Inputs!K55*K26*K27*Inputs!$C$31 | L35: =Inputs!L55*L26*L27*Inputs!$C$31 | M35: =Inputs!M55*M26*M27*Inputs!$C$31 | ... AE35: =Inputs!AE55*AE26*AE27*Inputs!$C$31 | AF35: =SUM(F35:AE35)
B36: — Advertising Spend | F36: =Inputs!F56*Inputs!$C$29 | G36: =Inputs!G56*Inputs!$C$29 | H36: =Inputs!H56*Inputs!$C$29 | I36: =Inputs!I56*Inputs!$C$29 | J36: =Inputs!J56*Inputs!$C$29 | K36: =Inputs!K56*Inputs!$C$29 | L36: =Inputs!L56*Inputs!$C$29 | M36: =Inputs!M56*Inputs!$C$29 | ... AE36: =Inputs!AE56*Inputs!$C$29 | AF36: =SUM(F36:AE36)
B37: Total Promo Spend | F37: =SUM(F31:F36) | G37: =SUM(G31:G36) | H37: =SUM(H31:H36) | I37: =SUM(I31:I36) | J37: =SUM(J31:J36) | K37: =SUM(K31:K36) | L37: =SUM(L31:L36) | M37: =SUM(M31:M36) | ... AE37: =SUM(AE31:AE36) | AF37: =SUM(F37:AE37)
B38: Gross Profit | F38: =F28-F30 | G38: =G28-G30 | H38: =H28-H30 | I38: =I28-I30 | J38: =J28-J30 | K38: =K28-K30 | L38: =L28-L30 | M38: =M28-M30 | ... AE38: =AE28-AE30 | AF38: =SUM(F38:AE38)
B39: Net Profit (after promo) | F39: =F38-F37 | G39: =G38-G37 | H39: =H38-H37 | I39: =I38-I37 | J39: =J38-J37 | K39: =K38-K37 | L39: =L38-L37 | M39: =M38-M37 | ... AE39: =AE38-AE37 | AF39: =SUM(F39:AE39)
B42: WORST – Demo+EndCap+TPD then Markdown (Wks 18-20)
B43: Week | F43: W1 | G43: W2 | H43: W3 | I43: W4 | J43: W5 | K43: W6 | L43: W7 | M43: W8 | N43: W9 | O43: W10 | P43: W11 | Q43: W12 | R43: W13 | S43: W14 | T43: W15 | U43: W16 | V43: W17 | W43: W18 | X43: W19 | Y43: W20 | Z43: W21 | AA43: W22 | AB43: W23 | AC43: W24 | AD43: W25 | AE43: W26 | AF43: TOTAL
B44: Wk-commencing | F44: =Inputs!$C$7+7*0 | G44: =Inputs!$C$7+7*1 | H44: =Inputs!$C$7+7*2 | I44: =Inputs!$C$7+7*3 | J44: =Inputs!$C$7+7*4 | K44: =Inputs!$C$7+7*5 | L44: =Inputs!$C$7+7*6 | M44: =Inputs!$C$7+7*7 | N44: =Inputs!$C$7+7*8 | O44: =Inputs!$C$7+7*9 | P44: =Inputs!$C$7+7*10 | Q44: =Inputs!$C$7+7*11 | R44: =Inputs!$C$7+7*12 | S44: =Inputs!$C$7+7*13 | T44: =Inputs!$C$7+7*14 | U44: =Inputs!$C$7+7*15 | V44: =Inputs!$C$7+7*16 | W44: =Inputs!$C$7+7*17 | X44: =Inputs!$C$7+7*18 | Y44: =Inputs!$C$7+7*19 | Z44: =Inputs!$C$7+7*20 | AA44: =Inputs!$C$7+7*21 | AB44: =Inputs!$C$7+7*22 | AC44: =Inputs!$C$7+7*23 | AD44: =Inputs!$C$7+7*24 | AE44: =Inputs!$C$7+7*25
B45: POS Units | F45: =ROUND(Inputs!$C$19*Inputs!F69,0) | G45: =ROUND(Inputs!$C$19*Inputs!G69,0) | H45: =ROUND(Inputs!$C$19*Inputs!H69,0) | I45: =ROUND(Inputs!$C$19*Inputs!I69,0) | J45: =ROUND(Inputs!$C$19*Inputs!J69,0) | K45: =ROUND(Inputs!$C$19*Inputs!K69,0) | L45: =ROUND(Inputs!$C$19*Inputs!L69,0) | M45: =ROUND(Inputs!$C$19*Inputs!M69,0) | ... AE45: =ROUND(Inputs!$C$19*Inputs!AE69,0) | AF45: =SUM(F45:AE45)
B46: Selling Price | F46: =Inputs!$C$12 | G46: =Inputs!$C$12 | H46: =Inputs!$C$12 | I46: =Inputs!$C$12 | J46: =Inputs!$C$12 | K46: =Inputs!$C$12 | L46: =Inputs!$C$12 | M46: =Inputs!$C$12 | ... AF46: =Inputs!$C$12
B47: Revenue | F47: =F45*F46 | G47: =G45*G46 | H47: =H45*H46 | I47: =I45*I46 | J47: =J45*J46 | K47: =K45*K46 | L47: =L45*L46 | M47: =M45*M46 | ... AE47: =AE45*AE46 | AF47: =SUM(F47:AE47)
B48: Cost Price | F48: =Inputs!$C$13 | G48: =Inputs!$C$13 | H48: =Inputs!$C$13 | I48: =Inputs!$C$13 | J48: =Inputs!$C$13 | K48: =Inputs!$C$13 | L48: =Inputs!$C$13 | M48: =Inputs!$C$13 | ... AF48: =Inputs!$C$13
B49: Raw COGS | F49: =F45*F48 | G49: =G45*G48 | H49: =H45*H48 | I49: =I45*I48 | J49: =J45*J48 | K49: =K45*K48 | L49: =L45*L48 | M49: =M45*M48 | ... AE49: =AE45*AE48 | AF49: =SUM(F49:AE49)
B50: — Demo Spend | F50: =Inputs!F63*Inputs!$C$24 | G50: =Inputs!G63*Inputs!$C$24 | H50: =Inputs!H63*Inputs!$C$24 | I50: =Inputs!I63*Inputs!$C$24 | J50: =Inputs!J63*Inputs!$C$24 | K50: =Inputs!K63*Inputs!$C$24 | L50: =Inputs!L63*Inputs!$C$24 | M50: =Inputs!M63*Inputs!$C$24 | ... AE50: =Inputs!AE63*Inputs!$C$24 | AF50: =SUM(F50:AE50)
B51: — End Cap Spend | F51: =Inputs!F64*Inputs!$C$27 | G51: =Inputs!G64*Inputs!$C$27 | H51: =Inputs!H64*Inputs!$C$27 | I51: =Inputs!I64*Inputs!$C$27 | J51: =Inputs!J64*Inputs!$C$27 | K51: =Inputs!K64*Inputs!$C$27 | L51: =Inputs!L64*Inputs!$C$27 | M51: =Inputs!M64*Inputs!$C$27 | ... AE51: =Inputs!AE64*Inputs!$C$27 | AF51: =SUM(F51:AE51)
B52: — Fence Spend | F52: =Inputs!F65*Inputs!$C$28 | G52: =Inputs!G65*Inputs!$C$28 | H52: =Inputs!H65*Inputs!$C$28 | I52: =Inputs!I65*Inputs!$C$28 | J52: =Inputs!J65*Inputs!$C$28 | K52: =Inputs!K65*Inputs!$C$28 | L52: =Inputs!L65*Inputs!$C$28 | M52: =Inputs!M65*Inputs!$C$28 | ... AE52: =Inputs!AE65*Inputs!$C$28 | AF52: =SUM(F52:AE52)
B53: — TPD Spend | F53: =Inputs!F66*F45*F46*Inputs!$C$30 | G53: =Inputs!G66*G45*G46*Inputs!$C$30 | H53: =Inputs!H66*H45*H46*Inputs!$C$30 | I53: =Inputs!I66*I45*I46*Inputs!$C$30 | J53: =Inputs!J66*J45*J46*Inputs!$C$30 | K53: =Inputs!K66*K45*K46*Inputs!$C$30 | L53: =Inputs!L66*L45*L46*Inputs!$C$30 | M53: =Inputs!M66*M45*M46*Inputs!$C$30 | ... AE53: =Inputs!AE66*AE45*AE46*Inputs!$C$30 | AF53: =SUM(F53:AE53)
B54: — Markdown Spend | F54: =Inputs!F67*F45*F46*Inputs!$C$31 | G54: =Inputs!G67*G45*G46*Inputs!$C$31 | H54: =Inputs!H67*H45*H46*Inputs!$C$31 | I54: =Inputs!I67*I45*I46*Inputs!$C$31 | J54: =Inputs!J67*J45*J46*Inputs!$C$31 | K54: =Inputs!K67*K45*K46*Inputs!$C$31 | L54: =Inputs!L67*L45*L46*Inputs!$C$31 | M54: =Inputs!M67*M45*M46*Inputs!$C$31 | ... AE54: =Inputs!AE67*AE45*AE46*Inputs!$C$31 | AF54: =SUM(F54:AE54)
B55: — Advertising Spend | F55: =Inputs!F68*Inputs!$C$29 | G55: =Inputs!G68*Inputs!$C$29 | H55: =Inputs!H68*Inputs!$C$29 | I55: =Inputs!I68*Inputs!$C$29 | J55: =Inputs!J68*Inputs!$C$29 | K55: =Inputs!K68*Inputs!$C$29 | L55: =Inputs!L68*Inputs!$C$29 | M55: =Inputs!M68*Inputs!$C$29 | ... AE55: =Inputs!AE68*Inputs!$C$29 | AF55: =SUM(F55:AE55)
B56: Total Promo Spend | F56: =SUM(F50:F55) | G56: =SUM(G50:G55) | H56: =SUM(H50:H55) | I56: =SUM(I50:I55) | J56: =SUM(J50:J55) | K56: =SUM(K50:K55) | L56: =SUM(L50:L55) | M56: =SUM(M50:M55) | ... AE56: =SUM(AE50:AE55) | AF56: =SUM(F56:AE56)
B57: Gross Profit | F57: =F47-F49 | G57: =G47-G49 | H57: =H47-H49 | I57: =I47-I49 | J57: =J47-J49 | K57: =K47-K49 | L57: =L47-L49 | M57: =M47-M49 | ... AE57: =AE47-AE49 | AF57: =SUM(F57:AE57)
B58: Net Profit (after promo) | F58: =F57-F56 | G58: =G57-G56 | H58: =H57-H56 | I58: =I57-I56 | J58: =J57-J56 | K58: =K57-K56 | L58: =L57-L56 | M58: =M57-M56 | ... AE58: =AE57-AE56 | AF58: =SUM(F58:AE58)

Sheet Summary
B2: ROI SUMMARY — Scenario Comparison
B3: ="Test window: W1 ("&TEXT(Inputs!$C$7,"dd-mmm-yyyy")&") → W"&Inputs!$C$9&" ("&TEXT(Inputs!$C$7+7*(Inputs!$C$9-1),"dd-mmm-yyyy")&")"
B5: Metric | C5: BEST | D5: IDEAL | E5: WORST
B6: Units Sold | C6: =Forecast!AF7 | D6: =Forecast!AF26 | E6: =Forecast!AF45
B7: Revenue | C7: =Forecast!AF9 | D7: =Forecast!AF28 | E7: =Forecast!AF47
B8: Raw COGS | C8: =Forecast!AF11 | D8: =Forecast!AF30 | E8: =Forecast!AF49
B9: Gross Profit | C9: =Forecast!AF19 | D9: =Forecast!AF38 | E9: =Forecast!AF57
B10: Gross Margin % | C10: =IFERROR(Forecast!AF19/Forecast!AF9,0) | D10: =IFERROR(Forecast!AF38/Forecast!AF28,0) | E10: =IFERROR(Forecast!AF57/Forecast!AF47,0)
B11: Demo Spend | C11: =Forecast!AF12 | D11: =Forecast!AF31 | E11: =Forecast!AF50
B12: End Cap Spend | C12: =Forecast!AF13 | D12: =Forecast!AF32 | E12: =Forecast!AF51
B13: Fence Spend | C13: =Forecast!AF14 | D13: =Forecast!AF33 | E13: =Forecast!AF52
B14: TPD Spend | C14: =Forecast!AF15 | D14: =Forecast!AF34 | E14: =Forecast!AF53
B15: Markdown Spend | C15: =Forecast!AF16 | D15: =Forecast!AF35 | E15: =Forecast!AF54
B16: Advertising Spend | C16: =Forecast!AF17 | D16: =Forecast!AF36 | E16: =Forecast!AF55
B17: Total Promo Spend | C17: =Forecast!AF18 | D17: =Forecast!AF37 | E17: =Forecast!AF56
B18: Net Profit | C18: =Forecast!AF20 | D18: =Forecast!AF39 | E18: =Forecast!AF58
B19: Net Margin % | C19: =IFERROR(Forecast!AF20/Forecast!AF9,0) | D19: =IFERROR(Forecast!AF39/Forecast!AF28,0) | E19: =IFERROR(Forecast!AF58/Forecast!AF47,0)
B20: ROI on Promo Spend | C20: =IFERROR(Forecast!AF20/Forecast!AF18,0) | D20: =IFERROR(Forecast!AF39/Forecast!AF37,0) | E20: =IFERROR(Forecast!AF58/Forecast!AF56,0)
B21: Avg Units / WH / Week | C21: =IFERROR(Forecast!AF7/Inputs!$C$8/Inputs!$C$9,0) | D21: =IFERROR(Forecast!AF26/Inputs!$C$8/Inputs!$C$9,0) | E21: =IFERROR(Forecast!AF45/Inputs!$C$8/Inputs!$C$9,0)
B24: Why each scenario?
B25: BEST | C25: Two national demo weekends combined with a TPD price promo. Demo lifts unit velocity ~3x in-week (Costco benchmark for supplements). No end cap booked, no markdown needed.
B26: IDEAL | C26: Full-court press: demo + end cap + TPD all running together for two weeks. Stacking end cap on demo weeks lifts velocity to ~3.6x (incremental ~20% on top of demo-only).
B27: WORST | C27: Same launch plan as IDEAL but sell-through stalls after the promo weeks. Residual inventory is cleared via three weeks of 50% markdown (Wks 18-20). Wk 20 spike reflects clearance blow-out (~2,400 units in one week).
