Workbook
Name StartDate: Inputs!$C$7
Name WHs: Inputs!$C$8
Name Period: Inputs!$C$9
Name Price: Inputs!$C$12
Name Cost: Inputs!$C$13
Name BaseUnits: Inputs!$C$19
Name DemoCost: Inputs!$C$24
Name EndCapCost: Inputs!$C$28
Name FenceCost: Inputs!$C$29
Name AdvertCost: Inputs!$C$30
Name TPDPct: Inputs!$C$31
Name MdPct: Inputs!$C$32

Sheet README
B2: Costco UK — D93 Portfolio ROI Model
B3: v5.0 · Bee Propolis market-test (baseline) + 1-year portfolio roll-up
B5: HOW TO USE
B7: 1. Two views in one workbook:
B8: • Bee Propolis deep-dive — 26-week market test with BEST / IDEAL / WORST scenarios.
B9: • Portfolio roll-up — annual Y1 numbers across all seven D93 SKUs with blended margin & ROI.
B11: 2. Only the YELLOW cells are editable. Every yellow cell is an input you can change.
B12: • Some yellow cells contain a formula by default (e.g. Gross Margin per unit = SP − Cost).
B13: • Type your own number into any yellow cell to override — the formula is replaced.
B14: • No separate 'override' column — one column, one place to change anything.
B16: 3. Change the 'Test Start Date (W1)' on Inputs and every week column on every sheet shifts dates.
B18: 4. On the Portfolio sheet, fill in SP / Cost / Y1 Units / Promo Spend for SKUs 2-7 from Asana.
... B34: Grey: Reference / structure (you generally won't edit)

Sheet Inputs
B2: INPUTS & ASSUMPTIONS — change any yellow cell
B3: Field | C3: Value | D3: Notes / justification
B5: 1. Product & Distribution
B6: SKU | C6: Bee Propolis Spray 30ml x 2 | D6: Costco UK market test SKU.
B7: Test Start Date (W1) | C7: 46034 | D7: Week-commencing date for W1. Drives every date header.
B8: Test Warehouses | C8: 20 | D8: Number of Costco UK warehouses in test.
B9: Test Period (Weeks) | C9: 26 | D9: Forecast horizon (26 weeks, W1 to W26).
B11: 2. Pricing & Cost (per unit, £)
B12: Selling Price (MSRP) | C12: 15.99 | D12: Retail per pack.
B13: Cost Price (landed) | C13: 7.29 | D13: Brand cost delivered.
B14: Gross Margin per unit | C14: =C12-C13 | D14: Default = SP − Cost. Type over to override (display-only — Forecast uses SP and Cost).
B15: Gross Margin % | C15: =IFERROR((C12-C13)/C12,0) | D15: Default = GP ÷ SP. Type over to override (display-only).
B17: 3. Base Demand (no promo)
B18: Units / Warehouse / Week | C18: 13.79 | D18: From prior 30ml SKU run-rate (500 × 0.8 / 29).
B19: Base Units / Week (all warehouses) | C19: =C18*C8 | D19: Default = per-wh rate × warehouses. Type over to set the all-wh weekly base directly.
B21: 4. Promo Economics
B22: Demo £ / warehouse / week | C22: 199 | D22: Costco standard demo rate.
B23: Demo cost factor | C23: 1.86 | D23: Staffing + POS overhead multiplier.
B24: Demo Total £ / week | C24: =C22*C8*C23 | D24: Default = rate × warehouses × factor. Type over to set total directly.
B25: End Cap £ / warehouse / booking | C25: 850 | D25: Costco standard end cap rental per warehouse per booking.
B26: End Cap cost factor | C26: 1.86 | D26: Same as demo.
B27: End Cap booking cycle (weeks) | C27: 2 | D27: End cap is typically booked across 2 weeks; per-week cost = total ÷ this.
B28: End Cap Total £ / week | C28: =C25*C8*C26/C27 | D28: Default = rate × warehouses × factor ÷ booking weeks. Type over to set directly.
B29: Fence £ / week (when active) | C29: 0 | D29: Not currently budgeted.
B30: Advertising £ / week (when active) | C30: 0 | D30: Not currently budgeted.
B31: TPD discount % (of net) | C31: 0.25 | D31: 20% off MSRP = 25% deduction on net.
B32: Markdown discount % | C32: 0.5 | D32: Clearance pricing.
B34: 5. Scenario activity & demand lift
B35: Toggle 1 = promo active, 0 = off per week. Lift is the demand multiplier vs base. Dates auto-fill from Test Start Date. All yellow cells are editable.
B37: BEST – x2 Demo (Wks 5-6) + TPD
B38: Rationale: Two demo weekends with TPD. Demo lifts ~3x in-week. No end cap, no markdown.
B39: Week | F39: W1 | G39: W2 | H39: W3 | I39: W4 | J39: W5 | K39: W6 | L39: W7 | M39: W8 | N39: W9 | O39: W10 | P39: W11 | Q39: W12 | R39: W13 | S39: W14 | T39: W15 | U39: W16 | V39: W17 | W39: W18 | X39: W19 | Y39: W20 | Z39: W21 | AA39: W22 | AB39: W23 | AC39: W24 | AD39: W25 | AE39: W26
B40: Wk-commencing | F40: =StartDate+7*0 | G40: =StartDate+7*1 | H40: =StartDate+7*2 | I40: =StartDate+7*3 | J40: =StartDate+7*4 | K40: =StartDate+7*5 | L40: =StartDate+7*6 | M40: =StartDate+7*7 | N40: =StartDate+7*8 | O40: =StartDate+7*9 | P40: =StartDate+7*10 | Q40: =StartDate+7*11 | R40: =StartDate+7*12 | S40: =StartDate+7*13 | T40: =StartDate+7*14 | U40: =StartDate+7*15 | V40: =StartDate+7*16 | W40: =StartDate+7*17 | X40: =StartDate+7*18 | Y40: =StartDate+7*19 | Z40: =StartDate+7*20 | AA40: =StartDate+7*21 | AB40: =StartDate+7*22 | AC40: =StartDate+7*23 | AD40: =StartDate+7*24 | AE40: =StartDate+7*25
B41: Demo | F41: 0 | G41: 0 | H41: 0 | I41: 0 | J41: 1 | K41: 1 | L41: 0 | M41: 0 | N41: 0 | O41: 0 | P41: 0 | Q41: 0 | R41: 0 | S41: 0 | T41: 0 | U41: 0 | V41: 0 | W41: 0 | X41: 0 | Y41: 0 | Z41: 0 | AA41: 0 | AB41: 0 | AC41: 0 | AD41: 0 | AE41: 0
B42: End Cap | F42: 0 | G42: 0 | H42: 0 | I42: 0 | J42: 0 | K42: 0 | L42: 0 | M42: 0 | N42: 0 | O42: 0 | P42: 0 | Q42: 0 | R42: 0 | S42: 0 | T42: 0 | U42: 0 | V42: 0 | W42: 0 | X42: 0 | Y42: 0 | Z42: 0 | AA42: 0 | AB42: 0 | AC42: 0 | AD42: 0 | AE42: 0
B43: Fence | F43: 0 | G43: 0 | H43: 0 | I43: 0 | J43: 0 | K43: 0 | L43: 0 | M43: 0 | N43: 0 | O43: 0 | P43: 0 | Q43: 0 | R43: 0 | S43: 0 | T43: 0 | U43: 0 | V43: 0 | W43: 0 | X43: 0 | Y43: 0 | Z43: 0 | AA43: 0 | AB43: 0 | AC43: 0 | AD43: 0 | AE43: 0
B44: TPD | F44: 0 | G44: 0 | H44: 0 | I44: 0 | J44: 1 | K44: 1 | L44: 0 | M44: 0 | N44: 0 | O44: 0 | P44: 0 | Q44: 0 | R44: 0 | S44: 0 | T44: 0 | U44: 0 | V44: 0 | W44: 0 | X44: 0 | Y44: 0 | Z44: 0 | AA44: 0 | AB44: 0 | AC44: 0 | AD44: 0 | AE44: 0
B45: Markdown | F45: 0 | G45: 0 | H45: 0 | I45: 0 | J45: 0 | K45: 0 | L45: 0 | M45: 0 | N45: 0 | O45: 0 | P45: 0 | Q45: 0 | R45: 0 | S45: 0 | T45: 0 | U45: 0 | V45: 0 | W45: 0 | X45: 0 | Y45: 0 | Z45: 0 | AA45: 0 | AB45: 0 | AC45: 0 | AD45: 0 | AE45: 0
B46: Advert | F46: 0 | G46: 0 | H46: 0 | I46: 0 | J46: 0 | K46: 0 | L46: 0 | M46: 0 | N46: 0 | O46: 0 | P46: 0 | Q46: 0 | R46: 0 | S46: 0 | T46: 0 | U46: 0 | V46: 0 | W46: 0 | X46: 0 | Y46: 0 | Z46: 0 | AA46: 0 | AB46: 0 | AC46: 0 | AD46: 0 | AE46: 0
B47: Lift Multiplier (x base) | F47: 1 | G47: 1 | H47: 1 | I47: 1 | J47: 3 | K47: 3 | L47: 1 | M47: 1 | N47: 1 | O47: 1 | P47: 1 | Q47: 1 | R47: 1 | S47: 1 | T47: 1 | U47: 1 | V47: 1 | W47: 1 | X47: 1 | Y47: 1 | Z47: 1 | AA47: 1 | AB47: 1 | AC47: 1 | AD47: 1 | AE47: 1
B49: IDEAL – x2 Demo + End Cap (Wks 5-6) + TPD
B50: Rationale: Demo + end cap + TPD stacked for two weeks. Combined velocity ~3.6x base.
B51: Week | F51: W1 | G51: W2 | H51: W3 | I51: W4 | J51: W5 | K51: W6 | L51: W7 | M51: W8 | N51: W9 | O51: W10 | P51: W11 | Q51: W12 | R51: W13 | S51: W14 | T51: W15 | U51: W16 | V51: W17 | W51: W18 | X51: W19 | Y51: W20 | Z51: W21 | AA51: W22 | AB51: W23 | AC51: W24 | AD51: W25 | AE51: W26
B52: Wk-commencing | F52: =StartDate+7*0 | G52: =StartDate+7*1 | H52: =StartDate+7*2 | I52: =StartDate+7*3 | J52: =StartDate+7*4 | K52: =StartDate+7*5 | L52: =StartDate+7*6 | M52: =StartDate+7*7 | N52: =StartDate+7*8 | O52: =StartDate+7*9 | P52: =StartDate+7*10 | Q52: =StartDate+7*11 | R52: =StartDate+7*12 | S52: =StartDate+7*13 | T52: =StartDate+7*14 | U52: =StartDate+7*15 | V52: =StartDate+7*16 | W52: =StartDate+7*17 | X52: =StartDate+7*18 | Y52: =StartDate+7*19 | Z52: =StartDate+7*20 | AA52: =StartDate+7*21 | AB52: =StartDate+7*22 | AC52: =StartDate+7*23 | AD52: =StartDate+7*24 | AE52: =StartDate+7*25
B53: Demo | F53: 0 | G53: 0 | H53: 0 | I53: 0 | J53: 1 | K53: 1 | L53: 0 | M53: 0 | N53: 0 | O53: 0 | P53: 0 | Q53: 0 | R53: 0 | S53: 0 | T53: 0 | U53: 0 | V53: 0 | W53: 0 | X53: 0 | Y53: 0 | Z53: 0 | AA53: 0 | AB53: 0 | AC53: 0 | AD53: 0 | AE53: 0
B54: End Cap | F54: 0 | G54: 0 | H54: 0 | I54: 0 | J54: 1 | K54: 1 | L54: 0 | M54: 0 | N54: 0 | O54: 0 | P54: 0 | Q54: 0 | R54: 0 | S54: 0 | T54: 0 | U54: 0 | V54: 0 | W54: 0 | X54: 0 | Y54: 0 | Z54: 0 | AA54: 0 | AB54: 0 | AC54: 0 | AD54: 0 | AE54: 0
B55: Fence | F55: 0 | G55: 0 | H55: 0 | I55: 0 | J55: 0 | K55: 0 | L55: 0 | M55: 0 | N55: 0 | O55: 0 | P55: 0 | Q55: 0 | R55: 0 | S55: 0 | T55: 0 | U55: 0 | V55: 0 | W55: 0 | X55: 0 | Y55: 0 | Z55: 0 | AA55: 0 | AB55: 0 | AC55: 0 | AD55: 0 | AE55: 0
B56: TPD | F56: 0 | G56: 0 | H56: 0 | I56: 0 | J56: 1 | K56: 1 | L56: 0 | M56: 0 | N56: 0 | O56: 0 | P56: 0 | Q56: 0 | R56: 0 | S56: 0 | T56: 0 | U56: 0 | V56: 0 | W56: 0 | X56: 0 | Y56: 0 | Z56: 0 | AA56: 0 | AB56: 0 | AC56: 0 | AD56: 0 | AE56: 0
B57: Markdown | F57: 0 | G57: 0 | H57: 0 | I57: 0 | J57: 0 | K57: 0 | L57: 0 | M57: 0 | N57: 0 | O57: 0 | P57: 0 | Q57: 0 | R57: 0 | S57: 0 | T57: 0 | U57: 0 | V57: 0 | W57: 0 | X57: 0 | Y57: 0 | Z57: 0 | AA57: 0 | AB57: 0 | AC57: 0 | AD57: 0 | AE57: 0
B58: Advert | F58: 0 | G58: 0 | H58: 0 | I58: 0 | J58: 0 | K58: 0 | L58: 0 | M58: 0 | N58: 0 | O58: 0 | P58: 0 | Q58: 0 | R58: 0 | S58: 0 | T58: 0 | U58: 0 | V58: 0 | W58: 0 | X58: 0 | Y58: 0 | Z58: 0 | AA58: 0 | AB58: 0 | AC58: 0 | AD58: 0 | AE58: 0
B59: Lift Multiplier (x base) | F59: 1 | G59: 1 | H59: 1 | I59: 1 | J59: 3.6 | K59: 3.6 | L59: 1 | M59: 1 | N59: 1 | O59: 1 | P59: 1 | Q59: 1 | R59: 1 | S59: 1 | T59: 1 | U59: 1 | V59: 1 | W59: 1 | X59: 1 | Y59: 1 | Z59: 1 | AA59: 1 | AB59: 1 | AC59: 1 | AD59: 1 | AE59: 1
B61: WORST – Demo+EndCap+TPD then Markdown (Wks 18-20)
B62: Rationale: Promo plan as IDEAL but residual inventory clears at 50% off over Wks 18-20.
B63: Week | F63: W1 | G63: W2 | H63: W3 | I63: W4 | J63: W5 | K63: W6 | L63: W7 | M63: W8 | N63: W9 | O63: W10 | P63: W11 | Q63: W12 | R63: W13 | S63: W14 | T63: W15 | U63: W16 | V63: W17 | W63: W18 | X63: W19 | Y63: W20 | Z63: W21 | AA63: W22 | AB63: W23 | AC63: W24 | AD63: W25 | AE63: W26
B64: Wk-commencing | F64: =StartDate+7*0 | G64: =StartDate+7*1 | H64: =StartDate+7*2 | I64: =StartDate+7*3 | J64: =StartDate+7*4 | K64: =StartDate+7*5 | L64: =StartDate+7*6 | M64: =StartDate+7*7 | N64: =StartDate+7*8 | O64: =StartDate+7*9 | P64: =StartDate+7*10 | Q64: =StartDate+7*11 | R64: =StartDate+7*12 | S64: =StartDate+7*13 | T64: =StartDate+7*14 | U64: =StartDate+7*15 | V64: =StartDate+7*16 | W64: =StartDate+7*17 | X64: =StartDate+7*18 | Y64: =StartDate+7*19 | Z64: =StartDate+7*20 | AA64: =StartDate+7*21 | AB64: =StartDate+7*22 | AC64: =StartDate+7*23 | AD64: =StartDate+7*24 | AE64: =StartDate+7*25
B65: Demo | F65: 0 | G65: 0 | H65: 0 | I65: 0 | J65: 1 | K65: 1 | L65: 0 | M65: 0 | N65: 0 | O65: 0 | P65: 0 | Q65: 0 | R65: 0 | S65: 0 | T65: 0 | U65: 0 | V65: 0 | W65: 0 | X65: 0 | Y65: 0 | Z65: 0 | AA65: 0 | AB65: 0 | AC65: 0 | AD65: 0 | AE65: 0
B66: End Cap | F66: 0 | G66: 0 | H66: 0 | I66: 0 | J66: 1 | K66: 1 | L66: 0 | M66: 0 | N66: 0 | O66: 0 | P66: 0 | Q66: 0 | R66: 0 | S66: 0 | T66: 0 | U66: 0 | V66: 0 | W66: 0 | X66: 0 | Y66: 0 | Z66: 0 | AA66: 0 | AB66: 0 | AC66: 0 | AD66: 0 | AE66: 0
B67: Fence | F67: 0 | G67: 0 | H67: 0 | I67: 0 | J67: 0 | K67: 0 | L67: 0 | M67: 0 | N67: 0 | O67: 0 | P67: 0 | Q67: 0 | R67: 0 | S67: 0 | T67: 0 | U67: 0 | V67: 0 | W67: 0 | X67: 0 | Y67: 0 | Z67: 0 | AA67: 0 | AB67: 0 | AC67: 0 | AD67: 0 | AE67: 0
B68: TPD | F68: 0 | G68: 0 | H68: 0 | I68: 0 | J68: 1 | K68: 1 | L68: 0 | M68: 0 | N68: 0 | O68: 0 | P68: 0 | Q68: 0 | R68: 0 | S68: 0 | T68: 0 | U68: 0 | V68: 0 | W68: 0 | X68: 0 | Y68: 0 | Z68: 0 | AA68: 0 | AB68: 0 | AC68: 0 | AD68: 0 | AE68: 0
B69: Markdown | F69: 0 | G69: 0 | H69: 0 | I69: 0 | J69: 0 | K69: 0 | L69: 0 | M69: 0 | N69: 0 | O69: 0 | P69: 0 | Q69: 0 | R69: 0 | S69: 0 | T69: 0 | U69: 0 | V69: 0 | W69: 1 | X69: 1 | Y69: 1 | Z69: 0 | AA69: 0 | AB69: 0 | AC69: 0 | AD69: 0 | AE69: 0
B70: Advert | F70: 0 | G70: 0 | H70: 0 | I70: 0 | J70: 0 | K70: 0 | L70: 0 | M70: 0 | N70: 0 | O70: 0 | P70: 0 | Q70: 0 | R70: 0 | S70: 0 | T70: 0 | U70: 0 | V70: 0 | W70: 0 | X70: 0 | Y70: 0 | Z70: 0 | AA70: 0 | AB70: 0 | AC70: 0 | AD70: 0 | AE70: 0
B71: Lift Multiplier (x base) | F71: 1 | G71: 1 | H71: 1 | I71: 1 | J71: 3 | K71: 3 | L71: 1 | M71: 1 | N71: 1 | O71: 1 | P71: 1 | Q71: 1 | R71: 1 | S71: 1 | T71: 1 | U71: 1 | V71: 1 | W71: 1 | X71: 0.3 | Y71: 8.7 | Z71: 1 | AA71: 1 | AB71: 1 | AC71: 1 | AD71: 1 | AE71: 1

Sheet Forecast
B2: FORECAST — Weekly P&L by Scenario
B4: BEST – x2 Demo (Wks 5-6) + TPD
B5: Week | F5: W1 | G5: W2 | H5: W3 | I5: W4 | J5: W5 | K5: W6 | L5: W7 | M5: W8 | N5: W9 | O5: W10 | P5: W11 | Q5: W12 | R5: W13 | S5: W14 | T5: W15 | U5: W16 | V5: W17 | W5: W18 | X5: W19 | Y5: W20 | Z5: W21 | AA5: W22 | AB5: W23 | AC5: W24 | AD5: W25 | AE5: W26 | AF5: TOTAL
B6: Wk-commencing | F6: =StartDate+7*0 | G6: =StartDate+7*1 | H6: =StartDate+7*2 | I6: =StartDate+7*3 | J6: =StartDate+7*4 | K6: =StartDate+7*5 | L6: =StartDate+7*6 | M6: =StartDate+7*7 | N6: =StartDate+7*8 | O6: =StartDate+7*9 | P6: =StartDate+7*10 | Q6: =StartDate+7*11 | R6: =StartDate+7*12 | S6: =StartDate+7*13 | T6: =StartDate+7*14 | U6: =StartDate+7*15 | V6: =StartDate+7*16 | W6: =StartDate+7*17 | X6: =StartDate+7*18 | Y6: =StartDate+7*19 | Z6: =StartDate+7*20 | AA6: =StartDate+7*21 | AB6: =StartDate+7*22 | AC6: =StartDate+7*23 | AD6: =StartDate+7*24 | AE6: =StartDate+7*25
B7: POS Units | F7: =ROUND(BaseUnits*Inputs!F47,0) | G7: =ROUND(BaseUnits*Inputs!G47,0) | H7: =ROUND(BaseUnits*Inputs!H47,0) | I7: =ROUND(BaseUnits*Inputs!I47,0) | J7: =ROUND(BaseUnits*Inputs!J47,0) | K7: =ROUND(BaseUnits*Inputs!K47,0) | L7: =ROUND(BaseUnits*Inputs!L47,0) | M7: =ROUND(BaseUnits*Inputs!M47,0) | ... AE7: =ROUND(BaseUnits*Inputs!AE47,0) | AF7: =SUM(F7:AE7)
B8: Selling Price | F8: =Price | G8: =Price | H8: =Price | I8: =Price | J8: =Price | K8: =Price | L8: =Price | M8: =Price | ... AF8: =Price
B9: Revenue | F9: =F7*F8 | G9: =G7*G8 | H9: =H7*H8 | I9: =I7*I8 | J9: =J7*J8 | K9: =K7*K8 | L9: =L7*L8 | M9: =M7*M8 | ... AE9: =AE7*AE8 | AF9: =SUM(F9:AE9)
B10: Cost Price | F10: =Cost | G10: =Cost | H10: =Cost | I10: =Cost | J10: =Cost | K10: =Cost | L10: =Cost | M10: =Cost | ... AF10: =Cost
B11: Raw COGS | F11: =F7*F10 | G11: =G7*G10 | H11: =H7*H10 | I11: =I7*I10 | J11: =J7*J10 | K11: =K7*K10 | L11: =L7*L10 | M11: =M7*M10 | ... AE11: =AE7*AE10 | AF11: =SUM(F11:AE11)
B12: — Demo Spend | F12: =Inputs!F41*DemoCost | G12: =Inputs!G41*DemoCost | H12: =Inputs!H41*DemoCost | I12: =Inputs!I41*DemoCost | J12: =Inputs!J41*DemoCost | K12: =Inputs!K41*DemoCost | L12: =Inputs!L41*DemoCost | M12: =Inputs!M41*DemoCost | ... AE12: =Inputs!AE41*DemoCost | AF12: =SUM(F12:AE12)
B13: — End Cap Spend | F13: =Inputs!F42*EndCapCost | G13: =Inputs!G42*EndCapCost | H13: =Inputs!H42*EndCapCost | I13: =Inputs!I42*EndCapCost | J13: =Inputs!J42*EndCapCost | K13: =Inputs!K42*EndCapCost | L13: =Inputs!L42*EndCapCost | M13: =Inputs!M42*EndCapCost | ... AE13: =Inputs!AE42*EndCapCost | AF13: =SUM(F13:AE13)
B14: — Fence Spend | F14: =Inputs!F43*FenceCost | G14: =Inputs!G43*FenceCost | H14: =Inputs!H43*FenceCost | I14: =Inputs!I43*FenceCost | J14: =Inputs!J43*FenceCost | K14: =Inputs!K43*FenceCost | L14: =Inputs!L43*FenceCost | M14: =Inputs!M43*FenceCost | ... AE14: =Inputs!AE43*FenceCost | AF14: =SUM(F14:AE14)
B15: — TPD Spend | F15: =Inputs!F44*F7*F8*TPDPct | G15: =Inputs!G44*G7*G8*TPDPct | H15: =Inputs!H44*H7*H8*TPDPct | I15: =Inputs!I44*I7*I8*TPDPct | J15: =Inputs!J44*J7*J8*TPDPct | K15: =Inputs!K44*K7*K8*TPDPct | L15: =Inputs!L44*L7*L8*TPDPct | M15: =Inputs!M44*M7*M8*TPDPct | ... AE15: =Inputs!AE44*AE7*AE8*TPDPct | AF15: =SUM(F15:AE15)
B16: — Markdown Spend | F16: =Inputs!F45*F7*F8*MdPct | G16: =Inputs!G45*G7*G8*MdPct | H16: =Inputs!H45*H7*H8*MdPct | I16: =Inputs!I45*I7*I8*MdPct | J16: =Inputs!J45*J7*J8*MdPct | K16: =Inputs!K45*K7*K8*MdPct | L16: =Inputs!L45*L7*L8*MdPct | M16: =Inputs!M45*M7*M8*MdPct | ... AE16: =Inputs!AE45*AE7*AE8*MdPct | AF16: =SUM(F16:AE16)
B17: — Advertising Spend | F17: =Inputs!F46*AdvertCost | G17: =Inputs!G46*AdvertCost | H17: =Inputs!H46*AdvertCost | I17: =Inputs!I46*AdvertCost | J17: =Inputs!J46*AdvertCost | K17: =Inputs!K46*AdvertCost | L17: =Inputs!L46*AdvertCost | M17: =Inputs!M46*AdvertCost | ... AE17: =Inputs!AE46*AdvertCost | AF17: =SUM(F17:AE17)
B18: Total Promo Spend | F18: =SUM(F12:F17) | G18: =SUM(G12:G17) | H18: =SUM(H12:H17) | I18: =SUM(I12:I17) | J18: =SUM(J12:J17) | K18: =SUM(K12:K17) | L18: =SUM(L12:L17) | M18: =SUM(M12:M17) | ... AE18: =SUM(AE12:AE17) | AF18: =SUM(F18:AE18)
B19: Gross Profit | F19: =F9-F11 | G19: =G9-G11 | H19: =H9-H11 | I19: =I9-I11 | J19: =J9-J11 | K19: =K9-K11 | L19: =L9-L11 | M19: =M9-M11 | ... AE19: =AE9-AE11 | AF19: =SUM(F19:AE19)
B20: Net Profit (after promo) | F20: =F19-F18 | G20: =G19-G18 | H20: =H19-H18 | I20: =I19-I18 | J20: =J19-J18 | K20: =K19-K18 | L20: =L19-L18 | M20: =M19-M18 | ... AE20: =AE19-AE18 | AF20: =SUM(F20:AE20)
B23: IDEAL – x2 Demo + End Cap (Wks 5-6) + TPD
B24: Week | F24: W1 | G24: W2 | H24: W3 | I24: W4 | J24: W5 | K24: W6 | L24: W7 | M24: W8 | N24: W9 | O24: W10 | P24: W11 | Q24: W12 | R24: W13 | S24: W14 | T24: W15 | U24: W16 | V24: W17 | W24: W18 | X24: W19 | Y24: W20 | Z24: W21 | AA24: W22 | AB24: W23 | AC24: W24 | AD24: W25 | AE24: W26 | AF24: TOTAL
B25: Wk-commencing | F25: =StartDate+7*0 | G25: =StartDate+7*1 | H25: =StartDate+7*2 | I25: =StartDate+7*3 | J25: =StartDate+7*4 | K25: =StartDate+7*5 | L25: =StartDate+7*6 | M25: =StartDate+7*7 | N25: =StartDate+7*8 | O25: =StartDate+7*9 | P25: =StartDate+7*10 | Q25: =StartDate+7*11 | R25: =StartDate+7*12 | S25: =StartDate+7*13 | T25: =StartDate+7*14 | U25: =StartDate+7*15 | V25: =StartDate+7*16 | W25: =StartDate+7*17 | X25: =StartDate+7*18 | Y25: =StartDate+7*19 | Z25: =StartDate+7*20 | AA25: =StartDate+7*21 | AB25: =StartDate+7*22 | AC25: =StartDate+7*23 | AD25: =StartDate+7*24 | AE25: =StartDate+7*25
B26: POS Units | F26: =ROUND(BaseUnits*Inputs!F59,0) | G26: =ROUND(BaseUnits*Inputs!G59,0) | H26: =ROUND(BaseUnits*Inputs!H59,0) | I26: =ROUND(BaseUnits*Inputs!I59,0) | J26: =ROUND(BaseUnits*Inputs!J59,0) | K26: =ROUND(BaseUnits*Inputs!K59,0) | L26: =ROUND(BaseUnits*Inputs!L59,0) | M26: =ROUND(BaseUnits*Inputs!M59,0) | ... AE26: =ROUND(BaseUnits*Inputs!AE59,0) | AF26: =SUM(F26:AE26)
B27: Selling Price | F27: =Price | G27: =Price | H27: =Price | I27: =Price | J27: =Price | K27: =Price | L27: =Price | M27: =Price | ... AF27: =Price
B28: Revenue | F28: =F26*F27 | G28: =G26*G27 | H28: =H26*H27 | I28: =I26*I27 | J28: =J26*J27 | K28: =K26*K27 | L28: =L26*L27 | M28: =M26*M27 | ... AE28: =AE26*AE27 | AF28: =SUM(F28:AE28)
B29: Cost Price | F29: =Cost | G29: =Cost | H29: =Cost | I29: =Cost | J29: =Cost | K29: =Cost | L29: =Cost | M29: =Cost | ... AF29: =Cost
B30: Raw COGS | F30: =F26*F29 | G30: =G26*G29 | H30: =H26*H29 | I30: =I26*I29 | J30: =J26*J29 | K30: =K26*K29 | L30: =L26*L29 | M30: =M26*M29 | ... AE30: =AE26*AE29 | AF30: =SUM(F30:AE30)
B31: — Demo Spend | F31: =Inputs!F53*DemoCost | G31: =Inputs!G53*DemoCost | H31: =Inputs!H53*DemoCost | I31: =Inputs!I53*DemoCost | J31: =Inputs!J53*DemoCost | K31: =Inputs!K53*DemoCost | L31: =Inputs!L53*DemoCost | M31: =Inputs!M53*DemoCost | ... AE31: =Inputs!AE53*DemoCost | AF31: =SUM(F31:AE31)
B32: — End Cap Spend | F32: =Inputs!F54*EndCapCost | G32: =Inputs!G54*EndCapCost | H32: =Inputs!H54*EndCapCost | I32: =Inputs!I54*EndCapCost | J32: =Inputs!J54*EndCapCost | K32: =Inputs!K54*EndCapCost | L32: =Inputs!L54*EndCapCost | M32: =Inputs!M54*EndCapCost | ... AE32: =Inputs!AE54*EndCapCost | AF32: =SUM(F32:AE32)
B33: — Fence Spend | F33: =Inputs!F55*FenceCost | G33: =Inputs!G55*FenceCost | H33: =Inputs!H55*FenceCost | I33: =Inputs!I55*FenceCost | J33: =Inputs!J55*FenceCost | K33: =Inputs!K55*FenceCost | L33: =Inputs!L55*FenceCost | M33: =Inputs!M55*FenceCost | ... AE33: =Inputs!AE55*FenceCost | AF33: =SUM(F33:AE33)
B34: — TPD Spend | F34: =Inputs!F56*F26*F27*TPDPct | G34: =Inputs!G56*G26*G27*TPDPct | H34: =Inputs!H56*H26*H27*TPDPct | I34: =Inputs!I56*I26*I27*TPDPct | J34: =Inputs!J56*J26*J27*TPDPct | K34: =Inputs!K56*K26*K27*TPDPct | L34: =Inputs!L56*L26*L27*TPDPct | M34: =Inputs!M56*M26*M27*TPDPct | ... AE34: =Inputs!AE56*AE26*AE27*TPDPct | AF34: =SUM(F34:AE34)
B35: — Markdown Spend | F35: =Inputs!F57*F26*F27*MdPct | G35: =Inputs!G57*G26*G27*MdPct | H35: =Inputs!H57*H26*H27*MdPct | I35: =Inputs!I57*I26*I27*MdPct | J35: =Inputs!J57*J26*J27*MdPct | K35: =Inputs!K57*K26*K27*MdPct | L35: =Inputs!L57*L26*L27*MdPct | M35: =Inputs!M57*M26*M27*MdPct | ... AE35: =Inputs!AE57*AE26*AE27*MdPct | AF35: =SUM(F35:AE35)
B36: — Advertising Spend | F36: =Inputs!F58*AdvertCost | G36: =Inputs!G58*AdvertCost | H36: =Inputs!H58*AdvertCost | I36: =Inputs!I58*AdvertCost | J36: =Inputs!J58*AdvertCost | K36: =Inputs!K58*AdvertCost | L36: =Inputs!L58*AdvertCost | M36: =Inputs!M58*AdvertCost | ... AE36: =Inputs!AE58*AdvertCost | AF36: =SUM(F36:AE36)
B37: Total Promo Spend | F37: =SUM(F31:F36) | G37: =SUM(G31:G36) | H37: =SUM(H31:H36) | I37: =SUM(I31:I36) | J37: =SUM(J31:J36) | K37: =SUM(K31:K36) | L37: =SUM(L31:L36) | M37: =SUM(M31:M36) | ... AE37: =SUM(AE31:AE36) | AF37: =SUM(F37:AE37)
B38: Gross Profit | F38: =F28-F30 | G38: =G28-G30 | H38: =H28-H30 | I38: =I28-I30 | J38: =J28-J30 | K38: =K28-K30 | L38: =L28-L30 | M38: =M28-M30 | ... AE38: =AE28-AE30 | AF38: =SUM(F38:AE38)
B39: Net Profit (after promo) | F39: =F38-F37 | G39: =G38-G37 | H39: =H38-H37 | I39: =I38-I37 | J39: =J38-J37 | K39: =K38-K37 | L39: =L38-L37 | M39: =M38-M37 | ... AE39: =AE38-AE37 | AF39: =SUM(F39:AE39)
B42: WORST – Demo+EndCap+TPD then Markdown (Wks 18-20)
B43: Week | F43: W1 | G43: W2 | H43: W3 | I43: W4 | J43: W5 | K43: W6 | L43: W7 | M43: W8 | N43: W9 | O43: W10 | P43: W11 | Q43: W12 | R43: W13 | S43: W14 | T43: W15 | U43: W16 | V43: W17 | W43: W18 | X43: W19 | Y43: W20 | Z43: W21 | AA43: W22 | AB43: W23 | AC43: W24 | AD43: W25 | AE43: W26 | AF43: TOTAL
B44: Wk-commencing | F44: =StartDate+7*0 | G44: =StartDate+7*1 | H44: =StartDate+7*2 | I44: =StartDate+7*3 | J44: =StartDate+7*4 | K44: =StartDate+7*5 | L44: =StartDate+7*6 | M44: =StartDate+7*7 | N44: =StartDate+7*8 | O44: =StartDate+7*9 | P44: =StartDate+7*10 | Q44: =StartDate+7*11 | R44: =StartDate+7*12 | S44: =StartDate+7*13 | T44: =StartDate+7*14 | U44: =StartDate+7*15 | V44: =StartDate+7*16 | W44: =StartDate+7*17 | X44: =StartDate+7*18 | Y44: =StartDate+7*19 | Z44: =StartDate+7*20 | AA44: =StartDate+7*21 | AB44: =StartDate+7*22 | AC44: =StartDate+7*23 | AD44: =StartDate+7*24 | AE44: =StartDate+7*25
B45: POS Units | F45: =ROUND(BaseUnits*Inputs!F71,0) | G45: =ROUND(BaseUnits*Inputs!G71,0) | H45: =ROUND(BaseUnits*Inputs!H71,0) | I45: =ROUND(BaseUnits*Inputs!I71,0) | J45: =ROUND(BaseUnits*Inputs!J71,0) | K45: =ROUND(BaseUnits*Inputs!K71,0) | L45: =ROUND(BaseUnits*Inputs!L71,0) | M45: =ROUND(BaseUnits*Inputs!M71,0) | ... AE45: =ROUND(BaseUnits*Inputs!AE71,0) | AF45: =SUM(F45:AE45)
B46: Selling Price | F46: =Price | G46: =Price | H46: =Price | I46: =Price | J46: =Price | K46: =Price | L46: =Price | M46: =Price | ... AF46: =Price
B47: Revenue | F47: =F45*F46 | G47: =G45*G46 | H47: =H45*H46 | I47: =I45*I46 | J47: =J45*J46 | K47: =K45*K46 | L47: =L45*L46 | M47: =M45*M46 | ... AE47: =AE45*AE46 | AF47: =SUM(F47:AE47)
B48: Cost Price | F48: =Cost | G48: =Cost | H48: =Cost | I48: =Cost | J48: =Cost | K48: =Cost | L48: =Cost | M48: =Cost | ... AF48: =Cost
B49: Raw COGS | F49: =F45*F48 | G49: =G45*G48 | H49: =H45*H48 | I49: =I45*I48 | J49: =J45*J48 | K49: =K45*K48 | L49: =L45*L48 | M49: =M45*M48 | ... AE49: =AE45*AE48 | AF49: =SUM(F49:AE49)
B50: — Demo Spend | F50: =Inputs!F65*DemoCost | G50: =Inputs!G65*DemoCost | H50: =Inputs!H65*DemoCost | I50: =Inputs!I65*DemoCost | J50: =Inputs!J65*DemoCost | K50: =Inputs!K65*DemoCost | L50: =Inputs!L65*DemoCost | M50: =Inputs!M65*DemoCost | ... AE50: =Inputs!AE65*DemoCost | AF50: =SUM(F50:AE50)
B51: — End Cap Spend | F51: =Inputs!F66*EndCapCost | G51: =Inputs!G66*EndCapCost | H51: =Inputs!H66*EndCapCost | I51: =Inputs!I66*EndCapCost | J51: =Inputs!J66*EndCapCost | K51: =Inputs!K66*EndCapCost | L51: =Inputs!L66*EndCapCost | M51: =Inputs!M66*EndCapCost | ... AE51: =Inputs!AE66*EndCapCost | AF51: =SUM(F51:AE51)
B52: — Fence Spend | F52: =Inputs!F67*FenceCost | G52: =Inputs!G67*FenceCost | H52: =Inputs!H67*FenceCost | I52: =Inputs!I67*FenceCost | J52: =Inputs!J67*FenceCost | K52: =Inputs!K67*FenceCost | L52: =Inputs!L67*FenceCost | M52: =Inputs!M67*FenceCost | ... AE52: =Inputs!AE67*FenceCost | AF52: =SUM(F52:AE52)
B53: — TPD Spend | F53: =Inputs!F68*F45*F46*TPDPct | G53: =Inputs!G68*G45*G46*TPDPct | H53: =Inputs!H68*H45*H46*TPDPct | I53: =Inputs!I68*I45*I46*TPDPct | J53: =Inputs!J68*J45*J46*TPDPct | K53: =Inputs!K68*K45*K46*TPDPct | L53: =Inputs!L68*L45*L46*TPDPct | M53: =Inputs!M68*M45*M46*TPDPct | ... AE53: =Inputs!AE68*AE45*AE46*TPDPct | AF53: =SUM(F53:AE53)
B54: — Markdown Spend | F54: =Inputs!F69*F45*F46*MdPct | G54: =Inputs!G69*G45*G46*MdPct | H54: =Inputs!H69*H45*H46*MdPct | I54: =Inputs!I69*I45*I46*MdPct | J54: =Inputs!J69*J45*J46*MdPct | K54: =Inputs!K69*K45*K46*MdPct | L54: =Inputs!L69*L45*L46*MdPct | M54: =Inputs!M69*M45*M46*MdPct | ... AE54: =Inputs!AE69*AE45*AE46*MdPct | AF54: =SUM(F54:AE54)
B55: — Advertising Spend | F55: =Inputs!F70*AdvertCost | G55: =Inputs!G70*AdvertCost | H55: =Inputs!H70*AdvertCost | I55: =Inputs!I70*AdvertCost | J55: =Inputs!J70*AdvertCost | K55: =Inputs!K70*AdvertCost | L55: =Inputs!L70*AdvertCost | M55: =Inputs!M70*AdvertCost | ... AE55: =Inputs!AE70*AdvertCost | AF55: =SUM(F55:AE55)
B56: Total Promo Spend | F56: =SUM(F50:F55) | G56: =SUM(G50:G55) | H56: =SUM(H50:H55) | I56: =SUM(I50:I55) | J56: =SUM(J50:J55) | K56: =SUM(K50:K55) | L56: =SUM(L50:L55) | M56: =SUM(M50:M55) | ... AE56: =SUM(AE50:AE55) | AF56: =SUM(F56:AE56)
B57: Gross Profit | F57: =F47-F49 | G57: =G47-G49 | H57: =H47-H49 | I57: =I47-I49 | J57: =J47-J49 | K57: =K47-K49 | L57: =L47-L49 | M57: =M47-M49 | ... AE57: =AE47-AE49 | AF57: =SUM(F57:AE57)
B58: Net Profit (after promo) | F58: =F57-F56 | G58: =G57-G56 | H58: =H57-H56 | I58: =I57-I56 | J58: =J57-J56 | K58: =K57-K56 | L58: =L57-L56 | M58: =M57-M56 | ... AE58: =AE57-AE56 | AF58: =SUM(F58:AE58)

Sheet Summary
B2: ROI SUMMARY — Bee Propolis Scenario Comparison
B3: ="Test window: W1 ("&TEXT(StartDate,"dd-mmm-yyyy")&") → W"&Period&" ("&TEXT(StartDate+7*(Period-1),"dd-mmm-yyyy")&")"
B5: Metric | C5: BEST | D5: IDEAL | E5: WORST
B6: Units Sold | C6: =Forecast!AF7 | D6: =Forecast!AF26 | E6: =Forecast!AF45
B7: Revenue | C7: =Forecast!AF9 | D7: =Forecast!AF28 | E7: =Forecast!AF47
B8: Raw COGS | C8: =Forecast!AF11 | D8: =Forecast!AF30 | E8: =Forecast!AF49
B9: Gross Profit | C9: =Forecast!AF19 | D9: =Forecast!AF38 | E9: =Forecast!AF57
B10: Gross Margin % | C10: =IFERROR(Forecast!AF19/Forecast!AF9,0) | D10: =IFERROR(Forecast!AF38/Forecast!AF28,0) | E10: =IFERROR(Forecast!AF57/Forecast!AF47,0)
B11: Demo Spend | C11: =Forecast!AF12 | D11: =Forecast!AF31 | E11: =Forecast!AF50
B12: End Cap Spend | C12: =Forecast!AF13 | D12: =Forecast!AF32 | E12: =Forecast!AF51
B13: Fence Spend | C13: =Forecast!AF14 | D13: =Forecast!AF33 | E13: =Forecast!AF52
B14: TPD Spend | C14: =Forecast!AF15 | D14: =Forecast!AF34 | E14: =Forecast!AF53
B15: Markdown Spend | C15: =Forecast!AF16 | D15: =Forecast!AF35 | E15: =Forecast!AF54
B16: Advertising Spend | C16: =Forecast!AF17 | D16: =Forecast!AF36 | E16: =Forecast!AF55
B17: Total Promo Spend | C17: =Forecast!AF18 | D17: =Forecast!AF37 | E17: =Forecast!AF56
B18: Net Profit | C18: =Forecast!AF20 | D18: =Forecast!AF39 | E18: =Forecast!AF58
B19: Net Margin % | C19: =IFERROR(Forecast!AF20/Forecast!AF9,0) | D19: =IFERROR(Forecast!AF39/Forecast!AF28,0) | E19: =IFERROR(Forecast!AF58/Forecast!AF47,0)
B20: ROI on Promo Spend | C20: =IFERROR(Forecast!AF20/Forecast!AF18,0) | D20: =IFERROR(Forecast!AF39/Forecast!AF37,0) | E20: =IFERROR(Forecast!AF58/Forecast!AF56,0)
B21: Avg Units / WH / Week | C21: =IFERROR(Forecast!AF7/WHs/Period,0) | D21: =IFERROR(Forecast!AF26/WHs/Period,0) | E21: =IFERROR(Forecast!AF45/WHs/Period,0)
B24: Why each scenario?
B25: BEST | C25: Two demo weekends with TPD. Demo lifts ~3x in-week. No end cap, no markdown.
B26: IDEAL | C26: Demo + end cap + TPD stacked for two weeks. Combined velocity ~3.6x base.
B27: WORST | C27: Promo plan as IDEAL but residual inventory clears at 50% off over Wks 18-20.

Sheet Portfolio
B2: PORTFOLIO — D93 Pitch SKUs (Annual Y1 Roll-Up)
B3: Bee Propolis pre-filled at indicative annual numbers. For SKUs 2-7, paste SP / Cost / Y1 Units / Promo Spend from Asana into the yellow cells. Bottom row blends across SKUs.
B5: # | C5: Code | D5: SKU | E5: Pack | F5: SP £ | G5: Cost £ | H5: GM/u £ | I5: GM % | J5: Y1 Units | K5: Revenue £ | L5: COGS £ | M5: GP £ | N5: Promo £ | O5: Net Profit £ | P5: Net % | Q5: ROI % | R5: Rationale / status
B6: 1 | C6: UK-D93-#1 | D6: Bee Propolis Spray 30ml x2 | E6: 30ml x 2 | F6: 15.99 | G6: 7.29 | H6: =IFERROR(F6-G6,0) | I6: =IFERROR((F6-G6)/F6,0) | J6: 17000 | K6: =IFERROR(J6*F6,0) | L6: =IFERROR(J6*G6,0) | M6: =IFERROR(K6-L6,0) | N6: 25000 | O6: =IFERROR(M6-N6,0) | P6: =IFERROR(O6/K6,0) | Q6: =IFERROR(O6/N6,0) | R6: Lead pitch — strong GP%, supported by demo + TPD.
B7: 2 | C7: UK-D93-#2 | D7: Mag 8-in-1 90's/120's | H7: =IFERROR(F7-G7,0) | I7: =IFERROR((F7-G7)/F7,0) | K7: =IFERROR(J7*F7,0) | L7: =IFERROR(J7*G7,0) | M7: =IFERROR(K7-L7,0) | O7: =IFERROR(M7-N7,0) | P7: =IFERROR(O7/K7,0) | Q7: =IFERROR(O7/N7,0)
B8: 3 | C8: UK-D93-#3 | D8: O1 450g | H8: =IFERROR(F8-G8,0) | I8: =IFERROR((F8-G8)/F8,0) | K8: =IFERROR(J8*F8,0) | L8: =IFERROR(J8*G8,0) | M8: =IFERROR(K8-L8,0) | O8: =IFERROR(M8-N8,0) | P8: =IFERROR(O8/K8,0) | Q8: =IFERROR(O8/N8,0)
B9: 4 | C9: UK-D93-#4 | D9: Belli Bliss Raspberry, 450g | H9: =IFERROR(F9-G9,0) | I9: =IFERROR((F9-G9)/F9,0) | K9: =IFERROR(J9*F9,0) | L9: =IFERROR(J9*G9,0) | M9: =IFERROR(K9-L9,0) | O9: =IFERROR(M9-N9,0) | P9: =IFERROR(O9/K9,0) | Q9: =IFERROR(O9/N9,0)
B10: 5 | C10: UK-D93-#5 | D10: Daily Boost | H10: =IFERROR(F10-G10,0) | I10: =IFERROR((F10-G10)/F10,0) | K10: =IFERROR(J10*F10,0) | L10: =IFERROR(J10*G10,0) | M10: =IFERROR(K10-L10,0) | O10: =IFERROR(M10-N10,0) | P10: =IFERROR(O10/K10,0) | Q10: =IFERROR(O10/N10,0)
B11: 6 | C11: UK-D93-#6 | D11: Berberine 90's/120's | H11: =IFERROR(F11-G11,0) | I11: =IFERROR((F11-G11)/F11,0) | K11: =IFERROR(J11*F11,0) | L11: =IFERROR(J11*G11,0) | M11: =IFERROR(K11-L11,0) | O11: =IFERROR(M11-N11,0) | P11: =IFERROR(O11/K11,0) | Q11: =IFERROR(O11/N11,0)
B12: 7 | C12: UK-D93-#7 | D12: L-theanine Capsules 90's/120's | H12: =IFERROR(F12-G12,0) | I12: =IFERROR((F12-G12)/F12,0) | K12: =IFERROR(J12*F12,0) | L12: =IFERROR(J12*G12,0) | M12: =IFERROR(K12-L12,0) | O12: =IFERROR(M12-N12,0) | P12: =IFERROR(O12/K12,0) | Q12: =IFERROR(O12/N12,0)
D13: PORTFOLIO TOTAL / BLENDED | I13: =IFERROR(SUM(M6:M12)/SUM(K6:K12),0) | J13: =SUM(J6:J12) | K13: =SUM(K6:K12) | L13: =SUM(L6:L12) | M13: =SUM(M6:M12) | N13: =SUM(N6:N12) | O13: =SUM(O6:O12) | P13: =IFERROR(O13/K13,0) | Q13: =IFERROR(O13/N13,0) | R13: Blended across SKUs
B15: Blended GM% and Net% are revenue-weighted (Σ GP ÷ Σ Rev, Σ Net ÷ Σ Rev). Blended ROI is Σ Net Profit ÷ Σ Promo Spend. Yellow cells are inputs — fill in from Asana for rows 2-7.
