Workbook
Name UNITS_PER_CASE: Inputs!$B$5
Name SKU_LIST: Inputs!$A$9:$A$11
Name WHOLESALE_TABLE: Inputs!$B$9:$B$11
Name COGS_TABLE: Inputs!$C$9:$C$11
Name BEVMAX_LEAD: Inputs!$B$14
Name BEVMAX_CAP: Inputs!$B$15
Name TIER_LIST: Inputs!$A$19:$A$21
Name VELOCITY_TABLE: Inputs!$B$19:$D$21
Name RAMP_W1: Inputs!$B$24
Name RAMP_W2: Inputs!$B$25
Name RAMP_W3: Inputs!$B$26
Name RAMP_W4PLUS: Inputs!$B$27
Name ONLINE_AMZ: Inputs!$B$31:$B$33
Name ONLINE_DTC: Inputs!$C$31:$C$33
Name DOORS_ID: Doors!$A$5:$A$104
Name DOORS_BANNER: Doors!$B$5:$B$104
Name DOORS_NAME: Doors!$C$5:$C$104
Name DOORS_REGION: Doors!$E$5:$E$104
Name DOORS_TIER: Doors!$F$5:$F$104
Name DOORS_LIMELEMON: Doors!$G$5:$G$104
Name DOORS_PINEAPPLE: Doors!$H$5:$H$104
Name DOORS_RASPBERRY: Doors!$I$5:$I$104
Name DOORS_LAUNCH: Doors!$J$5:$J$104
Name BULK_ENABLED: 'Bulk Edit'!$B$5:$B$24
Name BULK_TIER: 'Bulk Edit'!$C$5:$C$24
Name BULK_SKU: 'Bulk Edit'!$D$5:$D$24
Name BULK_START: 'Bulk Edit'!$E$5:$E$24
Name BULK_END: 'Bulk Edit'!$F$5:$F$24
Name BULK_VALUE: 'Bulk Edit'!$G$5:$G$24
Name ACT_ID: Activations!$A$5:$A$34
Name ACT_TYPE: Activations!$B$5:$B$34
Name ACT_DOOR_SCOPE: Activations!$C$5:$C$34
Name ACT_SKU_SCOPE: Activations!$D$5:$D$34
Name ACT_START: Activations!$E$5:$E$34
Name ACT_END: Activations!$F$5:$F$34
Name ACT_UPLIFT: Activations!$G$5:$G$34
Name ACT_POSTLIFT: Activations!$H$5:$H$34
Name ACT_TRIAL: Activations!$I$5:$I$34
Name ACT_COST: Activations!$J$5:$J$34
Name ACTIVE_SCENARIO: Scenarios!$B$5
Name SCEN_MULT_TABLE: Scenarios!$B$9:$D$11
Name SCEN_NAMES: Scenarios!$B$8:$D$8
Name ACTIVE_MULT_TABLE: Scenarios!$B$14:$B$16
Name VG_DOOR_ID: 'Velocity Grid'!$B$5:$B$304
Name VG_BANNER: 'Velocity Grid'!$D$5:$D$304
Name VG_REGION: 'Velocity Grid'!$E$5:$E$304
Name VG_TIER: 'Velocity Grid'!$F$5:$F$304
Name VG_SKU: 'Velocity Grid'!$G$5:$G$304
Name VG_AUTH: 'Velocity Grid'!$H$5:$H$304
Name VG_LAUNCH: 'Velocity Grid'!$I$5:$I$304
Name VG_W1: 'Velocity Grid'!$J$5:$J$304
Name VG_W2: 'Velocity Grid'!$K$5:$K$304
Name VG_W3: 'Velocity Grid'!$L$5:$L$304
Name VG_W4: 'Velocity Grid'!$M$5:$M$304
Name VG_W5: 'Velocity Grid'!$N$5:$N$304
Name VG_W6: 'Velocity Grid'!$O$5:$O$304
Name VG_W7: 'Velocity Grid'!$P$5:$P$304
Name VG_W8: 'Velocity Grid'!$Q$5:$Q$304
Name VG_W9: 'Velocity Grid'!$R$5:$R$304
Name VG_W10: 'Velocity Grid'!$S$5:$S$304

Sheet Inputs
A1: Inputs and assumptions
A2: All yellow cells are editable. Source notes in column D.
A4: Case math
A5: Units per case | B5: 24 | D5: Six four packs per case. Locked structural constant.
A7: Wholesale pricing per case
A8: SKU | B8: Wholesale per case | C8: COGS per case | D8: Source note
A9: Lime Lemon | B9: 36 | C9: 18.5 | D9: Louis estimate, to validate with finance.
A10: Pineapple Passion Fruit | B10: 36 | C10: 18.5 | D10: Louis estimate, to validate with finance.
A11: Raspberry | B11: 36 | C11: 18.5 | D11: Louis estimate, to validate with finance.
A13: Bevmax co manufacturer
A14: Lead time in weeks | B14: 6 | D14: Weeks from PO release to delivery. Louis estimate, to validate.
A15: Weekly run capacity in cases | B15: 2500 | D15: Max cases per production week. Louis estimate, to validate.
A17: Default velocity by tier and SKU, units per week at steady state
A18: Tier | B18: Lime Lemon | C18: Pineapple Passion Fruit | D18: Raspberry | F18: Source: Louis estimate, to validate with category data.
A19: A | B19: 16 | C19: 14 | D19: 12
A20: B | B20: 10 | C20: 8 | D20: 7
A21: C | B21: 5 | C21: 4 | D21: 3
A23: Ramp curve, percent of steady state
A24: Week 1 | B24: 0.4 | D24: Editable. Louis estimate based on launch heuristic.
A25: Week 2 | B25: 0.6
A26: Week 3 | B26: 0.8
A27: Week 4 onward | B27: 1
A29: Online baseline, units per week at steady state
A30: SKU | B30: Amazon.ca | C30: Shopify DTC | D30: Source note
A31: Lime Lemon | B31: 160 | C31: 80 | D31: Placeholder. Louis estimate, to validate with channel managers.
A32: Pineapple Passion Fruit | B32: 140 | C32: 70 | D32: Placeholder. Louis estimate, to validate with channel managers.
A33: Raspberry | B33: 120 | C33: 60 | D33: Placeholder. Louis estimate, to validate with channel managers.
A35: Online ramp uses the same ramp curve above, starting from week 1.

Sheet Doors
A1: Door master list
A2: Replace placeholder rows with your authoritative door list. Launch Week is the first week a door receives shipment.
A4: Door ID | B4: Banner | C4: Store Name | D4: City | E4: Region | F4: Tier | G4: Lime Lemon Auth | H4: Pineapple Passion Fruit Auth | I4: Raspberry Auth | J4: Launch Week
A5: D001 | B5: Choices Markets | C5: Choices Vancouver 01 | D5: Vancouver | E5: Lower Mainland | F5: A | G5: Y | H5: Y | I5: Y | J5: 1
A6: D002 | B6: Nature's Fare Markets | C6: NatFare Burnaby 02 | D6: Burnaby | E6: Lower Mainland | F6: A | G6: Y | H6: Y | I6: Y | J6: 1
A7: D003 | B7: Whole Foods Market | C7: WFM Richmond 03 | D7: Richmond | E7: Lower Mainland | F7: A | G7: Y | H7: Y | I7: Y | J7: 1
A8: D004 | B8: Pomme Natural Market | C8: Pomme Surrey 04 | D8: Surrey | E8: Lower Mainland | F8: A | G8: Y | H8: Y | I8: Y | J8: 1
A9: D005 | B9: IGA Marketplace | C9: IGA Coquitlam 05 | D9: Coquitlam | E9: Lower Mainland | F9: A | G9: Y | H9: Y | I9: Y | J9: 1
A10: D006 | B10: Save On Foods | C10: SOF North Vancouver 06 | D10: North Vancouver | E10: Lower Mainland | F10: A | G10: Y | H10: Y | I10: Y | J10: 1
A11: D007 | B11: Urban Fare | C11: Urban West Vancouver 07 | D11: West Vancouver | E11: Lower Mainland | F11: A | G11: Y | H11: Y | I11: Y | J11: 1
A12: D008 | B12: Independent Grocer | C12: Indie Langley 08 | D12: Langley | E12: Lower Mainland | F12: A | G12: Y | H12: Y | I12: Y | J12: 1
A13: D009 | B13: Stong's Market | C13: Stongs New Westminster 09 | D13: New Westminster | E13: Lower Mainland | F13: A | G13: Y | H13: Y | I13: Y | J13: 1
A14: D010 | B14: Fresh St Market | C14: FreshSt Vancouver 01 | D14: Vancouver | E14: Lower Mainland | F14: A | G14: Y | H14: Y | I14: Y | J14: 1
A15: D011 | B15: Choices Markets | C15: Choices Burnaby 02 | D15: Burnaby | E15: Lower Mainland | F15: A | G15: Y | H15: Y | I15: Y | J15: 1
A16: D012 | B16: Nature's Fare Markets | C16: NatFare Richmond 03 | D16: Richmond | E16: Lower Mainland | F16: A | G16: Y | H16: Y | I16: Y | J16: 1
... A104: D100 | B104: Fresh St Market | C104: FreshSt Prince George 01 | D104: Prince George | E104: North | F104: C | G104: Y | H104: N | I104: Y | J104: 5

Sheet Velocity Grid
A1: Velocity Grid
A2: Heart of the model. Each row is one SKU at one door. W1 through W13 hold units per week. Formulas reflow when Inputs, Activations, Bulk Edit, or Scenarios change. Overtype a cell to apply a hard override. Overridden cells highlight in amber automatically.
A4: Row ID | B4: Door ID | C4: Door Name | D4: Banner | E4: Region | F4: Tier | G4: SKU | H4: Authorized | I4: Launch Week | J4: W1 | K4: W2 | L4: W3 | M4: W4 | N4: W5 | O4: W6 | P4: W7 | Q4: W8 | R4: W9 | S4: W10 | T4: W11 | U4: W12 | V4: W13
A5: R0001 | B5: =Doors!$A$5 | C5: =Doors!$C$5 | D5: =Doors!$B$5 | E5: =Doors!$E$5 | F5: =Doors!$F$5 | G5: Lime Lemon | H5: =Doors!$G$5 | I5: =Doors!$J$5 | J5: =IF(OR($H5<>"Y",1<$I5),0,IF(SUMPRODUCT(((BULK_ENABLED="Y")*((BULK_TIER="ALL")+(BULK_TIER=$F5))*((BULK_SKU="ALL")+(BULK_SKU=$G5))*(BULK_START<=1)*(BULK_END>=1)))>0,IFERROR(SUMPRODUCT(((BULK_ENABLED="Y")*((BULK_TIER="ALL")+(BULK_TIER=$F5))*((BULK_SKU="ALL")+(BULK_SKU=$G5))*(BULK_START<=1)*(BULK_END>=1))*IFERROR(BULK_VALUE,0))/MAX(1,SUMPRODUCT(((BULK_ENABLED="Y")*((BULK_TIER="ALL")+(BULK_TIER=$F5))*((BULK_SKU="ALL")+(BULK_SKU=$G5))*(BULK_START<=1)*(BULK_END>=1)))),0),ROUND((INDEX(VELOCITY_TABLE,MATCH($F5,TIER_LIST,0),1))*(IF((1-$I5+1)<=0,0,IF((1-$I5+1)=1,RAMP_W1,IF((1-$I5+1)=2,RAMP_W2,IF((1-$I5+1)=3,RAMP_W3,RAMP_W4PLUS)))))*(INDEX(ACTIVE_MULT_TABLE,1,1))*(1+SUMPRODUCT(SIGN(((ACT_DOOR_SCOPE="ALL")+(ACT_DOOR_SCOPE="TIER_"&$F5)+(ACT_DOOR_SCOPE=$B5)))*SIGN(((ACT_SKU_SCOPE="ALL")+(ACT_SKU_SCOPE=$G5)))*(ACT_START<=1)*(ACT_END>=1)*IFERROR(ACT_UPLIFT-1,0)))*(1+SUMPRODUCT(SIGN(((ACT_DOOR_SCOPE="ALL")+(ACT_DOOR_SCOPE="TIER_"&$F5)+(ACT_DOOR_SCOPE=$B5)))*SIGN(((ACT_SKU_SCOPE="ALL")+(ACT_SKU_SCOPE=$G5)))*(1>ACT_END)*(ACT_END>0)*IFERROR(ACT_POSTLIFT,0))),0))) | K5: =IF(OR($H5<>"Y",2<$I5),0,IF(SUMPRODUCT(((BULK_ENABLED="Y")*((BULK_TIER="ALL")+(BULK_TIER=$F5))*((BULK_SKU="ALL")+(BULK_SKU=$G5))*(BULK_START<=2)*(BULK_END>=2)))>0,IFERROR(SUMPRODUCT(((BULK_ENABLED="Y")*((BULK_TIER="ALL")+(BULK_TIER=$F5))*((BULK_SKU="ALL")+(BULK_SKU=$G5))*(BULK_START<=2)*(BULK_END>=2))*IFERROR(BULK_VALUE,0))/MAX(1,SUMPRODUCT(((BULK_ENABLED="Y")*((BULK_TIER="ALL")+(BULK_TIER=$F5))*((BULK_SKU="ALL")+(BULK_SKU=$G5))*(BULK_START<=2)*(BULK_END>=2)))),0),ROUND((INDEX(VELOCITY_TABLE,MATCH($F5,TIER_LIST,0),1))*(IF((2-$I5+1)<=0,0,IF((2-$I5+1)=1,RAMP_W1,IF((2-$I5+1)=2,RAMP_W2,IF((2-$I5+1)=3,RAMP_W3,RAMP_W4PLUS)))))*(INDEX(ACTIVE_MULT_TABLE,1,1))*(1+SUMPRODUCT(SIGN(((ACT_DOOR_SCOPE="ALL")+(ACT_DOOR_SCOPE="TIER_"&$F5)+(ACT_DOOR_SCOPE=$B5)))*SIGN(((ACT_SKU_SCOPE="ALL")+(ACT_SKU_SCOPE=$G5)))*(ACT_START<=2)*(ACT_END>=2)*IFERROR(ACT_UPLIFT-1,0)))*(1+SUMPRODUCT(SIGN(((ACT_DOOR_SCOPE="ALL")+(ACT_DOOR_SCOPE="TIER_"&$F5)+(ACT_DOOR_SCOPE=$B5)))*SIGN(((ACT_SKU_SCOPE="ALL")+(ACT_SKU_SCOPE=$G5)))*(2>ACT_END)*(ACT_END>0)*IFERROR(ACT_POSTLIFT,0))),0))) | L5: =IF(OR($H5<>"Y",3<$I5),0,IF(SUMPRODUCT(((BULK_ENABLED="Y")*((BULK_TIER="ALL")+(BULK_TIER=$F5))*((BULK_SKU="ALL")+(BULK_SKU=$G5))*(BULK_START<=3)*(BULK_END>=3)))>0,IFERROR(SUMPRODUCT(((BULK_ENABLED="Y")*((BULK_TIER="ALL")+(BULK_TIER=$F5))*((BULK_SKU="ALL")+(BULK_SKU=$G5))*(BULK_START<=3)*(BULK_END>=3))*IFERROR(BULK_VALUE,0))/MAX(1,SUMPRODUCT(((BULK_ENABLED="Y")*((BULK_TIER="ALL")+(BULK_TIER=$F5))*((BULK_SKU="ALL")+(BULK_SKU=$G5))*(BULK_START<=3)*(BULK_END>=3)))),0),ROUND((INDEX(VELOCITY_TABLE,MATCH($F5,TIER_LIST,0),1))*(IF((3-$I5+1)<=0,0,IF((3-$I5+1)=1,RAMP_W1,IF((3-$I5+1)=2,RAMP_W2,IF((3-$I5+1)=3,RAMP_W3,RAMP_W4PLUS)))))*(INDEX(ACTIVE_MULT_TABLE,1,1))*(1+SUMPRODUCT(SIGN(((ACT_DOOR_SCOPE="ALL")+(ACT_DOOR_SCOPE="TIER_"&$F5)+(ACT_DOOR_SCOPE=$B5)))*SIGN(((ACT_SKU_SCOPE="ALL")+(ACT_SKU_SCOPE=$G5)))*(ACT_START<=3)*(ACT_END>=3)*IFERROR(ACT_UPLIFT-1,0)))*(1+SUMPRODUCT(SIGN(((ACT_DOOR_SCOPE="ALL")+(ACT_DOOR_SCOPE="TIER_"&$F5)+(ACT_DOOR_SCOPE=$B5)))*SIGN(((ACT_SKU_SCOPE="ALL")+(ACT_SKU_SCOPE=$G5)))*(3>ACT_END)*(ACT_END>0)*IFERROR(ACT_POSTLIFT,0))),0))) | M5: =IF(OR($H5<>"Y",4<$I5),0,IF(SUMPRODUCT(((BULK_ENABLED="Y")*((BULK_TIER="ALL")+(BULK_TIER=$F5))*((BULK_SKU="ALL")+(BULK_SKU=$G5))*(BULK_START<=4)*(BULK_END>=4)))>0,IFERROR(SUMPRODUCT(((BULK_ENABLED="Y")*((BULK_TIER="ALL")+(BULK_TIER=$F5))*((BULK_SKU="ALL")+(BULK_SKU=$G5))*(BULK_START<=4)*(BULK_END>=4))*IFERROR(BULK_VALUE,0))/MAX(1,SUMPRODUCT(((BULK_ENABLED="Y")*((BULK_TIER="ALL")+(BULK_TIER=$F5))*((BULK_SKU="ALL")+(BULK_SKU=$G5))*(BULK_START<=4)*(BULK_END>=4)))),0),ROUND((INDEX(VELOCITY_TABLE,MATCH($F5,TIER_LIST,0),1))*(IF((4-$I5+1)<=0,0,IF((4-$I5+1)=1,RAMP_W1,IF((4-$I5+1)=2,RAMP_W2,IF((4-$I5+1)=3,RAMP_W3,RAMP_W4PLUS)))))*(INDEX(ACTIVE_MULT_TABLE,1,1))*(1+SUMPRODUCT(SIGN(((ACT_DOOR_SCOPE="ALL")+(ACT_DOOR_SCOPE="TIER_"&$F5)+(ACT_DOOR_SCOPE=$B5)))*SIGN(((ACT_SKU_SCOPE="ALL")+(ACT_SKU_SCOPE=$G5)))*(ACT_START<=4)*(ACT_END>=4)*IFERROR(ACT_UPLIFT-1,0)))*(1+SUMPRODUCT(SIGN(((ACT_DOOR_SCOPE="ALL")+(ACT_DOOR_SCOPE="TIER_"&$F5)+(ACT_DOOR_SCOPE=$B5)))*SIGN(((ACT_SKU_SCOPE="ALL")+(ACT_SKU_SCOPE=$G5)))*(4>ACT_END)*(ACT_END>0)*IFERROR(ACT_POSTLIFT,0))),0))) | N5: =IF(OR($H5<>"Y",5<$I5),0,IF(SUMPRODUCT(((BULK_ENABLED="Y")*((BULK_TIER="ALL")+(BULK_TIER=$F5))*((BULK_SKU="ALL")+(BULK_SKU=$G5))*(BULK_START<=5)*(BULK_END>=5)))>0,IFERROR(SUMPRODUCT(((BULK_ENABLED="Y")*((BULK_TIER="ALL")+(BULK_TIER=$F5))*((BULK_SKU="ALL")+(BULK_SKU=$G5))*(BULK_START<=5)*(BULK_END>=5))*IFERROR(BULK_VALUE,0))/MAX(1,SUMPRODUCT(((BULK_ENABLED="Y")*((BULK_TIER="ALL")+(BULK_TIER=$F5))*((BULK_SKU="ALL")+(BULK_SKU=$G5))*(BULK_START<=5)*(BULK_END>=5)))),0),ROUND((INDEX(VELOCITY_TABLE,MATCH($F5,TIER_LIST,0),1))*(IF((5-$I5+1)<=0,0,IF((5-$I5+1)=1,RAMP_W1,IF((5-$I5+1)=2,RAMP_W2,IF((5-$I5+1)=3,RAMP_W3,RAMP_W4PLUS)))))*(INDEX(ACTIVE_MULT_TABLE,1,1))*(1+SUMPRODUCT(SIGN(((ACT_DOOR_SCOPE="ALL")+(ACT_DOOR_SCOPE="TIER_"&$F5)+(ACT_DOOR_SCOPE=$B5)))*SIGN(((ACT_SKU_SCOPE="ALL")+(ACT_SKU_SCOPE=$G5)))*(ACT_START<=5)*(ACT_END>=5)*IFERROR(ACT_UPLIFT-1,0)))*(1+SUMPRODUCT(SIGN(((ACT_DOOR_SCOPE="ALL")+(ACT_DOOR_SCOPE="TIER_"&$F5)+(ACT_DOOR_SCOPE=$B5)))*SIGN(((ACT_SKU_SCOPE="ALL")+(ACT_SKU_SCOPE=$G5)))*(5>ACT_END)*(ACT_END>0)*IFERROR(ACT_POSTLIFT,0))),0))) | O5: =IF(OR($H5<>"Y",6<$I5),0,IF(SUMPRODUCT(((BULK_ENABLED="Y")*((BULK_TIER="ALL")+(BULK_TIER=$F5))*((BULK_SKU="ALL")+(BULK_SKU=$G5))*(BULK_START<=6)*(BULK_END>=6)))>0,IFERROR(SUMPRODUCT(((BULK_ENABLED="Y")*((BULK_TIER="ALL")+(BULK_TIER=$F5))*((BULK_SKU="ALL")+(BULK_SKU=$G5))*(BULK_START<=6)*(BULK_END>=6))*IFERROR(BULK_VALUE,0))/MAX(1,SUMPRODUCT(((BULK_ENABLED="Y")*((BULK_TIER="ALL")+(BULK_TIER=$F5))*((BULK_SKU="ALL")+(BULK_SKU=$G5))*(BULK_START<=6)*(BULK_END>=6)))),0),ROUND((INDEX(VELOCITY_TABLE,MATCH($F5,TIER_LIST,0),1))*(IF((6-$I5+1)<=0,0,IF((6-$I5+1)=1,RAMP_W1,IF((6-$I5+1)=2,RAMP_W2,IF((6-$I5+1)=3,RAMP_W3,RAMP_W4PLUS)))))*(INDEX(ACTIVE_MULT_TABLE,1,1))*(1+SUMPRODUCT(SIGN(((ACT_DOOR_SCOPE="ALL")+(ACT_DOOR_SCOPE="TIER_"&$F5)+(ACT_DOOR_SCOPE=$B5)))*SIGN(((ACT_SKU_SCOPE="ALL")+(ACT_SKU_SCOPE=$G5)))*(ACT_START<=6)*(ACT_END>=6)*IFERROR(ACT_UPLIFT-1,0)))*(1+SUMPRODUCT(SIGN(((ACT_DOOR_SCOPE="ALL")+(ACT_DOOR_SCOPE="TIER_"&$F5)+(ACT_DOOR_SCOPE=$B5)))*SIGN(((ACT_SKU_SCOPE="ALL")+(ACT_SKU_SCOPE=$G5)))*(6>ACT_END)*(ACT_END>0)*IFERROR(ACT_POSTLIFT,0))),0))) | P5: =IF(OR($H5<>"Y",7<$I5),0,IF(SUMPRODUCT(((BULK_ENABLED="Y")*((BULK_TIER="ALL")+(BULK_TIER=$F5))*((BULK_SKU="ALL")+(BULK_SKU=$G5))*(BULK_START<=7)*(BULK_END>=7)))>0,IFERROR(SUMPRODUCT(((BULK_ENABLED="Y")*((BULK_TIER="ALL")+(BULK_TIER=$F5))*((BULK_SKU="ALL")+(BULK_SKU=$G5))*(BULK_START<=7)*(BULK_END>=7))*IFERROR(BULK_VALUE,0))/MAX(1,SUMPRODUCT(((BULK_ENABLED="Y")*((BULK_TIER="ALL")+(BULK_TIER=$F5))*((BULK_SKU="ALL")+(BULK_SKU=$G5))*(BULK_START<=7)*(BULK_END>=7)))),0),ROUND((INDEX(VELOCITY_TABLE,MATCH($F5,TIER_LIST,0),1))*(IF((7-$I5+1)<=0,0,IF((7-$I5+1)=1,RAMP_W1,IF((7-$I5+1)=2,RAMP_W2,IF((7-$I5+1)=3,RAMP_W3,RAMP_W4PLUS)))))*(INDEX(ACTIVE_MULT_TABLE,1,1))*(1+SUMPRODUCT(SIGN(((ACT_DOOR_SCOPE="ALL")+(ACT_DOOR_SCOPE="TIER_"&$F5)+(ACT_DOOR_SCOPE=$B5)))*SIGN(((ACT_SKU_SCOPE="ALL")+(ACT_SKU_SCOPE=$G5)))*(ACT_START<=7)*(ACT_END>=7)*IFERROR(ACT_UPLIFT-1,0)))*(1+SUMPRODUCT(SIGN(((ACT_DOOR_SCOPE="ALL")+(ACT_DOOR_SCOPE="TIER_"&$F5)+(ACT_DOOR_SCOPE=$B5)))*SIGN(((ACT_SKU_SCOPE="ALL")+(ACT_SKU_SCOPE=$G5)))*(7>ACT_END)*(ACT_END>0)*IFERROR(ACT_POSTLIFT,0))),0))) | Q5: =IF(OR($H5<>"Y",8<$I5),0,IF(SUMPRODUCT(((BULK_ENABLED="Y")*((BULK_TIER="ALL")+(BULK_TIER=$F5))*((BULK_SKU="ALL")+(BULK_SKU=$G5))*(BULK_START<=8)*(BULK_END>=8)))>0,IFERROR(SUMPRODUCT(((BULK_ENABLED="Y")*((BULK_TIER="ALL")+(BULK_TIER=$F5))*((BULK_SKU="ALL")+(BULK_SKU=$G5))*(BULK_START<=8)*(BULK_END>=8))*IFERROR(BULK_VALUE,0))/MAX(1,SUMPRODUCT(((BULK_ENABLED="Y")*((BULK_TIER="ALL")+(BULK_TIER=$F5))*((BULK_SKU="ALL")+(BULK_SKU=$G5))*(BULK_START<=8)*(BULK_END>=8)))),0),ROUND((INDEX(VELOCITY_TABLE,MATCH($F5,TIER_LIST,0),1))*(IF((8-$I5+1)<=0,0,IF((8-$I5+1)=1,RAMP_W1,IF((8-$I5+1)=2,RAMP_W2,IF((8-$I5+1)=3,RAMP_W3,RAMP_W4PLUS)))))*(INDEX(ACTIVE_MULT_TABLE,1,1))*(1+SUMPRODUCT(SIGN(((ACT_DOOR_SCOPE="ALL")+(ACT_DOOR_SCOPE="TIER_"&$F5)+(ACT_DOOR_SCOPE=$B5)))*SIGN(((ACT_SKU_SCOPE="ALL")+(ACT_SKU_SCOPE=$G5)))*(ACT_START<=8)*(ACT_END>=8)*IFERROR(ACT_UPLIFT-1,0)))*(1+SUMPRODUCT(SIGN(((ACT_DOOR_SCOPE="ALL")+(ACT_DOOR_SCOPE="TIER_"&$F5)+(ACT_DOOR_SCOPE=$B5)))*SIGN(((ACT_SKU_SCOPE="ALL")+(ACT_SKU_SCOPE=$G5)))*(8>ACT_END)*(ACT_END>0)*IFERROR(ACT_POSTLIFT,0))),0))) | R5: =IF(OR($H5<>"Y",9<$I5),0,IF(SUMPRODUCT(((BULK_ENABLED="Y")*((BULK_TIER="ALL")+(BULK_TIER=$F5))*((BULK_SKU="ALL")+(BULK_SKU=$G5))*(BULK_START<=9)*(BULK_END>=9)))>0,IFERROR(SUMPRODUCT(((BULK_ENABLED="Y")*((BULK_TIER="ALL")+(BULK_TIER=$F5))*((BULK_SKU="ALL")+(BULK_SKU=$G5))*(BULK_START<=9)*(BULK_END>=9))*IFERROR(BULK_VALUE,0))/MAX(1,SUMPRODUCT(((BULK_ENABLED="Y")*((BULK_TIER="ALL")+(BULK_TIER=$F5))*((BULK_SKU="ALL")+(BULK_SKU=$G5))*(BULK_START<=9)*(BULK_END>=9)))),0),ROUND((INDEX(VELOCITY_TABLE,MATCH($F5,TIER_LIST,0),1))*(IF((9-$I5+1)<=0,0,IF((9-$I5+1)=1,RAMP_W1,IF((9-$I5+1)=2,RAMP_W2,IF((9-$I5+1)=3,RAMP_W3,RAMP_W4PLUS)))))*(INDEX(ACTIVE_MULT_TABLE,1,1))*(1+SUMPRODUCT(SIGN(((ACT_DOOR_SCOPE="ALL")+(ACT_DOOR_SCOPE="TIER_"&$F5)+(ACT_DOOR_SCOPE=$B5)))*SIGN(((ACT_SKU_SCOPE="ALL")+(ACT_SKU_SCOPE=$G5)))*(ACT_START<=9)*(ACT_END>=9)*IFERROR(ACT_UPLIFT-1,0)))*(1+SUMPRODUCT(SIGN(((ACT_DOOR_SCOPE="ALL")+(ACT_DOOR_SCOPE="TIER_"&$F5)+(ACT_DOOR_SCOPE=$B5)))*SIGN(((ACT_SKU_SCOPE="ALL")+(ACT_SKU_SCOPE=$G5)))*(9>ACT_END)*(ACT_END>0)*IFERROR(ACT_POSTLIFT,0))),0))) | S5: =IF(OR($H5<>"Y",10<$I5),0,IF(SUMPRODUCT(((BULK_ENABLED="Y")*((BULK_TIER="ALL")+(BULK_TIER=$F5))*((BULK_SKU="ALL")+(BULK_SKU=$G5))*(BULK_START<=10)*(BULK_END>=10)))>0,IFERROR(SUMPRODUCT(((BULK_ENABLED="Y")*((BULK_TIER="ALL")+(BULK_TIER=$F5))*((BULK_SKU="ALL")+(BULK_SKU=$G5))*(BULK_START<=10)*(BULK_END>=10))*IFERROR(BULK_VALUE,0))/MAX(1,SUMPRODUCT(((BULK_ENABLED="Y")*((BULK_TIER="ALL")+(BULK_TIER=$F5))*((BULK_SKU="ALL")+(BULK_SKU=$G5))*(BULK_START<=10)*(BULK_END>=10)))),0),ROUND((INDEX(VELOCITY_TABLE,MATCH($F5,TIER_LIST,0),1))*(IF((10-$I5+1)<=0,0,IF((10-$I5+1)=1,RAMP_W1,IF((10-$I5+1)=2,RAMP_W2,IF((10-$I5+1)=3,RAMP_W3,RAMP_W4PLUS)))))*(INDEX(ACTIVE_MULT_TABLE,1,1))*(1+SUMPRODUCT(SIGN(((ACT_DOOR_SCOPE="ALL")+(ACT_DOOR_SCOPE="TIER_"&$F5)+(ACT_DOOR_SCOPE=$B5)))*SIGN(((ACT_SKU_SCOPE="ALL")+(ACT_SKU_SCOPE=$G5)))*(ACT_START<=10)*(ACT_END>=10)*IFERROR(ACT_UPLIFT-1,0)))*(1+SUMPRODUCT(SIGN(((ACT_DOOR_SCOPE="ALL")+(ACT_DOOR_SCOPE="TIER_"&$F5)+(ACT_DOOR_SCOPE=$B5)))*SIGN(((ACT_SKU_SCOPE="ALL")+(ACT_SKU_SCOPE=$G5)))*(10>ACT_END)*(ACT_END>0)*IFERROR(ACT_POSTLIFT,0))),0))) | T5: =IF(OR($H5<>"Y",11<$I5),0,IF(SUMPRODUCT(((BULK_ENABLED="Y")*((BULK_TIER="ALL")+(BULK_TIER=$F5))*((BULK_SKU="ALL")+(BULK_SKU=$G5))*(BULK_START<=11)*(BULK_END>=11)))>0,IFERROR(SUMPRODUCT(((BULK_ENABLED="Y")*((BULK_TIER="ALL")+(BULK_TIER=$F5))*((BULK_SKU="ALL")+(BULK_SKU=$G5))*(BULK_START<=11)*(BULK_END>=11))*IFERROR(BULK_VALUE,0))/MAX(1,SUMPRODUCT(((BULK_ENABLED="Y")*((BULK_TIER="ALL")+(BULK_TIER=$F5))*((BULK_SKU="ALL")+(BULK_SKU=$G5))*(BULK_START<=11)*(BULK_END>=11)))),0),ROUND((INDEX(VELOCITY_TABLE,MATCH($F5,TIER_LIST,0),1))*(IF((11-$I5+1)<=0,0,IF((11-$I5+1)=1,RAMP_W1,IF((11-$I5+1)=2,RAMP_W2,IF((11-$I5+1)=3,RAMP_W3,RAMP_W4PLUS)))))*(INDEX(ACTIVE_MULT_TABLE,1,1))*(1+SUMPRODUCT(SIGN(((ACT_DOOR_SCOPE="ALL")+(ACT_DOOR_SCOPE="TIER_"&$F5)+(ACT_DOOR_SCOPE=$B5)))*SIGN(((ACT_SKU_SCOPE="ALL")+(ACT_SKU_SCOPE=$G5)))*(ACT_START<=11)*(ACT_END>=11)*IFERROR(ACT_UPLIFT-1,0)))*(1+SUMPRODUCT(SIGN(((ACT_DOOR_SCOPE="ALL")+(ACT_DOOR_SCOPE="TIER_"&$F5)+(ACT_DOOR_SCOPE=$B5)))*SIGN(((ACT_SKU_SCOPE="ALL")+(ACT_SKU_SCOPE=$G5)))*(11>ACT_END)*(ACT_END>0)*IFERROR(ACT_POSTLIFT,0))),0))) | U5: =IF(OR($H5<>"Y",12<$I5),0,IF(SUMPRODUCT(((BULK_ENABLED="Y")*((BULK_TIER="ALL")+(BULK_TIER=$F5))*((BULK_SKU="ALL")+(BULK_SKU=$G5))*(BULK_START<=12)*(BULK_END>=12)))>0,IFERROR(SUMPRODUCT(((BULK_ENABLED="Y")*((BULK_TIER="ALL")+(BULK_TIER=$F5))*((BULK_SKU="ALL")+(BULK_SKU=$G5))*(BULK_START<=12)*(BULK_END>=12))*IFERROR(BULK_VALUE,0))/MAX(1,SUMPRODUCT(((BULK_ENABLED="Y")*((BULK_TIER="ALL")+(BULK_TIER=$F5))*((BULK_SKU="ALL")+(BULK_SKU=$G5))*(BULK_START<=12)*(BULK_END>=12)))),0),ROUND((INDEX(VELOCITY_TABLE,MATCH($F5,TIER_LIST,0),1))*(IF((12-$I5+1)<=0,0,IF((12-$I5+1)=1,RAMP_W1,IF((12-$I5+1)=2,RAMP_W2,IF((12-$I5+1)=3,RAMP_W3,RAMP_W4PLUS)))))*(INDEX(ACTIVE_MULT_TABLE,1,1))*(1+SUMPRODUCT(SIGN(((ACT_DOOR_SCOPE="ALL")+(ACT_DOOR_SCOPE="TIER_"&$F5)+(ACT_DOOR_SCOPE=$B5)))*SIGN(((ACT_SKU_SCOPE="ALL")+(ACT_SKU_SCOPE=$G5)))*(ACT_START<=12)*(ACT_END>=12)*IFERROR(ACT_UPLIFT-1,0)))*(1+SUMPRODUCT(SIGN(((ACT_DOOR_SCOPE="ALL")+(ACT_DOOR_SCOPE="TIER_"&$F5)+(ACT_DOOR_SCOPE=$B5)))*SIGN(((ACT_SKU_SCOPE="ALL")+(ACT_SKU_SCOPE=$G5)))*(12>ACT_END)*(ACT_END>0)*IFERROR(ACT_POSTLIFT,0))),0))) | V5: =IF(OR($H5<>"Y",13<$I5),0,IF(SUMPRODUCT(((BULK_ENABLED="Y")*((BULK_TIER="ALL")+(BULK_TIER=$F5))*((BULK_SKU="ALL")+(BULK_SKU=$G5))*(BULK_START<=13)*(BULK_END>=13)))>0,IFERROR(SUMPRODUCT(((BULK_ENABLED="Y")*((BULK_TIER="ALL")+(BULK_TIER=$F5))*((BULK_SKU="ALL")+(BULK_SKU=$G5))*(BULK_START<=13)*(BULK_END>=13))*IFERROR(BULK_VALUE,0))/MAX(1,SUMPRODUCT(((BULK_ENABLED="Y")*((BULK_TIER="ALL")+(BULK_TIER=$F5))*((BULK_SKU="ALL")+(BULK_SKU=$G5))*(BULK_START<=13)*(BULK_END>=13)))),0),ROUND((INDEX(VELOCITY_TABLE,MATCH($F5,TIER_LIST,0),1))*(IF((13-$I5+1)<=0,0,IF((13-$I5+1)=1,RAMP_W1,IF((13-$I5+1)=2,RAMP_W2,IF((13-$I5+1)=3,RAMP_W3,RAMP_W4PLUS)))))*(INDEX(ACTIVE_MULT_TABLE,1,1))*(1+SUMPRODUCT(SIGN(((ACT_DOOR_SCOPE="ALL")+(ACT_DOOR_SCOPE="TIER_"&$F5)+(ACT_DOOR_SCOPE=$B5)))*SIGN(((ACT_SKU_SCOPE="ALL")+(ACT_SKU_SCOPE=$G5)))*(ACT_START<=13)*(ACT_END>=13)*IFERROR(ACT_UPLIFT-1,0)))*(1+SUMPRODUCT(SIGN(((ACT_DOOR_SCOPE="ALL")+(ACT_DOOR_SCOPE="TIER_"&$F5)+(ACT_DOOR_SCOPE=$B5)))*SIGN(((ACT_SKU_SCOPE="ALL")+(ACT_SKU_SCOPE=$G5)))*(13>ACT_END)*(ACT_END>0)*IFERROR(ACT_POSTLIFT,0))),0)))
A6: R0002 | B6: =Doors!$A$5 | C6: =Doors!$C$5 | D6: =Doors!$B$5 | E6: =Doors!$E$5 | F6: =Doors!$F$5 | G6: Pineapple Passion Fruit | H6: =Doors!$H$5 | I6: =Doors!$J$5 | J6: =IF(OR($H6<>"Y",1<$I6),0,IF(SUMPRODUCT(((BULK_ENABLED="Y")*((BULK_TIER="ALL")+(BULK_TIER=$F6))*((BULK_SKU="ALL")+(BULK_SKU=$G6))*(BULK_START<=1)*(BULK_END>=1)))>0,IFERROR(SUMPRODUCT(((BULK_ENABLED="Y")*((BULK_TIER="ALL")+(BULK_TIER=$F6))*((BULK_SKU="ALL")+(BULK_SKU=$G6))*(BULK_START<=1)*(BULK_END>=1))*IFERROR(BULK_VALUE,0))/MAX(1,SUMPRODUCT(((BULK_ENABLED="Y")*((BULK_TIER="ALL")+(BULK_TIER=$F6))*((BULK_SKU="ALL")+(BULK_SKU=$G6))*(BULK_START<=1)*(BULK_END>=1)))),0),ROUND((INDEX(VELOCITY_TABLE,MATCH($F6,TIER_LIST,0),2))*(IF((1-$I6+1)<=0,0,IF((1-$I6+1)=1,RAMP_W1,IF((1-$I6+1)=2,RAMP_W2,IF((1-$I6+1)=3,RAMP_W3,RAMP_W4PLUS)))))*(INDEX(ACTIVE_MULT_TABLE,2,1))*(1+SUMPRODUCT(SIGN(((ACT_DOOR_SCOPE="ALL")+(ACT_DOOR_SCOPE="TIER_"&$F6)+(ACT_DOOR_SCOPE=$B6)))*SIGN(((ACT_SKU_SCOPE="ALL")+(ACT_SKU_SCOPE=$G6)))*(ACT_START<=1)*(ACT_END>=1)*IFERROR(ACT_UPLIFT-1,0)))*(1+SUMPRODUCT(SIGN(((ACT_DOOR_SCOPE="ALL")+(ACT_DOOR_SCOPE="TIER_"&$F6)+(ACT_DOOR_SCOPE=$B6)))*SIGN(((ACT_SKU_SCOPE="ALL")+(ACT_SKU_SCOPE=$G6)))*(1>ACT_END)*(ACT_END>0)*IFERROR(ACT_POSTLIFT,0))),0))) | K6: =IF(OR($H6<>"Y",2<$I6),0,IF(SUMPRODUCT(((BULK_ENABLED="Y")*((BULK_TIER="ALL")+(BULK_TIER=$F6))*((BULK_SKU="ALL")+(BULK_SKU=$G6))*(BULK_START<=2)*(BULK_END>=2)))>0,IFERROR(SUMPRODUCT(((BULK_ENABLED="Y")*((BULK_TIER="ALL")+(BULK_TIER=$F6))*((BULK_SKU="ALL")+(BULK_SKU=$G6))*(BULK_START<=2)*(BULK_END>=2))*IFERROR(BULK_VALUE,0))/MAX(1,SUMPRODUCT(((BULK_ENABLED="Y")*((BULK_TIER="ALL")+(BULK_TIER=$F6))*((BULK_SKU="ALL")+(BULK_SKU=$G6))*(BULK_START<=2)*(BULK_END>=2)))),0),ROUND((INDEX(VELOCITY_TABLE,MATCH($F6,TIER_LIST,0),2))*(IF((2-$I6+1)<=0,0,IF((2-$I6+1)=1,RAMP_W1,IF((2-$I6+1)=2,RAMP_W2,IF((2-$I6+1)=3,RAMP_W3,RAMP_W4PLUS)))))*(INDEX(ACTIVE_MULT_TABLE,2,1))*(1+SUMPRODUCT(SIGN(((ACT_DOOR_SCOPE="ALL")+(ACT_DOOR_SCOPE="TIER_"&$F6)+(ACT_DOOR_SCOPE=$B6)))*SIGN(((ACT_SKU_SCOPE="ALL")+(ACT_SKU_SCOPE=$G6)))*(ACT_START<=2)*(ACT_END>=2)*IFERROR(ACT_UPLIFT-1,0)))*(1+SUMPRODUCT(SIGN(((ACT_DOOR_SCOPE="ALL")+(ACT_DOOR_SCOPE="TIER_"&$F6)+(ACT_DOOR_SCOPE=$B6)))*SIGN(((ACT_SKU_SCOPE="ALL")+(ACT_SKU_SCOPE=$G6)))*(2>ACT_END)*(ACT_END>0)*IFERROR(ACT_POSTLIFT,0))),0))) | L6: =IF(OR($H6<>"Y",3<$I6),0,IF(SUMPRODUCT(((BULK_ENABLED="Y")*((BULK_TIER="ALL")+(BULK_TIER=$F6))*((BULK_SKU="ALL")+(BULK_SKU=$G6))*(BULK_START<=3)*(BULK_END>=3)))>0,IFERROR(SUMPRODUCT(((BULK_ENABLED="Y")*((BULK_TIER="ALL")+(BULK_TIER=$F6))*((BULK_SKU="ALL")+(BULK_SKU=$G6))*(BULK_START<=3)*(BULK_END>=3))*IFERROR(BULK_VALUE,0))/MAX(1,SUMPRODUCT(((BULK_ENABLED="Y")*((BULK_TIER="ALL")+(BULK_TIER=$F6))*((BULK_SKU="ALL")+(BULK_SKU=$G6))*(BULK_START<=3)*(BULK_END>=3)))),0),ROUND((INDEX(VELOCITY_TABLE,MATCH($F6,TIER_LIST,0),2))*(IF((3-$I6+1)<=0,0,IF((3-$I6+1)=1,RAMP_W1,IF((3-$I6+1)=2,RAMP_W2,IF((3-$I6+1)=3,RAMP_W3,RAMP_W4PLUS)))))*(INDEX(ACTIVE_MULT_TABLE,2,1))*(1+SUMPRODUCT(SIGN(((ACT_DOOR_SCOPE="ALL")+(ACT_DOOR_SCOPE="TIER_"&$F6)+(ACT_DOOR_SCOPE=$B6)))*SIGN(((ACT_SKU_SCOPE="ALL")+(ACT_SKU_SCOPE=$G6)))*(ACT_START<=3)*(ACT_END>=3)*IFERROR(ACT_UPLIFT-1,0)))*(1+SUMPRODUCT(SIGN(((ACT_DOOR_SCOPE="ALL")+(ACT_DOOR_SCOPE="TIER_"&$F6)+(ACT_DOOR_SCOPE=$B6)))*SIGN(((ACT_SKU_SCOPE="ALL")+(ACT_SKU_SCOPE=$G6)))*(3>ACT_END)*(ACT_END>0)*IFERROR(ACT_POSTLIFT,0))),0))) | M6: =IF(OR($H6<>"Y",4<$I6),0,IF(SUMPRODUCT(((BULK_ENABLED="Y")*((BULK_TIER="ALL")+(BULK_TIER=$F6))*((BULK_SKU="ALL")+(BULK_SKU=$G6))*(BULK_START<=4)*(BULK_END>=4)))>0,IFERROR(SUMPRODUCT(((BULK_ENABLED="Y")*((BULK_TIER="ALL")+(BULK_TIER=$F6))*((BULK_SKU="ALL")+(BULK_SKU=$G6))*(BULK_START<=4)*(BULK_END>=4))*IFERROR(BULK_VALUE,0))/MAX(1,SUMPRODUCT(((BULK_ENABLED="Y")*((BULK_TIER="ALL")+(BULK_TIER=$F6))*((BULK_SKU="ALL")+(BULK_SKU=$G6))*(BULK_START<=4)*(BULK_END>=4)))),0),ROUND((INDEX(VELOCITY_TABLE,MATCH($F6,TIER_LIST,0),2))*(IF((4-$I6+1)<=0,0,IF((4-$I6+1)=1,RAMP_W1,IF((4-$I6+1)=2,RAMP_W2,IF((4-$I6+1)=3,RAMP_W3,RAMP_W4PLUS)))))*(INDEX(ACTIVE_MULT_TABLE,2,1))*(1+SUMPRODUCT(SIGN(((ACT_DOOR_SCOPE="ALL")+(ACT_DOOR_SCOPE="TIER_"&$F6)+(ACT_DOOR_SCOPE=$B6)))*SIGN(((ACT_SKU_SCOPE="ALL")+(ACT_SKU_SCOPE=$G6)))*(ACT_START<=4)*(ACT_END>=4)*IFERROR(ACT_UPLIFT-1,0)))*(1+SUMPRODUCT(SIGN(((ACT_DOOR_SCOPE="ALL")+(ACT_DOOR_SCOPE="TIER_"&$F6)+(ACT_DOOR_SCOPE=$B6)))*SIGN(((ACT_SKU_SCOPE="ALL")+(ACT_SKU_SCOPE=$G6)))*(4>ACT_END)*(ACT_END>0)*IFERROR(ACT_POSTLIFT,0))),0))) | N6: =IF(OR($H6<>"Y",5<$I6),0,IF(SUMPRODUCT(((BULK_ENABLED="Y")*((BULK_TIER="ALL")+(BULK_TIER=$F6))*((BULK_SKU="ALL")+(BULK_SKU=$G6))*(BULK_START<=5)*(BULK_END>=5)))>0,IFERROR(SUMPRODUCT(((BULK_ENABLED="Y")*((BULK_TIER="ALL")+(BULK_TIER=$F6))*((BULK_SKU="ALL")+(BULK_SKU=$G6))*(BULK_START<=5)*(BULK_END>=5))*IFERROR(BULK_VALUE,0))/MAX(1,SUMPRODUCT(((BULK_ENABLED="Y")*((BULK_TIER="ALL")+(BULK_TIER=$F6))*((BULK_SKU="ALL")+(BULK_SKU=$G6))*(BULK_START<=5)*(BULK_END>=5)))),0),ROUND((INDEX(VELOCITY_TABLE,MATCH($F6,TIER_LIST,0),2))*(IF((5-$I6+1)<=0,0,IF((5-$I6+1)=1,RAMP_W1,IF((5-$I6+1)=2,RAMP_W2,IF((5-$I6+1)=3,RAMP_W3,RAMP_W4PLUS)))))*(INDEX(ACTIVE_MULT_TABLE,2,1))*(1+SUMPRODUCT(SIGN(((ACT_DOOR_SCOPE="ALL")+(ACT_DOOR_SCOPE="TIER_"&$F6)+(ACT_DOOR_SCOPE=$B6)))*SIGN(((ACT_SKU_SCOPE="ALL")+(ACT_SKU_SCOPE=$G6)))*(ACT_START<=5)*(ACT_END>=5)*IFERROR(ACT_UPLIFT-1,0)))*(1+SUMPRODUCT(SIGN(((ACT_DOOR_SCOPE="ALL")+(ACT_DOOR_SCOPE="TIER_"&$F6)+(ACT_DOOR_SCOPE=$B6)))*SIGN(((ACT_SKU_SCOPE="ALL")+(ACT_SKU_SCOPE=$G6)))*(5>ACT_END)*(ACT_END>0)*IFERROR(ACT_POSTLIFT,0))),0))) | O6: =IF(OR($H6<>"Y",6<$I6),0,IF(SUMPRODUCT(((BULK_ENABLED="Y")*((BULK_TIER="ALL")+(BULK_TIER=$F6))*((BULK_SKU="ALL")+(BULK_SKU=$G6))*(BULK_START<=6)*(BULK_END>=6)))>0,IFERROR(SUMPRODUCT(((BULK_ENABLED="Y")*((BULK_TIER="ALL")+(BULK_TIER=$F6))*((BULK_SKU="ALL")+(BULK_SKU=$G6))*(BULK_START<=6)*(BULK_END>=6))*IFERROR(BULK_VALUE,0))/MAX(1,SUMPRODUCT(((BULK_ENABLED="Y")*((BULK_TIER="ALL")+(BULK_TIER=$F6))*((BULK_SKU="ALL")+(BULK_SKU=$G6))*(BULK_START<=6)*(BULK_END>=6)))),0),ROUND((INDEX(VELOCITY_TABLE,MATCH($F6,TIER_LIST,0),2))*(IF((6-$I6+1)<=0,0,IF((6-$I6+1)=1,RAMP_W1,IF((6-$I6+1)=2,RAMP_W2,IF((6-$I6+1)=3,RAMP_W3,RAMP_W4PLUS)))))*(INDEX(ACTIVE_MULT_TABLE,2,1))*(1+SUMPRODUCT(SIGN(((ACT_DOOR_SCOPE="ALL")+(ACT_DOOR_SCOPE="TIER_"&$F6)+(ACT_DOOR_SCOPE=$B6)))*SIGN(((ACT_SKU_SCOPE="ALL")+(ACT_SKU_SCOPE=$G6)))*(ACT_START<=6)*(ACT_END>=6)*IFERROR(ACT_UPLIFT-1,0)))*(1+SUMPRODUCT(SIGN(((ACT_DOOR_SCOPE="ALL")+(ACT_DOOR_SCOPE="TIER_"&$F6)+(ACT_DOOR_SCOPE=$B6)))*SIGN(((ACT_SKU_SCOPE="ALL")+(ACT_SKU_SCOPE=$G6)))*(6>ACT_END)*(ACT_END>0)*IFERROR(ACT_POSTLIFT,0))),0))) | P6: =IF(OR($H6<>"Y",7<$I6),0,IF(SUMPRODUCT(((BULK_ENABLED="Y")*((BULK_TIER="ALL")+(BULK_TIER=$F6))*((BULK_SKU="ALL")+(BULK_SKU=$G6))*(BULK_START<=7)*(BULK_END>=7)))>0,IFERROR(SUMPRODUCT(((BULK_ENABLED="Y")*((BULK_TIER="ALL")+(BULK_TIER=$F6))*((BULK_SKU="ALL")+(BULK_SKU=$G6))*(BULK_START<=7)*(BULK_END>=7))*IFERROR(BULK_VALUE,0))/MAX(1,SUMPRODUCT(((BULK_ENABLED="Y")*((BULK_TIER="ALL")+(BULK_TIER=$F6))*((BULK_SKU="ALL")+(BULK_SKU=$G6))*(BULK_START<=7)*(BULK_END>=7)))),0),ROUND((INDEX(VELOCITY_TABLE,MATCH($F6,TIER_LIST,0),2))*(IF((7-$I6+1)<=0,0,IF((7-$I6+1)=1,RAMP_W1,IF((7-$I6+1)=2,RAMP_W2,IF((7-$I6+1)=3,RAMP_W3,RAMP_W4PLUS)))))*(INDEX(ACTIVE_MULT_TABLE,2,1))*(1+SUMPRODUCT(SIGN(((ACT_DOOR_SCOPE="ALL")+(ACT_DOOR_SCOPE="TIER_"&$F6)+(ACT_DOOR_SCOPE=$B6)))*SIGN(((ACT_SKU_SCOPE="ALL")+(ACT_SKU_SCOPE=$G6)))*(ACT_START<=7)*(ACT_END>=7)*IFERROR(ACT_UPLIFT-1,0)))*(1+SUMPRODUCT(SIGN(((ACT_DOOR_SCOPE="ALL")+(ACT_DOOR_SCOPE="TIER_"&$F6)+(ACT_DOOR_SCOPE=$B6)))*SIGN(((ACT_SKU_SCOPE="ALL")+(ACT_SKU_SCOPE=$G6)))*(7>ACT_END)*(ACT_END>0)*IFERROR(ACT_POSTLIFT,0))),0))) | Q6: =IF(OR($H6<>"Y",8<$I6),0,IF(SUMPRODUCT(((BULK_ENABLED="Y")*((BULK_TIER="ALL")+(BULK_TIER=$F6))*((BULK_SKU="ALL")+(BULK_SKU=$G6))*(BULK_START<=8)*(BULK_END>=8)))>0,IFERROR(SUMPRODUCT(((BULK_ENABLED="Y")*((BULK_TIER="ALL")+(BULK_TIER=$F6))*((BULK_SKU="ALL")+(BULK_SKU=$G6))*(BULK_START<=8)*(BULK_END>=8))*IFERROR(BULK_VALUE,0))/MAX(1,SUMPRODUCT(((BULK_ENABLED="Y")*((BULK_TIER="ALL")+(BULK_TIER=$F6))*((BULK_SKU="ALL")+(BULK_SKU=$G6))*(BULK_START<=8)*(BULK_END>=8)))),0),ROUND((INDEX(VELOCITY_TABLE,MATCH($F6,TIER_LIST,0),2))*(IF((8-$I6+1)<=0,0,IF((8-$I6+1)=1,RAMP_W1,IF((8-$I6+1)=2,RAMP_W2,IF((8-$I6+1)=3,RAMP_W3,RAMP_W4PLUS)))))*(INDEX(ACTIVE_MULT_TABLE,2,1))*(1+SUMPRODUCT(SIGN(((ACT_DOOR_SCOPE="ALL")+(ACT_DOOR_SCOPE="TIER_"&$F6)+(ACT_DOOR_SCOPE=$B6)))*SIGN(((ACT_SKU_SCOPE="ALL")+(ACT_SKU_SCOPE=$G6)))*(ACT_START<=8)*(ACT_END>=8)*IFERROR(ACT_UPLIFT-1,0)))*(1+SUMPRODUCT(SIGN(((ACT_DOOR_SCOPE="ALL")+(ACT_DOOR_SCOPE="TIER_"&$F6)+(ACT_DOOR_SCOPE=$B6)))*SIGN(((ACT_SKU_SCOPE="ALL")+(ACT_SKU_SCOPE=$G6)))*(8>ACT_END)*(ACT_END>0)*IFERROR(ACT_POSTLIFT,0))),0))) | R6: =IF(OR($H6<>"Y",9<$I6),0,IF(SUMPRODUCT(((BULK_ENABLED="Y")*((BULK_TIER="ALL")+(BULK_TIER=$F6))*((BULK_SKU="ALL")+(BULK_SKU=$G6))*(BULK_START<=9)*(BULK_END>=9)))>0,IFERROR(SUMPRODUCT(((BULK_ENABLED="Y")*((BULK_TIER="ALL")+(BULK_TIER=$F6))*((BULK_SKU="ALL")+(BULK_SKU=$G6))*(BULK_START<=9)*(BULK_END>=9))*IFERROR(BULK_VALUE,0))/MAX(1,SUMPRODUCT(((BULK_ENABLED="Y")*((BULK_TIER="ALL")+(BULK_TIER=$F6))*((BULK_SKU="ALL")+(BULK_SKU=$G6))*(BULK_START<=9)*(BULK_END>=9)))),0),ROUND((INDEX(VELOCITY_TABLE,MATCH($F6,TIER_LIST,0),2))*(IF((9-$I6+1)<=0,0,IF((9-$I6+1)=1,RAMP_W1,IF((9-$I6+1)=2,RAMP_W2,IF((9-$I6+1)=3,RAMP_W3,RAMP_W4PLUS)))))*(INDEX(ACTIVE_MULT_TABLE,2,1))*(1+SUMPRODUCT(SIGN(((ACT_DOOR_SCOPE="ALL")+(ACT_DOOR_SCOPE="TIER_"&$F6)+(ACT_DOOR_SCOPE=$B6)))*SIGN(((ACT_SKU_SCOPE="ALL")+(ACT_SKU_SCOPE=$G6)))*(ACT_START<=9)*(ACT_END>=9)*IFERROR(ACT_UPLIFT-1,0)))*(1+SUMPRODUCT(SIGN(((ACT_DOOR_SCOPE="ALL")+(ACT_DOOR_SCOPE="TIER_"&$F6)+(ACT_DOOR_SCOPE=$B6)))*SIGN(((ACT_SKU_SCOPE="ALL")+(ACT_SKU_SCOPE=$G6)))*(9>ACT_END)*(ACT_END>0)*IFERROR(ACT_POSTLIFT,0))),0))) | S6: =IF(OR($H6<>"Y",10<$I6),0,IF(SUMPRODUCT(((BULK_ENABLED="Y")*((BULK_TIER="ALL")+(BULK_TIER=$F6))*((BULK_SKU="ALL")+(BULK_SKU=$G6))*(BULK_START<=10)*(BULK_END>=10)))>0,IFERROR(SUMPRODUCT(((BULK_ENABLED="Y")*((BULK_TIER="ALL")+(BULK_TIER=$F6))*((BULK_SKU="ALL")+(BULK_SKU=$G6))*(BULK_START<=10)*(BULK_END>=10))*IFERROR(BULK_VALUE,0))/MAX(1,SUMPRODUCT(((BULK_ENABLED="Y")*((BULK_TIER="ALL")+(BULK_TIER=$F6))*((BULK_SKU="ALL")+(BULK_SKU=$G6))*(BULK_START<=10)*(BULK_END>=10)))),0),ROUND((INDEX(VELOCITY_TABLE,MATCH($F6,TIER_LIST,0),2))*(IF((10-$I6+1)<=0,0,IF((10-$I6+1)=1,RAMP_W1,IF((10-$I6+1)=2,RAMP_W2,IF((10-$I6+1)=3,RAMP_W3,RAMP_W4PLUS)))))*(INDEX(ACTIVE_MULT_TABLE,2,1))*(1+SUMPRODUCT(SIGN(((ACT_DOOR_SCOPE="ALL")+(ACT_DOOR_SCOPE="TIER_"&$F6)+(ACT_DOOR_SCOPE=$B6)))*SIGN(((ACT_SKU_SCOPE="ALL")+(ACT_SKU_SCOPE=$G6)))*(ACT_START<=10)*(ACT_END>=10)*IFERROR(ACT_UPLIFT-1,0)))*(1+SUMPRODUCT(SIGN(((ACT_DOOR_SCOPE="ALL")+(ACT_DOOR_SCOPE="TIER_"&$F6)+(ACT_DOOR_SCOPE=$B6)))*SIGN(((ACT_SKU_SCOPE="ALL")+(ACT_SKU_SCOPE=$G6)))*(10>ACT_END)*(ACT_END>0)*IFERROR(ACT_POSTLIFT,0))),0))) | T6: =IF(OR($H6<>"Y",11<$I6),0,IF(SUMPRODUCT(((BULK_ENABLED="Y")*((BULK_TIER="ALL")+(BULK_TIER=$F6))*((BULK_SKU="ALL")+(BULK_SKU=$G6))*(BULK_START<=11)*(BULK_END>=11)))>0,IFERROR(SUMPRODUCT(((BULK_ENABLED="Y")*((BULK_TIER="ALL")+(BULK_TIER=$F6))*((BULK_SKU="ALL")+(BULK_SKU=$G6))*(BULK_START<=11)*(BULK_END>=11))*IFERROR(BULK_VALUE,0))/MAX(1,SUMPRODUCT(((BULK_ENABLED="Y")*((BULK_TIER="ALL")+(BULK_TIER=$F6))*((BULK_SKU="ALL")+(BULK_SKU=$G6))*(BULK_START<=11)*(BULK_END>=11)))),0),ROUND((INDEX(VELOCITY_TABLE,MATCH($F6,TIER_LIST,0),2))*(IF((11-$I6+1)<=0,0,IF((11-$I6+1)=1,RAMP_W1,IF((11-$I6+1)=2,RAMP_W2,IF((11-$I6+1)=3,RAMP_W3,RAMP_W4PLUS)))))*(INDEX(ACTIVE_MULT_TABLE,2,1))*(1+SUMPRODUCT(SIGN(((ACT_DOOR_SCOPE="ALL")+(ACT_DOOR_SCOPE="TIER_"&$F6)+(ACT_DOOR_SCOPE=$B6)))*SIGN(((ACT_SKU_SCOPE="ALL")+(ACT_SKU_SCOPE=$G6)))*(ACT_START<=11)*(ACT_END>=11)*IFERROR(ACT_UPLIFT-1,0)))*(1+SUMPRODUCT(SIGN(((ACT_DOOR_SCOPE="ALL")+(ACT_DOOR_SCOPE="TIER_"&$F6)+(ACT_DOOR_SCOPE=$B6)))*SIGN(((ACT_SKU_SCOPE="ALL")+(ACT_SKU_SCOPE=$G6)))*(11>ACT_END)*(ACT_END>0)*IFERROR(ACT_POSTLIFT,0))),0))) | U6: =IF(OR($H6<>"Y",12<$I6),0,IF(SUMPRODUCT(((BULK_ENABLED="Y")*((BULK_TIER="ALL")+(BULK_TIER=$F6))*((BULK_SKU="ALL")+(BULK_SKU=$G6))*(BULK_START<=12)*(BULK_END>=12)))>0,IFERROR(SUMPRODUCT(((BULK_ENABLED="Y")*((BULK_TIER="ALL")+(BULK_TIER=$F6))*((BULK_SKU="ALL")+(BULK_SKU=$G6))*(BULK_START<=12)*(BULK_END>=12))*IFERROR(BULK_VALUE,0))/MAX(1,SUMPRODUCT(((BULK_ENABLED="Y")*((BULK_TIER="ALL")+(BULK_TIER=$F6))*((BULK_SKU="ALL")+(BULK_SKU=$G6))*(BULK_START<=12)*(BULK_END>=12)))),0),ROUND((INDEX(VELOCITY_TABLE,MATCH($F6,TIER_LIST,0),2))*(IF((12-$I6+1)<=0,0,IF((12-$I6+1)=1,RAMP_W1,IF((12-$I6+1)=2,RAMP_W2,IF((12-$I6+1)=3,RAMP_W3,RAMP_W4PLUS)))))*(INDEX(ACTIVE_MULT_TABLE,2,1))*(1+SUMPRODUCT(SIGN(((ACT_DOOR_SCOPE="ALL")+(ACT_DOOR_SCOPE="TIER_"&$F6)+(ACT_DOOR_SCOPE=$B6)))*SIGN(((ACT_SKU_SCOPE="ALL")+(ACT_SKU_SCOPE=$G6)))*(ACT_START<=12)*(ACT_END>=12)*IFERROR(ACT_UPLIFT-1,0)))*(1+SUMPRODUCT(SIGN(((ACT_DOOR_SCOPE="ALL")+(ACT_DOOR_SCOPE="TIER_"&$F6)+(ACT_DOOR_SCOPE=$B6)))*SIGN(((ACT_SKU_SCOPE="ALL")+(ACT_SKU_SCOPE=$G6)))*(12>ACT_END)*(ACT_END>0)*IFERROR(ACT_POSTLIFT,0))),0))) | V6: =IF(OR($H6<>"Y",13<$I6),0,IF(SUMPRODUCT(((BULK_ENABLED="Y")*((BULK_TIER="ALL")+(BULK_TIER=$F6))*((BULK_SKU="ALL")+(BULK_SKU=$G6))*(BULK_START<=13)*(BULK_END>=13)))>0,IFERROR(SUMPRODUCT(((BULK_ENABLED="Y")*((BULK_TIER="ALL")+(BULK_TIER=$F6))*((BULK_SKU="ALL")+(BULK_SKU=$G6))*(BULK_START<=13)*(BULK_END>=13))*IFERROR(BULK_VALUE,0))/MAX(1,SUMPRODUCT(((BULK_ENABLED="Y")*((BULK_TIER="ALL")+(BULK_TIER=$F6))*((BULK_SKU="ALL")+(BULK_SKU=$G6))*(BULK_START<=13)*(BULK_END>=13)))),0),ROUND((INDEX(VELOCITY_TABLE,MATCH($F6,TIER_LIST,0),2))*(IF((13-$I6+1)<=0,0,IF((13-$I6+1)=1,RAMP_W1,IF((13-$I6+1)=2,RAMP_W2,IF((13-$I6+1)=3,RAMP_W3,RAMP_W4PLUS)))))*(INDEX(ACTIVE_MULT_TABLE,2,1))*(1+SUMPRODUCT(SIGN(((ACT_DOOR_SCOPE="ALL")+(ACT_DOOR_SCOPE="TIER_"&$F6)+(ACT_DOOR_SCOPE=$B6)))*SIGN(((ACT_SKU_SCOPE="ALL")+(ACT_SKU_SCOPE=$G6)))*(ACT_START<=13)*(ACT_END>=13)*IFERROR(ACT_UPLIFT-1,0)))*(1+SUMPRODUCT(SIGN(((ACT_DOOR_SCOPE="ALL")+(ACT_DOOR_SCOPE="TIER_"&$F6)+(ACT_DOOR_SCOPE=$B6)))*SIGN(((ACT_SKU_SCOPE="ALL")+(ACT_SKU_SCOPE=$G6)))*(13>ACT_END)*(ACT_END>0)*IFERROR(ACT_POSTLIFT,0))),0)))
A7: R0003 | B7: =Doors!$A$5 | C7: =Doors!$C$5 | D7: =Doors!$B$5 | E7: =Doors!$E$5 | F7: =Doors!$F$5 | G7: Raspberry | H7: =Doors!$I$5 | I7: =Doors!$J$5 | J7: =IF(OR($H7<>"Y",1<$I7),0,IF(SUMPRODUCT(((BULK_ENABLED="Y")*((BULK_TIER="ALL")+(BULK_TIER=$F7))*((BULK_SKU="ALL")+(BULK_SKU=$G7))*(BULK_START<=1)*(BULK_END>=1)))>0,IFERROR(SUMPRODUCT(((BULK_ENABLED="Y")*((BULK_TIER="ALL")+(BULK_TIER=$F7))*((BULK_SKU="ALL")+(BULK_SKU=$G7))*(BULK_START<=1)*(BULK_END>=1))*IFERROR(BULK_VALUE,0))/MAX(1,SUMPRODUCT(((BULK_ENABLED="Y")*((BULK_TIER="ALL")+(BULK_TIER=$F7))*((BULK_SKU="ALL")+(BULK_SKU=$G7))*(BULK_START<=1)*(BULK_END>=1)))),0),ROUND((INDEX(VELOCITY_TABLE,MATCH($F7,TIER_LIST,0),3))*(IF((1-$I7+1)<=0,0,IF((1-$I7+1)=1,RAMP_W1,IF((1-$I7+1)=2,RAMP_W2,IF((1-$I7+1)=3,RAMP_W3,RAMP_W4PLUS)))))*(INDEX(ACTIVE_MULT_TABLE,3,1))*(1+SUMPRODUCT(SIGN(((ACT_DOOR_SCOPE="ALL")+(ACT_DOOR_SCOPE="TIER_"&$F7)+(ACT_DOOR_SCOPE=$B7)))*SIGN(((ACT_SKU_SCOPE="ALL")+(ACT_SKU_SCOPE=$G7)))*(ACT_START<=1)*(ACT_END>=1)*IFERROR(ACT_UPLIFT-1,0)))*(1+SUMPRODUCT(SIGN(((ACT_DOOR_SCOPE="ALL")+(ACT_DOOR_SCOPE="TIER_"&$F7)+(ACT_DOOR_SCOPE=$B7)))*SIGN(((ACT_SKU_SCOPE="ALL")+(ACT_SKU_SCOPE=$G7)))*(1>ACT_END)*(ACT_END>0)*IFERROR(ACT_POSTLIFT,0))),0))) | K7: =IF(OR($H7<>"Y",2<$I7),0,IF(SUMPRODUCT(((BULK_ENABLED="Y")*((BULK_TIER="ALL")+(BULK_TIER=$F7))*((BULK_SKU="ALL")+(BULK_SKU=$G7))*(BULK_START<=2)*(BULK_END>=2)))>0,IFERROR(SUMPRODUCT(((BULK_ENABLED="Y")*((BULK_TIER="ALL")+(BULK_TIER=$F7))*((BULK_SKU="ALL")+(BULK_SKU=$G7))*(BULK_START<=2)*(BULK_END>=2))*IFERROR(BULK_VALUE,0))/MAX(1,SUMPRODUCT(((BULK_ENABLED="Y")*((BULK_TIER="ALL")+(BULK_TIER=$F7))*((BULK_SKU="ALL")+(BULK_SKU=$G7))*(BULK_START<=2)*(BULK_END>=2)))),0),ROUND((INDEX(VELOCITY_TABLE,MATCH($F7,TIER_LIST,0),3))*(IF((2-$I7+1)<=0,0,IF((2-$I7+1)=1,RAMP_W1,IF((2-$I7+1)=2,RAMP_W2,IF((2-$I7+1)=3,RAMP_W3,RAMP_W4PLUS)))))*(INDEX(ACTIVE_MULT_TABLE,3,1))*(1+SUMPRODUCT(SIGN(((ACT_DOOR_SCOPE="ALL")+(ACT_DOOR_SCOPE="TIER_"&$F7)+(ACT_DOOR_SCOPE=$B7)))*SIGN(((ACT_SKU_SCOPE="ALL")+(ACT_SKU_SCOPE=$G7)))*(ACT_START<=2)*(ACT_END>=2)*IFERROR(ACT_UPLIFT-1,0)))*(1+SUMPRODUCT(SIGN(((ACT_DOOR_SCOPE="ALL")+(ACT_DOOR_SCOPE="TIER_"&$F7)+(ACT_DOOR_SCOPE=$B7)))*SIGN(((ACT_SKU_SCOPE="ALL")+(ACT_SKU_SCOPE=$G7)))*(2>ACT_END)*(ACT_END>0)*IFERROR(ACT_POSTLIFT,0))),0))) | L7: =IF(OR($H7<>"Y",3<$I7),0,IF(SUMPRODUCT(((BULK_ENABLED="Y")*((BULK_TIER="ALL")+(BULK_TIER=$F7))*((BULK_SKU="ALL")+(BULK_SKU=$G7))*(BULK_START<=3)*(BULK_END>=3)))>0,IFERROR(SUMPRODUCT(((BULK_ENABLED="Y")*((BULK_TIER="ALL")+(BULK_TIER=$F7))*((BULK_SKU="ALL")+(BULK_SKU=$G7))*(BULK_START<=3)*(BULK_END>=3))*IFERROR(BULK_VALUE,0))/MAX(1,SUMPRODUCT(((BULK_ENABLED="Y")*((BULK_TIER="ALL")+(BULK_TIER=$F7))*((BULK_SKU="ALL")+(BULK_SKU=$G7))*(BULK_START<=3)*(BULK_END>=3)))),0),ROUND((INDEX(VELOCITY_TABLE,MATCH($F7,TIER_LIST,0),3))*(IF((3-$I7+1)<=0,0,IF((3-$I7+1)=1,RAMP_W1,IF((3-$I7+1)=2,RAMP_W2,IF((3-$I7+1)=3,RAMP_W3,RAMP_W4PLUS)))))*(INDEX(ACTIVE_MULT_TABLE,3,1))*(1+SUMPRODUCT(SIGN(((ACT_DOOR_SCOPE="ALL")+(ACT_DOOR_SCOPE="TIER_"&$F7)+(ACT_DOOR_SCOPE=$B7)))*SIGN(((ACT_SKU_SCOPE="ALL")+(ACT_SKU_SCOPE=$G7)))*(ACT_START<=3)*(ACT_END>=3)*IFERROR(ACT_UPLIFT-1,0)))*(1+SUMPRODUCT(SIGN(((ACT_DOOR_SCOPE="ALL")+(ACT_DOOR_SCOPE="TIER_"&$F7)+(ACT_DOOR_SCOPE=$B7)))*SIGN(((ACT_SKU_SCOPE="ALL")+(ACT_SKU_SCOPE=$G7)))*(3>ACT_END)*(ACT_END>0)*IFERROR(ACT_POSTLIFT,0))),0))) | M7: =IF(OR($H7<>"Y",4<$I7),0,IF(SUMPRODUCT(((BULK_ENABLED="Y")*((BULK_TIER="ALL")+(BULK_TIER=$F7))*((BULK_SKU="ALL")+(BULK_SKU=$G7))*(BULK_START<=4)*(BULK_END>=4)))>0,IFERROR(SUMPRODUCT(((BULK_ENABLED="Y")*((BULK_TIER="ALL")+(BULK_TIER=$F7))*((BULK_SKU="ALL")+(BULK_SKU=$G7))*(BULK_START<=4)*(BULK_END>=4))*IFERROR(BULK_VALUE,0))/MAX(1,SUMPRODUCT(((BULK_ENABLED="Y")*((BULK_TIER="ALL")+(BULK_TIER=$F7))*((BULK_SKU="ALL")+(BULK_SKU=$G7))*(BULK_START<=4)*(BULK_END>=4)))),0),ROUND((INDEX(VELOCITY_TABLE,MATCH($F7,TIER_LIST,0),3))*(IF((4-$I7+1)<=0,0,IF((4-$I7+1)=1,RAMP_W1,IF((4-$I7+1)=2,RAMP_W2,IF((4-$I7+1)=3,RAMP_W3,RAMP_W4PLUS)))))*(INDEX(ACTIVE_MULT_TABLE,3,1))*(1+SUMPRODUCT(SIGN(((ACT_DOOR_SCOPE="ALL")+(ACT_DOOR_SCOPE="TIER_"&$F7)+(ACT_DOOR_SCOPE=$B7)))*SIGN(((ACT_SKU_SCOPE="ALL")+(ACT_SKU_SCOPE=$G7)))*(ACT_START<=4)*(ACT_END>=4)*IFERROR(ACT_UPLIFT-1,0)))*(1+SUMPRODUCT(SIGN(((ACT_DOOR_SCOPE="ALL")+(ACT_DOOR_SCOPE="TIER_"&$F7)+(ACT_DOOR_SCOPE=$B7)))*SIGN(((ACT_SKU_SCOPE="ALL")+(ACT_SKU_SCOPE=$G7)))*(4>ACT_END)*(ACT_END>0)*IFERROR(ACT_POSTLIFT,0))),0))) | N7: =IF(OR($H7<>"Y",5<$I7),0,IF(SUMPRODUCT(((BULK_ENABLED="Y")*((BULK_TIER="ALL")+(BULK_TIER=$F7))*((BULK_SKU="ALL")+(BULK_SKU=$G7))*(BULK_START<=5)*(BULK_END>=5)))>0,IFERROR(SUMPRODUCT(((BULK_ENABLED="Y")*((BULK_TIER="ALL")+(BULK_TIER=$F7))*((BULK_SKU="ALL")+(BULK_SKU=$G7))*(BULK_START<=5)*(BULK_END>=5))*IFERROR(BULK_VALUE,0))/MAX(1,SUMPRODUCT(((BULK_ENABLED="Y")*((BULK_TIER="ALL")+(BULK_TIER=$F7))*((BULK_SKU="ALL")+(BULK_SKU=$G7))*(BULK_START<=5)*(BULK_END>=5)))),0),ROUND((INDEX(VELOCITY_TABLE,MATCH($F7,TIER_LIST,0),3))*(IF((5-$I7+1)<=0,0,IF((5-$I7+1)=1,RAMP_W1,IF((5-$I7+1)=2,RAMP_W2,IF((5-$I7+1)=3,RAMP_W3,RAMP_W4PLUS)))))*(INDEX(ACTIVE_MULT_TABLE,3,1))*(1+SUMPRODUCT(SIGN(((ACT_DOOR_SCOPE="ALL")+(ACT_DOOR_SCOPE="TIER_"&$F7)+(ACT_DOOR_SCOPE=$B7)))*SIGN(((ACT_SKU_SCOPE="ALL")+(ACT_SKU_SCOPE=$G7)))*(ACT_START<=5)*(ACT_END>=5)*IFERROR(ACT_UPLIFT-1,0)))*(1+SUMPRODUCT(SIGN(((ACT_DOOR_SCOPE="ALL")+(ACT_DOOR_SCOPE="TIER_"&$F7)+(ACT_DOOR_SCOPE=$B7)))*SIGN(((ACT_SKU_SCOPE="ALL")+(ACT_SKU_SCOPE=$G7)))*(5>ACT_END)*(ACT_END>0)*IFERROR(ACT_POSTLIFT,0))),0))) | O7: =IF(OR($H7<>"Y",6<$I7),0,IF(SUMPRODUCT(((BULK_ENABLED="Y")*((BULK_TIER="ALL")+(BULK_TIER=$F7))*((BULK_SKU="ALL")+(BULK_SKU=$G7))*(BULK_START<=6)*(BULK_END>=6)))>0,IFERROR(SUMPRODUCT(((BULK_ENABLED="Y")*((BULK_TIER="ALL")+(BULK_TIER=$F7))*((BULK_SKU="ALL")+(BULK_SKU=$G7))*(BULK_START<=6)*(BULK_END>=6))*IFERROR(BULK_VALUE,0))/MAX(1,SUMPRODUCT(((BULK_ENABLED="Y")*((BULK_TIER="ALL")+(BULK_TIER=$F7))*((BULK_SKU="ALL")+(BULK_SKU=$G7))*(BULK_START<=6)*(BULK_END>=6)))),0),ROUND((INDEX(VELOCITY_TABLE,MATCH($F7,TIER_LIST,0),3))*(IF((6-$I7+1)<=0,0,IF((6-$I7+1)=1,RAMP_W1,IF((6-$I7+1)=2,RAMP_W2,IF((6-$I7+1)=3,RAMP_W3,RAMP_W4PLUS)))))*(INDEX(ACTIVE_MULT_TABLE,3,1))*(1+SUMPRODUCT(SIGN(((ACT_DOOR_SCOPE="ALL")+(ACT_DOOR_SCOPE="TIER_"&$F7)+(ACT_DOOR_SCOPE=$B7)))*SIGN(((ACT_SKU_SCOPE="ALL")+(ACT_SKU_SCOPE=$G7)))*(ACT_START<=6)*(ACT_END>=6)*IFERROR(ACT_UPLIFT-1,0)))*(1+SUMPRODUCT(SIGN(((ACT_DOOR_SCOPE="ALL")+(ACT_DOOR_SCOPE="TIER_"&$F7)+(ACT_DOOR_SCOPE=$B7)))*SIGN(((ACT_SKU_SCOPE="ALL")+(ACT_SKU_SCOPE=$G7)))*(6>ACT_END)*(ACT_END>0)*IFERROR(ACT_POSTLIFT,0))),0))) | P7: =IF(OR($H7<>"Y",7<$I7),0,IF(SUMPRODUCT(((BULK_ENABLED="Y")*((BULK_TIER="ALL")+(BULK_TIER=$F7))*((BULK_SKU="ALL")+(BULK_SKU=$G7))*(BULK_START<=7)*(BULK_END>=7)))>0,IFERROR(SUMPRODUCT(((BULK_ENABLED="Y")*((BULK_TIER="ALL")+(BULK_TIER=$F7))*((BULK_SKU="ALL")+(BULK_SKU=$G7))*(BULK_START<=7)*(BULK_END>=7))*IFERROR(BULK_VALUE,0))/MAX(1,SUMPRODUCT(((BULK_ENABLED="Y")*((BULK_TIER="ALL")+(BULK_TIER=$F7))*((BULK_SKU="ALL")+(BULK_SKU=$G7))*(BULK_START<=7)*(BULK_END>=7)))),0),ROUND((INDEX(VELOCITY_TABLE,MATCH($F7,TIER_LIST,0),3))*(IF((7-$I7+1)<=0,0,IF((7-$I7+1)=1,RAMP_W1,IF((7-$I7+1)=2,RAMP_W2,IF((7-$I7+1)=3,RAMP_W3,RAMP_W4PLUS)))))*(INDEX(ACTIVE_MULT_TABLE,3,1))*(1+SUMPRODUCT(SIGN(((ACT_DOOR_SCOPE="ALL")+(ACT_DOOR_SCOPE="TIER_"&$F7)+(ACT_DOOR_SCOPE=$B7)))*SIGN(((ACT_SKU_SCOPE="ALL")+(ACT_SKU_SCOPE=$G7)))*(ACT_START<=7)*(ACT_END>=7)*IFERROR(ACT_UPLIFT-1,0)))*(1+SUMPRODUCT(SIGN(((ACT_DOOR_SCOPE="ALL")+(ACT_DOOR_SCOPE="TIER_"&$F7)+(ACT_DOOR_SCOPE=$B7)))*SIGN(((ACT_SKU_SCOPE="ALL")+(ACT_SKU_SCOPE=$G7)))*(7>ACT_END)*(ACT_END>0)*IFERROR(ACT_POSTLIFT,0))),0))) | Q7: =IF(OR($H7<>"Y",8<$I7),0,IF(SUMPRODUCT(((BULK_ENABLED="Y")*((BULK_TIER="ALL")+(BULK_TIER=$F7))*((BULK_SKU="ALL")+(BULK_SKU=$G7))*(BULK_START<=8)*(BULK_END>=8)))>0,IFERROR(SUMPRODUCT(((BULK_ENABLED="Y")*((BULK_TIER="ALL")+(BULK_TIER=$F7))*((BULK_SKU="ALL")+(BULK_SKU=$G7))*(BULK_START<=8)*(BULK_END>=8))*IFERROR(BULK_VALUE,0))/MAX(1,SUMPRODUCT(((BULK_ENABLED="Y")*((BULK_TIER="ALL")+(BULK_TIER=$F7))*((BULK_SKU="ALL")+(BULK_SKU=$G7))*(BULK_START<=8)*(BULK_END>=8)))),0),ROUND((INDEX(VELOCITY_TABLE,MATCH($F7,TIER_LIST,0),3))*(IF((8-$I7+1)<=0,0,IF((8-$I7+1)=1,RAMP_W1,IF((8-$I7+1)=2,RAMP_W2,IF((8-$I7+1)=3,RAMP_W3,RAMP_W4PLUS)))))*(INDEX(ACTIVE_MULT_TABLE,3,1))*(1+SUMPRODUCT(SIGN(((ACT_DOOR_SCOPE="ALL")+(ACT_DOOR_SCOPE="TIER_"&$F7)+(ACT_DOOR_SCOPE=$B7)))*SIGN(((ACT_SKU_SCOPE="ALL")+(ACT_SKU_SCOPE=$G7)))*(ACT_START<=8)*(ACT_END>=8)*IFERROR(ACT_UPLIFT-1,0)))*(1+SUMPRODUCT(SIGN(((ACT_DOOR_SCOPE="ALL")+(ACT_DOOR_SCOPE="TIER_"&$F7)+(ACT_DOOR_SCOPE=$B7)))*SIGN(((ACT_SKU_SCOPE="ALL")+(ACT_SKU_SCOPE=$G7)))*(8>ACT_END)*(ACT_END>0)*IFERROR(ACT_POSTLIFT,0))),0))) | R7: =IF(OR($H7<>"Y",9<$I7),0,IF(SUMPRODUCT(((BULK_ENABLED="Y")*((BULK_TIER="ALL")+(BULK_TIER=$F7))*((BULK_SKU="ALL")+(BULK_SKU=$G7))*(BULK_START<=9)*(BULK_END>=9)))>0,IFERROR(SUMPRODUCT(((BULK_ENABLED="Y")*((BULK_TIER="ALL")+(BULK_TIER=$F7))*((BULK_SKU="ALL")+(BULK_SKU=$G7))*(BULK_START<=9)*(BULK_END>=9))*IFERROR(BULK_VALUE,0))/MAX(1,SUMPRODUCT(((BULK_ENABLED="Y")*((BULK_TIER="ALL")+(BULK_TIER=$F7))*((BULK_SKU="ALL")+(BULK_SKU=$G7))*(BULK_START<=9)*(BULK_END>=9)))),0),ROUND((INDEX(VELOCITY_TABLE,MATCH($F7,TIER_LIST,0),3))*(IF((9-$I7+1)<=0,0,IF((9-$I7+1)=1,RAMP_W1,IF((9-$I7+1)=2,RAMP_W2,IF((9-$I7+1)=3,RAMP_W3,RAMP_W4PLUS)))))*(INDEX(ACTIVE_MULT_TABLE,3,1))*(1+SUMPRODUCT(SIGN(((ACT_DOOR_SCOPE="ALL")+(ACT_DOOR_SCOPE="TIER_"&$F7)+(ACT_DOOR_SCOPE=$B7)))*SIGN(((ACT_SKU_SCOPE="ALL")+(ACT_SKU_SCOPE=$G7)))*(ACT_START<=9)*(ACT_END>=9)*IFERROR(ACT_UPLIFT-1,0)))*(1+SUMPRODUCT(SIGN(((ACT_DOOR_SCOPE="ALL")+(ACT_DOOR_SCOPE="TIER_"&$F7)+(ACT_DOOR_SCOPE=$B7)))*SIGN(((ACT_SKU_SCOPE="ALL")+(ACT_SKU_SCOPE=$G7)))*(9>ACT_END)*(ACT_END>0)*IFERROR(ACT_POSTLIFT,0))),0))) | S7: =IF(OR($H7<>"Y",10<$I7),0,IF(SUMPRODUCT(((BULK_ENABLED="Y")*((BULK_TIER="ALL")+(BULK_TIER=$F7))*((BULK_SKU="ALL")+(BULK_SKU=$G7))*(BULK_START<=10)*(BULK_END>=10)))>0,IFERROR(SUMPRODUCT(((BULK_ENABLED="Y")*((BULK_TIER="ALL")+(BULK_TIER=$F7))*((BULK_SKU="ALL")+(BULK_SKU=$G7))*(BULK_START<=10)*(BULK_END>=10))*IFERROR(BULK_VALUE,0))/MAX(1,SUMPRODUCT(((BULK_ENABLED="Y")*((BULK_TIER="ALL")+(BULK_TIER=$F7))*((BULK_SKU="ALL")+(BULK_SKU=$G7))*(BULK_START<=10)*(BULK_END>=10)))),0),ROUND((INDEX(VELOCITY_TABLE,MATCH($F7,TIER_LIST,0),3))*(IF((10-$I7+1)<=0,0,IF((10-$I7+1)=1,RAMP_W1,IF((10-$I7+1)=2,RAMP_W2,IF((10-$I7+1)=3,RAMP_W3,RAMP_W4PLUS)))))*(INDEX(ACTIVE_MULT_TABLE,3,1))*(1+SUMPRODUCT(SIGN(((ACT_DOOR_SCOPE="ALL")+(ACT_DOOR_SCOPE="TIER_"&$F7)+(ACT_DOOR_SCOPE=$B7)))*SIGN(((ACT_SKU_SCOPE="ALL")+(ACT_SKU_SCOPE=$G7)))*(ACT_START<=10)*(ACT_END>=10)*IFERROR(ACT_UPLIFT-1,0)))*(1+SUMPRODUCT(SIGN(((ACT_DOOR_SCOPE="ALL")+(ACT_DOOR_SCOPE="TIER_"&$F7)+(ACT_DOOR_SCOPE=$B7)))*SIGN(((ACT_SKU_SCOPE="ALL")+(ACT_SKU_SCOPE=$G7)))*(10>ACT_END)*(ACT_END>0)*IFERROR(ACT_POSTLIFT,0))),0))) | T7: =IF(OR($H7<>"Y",11<$I7),0,IF(SUMPRODUCT(((BULK_ENABLED="Y")*((BULK_TIER="ALL")+(BULK_TIER=$F7))*((BULK_SKU="ALL")+(BULK_SKU=$G7))*(BULK_START<=11)*(BULK_END>=11)))>0,IFERROR(SUMPRODUCT(((BULK_ENABLED="Y")*((BULK_TIER="ALL")+(BULK_TIER=$F7))*((BULK_SKU="ALL")+(BULK_SKU=$G7))*(BULK_START<=11)*(BULK_END>=11))*IFERROR(BULK_VALUE,0))/MAX(1,SUMPRODUCT(((BULK_ENABLED="Y")*((BULK_TIER="ALL")+(BULK_TIER=$F7))*((BULK_SKU="ALL")+(BULK_SKU=$G7))*(BULK_START<=11)*(BULK_END>=11)))),0),ROUND((INDEX(VELOCITY_TABLE,MATCH($F7,TIER_LIST,0),3))*(IF((11-$I7+1)<=0,0,IF((11-$I7+1)=1,RAMP_W1,IF((11-$I7+1)=2,RAMP_W2,IF((11-$I7+1)=3,RAMP_W3,RAMP_W4PLUS)))))*(INDEX(ACTIVE_MULT_TABLE,3,1))*(1+SUMPRODUCT(SIGN(((ACT_DOOR_SCOPE="ALL")+(ACT_DOOR_SCOPE="TIER_"&$F7)+(ACT_DOOR_SCOPE=$B7)))*SIGN(((ACT_SKU_SCOPE="ALL")+(ACT_SKU_SCOPE=$G7)))*(ACT_START<=11)*(ACT_END>=11)*IFERROR(ACT_UPLIFT-1,0)))*(1+SUMPRODUCT(SIGN(((ACT_DOOR_SCOPE="ALL")+(ACT_DOOR_SCOPE="TIER_"&$F7)+(ACT_DOOR_SCOPE=$B7)))*SIGN(((ACT_SKU_SCOPE="ALL")+(ACT_SKU_SCOPE=$G7)))*(11>ACT_END)*(ACT_END>0)*IFERROR(ACT_POSTLIFT,0))),0))) | U7: =IF(OR($H7<>"Y",12<$I7),0,IF(SUMPRODUCT(((BULK_ENABLED="Y")*((BULK_TIER="ALL")+(BULK_TIER=$F7))*((BULK_SKU="ALL")+(BULK_SKU=$G7))*(BULK_START<=12)*(BULK_END>=12)))>0,IFERROR(SUMPRODUCT(((BULK_ENABLED="Y")*((BULK_TIER="ALL")+(BULK_TIER=$F7))*((BULK_SKU="ALL")+(BULK_SKU=$G7))*(BULK_START<=12)*(BULK_END>=12))*IFERROR(BULK_VALUE,0))/MAX(1,SUMPRODUCT(((BULK_ENABLED="Y")*((BULK_TIER="ALL")+(BULK_TIER=$F7))*((BULK_SKU="ALL")+(BULK_SKU=$G7))*(BULK_START<=12)*(BULK_END>=12)))),0),ROUND((INDEX(VELOCITY_TABLE,MATCH($F7,TIER_LIST,0),3))*(IF((12-$I7+1)<=0,0,IF((12-$I7+1)=1,RAMP_W1,IF((12-$I7+1)=2,RAMP_W2,IF((12-$I7+1)=3,RAMP_W3,RAMP_W4PLUS)))))*(INDEX(ACTIVE_MULT_TABLE,3,1))*(1+SUMPRODUCT(SIGN(((ACT_DOOR_SCOPE="ALL")+(ACT_DOOR_SCOPE="TIER_"&$F7)+(ACT_DOOR_SCOPE=$B7)))*SIGN(((ACT_SKU_SCOPE="ALL")+(ACT_SKU_SCOPE=$G7)))*(ACT_START<=12)*(ACT_END>=12)*IFERROR(ACT_UPLIFT-1,0)))*(1+SUMPRODUCT(SIGN(((ACT_DOOR_SCOPE="ALL")+(ACT_DOOR_SCOPE="TIER_"&$F7)+(ACT_DOOR_SCOPE=$B7)))*SIGN(((ACT_SKU_SCOPE="ALL")+(ACT_SKU_SCOPE=$G7)))*(12>ACT_END)*(ACT_END>0)*IFERROR(ACT_POSTLIFT,0))),0))) | V7: =IF(OR($H7<>"Y",13<$I7),0,IF(SUMPRODUCT(((BULK_ENABLED="Y")*((BULK_TIER="ALL")+(BULK_TIER=$F7))*((BULK_SKU="ALL")+(BULK_SKU=$G7))*(BULK_START<=13)*(BULK_END>=13)))>0,IFERROR(SUMPRODUCT(((BULK_ENABLED="Y")*((BULK_TIER="ALL")+(BULK_TIER=$F7))*((BULK_SKU="ALL")+(BULK_SKU=$G7))*(BULK_START<=13)*(BULK_END>=13))*IFERROR(BULK_VALUE,0))/MAX(1,SUMPRODUCT(((BULK_ENABLED="Y")*((BULK_TIER="ALL")+(BULK_TIER=$F7))*((BULK_SKU="ALL")+(BULK_SKU=$G7))*(BULK_START<=13)*(BULK_END>=13)))),0),ROUND((INDEX(VELOCITY_TABLE,MATCH($F7,TIER_LIST,0),3))*(IF((13-$I7+1)<=0,0,IF((13-$I7+1)=1,RAMP_W1,IF((13-$I7+1)=2,RAMP_W2,IF((13-$I7+1)=3,RAMP_W3,RAMP_W4PLUS)))))*(INDEX(ACTIVE_MULT_TABLE,3,1))*(1+SUMPRODUCT(SIGN(((ACT_DOOR_SCOPE="ALL")+(ACT_DOOR_SCOPE="TIER_"&$F7)+(ACT_DOOR_SCOPE=$B7)))*SIGN(((ACT_SKU_SCOPE="ALL")+(ACT_SKU_SCOPE=$G7)))*(ACT_START<=13)*(ACT_END>=13)*IFERROR(ACT_UPLIFT-1,0)))*(1+SUMPRODUCT(SIGN(((ACT_DOOR_SCOPE="ALL")+(ACT_DOOR_SCOPE="TIER_"&$F7)+(ACT_DOOR_SCOPE=$B7)))*SIGN(((ACT_SKU_SCOPE="ALL")+(ACT_SKU_SCOPE=$G7)))*(13>ACT_END)*(ACT_END>0)*IFERROR(ACT_POSTLIFT,0))),0)))
A8: R0004 | B8: =Doors!$A$6 | C8: =Doors!$C$6 | D8: =Doors!$B$6 | E8: =Doors!$E$6 | F8: =Doors!$F$6 | G8: Lime Lemon | H8: =Doors!$G$6 | I8: =Doors!$J$6 | J8: =IF(OR($H8<>"Y",1<$I8),0,IF(SUMPRODUCT(((BULK_ENABLED="Y")*((BULK_TIER="ALL")+(BULK_TIER=$F8))*((BULK_SKU="ALL")+(BULK_SKU=$G8))*(BULK_START<=1)*(BULK_END>=1)))>0,IFERROR(SUMPRODUCT(((BULK_ENABLED="Y")*((BULK_TIER="ALL")+(BULK_TIER=$F8))*((BULK_SKU="ALL")+(BULK_SKU=$G8))*(BULK_START<=1)*(BULK_END>=1))*IFERROR(BULK_VALUE,0))/MAX(1,SUMPRODUCT(((BULK_ENABLED="Y")*((BULK_TIER="ALL")+(BULK_TIER=$F8))*((BULK_SKU="ALL")+(BULK_SKU=$G8))*(BULK_START<=1)*(BULK_END>=1)))),0),ROUND((INDEX(VELOCITY_TABLE,MATCH($F8,TIER_LIST,0),1))*(IF((1-$I8+1)<=0,0,IF((1-$I8+1)=1,RAMP_W1,IF((1-$I8+1)=2,RAMP_W2,IF((1-$I8+1)=3,RAMP_W3,RAMP_W4PLUS)))))*(INDEX(ACTIVE_MULT_TABLE,1,1))*(1+SUMPRODUCT(SIGN(((ACT_DOOR_SCOPE="ALL")+(ACT_DOOR_SCOPE="TIER_"&$F8)+(ACT_DOOR_SCOPE=$B8)))*SIGN(((ACT_SKU_SCOPE="ALL")+(ACT_SKU_SCOPE=$G8)))*(ACT_START<=1)*(ACT_END>=1)*IFERROR(ACT_UPLIFT-1,0)))*(1+SUMPRODUCT(SIGN(((ACT_DOOR_SCOPE="ALL")+(ACT_DOOR_SCOPE="TIER_"&$F8)+(ACT_DOOR_SCOPE=$B8)))*SIGN(((ACT_SKU_SCOPE="ALL")+(ACT_SKU_SCOPE=$G8)))*(1>ACT_END)*(ACT_END>0)*IFERROR(ACT_POSTLIFT,0))),0))) | K8: =IF(OR($H8<>"Y",2<$I8),0,IF(SUMPRODUCT(((BULK_ENABLED="Y")*((BULK_TIER="ALL")+(BULK_TIER=$F8))*((BULK_SKU="ALL")+(BULK_SKU=$G8))*(BULK_START<=2)*(BULK_END>=2)))>0,IFERROR(SUMPRODUCT(((BULK_ENABLED="Y")*((BULK_TIER="ALL")+(BULK_TIER=$F8))*((BULK_SKU="ALL")+(BULK_SKU=$G8))*(BULK_START<=2)*(BULK_END>=2))*IFERROR(BULK_VALUE,0))/MAX(1,SUMPRODUCT(((BULK_ENABLED="Y")*((BULK_TIER="ALL")+(BULK_TIER=$F8))*((BULK_SKU="ALL")+(BULK_SKU=$G8))*(BULK_START<=2)*(BULK_END>=2)))),0),ROUND((INDEX(VELOCITY_TABLE,MATCH($F8,TIER_LIST,0),1))*(IF((2-$I8+1)<=0,0,IF((2-$I8+1)=1,RAMP_W1,IF((2-$I8+1)=2,RAMP_W2,IF((2-$I8+1)=3,RAMP_W3,RAMP_W4PLUS)))))*(INDEX(ACTIVE_MULT_TABLE,1,1))*(1+SUMPRODUCT(SIGN(((ACT_DOOR_SCOPE="ALL")+(ACT_DOOR_SCOPE="TIER_"&$F8)+(ACT_DOOR_SCOPE=$B8)))*SIGN(((ACT_SKU_SCOPE="ALL")+(ACT_SKU_SCOPE=$G8)))*(ACT_START<=2)*(ACT_END>=2)*IFERROR(ACT_UPLIFT-1,0)))*(1+SUMPRODUCT(SIGN(((ACT_DOOR_SCOPE="ALL")+(ACT_DOOR_SCOPE="TIER_"&$F8)+(ACT_DOOR_SCOPE=$B8)))*SIGN(((ACT_SKU_SCOPE="ALL")+(ACT_SKU_SCOPE=$G8)))*(2>ACT_END)*(ACT_END>0)*IFERROR(ACT_POSTLIFT,0))),0))) | L8: =IF(OR($H8<>"Y",3<$I8),0,IF(SUMPRODUCT(((BULK_ENABLED="Y")*((BULK_TIER="ALL")+(BULK_TIER=$F8))*((BULK_SKU="ALL")+(BULK_SKU=$G8))*(BULK_START<=3)*(BULK_END>=3)))>0,IFERROR(SUMPRODUCT(((BULK_ENABLED="Y")*((BULK_TIER="ALL")+(BULK_TIER=$F8))*((BULK_SKU="ALL")+(BULK_SKU=$G8))*(BULK_START<=3)*(BULK_END>=3))*IFERROR(BULK_VALUE,0))/MAX(1,SUMPRODUCT(((BULK_ENABLED="Y")*((BULK_TIER="ALL")+(BULK_TIER=$F8))*((BULK_SKU="ALL")+(BULK_SKU=$G8))*(BULK_START<=3)*(BULK_END>=3)))),0),ROUND((INDEX(VELOCITY_TABLE,MATCH($F8,TIER_LIST,0),1))*(IF((3-$I8+1)<=0,0,IF((3-$I8+1)=1,RAMP_W1,IF((3-$I8+1)=2,RAMP_W2,IF((3-$I8+1)=3,RAMP_W3,RAMP_W4PLUS)))))*(INDEX(ACTIVE_MULT_TABLE,1,1))*(1+SUMPRODUCT(SIGN(((ACT_DOOR_SCOPE="ALL")+(ACT_DOOR_SCOPE="TIER_"&$F8)+(ACT_DOOR_SCOPE=$B8)))*SIGN(((ACT_SKU_SCOPE="ALL")+(ACT_SKU_SCOPE=$G8)))*(ACT_START<=3)*(ACT_END>=3)*IFERROR(ACT_UPLIFT-1,0)))*(1+SUMPRODUCT(SIGN(((ACT_DOOR_SCOPE="ALL")+(ACT_DOOR_SCOPE="TIER_"&$F8)+(ACT_DOOR_SCOPE=$B8)))*SIGN(((ACT_SKU_SCOPE="ALL")+(ACT_SKU_SCOPE=$G8)))*(3>ACT_END)*(ACT_END>0)*IFERROR(ACT_POSTLIFT,0))),0))) | M8: =IF(OR($H8<>"Y",4<$I8),0,IF(SUMPRODUCT(((BULK_ENABLED="Y")*((BULK_TIER="ALL")+(BULK_TIER=$F8))*((BULK_SKU="ALL")+(BULK_SKU=$G8))*(BULK_START<=4)*(BULK_END>=4)))>0,IFERROR(SUMPRODUCT(((BULK_ENABLED="Y")*((BULK_TIER="ALL")+(BULK_TIER=$F8))*((BULK_SKU="ALL")+(BULK_SKU=$G8))*(BULK_START<=4)*(BULK_END>=4))*IFERROR(BULK_VALUE,0))/MAX(1,SUMPRODUCT(((BULK_ENABLED="Y")*((BULK_TIER="ALL")+(BULK_TIER=$F8))*((BULK_SKU="ALL")+(BULK_SKU=$G8))*(BULK_START<=4)*(BULK_END>=4)))),0),ROUND((INDEX(VELOCITY_TABLE,MATCH($F8,TIER_LIST,0),1))*(IF((4-$I8+1)<=0,0,IF((4-$I8+1)=1,RAMP_W1,IF((4-$I8+1)=2,RAMP_W2,IF((4-$I8+1)=3,RAMP_W3,RAMP_W4PLUS)))))*(INDEX(ACTIVE_MULT_TABLE,1,1))*(1+SUMPRODUCT(SIGN(((ACT_DOOR_SCOPE="ALL")+(ACT_DOOR_SCOPE="TIER_"&$F8)+(ACT_DOOR_SCOPE=$B8)))*SIGN(((ACT_SKU_SCOPE="ALL")+(ACT_SKU_SCOPE=$G8)))*(ACT_START<=4)*(ACT_END>=4)*IFERROR(ACT_UPLIFT-1,0)))*(1+SUMPRODUCT(SIGN(((ACT_DOOR_SCOPE="ALL")+(ACT_DOOR_SCOPE="TIER_"&$F8)+(ACT_DOOR_SCOPE=$B8)))*SIGN(((ACT_SKU_SCOPE="ALL")+(ACT_SKU_SCOPE=$G8)))*(4>ACT_END)*(ACT_END>0)*IFERROR(ACT_POSTLIFT,0))),0))) | N8: =IF(OR($H8<>"Y",5<$I8),0,IF(SUMPRODUCT(((BULK_ENABLED="Y")*((BULK_TIER="ALL")+(BULK_TIER=$F8))*((BULK_SKU="ALL")+(BULK_SKU=$G8))*(BULK_START<=5)*(BULK_END>=5)))>0,IFERROR(SUMPRODUCT(((BULK_ENABLED="Y")*((BULK_TIER="ALL")+(BULK_TIER=$F8))*((BULK_SKU="ALL")+(BULK_SKU=$G8))*(BULK_START<=5)*(BULK_END>=5))*IFERROR(BULK_VALUE,0))/MAX(1,SUMPRODUCT(((BULK_ENABLED="Y")*((BULK_TIER="ALL")+(BULK_TIER=$F8))*((BULK_SKU="ALL")+(BULK_SKU=$G8))*(BULK_START<=5)*(BULK_END>=5)))),0),ROUND((INDEX(VELOCITY_TABLE,MATCH($F8,TIER_LIST,0),1))*(IF((5-$I8+1)<=0,0,IF((5-$I8+1)=1,RAMP_W1,IF((5-$I8+1)=2,RAMP_W2,IF((5-$I8+1)=3,RAMP_W3,RAMP_W4PLUS)))))*(INDEX(ACTIVE_MULT_TABLE,1,1))*(1+SUMPRODUCT(SIGN(((ACT_DOOR_SCOPE="ALL")+(ACT_DOOR_SCOPE="TIER_"&$F8)+(ACT_DOOR_SCOPE=$B8)))*SIGN(((ACT_SKU_SCOPE="ALL")+(ACT_SKU_SCOPE=$G8)))*(ACT_START<=5)*(ACT_END>=5)*IFERROR(ACT_UPLIFT-1,0)))*(1+SUMPRODUCT(SIGN(((ACT_DOOR_SCOPE="ALL")+(ACT_DOOR_SCOPE="TIER_"&$F8)+(ACT_DOOR_SCOPE=$B8)))*SIGN(((ACT_SKU_SCOPE="ALL")+(ACT_SKU_SCOPE=$G8)))*(5>ACT_END)*(ACT_END>0)*IFERROR(ACT_POSTLIFT,0))),0))) | O8: =IF(OR($H8<>"Y",6<$I8),0,IF(SUMPRODUCT(((BULK_ENABLED="Y")*((BULK_TIER="ALL")+(BULK_TIER=$F8))*((BULK_SKU="ALL")+(BULK_SKU=$G8))*(BULK_START<=6)*(BULK_END>=6)))>0,IFERROR(SUMPRODUCT(((BULK_ENABLED="Y")*((BULK_TIER="ALL")+(BULK_TIER=$F8))*((BULK_SKU="ALL")+(BULK_SKU=$G8))*(BULK_START<=6)*(BULK_END>=6))*IFERROR(BULK_VALUE,0))/MAX(1,SUMPRODUCT(((BULK_ENABLED="Y")*((BULK_TIER="ALL")+(BULK_TIER=$F8))*((BULK_SKU="ALL")+(BULK_SKU=$G8))*(BULK_START<=6)*(BULK_END>=6)))),0),ROUND((INDEX(VELOCITY_TABLE,MATCH($F8,TIER_LIST,0),1))*(IF((6-$I8+1)<=0,0,IF((6-$I8+1)=1,RAMP_W1,IF((6-$I8+1)=2,RAMP_W2,IF((6-$I8+1)=3,RAMP_W3,RAMP_W4PLUS)))))*(INDEX(ACTIVE_MULT_TABLE,1,1))*(1+SUMPRODUCT(SIGN(((ACT_DOOR_SCOPE="ALL")+(ACT_DOOR_SCOPE="TIER_"&$F8)+(ACT_DOOR_SCOPE=$B8)))*SIGN(((ACT_SKU_SCOPE="ALL")+(ACT_SKU_SCOPE=$G8)))*(ACT_START<=6)*(ACT_END>=6)*IFERROR(ACT_UPLIFT-1,0)))*(1+SUMPRODUCT(SIGN(((ACT_DOOR_SCOPE="ALL")+(ACT_DOOR_SCOPE="TIER_"&$F8)+(ACT_DOOR_SCOPE=$B8)))*SIGN(((ACT_SKU_SCOPE="ALL")+(ACT_SKU_SCOPE=$G8)))*(6>ACT_END)*(ACT_END>0)*IFERROR(ACT_POSTLIFT,0))),0))) | P8: =IF(OR($H8<>"Y",7<$I8),0,IF(SUMPRODUCT(((BULK_ENABLED="Y")*((BULK_TIER="ALL")+(BULK_TIER=$F8))*((BULK_SKU="ALL")+(BULK_SKU=$G8))*(BULK_START<=7)*(BULK_END>=7)))>0,IFERROR(SUMPRODUCT(((BULK_ENABLED="Y")*((BULK_TIER="ALL")+(BULK_TIER=$F8))*((BULK_SKU="ALL")+(BULK_SKU=$G8))*(BULK_START<=7)*(BULK_END>=7))*IFERROR(BULK_VALUE,0))/MAX(1,SUMPRODUCT(((BULK_ENABLED="Y")*((BULK_TIER="ALL")+(BULK_TIER=$F8))*((BULK_SKU="ALL")+(BULK_SKU=$G8))*(BULK_START<=7)*(BULK_END>=7)))),0),ROUND((INDEX(VELOCITY_TABLE,MATCH($F8,TIER_LIST,0),1))*(IF((7-$I8+1)<=0,0,IF((7-$I8+1)=1,RAMP_W1,IF((7-$I8+1)=2,RAMP_W2,IF((7-$I8+1)=3,RAMP_W3,RAMP_W4PLUS)))))*(INDEX(ACTIVE_MULT_TABLE,1,1))*(1+SUMPRODUCT(SIGN(((ACT_DOOR_SCOPE="ALL")+(ACT_DOOR_SCOPE="TIER_"&$F8)+(ACT_DOOR_SCOPE=$B8)))*SIGN(((ACT_SKU_SCOPE="ALL")+(ACT_SKU_SCOPE=$G8)))*(ACT_START<=7)*(ACT_END>=7)*IFERROR(ACT_UPLIFT-1,0)))*(1+SUMPRODUCT(SIGN(((ACT_DOOR_SCOPE="ALL")+(ACT_DOOR_SCOPE="TIER_"&$F8)+(ACT_DOOR_SCOPE=$B8)))*SIGN(((ACT_SKU_SCOPE="ALL")+(ACT_SKU_SCOPE=$G8)))*(7>ACT_END)*(ACT_END>0)*IFERROR(ACT_POSTLIFT,0))),0))) | Q8: =IF(OR($H8<>"Y",8<$I8),0,IF(SUMPRODUCT(((BULK_ENABLED="Y")*((BULK_TIER="ALL")+(BULK_TIER=$F8))*((BULK_SKU="ALL")+(BULK_SKU=$G8))*(BULK_START<=8)*(BULK_END>=8)))>0,IFERROR(SUMPRODUCT(((BULK_ENABLED="Y")*((BULK_TIER="ALL")+(BULK_TIER=$F8))*((BULK_SKU="ALL")+(BULK_SKU=$G8))*(BULK_START<=8)*(BULK_END>=8))*IFERROR(BULK_VALUE,0))/MAX(1,SUMPRODUCT(((BULK_ENABLED="Y")*((BULK_TIER="ALL")+(BULK_TIER=$F8))*((BULK_SKU="ALL")+(BULK_SKU=$G8))*(BULK_START<=8)*(BULK_END>=8)))),0),ROUND((INDEX(VELOCITY_TABLE,MATCH($F8,TIER_LIST,0),1))*(IF((8-$I8+1)<=0,0,IF((8-$I8+1)=1,RAMP_W1,IF((8-$I8+1)=2,RAMP_W2,IF((8-$I8+1)=3,RAMP_W3,RAMP_W4PLUS)))))*(INDEX(ACTIVE_MULT_TABLE,1,1))*(1+SUMPRODUCT(SIGN(((ACT_DOOR_SCOPE="ALL")+(ACT_DOOR_SCOPE="TIER_"&$F8)+(ACT_DOOR_SCOPE=$B8)))*SIGN(((ACT_SKU_SCOPE="ALL")+(ACT_SKU_SCOPE=$G8)))*(ACT_START<=8)*(ACT_END>=8)*IFERROR(ACT_UPLIFT-1,0)))*(1+SUMPRODUCT(SIGN(((ACT_DOOR_SCOPE="ALL")+(ACT_DOOR_SCOPE="TIER_"&$F8)+(ACT_DOOR_SCOPE=$B8)))*SIGN(((ACT_SKU_SCOPE="ALL")+(ACT_SKU_SCOPE=$G8)))*(8>ACT_END)*(ACT_END>0)*IFERROR(ACT_POSTLIFT,0))),0))) | R8: =IF(OR($H8<>"Y",9<$I8),0,IF(SUMPRODUCT(((BULK_ENABLED="Y")*((BULK_TIER="ALL")+(BULK_TIER=$F8))*((BULK_SKU="ALL")+(BULK_SKU=$G8))*(BULK_START<=9)*(BULK_END>=9)))>0,IFERROR(SUMPRODUCT(((BULK_ENABLED="Y")*((BULK_TIER="ALL")+(BULK_TIER=$F8))*((BULK_SKU="ALL")+(BULK_SKU=$G8))*(BULK_START<=9)*(BULK_END>=9))*IFERROR(BULK_VALUE,0))/MAX(1,SUMPRODUCT(((BULK_ENABLED="Y")*((BULK_TIER="ALL")+(BULK_TIER=$F8))*((BULK_SKU="ALL")+(BULK_SKU=$G8))*(BULK_START<=9)*(BULK_END>=9)))),0),ROUND((INDEX(VELOCITY_TABLE,MATCH($F8,TIER_LIST,0),1))*(IF((9-$I8+1)<=0,0,IF((9-$I8+1)=1,RAMP_W1,IF((9-$I8+1)=2,RAMP_W2,IF((9-$I8+1)=3,RAMP_W3,RAMP_W4PLUS)))))*(INDEX(ACTIVE_MULT_TABLE,1,1))*(1+SUMPRODUCT(SIGN(((ACT_DOOR_SCOPE="ALL")+(ACT_DOOR_SCOPE="TIER_"&$F8)+(ACT_DOOR_SCOPE=$B8)))*SIGN(((ACT_SKU_SCOPE="ALL")+(ACT_SKU_SCOPE=$G8)))*(ACT_START<=9)*(ACT_END>=9)*IFERROR(ACT_UPLIFT-1,0)))*(1+SUMPRODUCT(SIGN(((ACT_DOOR_SCOPE="ALL")+(ACT_DOOR_SCOPE="TIER_"&$F8)+(ACT_DOOR_SCOPE=$B8)))*SIGN(((ACT_SKU_SCOPE="ALL")+(ACT_SKU_SCOPE=$G8)))*(9>ACT_END)*(ACT_END>0)*IFERROR(ACT_POSTLIFT,0))),0))) | S8: =IF(OR($H8<>"Y",10<$I8),0,IF(SUMPRODUCT(((BULK_ENABLED="Y")*((BULK_TIER="ALL")+(BULK_TIER=$F8))*((BULK_SKU="ALL")+(BULK_SKU=$G8))*(BULK_START<=10)*(BULK_END>=10)))>0,IFERROR(SUMPRODUCT(((BULK_ENABLED="Y")*((BULK_TIER="ALL")+(BULK_TIER=$F8))*((BULK_SKU="ALL")+(BULK_SKU=$G8))*(BULK_START<=10)*(BULK_END>=10))*IFERROR(BULK_VALUE,0))/MAX(1,SUMPRODUCT(((BULK_ENABLED="Y")*((BULK_TIER="ALL")+(BULK_TIER=$F8))*((BULK_SKU="ALL")+(BULK_SKU=$G8))*(BULK_START<=10)*(BULK_END>=10)))),0),ROUND((INDEX(VELOCITY_TABLE,MATCH($F8,TIER_LIST,0),1))*(IF((10-$I8+1)<=0,0,IF((10-$I8+1)=1,RAMP_W1,IF((10-$I8+1)=2,RAMP_W2,IF((10-$I8+1)=3,RAMP_W3,RAMP_W4PLUS)))))*(INDEX(ACTIVE_MULT_TABLE,1,1))*(1+SUMPRODUCT(SIGN(((ACT_DOOR_SCOPE="ALL")+(ACT_DOOR_SCOPE="TIER_"&$F8)+(ACT_DOOR_SCOPE=$B8)))*SIGN(((ACT_SKU_SCOPE="ALL")+(ACT_SKU_SCOPE=$G8)))*(ACT_START<=10)*(ACT_END>=10)*IFERROR(ACT_UPLIFT-1,0)))*(1+SUMPRODUCT(SIGN(((ACT_DOOR_SCOPE="ALL")+(ACT_DOOR_SCOPE="TIER_"&$F8)+(ACT_DOOR_SCOPE=$B8)))*SIGN(((ACT_SKU_SCOPE="ALL")+(ACT_SKU_SCOPE=$G8)))*(10>ACT_END)*(ACT_END>0)*IFERROR(ACT_POSTLIFT,0))),0))) | T8: =IF(OR($H8<>"Y",11<$I8),0,IF(SUMPRODUCT(((BULK_ENABLED="Y")*((BULK_TIER="ALL")+(BULK_TIER=$F8))*((BULK_SKU="ALL")+(BULK_SKU=$G8))*(BULK_START<=11)*(BULK_END>=11)))>0,IFERROR(SUMPRODUCT(((BULK_ENABLED="Y")*((BULK_TIER="ALL")+(BULK_TIER=$F8))*((BULK_SKU="ALL")+(BULK_SKU=$G8))*(BULK_START<=11)*(BULK_END>=11))*IFERROR(BULK_VALUE,0))/MAX(1,SUMPRODUCT(((BULK_ENABLED="Y")*((BULK_TIER="ALL")+(BULK_TIER=$F8))*((BULK_SKU="ALL")+(BULK_SKU=$G8))*(BULK_START<=11)*(BULK_END>=11)))),0),ROUND((INDEX(VELOCITY_TABLE,MATCH($F8,TIER_LIST,0),1))*(IF((11-$I8+1)<=0,0,IF((11-$I8+1)=1,RAMP_W1,IF((11-$I8+1)=2,RAMP_W2,IF((11-$I8+1)=3,RAMP_W3,RAMP_W4PLUS)))))*(INDEX(ACTIVE_MULT_TABLE,1,1))*(1+SUMPRODUCT(SIGN(((ACT_DOOR_SCOPE="ALL")+(ACT_DOOR_SCOPE="TIER_"&$F8)+(ACT_DOOR_SCOPE=$B8)))*SIGN(((ACT_SKU_SCOPE="ALL")+(ACT_SKU_SCOPE=$G8)))*(ACT_START<=11)*(ACT_END>=11)*IFERROR(ACT_UPLIFT-1,0)))*(1+SUMPRODUCT(SIGN(((ACT_DOOR_SCOPE="ALL")+(ACT_DOOR_SCOPE="TIER_"&$F8)+(ACT_DOOR_SCOPE=$B8)))*SIGN(((ACT_SKU_SCOPE="ALL")+(ACT_SKU_SCOPE=$G8)))*(11>ACT_END)*(ACT_END>0)*IFERROR(ACT_POSTLIFT,0))),0))) | U8: =IF(OR($H8<>"Y",12<$I8),0,IF(SUMPRODUCT(((BULK_ENABLED="Y")*((BULK_TIER="ALL")+(BULK_TIER=$F8))*((BULK_SKU="ALL")+(BULK_SKU=$G8))*(BULK_START<=12)*(BULK_END>=12)))>0,IFERROR(SUMPRODUCT(((BULK_ENABLED="Y")*((BULK_TIER="ALL")+(BULK_TIER=$F8))*((BULK_SKU="ALL")+(BULK_SKU=$G8))*(BULK_START<=12)*(BULK_END>=12))*IFERROR(BULK_VALUE,0))/MAX(1,SUMPRODUCT(((BULK_ENABLED="Y")*((BULK_TIER="ALL")+(BULK_TIER=$F8))*((BULK_SKU="ALL")+(BULK_SKU=$G8))*(BULK_START<=12)*(BULK_END>=12)))),0),ROUND((INDEX(VELOCITY_TABLE,MATCH($F8,TIER_LIST,0),1))*(IF((12-$I8+1)<=0,0,IF((12-$I8+1)=1,RAMP_W1,IF((12-$I8+1)=2,RAMP_W2,IF((12-$I8+1)=3,RAMP_W3,RAMP_W4PLUS)))))*(INDEX(ACTIVE_MULT_TABLE,1,1))*(1+SUMPRODUCT(SIGN(((ACT_DOOR_SCOPE="ALL")+(ACT_DOOR_SCOPE="TIER_"&$F8)+(ACT_DOOR_SCOPE=$B8)))*SIGN(((ACT_SKU_SCOPE="ALL")+(ACT_SKU_SCOPE=$G8)))*(ACT_START<=12)*(ACT_END>=12)*IFERROR(ACT_UPLIFT-1,0)))*(1+SUMPRODUCT(SIGN(((ACT_DOOR_SCOPE="ALL")+(ACT_DOOR_SCOPE="TIER_"&$F8)+(ACT_DOOR_SCOPE=$B8)))*SIGN(((ACT_SKU_SCOPE="ALL")+(ACT_SKU_SCOPE=$G8)))*(12>ACT_END)*(ACT_END>0)*IFERROR(ACT_POSTLIFT,0))),0))) | V8: =IF(OR($H8<>"Y",13<$I8),0,IF(SUMPRODUCT(((BULK_ENABLED="Y")*((BULK_TIER="ALL")+(BULK_TIER=$F8))*((BULK_SKU="ALL")+(BULK_SKU=$G8))*(BULK_START<=13)*(BULK_END>=13)))>0,IFERROR(SUMPRODUCT(((BULK_ENABLED="Y")*((BULK_TIER="ALL")+(BULK_TIER=$F8))*((BULK_SKU="ALL")+(BULK_SKU=$G8))*(BULK_START<=13)*(BULK_END>=13))*IFERROR(BULK_VALUE,0))/MAX(1,SUMPRODUCT(((BULK_ENABLED="Y")*((BULK_TIER="ALL")+(BULK_TIER=$F8))*((BULK_SKU="ALL")+(BULK_SKU=$G8))*(BULK_START<=13)*(BULK_END>=13)))),0),ROUND((INDEX(VELOCITY_TABLE,MATCH($F8,TIER_LIST,0),1))*(IF((13-$I8+1)<=0,0,IF((13-$I8+1)=1,RAMP_W1,IF((13-$I8+1)=2,RAMP_W2,IF((13-$I8+1)=3,RAMP_W3,RAMP_W4PLUS)))))*(INDEX(ACTIVE_MULT_TABLE,1,1))*(1+SUMPRODUCT(SIGN(((ACT_DOOR_SCOPE="ALL")+(ACT_DOOR_SCOPE="TIER_"&$F8)+(ACT_DOOR_SCOPE=$B8)))*SIGN(((ACT_SKU_SCOPE="ALL")+(ACT_SKU_SCOPE=$G8)))*(ACT_START<=13)*(ACT_END>=13)*IFERROR(ACT_UPLIFT-1,0)))*(1+SUMPRODUCT(SIGN(((ACT_DOOR_SCOPE="ALL")+(ACT_DOOR_SCOPE="TIER_"&$F8)+(ACT_DOOR_SCOPE=$B8)))*SIGN(((ACT_SKU_SCOPE="ALL")+(ACT_SKU_SCOPE=$G8)))*(13>ACT_END)*(ACT_END>0)*IFERROR(ACT_POSTLIFT,0))),0)))
A9: R0005 | B9: =Doors!$A$6 | C9: =Doors!$C$6 | D9: =Doors!$B$6 | E9: =Doors!$E$6 | F9: =Doors!$F$6 | G9: Pineapple Passion Fruit | H9: =Doors!$H$6 | I9: =Doors!$J$6 | J9: =IF(OR($H9<>"Y",1<$I9),0,IF(SUMPRODUCT(((BULK_ENABLED="Y")*((BULK_TIER="ALL")+(BULK_TIER=$F9))*((BULK_SKU="ALL")+(BULK_SKU=$G9))*(BULK_START<=1)*(BULK_END>=1)))>0,IFERROR(SUMPRODUCT(((BULK_ENABLED="Y")*((BULK_TIER="ALL")+(BULK_TIER=$F9))*((BULK_SKU="ALL")+(BULK_SKU=$G9))*(BULK_START<=1)*(BULK_END>=1))*IFERROR(BULK_VALUE,0))/MAX(1,SUMPRODUCT(((BULK_ENABLED="Y")*((BULK_TIER="ALL")+(BULK_TIER=$F9))*((BULK_SKU="ALL")+(BULK_SKU=$G9))*(BULK_START<=1)*(BULK_END>=1)))),0),ROUND((INDEX(VELOCITY_TABLE,MATCH($F9,TIER_LIST,0),2))*(IF((1-$I9+1)<=0,0,IF((1-$I9+1)=1,RAMP_W1,IF((1-$I9+1)=2,RAMP_W2,IF((1-$I9+1)=3,RAMP_W3,RAMP_W4PLUS)))))*(INDEX(ACTIVE_MULT_TABLE,2,1))*(1+SUMPRODUCT(SIGN(((ACT_DOOR_SCOPE="ALL")+(ACT_DOOR_SCOPE="TIER_"&$F9)+(ACT_DOOR_SCOPE=$B9)))*SIGN(((ACT_SKU_SCOPE="ALL")+(ACT_SKU_SCOPE=$G9)))*(ACT_START<=1)*(ACT_END>=1)*IFERROR(ACT_UPLIFT-1,0)))*(1+SUMPRODUCT(SIGN(((ACT_DOOR_SCOPE="ALL")+(ACT_DOOR_SCOPE="TIER_"&$F9)+(ACT_DOOR_SCOPE=$B9)))*SIGN(((ACT_SKU_SCOPE="ALL")+(ACT_SKU_SCOPE=$G9)))*(1>ACT_END)*(ACT_END>0)*IFERROR(ACT_POSTLIFT,0))),0))) | K9: =IF(OR($H9<>"Y",2<$I9),0,IF(SUMPRODUCT(((BULK_ENABLED="Y")*((BULK_TIER="ALL")+(BULK_TIER=$F9))*((BULK_SKU="ALL")+(BULK_SKU=$G9))*(BULK_START<=2)*(BULK_END>=2)))>0,IFERROR(SUMPRODUCT(((BULK_ENABLED="Y")*((BULK_TIER="ALL")+(BULK_TIER=$F9))*((BULK_SKU="ALL")+(BULK_SKU=$G9))*(BULK_START<=2)*(BULK_END>=2))*IFERROR(BULK_VALUE,0))/MAX(1,SUMPRODUCT(((BULK_ENABLED="Y")*((BULK_TIER="ALL")+(BULK_TIER=$F9))*((BULK_SKU="ALL")+(BULK_SKU=$G9))*(BULK_START<=2)*(BULK_END>=2)))),0),ROUND((INDEX(VELOCITY_TABLE,MATCH($F9,TIER_LIST,0),2))*(IF((2-$I9+1)<=0,0,IF((2-$I9+1)=1,RAMP_W1,IF((2-$I9+1)=2,RAMP_W2,IF((2-$I9+1)=3,RAMP_W3,RAMP_W4PLUS)))))*(INDEX(ACTIVE_MULT_TABLE,2,1))*(1+SUMPRODUCT(SIGN(((ACT_DOOR_SCOPE="ALL")+(ACT_DOOR_SCOPE="TIER_"&$F9)+(ACT_DOOR_SCOPE=$B9)))*SIGN(((ACT_SKU_SCOPE="ALL")+(ACT_SKU_SCOPE=$G9)))*(ACT_START<=2)*(ACT_END>=2)*IFERROR(ACT_UPLIFT-1,0)))*(1+SUMPRODUCT(SIGN(((ACT_DOOR_SCOPE="ALL")+(ACT_DOOR_SCOPE="TIER_"&$F9)+(ACT_DOOR_SCOPE=$B9)))*SIGN(((ACT_SKU_SCOPE="ALL")+(ACT_SKU_SCOPE=$G9)))*(2>ACT_END)*(ACT_END>0)*IFERROR(ACT_POSTLIFT,0))),0))) | L9: =IF(OR($H9<>"Y",3<$I9),0,IF(SUMPRODUCT(((BULK_ENABLED="Y")*((BULK_TIER="ALL")+(BULK_TIER=$F9))*((BULK_SKU="ALL")+(BULK_SKU=$G9))*(BULK_START<=3)*(BULK_END>=3)))>0,IFERROR(SUMPRODUCT(((BULK_ENABLED="Y")*((BULK_TIER="ALL")+(BULK_TIER=$F9))*((BULK_SKU="ALL")+(BULK_SKU=$G9))*(BULK_START<=3)*(BULK_END>=3))*IFERROR(BULK_VALUE,0))/MAX(1,SUMPRODUCT(((BULK_ENABLED="Y")*((BULK_TIER="ALL")+(BULK_TIER=$F9))*((BULK_SKU="ALL")+(BULK_SKU=$G9))*(BULK_START<=3)*(BULK_END>=3)))),0),ROUND((INDEX(VELOCITY_TABLE,MATCH($F9,TIER_LIST,0),2))*(IF((3-$I9+1)<=0,0,IF((3-$I9+1)=1,RAMP_W1,IF((3-$I9+1)=2,RAMP_W2,IF((3-$I9+1)=3,RAMP_W3,RAMP_W4PLUS)))))*(INDEX(ACTIVE_MULT_TABLE,2,1))*(1+SUMPRODUCT(SIGN(((ACT_DOOR_SCOPE="ALL")+(ACT_DOOR_SCOPE="TIER_"&$F9)+(ACT_DOOR_SCOPE=$B9)))*SIGN(((ACT_SKU_SCOPE="ALL")+(ACT_SKU_SCOPE=$G9)))*(ACT_START<=3)*(ACT_END>=3)*IFERROR(ACT_UPLIFT-1,0)))*(1+SUMPRODUCT(SIGN(((ACT_DOOR_SCOPE="ALL")+(ACT_DOOR_SCOPE="TIER_"&$F9)+(ACT_DOOR_SCOPE=$B9)))*SIGN(((ACT_SKU_SCOPE="ALL")+(ACT_SKU_SCOPE=$G9)))*(3>ACT_END)*(ACT_END>0)*IFERROR(ACT_POSTLIFT,0))),0))) | M9: =IF(OR($H9<>"Y",4<$I9),0,IF(SUMPRODUCT(((BULK_ENABLED="Y")*((BULK_TIER="ALL")+(BULK_TIER=$F9))*((BULK_SKU="ALL")+(BULK_SKU=$G9))*(BULK_START<=4)*(BULK_END>=4)))>0,IFERROR(SUMPRODUCT(((BULK_ENABLED="Y")*((BULK_TIER="ALL")+(BULK_TIER=$F9))*((BULK_SKU="ALL")+(BULK_SKU=$G9))*(BULK_START<=4)*(BULK_END>=4))*IFERROR(BULK_VALUE,0))/MAX(1,SUMPRODUCT(((BULK_ENABLED="Y")*((BULK_TIER="ALL")+(BULK_TIER=$F9))*((BULK_SKU="ALL")+(BULK_SKU=$G9))*(BULK_START<=4)*(BULK_END>=4)))),0),ROUND((INDEX(VELOCITY_TABLE,MATCH($F9,TIER_LIST,0),2))*(IF((4-$I9+1)<=0,0,IF((4-$I9+1)=1,RAMP_W1,IF((4-$I9+1)=2,RAMP_W2,IF((4-$I9+1)=3,RAMP_W3,RAMP_W4PLUS)))))*(INDEX(ACTIVE_MULT_TABLE,2,1))*(1+SUMPRODUCT(SIGN(((ACT_DOOR_SCOPE="ALL")+(ACT_DOOR_SCOPE="TIER_"&$F9)+(ACT_DOOR_SCOPE=$B9)))*SIGN(((ACT_SKU_SCOPE="ALL")+(ACT_SKU_SCOPE=$G9)))*(ACT_START<=4)*(ACT_END>=4)*IFERROR(ACT_UPLIFT-1,0)))*(1+SUMPRODUCT(SIGN(((ACT_DOOR_SCOPE="ALL")+(ACT_DOOR_SCOPE="TIER_"&$F9)+(ACT_DOOR_SCOPE=$B9)))*SIGN(((ACT_SKU_SCOPE="ALL")+(ACT_SKU_SCOPE=$G9)))*(4>ACT_END)*(ACT_END>0)*IFERROR(ACT_POSTLIFT,0))),0))) | N9: =IF(OR($H9<>"Y",5<$I9),0,IF(SUMPRODUCT(((BULK_ENABLED="Y")*((BULK_TIER="ALL")+(BULK_TIER=$F9))*((BULK_SKU="ALL")+(BULK_SKU=$G9))*(BULK_START<=5)*(BULK_END>=5)))>0,IFERROR(SUMPRODUCT(((BULK_ENABLED="Y")*((BULK_TIER="ALL")+(BULK_TIER=$F9))*((BULK_SKU="ALL")+(BULK_SKU=$G9))*(BULK_START<=5)*(BULK_END>=5))*IFERROR(BULK_VALUE,0))/MAX(1,SUMPRODUCT(((BULK_ENABLED="Y")*((BULK_TIER="ALL")+(BULK_TIER=$F9))*((BULK_SKU="ALL")+(BULK_SKU=$G9))*(BULK_START<=5)*(BULK_END>=5)))),0),ROUND((INDEX(VELOCITY_TABLE,MATCH($F9,TIER_LIST,0),2))*(IF((5-$I9+1)<=0,0,IF((5-$I9+1)=1,RAMP_W1,IF((5-$I9+1)=2,RAMP_W2,IF((5-$I9+1)=3,RAMP_W3,RAMP_W4PLUS)))))*(INDEX(ACTIVE_MULT_TABLE,2,1))*(1+SUMPRODUCT(SIGN(((ACT_DOOR_SCOPE="ALL")+(ACT_DOOR_SCOPE="TIER_"&$F9)+(ACT_DOOR_SCOPE=$B9)))*SIGN(((ACT_SKU_SCOPE="ALL")+(ACT_SKU_SCOPE=$G9)))*(ACT_START<=5)*(ACT_END>=5)*IFERROR(ACT_UPLIFT-1,0)))*(1+SUMPRODUCT(SIGN(((ACT_DOOR_SCOPE="ALL")+(ACT_DOOR_SCOPE="TIER_"&$F9)+(ACT_DOOR_SCOPE=$B9)))*SIGN(((ACT_SKU_SCOPE="ALL")+(ACT_SKU_SCOPE=$G9)))*(5>ACT_END)*(ACT_END>0)*IFERROR(ACT_POSTLIFT,0))),0))) | O9: =IF(OR($H9<>"Y",6<$I9),0,IF(SUMPRODUCT(((BULK_ENABLED="Y")*((BULK_TIER="ALL")+(BULK_TIER=$F9))*((BULK_SKU="ALL")+(BULK_SKU=$G9))*(BULK_START<=6)*(BULK_END>=6)))>0,IFERROR(SUMPRODUCT(((BULK_ENABLED="Y")*((BULK_TIER="ALL")+(BULK_TIER=$F9))*((BULK_SKU="ALL")+(BULK_SKU=$G9))*(BULK_START<=6)*(BULK_END>=6))*IFERROR(BULK_VALUE,0))/MAX(1,SUMPRODUCT(((BULK_ENABLED="Y")*((BULK_TIER="ALL")+(BULK_TIER=$F9))*((BULK_SKU="ALL")+(BULK_SKU=$G9))*(BULK_START<=6)*(BULK_END>=6)))),0),ROUND((INDEX(VELOCITY_TABLE,MATCH($F9,TIER_LIST,0),2))*(IF((6-$I9+1)<=0,0,IF((6-$I9+1)=1,RAMP_W1,IF((6-$I9+1)=2,RAMP_W2,IF((6-$I9+1)=3,RAMP_W3,RAMP_W4PLUS)))))*(INDEX(ACTIVE_MULT_TABLE,2,1))*(1+SUMPRODUCT(SIGN(((ACT_DOOR_SCOPE="ALL")+(ACT_DOOR_SCOPE="TIER_"&$F9)+(ACT_DOOR_SCOPE=$B9)))*SIGN(((ACT_SKU_SCOPE="ALL")+(ACT_SKU_SCOPE=$G9)))*(ACT_START<=6)*(ACT_END>=6)*IFERROR(ACT_UPLIFT-1,0)))*(1+SUMPRODUCT(SIGN(((ACT_DOOR_SCOPE="ALL")+(ACT_DOOR_SCOPE="TIER_"&$F9)+(ACT_DOOR_SCOPE=$B9)))*SIGN(((ACT_SKU_SCOPE="ALL")+(ACT_SKU_SCOPE=$G9)))*(6>ACT_END)*(ACT_END>0)*IFERROR(ACT_POSTLIFT,0))),0))) | P9: =IF(OR($H9<>"Y",7<$I9),0,IF(SUMPRODUCT(((BULK_ENABLED="Y")*((BULK_TIER="ALL")+(BULK_TIER=$F9))*((BULK_SKU="ALL")+(BULK_SKU=$G9))*(BULK_START<=7)*(BULK_END>=7)))>0,IFERROR(SUMPRODUCT(((BULK_ENABLED="Y")*((BULK_TIER="ALL")+(BULK_TIER=$F9))*((BULK_SKU="ALL")+(BULK_SKU=$G9))*(BULK_START<=7)*(BULK_END>=7))*IFERROR(BULK_VALUE,0))/MAX(1,SUMPRODUCT(((BULK_ENABLED="Y")*((BULK_TIER="ALL")+(BULK_TIER=$F9))*((BULK_SKU="ALL")+(BULK_SKU=$G9))*(BULK_START<=7)*(BULK_END>=7)))),0),ROUND((INDEX(VELOCITY_TABLE,MATCH($F9,TIER_LIST,0),2))*(IF((7-$I9+1)<=0,0,IF((7-$I9+1)=1,RAMP_W1,IF((7-$I9+1)=2,RAMP_W2,IF((7-$I9+1)=3,RAMP_W3,RAMP_W4PLUS)))))*(INDEX(ACTIVE_MULT_TABLE,2,1))*(1+SUMPRODUCT(SIGN(((ACT_DOOR_SCOPE="ALL")+(ACT_DOOR_SCOPE="TIER_"&$F9)+(ACT_DOOR_SCOPE=$B9)))*SIGN(((ACT_SKU_SCOPE="ALL")+(ACT_SKU_SCOPE=$G9)))*(ACT_START<=7)*(ACT_END>=7)*IFERROR(ACT_UPLIFT-1,0)))*(1+SUMPRODUCT(SIGN(((ACT_DOOR_SCOPE="ALL")+(ACT_DOOR_SCOPE="TIER_"&$F9)+(ACT_DOOR_SCOPE=$B9)))*SIGN(((ACT_SKU_SCOPE="ALL")+(ACT_SKU_SCOPE=$G9)))*(7>ACT_END)*(ACT_END>0)*IFERROR(ACT_POSTLIFT,0))),0))) | Q9: =IF(OR($H9<>"Y",8<$I9),0,IF(SUMPRODUCT(((BULK_ENABLED="Y")*((BULK_TIER="ALL")+(BULK_TIER=$F9))*((BULK_SKU="ALL")+(BULK_SKU=$G9))*(BULK_START<=8)*(BULK_END>=8)))>0,IFERROR(SUMPRODUCT(((BULK_ENABLED="Y")*((BULK_TIER="ALL")+(BULK_TIER=$F9))*((BULK_SKU="ALL")+(BULK_SKU=$G9))*(BULK_START<=8)*(BULK_END>=8))*IFERROR(BULK_VALUE,0))/MAX(1,SUMPRODUCT(((BULK_ENABLED="Y")*((BULK_TIER="ALL")+(BULK_TIER=$F9))*((BULK_SKU="ALL")+(BULK_SKU=$G9))*(BULK_START<=8)*(BULK_END>=8)))),0),ROUND((INDEX(VELOCITY_TABLE,MATCH($F9,TIER_LIST,0),2))*(IF((8-$I9+1)<=0,0,IF((8-$I9+1)=1,RAMP_W1,IF((8-$I9+1)=2,RAMP_W2,IF((8-$I9+1)=3,RAMP_W3,RAMP_W4PLUS)))))*(INDEX(ACTIVE_MULT_TABLE,2,1))*(1+SUMPRODUCT(SIGN(((ACT_DOOR_SCOPE="ALL")+(ACT_DOOR_SCOPE="TIER_"&$F9)+(ACT_DOOR_SCOPE=$B9)))*SIGN(((ACT_SKU_SCOPE="ALL")+(ACT_SKU_SCOPE=$G9)))*(ACT_START<=8)*(ACT_END>=8)*IFERROR(ACT_UPLIFT-1,0)))*(1+SUMPRODUCT(SIGN(((ACT_DOOR_SCOPE="ALL")+(ACT_DOOR_SCOPE="TIER_"&$F9)+(ACT_DOOR_SCOPE=$B9)))*SIGN(((ACT_SKU_SCOPE="ALL")+(ACT_SKU_SCOPE=$G9)))*(8>ACT_END)*(ACT_END>0)*IFERROR(ACT_POSTLIFT,0))),0))) | R9: =IF(OR($H9<>"Y",9<$I9),0,IF(SUMPRODUCT(((BULK_ENABLED="Y")*((BULK_TIER="ALL")+(BULK_TIER=$F9))*((BULK_SKU="ALL")+(BULK_SKU=$G9))*(BULK_START<=9)*(BULK_END>=9)))>0,IFERROR(SUMPRODUCT(((BULK_ENABLED="Y")*((BULK_TIER="ALL")+(BULK_TIER=$F9))*((BULK_SKU="ALL")+(BULK_SKU=$G9))*(BULK_START<=9)*(BULK_END>=9))*IFERROR(BULK_VALUE,0))/MAX(1,SUMPRODUCT(((BULK_ENABLED="Y")*((BULK_TIER="ALL")+(BULK_TIER=$F9))*((BULK_SKU="ALL")+(BULK_SKU=$G9))*(BULK_START<=9)*(BULK_END>=9)))),0),ROUND((INDEX(VELOCITY_TABLE,MATCH($F9,TIER_LIST,0),2))*(IF((9-$I9+1)<=0,0,IF((9-$I9+1)=1,RAMP_W1,IF((9-$I9+1)=2,RAMP_W2,IF((9-$I9+1)=3,RAMP_W3,RAMP_W4PLUS)))))*(INDEX(ACTIVE_MULT_TABLE,2,1))*(1+SUMPRODUCT(SIGN(((ACT_DOOR_SCOPE="ALL")+(ACT_DOOR_SCOPE="TIER_"&$F9)+(ACT_DOOR_SCOPE=$B9)))*SIGN(((ACT_SKU_SCOPE="ALL")+(ACT_SKU_SCOPE=$G9)))*(ACT_START<=9)*(ACT_END>=9)*IFERROR(ACT_UPLIFT-1,0)))*(1+SUMPRODUCT(SIGN(((ACT_DOOR_SCOPE="ALL")+(ACT_DOOR_SCOPE="TIER_"&$F9)+(ACT_DOOR_SCOPE=$B9)))*SIGN(((ACT_SKU_SCOPE="ALL")+(ACT_SKU_SCOPE=$G9)))*(9>ACT_END)*(ACT_END>0)*IFERROR(ACT_POSTLIFT,0))),0))) | S9: =IF(OR($H9<>"Y",10<$I9),0,IF(SUMPRODUCT(((BULK_ENABLED="Y")*((BULK_TIER="ALL")+(BULK_TIER=$F9))*((BULK_SKU="ALL")+(BULK_SKU=$G9))*(BULK_START<=10)*(BULK_END>=10)))>0,IFERROR(SUMPRODUCT(((BULK_ENABLED="Y")*((BULK_TIER="ALL")+(BULK_TIER=$F9))*((BULK_SKU="ALL")+(BULK_SKU=$G9))*(BULK_START<=10)*(BULK_END>=10))*IFERROR(BULK_VALUE,0))/MAX(1,SUMPRODUCT(((BULK_ENABLED="Y")*((BULK_TIER="ALL")+(BULK_TIER=$F9))*((BULK_SKU="ALL")+(BULK_SKU=$G9))*(BULK_START<=10)*(BULK_END>=10)))),0),ROUND((INDEX(VELOCITY_TABLE,MATCH($F9,TIER_LIST,0),2))*(IF((10-$I9+1)<=0,0,IF((10-$I9+1)=1,RAMP_W1,IF((10-$I9+1)=2,RAMP_W2,IF((10-$I9+1)=3,RAMP_W3,RAMP_W4PLUS)))))*(INDEX(ACTIVE_MULT_TABLE,2,1))*(1+SUMPRODUCT(SIGN(((ACT_DOOR_SCOPE="ALL")+(ACT_DOOR_SCOPE="TIER_"&$F9)+(ACT_DOOR_SCOPE=$B9)))*SIGN(((ACT_SKU_SCOPE="ALL")+(ACT_SKU_SCOPE=$G9)))*(ACT_START<=10)*(ACT_END>=10)*IFERROR(ACT_UPLIFT-1,0)))*(1+SUMPRODUCT(SIGN(((ACT_DOOR_SCOPE="ALL")+(ACT_DOOR_SCOPE="TIER_"&$F9)+(ACT_DOOR_SCOPE=$B9)))*SIGN(((ACT_SKU_SCOPE="ALL")+(ACT_SKU_SCOPE=$G9)))*(10>ACT_END)*(ACT_END>0)*IFERROR(ACT_POSTLIFT,0))),0))) | T9: =IF(OR($H9<>"Y",11<$I9),0,IF(SUMPRODUCT(((BULK_ENABLED="Y")*((BULK_TIER="ALL")+(BULK_TIER=$F9))*((BULK_SKU="ALL")+(BULK_SKU=$G9))*(BULK_START<=11)*(BULK_END>=11)))>0,IFERROR(SUMPRODUCT(((BULK_ENABLED="Y")*((BULK_TIER="ALL")+(BULK_TIER=$F9))*((BULK_SKU="ALL")+(BULK_SKU=$G9))*(BULK_START<=11)*(BULK_END>=11))*IFERROR(BULK_VALUE,0))/MAX(1,SUMPRODUCT(((BULK_ENABLED="Y")*((BULK_TIER="ALL")+(BULK_TIER=$F9))*((BULK_SKU="ALL")+(BULK_SKU=$G9))*(BULK_START<=11)*(BULK_END>=11)))),0),ROUND((INDEX(VELOCITY_TABLE,MATCH($F9,TIER_LIST,0),2))*(IF((11-$I9+1)<=0,0,IF((11-$I9+1)=1,RAMP_W1,IF((11-$I9+1)=2,RAMP_W2,IF((11-$I9+1)=3,RAMP_W3,RAMP_W4PLUS)))))*(INDEX(ACTIVE_MULT_TABLE,2,1))*(1+SUMPRODUCT(SIGN(((ACT_DOOR_SCOPE="ALL")+(ACT_DOOR_SCOPE="TIER_"&$F9)+(ACT_DOOR_SCOPE=$B9)))*SIGN(((ACT_SKU_SCOPE="ALL")+(ACT_SKU_SCOPE=$G9)))*(ACT_START<=11)*(ACT_END>=11)*IFERROR(ACT_UPLIFT-1,0)))*(1+SUMPRODUCT(SIGN(((ACT_DOOR_SCOPE="ALL")+(ACT_DOOR_SCOPE="TIER_"&$F9)+(ACT_DOOR_SCOPE=$B9)))*SIGN(((ACT_SKU_SCOPE="ALL")+(ACT_SKU_SCOPE=$G9)))*(11>ACT_END)*(ACT_END>0)*IFERROR(ACT_POSTLIFT,0))),0))) | U9: =IF(OR($H9<>"Y",12<$I9),0,IF(SUMPRODUCT(((BULK_ENABLED="Y")*((BULK_TIER="ALL")+(BULK_TIER=$F9))*((BULK_SKU="ALL")+(BULK_SKU=$G9))*(BULK_START<=12)*(BULK_END>=12)))>0,IFERROR(SUMPRODUCT(((BULK_ENABLED="Y")*((BULK_TIER="ALL")+(BULK_TIER=$F9))*((BULK_SKU="ALL")+(BULK_SKU=$G9))*(BULK_START<=12)*(BULK_END>=12))*IFERROR(BULK_VALUE,0))/MAX(1,SUMPRODUCT(((BULK_ENABLED="Y")*((BULK_TIER="ALL")+(BULK_TIER=$F9))*((BULK_SKU="ALL")+(BULK_SKU=$G9))*(BULK_START<=12)*(BULK_END>=12)))),0),ROUND((INDEX(VELOCITY_TABLE,MATCH($F9,TIER_LIST,0),2))*(IF((12-$I9+1)<=0,0,IF((12-$I9+1)=1,RAMP_W1,IF((12-$I9+1)=2,RAMP_W2,IF((12-$I9+1)=3,RAMP_W3,RAMP_W4PLUS)))))*(INDEX(ACTIVE_MULT_TABLE,2,1))*(1+SUMPRODUCT(SIGN(((ACT_DOOR_SCOPE="ALL")+(ACT_DOOR_SCOPE="TIER_"&$F9)+(ACT_DOOR_SCOPE=$B9)))*SIGN(((ACT_SKU_SCOPE="ALL")+(ACT_SKU_SCOPE=$G9)))*(ACT_START<=12)*(ACT_END>=12)*IFERROR(ACT_UPLIFT-1,0)))*(1+SUMPRODUCT(SIGN(((ACT_DOOR_SCOPE="ALL")+(ACT_DOOR_SCOPE="TIER_"&$F9)+(ACT_DOOR_SCOPE=$B9)))*SIGN(((ACT_SKU_SCOPE="ALL")+(ACT_SKU_SCOPE=$G9)))*(12>ACT_END)*(ACT_END>0)*IFERROR(ACT_POSTLIFT,0))),0))) | V9: =IF(OR($H9<>"Y",13<$I9),0,IF(SUMPRODUCT(((BULK_ENABLED="Y")*((BULK_TIER="ALL")+(BULK_TIER=$F9))*((BULK_SKU="ALL")+(BULK_SKU=$G9))*(BULK_START<=13)*(BULK_END>=13)))>0,IFERROR(SUMPRODUCT(((BULK_ENABLED="Y")*((BULK_TIER="ALL")+(BULK_TIER=$F9))*((BULK_SKU="ALL")+(BULK_SKU=$G9))*(BULK_START<=13)*(BULK_END>=13))*IFERROR(BULK_VALUE,0))/MAX(1,SUMPRODUCT(((BULK_ENABLED="Y")*((BULK_TIER="ALL")+(BULK_TIER=$F9))*((BULK_SKU="ALL")+(BULK_SKU=$G9))*(BULK_START<=13)*(BULK_END>=13)))),0),ROUND((INDEX(VELOCITY_TABLE,MATCH($F9,TIER_LIST,0),2))*(IF((13-$I9+1)<=0,0,IF((13-$I9+1)=1,RAMP_W1,IF((13-$I9+1)=2,RAMP_W2,IF((13-$I9+1)=3,RAMP_W3,RAMP_W4PLUS)))))*(INDEX(ACTIVE_MULT_TABLE,2,1))*(1+SUMPRODUCT(SIGN(((ACT_DOOR_SCOPE="ALL")+(ACT_DOOR_SCOPE="TIER_"&$F9)+(ACT_DOOR_SCOPE=$B9)))*SIGN(((ACT_SKU_SCOPE="ALL")+(ACT_SKU_SCOPE=$G9)))*(ACT_START<=13)*(ACT_END>=13)*IFERROR(ACT_UPLIFT-1,0)))*(1+SUMPRODUCT(SIGN(((ACT_DOOR_SCOPE="ALL")+(ACT_DOOR_SCOPE="TIER_"&$F9)+(ACT_DOOR_SCOPE=$B9)))*SIGN(((ACT_SKU_SCOPE="ALL")+(ACT_SKU_SCOPE=$G9)))*(13>ACT_END)*(ACT_END>0)*IFERROR(ACT_POSTLIFT,0))),0)))
A10: R0006 | B10: =Doors!$A$6 | C10: =Doors!$C$6 | D10: =Doors!$B$6 | E10: =Doors!$E$6 | F10: =Doors!$F$6 | G10: Raspberry | H10: =Doors!$I$6 | I10: =Doors!$J$6 | J10: =IF(OR($H10<>"Y",1<$I10),0,IF(SUMPRODUCT(((BULK_ENABLED="Y")*((BULK_TIER="ALL")+(BULK_TIER=$F10))*((BULK_SKU="ALL")+(BULK_SKU=$G10))*(BULK_START<=1)*(BULK_END>=1)))>0,IFERROR(SUMPRODUCT(((BULK_ENABLED="Y")*((BULK_TIER="ALL")+(BULK_TIER=$F10))*((BULK_SKU="ALL")+(BULK_SKU=$G10))*(BULK_START<=1)*(BULK_END>=1))*IFERROR(BULK_VALUE,0))/MAX(1,SUMPRODUCT(((BULK_ENABLED="Y")*((BULK_TIER="ALL")+(BULK_TIER=$F10))*((BULK_SKU="ALL")+(BULK_SKU=$G10))*(BULK_START<=1)*(BULK_END>=1)))),0),ROUND((INDEX(VELOCITY_TABLE,MATCH($F10,TIER_LIST,0),3))*(IF((1-$I10+1)<=0,0,IF((1-$I10+1)=1,RAMP_W1,IF((1-$I10+1)=2,RAMP_W2,IF((1-$I10+1)=3,RAMP_W3,RAMP_W4PLUS)))))*(INDEX(ACTIVE_MULT_TABLE,3,1))*(1+SUMPRODUCT(SIGN(((ACT_DOOR_SCOPE="ALL")+(ACT_DOOR_SCOPE="TIER_"&$F10)+(ACT_DOOR_SCOPE=$B10)))*SIGN(((ACT_SKU_SCOPE="ALL")+(ACT_SKU_SCOPE=$G10)))*(ACT_START<=1)*(ACT_END>=1)*IFERROR(ACT_UPLIFT-1,0)))*(1+SUMPRODUCT(SIGN(((ACT_DOOR_SCOPE="ALL")+(ACT_DOOR_SCOPE="TIER_"&$F10)+(ACT_DOOR_SCOPE=$B10)))*SIGN(((ACT_SKU_SCOPE="ALL")+(ACT_SKU_SCOPE=$G10)))*(1>ACT_END)*(ACT_END>0)*IFERROR(ACT_POSTLIFT,0))),0))) | K10: =IF(OR($H10<>"Y",2<$I10),0,IF(SUMPRODUCT(((BULK_ENABLED="Y")*((BULK_TIER="ALL")+(BULK_TIER=$F10))*((BULK_SKU="ALL")+(BULK_SKU=$G10))*(BULK_START<=2)*(BULK_END>=2)))>0,IFERROR(SUMPRODUCT(((BULK_ENABLED="Y")*((BULK_TIER="ALL")+(BULK_TIER=$F10))*((BULK_SKU="ALL")+(BULK_SKU=$G10))*(BULK_START<=2)*(BULK_END>=2))*IFERROR(BULK_VALUE,0))/MAX(1,SUMPRODUCT(((BULK_ENABLED="Y")*((BULK_TIER="ALL")+(BULK_TIER=$F10))*((BULK_SKU="ALL")+(BULK_SKU=$G10))*(BULK_START<=2)*(BULK_END>=2)))),0),ROUND((INDEX(VELOCITY_TABLE,MATCH($F10,TIER_LIST,0),3))*(IF((2-$I10+1)<=0,0,IF((2-$I10+1)=1,RAMP_W1,IF((2-$I10+1)=2,RAMP_W2,IF((2-$I10+1)=3,RAMP_W3,RAMP_W4PLUS)))))*(INDEX(ACTIVE_MULT_TABLE,3,1))*(1+SUMPRODUCT(SIGN(((ACT_DOOR_SCOPE="ALL")+(ACT_DOOR_SCOPE="TIER_"&$F10)+(ACT_DOOR_SCOPE=$B10)))*SIGN(((ACT_SKU_SCOPE="ALL")+(ACT_SKU_SCOPE=$G10)))*(ACT_START<=2)*(ACT_END>=2)*IFERROR(ACT_UPLIFT-1,0)))*(1+SUMPRODUCT(SIGN(((ACT_DOOR_SCOPE="ALL")+(ACT_DOOR_SCOPE="TIER_"&$F10)+(ACT_DOOR_SCOPE=$B10)))*SIGN(((ACT_SKU_SCOPE="ALL")+(ACT_SKU_SCOPE=$G10)))*(2>ACT_END)*(ACT_END>0)*IFERROR(ACT_POSTLIFT,0))),0))) | L10: =IF(OR($H10<>"Y",3<$I10),0,IF(SUMPRODUCT(((BULK_ENABLED="Y")*((BULK_TIER="ALL")+(BULK_TIER=$F10))*((BULK_SKU="ALL")+(BULK_SKU=$G10))*(BULK_START<=3)*(BULK_END>=3)))>0,IFERROR(SUMPRODUCT(((BULK_ENABLED="Y")*((BULK_TIER="ALL")+(BULK_TIER=$F10))*((BULK_SKU="ALL")+(BULK_SKU=$G10))*(BULK_START<=3)*(BULK_END>=3))*IFERROR(BULK_VALUE,0))/MAX(1,SUMPRODUCT(((BULK_ENABLED="Y")*((BULK_TIER="ALL")+(BULK_TIER=$F10))*((BULK_SKU="ALL")+(BULK_SKU=$G10))*(BULK_START<=3)*(BULK_END>=3)))),0),ROUND((INDEX(VELOCITY_TABLE,MATCH($F10,TIER_LIST,0),3))*(IF((3-$I10+1)<=0,0,IF((3-$I10+1)=1,RAMP_W1,IF((3-$I10+1)=2,RAMP_W2,IF((3-$I10+1)=3,RAMP_W3,RAMP_W4PLUS)))))*(INDEX(ACTIVE_MULT_TABLE,3,1))*(1+SUMPRODUCT(SIGN(((ACT_DOOR_SCOPE="ALL")+(ACT_DOOR_SCOPE="TIER_"&$F10)+(ACT_DOOR_SCOPE=$B10)))*SIGN(((ACT_SKU_SCOPE="ALL")+(ACT_SKU_SCOPE=$G10)))*(ACT_START<=3)*(ACT_END>=3)*IFERROR(ACT_UPLIFT-1,0)))*(1+SUMPRODUCT(SIGN(((ACT_DOOR_SCOPE="ALL")+(ACT_DOOR_SCOPE="TIER_"&$F10)+(ACT_DOOR_SCOPE=$B10)))*SIGN(((ACT_SKU_SCOPE="ALL")+(ACT_SKU_SCOPE=$G10)))*(3>ACT_END)*(ACT_END>0)*IFERROR(ACT_POSTLIFT,0))),0))) | M10: =IF(OR($H10<>"Y",4<$I10),0,IF(SUMPRODUCT(((BULK_ENABLED="Y")*((BULK_TIER="ALL")+(BULK_TIER=$F10))*((BULK_SKU="ALL")+(BULK_SKU=$G10))*(BULK_START<=4)*(BULK_END>=4)))>0,IFERROR(SUMPRODUCT(((BULK_ENABLED="Y")*((BULK_TIER="ALL")+(BULK_TIER=$F10))*((BULK_SKU="ALL")+(BULK_SKU=$G10))*(BULK_START<=4)*(BULK_END>=4))*IFERROR(BULK_VALUE,0))/MAX(1,SUMPRODUCT(((BULK_ENABLED="Y")*((BULK_TIER="ALL")+(BULK_TIER=$F10))*((BULK_SKU="ALL")+(BULK_SKU=$G10))*(BULK_START<=4)*(BULK_END>=4)))),0),ROUND((INDEX(VELOCITY_TABLE,MATCH($F10,TIER_LIST,0),3))*(IF((4-$I10+1)<=0,0,IF((4-$I10+1)=1,RAMP_W1,IF((4-$I10+1)=2,RAMP_W2,IF((4-$I10+1)=3,RAMP_W3,RAMP_W4PLUS)))))*(INDEX(ACTIVE_MULT_TABLE,3,1))*(1+SUMPRODUCT(SIGN(((ACT_DOOR_SCOPE="ALL")+(ACT_DOOR_SCOPE="TIER_"&$F10)+(ACT_DOOR_SCOPE=$B10)))*SIGN(((ACT_SKU_SCOPE="ALL")+(ACT_SKU_SCOPE=$G10)))*(ACT_START<=4)*(ACT_END>=4)*IFERROR(ACT_UPLIFT-1,0)))*(1+SUMPRODUCT(SIGN(((ACT_DOOR_SCOPE="ALL")+(ACT_DOOR_SCOPE="TIER_"&$F10)+(ACT_DOOR_SCOPE=$B10)))*SIGN(((ACT_SKU_SCOPE="ALL")+(ACT_SKU_SCOPE=$G10)))*(4>ACT_END)*(ACT_END>0)*IFERROR(ACT_POSTLIFT,0))),0))) | N10: =IF(OR($H10<>"Y",5<$I10),0,IF(SUMPRODUCT(((BULK_ENABLED="Y")*((BULK_TIER="ALL")+(BULK_TIER=$F10))*((BULK_SKU="ALL")+(BULK_SKU=$G10))*(BULK_START<=5)*(BULK_END>=5)))>0,IFERROR(SUMPRODUCT(((BULK_ENABLED="Y")*((BULK_TIER="ALL")+(BULK_TIER=$F10))*((BULK_SKU="ALL")+(BULK_SKU=$G10))*(BULK_START<=5)*(BULK_END>=5))*IFERROR(BULK_VALUE,0))/MAX(1,SUMPRODUCT(((BULK_ENABLED="Y")*((BULK_TIER="ALL")+(BULK_TIER=$F10))*((BULK_SKU="ALL")+(BULK_SKU=$G10))*(BULK_START<=5)*(BULK_END>=5)))),0),ROUND((INDEX(VELOCITY_TABLE,MATCH($F10,TIER_LIST,0),3))*(IF((5-$I10+1)<=0,0,IF((5-$I10+1)=1,RAMP_W1,IF((5-$I10+1)=2,RAMP_W2,IF((5-$I10+1)=3,RAMP_W3,RAMP_W4PLUS)))))*(INDEX(ACTIVE_MULT_TABLE,3,1))*(1+SUMPRODUCT(SIGN(((ACT_DOOR_SCOPE="ALL")+(ACT_DOOR_SCOPE="TIER_"&$F10)+(ACT_DOOR_SCOPE=$B10)))*SIGN(((ACT_SKU_SCOPE="ALL")+(ACT_SKU_SCOPE=$G10)))*(ACT_START<=5)*(ACT_END>=5)*IFERROR(ACT_UPLIFT-1,0)))*(1+SUMPRODUCT(SIGN(((ACT_DOOR_SCOPE="ALL")+(ACT_DOOR_SCOPE="TIER_"&$F10)+(ACT_DOOR_SCOPE=$B10)))*SIGN(((ACT_SKU_SCOPE="ALL")+(ACT_SKU_SCOPE=$G10)))*(5>ACT_END)*(ACT_END>0)*IFERROR(ACT_POSTLIFT,0))),0))) | O10: =IF(OR($H10<>"Y",6<$I10),0,IF(SUMPRODUCT(((BULK_ENABLED="Y")*((BULK_TIER="ALL")+(BULK_TIER=$F10))*((BULK_SKU="ALL")+(BULK_SKU=$G10))*(BULK_START<=6)*(BULK_END>=6)))>0,IFERROR(SUMPRODUCT(((BULK_ENABLED="Y")*((BULK_TIER="ALL")+(BULK_TIER=$F10))*((BULK_SKU="ALL")+(BULK_SKU=$G10))*(BULK_START<=6)*(BULK_END>=6))*IFERROR(BULK_VALUE,0))/MAX(1,SUMPRODUCT(((BULK_ENABLED="Y")*((BULK_TIER="ALL")+(BULK_TIER=$F10))*((BULK_SKU="ALL")+(BULK_SKU=$G10))*(BULK_START<=6)*(BULK_END>=6)))),0),ROUND((INDEX(VELOCITY_TABLE,MATCH($F10,TIER_LIST,0),3))*(IF((6-$I10+1)<=0,0,IF((6-$I10+1)=1,RAMP_W1,IF((6-$I10+1)=2,RAMP_W2,IF((6-$I10+1)=3,RAMP_W3,RAMP_W4PLUS)))))*(INDEX(ACTIVE_MULT_TABLE,3,1))*(1+SUMPRODUCT(SIGN(((ACT_DOOR_SCOPE="ALL")+(ACT_DOOR_SCOPE="TIER_"&$F10)+(ACT_DOOR_SCOPE=$B10)))*SIGN(((ACT_SKU_SCOPE="ALL")+(ACT_SKU_SCOPE=$G10)))*(ACT_START<=6)*(ACT_END>=6)*IFERROR(ACT_UPLIFT-1,0)))*(1+SUMPRODUCT(SIGN(((ACT_DOOR_SCOPE="ALL")+(ACT_DOOR_SCOPE="TIER_"&$F10)+(ACT_DOOR_SCOPE=$B10)))*SIGN(((ACT_SKU_SCOPE="ALL")+(ACT_SKU_SCOPE=$G10)))*(6>ACT_END)*(ACT_END>0)*IFERROR(ACT_POSTLIFT,0))),0))) | P10: =IF(OR($H10<>"Y",7<$I10),0,IF(SUMPRODUCT(((BULK_ENABLED="Y")*((BULK_TIER="ALL")+(BULK_TIER=$F10))*((BULK_SKU="ALL")+(BULK_SKU=$G10))*(BULK_START<=7)*(BULK_END>=7)))>0,IFERROR(SUMPRODUCT(((BULK_ENABLED="Y")*((BULK_TIER="ALL")+(BULK_TIER=$F10))*((BULK_SKU="ALL")+(BULK_SKU=$G10))*(BULK_START<=7)*(BULK_END>=7))*IFERROR(BULK_VALUE,0))/MAX(1,SUMPRODUCT(((BULK_ENABLED="Y")*((BULK_TIER="ALL")+(BULK_TIER=$F10))*((BULK_SKU="ALL")+(BULK_SKU=$G10))*(BULK_START<=7)*(BULK_END>=7)))),0),ROUND((INDEX(VELOCITY_TABLE,MATCH($F10,TIER_LIST,0),3))*(IF((7-$I10+1)<=0,0,IF((7-$I10+1)=1,RAMP_W1,IF((7-$I10+1)=2,RAMP_W2,IF((7-$I10+1)=3,RAMP_W3,RAMP_W4PLUS)))))*(INDEX(ACTIVE_MULT_TABLE,3,1))*(1+SUMPRODUCT(SIGN(((ACT_DOOR_SCOPE="ALL")+(ACT_DOOR_SCOPE="TIER_"&$F10)+(ACT_DOOR_SCOPE=$B10)))*SIGN(((ACT_SKU_SCOPE="ALL")+(ACT_SKU_SCOPE=$G10)))*(ACT_START<=7)*(ACT_END>=7)*IFERROR(ACT_UPLIFT-1,0)))*(1+SUMPRODUCT(SIGN(((ACT_DOOR_SCOPE="ALL")+(ACT_DOOR_SCOPE="TIER_"&$F10)+(ACT_DOOR_SCOPE=$B10)))*SIGN(((ACT_SKU_SCOPE="ALL")+(ACT_SKU_SCOPE=$G10)))*(7>ACT_END)*(ACT_END>0)*IFERROR(ACT_POSTLIFT,0))),0))) | Q10: =IF(OR($H10<>"Y",8<$I10),0,IF(SUMPRODUCT(((BULK_ENABLED="Y")*((BULK_TIER="ALL")+(BULK_TIER=$F10))*((BULK_SKU="ALL")+(BULK_SKU=$G10))*(BULK_START<=8)*(BULK_END>=8)))>0,IFERROR(SUMPRODUCT(((BULK_ENABLED="Y")*((BULK_TIER="ALL")+(BULK_TIER=$F10))*((BULK_SKU="ALL")+(BULK_SKU=$G10))*(BULK_START<=8)*(BULK_END>=8))*IFERROR(BULK_VALUE,0))/MAX(1,SUMPRODUCT(((BULK_ENABLED="Y")*((BULK_TIER="ALL")+(BULK_TIER=$F10))*((BULK_SKU="ALL")+(BULK_SKU=$G10))*(BULK_START<=8)*(BULK_END>=8)))),0),ROUND((INDEX(VELOCITY_TABLE,MATCH($F10,TIER_LIST,0),3))*(IF((8-$I10+1)<=0,0,IF((8-$I10+1)=1,RAMP_W1,IF((8-$I10+1)=2,RAMP_W2,IF((8-$I10+1)=3,RAMP_W3,RAMP_W4PLUS)))))*(INDEX(ACTIVE_MULT_TABLE,3,1))*(1+SUMPRODUCT(SIGN(((ACT_DOOR_SCOPE="ALL")+(ACT_DOOR_SCOPE="TIER_"&$F10)+(ACT_DOOR_SCOPE=$B10)))*SIGN(((ACT_SKU_SCOPE="ALL")+(ACT_SKU_SCOPE=$G10)))*(ACT_START<=8)*(ACT_END>=8)*IFERROR(ACT_UPLIFT-1,0)))*(1+SUMPRODUCT(SIGN(((ACT_DOOR_SCOPE="ALL")+(ACT_DOOR_SCOPE="TIER_"&$F10)+(ACT_DOOR_SCOPE=$B10)))*SIGN(((ACT_SKU_SCOPE="ALL")+(ACT_SKU_SCOPE=$G10)))*(8>ACT_END)*(ACT_END>0)*IFERROR(ACT_POSTLIFT,0))),0))) | R10: =IF(OR($H10<>"Y",9<$I10),0,IF(SUMPRODUCT(((BULK_ENABLED="Y")*((BULK_TIER="ALL")+(BULK_TIER=$F10))*((BULK_SKU="ALL")+(BULK_SKU=$G10))*(BULK_START<=9)*(BULK_END>=9)))>0,IFERROR(SUMPRODUCT(((BULK_ENABLED="Y")*((BULK_TIER="ALL")+(BULK_TIER=$F10))*((BULK_SKU="ALL")+(BULK_SKU=$G10))*(BULK_START<=9)*(BULK_END>=9))*IFERROR(BULK_VALUE,0))/MAX(1,SUMPRODUCT(((BULK_ENABLED="Y")*((BULK_TIER="ALL")+(BULK_TIER=$F10))*((BULK_SKU="ALL")+(BULK_SKU=$G10))*(BULK_START<=9)*(BULK_END>=9)))),0),ROUND((INDEX(VELOCITY_TABLE,MATCH($F10,TIER_LIST,0),3))*(IF((9-$I10+1)<=0,0,IF((9-$I10+1)=1,RAMP_W1,IF((9-$I10+1)=2,RAMP_W2,IF((9-$I10+1)=3,RAMP_W3,RAMP_W4PLUS)))))*(INDEX(ACTIVE_MULT_TABLE,3,1))*(1+SUMPRODUCT(SIGN(((ACT_DOOR_SCOPE="ALL")+(ACT_DOOR_SCOPE="TIER_"&$F10)+(ACT_DOOR_SCOPE=$B10)))*SIGN(((ACT_SKU_SCOPE="ALL")+(ACT_SKU_SCOPE=$G10)))*(ACT_START<=9)*(ACT_END>=9)*IFERROR(ACT_UPLIFT-1,0)))*(1+SUMPRODUCT(SIGN(((ACT_DOOR_SCOPE="ALL")+(ACT_DOOR_SCOPE="TIER_"&$F10)+(ACT_DOOR_SCOPE=$B10)))*SIGN(((ACT_SKU_SCOPE="ALL")+(ACT_SKU_SCOPE=$G10)))*(9>ACT_END)*(ACT_END>0)*IFERROR(ACT_POSTLIFT,0))),0))) | S10: =IF(OR($H10<>"Y",10<$I10),0,IF(SUMPRODUCT(((BULK_ENABLED="Y")*((BULK_TIER="ALL")+(BULK_TIER=$F10))*((BULK_SKU="ALL")+(BULK_SKU=$G10))*(BULK_START<=10)*(BULK_END>=10)))>0,IFERROR(SUMPRODUCT(((BULK_ENABLED="Y")*((BULK_TIER="ALL")+(BULK_TIER=$F10))*((BULK_SKU="ALL")+(BULK_SKU=$G10))*(BULK_START<=10)*(BULK_END>=10))*IFERROR(BULK_VALUE,0))/MAX(1,SUMPRODUCT(((BULK_ENABLED="Y")*((BULK_TIER="ALL")+(BULK_TIER=$F10))*((BULK_SKU="ALL")+(BULK_SKU=$G10))*(BULK_START<=10)*(BULK_END>=10)))),0),ROUND((INDEX(VELOCITY_TABLE,MATCH($F10,TIER_LIST,0),3))*(IF((10-$I10+1)<=0,0,IF((10-$I10+1)=1,RAMP_W1,IF((10-$I10+1)=2,RAMP_W2,IF((10-$I10+1)=3,RAMP_W3,RAMP_W4PLUS)))))*(INDEX(ACTIVE_MULT_TABLE,3,1))*(1+SUMPRODUCT(SIGN(((ACT_DOOR_SCOPE="ALL")+(ACT_DOOR_SCOPE="TIER_"&$F10)+(ACT_DOOR_SCOPE=$B10)))*SIGN(((ACT_SKU_SCOPE="ALL")+(ACT_SKU_SCOPE=$G10)))*(ACT_START<=10)*(ACT_END>=10)*IFERROR(ACT_UPLIFT-1,0)))*(1+SUMPRODUCT(SIGN(((ACT_DOOR_SCOPE="ALL")+(ACT_DOOR_SCOPE="TIER_"&$F10)+(ACT_DOOR_SCOPE=$B10)))*SIGN(((ACT_SKU_SCOPE="ALL")+(ACT_SKU_SCOPE=$G10)))*(10>ACT_END)*(ACT_END>0)*IFERROR(ACT_POSTLIFT,0))),0))) | T10: =IF(OR($H10<>"Y",11<$I10),0,IF(SUMPRODUCT(((BULK_ENABLED="Y")*((BULK_TIER="ALL")+(BULK_TIER=$F10))*((BULK_SKU="ALL")+(BULK_SKU=$G10))*(BULK_START<=11)*(BULK_END>=11)))>0,IFERROR(SUMPRODUCT(((BULK_ENABLED="Y")*((BULK_TIER="ALL")+(BULK_TIER=$F10))*((BULK_SKU="ALL")+(BULK_SKU=$G10))*(BULK_START<=11)*(BULK_END>=11))*IFERROR(BULK_VALUE,0))/MAX(1,SUMPRODUCT(((BULK_ENABLED="Y")*((BULK_TIER="ALL")+(BULK_TIER=$F10))*((BULK_SKU="ALL")+(BULK_SKU=$G10))*(BULK_START<=11)*(BULK_END>=11)))),0),ROUND((INDEX(VELOCITY_TABLE,MATCH($F10,TIER_LIST,0),3))*(IF((11-$I10+1)<=0,0,IF((11-$I10+1)=1,RAMP_W1,IF((11-$I10+1)=2,RAMP_W2,IF((11-$I10+1)=3,RAMP_W3,RAMP_W4PLUS)))))*(INDEX(ACTIVE_MULT_TABLE,3,1))*(1+SUMPRODUCT(SIGN(((ACT_DOOR_SCOPE="ALL")+(ACT_DOOR_SCOPE="TIER_"&$F10)+(ACT_DOOR_SCOPE=$B10)))*SIGN(((ACT_SKU_SCOPE="ALL")+(ACT_SKU_SCOPE=$G10)))*(ACT_START<=11)*(ACT_END>=11)*IFERROR(ACT_UPLIFT-1,0)))*(1+SUMPRODUCT(SIGN(((ACT_DOOR_SCOPE="ALL")+(ACT_DOOR_SCOPE="TIER_"&$F10)+(ACT_DOOR_SCOPE=$B10)))*SIGN(((ACT_SKU_SCOPE="ALL")+(ACT_SKU_SCOPE=$G10)))*(11>ACT_END)*(ACT_END>0)*IFERROR(ACT_POSTLIFT,0))),0))) | U10: =IF(OR($H10<>"Y",12<$I10),0,IF(SUMPRODUCT(((BULK_ENABLED="Y")*((BULK_TIER="ALL")+(BULK_TIER=$F10))*((BULK_SKU="ALL")+(BULK_SKU=$G10))*(BULK_START<=12)*(BULK_END>=12)))>0,IFERROR(SUMPRODUCT(((BULK_ENABLED="Y")*((BULK_TIER="ALL")+(BULK_TIER=$F10))*((BULK_SKU="ALL")+(BULK_SKU=$G10))*(BULK_START<=12)*(BULK_END>=12))*IFERROR(BULK_VALUE,0))/MAX(1,SUMPRODUCT(((BULK_ENABLED="Y")*((BULK_TIER="ALL")+(BULK_TIER=$F10))*((BULK_SKU="ALL")+(BULK_SKU=$G10))*(BULK_START<=12)*(BULK_END>=12)))),0),ROUND((INDEX(VELOCITY_TABLE,MATCH($F10,TIER_LIST,0),3))*(IF((12-$I10+1)<=0,0,IF((12-$I10+1)=1,RAMP_W1,IF((12-$I10+1)=2,RAMP_W2,IF((12-$I10+1)=3,RAMP_W3,RAMP_W4PLUS)))))*(INDEX(ACTIVE_MULT_TABLE,3,1))*(1+SUMPRODUCT(SIGN(((ACT_DOOR_SCOPE="ALL")+(ACT_DOOR_SCOPE="TIER_"&$F10)+(ACT_DOOR_SCOPE=$B10)))*SIGN(((ACT_SKU_SCOPE="ALL")+(ACT_SKU_SCOPE=$G10)))*(ACT_START<=12)*(ACT_END>=12)*IFERROR(ACT_UPLIFT-1,0)))*(1+SUMPRODUCT(SIGN(((ACT_DOOR_SCOPE="ALL")+(ACT_DOOR_SCOPE="TIER_"&$F10)+(ACT_DOOR_SCOPE=$B10)))*SIGN(((ACT_SKU_SCOPE="ALL")+(ACT_SKU_SCOPE=$G10)))*(12>ACT_END)*(ACT_END>0)*IFERROR(ACT_POSTLIFT,0))),0))) | V10: =IF(OR($H10<>"Y",13<$I10),0,IF(SUMPRODUCT(((BULK_ENABLED="Y")*((BULK_TIER="ALL")+(BULK_TIER=$F10))*((BULK_SKU="ALL")+(BULK_SKU=$G10))*(BULK_START<=13)*(BULK_END>=13)))>0,IFERROR(SUMPRODUCT(((BULK_ENABLED="Y")*((BULK_TIER="ALL")+(BULK_TIER=$F10))*((BULK_SKU="ALL")+(BULK_SKU=$G10))*(BULK_START<=13)*(BULK_END>=13))*IFERROR(BULK_VALUE,0))/MAX(1,SUMPRODUCT(((BULK_ENABLED="Y")*((BULK_TIER="ALL")+(BULK_TIER=$F10))*((BULK_SKU="ALL")+(BULK_SKU=$G10))*(BULK_START<=13)*(BULK_END>=13)))),0),ROUND((INDEX(VELOCITY_TABLE,MATCH($F10,TIER_LIST,0),3))*(IF((13-$I10+1)<=0,0,IF((13-$I10+1)=1,RAMP_W1,IF((13-$I10+1)=2,RAMP_W2,IF((13-$I10+1)=3,RAMP_W3,RAMP_W4PLUS)))))*(INDEX(ACTIVE_MULT_TABLE,3,1))*(1+SUMPRODUCT(SIGN(((ACT_DOOR_SCOPE="ALL")+(ACT_DOOR_SCOPE="TIER_"&$F10)+(ACT_DOOR_SCOPE=$B10)))*SIGN(((ACT_SKU_SCOPE="ALL")+(ACT_SKU_SCOPE=$G10)))*(ACT_START<=13)*(ACT_END>=13)*IFERROR(ACT_UPLIFT-1,0)))*(1+SUMPRODUCT(SIGN(((ACT_DOOR_SCOPE="ALL")+(ACT_DOOR_SCOPE="TIER_"&$F10)+(ACT_DOOR_SCOPE=$B10)))*SIGN(((ACT_SKU_SCOPE="ALL")+(ACT_SKU_SCOPE=$G10)))*(13>ACT_END)*(ACT_END>0)*IFERROR(ACT_POSTLIFT,0))),0)))
A11: R0007 | B11: =Doors!$A$7 | C11: =Doors!$C$7 | D11: =Doors!$B$7 | E11: =Doors!$E$7 | F11: =Doors!$F$7 | G11: Lime Lemon | H11: =Doors!$G$7 | I11: =Doors!$J$7 | J11: =IF(OR($H11<>"Y",1<$I11),0,IF(SUMPRODUCT(((BULK_ENABLED="Y")*((BULK_TIER="ALL")+(BULK_TIER=$F11))*((BULK_SKU="ALL")+(BULK_SKU=$G11))*(BULK_START<=1)*(BULK_END>=1)))>0,IFERROR(SUMPRODUCT(((BULK_ENABLED="Y")*((BULK_TIER="ALL")+(BULK_TIER=$F11))*((BULK_SKU="ALL")+(BULK_SKU=$G11))*(BULK_START<=1)*(BULK_END>=1))*IFERROR(BULK_VALUE,0))/MAX(1,SUMPRODUCT(((BULK_ENABLED="Y")*((BULK_TIER="ALL")+(BULK_TIER=$F11))*((BULK_SKU="ALL")+(BULK_SKU=$G11))*(BULK_START<=1)*(BULK_END>=1)))),0),ROUND((INDEX(VELOCITY_TABLE,MATCH($F11,TIER_LIST,0),1))*(IF((1-$I11+1)<=0,0,IF((1-$I11+1)=1,RAMP_W1,IF((1-$I11+1)=2,RAMP_W2,IF((1-$I11+1)=3,RAMP_W3,RAMP_W4PLUS)))))*(INDEX(ACTIVE_MULT_TABLE,1,1))*(1+SUMPRODUCT(SIGN(((ACT_DOOR_SCOPE="ALL")+(ACT_DOOR_SCOPE="TIER_"&$F11)+(ACT_DOOR_SCOPE=$B11)))*SIGN(((ACT_SKU_SCOPE="ALL")+(ACT_SKU_SCOPE=$G11)))*(ACT_START<=1)*(ACT_END>=1)*IFERROR(ACT_UPLIFT-1,0)))*(1+SUMPRODUCT(SIGN(((ACT_DOOR_SCOPE="ALL")+(ACT_DOOR_SCOPE="TIER_"&$F11)+(ACT_DOOR_SCOPE=$B11)))*SIGN(((ACT_SKU_SCOPE="ALL")+(ACT_SKU_SCOPE=$G11)))*(1>ACT_END)*(ACT_END>0)*IFERROR(ACT_POSTLIFT,0))),0))) | K11: =IF(OR($H11<>"Y",2<$I11),0,IF(SUMPRODUCT(((BULK_ENABLED="Y")*((BULK_TIER="ALL")+(BULK_TIER=$F11))*((BULK_SKU="ALL")+(BULK_SKU=$G11))*(BULK_START<=2)*(BULK_END>=2)))>0,IFERROR(SUMPRODUCT(((BULK_ENABLED="Y")*((BULK_TIER="ALL")+(BULK_TIER=$F11))*((BULK_SKU="ALL")+(BULK_SKU=$G11))*(BULK_START<=2)*(BULK_END>=2))*IFERROR(BULK_VALUE,0))/MAX(1,SUMPRODUCT(((BULK_ENABLED="Y")*((BULK_TIER="ALL")+(BULK_TIER=$F11))*((BULK_SKU="ALL")+(BULK_SKU=$G11))*(BULK_START<=2)*(BULK_END>=2)))),0),ROUND((INDEX(VELOCITY_TABLE,MATCH($F11,TIER_LIST,0),1))*(IF((2-$I11+1)<=0,0,IF((2-$I11+1)=1,RAMP_W1,IF((2-$I11+1)=2,RAMP_W2,IF((2-$I11+1)=3,RAMP_W3,RAMP_W4PLUS)))))*(INDEX(ACTIVE_MULT_TABLE,1,1))*(1+SUMPRODUCT(SIGN(((ACT_DOOR_SCOPE="ALL")+(ACT_DOOR_SCOPE="TIER_"&$F11)+(ACT_DOOR_SCOPE=$B11)))*SIGN(((ACT_SKU_SCOPE="ALL")+(ACT_SKU_SCOPE=$G11)))*(ACT_START<=2)*(ACT_END>=2)*IFERROR(ACT_UPLIFT-1,0)))*(1+SUMPRODUCT(SIGN(((ACT_DOOR_SCOPE="ALL")+(ACT_DOOR_SCOPE="TIER_"&$F11)+(ACT_DOOR_SCOPE=$B11)))*SIGN(((ACT_SKU_SCOPE="ALL")+(ACT_SKU_SCOPE=$G11)))*(2>ACT_END)*(ACT_END>0)*IFERROR(ACT_POSTLIFT,0))),0))) | L11: =IF(OR($H11<>"Y",3<$I11),0,IF(SUMPRODUCT(((BULK_ENABLED="Y")*((BULK_TIER="ALL")+(BULK_TIER=$F11))*((BULK_SKU="ALL")+(BULK_SKU=$G11))*(BULK_START<=3)*(BULK_END>=3)))>0,IFERROR(SUMPRODUCT(((BULK_ENABLED="Y")*((BULK_TIER="ALL")+(BULK_TIER=$F11))*((BULK_SKU="ALL")+(BULK_SKU=$G11))*(BULK_START<=3)*(BULK_END>=3))*IFERROR(BULK_VALUE,0))/MAX(1,SUMPRODUCT(((BULK_ENABLED="Y")*((BULK_TIER="ALL")+(BULK_TIER=$F11))*((BULK_SKU="ALL")+(BULK_SKU=$G11))*(BULK_START<=3)*(BULK_END>=3)))),0),ROUND((INDEX(VELOCITY_TABLE,MATCH($F11,TIER_LIST,0),1))*(IF((3-$I11+1)<=0,0,IF((3-$I11+1)=1,RAMP_W1,IF((3-$I11+1)=2,RAMP_W2,IF((3-$I11+1)=3,RAMP_W3,RAMP_W4PLUS)))))*(INDEX(ACTIVE_MULT_TABLE,1,1))*(1+SUMPRODUCT(SIGN(((ACT_DOOR_SCOPE="ALL")+(ACT_DOOR_SCOPE="TIER_"&$F11)+(ACT_DOOR_SCOPE=$B11)))*SIGN(((ACT_SKU_SCOPE="ALL")+(ACT_SKU_SCOPE=$G11)))*(ACT_START<=3)*(ACT_END>=3)*IFERROR(ACT_UPLIFT-1,0)))*(1+SUMPRODUCT(SIGN(((ACT_DOOR_SCOPE="ALL")+(ACT_DOOR_SCOPE="TIER_"&$F11)+(ACT_DOOR_SCOPE=$B11)))*SIGN(((ACT_SKU_SCOPE="ALL")+(ACT_SKU_SCOPE=$G11)))*(3>ACT_END)*(ACT_END>0)*IFERROR(ACT_POSTLIFT,0))),0))) | M11: =IF(OR($H11<>"Y",4<$I11),0,IF(SUMPRODUCT(((BULK_ENABLED="Y")*((BULK_TIER="ALL")+(BULK_TIER=$F11))*((BULK_SKU="ALL")+(BULK_SKU=$G11))*(BULK_START<=4)*(BULK_END>=4)))>0,IFERROR(SUMPRODUCT(((BULK_ENABLED="Y")*((BULK_TIER="ALL")+(BULK_TIER=$F11))*((BULK_SKU="ALL")+(BULK_SKU=$G11))*(BULK_START<=4)*(BULK_END>=4))*IFERROR(BULK_VALUE,0))/MAX(1,SUMPRODUCT(((BULK_ENABLED="Y")*((BULK_TIER="ALL")+(BULK_TIER=$F11))*((BULK_SKU="ALL")+(BULK_SKU=$G11))*(BULK_START<=4)*(BULK_END>=4)))),0),ROUND((INDEX(VELOCITY_TABLE,MATCH($F11,TIER_LIST,0),1))*(IF((4-$I11+1)<=0,0,IF((4-$I11+1)=1,RAMP_W1,IF((4-$I11+1)=2,RAMP_W2,IF((4-$I11+1)=3,RAMP_W3,RAMP_W4PLUS)))))*(INDEX(ACTIVE_MULT_TABLE,1,1))*(1+SUMPRODUCT(SIGN(((ACT_DOOR_SCOPE="ALL")+(ACT_DOOR_SCOPE="TIER_"&$F11)+(ACT_DOOR_SCOPE=$B11)))*SIGN(((ACT_SKU_SCOPE="ALL")+(ACT_SKU_SCOPE=$G11)))*(ACT_START<=4)*(ACT_END>=4)*IFERROR(ACT_UPLIFT-1,0)))*(1+SUMPRODUCT(SIGN(((ACT_DOOR_SCOPE="ALL")+(ACT_DOOR_SCOPE="TIER_"&$F11)+(ACT_DOOR_SCOPE=$B11)))*SIGN(((ACT_SKU_SCOPE="ALL")+(ACT_SKU_SCOPE=$G11)))*(4>ACT_END)*(ACT_END>0)*IFERROR(ACT_POSTLIFT,0))),0))) | N11: =IF(OR($H11<>"Y",5<$I11),0,IF(SUMPRODUCT(((BULK_ENABLED="Y")*((BULK_TIER="ALL")+(BULK_TIER=$F11))*((BULK_SKU="ALL")+(BULK_SKU=$G11))*(BULK_START<=5)*(BULK_END>=5)))>0,IFERROR(SUMPRODUCT(((BULK_ENABLED="Y")*((BULK_TIER="ALL")+(BULK_TIER=$F11))*((BULK_SKU="ALL")+(BULK_SKU=$G11))*(BULK_START<=5)*(BULK_END>=5))*IFERROR(BULK_VALUE,0))/MAX(1,SUMPRODUCT(((BULK_ENABLED="Y")*((BULK_TIER="ALL")+(BULK_TIER=$F11))*((BULK_SKU="ALL")+(BULK_SKU=$G11))*(BULK_START<=5)*(BULK_END>=5)))),0),ROUND((INDEX(VELOCITY_TABLE,MATCH($F11,TIER_LIST,0),1))*(IF((5-$I11+1)<=0,0,IF((5-$I11+1)=1,RAMP_W1,IF((5-$I11+1)=2,RAMP_W2,IF((5-$I11+1)=3,RAMP_W3,RAMP_W4PLUS)))))*(INDEX(ACTIVE_MULT_TABLE,1,1))*(1+SUMPRODUCT(SIGN(((ACT_DOOR_SCOPE="ALL")+(ACT_DOOR_SCOPE="TIER_"&$F11)+(ACT_DOOR_SCOPE=$B11)))*SIGN(((ACT_SKU_SCOPE="ALL")+(ACT_SKU_SCOPE=$G11)))*(ACT_START<=5)*(ACT_END>=5)*IFERROR(ACT_UPLIFT-1,0)))*(1+SUMPRODUCT(SIGN(((ACT_DOOR_SCOPE="ALL")+(ACT_DOOR_SCOPE="TIER_"&$F11)+(ACT_DOOR_SCOPE=$B11)))*SIGN(((ACT_SKU_SCOPE="ALL")+(ACT_SKU_SCOPE=$G11)))*(5>ACT_END)*(ACT_END>0)*IFERROR(ACT_POSTLIFT,0))),0))) | O11: =IF(OR($H11<>"Y",6<$I11),0,IF(SUMPRODUCT(((BULK_ENABLED="Y")*((BULK_TIER="ALL")+(BULK_TIER=$F11))*((BULK_SKU="ALL")+(BULK_SKU=$G11))*(BULK_START<=6)*(BULK_END>=6)))>0,IFERROR(SUMPRODUCT(((BULK_ENABLED="Y")*((BULK_TIER="ALL")+(BULK_TIER=$F11))*((BULK_SKU="ALL")+(BULK_SKU=$G11))*(BULK_START<=6)*(BULK_END>=6))*IFERROR(BULK_VALUE,0))/MAX(1,SUMPRODUCT(((BULK_ENABLED="Y")*((BULK_TIER="ALL")+(BULK_TIER=$F11))*((BULK_SKU="ALL")+(BULK_SKU=$G11))*(BULK_START<=6)*(BULK_END>=6)))),0),ROUND((INDEX(VELOCITY_TABLE,MATCH($F11,TIER_LIST,0),1))*(IF((6-$I11+1)<=0,0,IF((6-$I11+1)=1,RAMP_W1,IF((6-$I11+1)=2,RAMP_W2,IF((6-$I11+1)=3,RAMP_W3,RAMP_W4PLUS)))))*(INDEX(ACTIVE_MULT_TABLE,1,1))*(1+SUMPRODUCT(SIGN(((ACT_DOOR_SCOPE="ALL")+(ACT_DOOR_SCOPE="TIER_"&$F11)+(ACT_DOOR_SCOPE=$B11)))*SIGN(((ACT_SKU_SCOPE="ALL")+(ACT_SKU_SCOPE=$G11)))*(ACT_START<=6)*(ACT_END>=6)*IFERROR(ACT_UPLIFT-1,0)))*(1+SUMPRODUCT(SIGN(((ACT_DOOR_SCOPE="ALL")+(ACT_DOOR_SCOPE="TIER_"&$F11)+(ACT_DOOR_SCOPE=$B11)))*SIGN(((ACT_SKU_SCOPE="ALL")+(ACT_SKU_SCOPE=$G11)))*(6>ACT_END)*(ACT_END>0)*IFERROR(ACT_POSTLIFT,0))),0))) | P11: =IF(OR($H11<>"Y",7<$I11),0,IF(SUMPRODUCT(((BULK_ENABLED="Y")*((BULK_TIER="ALL")+(BULK_TIER=$F11))*((BULK_SKU="ALL")+(BULK_SKU=$G11))*(BULK_START<=7)*(BULK_END>=7)))>0,IFERROR(SUMPRODUCT(((BULK_ENABLED="Y")*((BULK_TIER="ALL")+(BULK_TIER=$F11))*((BULK_SKU="ALL")+(BULK_SKU=$G11))*(BULK_START<=7)*(BULK_END>=7))*IFERROR(BULK_VALUE,0))/MAX(1,SUMPRODUCT(((BULK_ENABLED="Y")*((BULK_TIER="ALL")+(BULK_TIER=$F11))*((BULK_SKU="ALL")+(BULK_SKU=$G11))*(BULK_START<=7)*(BULK_END>=7)))),0),ROUND((INDEX(VELOCITY_TABLE,MATCH($F11,TIER_LIST,0),1))*(IF((7-$I11+1)<=0,0,IF((7-$I11+1)=1,RAMP_W1,IF((7-$I11+1)=2,RAMP_W2,IF((7-$I11+1)=3,RAMP_W3,RAMP_W4PLUS)))))*(INDEX(ACTIVE_MULT_TABLE,1,1))*(1+SUMPRODUCT(SIGN(((ACT_DOOR_SCOPE="ALL")+(ACT_DOOR_SCOPE="TIER_"&$F11)+(ACT_DOOR_SCOPE=$B11)))*SIGN(((ACT_SKU_SCOPE="ALL")+(ACT_SKU_SCOPE=$G11)))*(ACT_START<=7)*(ACT_END>=7)*IFERROR(ACT_UPLIFT-1,0)))*(1+SUMPRODUCT(SIGN(((ACT_DOOR_SCOPE="ALL")+(ACT_DOOR_SCOPE="TIER_"&$F11)+(ACT_DOOR_SCOPE=$B11)))*SIGN(((ACT_SKU_SCOPE="ALL")+(ACT_SKU_SCOPE=$G11)))*(7>ACT_END)*(ACT_END>0)*IFERROR(ACT_POSTLIFT,0))),0))) | Q11: =IF(OR($H11<>"Y",8<$I11),0,IF(SUMPRODUCT(((BULK_ENABLED="Y")*((BULK_TIER="ALL")+(BULK_TIER=$F11))*((BULK_SKU="ALL")+(BULK_SKU=$G11))*(BULK_START<=8)*(BULK_END>=8)))>0,IFERROR(SUMPRODUCT(((BULK_ENABLED="Y")*((BULK_TIER="ALL")+(BULK_TIER=$F11))*((BULK_SKU="ALL")+(BULK_SKU=$G11))*(BULK_START<=8)*(BULK_END>=8))*IFERROR(BULK_VALUE,0))/MAX(1,SUMPRODUCT(((BULK_ENABLED="Y")*((BULK_TIER="ALL")+(BULK_TIER=$F11))*((BULK_SKU="ALL")+(BULK_SKU=$G11))*(BULK_START<=8)*(BULK_END>=8)))),0),ROUND((INDEX(VELOCITY_TABLE,MATCH($F11,TIER_LIST,0),1))*(IF((8-$I11+1)<=0,0,IF((8-$I11+1)=1,RAMP_W1,IF((8-$I11+1)=2,RAMP_W2,IF((8-$I11+1)=3,RAMP_W3,RAMP_W4PLUS)))))*(INDEX(ACTIVE_MULT_TABLE,1,1))*(1+SUMPRODUCT(SIGN(((ACT_DOOR_SCOPE="ALL")+(ACT_DOOR_SCOPE="TIER_"&$F11)+(ACT_DOOR_SCOPE=$B11)))*SIGN(((ACT_SKU_SCOPE="ALL")+(ACT_SKU_SCOPE=$G11)))*(ACT_START<=8)*(ACT_END>=8)*IFERROR(ACT_UPLIFT-1,0)))*(1+SUMPRODUCT(SIGN(((ACT_DOOR_SCOPE="ALL")+(ACT_DOOR_SCOPE="TIER_"&$F11)+(ACT_DOOR_SCOPE=$B11)))*SIGN(((ACT_SKU_SCOPE="ALL")+(ACT_SKU_SCOPE=$G11)))*(8>ACT_END)*(ACT_END>0)*IFERROR(ACT_POSTLIFT,0))),0))) | R11: =IF(OR($H11<>"Y",9<$I11),0,IF(SUMPRODUCT(((BULK_ENABLED="Y")*((BULK_TIER="ALL")+(BULK_TIER=$F11))*((BULK_SKU="ALL")+(BULK_SKU=$G11))*(BULK_START<=9)*(BULK_END>=9)))>0,IFERROR(SUMPRODUCT(((BULK_ENABLED="Y")*((BULK_TIER="ALL")+(BULK_TIER=$F11))*((BULK_SKU="ALL")+(BULK_SKU=$G11))*(BULK_START<=9)*(BULK_END>=9))*IFERROR(BULK_VALUE,0))/MAX(1,SUMPRODUCT(((BULK_ENABLED="Y")*((BULK_TIER="ALL")+(BULK_TIER=$F11))*((BULK_SKU="ALL")+(BULK_SKU=$G11))*(BULK_START<=9)*(BULK_END>=9)))),0),ROUND((INDEX(VELOCITY_TABLE,MATCH($F11,TIER_LIST,0),1))*(IF((9-$I11+1)<=0,0,IF((9-$I11+1)=1,RAMP_W1,IF((9-$I11+1)=2,RAMP_W2,IF((9-$I11+1)=3,RAMP_W3,RAMP_W4PLUS)))))*(INDEX(ACTIVE_MULT_TABLE,1,1))*(1+SUMPRODUCT(SIGN(((ACT_DOOR_SCOPE="ALL")+(ACT_DOOR_SCOPE="TIER_"&$F11)+(ACT_DOOR_SCOPE=$B11)))*SIGN(((ACT_SKU_SCOPE="ALL")+(ACT_SKU_SCOPE=$G11)))*(ACT_START<=9)*(ACT_END>=9)*IFERROR(ACT_UPLIFT-1,0)))*(1+SUMPRODUCT(SIGN(((ACT_DOOR_SCOPE="ALL")+(ACT_DOOR_SCOPE="TIER_"&$F11)+(ACT_DOOR_SCOPE=$B11)))*SIGN(((ACT_SKU_SCOPE="ALL")+(ACT_SKU_SCOPE=$G11)))*(9>ACT_END)*(ACT_END>0)*IFERROR(ACT_POSTLIFT,0))),0))) | S11: =IF(OR($H11<>"Y",10<$I11),0,IF(SUMPRODUCT(((BULK_ENABLED="Y")*((BULK_TIER="ALL")+(BULK_TIER=$F11))*((BULK_SKU="ALL")+(BULK_SKU=$G11))*(BULK_START<=10)*(BULK_END>=10)))>0,IFERROR(SUMPRODUCT(((BULK_ENABLED="Y")*((BULK_TIER="ALL")+(BULK_TIER=$F11))*((BULK_SKU="ALL")+(BULK_SKU=$G11))*(BULK_START<=10)*(BULK_END>=10))*IFERROR(BULK_VALUE,0))/MAX(1,SUMPRODUCT(((BULK_ENABLED="Y")*((BULK_TIER="ALL")+(BULK_TIER=$F11))*((BULK_SKU="ALL")+(BULK_SKU=$G11))*(BULK_START<=10)*(BULK_END>=10)))),0),ROUND((INDEX(VELOCITY_TABLE,MATCH($F11,TIER_LIST,0),1))*(IF((10-$I11+1)<=0,0,IF((10-$I11+1)=1,RAMP_W1,IF((10-$I11+1)=2,RAMP_W2,IF((10-$I11+1)=3,RAMP_W3,RAMP_W4PLUS)))))*(INDEX(ACTIVE_MULT_TABLE,1,1))*(1+SUMPRODUCT(SIGN(((ACT_DOOR_SCOPE="ALL")+(ACT_DOOR_SCOPE="TIER_"&$F11)+(ACT_DOOR_SCOPE=$B11)))*SIGN(((ACT_SKU_SCOPE="ALL")+(ACT_SKU_SCOPE=$G11)))*(ACT_START<=10)*(ACT_END>=10)*IFERROR(ACT_UPLIFT-1,0)))*(1+SUMPRODUCT(SIGN(((ACT_DOOR_SCOPE="ALL")+(ACT_DOOR_SCOPE="TIER_"&$F11)+(ACT_DOOR_SCOPE=$B11)))*SIGN(((ACT_SKU_SCOPE="ALL")+(ACT_SKU_SCOPE=$G11)))*(10>ACT_END)*(ACT_END>0)*IFERROR(ACT_POSTLIFT,0))),0))) | T11: =IF(OR($H11<>"Y",11<$I11),0,IF(SUMPRODUCT(((BULK_ENABLED="Y")*((BULK_TIER="ALL")+(BULK_TIER=$F11))*((BULK_SKU="ALL")+(BULK_SKU=$G11))*(BULK_START<=11)*(BULK_END>=11)))>0,IFERROR(SUMPRODUCT(((BULK_ENABLED="Y")*((BULK_TIER="ALL")+(BULK_TIER=$F11))*((BULK_SKU="ALL")+(BULK_SKU=$G11))*(BULK_START<=11)*(BULK_END>=11))*IFERROR(BULK_VALUE,0))/MAX(1,SUMPRODUCT(((BULK_ENABLED="Y")*((BULK_TIER="ALL")+(BULK_TIER=$F11))*((BULK_SKU="ALL")+(BULK_SKU=$G11))*(BULK_START<=11)*(BULK_END>=11)))),0),ROUND((INDEX(VELOCITY_TABLE,MATCH($F11,TIER_LIST,0),1))*(IF((11-$I11+1)<=0,0,IF((11-$I11+1)=1,RAMP_W1,IF((11-$I11+1)=2,RAMP_W2,IF((11-$I11+1)=3,RAMP_W3,RAMP_W4PLUS)))))*(INDEX(ACTIVE_MULT_TABLE,1,1))*(1+SUMPRODUCT(SIGN(((ACT_DOOR_SCOPE="ALL")+(ACT_DOOR_SCOPE="TIER_"&$F11)+(ACT_DOOR_SCOPE=$B11)))*SIGN(((ACT_SKU_SCOPE="ALL")+(ACT_SKU_SCOPE=$G11)))*(ACT_START<=11)*(ACT_END>=11)*IFERROR(ACT_UPLIFT-1,0)))*(1+SUMPRODUCT(SIGN(((ACT_DOOR_SCOPE="ALL")+(ACT_DOOR_SCOPE="TIER_"&$F11)+(ACT_DOOR_SCOPE=$B11)))*SIGN(((ACT_SKU_SCOPE="ALL")+(ACT_SKU_SCOPE=$G11)))*(11>ACT_END)*(ACT_END>0)*IFERROR(ACT_POSTLIFT,0))),0))) | U11: =IF(OR($H11<>"Y",12<$I11),0,IF(SUMPRODUCT(((BULK_ENABLED="Y")*((BULK_TIER="ALL")+(BULK_TIER=$F11))*((BULK_SKU="ALL")+(BULK_SKU=$G11))*(BULK_START<=12)*(BULK_END>=12)))>0,IFERROR(SUMPRODUCT(((BULK_ENABLED="Y")*((BULK_TIER="ALL")+(BULK_TIER=$F11))*((BULK_SKU="ALL")+(BULK_SKU=$G11))*(BULK_START<=12)*(BULK_END>=12))*IFERROR(BULK_VALUE,0))/MAX(1,SUMPRODUCT(((BULK_ENABLED="Y")*((BULK_TIER="ALL")+(BULK_TIER=$F11))*((BULK_SKU="ALL")+(BULK_SKU=$G11))*(BULK_START<=12)*(BULK_END>=12)))),0),ROUND((INDEX(VELOCITY_TABLE,MATCH($F11,TIER_LIST,0),1))*(IF((12-$I11+1)<=0,0,IF((12-$I11+1)=1,RAMP_W1,IF((12-$I11+1)=2,RAMP_W2,IF((12-$I11+1)=3,RAMP_W3,RAMP_W4PLUS)))))*(INDEX(ACTIVE_MULT_TABLE,1,1))*(1+SUMPRODUCT(SIGN(((ACT_DOOR_SCOPE="ALL")+(ACT_DOOR_SCOPE="TIER_"&$F11)+(ACT_DOOR_SCOPE=$B11)))*SIGN(((ACT_SKU_SCOPE="ALL")+(ACT_SKU_SCOPE=$G11)))*(ACT_START<=12)*(ACT_END>=12)*IFERROR(ACT_UPLIFT-1,0)))*(1+SUMPRODUCT(SIGN(((ACT_DOOR_SCOPE="ALL")+(ACT_DOOR_SCOPE="TIER_"&$F11)+(ACT_DOOR_SCOPE=$B11)))*SIGN(((ACT_SKU_SCOPE="ALL")+(ACT_SKU_SCOPE=$G11)))*(12>ACT_END)*(ACT_END>0)*IFERROR(ACT_POSTLIFT,0))),0))) | V11: =IF(OR($H11<>"Y",13<$I11),0,IF(SUMPRODUCT(((BULK_ENABLED="Y")*((BULK_TIER="ALL")+(BULK_TIER=$F11))*((BULK_SKU="ALL")+(BULK_SKU=$G11))*(BULK_START<=13)*(BULK_END>=13)))>0,IFERROR(SUMPRODUCT(((BULK_ENABLED="Y")*((BULK_TIER="ALL")+(BULK_TIER=$F11))*((BULK_SKU="ALL")+(BULK_SKU=$G11))*(BULK_START<=13)*(BULK_END>=13))*IFERROR(BULK_VALUE,0))/MAX(1,SUMPRODUCT(((BULK_ENABLED="Y")*((BULK_TIER="ALL")+(BULK_TIER=$F11))*((BULK_SKU="ALL")+(BULK_SKU=$G11))*(BULK_START<=13)*(BULK_END>=13)))),0),ROUND((INDEX(VELOCITY_TABLE,MATCH($F11,TIER_LIST,0),1))*(IF((13-$I11+1)<=0,0,IF((13-$I11+1)=1,RAMP_W1,IF((13-$I11+1)=2,RAMP_W2,IF((13-$I11+1)=3,RAMP_W3,RAMP_W4PLUS)))))*(INDEX(ACTIVE_MULT_TABLE,1,1))*(1+SUMPRODUCT(SIGN(((ACT_DOOR_SCOPE="ALL")+(ACT_DOOR_SCOPE="TIER_"&$F11)+(ACT_DOOR_SCOPE=$B11)))*SIGN(((ACT_SKU_SCOPE="ALL")+(ACT_SKU_SCOPE=$G11)))*(ACT_START<=13)*(ACT_END>=13)*IFERROR(ACT_UPLIFT-1,0)))*(1+SUMPRODUCT(SIGN(((ACT_DOOR_SCOPE="ALL")+(ACT_DOOR_SCOPE="TIER_"&$F11)+(ACT_DOOR_SCOPE=$B11)))*SIGN(((ACT_SKU_SCOPE="ALL")+(ACT_SKU_SCOPE=$G11)))*(13>ACT_END)*(ACT_END>0)*IFERROR(ACT_POSTLIFT,0))),0)))
A12: R0008 | B12: =Doors!$A$7 | C12: =Doors!$C$7 | D12: =Doors!$B$7 | E12: =Doors!$E$7 | F12: =Doors!$F$7 | G12: Pineapple Passion Fruit | H12: =Doors!$H$7 | I12: =Doors!$J$7 | J12: =IF(OR($H12<>"Y",1<$I12),0,IF(SUMPRODUCT(((BULK_ENABLED="Y")*((BULK_TIER="ALL")+(BULK_TIER=$F12))*((BULK_SKU="ALL")+(BULK_SKU=$G12))*(BULK_START<=1)*(BULK_END>=1)))>0,IFERROR(SUMPRODUCT(((BULK_ENABLED="Y")*((BULK_TIER="ALL")+(BULK_TIER=$F12))*((BULK_SKU="ALL")+(BULK_SKU=$G12))*(BULK_START<=1)*(BULK_END>=1))*IFERROR(BULK_VALUE,0))/MAX(1,SUMPRODUCT(((BULK_ENABLED="Y")*((BULK_TIER="ALL")+(BULK_TIER=$F12))*((BULK_SKU="ALL")+(BULK_SKU=$G12))*(BULK_START<=1)*(BULK_END>=1)))),0),ROUND((INDEX(VELOCITY_TABLE,MATCH($F12,TIER_LIST,0),2))*(IF((1-$I12+1)<=0,0,IF((1-$I12+1)=1,RAMP_W1,IF((1-$I12+1)=2,RAMP_W2,IF((1-$I12+1)=3,RAMP_W3,RAMP_W4PLUS)))))*(INDEX(ACTIVE_MULT_TABLE,2,1))*(1+SUMPRODUCT(SIGN(((ACT_DOOR_SCOPE="ALL")+(ACT_DOOR_SCOPE="TIER_"&$F12)+(ACT_DOOR_SCOPE=$B12)))*SIGN(((ACT_SKU_SCOPE="ALL")+(ACT_SKU_SCOPE=$G12)))*(ACT_START<=1)*(ACT_END>=1)*IFERROR(ACT_UPLIFT-1,0)))*(1+SUMPRODUCT(SIGN(((ACT_DOOR_SCOPE="ALL")+(ACT_DOOR_SCOPE="TIER_"&$F12)+(ACT_DOOR_SCOPE=$B12)))*SIGN(((ACT_SKU_SCOPE="ALL")+(ACT_SKU_SCOPE=$G12)))*(1>ACT_END)*(ACT_END>0)*IFERROR(ACT_POSTLIFT,0))),0))) | K12: =IF(OR($H12<>"Y",2<$I12),0,IF(SUMPRODUCT(((BULK_ENABLED="Y")*((BULK_TIER="ALL")+(BULK_TIER=$F12))*((BULK_SKU="ALL")+(BULK_SKU=$G12))*(BULK_START<=2)*(BULK_END>=2)))>0,IFERROR(SUMPRODUCT(((BULK_ENABLED="Y")*((BULK_TIER="ALL")+(BULK_TIER=$F12))*((BULK_SKU="ALL")+(BULK_SKU=$G12))*(BULK_START<=2)*(BULK_END>=2))*IFERROR(BULK_VALUE,0))/MAX(1,SUMPRODUCT(((BULK_ENABLED="Y")*((BULK_TIER="ALL")+(BULK_TIER=$F12))*((BULK_SKU="ALL")+(BULK_SKU=$G12))*(BULK_START<=2)*(BULK_END>=2)))),0),ROUND((INDEX(VELOCITY_TABLE,MATCH($F12,TIER_LIST,0),2))*(IF((2-$I12+1)<=0,0,IF((2-$I12+1)=1,RAMP_W1,IF((2-$I12+1)=2,RAMP_W2,IF((2-$I12+1)=3,RAMP_W3,RAMP_W4PLUS)))))*(INDEX(ACTIVE_MULT_TABLE,2,1))*(1+SUMPRODUCT(SIGN(((ACT_DOOR_SCOPE="ALL")+(ACT_DOOR_SCOPE="TIER_"&$F12)+(ACT_DOOR_SCOPE=$B12)))*SIGN(((ACT_SKU_SCOPE="ALL")+(ACT_SKU_SCOPE=$G12)))*(ACT_START<=2)*(ACT_END>=2)*IFERROR(ACT_UPLIFT-1,0)))*(1+SUMPRODUCT(SIGN(((ACT_DOOR_SCOPE="ALL")+(ACT_DOOR_SCOPE="TIER_"&$F12)+(ACT_DOOR_SCOPE=$B12)))*SIGN(((ACT_SKU_SCOPE="ALL")+(ACT_SKU_SCOPE=$G12)))*(2>ACT_END)*(ACT_END>0)*IFERROR(ACT_POSTLIFT,0))),0))) | L12: =IF(OR($H12<>"Y",3<$I12),0,IF(SUMPRODUCT(((BULK_ENABLED="Y")*((BULK_TIER="ALL")+(BULK_TIER=$F12))*((BULK_SKU="ALL")+(BULK_SKU=$G12))*(BULK_START<=3)*(BULK_END>=3)))>0,IFERROR(SUMPRODUCT(((BULK_ENABLED="Y")*((BULK_TIER="ALL")+(BULK_TIER=$F12))*((BULK_SKU="ALL")+(BULK_SKU=$G12))*(BULK_START<=3)*(BULK_END>=3))*IFERROR(BULK_VALUE,0))/MAX(1,SUMPRODUCT(((BULK_ENABLED="Y")*((BULK_TIER="ALL")+(BULK_TIER=$F12))*((BULK_SKU="ALL")+(BULK_SKU=$G12))*(BULK_START<=3)*(BULK_END>=3)))),0),ROUND((INDEX(VELOCITY_TABLE,MATCH($F12,TIER_LIST,0),2))*(IF((3-$I12+1)<=0,0,IF((3-$I12+1)=1,RAMP_W1,IF((3-$I12+1)=2,RAMP_W2,IF((3-$I12+1)=3,RAMP_W3,RAMP_W4PLUS)))))*(INDEX(ACTIVE_MULT_TABLE,2,1))*(1+SUMPRODUCT(SIGN(((ACT_DOOR_SCOPE="ALL")+(ACT_DOOR_SCOPE="TIER_"&$F12)+(ACT_DOOR_SCOPE=$B12)))*SIGN(((ACT_SKU_SCOPE="ALL")+(ACT_SKU_SCOPE=$G12)))*(ACT_START<=3)*(ACT_END>=3)*IFERROR(ACT_UPLIFT-1,0)))*(1+SUMPRODUCT(SIGN(((ACT_DOOR_SCOPE="ALL")+(ACT_DOOR_SCOPE="TIER_"&$F12)+(ACT_DOOR_SCOPE=$B12)))*SIGN(((ACT_SKU_SCOPE="ALL")+(ACT_SKU_SCOPE=$G12)))*(3>ACT_END)*(ACT_END>0)*IFERROR(ACT_POSTLIFT,0))),0))) | M12: =IF(OR($H12<>"Y",4<$I12),0,IF(SUMPRODUCT(((BULK_ENABLED="Y")*((BULK_TIER="ALL")+(BULK_TIER=$F12))*((BULK_SKU="ALL")+(BULK_SKU=$G12))*(BULK_START<=4)*(BULK_END>=4)))>0,IFERROR(SUMPRODUCT(((BULK_ENABLED="Y")*((BULK_TIER="ALL")+(BULK_TIER=$F12))*((BULK_SKU="ALL")+(BULK_SKU=$G12))*(BULK_START<=4)*(BULK_END>=4))*IFERROR(BULK_VALUE,0))/MAX(1,SUMPRODUCT(((BULK_ENABLED="Y")*((BULK_TIER="ALL")+(BULK_TIER=$F12))*((BULK_SKU="ALL")+(BULK_SKU=$G12))*(BULK_START<=4)*(BULK_END>=4)))),0),ROUND((INDEX(VELOCITY_TABLE,MATCH($F12,TIER_LIST,0),2))*(IF((4-$I12+1)<=0,0,IF((4-$I12+1)=1,RAMP_W1,IF((4-$I12+1)=2,RAMP_W2,IF((4-$I12+1)=3,RAMP_W3,RAMP_W4PLUS)))))*(INDEX(ACTIVE_MULT_TABLE,2,1))*(1+SUMPRODUCT(SIGN(((ACT_DOOR_SCOPE="ALL")+(ACT_DOOR_SCOPE="TIER_"&$F12)+(ACT_DOOR_SCOPE=$B12)))*SIGN(((ACT_SKU_SCOPE="ALL")+(ACT_SKU_SCOPE=$G12)))*(ACT_START<=4)*(ACT_END>=4)*IFERROR(ACT_UPLIFT-1,0)))*(1+SUMPRODUCT(SIGN(((ACT_DOOR_SCOPE="ALL")+(ACT_DOOR_SCOPE="TIER_"&$F12)+(ACT_DOOR_SCOPE=$B12)))*SIGN(((ACT_SKU_SCOPE="ALL")+(ACT_SKU_SCOPE=$G12)))*(4>ACT_END)*(ACT_END>0)*IFERROR(ACT_POSTLIFT,0))),0))) | N12: =IF(OR($H12<>"Y",5<$I12),0,IF(SUMPRODUCT(((BULK_ENABLED="Y")*((BULK_TIER="ALL")+(BULK_TIER=$F12))*((BULK_SKU="ALL")+(BULK_SKU=$G12))*(BULK_START<=5)*(BULK_END>=5)))>0,IFERROR(SUMPRODUCT(((BULK_ENABLED="Y")*((BULK_TIER="ALL")+(BULK_TIER=$F12))*((BULK_SKU="ALL")+(BULK_SKU=$G12))*(BULK_START<=5)*(BULK_END>=5))*IFERROR(BULK_VALUE,0))/MAX(1,SUMPRODUCT(((BULK_ENABLED="Y")*((BULK_TIER="ALL")+(BULK_TIER=$F12))*((BULK_SKU="ALL")+(BULK_SKU=$G12))*(BULK_START<=5)*(BULK_END>=5)))),0),ROUND((INDEX(VELOCITY_TABLE,MATCH($F12,TIER_LIST,0),2))*(IF((5-$I12+1)<=0,0,IF((5-$I12+1)=1,RAMP_W1,IF((5-$I12+1)=2,RAMP_W2,IF((5-$I12+1)=3,RAMP_W3,RAMP_W4PLUS)))))*(INDEX(ACTIVE_MULT_TABLE,2,1))*(1+SUMPRODUCT(SIGN(((ACT_DOOR_SCOPE="ALL")+(ACT_DOOR_SCOPE="TIER_"&$F12)+(ACT_DOOR_SCOPE=$B12)))*SIGN(((ACT_SKU_SCOPE="ALL")+(ACT_SKU_SCOPE=$G12)))*(ACT_START<=5)*(ACT_END>=5)*IFERROR(ACT_UPLIFT-1,0)))*(1+SUMPRODUCT(SIGN(((ACT_DOOR_SCOPE="ALL")+(ACT_DOOR_SCOPE="TIER_"&$F12)+(ACT_DOOR_SCOPE=$B12)))*SIGN(((ACT_SKU_SCOPE="ALL")+(ACT_SKU_SCOPE=$G12)))*(5>ACT_END)*(ACT_END>0)*IFERROR(ACT_POSTLIFT,0))),0))) | O12: =IF(OR($H12<>"Y",6<$I12),0,IF(SUMPRODUCT(((BULK_ENABLED="Y")*((BULK_TIER="ALL")+(BULK_TIER=$F12))*((BULK_SKU="ALL")+(BULK_SKU=$G12))*(BULK_START<=6)*(BULK_END>=6)))>0,IFERROR(SUMPRODUCT(((BULK_ENABLED="Y")*((BULK_TIER="ALL")+(BULK_TIER=$F12))*((BULK_SKU="ALL")+(BULK_SKU=$G12))*(BULK_START<=6)*(BULK_END>=6))*IFERROR(BULK_VALUE,0))/MAX(1,SUMPRODUCT(((BULK_ENABLED="Y")*((BULK_TIER="ALL")+(BULK_TIER=$F12))*((BULK_SKU="ALL")+(BULK_SKU=$G12))*(BULK_START<=6)*(BULK_END>=6)))),0),ROUND((INDEX(VELOCITY_TABLE,MATCH($F12,TIER_LIST,0),2))*(IF((6-$I12+1)<=0,0,IF((6-$I12+1)=1,RAMP_W1,IF((6-$I12+1)=2,RAMP_W2,IF((6-$I12+1)=3,RAMP_W3,RAMP_W4PLUS)))))*(INDEX(ACTIVE_MULT_TABLE,2,1))*(1+SUMPRODUCT(SIGN(((ACT_DOOR_SCOPE="ALL")+(ACT_DOOR_SCOPE="TIER_"&$F12)+(ACT_DOOR_SCOPE=$B12)))*SIGN(((ACT_SKU_SCOPE="ALL")+(ACT_SKU_SCOPE=$G12)))*(ACT_START<=6)*(ACT_END>=6)*IFERROR(ACT_UPLIFT-1,0)))*(1+SUMPRODUCT(SIGN(((ACT_DOOR_SCOPE="ALL")+(ACT_DOOR_SCOPE="TIER_"&$F12)+(ACT_DOOR_SCOPE=$B12)))*SIGN(((ACT_SKU_SCOPE="ALL")+(ACT_SKU_SCOPE=$G12)))*(6>ACT_END)*(ACT_END>0)*IFERROR(ACT_POSTLIFT,0))),0))) | P12: =IF(OR($H12<>"Y",7<$I12),0,IF(SUMPRODUCT(((BULK_ENABLED="Y")*((BULK_TIER="ALL")+(BULK_TIER=$F12))*((BULK_SKU="ALL")+(BULK_SKU=$G12))*(BULK_START<=7)*(BULK_END>=7)))>0,IFERROR(SUMPRODUCT(((BULK_ENABLED="Y")*((BULK_TIER="ALL")+(BULK_TIER=$F12))*((BULK_SKU="ALL")+(BULK_SKU=$G12))*(BULK_START<=7)*(BULK_END>=7))*IFERROR(BULK_VALUE,0))/MAX(1,SUMPRODUCT(((BULK_ENABLED="Y")*((BULK_TIER="ALL")+(BULK_TIER=$F12))*((BULK_SKU="ALL")+(BULK_SKU=$G12))*(BULK_START<=7)*(BULK_END>=7)))),0),ROUND((INDEX(VELOCITY_TABLE,MATCH($F12,TIER_LIST,0),2))*(IF((7-$I12+1)<=0,0,IF((7-$I12+1)=1,RAMP_W1,IF((7-$I12+1)=2,RAMP_W2,IF((7-$I12+1)=3,RAMP_W3,RAMP_W4PLUS)))))*(INDEX(ACTIVE_MULT_TABLE,2,1))*(1+SUMPRODUCT(SIGN(((ACT_DOOR_SCOPE="ALL")+(ACT_DOOR_SCOPE="TIER_"&$F12)+(ACT_DOOR_SCOPE=$B12)))*SIGN(((ACT_SKU_SCOPE="ALL")+(ACT_SKU_SCOPE=$G12)))*(ACT_START<=7)*(ACT_END>=7)*IFERROR(ACT_UPLIFT-1,0)))*(1+SUMPRODUCT(SIGN(((ACT_DOOR_SCOPE="ALL")+(ACT_DOOR_SCOPE="TIER_"&$F12)+(ACT_DOOR_SCOPE=$B12)))*SIGN(((ACT_SKU_SCOPE="ALL")+(ACT_SKU_SCOPE=$G12)))*(7>ACT_END)*(ACT_END>0)*IFERROR(ACT_POSTLIFT,0))),0))) | Q12: =IF(OR($H12<>"Y",8<$I12),0,IF(SUMPRODUCT(((BULK_ENABLED="Y")*((BULK_TIER="ALL")+(BULK_TIER=$F12))*((BULK_SKU="ALL")+(BULK_SKU=$G12))*(BULK_START<=8)*(BULK_END>=8)))>0,IFERROR(SUMPRODUCT(((BULK_ENABLED="Y")*((BULK_TIER="ALL")+(BULK_TIER=$F12))*((BULK_SKU="ALL")+(BULK_SKU=$G12))*(BULK_START<=8)*(BULK_END>=8))*IFERROR(BULK_VALUE,0))/MAX(1,SUMPRODUCT(((BULK_ENABLED="Y")*((BULK_TIER="ALL")+(BULK_TIER=$F12))*((BULK_SKU="ALL")+(BULK_SKU=$G12))*(BULK_START<=8)*(BULK_END>=8)))),0),ROUND((INDEX(VELOCITY_TABLE,MATCH($F12,TIER_LIST,0),2))*(IF((8-$I12+1)<=0,0,IF((8-$I12+1)=1,RAMP_W1,IF((8-$I12+1)=2,RAMP_W2,IF((8-$I12+1)=3,RAMP_W3,RAMP_W4PLUS)))))*(INDEX(ACTIVE_MULT_TABLE,2,1))*(1+SUMPRODUCT(SIGN(((ACT_DOOR_SCOPE="ALL")+(ACT_DOOR_SCOPE="TIER_"&$F12)+(ACT_DOOR_SCOPE=$B12)))*SIGN(((ACT_SKU_SCOPE="ALL")+(ACT_SKU_SCOPE=$G12)))*(ACT_START<=8)*(ACT_END>=8)*IFERROR(ACT_UPLIFT-1,0)))*(1+SUMPRODUCT(SIGN(((ACT_DOOR_SCOPE="ALL")+(ACT_DOOR_SCOPE="TIER_"&$F12)+(ACT_DOOR_SCOPE=$B12)))*SIGN(((ACT_SKU_SCOPE="ALL")+(ACT_SKU_SCOPE=$G12)))*(8>ACT_END)*(ACT_END>0)*IFERROR(ACT_POSTLIFT,0))),0))) | R12: =IF(OR($H12<>"Y",9<$I12),0,IF(SUMPRODUCT(((BULK_ENABLED="Y")*((BULK_TIER="ALL")+(BULK_TIER=$F12))*((BULK_SKU="ALL")+(BULK_SKU=$G12))*(BULK_START<=9)*(BULK_END>=9)))>0,IFERROR(SUMPRODUCT(((BULK_ENABLED="Y")*((BULK_TIER="ALL")+(BULK_TIER=$F12))*((BULK_SKU="ALL")+(BULK_SKU=$G12))*(BULK_START<=9)*(BULK_END>=9))*IFERROR(BULK_VALUE,0))/MAX(1,SUMPRODUCT(((BULK_ENABLED="Y")*((BULK_TIER="ALL")+(BULK_TIER=$F12))*((BULK_SKU="ALL")+(BULK_SKU=$G12))*(BULK_START<=9)*(BULK_END>=9)))),0),ROUND((INDEX(VELOCITY_TABLE,MATCH($F12,TIER_LIST,0),2))*(IF((9-$I12+1)<=0,0,IF((9-$I12+1)=1,RAMP_W1,IF((9-$I12+1)=2,RAMP_W2,IF((9-$I12+1)=3,RAMP_W3,RAMP_W4PLUS)))))*(INDEX(ACTIVE_MULT_TABLE,2,1))*(1+SUMPRODUCT(SIGN(((ACT_DOOR_SCOPE="ALL")+(ACT_DOOR_SCOPE="TIER_"&$F12)+(ACT_DOOR_SCOPE=$B12)))*SIGN(((ACT_SKU_SCOPE="ALL")+(ACT_SKU_SCOPE=$G12)))*(ACT_START<=9)*(ACT_END>=9)*IFERROR(ACT_UPLIFT-1,0)))*(1+SUMPRODUCT(SIGN(((ACT_DOOR_SCOPE="ALL")+(ACT_DOOR_SCOPE="TIER_"&$F12)+(ACT_DOOR_SCOPE=$B12)))*SIGN(((ACT_SKU_SCOPE="ALL")+(ACT_SKU_SCOPE=$G12)))*(9>ACT_END)*(ACT_END>0)*IFERROR(ACT_POSTLIFT,0))),0))) | S12: =IF(OR($H12<>"Y",10<$I12),0,IF(SUMPRODUCT(((BULK_ENABLED="Y")*((BULK_TIER="ALL")+(BULK_TIER=$F12))*((BULK_SKU="ALL")+(BULK_SKU=$G12))*(BULK_START<=10)*(BULK_END>=10)))>0,IFERROR(SUMPRODUCT(((BULK_ENABLED="Y")*((BULK_TIER="ALL")+(BULK_TIER=$F12))*((BULK_SKU="ALL")+(BULK_SKU=$G12))*(BULK_START<=10)*(BULK_END>=10))*IFERROR(BULK_VALUE,0))/MAX(1,SUMPRODUCT(((BULK_ENABLED="Y")*((BULK_TIER="ALL")+(BULK_TIER=$F12))*((BULK_SKU="ALL")+(BULK_SKU=$G12))*(BULK_START<=10)*(BULK_END>=10)))),0),ROUND((INDEX(VELOCITY_TABLE,MATCH($F12,TIER_LIST,0),2))*(IF((10-$I12+1)<=0,0,IF((10-$I12+1)=1,RAMP_W1,IF((10-$I12+1)=2,RAMP_W2,IF((10-$I12+1)=3,RAMP_W3,RAMP_W4PLUS)))))*(INDEX(ACTIVE_MULT_TABLE,2,1))*(1+SUMPRODUCT(SIGN(((ACT_DOOR_SCOPE="ALL")+(ACT_DOOR_SCOPE="TIER_"&$F12)+(ACT_DOOR_SCOPE=$B12)))*SIGN(((ACT_SKU_SCOPE="ALL")+(ACT_SKU_SCOPE=$G12)))*(ACT_START<=10)*(ACT_END>=10)*IFERROR(ACT_UPLIFT-1,0)))*(1+SUMPRODUCT(SIGN(((ACT_DOOR_SCOPE="ALL")+(ACT_DOOR_SCOPE="TIER_"&$F12)+(ACT_DOOR_SCOPE=$B12)))*SIGN(((ACT_SKU_SCOPE="ALL")+(ACT_SKU_SCOPE=$G12)))*(10>ACT_END)*(ACT_END>0)*IFERROR(ACT_POSTLIFT,0))),0))) | T12: =IF(OR($H12<>"Y",11<$I12),0,IF(SUMPRODUCT(((BULK_ENABLED="Y")*((BULK_TIER="ALL")+(BULK_TIER=$F12))*((BULK_SKU="ALL")+(BULK_SKU=$G12))*(BULK_START<=11)*(BULK_END>=11)))>0,IFERROR(SUMPRODUCT(((BULK_ENABLED="Y")*((BULK_TIER="ALL")+(BULK_TIER=$F12))*((BULK_SKU="ALL")+(BULK_SKU=$G12))*(BULK_START<=11)*(BULK_END>=11))*IFERROR(BULK_VALUE,0))/MAX(1,SUMPRODUCT(((BULK_ENABLED="Y")*((BULK_TIER="ALL")+(BULK_TIER=$F12))*((BULK_SKU="ALL")+(BULK_SKU=$G12))*(BULK_START<=11)*(BULK_END>=11)))),0),ROUND((INDEX(VELOCITY_TABLE,MATCH($F12,TIER_LIST,0),2))*(IF((11-$I12+1)<=0,0,IF((11-$I12+1)=1,RAMP_W1,IF((11-$I12+1)=2,RAMP_W2,IF((11-$I12+1)=3,RAMP_W3,RAMP_W4PLUS)))))*(INDEX(ACTIVE_MULT_TABLE,2,1))*(1+SUMPRODUCT(SIGN(((ACT_DOOR_SCOPE="ALL")+(ACT_DOOR_SCOPE="TIER_"&$F12)+(ACT_DOOR_SCOPE=$B12)))*SIGN(((ACT_SKU_SCOPE="ALL")+(ACT_SKU_SCOPE=$G12)))*(ACT_START<=11)*(ACT_END>=11)*IFERROR(ACT_UPLIFT-1,0)))*(1+SUMPRODUCT(SIGN(((ACT_DOOR_SCOPE="ALL")+(ACT_DOOR_SCOPE="TIER_"&$F12)+(ACT_DOOR_SCOPE=$B12)))*SIGN(((ACT_SKU_SCOPE="ALL")+(ACT_SKU_SCOPE=$G12)))*(11>ACT_END)*(ACT_END>0)*IFERROR(ACT_POSTLIFT,0))),0))) | U12: =IF(OR($H12<>"Y",12<$I12),0,IF(SUMPRODUCT(((BULK_ENABLED="Y")*((BULK_TIER="ALL")+(BULK_TIER=$F12))*((BULK_SKU="ALL")+(BULK_SKU=$G12))*(BULK_START<=12)*(BULK_END>=12)))>0,IFERROR(SUMPRODUCT(((BULK_ENABLED="Y")*((BULK_TIER="ALL")+(BULK_TIER=$F12))*((BULK_SKU="ALL")+(BULK_SKU=$G12))*(BULK_START<=12)*(BULK_END>=12))*IFERROR(BULK_VALUE,0))/MAX(1,SUMPRODUCT(((BULK_ENABLED="Y")*((BULK_TIER="ALL")+(BULK_TIER=$F12))*((BULK_SKU="ALL")+(BULK_SKU=$G12))*(BULK_START<=12)*(BULK_END>=12)))),0),ROUND((INDEX(VELOCITY_TABLE,MATCH($F12,TIER_LIST,0),2))*(IF((12-$I12+1)<=0,0,IF((12-$I12+1)=1,RAMP_W1,IF((12-$I12+1)=2,RAMP_W2,IF((12-$I12+1)=3,RAMP_W3,RAMP_W4PLUS)))))*(INDEX(ACTIVE_MULT_TABLE,2,1))*(1+SUMPRODUCT(SIGN(((ACT_DOOR_SCOPE="ALL")+(ACT_DOOR_SCOPE="TIER_"&$F12)+(ACT_DOOR_SCOPE=$B12)))*SIGN(((ACT_SKU_SCOPE="ALL")+(ACT_SKU_SCOPE=$G12)))*(ACT_START<=12)*(ACT_END>=12)*IFERROR(ACT_UPLIFT-1,0)))*(1+SUMPRODUCT(SIGN(((ACT_DOOR_SCOPE="ALL")+(ACT_DOOR_SCOPE="TIER_"&$F12)+(ACT_DOOR_SCOPE=$B12)))*SIGN(((ACT_SKU_SCOPE="ALL")+(ACT_SKU_SCOPE=$G12)))*(12>ACT_END)*(ACT_END>0)*IFERROR(ACT_POSTLIFT,0))),0))) | V12: =IF(OR($H12<>"Y",13<$I12),0,IF(SUMPRODUCT(((BULK_ENABLED="Y")*((BULK_TIER="ALL")+(BULK_TIER=$F12))*((BULK_SKU="ALL")+(BULK_SKU=$G12))*(BULK_START<=13)*(BULK_END>=13)))>0,IFERROR(SUMPRODUCT(((BULK_ENABLED="Y")*((BULK_TIER="ALL")+(BULK_TIER=$F12))*((BULK_SKU="ALL")+(BULK_SKU=$G12))*(BULK_START<=13)*(BULK_END>=13))*IFERROR(BULK_VALUE,0))/MAX(1,SUMPRODUCT(((BULK_ENABLED="Y")*((BULK_TIER="ALL")+(BULK_TIER=$F12))*((BULK_SKU="ALL")+(BULK_SKU=$G12))*(BULK_START<=13)*(BULK_END>=13)))),0),ROUND((INDEX(VELOCITY_TABLE,MATCH($F12,TIER_LIST,0),2))*(IF((13-$I12+1)<=0,0,IF((13-$I12+1)=1,RAMP_W1,IF((13-$I12+1)=2,RAMP_W2,IF((13-$I12+1)=3,RAMP_W3,RAMP_W4PLUS)))))*(INDEX(ACTIVE_MULT_TABLE,2,1))*(1+SUMPRODUCT(SIGN(((ACT_DOOR_SCOPE="ALL")+(ACT_DOOR_SCOPE="TIER_"&$F12)+(ACT_DOOR_SCOPE=$B12)))*SIGN(((ACT_SKU_SCOPE="ALL")+(ACT_SKU_SCOPE=$G12)))*(ACT_START<=13)*(ACT_END>=13)*IFERROR(ACT_UPLIFT-1,0)))*(1+SUMPRODUCT(SIGN(((ACT_DOOR_SCOPE="ALL")+(ACT_DOOR_SCOPE="TIER_"&$F12)+(ACT_DOOR_SCOPE=$B12)))*SIGN(((ACT_SKU_SCOPE="ALL")+(ACT_SKU_SCOPE=$G12)))*(13>ACT_END)*(ACT_END>0)*IFERROR(ACT_POSTLIFT,0))),0)))
A13: R0009 | B13: =Doors!$A$7 | C13: =Doors!$C$7 | D13: =Doors!$B$7 | E13: =Doors!$E$7 | F13: =Doors!$F$7 | G13: Raspberry | H13: =Doors!$I$7 | I13: =Doors!$J$7 | J13: =IF(OR($H13<>"Y",1<$I13),0,IF(SUMPRODUCT(((BULK_ENABLED="Y")*((BULK_TIER="ALL")+(BULK_TIER=$F13))*((BULK_SKU="ALL")+(BULK_SKU=$G13))*(BULK_START<=1)*(BULK_END>=1)))>0,IFERROR(SUMPRODUCT(((BULK_ENABLED="Y")*((BULK_TIER="ALL")+(BULK_TIER=$F13))*((BULK_SKU="ALL")+(BULK_SKU=$G13))*(BULK_START<=1)*(BULK_END>=1))*IFERROR(BULK_VALUE,0))/MAX(1,SUMPRODUCT(((BULK_ENABLED="Y")*((BULK_TIER="ALL")+(BULK_TIER=$F13))*((BULK_SKU="ALL")+(BULK_SKU=$G13))*(BULK_START<=1)*(BULK_END>=1)))),0),ROUND((INDEX(VELOCITY_TABLE,MATCH($F13,TIER_LIST,0),3))*(IF((1-$I13+1)<=0,0,IF((1-$I13+1)=1,RAMP_W1,IF((1-$I13+1)=2,RAMP_W2,IF((1-$I13+1)=3,RAMP_W3,RAMP_W4PLUS)))))*(INDEX(ACTIVE_MULT_TABLE,3,1))*(1+SUMPRODUCT(SIGN(((ACT_DOOR_SCOPE="ALL")+(ACT_DOOR_SCOPE="TIER_"&$F13)+(ACT_DOOR_SCOPE=$B13)))*SIGN(((ACT_SKU_SCOPE="ALL")+(ACT_SKU_SCOPE=$G13)))*(ACT_START<=1)*(ACT_END>=1)*IFERROR(ACT_UPLIFT-1,0)))*(1+SUMPRODUCT(SIGN(((ACT_DOOR_SCOPE="ALL")+(ACT_DOOR_SCOPE="TIER_"&$F13)+(ACT_DOOR_SCOPE=$B13)))*SIGN(((ACT_SKU_SCOPE="ALL")+(ACT_SKU_SCOPE=$G13)))*(1>ACT_END)*(ACT_END>0)*IFERROR(ACT_POSTLIFT,0))),0))) | K13: =IF(OR($H13<>"Y",2<$I13),0,IF(SUMPRODUCT(((BULK_ENABLED="Y")*((BULK_TIER="ALL")+(BULK_TIER=$F13))*((BULK_SKU="ALL")+(BULK_SKU=$G13))*(BULK_START<=2)*(BULK_END>=2)))>0,IFERROR(SUMPRODUCT(((BULK_ENABLED="Y")*((BULK_TIER="ALL")+(BULK_TIER=$F13))*((BULK_SKU="ALL")+(BULK_SKU=$G13))*(BULK_START<=2)*(BULK_END>=2))*IFERROR(BULK_VALUE,0))/MAX(1,SUMPRODUCT(((BULK_ENABLED="Y")*((BULK_TIER="ALL")+(BULK_TIER=$F13))*((BULK_SKU="ALL")+(BULK_SKU=$G13))*(BULK_START<=2)*(BULK_END>=2)))),0),ROUND((INDEX(VELOCITY_TABLE,MATCH($F13,TIER_LIST,0),3))*(IF((2-$I13+1)<=0,0,IF((2-$I13+1)=1,RAMP_W1,IF((2-$I13+1)=2,RAMP_W2,IF((2-$I13+1)=3,RAMP_W3,RAMP_W4PLUS)))))*(INDEX(ACTIVE_MULT_TABLE,3,1))*(1+SUMPRODUCT(SIGN(((ACT_DOOR_SCOPE="ALL")+(ACT_DOOR_SCOPE="TIER_"&$F13)+(ACT_DOOR_SCOPE=$B13)))*SIGN(((ACT_SKU_SCOPE="ALL")+(ACT_SKU_SCOPE=$G13)))*(ACT_START<=2)*(ACT_END>=2)*IFERROR(ACT_UPLIFT-1,0)))*(1+SUMPRODUCT(SIGN(((ACT_DOOR_SCOPE="ALL")+(ACT_DOOR_SCOPE="TIER_"&$F13)+(ACT_DOOR_SCOPE=$B13)))*SIGN(((ACT_SKU_SCOPE="ALL")+(ACT_SKU_SCOPE=$G13)))*(2>ACT_END)*(ACT_END>0)*IFERROR(ACT_POSTLIFT,0))),0))) | L13: =IF(OR($H13<>"Y",3<$I13),0,IF(SUMPRODUCT(((BULK_ENABLED="Y")*((BULK_TIER="ALL")+(BULK_TIER=$F13))*((BULK_SKU="ALL")+(BULK_SKU=$G13))*(BULK_START<=3)*(BULK_END>=3)))>0,IFERROR(SUMPRODUCT(((BULK_ENABLED="Y")*((BULK_TIER="ALL")+(BULK_TIER=$F13))*((BULK_SKU="ALL")+(BULK_SKU=$G13))*(BULK_START<=3)*(BULK_END>=3))*IFERROR(BULK_VALUE,0))/MAX(1,SUMPRODUCT(((BULK_ENABLED="Y")*((BULK_TIER="ALL")+(BULK_TIER=$F13))*((BULK_SKU="ALL")+(BULK_SKU=$G13))*(BULK_START<=3)*(BULK_END>=3)))),0),ROUND((INDEX(VELOCITY_TABLE,MATCH($F13,TIER_LIST,0),3))*(IF((3-$I13+1)<=0,0,IF((3-$I13+1)=1,RAMP_W1,IF((3-$I13+1)=2,RAMP_W2,IF((3-$I13+1)=3,RAMP_W3,RAMP_W4PLUS)))))*(INDEX(ACTIVE_MULT_TABLE,3,1))*(1+SUMPRODUCT(SIGN(((ACT_DOOR_SCOPE="ALL")+(ACT_DOOR_SCOPE="TIER_"&$F13)+(ACT_DOOR_SCOPE=$B13)))*SIGN(((ACT_SKU_SCOPE="ALL")+(ACT_SKU_SCOPE=$G13)))*(ACT_START<=3)*(ACT_END>=3)*IFERROR(ACT_UPLIFT-1,0)))*(1+SUMPRODUCT(SIGN(((ACT_DOOR_SCOPE="ALL")+(ACT_DOOR_SCOPE="TIER_"&$F13)+(ACT_DOOR_SCOPE=$B13)))*SIGN(((ACT_SKU_SCOPE="ALL")+(ACT_SKU_SCOPE=$G13)))*(3>ACT_END)*(ACT_END>0)*IFERROR(ACT_POSTLIFT,0))),0))) | M13: =IF(OR($H13<>"Y",4<$I13),0,IF(SUMPRODUCT(((BULK_ENABLED="Y")*((BULK_TIER="ALL")+(BULK_TIER=$F13))*((BULK_SKU="ALL")+(BULK_SKU=$G13))*(BULK_START<=4)*(BULK_END>=4)))>0,IFERROR(SUMPRODUCT(((BULK_ENABLED="Y")*((BULK_TIER="ALL")+(BULK_TIER=$F13))*((BULK_SKU="ALL")+(BULK_SKU=$G13))*(BULK_START<=4)*(BULK_END>=4))*IFERROR(BULK_VALUE,0))/MAX(1,SUMPRODUCT(((BULK_ENABLED="Y")*((BULK_TIER="ALL")+(BULK_TIER=$F13))*((BULK_SKU="ALL")+(BULK_SKU=$G13))*(BULK_START<=4)*(BULK_END>=4)))),0),ROUND((INDEX(VELOCITY_TABLE,MATCH($F13,TIER_LIST,0),3))*(IF((4-$I13+1)<=0,0,IF((4-$I13+1)=1,RAMP_W1,IF((4-$I13+1)=2,RAMP_W2,IF((4-$I13+1)=3,RAMP_W3,RAMP_W4PLUS)))))*(INDEX(ACTIVE_MULT_TABLE,3,1))*(1+SUMPRODUCT(SIGN(((ACT_DOOR_SCOPE="ALL")+(ACT_DOOR_SCOPE="TIER_"&$F13)+(ACT_DOOR_SCOPE=$B13)))*SIGN(((ACT_SKU_SCOPE="ALL")+(ACT_SKU_SCOPE=$G13)))*(ACT_START<=4)*(ACT_END>=4)*IFERROR(ACT_UPLIFT-1,0)))*(1+SUMPRODUCT(SIGN(((ACT_DOOR_SCOPE="ALL")+(ACT_DOOR_SCOPE="TIER_"&$F13)+(ACT_DOOR_SCOPE=$B13)))*SIGN(((ACT_SKU_SCOPE="ALL")+(ACT_SKU_SCOPE=$G13)))*(4>ACT_END)*(ACT_END>0)*IFERROR(ACT_POSTLIFT,0))),0))) | N13: =IF(OR($H13<>"Y",5<$I13),0,IF(SUMPRODUCT(((BULK_ENABLED="Y")*((BULK_TIER="ALL")+(BULK_TIER=$F13))*((BULK_SKU="ALL")+(BULK_SKU=$G13))*(BULK_START<=5)*(BULK_END>=5)))>0,IFERROR(SUMPRODUCT(((BULK_ENABLED="Y")*((BULK_TIER="ALL")+(BULK_TIER=$F13))*((BULK_SKU="ALL")+(BULK_SKU=$G13))*(BULK_START<=5)*(BULK_END>=5))*IFERROR(BULK_VALUE,0))/MAX(1,SUMPRODUCT(((BULK_ENABLED="Y")*((BULK_TIER="ALL")+(BULK_TIER=$F13))*((BULK_SKU="ALL")+(BULK_SKU=$G13))*(BULK_START<=5)*(BULK_END>=5)))),0),ROUND((INDEX(VELOCITY_TABLE,MATCH($F13,TIER_LIST,0),3))*(IF((5-$I13+1)<=0,0,IF((5-$I13+1)=1,RAMP_W1,IF((5-$I13+1)=2,RAMP_W2,IF((5-$I13+1)=3,RAMP_W3,RAMP_W4PLUS)))))*(INDEX(ACTIVE_MULT_TABLE,3,1))*(1+SUMPRODUCT(SIGN(((ACT_DOOR_SCOPE="ALL")+(ACT_DOOR_SCOPE="TIER_"&$F13)+(ACT_DOOR_SCOPE=$B13)))*SIGN(((ACT_SKU_SCOPE="ALL")+(ACT_SKU_SCOPE=$G13)))*(ACT_START<=5)*(ACT_END>=5)*IFERROR(ACT_UPLIFT-1,0)))*(1+SUMPRODUCT(SIGN(((ACT_DOOR_SCOPE="ALL")+(ACT_DOOR_SCOPE="TIER_"&$F13)+(ACT_DOOR_SCOPE=$B13)))*SIGN(((ACT_SKU_SCOPE="ALL")+(ACT_SKU_SCOPE=$G13)))*(5>ACT_END)*(ACT_END>0)*IFERROR(ACT_POSTLIFT,0))),0))) | O13: =IF(OR($H13<>"Y",6<$I13),0,IF(SUMPRODUCT(((BULK_ENABLED="Y")*((BULK_TIER="ALL")+(BULK_TIER=$F13))*((BULK_SKU="ALL")+(BULK_SKU=$G13))*(BULK_START<=6)*(BULK_END>=6)))>0,IFERROR(SUMPRODUCT(((BULK_ENABLED="Y")*((BULK_TIER="ALL")+(BULK_TIER=$F13))*((BULK_SKU="ALL")+(BULK_SKU=$G13))*(BULK_START<=6)*(BULK_END>=6))*IFERROR(BULK_VALUE,0))/MAX(1,SUMPRODUCT(((BULK_ENABLED="Y")*((BULK_TIER="ALL")+(BULK_TIER=$F13))*((BULK_SKU="ALL")+(BULK_SKU=$G13))*(BULK_START<=6)*(BULK_END>=6)))),0),ROUND((INDEX(VELOCITY_TABLE,MATCH($F13,TIER_LIST,0),3))*(IF((6-$I13+1)<=0,0,IF((6-$I13+1)=1,RAMP_W1,IF((6-$I13+1)=2,RAMP_W2,IF((6-$I13+1)=3,RAMP_W3,RAMP_W4PLUS)))))*(INDEX(ACTIVE_MULT_TABLE,3,1))*(1+SUMPRODUCT(SIGN(((ACT_DOOR_SCOPE="ALL")+(ACT_DOOR_SCOPE="TIER_"&$F13)+(ACT_DOOR_SCOPE=$B13)))*SIGN(((ACT_SKU_SCOPE="ALL")+(ACT_SKU_SCOPE=$G13)))*(ACT_START<=6)*(ACT_END>=6)*IFERROR(ACT_UPLIFT-1,0)))*(1+SUMPRODUCT(SIGN(((ACT_DOOR_SCOPE="ALL")+(ACT_DOOR_SCOPE="TIER_"&$F13)+(ACT_DOOR_SCOPE=$B13)))*SIGN(((ACT_SKU_SCOPE="ALL")+(ACT_SKU_SCOPE=$G13)))*(6>ACT_END)*(ACT_END>0)*IFERROR(ACT_POSTLIFT,0))),0))) | P13: =IF(OR($H13<>"Y",7<$I13),0,IF(SUMPRODUCT(((BULK_ENABLED="Y")*((BULK_TIER="ALL")+(BULK_TIER=$F13))*((BULK_SKU="ALL")+(BULK_SKU=$G13))*(BULK_START<=7)*(BULK_END>=7)))>0,IFERROR(SUMPRODUCT(((BULK_ENABLED="Y")*((BULK_TIER="ALL")+(BULK_TIER=$F13))*((BULK_SKU="ALL")+(BULK_SKU=$G13))*(BULK_START<=7)*(BULK_END>=7))*IFERROR(BULK_VALUE,0))/MAX(1,SUMPRODUCT(((BULK_ENABLED="Y")*((BULK_TIER="ALL")+(BULK_TIER=$F13))*((BULK_SKU="ALL")+(BULK_SKU=$G13))*(BULK_START<=7)*(BULK_END>=7)))),0),ROUND((INDEX(VELOCITY_TABLE,MATCH($F13,TIER_LIST,0),3))*(IF((7-$I13+1)<=0,0,IF((7-$I13+1)=1,RAMP_W1,IF((7-$I13+1)=2,RAMP_W2,IF((7-$I13+1)=3,RAMP_W3,RAMP_W4PLUS)))))*(INDEX(ACTIVE_MULT_TABLE,3,1))*(1+SUMPRODUCT(SIGN(((ACT_DOOR_SCOPE="ALL")+(ACT_DOOR_SCOPE="TIER_"&$F13)+(ACT_DOOR_SCOPE=$B13)))*SIGN(((ACT_SKU_SCOPE="ALL")+(ACT_SKU_SCOPE=$G13)))*(ACT_START<=7)*(ACT_END>=7)*IFERROR(ACT_UPLIFT-1,0)))*(1+SUMPRODUCT(SIGN(((ACT_DOOR_SCOPE="ALL")+(ACT_DOOR_SCOPE="TIER_"&$F13)+(ACT_DOOR_SCOPE=$B13)))*SIGN(((ACT_SKU_SCOPE="ALL")+(ACT_SKU_SCOPE=$G13)))*(7>ACT_END)*(ACT_END>0)*IFERROR(ACT_POSTLIFT,0))),0))) | Q13: =IF(OR($H13<>"Y",8<$I13),0,IF(SUMPRODUCT(((BULK_ENABLED="Y")*((BULK_TIER="ALL")+(BULK_TIER=$F13))*((BULK_SKU="ALL")+(BULK_SKU=$G13))*(BULK_START<=8)*(BULK_END>=8)))>0,IFERROR(SUMPRODUCT(((BULK_ENABLED="Y")*((BULK_TIER="ALL")+(BULK_TIER=$F13))*((BULK_SKU="ALL")+(BULK_SKU=$G13))*(BULK_START<=8)*(BULK_END>=8))*IFERROR(BULK_VALUE,0))/MAX(1,SUMPRODUCT(((BULK_ENABLED="Y")*((BULK_TIER="ALL")+(BULK_TIER=$F13))*((BULK_SKU="ALL")+(BULK_SKU=$G13))*(BULK_START<=8)*(BULK_END>=8)))),0),ROUND((INDEX(VELOCITY_TABLE,MATCH($F13,TIER_LIST,0),3))*(IF((8-$I13+1)<=0,0,IF((8-$I13+1)=1,RAMP_W1,IF((8-$I13+1)=2,RAMP_W2,IF((8-$I13+1)=3,RAMP_W3,RAMP_W4PLUS)))))*(INDEX(ACTIVE_MULT_TABLE,3,1))*(1+SUMPRODUCT(SIGN(((ACT_DOOR_SCOPE="ALL")+(ACT_DOOR_SCOPE="TIER_"&$F13)+(ACT_DOOR_SCOPE=$B13)))*SIGN(((ACT_SKU_SCOPE="ALL")+(ACT_SKU_SCOPE=$G13)))*(ACT_START<=8)*(ACT_END>=8)*IFERROR(ACT_UPLIFT-1,0)))*(1+SUMPRODUCT(SIGN(((ACT_DOOR_SCOPE="ALL")+(ACT_DOOR_SCOPE="TIER_"&$F13)+(ACT_DOOR_SCOPE=$B13)))*SIGN(((ACT_SKU_SCOPE="ALL")+(ACT_SKU_SCOPE=$G13)))*(8>ACT_END)*(ACT_END>0)*IFERROR(ACT_POSTLIFT,0))),0))) | R13: =IF(OR($H13<>"Y",9<$I13),0,IF(SUMPRODUCT(((BULK_ENABLED="Y")*((BULK_TIER="ALL")+(BULK_TIER=$F13))*((BULK_SKU="ALL")+(BULK_SKU=$G13))*(BULK_START<=9)*(BULK_END>=9)))>0,IFERROR(SUMPRODUCT(((BULK_ENABLED="Y")*((BULK_TIER="ALL")+(BULK_TIER=$F13))*((BULK_SKU="ALL")+(BULK_SKU=$G13))*(BULK_START<=9)*(BULK_END>=9))*IFERROR(BULK_VALUE,0))/MAX(1,SUMPRODUCT(((BULK_ENABLED="Y")*((BULK_TIER="ALL")+(BULK_TIER=$F13))*((BULK_SKU="ALL")+(BULK_SKU=$G13))*(BULK_START<=9)*(BULK_END>=9)))),0),ROUND((INDEX(VELOCITY_TABLE,MATCH($F13,TIER_LIST,0),3))*(IF((9-$I13+1)<=0,0,IF((9-$I13+1)=1,RAMP_W1,IF((9-$I13+1)=2,RAMP_W2,IF((9-$I13+1)=3,RAMP_W3,RAMP_W4PLUS)))))*(INDEX(ACTIVE_MULT_TABLE,3,1))*(1+SUMPRODUCT(SIGN(((ACT_DOOR_SCOPE="ALL")+(ACT_DOOR_SCOPE="TIER_"&$F13)+(ACT_DOOR_SCOPE=$B13)))*SIGN(((ACT_SKU_SCOPE="ALL")+(ACT_SKU_SCOPE=$G13)))*(ACT_START<=9)*(ACT_END>=9)*IFERROR(ACT_UPLIFT-1,0)))*(1+SUMPRODUCT(SIGN(((ACT_DOOR_SCOPE="ALL")+(ACT_DOOR_SCOPE="TIER_"&$F13)+(ACT_DOOR_SCOPE=$B13)))*SIGN(((ACT_SKU_SCOPE="ALL")+(ACT_SKU_SCOPE=$G13)))*(9>ACT_END)*(ACT_END>0)*IFERROR(ACT_POSTLIFT,0))),0))) | S13: =IF(OR($H13<>"Y",10<$I13),0,IF(SUMPRODUCT(((BULK_ENABLED="Y")*((BULK_TIER="ALL")+(BULK_TIER=$F13))*((BULK_SKU="ALL")+(BULK_SKU=$G13))*(BULK_START<=10)*(BULK_END>=10)))>0,IFERROR(SUMPRODUCT(((BULK_ENABLED="Y")*((BULK_TIER="ALL")+(BULK_TIER=$F13))*((BULK_SKU="ALL")+(BULK_SKU=$G13))*(BULK_START<=10)*(BULK_END>=10))*IFERROR(BULK_VALUE,0))/MAX(1,SUMPRODUCT(((BULK_ENABLED="Y")*((BULK_TIER="ALL")+(BULK_TIER=$F13))*((BULK_SKU="ALL")+(BULK_SKU=$G13))*(BULK_START<=10)*(BULK_END>=10)))),0),ROUND((INDEX(VELOCITY_TABLE,MATCH($F13,TIER_LIST,0),3))*(IF((10-$I13+1)<=0,0,IF((10-$I13+1)=1,RAMP_W1,IF((10-$I13+1)=2,RAMP_W2,IF((10-$I13+1)=3,RAMP_W3,RAMP_W4PLUS)))))*(INDEX(ACTIVE_MULT_TABLE,3,1))*(1+SUMPRODUCT(SIGN(((ACT_DOOR_SCOPE="ALL")+(ACT_DOOR_SCOPE="TIER_"&$F13)+(ACT_DOOR_SCOPE=$B13)))*SIGN(((ACT_SKU_SCOPE="ALL")+(ACT_SKU_SCOPE=$G13)))*(ACT_START<=10)*(ACT_END>=10)*IFERROR(ACT_UPLIFT-1,0)))*(1+SUMPRODUCT(SIGN(((ACT_DOOR_SCOPE="ALL")+(ACT_DOOR_SCOPE="TIER_"&$F13)+(ACT_DOOR_SCOPE=$B13)))*SIGN(((ACT_SKU_SCOPE="ALL")+(ACT_SKU_SCOPE=$G13)))*(10>ACT_END)*(ACT_END>0)*IFERROR(ACT_POSTLIFT,0))),0))) | T13: =IF(OR($H13<>"Y",11<$I13),0,IF(SUMPRODUCT(((BULK_ENABLED="Y")*((BULK_TIER="ALL")+(BULK_TIER=$F13))*((BULK_SKU="ALL")+(BULK_SKU=$G13))*(BULK_START<=11)*(BULK_END>=11)))>0,IFERROR(SUMPRODUCT(((BULK_ENABLED="Y")*((BULK_TIER="ALL")+(BULK_TIER=$F13))*((BULK_SKU="ALL")+(BULK_SKU=$G13))*(BULK_START<=11)*(BULK_END>=11))*IFERROR(BULK_VALUE,0))/MAX(1,SUMPRODUCT(((BULK_ENABLED="Y")*((BULK_TIER="ALL")+(BULK_TIER=$F13))*((BULK_SKU="ALL")+(BULK_SKU=$G13))*(BULK_START<=11)*(BULK_END>=11)))),0),ROUND((INDEX(VELOCITY_TABLE,MATCH($F13,TIER_LIST,0),3))*(IF((11-$I13+1)<=0,0,IF((11-$I13+1)=1,RAMP_W1,IF((11-$I13+1)=2,RAMP_W2,IF((11-$I13+1)=3,RAMP_W3,RAMP_W4PLUS)))))*(INDEX(ACTIVE_MULT_TABLE,3,1))*(1+SUMPRODUCT(SIGN(((ACT_DOOR_SCOPE="ALL")+(ACT_DOOR_SCOPE="TIER_"&$F13)+(ACT_DOOR_SCOPE=$B13)))*SIGN(((ACT_SKU_SCOPE="ALL")+(ACT_SKU_SCOPE=$G13)))*(ACT_START<=11)*(ACT_END>=11)*IFERROR(ACT_UPLIFT-1,0)))*(1+SUMPRODUCT(SIGN(((ACT_DOOR_SCOPE="ALL")+(ACT_DOOR_SCOPE="TIER_"&$F13)+(ACT_DOOR_SCOPE=$B13)))*SIGN(((ACT_SKU_SCOPE="ALL")+(ACT_SKU_SCOPE=$G13)))*(11>ACT_END)*(ACT_END>0)*IFERROR(ACT_POSTLIFT,0))),0))) | U13: =IF(OR($H13<>"Y",12<$I13),0,IF(SUMPRODUCT(((BULK_ENABLED="Y")*((BULK_TIER="ALL")+(BULK_TIER=$F13))*((BULK_SKU="ALL")+(BULK_SKU=$G13))*(BULK_START<=12)*(BULK_END>=12)))>0,IFERROR(SUMPRODUCT(((BULK_ENABLED="Y")*((BULK_TIER="ALL")+(BULK_TIER=$F13))*((BULK_SKU="ALL")+(BULK_SKU=$G13))*(BULK_START<=12)*(BULK_END>=12))*IFERROR(BULK_VALUE,0))/MAX(1,SUMPRODUCT(((BULK_ENABLED="Y")*((BULK_TIER="ALL")+(BULK_TIER=$F13))*((BULK_SKU="ALL")+(BULK_SKU=$G13))*(BULK_START<=12)*(BULK_END>=12)))),0),ROUND((INDEX(VELOCITY_TABLE,MATCH($F13,TIER_LIST,0),3))*(IF((12-$I13+1)<=0,0,IF((12-$I13+1)=1,RAMP_W1,IF((12-$I13+1)=2,RAMP_W2,IF((12-$I13+1)=3,RAMP_W3,RAMP_W4PLUS)))))*(INDEX(ACTIVE_MULT_TABLE,3,1))*(1+SUMPRODUCT(SIGN(((ACT_DOOR_SCOPE="ALL")+(ACT_DOOR_SCOPE="TIER_"&$F13)+(ACT_DOOR_SCOPE=$B13)))*SIGN(((ACT_SKU_SCOPE="ALL")+(ACT_SKU_SCOPE=$G13)))*(ACT_START<=12)*(ACT_END>=12)*IFERROR(ACT_UPLIFT-1,0)))*(1+SUMPRODUCT(SIGN(((ACT_DOOR_SCOPE="ALL")+(ACT_DOOR_SCOPE="TIER_"&$F13)+(ACT_DOOR_SCOPE=$B13)))*SIGN(((ACT_SKU_SCOPE="ALL")+(ACT_SKU_SCOPE=$G13)))*(12>ACT_END)*(ACT_END>0)*IFERROR(ACT_POSTLIFT,0))),0))) | V13: =IF(OR($H13<>"Y",13<$I13),0,IF(SUMPRODUCT(((BULK_ENABLED="Y")*((BULK_TIER="ALL")+(BULK_TIER=$F13))*((BULK_SKU="ALL")+(BULK_SKU=$G13))*(BULK_START<=13)*(BULK_END>=13)))>0,IFERROR(SUMPRODUCT(((BULK_ENABLED="Y")*((BULK_TIER="ALL")+(BULK_TIER=$F13))*((BULK_SKU="ALL")+(BULK_SKU=$G13))*(BULK_START<=13)*(BULK_END>=13))*IFERROR(BULK_VALUE,0))/MAX(1,SUMPRODUCT(((BULK_ENABLED="Y")*((BULK_TIER="ALL")+(BULK_TIER=$F13))*((BULK_SKU="ALL")+(BULK_SKU=$G13))*(BULK_START<=13)*(BULK_END>=13)))),0),ROUND((INDEX(VELOCITY_TABLE,MATCH($F13,TIER_LIST,0),3))*(IF((13-$I13+1)<=0,0,IF((13-$I13+1)=1,RAMP_W1,IF((13-$I13+1)=2,RAMP_W2,IF((13-$I13+1)=3,RAMP_W3,RAMP_W4PLUS)))))*(INDEX(ACTIVE_MULT_TABLE,3,1))*(1+SUMPRODUCT(SIGN(((ACT_DOOR_SCOPE="ALL")+(ACT_DOOR_SCOPE="TIER_"&$F13)+(ACT_DOOR_SCOPE=$B13)))*SIGN(((ACT_SKU_SCOPE="ALL")+(ACT_SKU_SCOPE=$G13)))*(ACT_START<=13)*(ACT_END>=13)*IFERROR(ACT_UPLIFT-1,0)))*(1+SUMPRODUCT(SIGN(((ACT_DOOR_SCOPE="ALL")+(ACT_DOOR_SCOPE="TIER_"&$F13)+(ACT_DOOR_SCOPE=$B13)))*SIGN(((ACT_SKU_SCOPE="ALL")+(ACT_SKU_SCOPE=$G13)))*(13>ACT_END)*(ACT_END>0)*IFERROR(ACT_POSTLIFT,0))),0)))
A14: R0010 | B14: =Doors!$A$8 | C14: =Doors!$C$8 | D14: =Doors!$B$8 | E14: =Doors!$E$8 | F14: =Doors!$F$8 | G14: Lime Lemon | H14: =Doors!$G$8 | I14: =Doors!$J$8 | J14: =IF(OR($H14<>"Y",1<$I14),0,IF(SUMPRODUCT(((BULK_ENABLED="Y")*((BULK_TIER="ALL")+(BULK_TIER=$F14))*((BULK_SKU="ALL")+(BULK_SKU=$G14))*(BULK_START<=1)*(BULK_END>=1)))>0,IFERROR(SUMPRODUCT(((BULK_ENABLED="Y")*((BULK_TIER="ALL")+(BULK_TIER=$F14))*((BULK_SKU="ALL")+(BULK_SKU=$G14))*(BULK_START<=1)*(BULK_END>=1))*IFERROR(BULK_VALUE,0))/MAX(1,SUMPRODUCT(((BULK_ENABLED="Y")*((BULK_TIER="ALL")+(BULK_TIER=$F14))*((BULK_SKU="ALL")+(BULK_SKU=$G14))*(BULK_START<=1)*(BULK_END>=1)))),0),ROUND((INDEX(VELOCITY_TABLE,MATCH($F14,TIER_LIST,0),1))*(IF((1-$I14+1)<=0,0,IF((1-$I14+1)=1,RAMP_W1,IF((1-$I14+1)=2,RAMP_W2,IF((1-$I14+1)=3,RAMP_W3,RAMP_W4PLUS)))))*(INDEX(ACTIVE_MULT_TABLE,1,1))*(1+SUMPRODUCT(SIGN(((ACT_DOOR_SCOPE="ALL")+(ACT_DOOR_SCOPE="TIER_"&$F14)+(ACT_DOOR_SCOPE=$B14)))*SIGN(((ACT_SKU_SCOPE="ALL")+(ACT_SKU_SCOPE=$G14)))*(ACT_START<=1)*(ACT_END>=1)*IFERROR(ACT_UPLIFT-1,0)))*(1+SUMPRODUCT(SIGN(((ACT_DOOR_SCOPE="ALL")+(ACT_DOOR_SCOPE="TIER_"&$F14)+(ACT_DOOR_SCOPE=$B14)))*SIGN(((ACT_SKU_SCOPE="ALL")+(ACT_SKU_SCOPE=$G14)))*(1>ACT_END)*(ACT_END>0)*IFERROR(ACT_POSTLIFT,0))),0))) | K14: =IF(OR($H14<>"Y",2<$I14),0,IF(SUMPRODUCT(((BULK_ENABLED="Y")*((BULK_TIER="ALL")+(BULK_TIER=$F14))*((BULK_SKU="ALL")+(BULK_SKU=$G14))*(BULK_START<=2)*(BULK_END>=2)))>0,IFERROR(SUMPRODUCT(((BULK_ENABLED="Y")*((BULK_TIER="ALL")+(BULK_TIER=$F14))*((BULK_SKU="ALL")+(BULK_SKU=$G14))*(BULK_START<=2)*(BULK_END>=2))*IFERROR(BULK_VALUE,0))/MAX(1,SUMPRODUCT(((BULK_ENABLED="Y")*((BULK_TIER="ALL")+(BULK_TIER=$F14))*((BULK_SKU="ALL")+(BULK_SKU=$G14))*(BULK_START<=2)*(BULK_END>=2)))),0),ROUND((INDEX(VELOCITY_TABLE,MATCH($F14,TIER_LIST,0),1))*(IF((2-$I14+1)<=0,0,IF((2-$I14+1)=1,RAMP_W1,IF((2-$I14+1)=2,RAMP_W2,IF((2-$I14+1)=3,RAMP_W3,RAMP_W4PLUS)))))*(INDEX(ACTIVE_MULT_TABLE,1,1))*(1+SUMPRODUCT(SIGN(((ACT_DOOR_SCOPE="ALL")+(ACT_DOOR_SCOPE="TIER_"&$F14)+(ACT_DOOR_SCOPE=$B14)))*SIGN(((ACT_SKU_SCOPE="ALL")+(ACT_SKU_SCOPE=$G14)))*(ACT_START<=2)*(ACT_END>=2)*IFERROR(ACT_UPLIFT-1,0)))*(1+SUMPRODUCT(SIGN(((ACT_DOOR_SCOPE="ALL")+(ACT_DOOR_SCOPE="TIER_"&$F14)+(ACT_DOOR_SCOPE=$B14)))*SIGN(((ACT_SKU_SCOPE="ALL")+(ACT_SKU_SCOPE=$G14)))*(2>ACT_END)*(ACT_END>0)*IFERROR(ACT_POSTLIFT,0))),0))) | L14: =IF(OR($H14<>"Y",3<$I14),0,IF(SUMPRODUCT(((BULK_ENABLED="Y")*((BULK_TIER="ALL")+(BULK_TIER=$F14))*((BULK_SKU="ALL")+(BULK_SKU=$G14))*(BULK_START<=3)*(BULK_END>=3)))>0,IFERROR(SUMPRODUCT(((BULK_ENABLED="Y")*((BULK_TIER="ALL")+(BULK_TIER=$F14))*((BULK_SKU="ALL")+(BULK_SKU=$G14))*(BULK_START<=3)*(BULK_END>=3))*IFERROR(BULK_VALUE,0))/MAX(1,SUMPRODUCT(((BULK_ENABLED="Y")*((BULK_TIER="ALL")+(BULK_TIER=$F14))*((BULK_SKU="ALL")+(BULK_SKU=$G14))*(BULK_START<=3)*(BULK_END>=3)))),0),ROUND((INDEX(VELOCITY_TABLE,MATCH($F14,TIER_LIST,0),1))*(IF((3-$I14+1)<=0,0,IF((3-$I14+1)=1,RAMP_W1,IF((3-$I14+1)=2,RAMP_W2,IF((3-$I14+1)=3,RAMP_W3,RAMP_W4PLUS)))))*(INDEX(ACTIVE_MULT_TABLE,1,1))*(1+SUMPRODUCT(SIGN(((ACT_DOOR_SCOPE="ALL")+(ACT_DOOR_SCOPE="TIER_"&$F14)+(ACT_DOOR_SCOPE=$B14)))*SIGN(((ACT_SKU_SCOPE="ALL")+(ACT_SKU_SCOPE=$G14)))*(ACT_START<=3)*(ACT_END>=3)*IFERROR(ACT_UPLIFT-1,0)))*(1+SUMPRODUCT(SIGN(((ACT_DOOR_SCOPE="ALL")+(ACT_DOOR_SCOPE="TIER_"&$F14)+(ACT_DOOR_SCOPE=$B14)))*SIGN(((ACT_SKU_SCOPE="ALL")+(ACT_SKU_SCOPE=$G14)))*(3>ACT_END)*(ACT_END>0)*IFERROR(ACT_POSTLIFT,0))),0))) | M14: =IF(OR($H14<>"Y",4<$I14),0,IF(SUMPRODUCT(((BULK_ENABLED="Y")*((BULK_TIER="ALL")+(BULK_TIER=$F14))*((BULK_SKU="ALL")+(BULK_SKU=$G14))*(BULK_START<=4)*(BULK_END>=4)))>0,IFERROR(SUMPRODUCT(((BULK_ENABLED="Y")*((BULK_TIER="ALL")+(BULK_TIER=$F14))*((BULK_SKU="ALL")+(BULK_SKU=$G14))*(BULK_START<=4)*(BULK_END>=4))*IFERROR(BULK_VALUE,0))/MAX(1,SUMPRODUCT(((BULK_ENABLED="Y")*((BULK_TIER="ALL")+(BULK_TIER=$F14))*((BULK_SKU="ALL")+(BULK_SKU=$G14))*(BULK_START<=4)*(BULK_END>=4)))),0),ROUND((INDEX(VELOCITY_TABLE,MATCH($F14,TIER_LIST,0),1))*(IF((4-$I14+1)<=0,0,IF((4-$I14+1)=1,RAMP_W1,IF((4-$I14+1)=2,RAMP_W2,IF((4-$I14+1)=3,RAMP_W3,RAMP_W4PLUS)))))*(INDEX(ACTIVE_MULT_TABLE,1,1))*(1+SUMPRODUCT(SIGN(((ACT_DOOR_SCOPE="ALL")+(ACT_DOOR_SCOPE="TIER_"&$F14)+(ACT_DOOR_SCOPE=$B14)))*SIGN(((ACT_SKU_SCOPE="ALL")+(ACT_SKU_SCOPE=$G14)))*(ACT_START<=4)*(ACT_END>=4)*IFERROR(ACT_UPLIFT-1,0)))*(1+SUMPRODUCT(SIGN(((ACT_DOOR_SCOPE="ALL")+(ACT_DOOR_SCOPE="TIER_"&$F14)+(ACT_DOOR_SCOPE=$B14)))*SIGN(((ACT_SKU_SCOPE="ALL")+(ACT_SKU_SCOPE=$G14)))*(4>ACT_END)*(ACT_END>0)*IFERROR(ACT_POSTLIFT,0))),0))) | N14: =IF(OR($H14<>"Y",5<$I14),0,IF(SUMPRODUCT(((BULK_ENABLED="Y")*((BULK_TIER="ALL")+(BULK_TIER=$F14))*((BULK_SKU="ALL")+(BULK_SKU=$G14))*(BULK_START<=5)*(BULK_END>=5)))>0,IFERROR(SUMPRODUCT(((BULK_ENABLED="Y")*((BULK_TIER="ALL")+(BULK_TIER=$F14))*((BULK_SKU="ALL")+(BULK_SKU=$G14))*(BULK_START<=5)*(BULK_END>=5))*IFERROR(BULK_VALUE,0))/MAX(1,SUMPRODUCT(((BULK_ENABLED="Y")*((BULK_TIER="ALL")+(BULK_TIER=$F14))*((BULK_SKU="ALL")+(BULK_SKU=$G14))*(BULK_START<=5)*(BULK_END>=5)))),0),ROUND((INDEX(VELOCITY_TABLE,MATCH($F14,TIER_LIST,0),1))*(IF((5-$I14+1)<=0,0,IF((5-$I14+1)=1,RAMP_W1,IF((5-$I14+1)=2,RAMP_W2,IF((5-$I14+1)=3,RAMP_W3,RAMP_W4PLUS)))))*(INDEX(ACTIVE_MULT_TABLE,1,1))*(1+SUMPRODUCT(SIGN(((ACT_DOOR_SCOPE="ALL")+(ACT_DOOR_SCOPE="TIER_"&$F14)+(ACT_DOOR_SCOPE=$B14)))*SIGN(((ACT_SKU_SCOPE="ALL")+(ACT_SKU_SCOPE=$G14)))*(ACT_START<=5)*(ACT_END>=5)*IFERROR(ACT_UPLIFT-1,0)))*(1+SUMPRODUCT(SIGN(((ACT_DOOR_SCOPE="ALL")+(ACT_DOOR_SCOPE="TIER_"&$F14)+(ACT_DOOR_SCOPE=$B14)))*SIGN(((ACT_SKU_SCOPE="ALL")+(ACT_SKU_SCOPE=$G14)))*(5>ACT_END)*(ACT_END>0)*IFERROR(ACT_POSTLIFT,0))),0))) | O14: =IF(OR($H14<>"Y",6<$I14),0,IF(SUMPRODUCT(((BULK_ENABLED="Y")*((BULK_TIER="ALL")+(BULK_TIER=$F14))*((BULK_SKU="ALL")+(BULK_SKU=$G14))*(BULK_START<=6)*(BULK_END>=6)))>0,IFERROR(SUMPRODUCT(((BULK_ENABLED="Y")*((BULK_TIER="ALL")+(BULK_TIER=$F14))*((BULK_SKU="ALL")+(BULK_SKU=$G14))*(BULK_START<=6)*(BULK_END>=6))*IFERROR(BULK_VALUE,0))/MAX(1,SUMPRODUCT(((BULK_ENABLED="Y")*((BULK_TIER="ALL")+(BULK_TIER=$F14))*((BULK_SKU="ALL")+(BULK_SKU=$G14))*(BULK_START<=6)*(BULK_END>=6)))),0),ROUND((INDEX(VELOCITY_TABLE,MATCH($F14,TIER_LIST,0),1))*(IF((6-$I14+1)<=0,0,IF((6-$I14+1)=1,RAMP_W1,IF((6-$I14+1)=2,RAMP_W2,IF((6-$I14+1)=3,RAMP_W3,RAMP_W4PLUS)))))*(INDEX(ACTIVE_MULT_TABLE,1,1))*(1+SUMPRODUCT(SIGN(((ACT_DOOR_SCOPE="ALL")+(ACT_DOOR_SCOPE="TIER_"&$F14)+(ACT_DOOR_SCOPE=$B14)))*SIGN(((ACT_SKU_SCOPE="ALL")+(ACT_SKU_SCOPE=$G14)))*(ACT_START<=6)*(ACT_END>=6)*IFERROR(ACT_UPLIFT-1,0)))*(1+SUMPRODUCT(SIGN(((ACT_DOOR_SCOPE="ALL")+(ACT_DOOR_SCOPE="TIER_"&$F14)+(ACT_DOOR_SCOPE=$B14)))*SIGN(((ACT_SKU_SCOPE="ALL")+(ACT_SKU_SCOPE=$G14)))*(6>ACT_END)*(ACT_END>0)*IFERROR(ACT_POSTLIFT,0))),0))) | P14: =IF(OR($H14<>"Y",7<$I14),0,IF(SUMPRODUCT(((BULK_ENABLED="Y")*((BULK_TIER="ALL")+(BULK_TIER=$F14))*((BULK_SKU="ALL")+(BULK_SKU=$G14))*(BULK_START<=7)*(BULK_END>=7)))>0,IFERROR(SUMPRODUCT(((BULK_ENABLED="Y")*((BULK_TIER="ALL")+(BULK_TIER=$F14))*((BULK_SKU="ALL")+(BULK_SKU=$G14))*(BULK_START<=7)*(BULK_END>=7))*IFERROR(BULK_VALUE,0))/MAX(1,SUMPRODUCT(((BULK_ENABLED="Y")*((BULK_TIER="ALL")+(BULK_TIER=$F14))*((BULK_SKU="ALL")+(BULK_SKU=$G14))*(BULK_START<=7)*(BULK_END>=7)))),0),ROUND((INDEX(VELOCITY_TABLE,MATCH($F14,TIER_LIST,0),1))*(IF((7-$I14+1)<=0,0,IF((7-$I14+1)=1,RAMP_W1,IF((7-$I14+1)=2,RAMP_W2,IF((7-$I14+1)=3,RAMP_W3,RAMP_W4PLUS)))))*(INDEX(ACTIVE_MULT_TABLE,1,1))*(1+SUMPRODUCT(SIGN(((ACT_DOOR_SCOPE="ALL")+(ACT_DOOR_SCOPE="TIER_"&$F14)+(ACT_DOOR_SCOPE=$B14)))*SIGN(((ACT_SKU_SCOPE="ALL")+(ACT_SKU_SCOPE=$G14)))*(ACT_START<=7)*(ACT_END>=7)*IFERROR(ACT_UPLIFT-1,0)))*(1+SUMPRODUCT(SIGN(((ACT_DOOR_SCOPE="ALL")+(ACT_DOOR_SCOPE="TIER_"&$F14)+(ACT_DOOR_SCOPE=$B14)))*SIGN(((ACT_SKU_SCOPE="ALL")+(ACT_SKU_SCOPE=$G14)))*(7>ACT_END)*(ACT_END>0)*IFERROR(ACT_POSTLIFT,0))),0))) | Q14: =IF(OR($H14<>"Y",8<$I14),0,IF(SUMPRODUCT(((BULK_ENABLED="Y")*((BULK_TIER="ALL")+(BULK_TIER=$F14))*((BULK_SKU="ALL")+(BULK_SKU=$G14))*(BULK_START<=8)*(BULK_END>=8)))>0,IFERROR(SUMPRODUCT(((BULK_ENABLED="Y")*((BULK_TIER="ALL")+(BULK_TIER=$F14))*((BULK_SKU="ALL")+(BULK_SKU=$G14))*(BULK_START<=8)*(BULK_END>=8))*IFERROR(BULK_VALUE,0))/MAX(1,SUMPRODUCT(((BULK_ENABLED="Y")*((BULK_TIER="ALL")+(BULK_TIER=$F14))*((BULK_SKU="ALL")+(BULK_SKU=$G14))*(BULK_START<=8)*(BULK_END>=8)))),0),ROUND((INDEX(VELOCITY_TABLE,MATCH($F14,TIER_LIST,0),1))*(IF((8-$I14+1)<=0,0,IF((8-$I14+1)=1,RAMP_W1,IF((8-$I14+1)=2,RAMP_W2,IF((8-$I14+1)=3,RAMP_W3,RAMP_W4PLUS)))))*(INDEX(ACTIVE_MULT_TABLE,1,1))*(1+SUMPRODUCT(SIGN(((ACT_DOOR_SCOPE="ALL")+(ACT_DOOR_SCOPE="TIER_"&$F14)+(ACT_DOOR_SCOPE=$B14)))*SIGN(((ACT_SKU_SCOPE="ALL")+(ACT_SKU_SCOPE=$G14)))*(ACT_START<=8)*(ACT_END>=8)*IFERROR(ACT_UPLIFT-1,0)))*(1+SUMPRODUCT(SIGN(((ACT_DOOR_SCOPE="ALL")+(ACT_DOOR_SCOPE="TIER_"&$F14)+(ACT_DOOR_SCOPE=$B14)))*SIGN(((ACT_SKU_SCOPE="ALL")+(ACT_SKU_SCOPE=$G14)))*(8>ACT_END)*(ACT_END>0)*IFERROR(ACT_POSTLIFT,0))),0))) | R14: =IF(OR($H14<>"Y",9<$I14),0,IF(SUMPRODUCT(((BULK_ENABLED="Y")*((BULK_TIER="ALL")+(BULK_TIER=$F14))*((BULK_SKU="ALL")+(BULK_SKU=$G14))*(BULK_START<=9)*(BULK_END>=9)))>0,IFERROR(SUMPRODUCT(((BULK_ENABLED="Y")*((BULK_TIER="ALL")+(BULK_TIER=$F14))*((BULK_SKU="ALL")+(BULK_SKU=$G14))*(BULK_START<=9)*(BULK_END>=9))*IFERROR(BULK_VALUE,0))/MAX(1,SUMPRODUCT(((BULK_ENABLED="Y")*((BULK_TIER="ALL")+(BULK_TIER=$F14))*((BULK_SKU="ALL")+(BULK_SKU=$G14))*(BULK_START<=9)*(BULK_END>=9)))),0),ROUND((INDEX(VELOCITY_TABLE,MATCH($F14,TIER_LIST,0),1))*(IF((9-$I14+1)<=0,0,IF((9-$I14+1)=1,RAMP_W1,IF((9-$I14+1)=2,RAMP_W2,IF((9-$I14+1)=3,RAMP_W3,RAMP_W4PLUS)))))*(INDEX(ACTIVE_MULT_TABLE,1,1))*(1+SUMPRODUCT(SIGN(((ACT_DOOR_SCOPE="ALL")+(ACT_DOOR_SCOPE="TIER_"&$F14)+(ACT_DOOR_SCOPE=$B14)))*SIGN(((ACT_SKU_SCOPE="ALL")+(ACT_SKU_SCOPE=$G14)))*(ACT_START<=9)*(ACT_END>=9)*IFERROR(ACT_UPLIFT-1,0)))*(1+SUMPRODUCT(SIGN(((ACT_DOOR_SCOPE="ALL")+(ACT_DOOR_SCOPE="TIER_"&$F14)+(ACT_DOOR_SCOPE=$B14)))*SIGN(((ACT_SKU_SCOPE="ALL")+(ACT_SKU_SCOPE=$G14)))*(9>ACT_END)*(ACT_END>0)*IFERROR(ACT_POSTLIFT,0))),0))) | S14: =IF(OR($H14<>"Y",10<$I14),0,IF(SUMPRODUCT(((BULK_ENABLED="Y")*((BULK_TIER="ALL")+(BULK_TIER=$F14))*((BULK_SKU="ALL")+(BULK_SKU=$G14))*(BULK_START<=10)*(BULK_END>=10)))>0,IFERROR(SUMPRODUCT(((BULK_ENABLED="Y")*((BULK_TIER="ALL")+(BULK_TIER=$F14))*((BULK_SKU="ALL")+(BULK_SKU=$G14))*(BULK_START<=10)*(BULK_END>=10))*IFERROR(BULK_VALUE,0))/MAX(1,SUMPRODUCT(((BULK_ENABLED="Y")*((BULK_TIER="ALL")+(BULK_TIER=$F14))*((BULK_SKU="ALL")+(BULK_SKU=$G14))*(BULK_START<=10)*(BULK_END>=10)))),0),ROUND((INDEX(VELOCITY_TABLE,MATCH($F14,TIER_LIST,0),1))*(IF((10-$I14+1)<=0,0,IF((10-$I14+1)=1,RAMP_W1,IF((10-$I14+1)=2,RAMP_W2,IF((10-$I14+1)=3,RAMP_W3,RAMP_W4PLUS)))))*(INDEX(ACTIVE_MULT_TABLE,1,1))*(1+SUMPRODUCT(SIGN(((ACT_DOOR_SCOPE="ALL")+(ACT_DOOR_SCOPE="TIER_"&$F14)+(ACT_DOOR_SCOPE=$B14)))*SIGN(((ACT_SKU_SCOPE="ALL")+(ACT_SKU_SCOPE=$G14)))*(ACT_START<=10)*(ACT_END>=10)*IFERROR(ACT_UPLIFT-1,0)))*(1+SUMPRODUCT(SIGN(((ACT_DOOR_SCOPE="ALL")+(ACT_DOOR_SCOPE="TIER_"&$F14)+(ACT_DOOR_SCOPE=$B14)))*SIGN(((ACT_SKU_SCOPE="ALL")+(ACT_SKU_SCOPE=$G14)))*(10>ACT_END)*(ACT_END>0)*IFERROR(ACT_POSTLIFT,0))),0))) | T14: =IF(OR($H14<>"Y",11<$I14),0,IF(SUMPRODUCT(((BULK_ENABLED="Y")*((BULK_TIER="ALL")+(BULK_TIER=$F14))*((BULK_SKU="ALL")+(BULK_SKU=$G14))*(BULK_START<=11)*(BULK_END>=11)))>0,IFERROR(SUMPRODUCT(((BULK_ENABLED="Y")*((BULK_TIER="ALL")+(BULK_TIER=$F14))*((BULK_SKU="ALL")+(BULK_SKU=$G14))*(BULK_START<=11)*(BULK_END>=11))*IFERROR(BULK_VALUE,0))/MAX(1,SUMPRODUCT(((BULK_ENABLED="Y")*((BULK_TIER="ALL")+(BULK_TIER=$F14))*((BULK_SKU="ALL")+(BULK_SKU=$G14))*(BULK_START<=11)*(BULK_END>=11)))),0),ROUND((INDEX(VELOCITY_TABLE,MATCH($F14,TIER_LIST,0),1))*(IF((11-$I14+1)<=0,0,IF((11-$I14+1)=1,RAMP_W1,IF((11-$I14+1)=2,RAMP_W2,IF((11-$I14+1)=3,RAMP_W3,RAMP_W4PLUS)))))*(INDEX(ACTIVE_MULT_TABLE,1,1))*(1+SUMPRODUCT(SIGN(((ACT_DOOR_SCOPE="ALL")+(ACT_DOOR_SCOPE="TIER_"&$F14)+(ACT_DOOR_SCOPE=$B14)))*SIGN(((ACT_SKU_SCOPE="ALL")+(ACT_SKU_SCOPE=$G14)))*(ACT_START<=11)*(ACT_END>=11)*IFERROR(ACT_UPLIFT-1,0)))*(1+SUMPRODUCT(SIGN(((ACT_DOOR_SCOPE="ALL")+(ACT_DOOR_SCOPE="TIER_"&$F14)+(ACT_DOOR_SCOPE=$B14)))*SIGN(((ACT_SKU_SCOPE="ALL")+(ACT_SKU_SCOPE=$G14)))*(11>ACT_END)*(ACT_END>0)*IFERROR(ACT_POSTLIFT,0))),0))) | U14: =IF(OR($H14<>"Y",12<$I14),0,IF(SUMPRODUCT(((BULK_ENABLED="Y")*((BULK_TIER="ALL")+(BULK_TIER=$F14))*((BULK_SKU="ALL")+(BULK_SKU=$G14))*(BULK_START<=12)*(BULK_END>=12)))>0,IFERROR(SUMPRODUCT(((BULK_ENABLED="Y")*((BULK_TIER="ALL")+(BULK_TIER=$F14))*((BULK_SKU="ALL")+(BULK_SKU=$G14))*(BULK_START<=12)*(BULK_END>=12))*IFERROR(BULK_VALUE,0))/MAX(1,SUMPRODUCT(((BULK_ENABLED="Y")*((BULK_TIER="ALL")+(BULK_TIER=$F14))*((BULK_SKU="ALL")+(BULK_SKU=$G14))*(BULK_START<=12)*(BULK_END>=12)))),0),ROUND((INDEX(VELOCITY_TABLE,MATCH($F14,TIER_LIST,0),1))*(IF((12-$I14+1)<=0,0,IF((12-$I14+1)=1,RAMP_W1,IF((12-$I14+1)=2,RAMP_W2,IF((12-$I14+1)=3,RAMP_W3,RAMP_W4PLUS)))))*(INDEX(ACTIVE_MULT_TABLE,1,1))*(1+SUMPRODUCT(SIGN(((ACT_DOOR_SCOPE="ALL")+(ACT_DOOR_SCOPE="TIER_"&$F14)+(ACT_DOOR_SCOPE=$B14)))*SIGN(((ACT_SKU_SCOPE="ALL")+(ACT_SKU_SCOPE=$G14)))*(ACT_START<=12)*(ACT_END>=12)*IFERROR(ACT_UPLIFT-1,0)))*(1+SUMPRODUCT(SIGN(((ACT_DOOR_SCOPE="ALL")+(ACT_DOOR_SCOPE="TIER_"&$F14)+(ACT_DOOR_SCOPE=$B14)))*SIGN(((ACT_SKU_SCOPE="ALL")+(ACT_SKU_SCOPE=$G14)))*(12>ACT_END)*(ACT_END>0)*IFERROR(ACT_POSTLIFT,0))),0))) | V14: =IF(OR($H14<>"Y",13<$I14),0,IF(SUMPRODUCT(((BULK_ENABLED="Y")*((BULK_TIER="ALL")+(BULK_TIER=$F14))*((BULK_SKU="ALL")+(BULK_SKU=$G14))*(BULK_START<=13)*(BULK_END>=13)))>0,IFERROR(SUMPRODUCT(((BULK_ENABLED="Y")*((BULK_TIER="ALL")+(BULK_TIER=$F14))*((BULK_SKU="ALL")+(BULK_SKU=$G14))*(BULK_START<=13)*(BULK_END>=13))*IFERROR(BULK_VALUE,0))/MAX(1,SUMPRODUCT(((BULK_ENABLED="Y")*((BULK_TIER="ALL")+(BULK_TIER=$F14))*((BULK_SKU="ALL")+(BULK_SKU=$G14))*(BULK_START<=13)*(BULK_END>=13)))),0),ROUND((INDEX(VELOCITY_TABLE,MATCH($F14,TIER_LIST,0),1))*(IF((13-$I14+1)<=0,0,IF((13-$I14+1)=1,RAMP_W1,IF((13-$I14+1)=2,RAMP_W2,IF((13-$I14+1)=3,RAMP_W3,RAMP_W4PLUS)))))*(INDEX(ACTIVE_MULT_TABLE,1,1))*(1+SUMPRODUCT(SIGN(((ACT_DOOR_SCOPE="ALL")+(ACT_DOOR_SCOPE="TIER_"&$F14)+(ACT_DOOR_SCOPE=$B14)))*SIGN(((ACT_SKU_SCOPE="ALL")+(ACT_SKU_SCOPE=$G14)))*(ACT_START<=13)*(ACT_END>=13)*IFERROR(ACT_UPLIFT-1,0)))*(1+SUMPRODUCT(SIGN(((ACT_DOOR_SCOPE="ALL")+(ACT_DOOR_SCOPE="TIER_"&$F14)+(ACT_DOOR_SCOPE=$B14)))*SIGN(((ACT_SKU_SCOPE="ALL")+(ACT_SKU_SCOPE=$G14)))*(13>ACT_END)*(ACT_END>0)*IFERROR(ACT_POSTLIFT,0))),0)))
A15: R0011 | B15: =Doors!$A$8 | C15: =Doors!$C$8 | D15: =Doors!$B$8 | E15: =Doors!$E$8 | F15: =Doors!$F$8 | G15: Pineapple Passion Fruit | H15: =Doors!$H$8 | I15: =Doors!$J$8 | J15: =IF(OR($H15<>"Y",1<$I15),0,IF(SUMPRODUCT(((BULK_ENABLED="Y")*((BULK_TIER="ALL")+(BULK_TIER=$F15))*((BULK_SKU="ALL")+(BULK_SKU=$G15))*(BULK_START<=1)*(BULK_END>=1)))>0,IFERROR(SUMPRODUCT(((BULK_ENABLED="Y")*((BULK_TIER="ALL")+(BULK_TIER=$F15))*((BULK_SKU="ALL")+(BULK_SKU=$G15))*(BULK_START<=1)*(BULK_END>=1))*IFERROR(BULK_VALUE,0))/MAX(1,SUMPRODUCT(((BULK_ENABLED="Y")*((BULK_TIER="ALL")+(BULK_TIER=$F15))*((BULK_SKU="ALL")+(BULK_SKU=$G15))*(BULK_START<=1)*(BULK_END>=1)))),0),ROUND((INDEX(VELOCITY_TABLE,MATCH($F15,TIER_LIST,0),2))*(IF((1-$I15+1)<=0,0,IF((1-$I15+1)=1,RAMP_W1,IF((1-$I15+1)=2,RAMP_W2,IF((1-$I15+1)=3,RAMP_W3,RAMP_W4PLUS)))))*(INDEX(ACTIVE_MULT_TABLE,2,1))*(1+SUMPRODUCT(SIGN(((ACT_DOOR_SCOPE="ALL")+(ACT_DOOR_SCOPE="TIER_"&$F15)+(ACT_DOOR_SCOPE=$B15)))*SIGN(((ACT_SKU_SCOPE="ALL")+(ACT_SKU_SCOPE=$G15)))*(ACT_START<=1)*(ACT_END>=1)*IFERROR(ACT_UPLIFT-1,0)))*(1+SUMPRODUCT(SIGN(((ACT_DOOR_SCOPE="ALL")+(ACT_DOOR_SCOPE="TIER_"&$F15)+(ACT_DOOR_SCOPE=$B15)))*SIGN(((ACT_SKU_SCOPE="ALL")+(ACT_SKU_SCOPE=$G15)))*(1>ACT_END)*(ACT_END>0)*IFERROR(ACT_POSTLIFT,0))),0))) | K15: =IF(OR($H15<>"Y",2<$I15),0,IF(SUMPRODUCT(((BULK_ENABLED="Y")*((BULK_TIER="ALL")+(BULK_TIER=$F15))*((BULK_SKU="ALL")+(BULK_SKU=$G15))*(BULK_START<=2)*(BULK_END>=2)))>0,IFERROR(SUMPRODUCT(((BULK_ENABLED="Y")*((BULK_TIER="ALL")+(BULK_TIER=$F15))*((BULK_SKU="ALL")+(BULK_SKU=$G15))*(BULK_START<=2)*(BULK_END>=2))*IFERROR(BULK_VALUE,0))/MAX(1,SUMPRODUCT(((BULK_ENABLED="Y")*((BULK_TIER="ALL")+(BULK_TIER=$F15))*((BULK_SKU="ALL")+(BULK_SKU=$G15))*(BULK_START<=2)*(BULK_END>=2)))),0),ROUND((INDEX(VELOCITY_TABLE,MATCH($F15,TIER_LIST,0),2))*(IF((2-$I15+1)<=0,0,IF((2-$I15+1)=1,RAMP_W1,IF((2-$I15+1)=2,RAMP_W2,IF((2-$I15+1)=3,RAMP_W3,RAMP_W4PLUS)))))*(INDEX(ACTIVE_MULT_TABLE,2,1))*(1+SUMPRODUCT(SIGN(((ACT_DOOR_SCOPE="ALL")+(ACT_DOOR_SCOPE="TIER_"&$F15)+(ACT_DOOR_SCOPE=$B15)))*SIGN(((ACT_SKU_SCOPE="ALL")+(ACT_SKU_SCOPE=$G15)))*(ACT_START<=2)*(ACT_END>=2)*IFERROR(ACT_UPLIFT-1,0)))*(1+SUMPRODUCT(SIGN(((ACT_DOOR_SCOPE="ALL")+(ACT_DOOR_SCOPE="TIER_"&$F15)+(ACT_DOOR_SCOPE=$B15)))*SIGN(((ACT_SKU_SCOPE="ALL")+(ACT_SKU_SCOPE=$G15)))*(2>ACT_END)*(ACT_END>0)*IFERROR(ACT_POSTLIFT,0))),0))) | L15: =IF(OR($H15<>"Y",3<$I15),0,IF(SUMPRODUCT(((BULK_ENABLED="Y")*((BULK_TIER="ALL")+(BULK_TIER=$F15))*((BULK_SKU="ALL")+(BULK_SKU=$G15))*(BULK_START<=3)*(BULK_END>=3)))>0,IFERROR(SUMPRODUCT(((BULK_ENABLED="Y")*((BULK_TIER="ALL")+(BULK_TIER=$F15))*((BULK_SKU="ALL")+(BULK_SKU=$G15))*(BULK_START<=3)*(BULK_END>=3))*IFERROR(BULK_VALUE,0))/MAX(1,SUMPRODUCT(((BULK_ENABLED="Y")*((BULK_TIER="ALL")+(BULK_TIER=$F15))*((BULK_SKU="ALL")+(BULK_SKU=$G15))*(BULK_START<=3)*(BULK_END>=3)))),0),ROUND((INDEX(VELOCITY_TABLE,MATCH($F15,TIER_LIST,0),2))*(IF((3-$I15+1)<=0,0,IF((3-$I15+1)=1,RAMP_W1,IF((3-$I15+1)=2,RAMP_W2,IF((3-$I15+1)=3,RAMP_W3,RAMP_W4PLUS)))))*(INDEX(ACTIVE_MULT_TABLE,2,1))*(1+SUMPRODUCT(SIGN(((ACT_DOOR_SCOPE="ALL")+(ACT_DOOR_SCOPE="TIER_"&$F15)+(ACT_DOOR_SCOPE=$B15)))*SIGN(((ACT_SKU_SCOPE="ALL")+(ACT_SKU_SCOPE=$G15)))*(ACT_START<=3)*(ACT_END>=3)*IFERROR(ACT_UPLIFT-1,0)))*(1+SUMPRODUCT(SIGN(((ACT_DOOR_SCOPE="ALL")+(ACT_DOOR_SCOPE="TIER_"&$F15)+(ACT_DOOR_SCOPE=$B15)))*SIGN(((ACT_SKU_SCOPE="ALL")+(ACT_SKU_SCOPE=$G15)))*(3>ACT_END)*(ACT_END>0)*IFERROR(ACT_POSTLIFT,0))),0))) | M15: =IF(OR($H15<>"Y",4<$I15),0,IF(SUMPRODUCT(((BULK_ENABLED="Y")*((BULK_TIER="ALL")+(BULK_TIER=$F15))*((BULK_SKU="ALL")+(BULK_SKU=$G15))*(BULK_START<=4)*(BULK_END>=4)))>0,IFERROR(SUMPRODUCT(((BULK_ENABLED="Y")*((BULK_TIER="ALL")+(BULK_TIER=$F15))*((BULK_SKU="ALL")+(BULK_SKU=$G15))*(BULK_START<=4)*(BULK_END>=4))*IFERROR(BULK_VALUE,0))/MAX(1,SUMPRODUCT(((BULK_ENABLED="Y")*((BULK_TIER="ALL")+(BULK_TIER=$F15))*((BULK_SKU="ALL")+(BULK_SKU=$G15))*(BULK_START<=4)*(BULK_END>=4)))),0),ROUND((INDEX(VELOCITY_TABLE,MATCH($F15,TIER_LIST,0),2))*(IF((4-$I15+1)<=0,0,IF((4-$I15+1)=1,RAMP_W1,IF((4-$I15+1)=2,RAMP_W2,IF((4-$I15+1)=3,RAMP_W3,RAMP_W4PLUS)))))*(INDEX(ACTIVE_MULT_TABLE,2,1))*(1+SUMPRODUCT(SIGN(((ACT_DOOR_SCOPE="ALL")+(ACT_DOOR_SCOPE="TIER_"&$F15)+(ACT_DOOR_SCOPE=$B15)))*SIGN(((ACT_SKU_SCOPE="ALL")+(ACT_SKU_SCOPE=$G15)))*(ACT_START<=4)*(ACT_END>=4)*IFERROR(ACT_UPLIFT-1,0)))*(1+SUMPRODUCT(SIGN(((ACT_DOOR_SCOPE="ALL")+(ACT_DOOR_SCOPE="TIER_"&$F15)+(ACT_DOOR_SCOPE=$B15)))*SIGN(((ACT_SKU_SCOPE="ALL")+(ACT_SKU_SCOPE=$G15)))*(4>ACT_END)*(ACT_END>0)*IFERROR(ACT_POSTLIFT,0))),0))) | N15: =IF(OR($H15<>"Y",5<$I15),0,IF(SUMPRODUCT(((BULK_ENABLED="Y")*((BULK_TIER="ALL")+(BULK_TIER=$F15))*((BULK_SKU="ALL")+(BULK_SKU=$G15))*(BULK_START<=5)*(BULK_END>=5)))>0,IFERROR(SUMPRODUCT(((BULK_ENABLED="Y")*((BULK_TIER="ALL")+(BULK_TIER=$F15))*((BULK_SKU="ALL")+(BULK_SKU=$G15))*(BULK_START<=5)*(BULK_END>=5))*IFERROR(BULK_VALUE,0))/MAX(1,SUMPRODUCT(((BULK_ENABLED="Y")*((BULK_TIER="ALL")+(BULK_TIER=$F15))*((BULK_SKU="ALL")+(BULK_SKU=$G15))*(BULK_START<=5)*(BULK_END>=5)))),0),ROUND((INDEX(VELOCITY_TABLE,MATCH($F15,TIER_LIST,0),2))*(IF((5-$I15+1)<=0,0,IF((5-$I15+1)=1,RAMP_W1,IF((5-$I15+1)=2,RAMP_W2,IF((5-$I15+1)=3,RAMP_W3,RAMP_W4PLUS)))))*(INDEX(ACTIVE_MULT_TABLE,2,1))*(1+SUMPRODUCT(SIGN(((ACT_DOOR_SCOPE="ALL")+(ACT_DOOR_SCOPE="TIER_"&$F15)+(ACT_DOOR_SCOPE=$B15)))*SIGN(((ACT_SKU_SCOPE="ALL")+(ACT_SKU_SCOPE=$G15)))*(ACT_START<=5)*(ACT_END>=5)*IFERROR(ACT_UPLIFT-1,0)))*(1+SUMPRODUCT(SIGN(((ACT_DOOR_SCOPE="ALL")+(ACT_DOOR_SCOPE="TIER_"&$F15)+(ACT_DOOR_SCOPE=$B15)))*SIGN(((ACT_SKU_SCOPE="ALL")+(ACT_SKU_SCOPE=$G15)))*(5>ACT_END)*(ACT_END>0)*IFERROR(ACT_POSTLIFT,0))),0))) | O15: =IF(OR($H15<>"Y",6<$I15),0,IF(SUMPRODUCT(((BULK_ENABLED="Y")*((BULK_TIER="ALL")+(BULK_TIER=$F15))*((BULK_SKU="ALL")+(BULK_SKU=$G15))*(BULK_START<=6)*(BULK_END>=6)))>0,IFERROR(SUMPRODUCT(((BULK_ENABLED="Y")*((BULK_TIER="ALL")+(BULK_TIER=$F15))*((BULK_SKU="ALL")+(BULK_SKU=$G15))*(BULK_START<=6)*(BULK_END>=6))*IFERROR(BULK_VALUE,0))/MAX(1,SUMPRODUCT(((BULK_ENABLED="Y")*((BULK_TIER="ALL")+(BULK_TIER=$F15))*((BULK_SKU="ALL")+(BULK_SKU=$G15))*(BULK_START<=6)*(BULK_END>=6)))),0),ROUND((INDEX(VELOCITY_TABLE,MATCH($F15,TIER_LIST,0),2))*(IF((6-$I15+1)<=0,0,IF((6-$I15+1)=1,RAMP_W1,IF((6-$I15+1)=2,RAMP_W2,IF((6-$I15+1)=3,RAMP_W3,RAMP_W4PLUS)))))*(INDEX(ACTIVE_MULT_TABLE,2,1))*(1+SUMPRODUCT(SIGN(((ACT_DOOR_SCOPE="ALL")+(ACT_DOOR_SCOPE="TIER_"&$F15)+(ACT_DOOR_SCOPE=$B15)))*SIGN(((ACT_SKU_SCOPE="ALL")+(ACT_SKU_SCOPE=$G15)))*(ACT_START<=6)*(ACT_END>=6)*IFERROR(ACT_UPLIFT-1,0)))*(1+SUMPRODUCT(SIGN(((ACT_DOOR_SCOPE="ALL")+(ACT_DOOR_SCOPE="TIER_"&$F15)+(ACT_DOOR_SCOPE=$B15)))*SIGN(((ACT_SKU_SCOPE="ALL")+(ACT_SKU_SCOPE=$G15)))*(6>ACT_END)*(ACT_END>0)*IFERROR(ACT_POSTLIFT,0))),0))) | P15: =IF(OR($H15<>"Y",7<$I15),0,IF(SUMPRODUCT(((BULK_ENABLED="Y")*((BULK_TIER="ALL")+(BULK_TIER=$F15))*((BULK_SKU="ALL")+(BULK_SKU=$G15))*(BULK_START<=7)*(BULK_END>=7)))>0,IFERROR(SUMPRODUCT(((BULK_ENABLED="Y")*((BULK_TIER="ALL")+(BULK_TIER=$F15))*((BULK_SKU="ALL")+(BULK_SKU=$G15))*(BULK_START<=7)*(BULK_END>=7))*IFERROR(BULK_VALUE,0))/MAX(1,SUMPRODUCT(((BULK_ENABLED="Y")*((BULK_TIER="ALL")+(BULK_TIER=$F15))*((BULK_SKU="ALL")+(BULK_SKU=$G15))*(BULK_START<=7)*(BULK_END>=7)))),0),ROUND((INDEX(VELOCITY_TABLE,MATCH($F15,TIER_LIST,0),2))*(IF((7-$I15+1)<=0,0,IF((7-$I15+1)=1,RAMP_W1,IF((7-$I15+1)=2,RAMP_W2,IF((7-$I15+1)=3,RAMP_W3,RAMP_W4PLUS)))))*(INDEX(ACTIVE_MULT_TABLE,2,1))*(1+SUMPRODUCT(SIGN(((ACT_DOOR_SCOPE="ALL")+(ACT_DOOR_SCOPE="TIER_"&$F15)+(ACT_DOOR_SCOPE=$B15)))*SIGN(((ACT_SKU_SCOPE="ALL")+(ACT_SKU_SCOPE=$G15)))*(ACT_START<=7)*(ACT_END>=7)*IFERROR(ACT_UPLIFT-1,0)))*(1+SUMPRODUCT(SIGN(((ACT_DOOR_SCOPE="ALL")+(ACT_DOOR_SCOPE="TIER_"&$F15)+(ACT_DOOR_SCOPE=$B15)))*SIGN(((ACT_SKU_SCOPE="ALL")+(ACT_SKU_SCOPE=$G15)))*(7>ACT_END)*(ACT_END>0)*IFERROR(ACT_POSTLIFT,0))),0))) | Q15: =IF(OR($H15<>"Y",8<$I15),0,IF(SUMPRODUCT(((BULK_ENABLED="Y")*((BULK_TIER="ALL")+(BULK_TIER=$F15))*((BULK_SKU="ALL")+(BULK_SKU=$G15))*(BULK_START<=8)*(BULK_END>=8)))>0,IFERROR(SUMPRODUCT(((BULK_ENABLED="Y")*((BULK_TIER="ALL")+(BULK_TIER=$F15))*((BULK_SKU="ALL")+(BULK_SKU=$G15))*(BULK_START<=8)*(BULK_END>=8))*IFERROR(BULK_VALUE,0))/MAX(1,SUMPRODUCT(((BULK_ENABLED="Y")*((BULK_TIER="ALL")+(BULK_TIER=$F15))*((BULK_SKU="ALL")+(BULK_SKU=$G15))*(BULK_START<=8)*(BULK_END>=8)))),0),ROUND((INDEX(VELOCITY_TABLE,MATCH($F15,TIER_LIST,0),2))*(IF((8-$I15+1)<=0,0,IF((8-$I15+1)=1,RAMP_W1,IF((8-$I15+1)=2,RAMP_W2,IF((8-$I15+1)=3,RAMP_W3,RAMP_W4PLUS)))))*(INDEX(ACTIVE_MULT_TABLE,2,1))*(1+SUMPRODUCT(SIGN(((ACT_DOOR_SCOPE="ALL")+(ACT_DOOR_SCOPE="TIER_"&$F15)+(ACT_DOOR_SCOPE=$B15)))*SIGN(((ACT_SKU_SCOPE="ALL")+(ACT_SKU_SCOPE=$G15)))*(ACT_START<=8)*(ACT_END>=8)*IFERROR(ACT_UPLIFT-1,0)))*(1+SUMPRODUCT(SIGN(((ACT_DOOR_SCOPE="ALL")+(ACT_DOOR_SCOPE="TIER_"&$F15)+(ACT_DOOR_SCOPE=$B15)))*SIGN(((ACT_SKU_SCOPE="ALL")+(ACT_SKU_SCOPE=$G15)))*(8>ACT_END)*(ACT_END>0)*IFERROR(ACT_POSTLIFT,0))),0))) | R15: =IF(OR($H15<>"Y",9<$I15),0,IF(SUMPRODUCT(((BULK_ENABLED="Y")*((BULK_TIER="ALL")+(BULK_TIER=$F15))*((BULK_SKU="ALL")+(BULK_SKU=$G15))*(BULK_START<=9)*(BULK_END>=9)))>0,IFERROR(SUMPRODUCT(((BULK_ENABLED="Y")*((BULK_TIER="ALL")+(BULK_TIER=$F15))*((BULK_SKU="ALL")+(BULK_SKU=$G15))*(BULK_START<=9)*(BULK_END>=9))*IFERROR(BULK_VALUE,0))/MAX(1,SUMPRODUCT(((BULK_ENABLED="Y")*((BULK_TIER="ALL")+(BULK_TIER=$F15))*((BULK_SKU="ALL")+(BULK_SKU=$G15))*(BULK_START<=9)*(BULK_END>=9)))),0),ROUND((INDEX(VELOCITY_TABLE,MATCH($F15,TIER_LIST,0),2))*(IF((9-$I15+1)<=0,0,IF((9-$I15+1)=1,RAMP_W1,IF((9-$I15+1)=2,RAMP_W2,IF((9-$I15+1)=3,RAMP_W3,RAMP_W4PLUS)))))*(INDEX(ACTIVE_MULT_TABLE,2,1))*(1+SUMPRODUCT(SIGN(((ACT_DOOR_SCOPE="ALL")+(ACT_DOOR_SCOPE="TIER_"&$F15)+(ACT_DOOR_SCOPE=$B15)))*SIGN(((ACT_SKU_SCOPE="ALL")+(ACT_SKU_SCOPE=$G15)))*(ACT_START<=9)*(ACT_END>=9)*IFERROR(ACT_UPLIFT-1,0)))*(1+SUMPRODUCT(SIGN(((ACT_DOOR_SCOPE="ALL")+(ACT_DOOR_SCOPE="TIER_"&$F15)+(ACT_DOOR_SCOPE=$B15)))*SIGN(((ACT_SKU_SCOPE="ALL")+(ACT_SKU_SCOPE=$G15)))*(9>ACT_END)*(ACT_END>0)*IFERROR(ACT_POSTLIFT,0))),0))) | S15: =IF(OR($H15<>"Y",10<$I15),0,IF(SUMPRODUCT(((BULK_ENABLED="Y")*((BULK_TIER="ALL")+(BULK_TIER=$F15))*((BULK_SKU="ALL")+(BULK_SKU=$G15))*(BULK_START<=10)*(BULK_END>=10)))>0,IFERROR(SUMPRODUCT(((BULK_ENABLED="Y")*((BULK_TIER="ALL")+(BULK_TIER=$F15))*((BULK_SKU="ALL")+(BULK_SKU=$G15))*(BULK_START<=10)*(BULK_END>=10))*IFERROR(BULK_VALUE,0))/MAX(1,SUMPRODUCT(((BULK_ENABLED="Y")*((BULK_TIER="ALL")+(BULK_TIER=$F15))*((BULK_SKU="ALL")+(BULK_SKU=$G15))*(BULK_START<=10)*(BULK_END>=10)))),0),ROUND((INDEX(VELOCITY_TABLE,MATCH($F15,TIER_LIST,0),2))*(IF((10-$I15+1)<=0,0,IF((10-$I15+1)=1,RAMP_W1,IF((10-$I15+1)=2,RAMP_W2,IF((10-$I15+1)=3,RAMP_W3,RAMP_W4PLUS)))))*(INDEX(ACTIVE_MULT_TABLE,2,1))*(1+SUMPRODUCT(SIGN(((ACT_DOOR_SCOPE="ALL")+(ACT_DOOR_SCOPE="TIER_"&$F15)+(ACT_DOOR_SCOPE=$B15)))*SIGN(((ACT_SKU_SCOPE="ALL")+(ACT_SKU_SCOPE=$G15)))*(ACT_START<=10)*(ACT_END>=10)*IFERROR(ACT_UPLIFT-1,0)))*(1+SUMPRODUCT(SIGN(((ACT_DOOR_SCOPE="ALL")+(ACT_DOOR_SCOPE="TIER_"&$F15)+(ACT_DOOR_SCOPE=$B15)))*SIGN(((ACT_SKU_SCOPE="ALL")+(ACT_SKU_SCOPE=$G15)))*(10>ACT_END)*(ACT_END>0)*IFERROR(ACT_POSTLIFT,0))),0))) | T15: =IF(OR($H15<>"Y",11<$I15),0,IF(SUMPRODUCT(((BULK_ENABLED="Y")*((BULK_TIER="ALL")+(BULK_TIER=$F15))*((BULK_SKU="ALL")+(BULK_SKU=$G15))*(BULK_START<=11)*(BULK_END>=11)))>0,IFERROR(SUMPRODUCT(((BULK_ENABLED="Y")*((BULK_TIER="ALL")+(BULK_TIER=$F15))*((BULK_SKU="ALL")+(BULK_SKU=$G15))*(BULK_START<=11)*(BULK_END>=11))*IFERROR(BULK_VALUE,0))/MAX(1,SUMPRODUCT(((BULK_ENABLED="Y")*((BULK_TIER="ALL")+(BULK_TIER=$F15))*((BULK_SKU="ALL")+(BULK_SKU=$G15))*(BULK_START<=11)*(BULK_END>=11)))),0),ROUND((INDEX(VELOCITY_TABLE,MATCH($F15,TIER_LIST,0),2))*(IF((11-$I15+1)<=0,0,IF((11-$I15+1)=1,RAMP_W1,IF((11-$I15+1)=2,RAMP_W2,IF((11-$I15+1)=3,RAMP_W3,RAMP_W4PLUS)))))*(INDEX(ACTIVE_MULT_TABLE,2,1))*(1+SUMPRODUCT(SIGN(((ACT_DOOR_SCOPE="ALL")+(ACT_DOOR_SCOPE="TIER_"&$F15)+(ACT_DOOR_SCOPE=$B15)))*SIGN(((ACT_SKU_SCOPE="ALL")+(ACT_SKU_SCOPE=$G15)))*(ACT_START<=11)*(ACT_END>=11)*IFERROR(ACT_UPLIFT-1,0)))*(1+SUMPRODUCT(SIGN(((ACT_DOOR_SCOPE="ALL")+(ACT_DOOR_SCOPE="TIER_"&$F15)+(ACT_DOOR_SCOPE=$B15)))*SIGN(((ACT_SKU_SCOPE="ALL")+(ACT_SKU_SCOPE=$G15)))*(11>ACT_END)*(ACT_END>0)*IFERROR(ACT_POSTLIFT,0))),0))) | U15: =IF(OR($H15<>"Y",12<$I15),0,IF(SUMPRODUCT(((BULK_ENABLED="Y")*((BULK_TIER="ALL")+(BULK_TIER=$F15))*((BULK_SKU="ALL")+(BULK_SKU=$G15))*(BULK_START<=12)*(BULK_END>=12)))>0,IFERROR(SUMPRODUCT(((BULK_ENABLED="Y")*((BULK_TIER="ALL")+(BULK_TIER=$F15))*((BULK_SKU="ALL")+(BULK_SKU=$G15))*(BULK_START<=12)*(BULK_END>=12))*IFERROR(BULK_VALUE,0))/MAX(1,SUMPRODUCT(((BULK_ENABLED="Y")*((BULK_TIER="ALL")+(BULK_TIER=$F15))*((BULK_SKU="ALL")+(BULK_SKU=$G15))*(BULK_START<=12)*(BULK_END>=12)))),0),ROUND((INDEX(VELOCITY_TABLE,MATCH($F15,TIER_LIST,0),2))*(IF((12-$I15+1)<=0,0,IF((12-$I15+1)=1,RAMP_W1,IF((12-$I15+1)=2,RAMP_W2,IF((12-$I15+1)=3,RAMP_W3,RAMP_W4PLUS)))))*(INDEX(ACTIVE_MULT_TABLE,2,1))*(1+SUMPRODUCT(SIGN(((ACT_DOOR_SCOPE="ALL")+(ACT_DOOR_SCOPE="TIER_"&$F15)+(ACT_DOOR_SCOPE=$B15)))*SIGN(((ACT_SKU_SCOPE="ALL")+(ACT_SKU_SCOPE=$G15)))*(ACT_START<=12)*(ACT_END>=12)*IFERROR(ACT_UPLIFT-1,0)))*(1+SUMPRODUCT(SIGN(((ACT_DOOR_SCOPE="ALL")+(ACT_DOOR_SCOPE="TIER_"&$F15)+(ACT_DOOR_SCOPE=$B15)))*SIGN(((ACT_SKU_SCOPE="ALL")+(ACT_SKU_SCOPE=$G15)))*(12>ACT_END)*(ACT_END>0)*IFERROR(ACT_POSTLIFT,0))),0))) | V15: =IF(OR($H15<>"Y",13<$I15),0,IF(SUMPRODUCT(((BULK_ENABLED="Y")*((BULK_TIER="ALL")+(BULK_TIER=$F15))*((BULK_SKU="ALL")+(BULK_SKU=$G15))*(BULK_START<=13)*(BULK_END>=13)))>0,IFERROR(SUMPRODUCT(((BULK_ENABLED="Y")*((BULK_TIER="ALL")+(BULK_TIER=$F15))*((BULK_SKU="ALL")+(BULK_SKU=$G15))*(BULK_START<=13)*(BULK_END>=13))*IFERROR(BULK_VALUE,0))/MAX(1,SUMPRODUCT(((BULK_ENABLED="Y")*((BULK_TIER="ALL")+(BULK_TIER=$F15))*((BULK_SKU="ALL")+(BULK_SKU=$G15))*(BULK_START<=13)*(BULK_END>=13)))),0),ROUND((INDEX(VELOCITY_TABLE,MATCH($F15,TIER_LIST,0),2))*(IF((13-$I15+1)<=0,0,IF((13-$I15+1)=1,RAMP_W1,IF((13-$I15+1)=2,RAMP_W2,IF((13-$I15+1)=3,RAMP_W3,RAMP_W4PLUS)))))*(INDEX(ACTIVE_MULT_TABLE,2,1))*(1+SUMPRODUCT(SIGN(((ACT_DOOR_SCOPE="ALL")+(ACT_DOOR_SCOPE="TIER_"&$F15)+(ACT_DOOR_SCOPE=$B15)))*SIGN(((ACT_SKU_SCOPE="ALL")+(ACT_SKU_SCOPE=$G15)))*(ACT_START<=13)*(ACT_END>=13)*IFERROR(ACT_UPLIFT-1,0)))*(1+SUMPRODUCT(SIGN(((ACT_DOOR_SCOPE="ALL")+(ACT_DOOR_SCOPE="TIER_"&$F15)+(ACT_DOOR_SCOPE=$B15)))*SIGN(((ACT_SKU_SCOPE="ALL")+(ACT_SKU_SCOPE=$G15)))*(13>ACT_END)*(ACT_END>0)*IFERROR(ACT_POSTLIFT,0))),0)))
A16: R0012 | B16: =Doors!$A$8 | C16: =Doors!$C$8 | D16: =Doors!$B$8 | E16: =Doors!$E$8 | F16: =Doors!$F$8 | G16: Raspberry | H16: =Doors!$I$8 | I16: =Doors!$J$8 | J16: =IF(OR($H16<>"Y",1<$I16),0,IF(SUMPRODUCT(((BULK_ENABLED="Y")*((BULK_TIER="ALL")+(BULK_TIER=$F16))*((BULK_SKU="ALL")+(BULK_SKU=$G16))*(BULK_START<=1)*(BULK_END>=1)))>0,IFERROR(SUMPRODUCT(((BULK_ENABLED="Y")*((BULK_TIER="ALL")+(BULK_TIER=$F16))*((BULK_SKU="ALL")+(BULK_SKU=$G16))*(BULK_START<=1)*(BULK_END>=1))*IFERROR(BULK_VALUE,0))/MAX(1,SUMPRODUCT(((BULK_ENABLED="Y")*((BULK_TIER="ALL")+(BULK_TIER=$F16))*((BULK_SKU="ALL")+(BULK_SKU=$G16))*(BULK_START<=1)*(BULK_END>=1)))),0),ROUND((INDEX(VELOCITY_TABLE,MATCH($F16,TIER_LIST,0),3))*(IF((1-$I16+1)<=0,0,IF((1-$I16+1)=1,RAMP_W1,IF((1-$I16+1)=2,RAMP_W2,IF((1-$I16+1)=3,RAMP_W3,RAMP_W4PLUS)))))*(INDEX(ACTIVE_MULT_TABLE,3,1))*(1+SUMPRODUCT(SIGN(((ACT_DOOR_SCOPE="ALL")+(ACT_DOOR_SCOPE="TIER_"&$F16)+(ACT_DOOR_SCOPE=$B16)))*SIGN(((ACT_SKU_SCOPE="ALL")+(ACT_SKU_SCOPE=$G16)))*(ACT_START<=1)*(ACT_END>=1)*IFERROR(ACT_UPLIFT-1,0)))*(1+SUMPRODUCT(SIGN(((ACT_DOOR_SCOPE="ALL")+(ACT_DOOR_SCOPE="TIER_"&$F16)+(ACT_DOOR_SCOPE=$B16)))*SIGN(((ACT_SKU_SCOPE="ALL")+(ACT_SKU_SCOPE=$G16)))*(1>ACT_END)*(ACT_END>0)*IFERROR(ACT_POSTLIFT,0))),0))) | K16: =IF(OR($H16<>"Y",2<$I16),0,IF(SUMPRODUCT(((BULK_ENABLED="Y")*((BULK_TIER="ALL")+(BULK_TIER=$F16))*((BULK_SKU="ALL")+(BULK_SKU=$G16))*(BULK_START<=2)*(BULK_END>=2)))>0,IFERROR(SUMPRODUCT(((BULK_ENABLED="Y")*((BULK_TIER="ALL")+(BULK_TIER=$F16))*((BULK_SKU="ALL")+(BULK_SKU=$G16))*(BULK_START<=2)*(BULK_END>=2))*IFERROR(BULK_VALUE,0))/MAX(1,SUMPRODUCT(((BULK_ENABLED="Y")*((BULK_TIER="ALL")+(BULK_TIER=$F16))*((BULK_SKU="ALL")+(BULK_SKU=$G16))*(BULK_START<=2)*(BULK_END>=2)))),0),ROUND((INDEX(VELOCITY_TABLE,MATCH($F16,TIER_LIST,0),3))*(IF((2-$I16+1)<=0,0,IF((2-$I16+1)=1,RAMP_W1,IF((2-$I16+1)=2,RAMP_W2,IF((2-$I16+1)=3,RAMP_W3,RAMP_W4PLUS)))))*(INDEX(ACTIVE_MULT_TABLE,3,1))*(1+SUMPRODUCT(SIGN(((ACT_DOOR_SCOPE="ALL")+(ACT_DOOR_SCOPE="TIER_"&$F16)+(ACT_DOOR_SCOPE=$B16)))*SIGN(((ACT_SKU_SCOPE="ALL")+(ACT_SKU_SCOPE=$G16)))*(ACT_START<=2)*(ACT_END>=2)*IFERROR(ACT_UPLIFT-1,0)))*(1+SUMPRODUCT(SIGN(((ACT_DOOR_SCOPE="ALL")+(ACT_DOOR_SCOPE="TIER_"&$F16)+(ACT_DOOR_SCOPE=$B16)))*SIGN(((ACT_SKU_SCOPE="ALL")+(ACT_SKU_SCOPE=$G16)))*(2>ACT_END)*(ACT_END>0)*IFERROR(ACT_POSTLIFT,0))),0))) | L16: =IF(OR($H16<>"Y",3<$I16),0,IF(SUMPRODUCT(((BULK_ENABLED="Y")*((BULK_TIER="ALL")+(BULK_TIER=$F16))*((BULK_SKU="ALL")+(BULK_SKU=$G16))*(BULK_START<=3)*(BULK_END>=3)))>0,IFERROR(SUMPRODUCT(((BULK_ENABLED="Y")*((BULK_TIER="ALL")+(BULK_TIER=$F16))*((BULK_SKU="ALL")+(BULK_SKU=$G16))*(BULK_START<=3)*(BULK_END>=3))*IFERROR(BULK_VALUE,0))/MAX(1,SUMPRODUCT(((BULK_ENABLED="Y")*((BULK_TIER="ALL")+(BULK_TIER=$F16))*((BULK_SKU="ALL")+(BULK_SKU=$G16))*(BULK_START<=3)*(BULK_END>=3)))),0),ROUND((INDEX(VELOCITY_TABLE,MATCH($F16,TIER_LIST,0),3))*(IF((3-$I16+1)<=0,0,IF((3-$I16+1)=1,RAMP_W1,IF((3-$I16+1)=2,RAMP_W2,IF((3-$I16+1)=3,RAMP_W3,RAMP_W4PLUS)))))*(INDEX(ACTIVE_MULT_TABLE,3,1))*(1+SUMPRODUCT(SIGN(((ACT_DOOR_SCOPE="ALL")+(ACT_DOOR_SCOPE="TIER_"&$F16)+(ACT_DOOR_SCOPE=$B16)))*SIGN(((ACT_SKU_SCOPE="ALL")+(ACT_SKU_SCOPE=$G16)))*(ACT_START<=3)*(ACT_END>=3)*IFERROR(ACT_UPLIFT-1,0)))*(1+SUMPRODUCT(SIGN(((ACT_DOOR_SCOPE="ALL")+(ACT_DOOR_SCOPE="TIER_"&$F16)+(ACT_DOOR_SCOPE=$B16)))*SIGN(((ACT_SKU_SCOPE="ALL")+(ACT_SKU_SCOPE=$G16)))*(3>ACT_END)*(ACT_END>0)*IFERROR(ACT_POSTLIFT,0))),0))) | M16: =IF(OR($H16<>"Y",4<$I16),0,IF(SUMPRODUCT(((BULK_ENABLED="Y")*((BULK_TIER="ALL")+(BULK_TIER=$F16))*((BULK_SKU="ALL")+(BULK_SKU=$G16))*(BULK_START<=4)*(BULK_END>=4)))>0,IFERROR(SUMPRODUCT(((BULK_ENABLED="Y")*((BULK_TIER="ALL")+(BULK_TIER=$F16))*((BULK_SKU="ALL")+(BULK_SKU=$G16))*(BULK_START<=4)*(BULK_END>=4))*IFERROR(BULK_VALUE,0))/MAX(1,SUMPRODUCT(((BULK_ENABLED="Y")*((BULK_TIER="ALL")+(BULK_TIER=$F16))*((BULK_SKU="ALL")+(BULK_SKU=$G16))*(BULK_START<=4)*(BULK_END>=4)))),0),ROUND((INDEX(VELOCITY_TABLE,MATCH($F16,TIER_LIST,0),3))*(IF((4-$I16+1)<=0,0,IF((4-$I16+1)=1,RAMP_W1,IF((4-$I16+1)=2,RAMP_W2,IF((4-$I16+1)=3,RAMP_W3,RAMP_W4PLUS)))))*(INDEX(ACTIVE_MULT_TABLE,3,1))*(1+SUMPRODUCT(SIGN(((ACT_DOOR_SCOPE="ALL")+(ACT_DOOR_SCOPE="TIER_"&$F16)+(ACT_DOOR_SCOPE=$B16)))*SIGN(((ACT_SKU_SCOPE="ALL")+(ACT_SKU_SCOPE=$G16)))*(ACT_START<=4)*(ACT_END>=4)*IFERROR(ACT_UPLIFT-1,0)))*(1+SUMPRODUCT(SIGN(((ACT_DOOR_SCOPE="ALL")+(ACT_DOOR_SCOPE="TIER_"&$F16)+(ACT_DOOR_SCOPE=$B16)))*SIGN(((ACT_SKU_SCOPE="ALL")+(ACT_SKU_SCOPE=$G16)))*(4>ACT_END)*(ACT_END>0)*IFERROR(ACT_POSTLIFT,0))),0))) | N16: =IF(OR($H16<>"Y",5<$I16),0,IF(SUMPRODUCT(((BULK_ENABLED="Y")*((BULK_TIER="ALL")+(BULK_TIER=$F16))*((BULK_SKU="ALL")+(BULK_SKU=$G16))*(BULK_START<=5)*(BULK_END>=5)))>0,IFERROR(SUMPRODUCT(((BULK_ENABLED="Y")*((BULK_TIER="ALL")+(BULK_TIER=$F16))*((BULK_SKU="ALL")+(BULK_SKU=$G16))*(BULK_START<=5)*(BULK_END>=5))*IFERROR(BULK_VALUE,0))/MAX(1,SUMPRODUCT(((BULK_ENABLED="Y")*((BULK_TIER="ALL")+(BULK_TIER=$F16))*((BULK_SKU="ALL")+(BULK_SKU=$G16))*(BULK_START<=5)*(BULK_END>=5)))),0),ROUND((INDEX(VELOCITY_TABLE,MATCH($F16,TIER_LIST,0),3))*(IF((5-$I16+1)<=0,0,IF((5-$I16+1)=1,RAMP_W1,IF((5-$I16+1)=2,RAMP_W2,IF((5-$I16+1)=3,RAMP_W3,RAMP_W4PLUS)))))*(INDEX(ACTIVE_MULT_TABLE,3,1))*(1+SUMPRODUCT(SIGN(((ACT_DOOR_SCOPE="ALL")+(ACT_DOOR_SCOPE="TIER_"&$F16)+(ACT_DOOR_SCOPE=$B16)))*SIGN(((ACT_SKU_SCOPE="ALL")+(ACT_SKU_SCOPE=$G16)))*(ACT_START<=5)*(ACT_END>=5)*IFERROR(ACT_UPLIFT-1,0)))*(1+SUMPRODUCT(SIGN(((ACT_DOOR_SCOPE="ALL")+(ACT_DOOR_SCOPE="TIER_"&$F16)+(ACT_DOOR_SCOPE=$B16)))*SIGN(((ACT_SKU_SCOPE="ALL")+(ACT_SKU_SCOPE=$G16)))*(5>ACT_END)*(ACT_END>0)*IFERROR(ACT_POSTLIFT,0))),0))) | O16: =IF(OR($H16<>"Y",6<$I16),0,IF(SUMPRODUCT(((BULK_ENABLED="Y")*((BULK_TIER="ALL")+(BULK_TIER=$F16))*((BULK_SKU="ALL")+(BULK_SKU=$G16))*(BULK_START<=6)*(BULK_END>=6)))>0,IFERROR(SUMPRODUCT(((BULK_ENABLED="Y")*((BULK_TIER="ALL")+(BULK_TIER=$F16))*((BULK_SKU="ALL")+(BULK_SKU=$G16))*(BULK_START<=6)*(BULK_END>=6))*IFERROR(BULK_VALUE,0))/MAX(1,SUMPRODUCT(((BULK_ENABLED="Y")*((BULK_TIER="ALL")+(BULK_TIER=$F16))*((BULK_SKU="ALL")+(BULK_SKU=$G16))*(BULK_START<=6)*(BULK_END>=6)))),0),ROUND((INDEX(VELOCITY_TABLE,MATCH($F16,TIER_LIST,0),3))*(IF((6-$I16+1)<=0,0,IF((6-$I16+1)=1,RAMP_W1,IF((6-$I16+1)=2,RAMP_W2,IF((6-$I16+1)=3,RAMP_W3,RAMP_W4PLUS)))))*(INDEX(ACTIVE_MULT_TABLE,3,1))*(1+SUMPRODUCT(SIGN(((ACT_DOOR_SCOPE="ALL")+(ACT_DOOR_SCOPE="TIER_"&$F16)+(ACT_DOOR_SCOPE=$B16)))*SIGN(((ACT_SKU_SCOPE="ALL")+(ACT_SKU_SCOPE=$G16)))*(ACT_START<=6)*(ACT_END>=6)*IFERROR(ACT_UPLIFT-1,0)))*(1+SUMPRODUCT(SIGN(((ACT_DOOR_SCOPE="ALL")+(ACT_DOOR_SCOPE="TIER_"&$F16)+(ACT_DOOR_SCOPE=$B16)))*SIGN(((ACT_SKU_SCOPE="ALL")+(ACT_SKU_SCOPE=$G16)))*(6>ACT_END)*(ACT_END>0)*IFERROR(ACT_POSTLIFT,0))),0))) | P16: =IF(OR($H16<>"Y",7<$I16),0,IF(SUMPRODUCT(((BULK_ENABLED="Y")*((BULK_TIER="ALL")+(BULK_TIER=$F16))*((BULK_SKU="ALL")+(BULK_SKU=$G16))*(BULK_START<=7)*(BULK_END>=7)))>0,IFERROR(SUMPRODUCT(((BULK_ENABLED="Y")*((BULK_TIER="ALL")+(BULK_TIER=$F16))*((BULK_SKU="ALL")+(BULK_SKU=$G16))*(BULK_START<=7)*(BULK_END>=7))*IFERROR(BULK_VALUE,0))/MAX(1,SUMPRODUCT(((BULK_ENABLED="Y")*((BULK_TIER="ALL")+(BULK_TIER=$F16))*((BULK_SKU="ALL")+(BULK_SKU=$G16))*(BULK_START<=7)*(BULK_END>=7)))),0),ROUND((INDEX(VELOCITY_TABLE,MATCH($F16,TIER_LIST,0),3))*(IF((7-$I16+1)<=0,0,IF((7-$I16+1)=1,RAMP_W1,IF((7-$I16+1)=2,RAMP_W2,IF((7-$I16+1)=3,RAMP_W3,RAMP_W4PLUS)))))*(INDEX(ACTIVE_MULT_TABLE,3,1))*(1+SUMPRODUCT(SIGN(((ACT_DOOR_SCOPE="ALL")+(ACT_DOOR_SCOPE="TIER_"&$F16)+(ACT_DOOR_SCOPE=$B16)))*SIGN(((ACT_SKU_SCOPE="ALL")+(ACT_SKU_SCOPE=$G16)))*(ACT_START<=7)*(ACT_END>=7)*IFERROR(ACT_UPLIFT-1,0)))*(1+SUMPRODUCT(SIGN(((ACT_DOOR_SCOPE="ALL")+(ACT_DOOR_SCOPE="TIER_"&$F16)+(ACT_DOOR_SCOPE=$B16)))*SIGN(((ACT_SKU_SCOPE="ALL")+(ACT_SKU_SCOPE=$G16)))*(7>ACT_END)*(ACT_END>0)*IFERROR(ACT_POSTLIFT,0))),0))) | Q16: =IF(OR($H16<>"Y",8<$I16),0,IF(SUMPRODUCT(((BULK_ENABLED="Y")*((BULK_TIER="ALL")+(BULK_TIER=$F16))*((BULK_SKU="ALL")+(BULK_SKU=$G16))*(BULK_START<=8)*(BULK_END>=8)))>0,IFERROR(SUMPRODUCT(((BULK_ENABLED="Y")*((BULK_TIER="ALL")+(BULK_TIER=$F16))*((BULK_SKU="ALL")+(BULK_SKU=$G16))*(BULK_START<=8)*(BULK_END>=8))*IFERROR(BULK_VALUE,0))/MAX(1,SUMPRODUCT(((BULK_ENABLED="Y")*((BULK_TIER="ALL")+(BULK_TIER=$F16))*((BULK_SKU="ALL")+(BULK_SKU=$G16))*(BULK_START<=8)*(BULK_END>=8)))),0),ROUND((INDEX(VELOCITY_TABLE,MATCH($F16,TIER_LIST,0),3))*(IF((8-$I16+1)<=0,0,IF((8-$I16+1)=1,RAMP_W1,IF((8-$I16+1)=2,RAMP_W2,IF((8-$I16+1)=3,RAMP_W3,RAMP_W4PLUS)))))*(INDEX(ACTIVE_MULT_TABLE,3,1))*(1+SUMPRODUCT(SIGN(((ACT_DOOR_SCOPE="ALL")+(ACT_DOOR_SCOPE="TIER_"&$F16)+(ACT_DOOR_SCOPE=$B16)))*SIGN(((ACT_SKU_SCOPE="ALL")+(ACT_SKU_SCOPE=$G16)))*(ACT_START<=8)*(ACT_END>=8)*IFERROR(ACT_UPLIFT-1,0)))*(1+SUMPRODUCT(SIGN(((ACT_DOOR_SCOPE="ALL")+(ACT_DOOR_SCOPE="TIER_"&$F16)+(ACT_DOOR_SCOPE=$B16)))*SIGN(((ACT_SKU_SCOPE="ALL")+(ACT_SKU_SCOPE=$G16)))*(8>ACT_END)*(ACT_END>0)*IFERROR(ACT_POSTLIFT,0))),0))) | R16: =IF(OR($H16<>"Y",9<$I16),0,IF(SUMPRODUCT(((BULK_ENABLED="Y")*((BULK_TIER="ALL")+(BULK_TIER=$F16))*((BULK_SKU="ALL")+(BULK_SKU=$G16))*(BULK_START<=9)*(BULK_END>=9)))>0,IFERROR(SUMPRODUCT(((BULK_ENABLED="Y")*((BULK_TIER="ALL")+(BULK_TIER=$F16))*((BULK_SKU="ALL")+(BULK_SKU=$G16))*(BULK_START<=9)*(BULK_END>=9))*IFERROR(BULK_VALUE,0))/MAX(1,SUMPRODUCT(((BULK_ENABLED="Y")*((BULK_TIER="ALL")+(BULK_TIER=$F16))*((BULK_SKU="ALL")+(BULK_SKU=$G16))*(BULK_START<=9)*(BULK_END>=9)))),0),ROUND((INDEX(VELOCITY_TABLE,MATCH($F16,TIER_LIST,0),3))*(IF((9-$I16+1)<=0,0,IF((9-$I16+1)=1,RAMP_W1,IF((9-$I16+1)=2,RAMP_W2,IF((9-$I16+1)=3,RAMP_W3,RAMP_W4PLUS)))))*(INDEX(ACTIVE_MULT_TABLE,3,1))*(1+SUMPRODUCT(SIGN(((ACT_DOOR_SCOPE="ALL")+(ACT_DOOR_SCOPE="TIER_"&$F16)+(ACT_DOOR_SCOPE=$B16)))*SIGN(((ACT_SKU_SCOPE="ALL")+(ACT_SKU_SCOPE=$G16)))*(ACT_START<=9)*(ACT_END>=9)*IFERROR(ACT_UPLIFT-1,0)))*(1+SUMPRODUCT(SIGN(((ACT_DOOR_SCOPE="ALL")+(ACT_DOOR_SCOPE="TIER_"&$F16)+(ACT_DOOR_SCOPE=$B16)))*SIGN(((ACT_SKU_SCOPE="ALL")+(ACT_SKU_SCOPE=$G16)))*(9>ACT_END)*(ACT_END>0)*IFERROR(ACT_POSTLIFT,0))),0))) | S16: =IF(OR($H16<>"Y",10<$I16),0,IF(SUMPRODUCT(((BULK_ENABLED="Y")*((BULK_TIER="ALL")+(BULK_TIER=$F16))*((BULK_SKU="ALL")+(BULK_SKU=$G16))*(BULK_START<=10)*(BULK_END>=10)))>0,IFERROR(SUMPRODUCT(((BULK_ENABLED="Y")*((BULK_TIER="ALL")+(BULK_TIER=$F16))*((BULK_SKU="ALL")+(BULK_SKU=$G16))*(BULK_START<=10)*(BULK_END>=10))*IFERROR(BULK_VALUE,0))/MAX(1,SUMPRODUCT(((BULK_ENABLED="Y")*((BULK_TIER="ALL")+(BULK_TIER=$F16))*((BULK_SKU="ALL")+(BULK_SKU=$G16))*(BULK_START<=10)*(BULK_END>=10)))),0),ROUND((INDEX(VELOCITY_TABLE,MATCH($F16,TIER_LIST,0),3))*(IF((10-$I16+1)<=0,0,IF((10-$I16+1)=1,RAMP_W1,IF((10-$I16+1)=2,RAMP_W2,IF((10-$I16+1)=3,RAMP_W3,RAMP_W4PLUS)))))*(INDEX(ACTIVE_MULT_TABLE,3,1))*(1+SUMPRODUCT(SIGN(((ACT_DOOR_SCOPE="ALL")+(ACT_DOOR_SCOPE="TIER_"&$F16)+(ACT_DOOR_SCOPE=$B16)))*SIGN(((ACT_SKU_SCOPE="ALL")+(ACT_SKU_SCOPE=$G16)))*(ACT_START<=10)*(ACT_END>=10)*IFERROR(ACT_UPLIFT-1,0)))*(1+SUMPRODUCT(SIGN(((ACT_DOOR_SCOPE="ALL")+(ACT_DOOR_SCOPE="TIER_"&$F16)+(ACT_DOOR_SCOPE=$B16)))*SIGN(((ACT_SKU_SCOPE="ALL")+(ACT_SKU_SCOPE=$G16)))*(10>ACT_END)*(ACT_END>0)*IFERROR(ACT_POSTLIFT,0))),0))) | T16: =IF(OR($H16<>"Y",11<$I16),0,IF(SUMPRODUCT(((BULK_ENABLED="Y")*((BULK_TIER="ALL")+(BULK_TIER=$F16))*((BULK_SKU="ALL")+(BULK_SKU=$G16))*(BULK_START<=11)*(BULK_END>=11)))>0,IFERROR(SUMPRODUCT(((BULK_ENABLED="Y")*((BULK_TIER="ALL")+(BULK_TIER=$F16))*((BULK_SKU="ALL")+(BULK_SKU=$G16))*(BULK_START<=11)*(BULK_END>=11))*IFERROR(BULK_VALUE,0))/MAX(1,SUMPRODUCT(((BULK_ENABLED="Y")*((BULK_TIER="ALL")+(BULK_TIER=$F16))*((BULK_SKU="ALL")+(BULK_SKU=$G16))*(BULK_START<=11)*(BULK_END>=11)))),0),ROUND((INDEX(VELOCITY_TABLE,MATCH($F16,TIER_LIST,0),3))*(IF((11-$I16+1)<=0,0,IF((11-$I16+1)=1,RAMP_W1,IF((11-$I16+1)=2,RAMP_W2,IF((11-$I16+1)=3,RAMP_W3,RAMP_W4PLUS)))))*(INDEX(ACTIVE_MULT_TABLE,3,1))*(1+SUMPRODUCT(SIGN(((ACT_DOOR_SCOPE="ALL")+(ACT_DOOR_SCOPE="TIER_"&$F16)+(ACT_DOOR_SCOPE=$B16)))*SIGN(((ACT_SKU_SCOPE="ALL")+(ACT_SKU_SCOPE=$G16)))*(ACT_START<=11)*(ACT_END>=11)*IFERROR(ACT_UPLIFT-1,0)))*(1+SUMPRODUCT(SIGN(((ACT_DOOR_SCOPE="ALL")+(ACT_DOOR_SCOPE="TIER_"&$F16)+(ACT_DOOR_SCOPE=$B16)))*SIGN(((ACT_SKU_SCOPE="ALL")+(ACT_SKU_SCOPE=$G16)))*(11>ACT_END)*(ACT_END>0)*IFERROR(ACT_POSTLIFT,0))),0))) | U16: =IF(OR($H16<>"Y",12<$I16),0,IF(SUMPRODUCT(((BULK_ENABLED="Y")*((BULK_TIER="ALL")+(BULK_TIER=$F16))*((BULK_SKU="ALL")+(BULK_SKU=$G16))*(BULK_START<=12)*(BULK_END>=12)))>0,IFERROR(SUMPRODUCT(((BULK_ENABLED="Y")*((BULK_TIER="ALL")+(BULK_TIER=$F16))*((BULK_SKU="ALL")+(BULK_SKU=$G16))*(BULK_START<=12)*(BULK_END>=12))*IFERROR(BULK_VALUE,0))/MAX(1,SUMPRODUCT(((BULK_ENABLED="Y")*((BULK_TIER="ALL")+(BULK_TIER=$F16))*((BULK_SKU="ALL")+(BULK_SKU=$G16))*(BULK_START<=12)*(BULK_END>=12)))),0),ROUND((INDEX(VELOCITY_TABLE,MATCH($F16,TIER_LIST,0),3))*(IF((12-$I16+1)<=0,0,IF((12-$I16+1)=1,RAMP_W1,IF((12-$I16+1)=2,RAMP_W2,IF((12-$I16+1)=3,RAMP_W3,RAMP_W4PLUS)))))*(INDEX(ACTIVE_MULT_TABLE,3,1))*(1+SUMPRODUCT(SIGN(((ACT_DOOR_SCOPE="ALL")+(ACT_DOOR_SCOPE="TIER_"&$F16)+(ACT_DOOR_SCOPE=$B16)))*SIGN(((ACT_SKU_SCOPE="ALL")+(ACT_SKU_SCOPE=$G16)))*(ACT_START<=12)*(ACT_END>=12)*IFERROR(ACT_UPLIFT-1,0)))*(1+SUMPRODUCT(SIGN(((ACT_DOOR_SCOPE="ALL")+(ACT_DOOR_SCOPE="TIER_"&$F16)+(ACT_DOOR_SCOPE=$B16)))*SIGN(((ACT_SKU_SCOPE="ALL")+(ACT_SKU_SCOPE=$G16)))*(12>ACT_END)*(ACT_END>0)*IFERROR(ACT_POSTLIFT,0))),0))) | V16: =IF(OR($H16<>"Y",13<$I16),0,IF(SUMPRODUCT(((BULK_ENABLED="Y")*((BULK_TIER="ALL")+(BULK_TIER=$F16))*((BULK_SKU="ALL")+(BULK_SKU=$G16))*(BULK_START<=13)*(BULK_END>=13)))>0,IFERROR(SUMPRODUCT(((BULK_ENABLED="Y")*((BULK_TIER="ALL")+(BULK_TIER=$F16))*((BULK_SKU="ALL")+(BULK_SKU=$G16))*(BULK_START<=13)*(BULK_END>=13))*IFERROR(BULK_VALUE,0))/MAX(1,SUMPRODUCT(((BULK_ENABLED="Y")*((BULK_TIER="ALL")+(BULK_TIER=$F16))*((BULK_SKU="ALL")+(BULK_SKU=$G16))*(BULK_START<=13)*(BULK_END>=13)))),0),ROUND((INDEX(VELOCITY_TABLE,MATCH($F16,TIER_LIST,0),3))*(IF((13-$I16+1)<=0,0,IF((13-$I16+1)=1,RAMP_W1,IF((13-$I16+1)=2,RAMP_W2,IF((13-$I16+1)=3,RAMP_W3,RAMP_W4PLUS)))))*(INDEX(ACTIVE_MULT_TABLE,3,1))*(1+SUMPRODUCT(SIGN(((ACT_DOOR_SCOPE="ALL")+(ACT_DOOR_SCOPE="TIER_"&$F16)+(ACT_DOOR_SCOPE=$B16)))*SIGN(((ACT_SKU_SCOPE="ALL")+(ACT_SKU_SCOPE=$G16)))*(ACT_START<=13)*(ACT_END>=13)*IFERROR(ACT_UPLIFT-1,0)))*(1+SUMPRODUCT(SIGN(((ACT_DOOR_SCOPE="ALL")+(ACT_DOOR_SCOPE="TIER_"&$F16)+(ACT_DOOR_SCOPE=$B16)))*SIGN(((ACT_SKU_SCOPE="ALL")+(ACT_SKU_SCOPE=$G16)))*(13>ACT_END)*(ACT_END>0)*IFERROR(ACT_POSTLIFT,0))),0)))
A17: R0013 | B17: =Doors!$A$9 | C17: =Doors!$C$9 | D17: =Doors!$B$9 | E17: =Doors!$E$9 | F17: =Doors!$F$9 | G17: Lime Lemon | H17: =Doors!$G$9 | I17: =Doors!$J$9 | J17: =IF(OR($H17<>"Y",1<$I17),0,IF(SUMPRODUCT(((BULK_ENABLED="Y")*((BULK_TIER="ALL")+(BULK_TIER=$F17))*((BULK_SKU="ALL")+(BULK_SKU=$G17))*(BULK_START<=1)*(BULK_END>=1)))>0,IFERROR(SUMPRODUCT(((BULK_ENABLED="Y")*((BULK_TIER="ALL")+(BULK_TIER=$F17))*((BULK_SKU="ALL")+(BULK_SKU=$G17))*(BULK_START<=1)*(BULK_END>=1))*IFERROR(BULK_VALUE,0))/MAX(1,SUMPRODUCT(((BULK_ENABLED="Y")*((BULK_TIER="ALL")+(BULK_TIER=$F17))*((BULK_SKU="ALL")+(BULK_SKU=$G17))*(BULK_START<=1)*(BULK_END>=1)))),0),ROUND((INDEX(VELOCITY_TABLE,MATCH($F17,TIER_LIST,0),1))*(IF((1-$I17+1)<=0,0,IF((1-$I17+1)=1,RAMP_W1,IF((1-$I17+1)=2,RAMP_W2,IF((1-$I17+1)=3,RAMP_W3,RAMP_W4PLUS)))))*(INDEX(ACTIVE_MULT_TABLE,1,1))*(1+SUMPRODUCT(SIGN(((ACT_DOOR_SCOPE="ALL")+(ACT_DOOR_SCOPE="TIER_"&$F17)+(ACT_DOOR_SCOPE=$B17)))*SIGN(((ACT_SKU_SCOPE="ALL")+(ACT_SKU_SCOPE=$G17)))*(ACT_START<=1)*(ACT_END>=1)*IFERROR(ACT_UPLIFT-1,0)))*(1+SUMPRODUCT(SIGN(((ACT_DOOR_SCOPE="ALL")+(ACT_DOOR_SCOPE="TIER_"&$F17)+(ACT_DOOR_SCOPE=$B17)))*SIGN(((ACT_SKU_SCOPE="ALL")+(ACT_SKU_SCOPE=$G17)))*(1>ACT_END)*(ACT_END>0)*IFERROR(ACT_POSTLIFT,0))),0))) | K17: =IF(OR($H17<>"Y",2<$I17),0,IF(SUMPRODUCT(((BULK_ENABLED="Y")*((BULK_TIER="ALL")+(BULK_TIER=$F17))*((BULK_SKU="ALL")+(BULK_SKU=$G17))*(BULK_START<=2)*(BULK_END>=2)))>0,IFERROR(SUMPRODUCT(((BULK_ENABLED="Y")*((BULK_TIER="ALL")+(BULK_TIER=$F17))*((BULK_SKU="ALL")+(BULK_SKU=$G17))*(BULK_START<=2)*(BULK_END>=2))*IFERROR(BULK_VALUE,0))/MAX(1,SUMPRODUCT(((BULK_ENABLED="Y")*((BULK_TIER="ALL")+(BULK_TIER=$F17))*((BULK_SKU="ALL")+(BULK_SKU=$G17))*(BULK_START<=2)*(BULK_END>=2)))),0),ROUND((INDEX(VELOCITY_TABLE,MATCH($F17,TIER_LIST,0),1))*(IF((2-$I17+1)<=0,0,IF((2-$I17+1)=1,RAMP_W1,IF((2-$I17+1)=2,RAMP_W2,IF((2-$I17+1)=3,RAMP_W3,RAMP_W4PLUS)))))*(INDEX(ACTIVE_MULT_TABLE,1,1))*(1+SUMPRODUCT(SIGN(((ACT_DOOR_SCOPE="ALL")+(ACT_DOOR_SCOPE="TIER_"&$F17)+(ACT_DOOR_SCOPE=$B17)))*SIGN(((ACT_SKU_SCOPE="ALL")+(ACT_SKU_SCOPE=$G17)))*(ACT_START<=2)*(ACT_END>=2)*IFERROR(ACT_UPLIFT-1,0)))*(1+SUMPRODUCT(SIGN(((ACT_DOOR_SCOPE="ALL")+(ACT_DOOR_SCOPE="TIER_"&$F17)+(ACT_DOOR_SCOPE=$B17)))*SIGN(((ACT_SKU_SCOPE="ALL")+(ACT_SKU_SCOPE=$G17)))*(2>ACT_END)*(ACT_END>0)*IFERROR(ACT_POSTLIFT,0))),0))) | L17: =IF(OR($H17<>"Y",3<$I17),0,IF(SUMPRODUCT(((BULK_ENABLED="Y")*((BULK_TIER="ALL")+(BULK_TIER=$F17))*((BULK_SKU="ALL")+(BULK_SKU=$G17))*(BULK_START<=3)*(BULK_END>=3)))>0,IFERROR(SUMPRODUCT(((BULK_ENABLED="Y")*((BULK_TIER="ALL")+(BULK_TIER=$F17))*((BULK_SKU="ALL")+(BULK_SKU=$G17))*(BULK_START<=3)*(BULK_END>=3))*IFERROR(BULK_VALUE,0))/MAX(1,SUMPRODUCT(((BULK_ENABLED="Y")*((BULK_TIER="ALL")+(BULK_TIER=$F17))*((BULK_SKU="ALL")+(BULK_SKU=$G17))*(BULK_START<=3)*(BULK_END>=3)))),0),ROUND((INDEX(VELOCITY_TABLE,MATCH($F17,TIER_LIST,0),1))*(IF((3-$I17+1)<=0,0,IF((3-$I17+1)=1,RAMP_W1,IF((3-$I17+1)=2,RAMP_W2,IF((3-$I17+1)=3,RAMP_W3,RAMP_W4PLUS)))))*(INDEX(ACTIVE_MULT_TABLE,1,1))*(1+SUMPRODUCT(SIGN(((ACT_DOOR_SCOPE="ALL")+(ACT_DOOR_SCOPE="TIER_"&$F17)+(ACT_DOOR_SCOPE=$B17)))*SIGN(((ACT_SKU_SCOPE="ALL")+(ACT_SKU_SCOPE=$G17)))*(ACT_START<=3)*(ACT_END>=3)*IFERROR(ACT_UPLIFT-1,0)))*(1+SUMPRODUCT(SIGN(((ACT_DOOR_SCOPE="ALL")+(ACT_DOOR_SCOPE="TIER_"&$F17)+(ACT_DOOR_SCOPE=$B17)))*SIGN(((ACT_SKU_SCOPE="ALL")+(ACT_SKU_SCOPE=$G17)))*(3>ACT_END)*(ACT_END>0)*IFERROR(ACT_POSTLIFT,0))),0))) | M17: =IF(OR($H17<>"Y",4<$I17),0,IF(SUMPRODUCT(((BULK_ENABLED="Y")*((BULK_TIER="ALL")+(BULK_TIER=$F17))*((BULK_SKU="ALL")+(BULK_SKU=$G17))*(BULK_START<=4)*(BULK_END>=4)))>0,IFERROR(SUMPRODUCT(((BULK_ENABLED="Y")*((BULK_TIER="ALL")+(BULK_TIER=$F17))*((BULK_SKU="ALL")+(BULK_SKU=$G17))*(BULK_START<=4)*(BULK_END>=4))*IFERROR(BULK_VALUE,0))/MAX(1,SUMPRODUCT(((BULK_ENABLED="Y")*((BULK_TIER="ALL")+(BULK_TIER=$F17))*((BULK_SKU="ALL")+(BULK_SKU=$G17))*(BULK_START<=4)*(BULK_END>=4)))),0),ROUND((INDEX(VELOCITY_TABLE,MATCH($F17,TIER_LIST,0),1))*(IF((4-$I17+1)<=0,0,IF((4-$I17+1)=1,RAMP_W1,IF((4-$I17+1)=2,RAMP_W2,IF((4-$I17+1)=3,RAMP_W3,RAMP_W4PLUS)))))*(INDEX(ACTIVE_MULT_TABLE,1,1))*(1+SUMPRODUCT(SIGN(((ACT_DOOR_SCOPE="ALL")+(ACT_DOOR_SCOPE="TIER_"&$F17)+(ACT_DOOR_SCOPE=$B17)))*SIGN(((ACT_SKU_SCOPE="ALL")+(ACT_SKU_SCOPE=$G17)))*(ACT_START<=4)*(ACT_END>=4)*IFERROR(ACT_UPLIFT-1,0)))*(1+SUMPRODUCT(SIGN(((ACT_DOOR_SCOPE="ALL")+(ACT_DOOR_SCOPE="TIER_"&$F17)+(ACT_DOOR_SCOPE=$B17)))*SIGN(((ACT_SKU_SCOPE="ALL")+(ACT_SKU_SCOPE=$G17)))*(4>ACT_END)*(ACT_END>0)*IFERROR(ACT_POSTLIFT,0))),0))) | N17: =IF(OR($H17<>"Y",5<$I17),0,IF(SUMPRODUCT(((BULK_ENABLED="Y")*((BULK_TIER="ALL")+(BULK_TIER=$F17))*((BULK_SKU="ALL")+(BULK_SKU=$G17))*(BULK_START<=5)*(BULK_END>=5)))>0,IFERROR(SUMPRODUCT(((BULK_ENABLED="Y")*((BULK_TIER="ALL")+(BULK_TIER=$F17))*((BULK_SKU="ALL")+(BULK_SKU=$G17))*(BULK_START<=5)*(BULK_END>=5))*IFERROR(BULK_VALUE,0))/MAX(1,SUMPRODUCT(((BULK_ENABLED="Y")*((BULK_TIER="ALL")+(BULK_TIER=$F17))*((BULK_SKU="ALL")+(BULK_SKU=$G17))*(BULK_START<=5)*(BULK_END>=5)))),0),ROUND((INDEX(VELOCITY_TABLE,MATCH($F17,TIER_LIST,0),1))*(IF((5-$I17+1)<=0,0,IF((5-$I17+1)=1,RAMP_W1,IF((5-$I17+1)=2,RAMP_W2,IF((5-$I17+1)=3,RAMP_W3,RAMP_W4PLUS)))))*(INDEX(ACTIVE_MULT_TABLE,1,1))*(1+SUMPRODUCT(SIGN(((ACT_DOOR_SCOPE="ALL")+(ACT_DOOR_SCOPE="TIER_"&$F17)+(ACT_DOOR_SCOPE=$B17)))*SIGN(((ACT_SKU_SCOPE="ALL")+(ACT_SKU_SCOPE=$G17)))*(ACT_START<=5)*(ACT_END>=5)*IFERROR(ACT_UPLIFT-1,0)))*(1+SUMPRODUCT(SIGN(((ACT_DOOR_SCOPE="ALL")+(ACT_DOOR_SCOPE="TIER_"&$F17)+(ACT_DOOR_SCOPE=$B17)))*SIGN(((ACT_SKU_SCOPE="ALL")+(ACT_SKU_SCOPE=$G17)))*(5>ACT_END)*(ACT_END>0)*IFERROR(ACT_POSTLIFT,0))),0))) | O17: =IF(OR($H17<>"Y",6<$I17),0,IF(SUMPRODUCT(((BULK_ENABLED="Y")*((BULK_TIER="ALL")+(BULK_TIER=$F17))*((BULK_SKU="ALL")+(BULK_SKU=$G17))*(BULK_START<=6)*(BULK_END>=6)))>0,IFERROR(SUMPRODUCT(((BULK_ENABLED="Y")*((BULK_TIER="ALL")+(BULK_TIER=$F17))*((BULK_SKU="ALL")+(BULK_SKU=$G17))*(BULK_START<=6)*(BULK_END>=6))*IFERROR(BULK_VALUE,0))/MAX(1,SUMPRODUCT(((BULK_ENABLED="Y")*((BULK_TIER="ALL")+(BULK_TIER=$F17))*((BULK_SKU="ALL")+(BULK_SKU=$G17))*(BULK_START<=6)*(BULK_END>=6)))),0),ROUND((INDEX(VELOCITY_TABLE,MATCH($F17,TIER_LIST,0),1))*(IF((6-$I17+1)<=0,0,IF((6-$I17+1)=1,RAMP_W1,IF((6-$I17+1)=2,RAMP_W2,IF((6-$I17+1)=3,RAMP_W3,RAMP_W4PLUS)))))*(INDEX(ACTIVE_MULT_TABLE,1,1))*(1+SUMPRODUCT(SIGN(((ACT_DOOR_SCOPE="ALL")+(ACT_DOOR_SCOPE="TIER_"&$F17)+(ACT_DOOR_SCOPE=$B17)))*SIGN(((ACT_SKU_SCOPE="ALL")+(ACT_SKU_SCOPE=$G17)))*(ACT_START<=6)*(ACT_END>=6)*IFERROR(ACT_UPLIFT-1,0)))*(1+SUMPRODUCT(SIGN(((ACT_DOOR_SCOPE="ALL")+(ACT_DOOR_SCOPE="TIER_"&$F17)+(ACT_DOOR_SCOPE=$B17)))*SIGN(((ACT_SKU_SCOPE="ALL")+(ACT_SKU_SCOPE=$G17)))*(6>ACT_END)*(ACT_END>0)*IFERROR(ACT_POSTLIFT,0))),0))) | P17: =IF(OR($H17<>"Y",7<$I17),0,IF(SUMPRODUCT(((BULK_ENABLED="Y")*((BULK_TIER="ALL")+(BULK_TIER=$F17))*((BULK_SKU="ALL")+(BULK_SKU=$G17))*(BULK_START<=7)*(BULK_END>=7)))>0,IFERROR(SUMPRODUCT(((BULK_ENABLED="Y")*((BULK_TIER="ALL")+(BULK_TIER=$F17))*((BULK_SKU="ALL")+(BULK_SKU=$G17))*(BULK_START<=7)*(BULK_END>=7))*IFERROR(BULK_VALUE,0))/MAX(1,SUMPRODUCT(((BULK_ENABLED="Y")*((BULK_TIER="ALL")+(BULK_TIER=$F17))*((BULK_SKU="ALL")+(BULK_SKU=$G17))*(BULK_START<=7)*(BULK_END>=7)))),0),ROUND((INDEX(VELOCITY_TABLE,MATCH($F17,TIER_LIST,0),1))*(IF((7-$I17+1)<=0,0,IF((7-$I17+1)=1,RAMP_W1,IF((7-$I17+1)=2,RAMP_W2,IF((7-$I17+1)=3,RAMP_W3,RAMP_W4PLUS)))))*(INDEX(ACTIVE_MULT_TABLE,1,1))*(1+SUMPRODUCT(SIGN(((ACT_DOOR_SCOPE="ALL")+(ACT_DOOR_SCOPE="TIER_"&$F17)+(ACT_DOOR_SCOPE=$B17)))*SIGN(((ACT_SKU_SCOPE="ALL")+(ACT_SKU_SCOPE=$G17)))*(ACT_START<=7)*(ACT_END>=7)*IFERROR(ACT_UPLIFT-1,0)))*(1+SUMPRODUCT(SIGN(((ACT_DOOR_SCOPE="ALL")+(ACT_DOOR_SCOPE="TIER_"&$F17)+(ACT_DOOR_SCOPE=$B17)))*SIGN(((ACT_SKU_SCOPE="ALL")+(ACT_SKU_SCOPE=$G17)))*(7>ACT_END)*(ACT_END>0)*IFERROR(ACT_POSTLIFT,0))),0))) | Q17: =IF(OR($H17<>"Y",8<$I17),0,IF(SUMPRODUCT(((BULK_ENABLED="Y")*((BULK_TIER="ALL")+(BULK_TIER=$F17))*((BULK_SKU="ALL")+(BULK_SKU=$G17))*(BULK_START<=8)*(BULK_END>=8)))>0,IFERROR(SUMPRODUCT(((BULK_ENABLED="Y")*((BULK_TIER="ALL")+(BULK_TIER=$F17))*((BULK_SKU="ALL")+(BULK_SKU=$G17))*(BULK_START<=8)*(BULK_END>=8))*IFERROR(BULK_VALUE,0))/MAX(1,SUMPRODUCT(((BULK_ENABLED="Y")*((BULK_TIER="ALL")+(BULK_TIER=$F17))*((BULK_SKU="ALL")+(BULK_SKU=$G17))*(BULK_START<=8)*(BULK_END>=8)))),0),ROUND((INDEX(VELOCITY_TABLE,MATCH($F17,TIER_LIST,0),1))*(IF((8-$I17+1)<=0,0,IF((8-$I17+1)=1,RAMP_W1,IF((8-$I17+1)=2,RAMP_W2,IF((8-$I17+1)=3,RAMP_W3,RAMP_W4PLUS)))))*(INDEX(ACTIVE_MULT_TABLE,1,1))*(1+SUMPRODUCT(SIGN(((ACT_DOOR_SCOPE="ALL")+(ACT_DOOR_SCOPE="TIER_"&$F17)+(ACT_DOOR_SCOPE=$B17)))*SIGN(((ACT_SKU_SCOPE="ALL")+(ACT_SKU_SCOPE=$G17)))*(ACT_START<=8)*(ACT_END>=8)*IFERROR(ACT_UPLIFT-1,0)))*(1+SUMPRODUCT(SIGN(((ACT_DOOR_SCOPE="ALL")+(ACT_DOOR_SCOPE="TIER_"&$F17)+(ACT_DOOR_SCOPE=$B17)))*SIGN(((ACT_SKU_SCOPE="ALL")+(ACT_SKU_SCOPE=$G17)))*(8>ACT_END)*(ACT_END>0)*IFERROR(ACT_POSTLIFT,0))),0))) | R17: =IF(OR($H17<>"Y",9<$I17),0,IF(SUMPRODUCT(((BULK_ENABLED="Y")*((BULK_TIER="ALL")+(BULK_TIER=$F17))*((BULK_SKU="ALL")+(BULK_SKU=$G17))*(BULK_START<=9)*(BULK_END>=9)))>0,IFERROR(SUMPRODUCT(((BULK_ENABLED="Y")*((BULK_TIER="ALL")+(BULK_TIER=$F17))*((BULK_SKU="ALL")+(BULK_SKU=$G17))*(BULK_START<=9)*(BULK_END>=9))*IFERROR(BULK_VALUE,0))/MAX(1,SUMPRODUCT(((BULK_ENABLED="Y")*((BULK_TIER="ALL")+(BULK_TIER=$F17))*((BULK_SKU="ALL")+(BULK_SKU=$G17))*(BULK_START<=9)*(BULK_END>=9)))),0),ROUND((INDEX(VELOCITY_TABLE,MATCH($F17,TIER_LIST,0),1))*(IF((9-$I17+1)<=0,0,IF((9-$I17+1)=1,RAMP_W1,IF((9-$I17+1)=2,RAMP_W2,IF((9-$I17+1)=3,RAMP_W3,RAMP_W4PLUS)))))*(INDEX(ACTIVE_MULT_TABLE,1,1))*(1+SUMPRODUCT(SIGN(((ACT_DOOR_SCOPE="ALL")+(ACT_DOOR_SCOPE="TIER_"&$F17)+(ACT_DOOR_SCOPE=$B17)))*SIGN(((ACT_SKU_SCOPE="ALL")+(ACT_SKU_SCOPE=$G17)))*(ACT_START<=9)*(ACT_END>=9)*IFERROR(ACT_UPLIFT-1,0)))*(1+SUMPRODUCT(SIGN(((ACT_DOOR_SCOPE="ALL")+(ACT_DOOR_SCOPE="TIER_"&$F17)+(ACT_DOOR_SCOPE=$B17)))*SIGN(((ACT_SKU_SCOPE="ALL")+(ACT_SKU_SCOPE=$G17)))*(9>ACT_END)*(ACT_END>0)*IFERROR(ACT_POSTLIFT,0))),0))) | S17: =IF(OR($H17<>"Y",10<$I17),0,IF(SUMPRODUCT(((BULK_ENABLED="Y")*((BULK_TIER="ALL")+(BULK_TIER=$F17))*((BULK_SKU="ALL")+(BULK_SKU=$G17))*(BULK_START<=10)*(BULK_END>=10)))>0,IFERROR(SUMPRODUCT(((BULK_ENABLED="Y")*((BULK_TIER="ALL")+(BULK_TIER=$F17))*((BULK_SKU="ALL")+(BULK_SKU=$G17))*(BULK_START<=10)*(BULK_END>=10))*IFERROR(BULK_VALUE,0))/MAX(1,SUMPRODUCT(((BULK_ENABLED="Y")*((BULK_TIER="ALL")+(BULK_TIER=$F17))*((BULK_SKU="ALL")+(BULK_SKU=$G17))*(BULK_START<=10)*(BULK_END>=10)))),0),ROUND((INDEX(VELOCITY_TABLE,MATCH($F17,TIER_LIST,0),1))*(IF((10-$I17+1)<=0,0,IF((10-$I17+1)=1,RAMP_W1,IF((10-$I17+1)=2,RAMP_W2,IF((10-$I17+1)=3,RAMP_W3,RAMP_W4PLUS)))))*(INDEX(ACTIVE_MULT_TABLE,1,1))*(1+SUMPRODUCT(SIGN(((ACT_DOOR_SCOPE="ALL")+(ACT_DOOR_SCOPE="TIER_"&$F17)+(ACT_DOOR_SCOPE=$B17)))*SIGN(((ACT_SKU_SCOPE="ALL")+(ACT_SKU_SCOPE=$G17)))*(ACT_START<=10)*(ACT_END>=10)*IFERROR(ACT_UPLIFT-1,0)))*(1+SUMPRODUCT(SIGN(((ACT_DOOR_SCOPE="ALL")+(ACT_DOOR_SCOPE="TIER_"&$F17)+(ACT_DOOR_SCOPE=$B17)))*SIGN(((ACT_SKU_SCOPE="ALL")+(ACT_SKU_SCOPE=$G17)))*(10>ACT_END)*(ACT_END>0)*IFERROR(ACT_POSTLIFT,0))),0))) | T17: =IF(OR($H17<>"Y",11<$I17),0,IF(SUMPRODUCT(((BULK_ENABLED="Y")*((BULK_TIER="ALL")+(BULK_TIER=$F17))*((BULK_SKU="ALL")+(BULK_SKU=$G17))*(BULK_START<=11)*(BULK_END>=11)))>0,IFERROR(SUMPRODUCT(((BULK_ENABLED="Y")*((BULK_TIER="ALL")+(BULK_TIER=$F17))*((BULK_SKU="ALL")+(BULK_SKU=$G17))*(BULK_START<=11)*(BULK_END>=11))*IFERROR(BULK_VALUE,0))/MAX(1,SUMPRODUCT(((BULK_ENABLED="Y")*((BULK_TIER="ALL")+(BULK_TIER=$F17))*((BULK_SKU="ALL")+(BULK_SKU=$G17))*(BULK_START<=11)*(BULK_END>=11)))),0),ROUND((INDEX(VELOCITY_TABLE,MATCH($F17,TIER_LIST,0),1))*(IF((11-$I17+1)<=0,0,IF((11-$I17+1)=1,RAMP_W1,IF((11-$I17+1)=2,RAMP_W2,IF((11-$I17+1)=3,RAMP_W3,RAMP_W4PLUS)))))*(INDEX(ACTIVE_MULT_TABLE,1,1))*(1+SUMPRODUCT(SIGN(((ACT_DOOR_SCOPE="ALL")+(ACT_DOOR_SCOPE="TIER_"&$F17)+(ACT_DOOR_SCOPE=$B17)))*SIGN(((ACT_SKU_SCOPE="ALL")+(ACT_SKU_SCOPE=$G17)))*(ACT_START<=11)*(ACT_END>=11)*IFERROR(ACT_UPLIFT-1,0)))*(1+SUMPRODUCT(SIGN(((ACT_DOOR_SCOPE="ALL")+(ACT_DOOR_SCOPE="TIER_"&$F17)+(ACT_DOOR_SCOPE=$B17)))*SIGN(((ACT_SKU_SCOPE="ALL")+(ACT_SKU_SCOPE=$G17)))*(11>ACT_END)*(ACT_END>0)*IFERROR(ACT_POSTLIFT,0))),0))) | U17: =IF(OR($H17<>"Y",12<$I17),0,IF(SUMPRODUCT(((BULK_ENABLED="Y")*((BULK_TIER="ALL")+(BULK_TIER=$F17))*((BULK_SKU="ALL")+(BULK_SKU=$G17))*(BULK_START<=12)*(BULK_END>=12)))>0,IFERROR(SUMPRODUCT(((BULK_ENABLED="Y")*((BULK_TIER="ALL")+(BULK_TIER=$F17))*((BULK_SKU="ALL")+(BULK_SKU=$G17))*(BULK_START<=12)*(BULK_END>=12))*IFERROR(BULK_VALUE,0))/MAX(1,SUMPRODUCT(((BULK_ENABLED="Y")*((BULK_TIER="ALL")+(BULK_TIER=$F17))*((BULK_SKU="ALL")+(BULK_SKU=$G17))*(BULK_START<=12)*(BULK_END>=12)))),0),ROUND((INDEX(VELOCITY_TABLE,MATCH($F17,TIER_LIST,0),1))*(IF((12-$I17+1)<=0,0,IF((12-$I17+1)=1,RAMP_W1,IF((12-$I17+1)=2,RAMP_W2,IF((12-$I17+1)=3,RAMP_W3,RAMP_W4PLUS)))))*(INDEX(ACTIVE_MULT_TABLE,1,1))*(1+SUMPRODUCT(SIGN(((ACT_DOOR_SCOPE="ALL")+(ACT_DOOR_SCOPE="TIER_"&$F17)+(ACT_DOOR_SCOPE=$B17)))*SIGN(((ACT_SKU_SCOPE="ALL")+(ACT_SKU_SCOPE=$G17)))*(ACT_START<=12)*(ACT_END>=12)*IFERROR(ACT_UPLIFT-1,0)))*(1+SUMPRODUCT(SIGN(((ACT_DOOR_SCOPE="ALL")+(ACT_DOOR_SCOPE="TIER_"&$F17)+(ACT_DOOR_SCOPE=$B17)))*SIGN(((ACT_SKU_SCOPE="ALL")+(ACT_SKU_SCOPE=$G17)))*(12>ACT_END)*(ACT_END>0)*IFERROR(ACT_POSTLIFT,0))),0))) | V17: =IF(OR($H17<>"Y",13<$I17),0,IF(SUMPRODUCT(((BULK_ENABLED="Y")*((BULK_TIER="ALL")+(BULK_TIER=$F17))*((BULK_SKU="ALL")+(BULK_SKU=$G17))*(BULK_START<=13)*(BULK_END>=13)))>0,IFERROR(SUMPRODUCT(((BULK_ENABLED="Y")*((BULK_TIER="ALL")+(BULK_TIER=$F17))*((BULK_SKU="ALL")+(BULK_SKU=$G17))*(BULK_START<=13)*(BULK_END>=13))*IFERROR(BULK_VALUE,0))/MAX(1,SUMPRODUCT(((BULK_ENABLED="Y")*((BULK_TIER="ALL")+(BULK_TIER=$F17))*((BULK_SKU="ALL")+(BULK_SKU=$G17))*(BULK_START<=13)*(BULK_END>=13)))),0),ROUND((INDEX(VELOCITY_TABLE,MATCH($F17,TIER_LIST,0),1))*(IF((13-$I17+1)<=0,0,IF((13-$I17+1)=1,RAMP_W1,IF((13-$I17+1)=2,RAMP_W2,IF((13-$I17+1)=3,RAMP_W3,RAMP_W4PLUS)))))*(INDEX(ACTIVE_MULT_TABLE,1,1))*(1+SUMPRODUCT(SIGN(((ACT_DOOR_SCOPE="ALL")+(ACT_DOOR_SCOPE="TIER_"&$F17)+(ACT_DOOR_SCOPE=$B17)))*SIGN(((ACT_SKU_SCOPE="ALL")+(ACT_SKU_SCOPE=$G17)))*(ACT_START<=13)*(ACT_END>=13)*IFERROR(ACT_UPLIFT-1,0)))*(1+SUMPRODUCT(SIGN(((ACT_DOOR_SCOPE="ALL")+(ACT_DOOR_SCOPE="TIER_"&$F17)+(ACT_DOOR_SCOPE=$B17)))*SIGN(((ACT_SKU_SCOPE="ALL")+(ACT_SKU_SCOPE=$G17)))*(13>ACT_END)*(ACT_END>0)*IFERROR(ACT_POSTLIFT,0))),0)))
