Workbook

Sheet P&L
A1: Organika MÜV Sparkling Electrolytes — Annual P&L
A2: Yellow = inputs. COGS is built on COGS_BOM; revenue & channel costs on Channels. This is the blended roll-up.
A4: OPERATING ASSUMPTIONS
B5: Annual volume (cases) | C5: 250000
B6: Units / case | C6: 12
B7: Total units (cans) | C7: =C5*C6
B8: Brand marketing (% net sales) | C8: 0.08
B9: Sales & team salaries | C9: 600000
B10: G&A / overhead | C10: 850000
B11: R&D / innovation | C11: 180000
B12: Depreciation & amortization | C12: 150000
B13: Fixed costs (sales + G&A + R&D) | C13: =C9+C10+C11
A16: P&L STATEMENT — GROSS SALES TO EBIT
B17: Line | C17: Total | D17: Per case | E17: % net
B18: Gross sales | C18: =Channels!$L$9 | D18: =C18/$C$5 | E18: =C18/Channels!$O$9
B19: Less: trade & promo | C19: =-Channels!$M$9 | D19: =C19/$C$5 | E19: =C19/Channels!$O$9
B20: Less: returns & spoilage | C20: =-Channels!$N$9 | D20: =C20/$C$5 | E20: =C20/Channels!$O$9
B21: Net sales | C21: =Channels!$O$9 | D21: =C21/$C$5 | E21: =C21/Channels!$O$9
B22: Less: COGS | C22: =-Channels!$P$9 | D22: =C22/$C$5 | E22: =C22/Channels!$O$9
B23: Gross profit | C23: =Channels!$Q$9 | D23: =C23/$C$5 | E23: =C23/Channels!$O$9
B24: Less: fulfillment & freight | C24: =-Channels!$T$9 | D24: =C24/$C$5 | E24: =C24/Channels!$O$9
B25: Less: platform & selling fees | C25: =-Channels!$R$9 | D25: =C25/$C$5 | E25: =C25/Channels!$O$9
B26: Less: channel marketing (PPC/CAC) | C26: =-Channels!$S$9 | D26: =C26/$C$5 | E26: =C26/Channels!$O$9
B27: Less: slotting & listing | C27: =-Channels!$U$9 | D27: =C27/$C$5 | E27: =C27/Channels!$O$9
B28: Contribution margin | C28: =Channels!$V$9 | D28: =C28/$C$5 | E28: =C28/Channels!$O$9
B29: Less: brand marketing | C29: =-C8*Channels!$O$9 | D29: =C29/$C$5 | E29: =C29/Channels!$O$9
B30: Less: sales & team | C30: =-C9 | D30: =C30/$C$5 | E30: =C30/Channels!$O$9
B31: Less: G&A / overhead | C31: =-C10 | D31: =C31/$C$5 | E31: =C31/Channels!$O$9
B32: Less: R&D | C32: =-C11 | D32: =C32/$C$5 | E32: =C32/Channels!$O$9
B33: EBITDA | C33: =Channels!$V$9-C8*Channels!$O$9-C13 | D33: =C33/$C$5 | E33: =C33/Channels!$O$9
B34: Less: D&A | C34: =-C12 | D34: =C34/$C$5 | E34: =C34/Channels!$O$9
B35: EBIT | C35: =Channels!$V$9-C8*Channels!$O$9-C13-C12 | D35: =C35/$C$5 | E35: =C35/Channels!$O$9
B37: Break-even cases (EBITDA = 0) | C37: =C13/((Channels!$V$9/C5)-C8*(Channels!$O$9/C5))

Sheet COGS_BOM
A1: Bill of materials — landed cost per 355 ml can
A2: Edit any line (yellow). Groups roll up, then a yield-loss allowance grosses up the survivors.
A4: LIQUID & INGREDIENTS
B5: Carbonated water (RO + CO₂) | C5: 0.014
B6: Sodium / potassium citrate blend | C6: 0.055
B7: Magnesium bisglycinate | C7: 0.048
B8: Fibersol® prebiotic fiber | C8: 0.03
B9: Natural flavour | C9: 0.04
B10: Acids (citric / malic / phosphoric) | C10: 0.01
B11: Stevia extract | C11: 0.022
B12: subtotal | C12: =SUM(C5:C11)
A14: PRIMARY PACKAGING
B15: Aluminium can 355 ml (printed) | C15: 0.15
B16: Can end / lid | C16: 0.022
B17: Tab | C17: 0.004
B18: subtotal | C18: =SUM(C15:C17)
A20: SECONDARY PACKAGING
B21: Tray (per can) | C21: 0.016
B22: Shrink film (per can) | C22: 0.006
B23: subtotal | C23: =SUM(C21:C22)
A25: TERTIARY / LOGISTICS
B26: Case / carton (per can) | C26: 0.006
B27: Pallet & stretch wrap (per can) | C27: 0.003
B28: subtotal | C28: =SUM(C26:C27)
A30: CO-PACK CONVERSION
B31: Co-pack fill & seam fee | C31: 0.09
B32: Blending / batching | C32: 0.018
B33: QA / lab / coding | C33: 0.008
B34: subtotal | C34: =SUM(C31:C33)
A36: ROLL-UP TO COGS / UNIT
B37: Sum of components | C37: =C12+C18+C23+C28+C34
B38: Inbound freight / unit | C38: 0.016
B39: Landed cost before loss | C39: =C37+C38
B40: Yield / scrap loss | C40: 0.04
B41: COGS / unit (landed) | C41: =C39/(1-C40)
B42: COGS / case | C42: =C41*'P&L'!C6

Sheet Channels
A1: Channel economics — route-to-market P&L
A2: Each channel carries its own price realization and cost stack. Columns K–W are live formulas; the totals row feeds the P&L.
A4: Channel | B4: Mix % | C4: SRP | D4: Sell price | E4: Trade % | F4: Spoil % | G4: Fee % | H4: Ad % | I4: Ful $ | J4: Slot $ | K4: Units | L4: Gross | M4: Trade | N4: Spoil | O4: Net | P4: COGS | Q4: Gross profit | R4: Fees | S4: Ad | T4: Ful | U4: Slot | V4: Contribution | W4: CM %
A5: DTC (own site) | B5: 0.12 | C5: 2.99 | D5: 2.99 | E5: 0.12 | F5: 0.02 | G5: 0.03 | H5: 0.22 | I5: 0.85 | J5: 0 | K5: ='P&L'!$C$7*B5 | L5: =D5*K5 | M5: =L5*E5 | N5: =L5*F5 | O5: =L5-M5-N5 | P5: =COGS_BOM!$C$41*K5 | Q5: =O5-P5 | R5: =L5*G5 | S5: =L5*H5 | T5: =I5*K5 | U5: =J5*K5 | V5: =Q5-R5-S5-T5-U5 | W5: =IF(O5<>0,V5/O5,"")
A6: Amazon | B6: 0.18 | C6: 2.99 | D6: 2.79 | E6: 0.08 | F6: 0.03 | G6: 0.15 | H6: 0.13 | I6: 0.48 | J6: 0 | K6: ='P&L'!$C$7*B6 | L6: =D6*K6 | M6: =L6*E6 | N6: =L6*F6 | O6: =L6-M6-N6 | P6: =COGS_BOM!$C$41*K6 | Q6: =O6-P6 | R6: =L6*G6 | S6: =L6*H6 | T6: =I6*K6 | U6: =J6*K6 | V6: =Q6-R6-S6-T6-U6 | W6: =IF(O6<>0,V6/O6,"")
A7: Retail / Distributor | B7: 0.52 | C7: 2.99 | D7: 1.55 | E7: 0.15 | F7: 0.02 | G7: 0.05 | H7: 0.02 | I7: 0.11 | J7: 0.07 | K7: ='P&L'!$C$7*B7 | L7: =D7*K7 | M7: =L7*E7 | N7: =L7*F7 | O7: =L7-M7-N7 | P7: =COGS_BOM!$C$41*K7 | Q7: =O7-P7 | R7: =L7*G7 | S7: =L7*H7 | T7: =I7*K7 | U7: =J7*K7 | V7: =Q7-R7-S7-T7-U7 | W7: =IF(O7<>0,V7/O7,"")
A8: Club / Mass | B8: 0.18 | C8: 2.79 | D8: 1.4 | E8: 0.08 | F8: 0.01 | G8: 0.03 | H8: 0.01 | I8: 0.09 | J8: 0.1 | K8: ='P&L'!$C$7*B8 | L8: =D8*K8 | M8: =L8*E8 | N8: =L8*F8 | O8: =L8-M8-N8 | P8: =COGS_BOM!$C$41*K8 | Q8: =O8-P8 | R8: =L8*G8 | S8: =L8*H8 | T8: =I8*K8 | U8: =J8*K8 | V8: =Q8-R8-S8-T8-U8 | W8: =IF(O8<>0,V8/O8,"")
A9: Company total | B9: =SUM(B5:B8) | K9: =SUM(K5:K8) | L9: =SUM(L5:L8) | M9: =SUM(M5:M8) | N9: =SUM(N5:N8) | O9: =SUM(O5:O8) | P9: =SUM(P5:P8) | Q9: =SUM(Q5:Q8) | R9: =SUM(R5:R8) | ... V9: =SUM(V5:V8) | W9: =V9/O9

Sheet Sensitivity
A1: Sensitivity — EBITDA % across price × COGS
A2: Every cell re-runs the blended model for a scaled selling-price and COGS. Centre = today. Edit the range.
B3: Range ± | C3: 0.2
B6: Price ↓ / COGS → | C6: =1+$C$3*((0/3)-1) | D6: =1+$C$3*((1/3)-1) | E6: =1+$C$3*((2/3)-1) | F6: =1+$C$3*((3/3)-1) | G6: =1+$C$3*((4/3)-1) | H6: =1+$C$3*((5/3)-1) | I6: =1+$C$3*((6/3)-1)
B7: =1+$C$3*(1-(0/3)) | C7: =($B7*Channels!$O$9-C$6*Channels!$P$9-$B7*(Channels!$R$9+Channels!$S$9)-(Channels!$T$9+Channels!$U$9)-'P&L'!$C$8*$B7*Channels!$O$9-'P&L'!$C$13)/($B7*Channels!$O$9) | D7: =($B7*Channels!$O$9-D$6*Channels!$P$9-$B7*(Channels!$R$9+Channels!$S$9)-(Channels!$T$9+Channels!$U$9)-'P&L'!$C$8*$B7*Channels!$O$9-'P&L'!$C$13)/($B7*Channels!$O$9) | E7: =($B7*Channels!$O$9-E$6*Channels!$P$9-$B7*(Channels!$R$9+Channels!$S$9)-(Channels!$T$9+Channels!$U$9)-'P&L'!$C$8*$B7*Channels!$O$9-'P&L'!$C$13)/($B7*Channels!$O$9) | F7: =($B7*Channels!$O$9-F$6*Channels!$P$9-$B7*(Channels!$R$9+Channels!$S$9)-(Channels!$T$9+Channels!$U$9)-'P&L'!$C$8*$B7*Channels!$O$9-'P&L'!$C$13)/($B7*Channels!$O$9) | G7: =($B7*Channels!$O$9-G$6*Channels!$P$9-$B7*(Channels!$R$9+Channels!$S$9)-(Channels!$T$9+Channels!$U$9)-'P&L'!$C$8*$B7*Channels!$O$9-'P&L'!$C$13)/($B7*Channels!$O$9) | H7: =($B7*Channels!$O$9-H$6*Channels!$P$9-$B7*(Channels!$R$9+Channels!$S$9)-(Channels!$T$9+Channels!$U$9)-'P&L'!$C$8*$B7*Channels!$O$9-'P&L'!$C$13)/($B7*Channels!$O$9) | I7: =($B7*Channels!$O$9-I$6*Channels!$P$9-$B7*(Channels!$R$9+Channels!$S$9)-(Channels!$T$9+Channels!$U$9)-'P&L'!$C$8*$B7*Channels!$O$9-'P&L'!$C$13)/($B7*Channels!$O$9)
B8: =1+$C$3*(1-(1/3)) | C8: =($B8*Channels!$O$9-C$6*Channels!$P$9-$B8*(Channels!$R$9+Channels!$S$9)-(Channels!$T$9+Channels!$U$9)-'P&L'!$C$8*$B8*Channels!$O$9-'P&L'!$C$13)/($B8*Channels!$O$9) | D8: =($B8*Channels!$O$9-D$6*Channels!$P$9-$B8*(Channels!$R$9+Channels!$S$9)-(Channels!$T$9+Channels!$U$9)-'P&L'!$C$8*$B8*Channels!$O$9-'P&L'!$C$13)/($B8*Channels!$O$9) | E8: =($B8*Channels!$O$9-E$6*Channels!$P$9-$B8*(Channels!$R$9+Channels!$S$9)-(Channels!$T$9+Channels!$U$9)-'P&L'!$C$8*$B8*Channels!$O$9-'P&L'!$C$13)/($B8*Channels!$O$9) | F8: =($B8*Channels!$O$9-F$6*Channels!$P$9-$B8*(Channels!$R$9+Channels!$S$9)-(Channels!$T$9+Channels!$U$9)-'P&L'!$C$8*$B8*Channels!$O$9-'P&L'!$C$13)/($B8*Channels!$O$9) | G8: =($B8*Channels!$O$9-G$6*Channels!$P$9-$B8*(Channels!$R$9+Channels!$S$9)-(Channels!$T$9+Channels!$U$9)-'P&L'!$C$8*$B8*Channels!$O$9-'P&L'!$C$13)/($B8*Channels!$O$9) | H8: =($B8*Channels!$O$9-H$6*Channels!$P$9-$B8*(Channels!$R$9+Channels!$S$9)-(Channels!$T$9+Channels!$U$9)-'P&L'!$C$8*$B8*Channels!$O$9-'P&L'!$C$13)/($B8*Channels!$O$9) | I8: =($B8*Channels!$O$9-I$6*Channels!$P$9-$B8*(Channels!$R$9+Channels!$S$9)-(Channels!$T$9+Channels!$U$9)-'P&L'!$C$8*$B8*Channels!$O$9-'P&L'!$C$13)/($B8*Channels!$O$9)
B9: =1+$C$3*(1-(2/3)) | C9: =($B9*Channels!$O$9-C$6*Channels!$P$9-$B9*(Channels!$R$9+Channels!$S$9)-(Channels!$T$9+Channels!$U$9)-'P&L'!$C$8*$B9*Channels!$O$9-'P&L'!$C$13)/($B9*Channels!$O$9) | D9: =($B9*Channels!$O$9-D$6*Channels!$P$9-$B9*(Channels!$R$9+Channels!$S$9)-(Channels!$T$9+Channels!$U$9)-'P&L'!$C$8*$B9*Channels!$O$9-'P&L'!$C$13)/($B9*Channels!$O$9) | E9: =($B9*Channels!$O$9-E$6*Channels!$P$9-$B9*(Channels!$R$9+Channels!$S$9)-(Channels!$T$9+Channels!$U$9)-'P&L'!$C$8*$B9*Channels!$O$9-'P&L'!$C$13)/($B9*Channels!$O$9) | F9: =($B9*Channels!$O$9-F$6*Channels!$P$9-$B9*(Channels!$R$9+Channels!$S$9)-(Channels!$T$9+Channels!$U$9)-'P&L'!$C$8*$B9*Channels!$O$9-'P&L'!$C$13)/($B9*Channels!$O$9) | G9: =($B9*Channels!$O$9-G$6*Channels!$P$9-$B9*(Channels!$R$9+Channels!$S$9)-(Channels!$T$9+Channels!$U$9)-'P&L'!$C$8*$B9*Channels!$O$9-'P&L'!$C$13)/($B9*Channels!$O$9) | H9: =($B9*Channels!$O$9-H$6*Channels!$P$9-$B9*(Channels!$R$9+Channels!$S$9)-(Channels!$T$9+Channels!$U$9)-'P&L'!$C$8*$B9*Channels!$O$9-'P&L'!$C$13)/($B9*Channels!$O$9) | I9: =($B9*Channels!$O$9-I$6*Channels!$P$9-$B9*(Channels!$R$9+Channels!$S$9)-(Channels!$T$9+Channels!$U$9)-'P&L'!$C$8*$B9*Channels!$O$9-'P&L'!$C$13)/($B9*Channels!$O$9)
B10: =1+$C$3*(1-(3/3)) | C10: =($B10*Channels!$O$9-C$6*Channels!$P$9-$B10*(Channels!$R$9+Channels!$S$9)-(Channels!$T$9+Channels!$U$9)-'P&L'!$C$8*$B10*Channels!$O$9-'P&L'!$C$13)/($B10*Channels!$O$9) | D10: =($B10*Channels!$O$9-D$6*Channels!$P$9-$B10*(Channels!$R$9+Channels!$S$9)-(Channels!$T$9+Channels!$U$9)-'P&L'!$C$8*$B10*Channels!$O$9-'P&L'!$C$13)/($B10*Channels!$O$9) | E10: =($B10*Channels!$O$9-E$6*Channels!$P$9-$B10*(Channels!$R$9+Channels!$S$9)-(Channels!$T$9+Channels!$U$9)-'P&L'!$C$8*$B10*Channels!$O$9-'P&L'!$C$13)/($B10*Channels!$O$9) | F10: =($B10*Channels!$O$9-F$6*Channels!$P$9-$B10*(Channels!$R$9+Channels!$S$9)-(Channels!$T$9+Channels!$U$9)-'P&L'!$C$8*$B10*Channels!$O$9-'P&L'!$C$13)/($B10*Channels!$O$9) | G10: =($B10*Channels!$O$9-G$6*Channels!$P$9-$B10*(Channels!$R$9+Channels!$S$9)-(Channels!$T$9+Channels!$U$9)-'P&L'!$C$8*$B10*Channels!$O$9-'P&L'!$C$13)/($B10*Channels!$O$9) | H10: =($B10*Channels!$O$9-H$6*Channels!$P$9-$B10*(Channels!$R$9+Channels!$S$9)-(Channels!$T$9+Channels!$U$9)-'P&L'!$C$8*$B10*Channels!$O$9-'P&L'!$C$13)/($B10*Channels!$O$9) | I10: =($B10*Channels!$O$9-I$6*Channels!$P$9-$B10*(Channels!$R$9+Channels!$S$9)-(Channels!$T$9+Channels!$U$9)-'P&L'!$C$8*$B10*Channels!$O$9-'P&L'!$C$13)/($B10*Channels!$O$9)
B11: =1+$C$3*(1-(4/3)) | C11: =($B11*Channels!$O$9-C$6*Channels!$P$9-$B11*(Channels!$R$9+Channels!$S$9)-(Channels!$T$9+Channels!$U$9)-'P&L'!$C$8*$B11*Channels!$O$9-'P&L'!$C$13)/($B11*Channels!$O$9) | D11: =($B11*Channels!$O$9-D$6*Channels!$P$9-$B11*(Channels!$R$9+Channels!$S$9)-(Channels!$T$9+Channels!$U$9)-'P&L'!$C$8*$B11*Channels!$O$9-'P&L'!$C$13)/($B11*Channels!$O$9) | E11: =($B11*Channels!$O$9-E$6*Channels!$P$9-$B11*(Channels!$R$9+Channels!$S$9)-(Channels!$T$9+Channels!$U$9)-'P&L'!$C$8*$B11*Channels!$O$9-'P&L'!$C$13)/($B11*Channels!$O$9) | F11: =($B11*Channels!$O$9-F$6*Channels!$P$9-$B11*(Channels!$R$9+Channels!$S$9)-(Channels!$T$9+Channels!$U$9)-'P&L'!$C$8*$B11*Channels!$O$9-'P&L'!$C$13)/($B11*Channels!$O$9) | G11: =($B11*Channels!$O$9-G$6*Channels!$P$9-$B11*(Channels!$R$9+Channels!$S$9)-(Channels!$T$9+Channels!$U$9)-'P&L'!$C$8*$B11*Channels!$O$9-'P&L'!$C$13)/($B11*Channels!$O$9) | H11: =($B11*Channels!$O$9-H$6*Channels!$P$9-$B11*(Channels!$R$9+Channels!$S$9)-(Channels!$T$9+Channels!$U$9)-'P&L'!$C$8*$B11*Channels!$O$9-'P&L'!$C$13)/($B11*Channels!$O$9) | I11: =($B11*Channels!$O$9-I$6*Channels!$P$9-$B11*(Channels!$R$9+Channels!$S$9)-(Channels!$T$9+Channels!$U$9)-'P&L'!$C$8*$B11*Channels!$O$9-'P&L'!$C$13)/($B11*Channels!$O$9)
B12: =1+$C$3*(1-(5/3)) | C12: =($B12*Channels!$O$9-C$6*Channels!$P$9-$B12*(Channels!$R$9+Channels!$S$9)-(Channels!$T$9+Channels!$U$9)-'P&L'!$C$8*$B12*Channels!$O$9-'P&L'!$C$13)/($B12*Channels!$O$9) | D12: =($B12*Channels!$O$9-D$6*Channels!$P$9-$B12*(Channels!$R$9+Channels!$S$9)-(Channels!$T$9+Channels!$U$9)-'P&L'!$C$8*$B12*Channels!$O$9-'P&L'!$C$13)/($B12*Channels!$O$9) | E12: =($B12*Channels!$O$9-E$6*Channels!$P$9-$B12*(Channels!$R$9+Channels!$S$9)-(Channels!$T$9+Channels!$U$9)-'P&L'!$C$8*$B12*Channels!$O$9-'P&L'!$C$13)/($B12*Channels!$O$9) | F12: =($B12*Channels!$O$9-F$6*Channels!$P$9-$B12*(Channels!$R$9+Channels!$S$9)-(Channels!$T$9+Channels!$U$9)-'P&L'!$C$8*$B12*Channels!$O$9-'P&L'!$C$13)/($B12*Channels!$O$9) | G12: =($B12*Channels!$O$9-G$6*Channels!$P$9-$B12*(Channels!$R$9+Channels!$S$9)-(Channels!$T$9+Channels!$U$9)-'P&L'!$C$8*$B12*Channels!$O$9-'P&L'!$C$13)/($B12*Channels!$O$9) | H12: =($B12*Channels!$O$9-H$6*Channels!$P$9-$B12*(Channels!$R$9+Channels!$S$9)-(Channels!$T$9+Channels!$U$9)-'P&L'!$C$8*$B12*Channels!$O$9-'P&L'!$C$13)/($B12*Channels!$O$9) | I12: =($B12*Channels!$O$9-I$6*Channels!$P$9-$B12*(Channels!$R$9+Channels!$S$9)-(Channels!$T$9+Channels!$U$9)-'P&L'!$C$8*$B12*Channels!$O$9-'P&L'!$C$13)/($B12*Channels!$O$9)
B13: =1+$C$3*(1-(6/3)) | C13: =($B13*Channels!$O$9-C$6*Channels!$P$9-$B13*(Channels!$R$9+Channels!$S$9)-(Channels!$T$9+Channels!$U$9)-'P&L'!$C$8*$B13*Channels!$O$9-'P&L'!$C$13)/($B13*Channels!$O$9) | D13: =($B13*Channels!$O$9-D$6*Channels!$P$9-$B13*(Channels!$R$9+Channels!$S$9)-(Channels!$T$9+Channels!$U$9)-'P&L'!$C$8*$B13*Channels!$O$9-'P&L'!$C$13)/($B13*Channels!$O$9) | E13: =($B13*Channels!$O$9-E$6*Channels!$P$9-$B13*(Channels!$R$9+Channels!$S$9)-(Channels!$T$9+Channels!$U$9)-'P&L'!$C$8*$B13*Channels!$O$9-'P&L'!$C$13)/($B13*Channels!$O$9) | F13: =($B13*Channels!$O$9-F$6*Channels!$P$9-$B13*(Channels!$R$9+Channels!$S$9)-(Channels!$T$9+Channels!$U$9)-'P&L'!$C$8*$B13*Channels!$O$9-'P&L'!$C$13)/($B13*Channels!$O$9) | G13: =($B13*Channels!$O$9-G$6*Channels!$P$9-$B13*(Channels!$R$9+Channels!$S$9)-(Channels!$T$9+Channels!$U$9)-'P&L'!$C$8*$B13*Channels!$O$9-'P&L'!$C$13)/($B13*Channels!$O$9) | H13: =($B13*Channels!$O$9-H$6*Channels!$P$9-$B13*(Channels!$R$9+Channels!$S$9)-(Channels!$T$9+Channels!$U$9)-'P&L'!$C$8*$B13*Channels!$O$9-'P&L'!$C$13)/($B13*Channels!$O$9) | I13: =($B13*Channels!$O$9-I$6*Channels!$P$9-$B13*(Channels!$R$9+Channels!$S$9)-(Channels!$T$9+Channels!$U$9)-'P&L'!$C$8*$B13*Channels!$O$9-'P&L'!$C$13)/($B13*Channels!$O$9)
B15: Green = higher EBITDA margin. The steeper the colour shift along a row vs a column, the bigger that lever.

Sheet Scenarios
A1: Scenario planning — Base / Bull / Bear
A2: Bull and Bear scale your Base assumptions. Multipliers are editable; metrics derive from the channel totals.
B4: Multiplier | C4: Base | D4: Bull | E4: Bear
B5: Volume × | C5: 1 | D5: 1.4 | E5: 0.75
B6: Price × | C6: 1 | D6: 1.05 | E6: 0.97
B7: COGS × | C7: 1 | D7: 0.9 | E7: 1.1
B8: Trade × | C8: 1 | D8: 0.85 | E8: 1.15
B9: Ad / CAC × | C9: 1 | D9: 0.85 | E9: 1.2
A11: RESULTING P&L
B12: Metric | C12: Base | D12: Bull | E12: Bear
B13: Annual cases | C13: ='P&L'!$C$5*C5 | D13: ='P&L'!$C$5*D5 | E13: ='P&L'!$C$5*E5
B14: Net sales | C14: =(C6*C5*(Channels!$L$9-C8*Channels!$M$9-Channels!$N$9)) | D14: =(D6*D5*(Channels!$L$9-D8*Channels!$M$9-Channels!$N$9)) | E14: =(E6*E5*(Channels!$L$9-E8*Channels!$M$9-Channels!$N$9))
B15: Gross margin % | C15: =((C6*C5*(Channels!$L$9-C8*Channels!$M$9-Channels!$N$9))-C7*C5*Channels!$P$9)/(C6*C5*(Channels!$L$9-C8*Channels!$M$9-Channels!$N$9)) | D15: =((D6*D5*(Channels!$L$9-D8*Channels!$M$9-Channels!$N$9))-D7*D5*Channels!$P$9)/(D6*D5*(Channels!$L$9-D8*Channels!$M$9-Channels!$N$9)) | E15: =((E6*E5*(Channels!$L$9-E8*Channels!$M$9-Channels!$N$9))-E7*E5*Channels!$P$9)/(E6*E5*(Channels!$L$9-E8*Channels!$M$9-Channels!$N$9))
B16: Contribution $ | C16: =(((C6*C5*(Channels!$L$9-C8*Channels!$M$9-Channels!$N$9))-C7*C5*Channels!$P$9)-C6*C5*Channels!$R$9-C9*C6*C5*Channels!$S$9-C5*Channels!$T$9-C5*Channels!$U$9) | D16: =(((D6*D5*(Channels!$L$9-D8*Channels!$M$9-Channels!$N$9))-D7*D5*Channels!$P$9)-D6*D5*Channels!$R$9-D9*D6*D5*Channels!$S$9-D5*Channels!$T$9-D5*Channels!$U$9) | E16: =(((E6*E5*(Channels!$L$9-E8*Channels!$M$9-Channels!$N$9))-E7*E5*Channels!$P$9)-E6*E5*Channels!$R$9-E9*E6*E5*Channels!$S$9-E5*Channels!$T$9-E5*Channels!$U$9)
B17: Contribution % | C17: =(((C6*C5*(Channels!$L$9-C8*Channels!$M$9-Channels!$N$9))-C7*C5*Channels!$P$9)-C6*C5*Channels!$R$9-C9*C6*C5*Channels!$S$9-C5*Channels!$T$9-C5*Channels!$U$9)/(C6*C5*(Channels!$L$9-C8*Channels!$M$9-Channels!$N$9)) | D17: =(((D6*D5*(Channels!$L$9-D8*Channels!$M$9-Channels!$N$9))-D7*D5*Channels!$P$9)-D6*D5*Channels!$R$9-D9*D6*D5*Channels!$S$9-D5*Channels!$T$9-D5*Channels!$U$9)/(D6*D5*(Channels!$L$9-D8*Channels!$M$9-Channels!$N$9)) | E17: =(((E6*E5*(Channels!$L$9-E8*Channels!$M$9-Channels!$N$9))-E7*E5*Channels!$P$9)-E6*E5*Channels!$R$9-E9*E6*E5*Channels!$S$9-E5*Channels!$T$9-E5*Channels!$U$9)/(E6*E5*(Channels!$L$9-E8*Channels!$M$9-Channels!$N$9))
B18: EBITDA $ | C18: =((((C6*C5*(Channels!$L$9-C8*Channels!$M$9-Channels!$N$9))-C7*C5*Channels!$P$9)-C6*C5*Channels!$R$9-C9*C6*C5*Channels!$S$9-C5*Channels!$T$9-C5*Channels!$U$9)-'P&L'!$C$8*(C6*C5*(Channels!$L$9-C8*Channels!$M$9-Channels!$N$9))-'P&L'!$C$13) | D18: =((((D6*D5*(Channels!$L$9-D8*Channels!$M$9-Channels!$N$9))-D7*D5*Channels!$P$9)-D6*D5*Channels!$R$9-D9*D6*D5*Channels!$S$9-D5*Channels!$T$9-D5*Channels!$U$9)-'P&L'!$C$8*(D6*D5*(Channels!$L$9-D8*Channels!$M$9-Channels!$N$9))-'P&L'!$C$13) | E18: =((((E6*E5*(Channels!$L$9-E8*Channels!$M$9-Channels!$N$9))-E7*E5*Channels!$P$9)-E6*E5*Channels!$R$9-E9*E6*E5*Channels!$S$9-E5*Channels!$T$9-E5*Channels!$U$9)-'P&L'!$C$8*(E6*E5*(Channels!$L$9-E8*Channels!$M$9-Channels!$N$9))-'P&L'!$C$13)
B19: EBITDA % | C19: =((((C6*C5*(Channels!$L$9-C8*Channels!$M$9-Channels!$N$9))-C7*C5*Channels!$P$9)-C6*C5*Channels!$R$9-C9*C6*C5*Channels!$S$9-C5*Channels!$T$9-C5*Channels!$U$9)-'P&L'!$C$8*(C6*C5*(Channels!$L$9-C8*Channels!$M$9-Channels!$N$9))-'P&L'!$C$13)/(C6*C5*(Channels!$L$9-C8*Channels!$M$9-Channels!$N$9)) | D19: =((((D6*D5*(Channels!$L$9-D8*Channels!$M$9-Channels!$N$9))-D7*D5*Channels!$P$9)-D6*D5*Channels!$R$9-D9*D6*D5*Channels!$S$9-D5*Channels!$T$9-D5*Channels!$U$9)-'P&L'!$C$8*(D6*D5*(Channels!$L$9-D8*Channels!$M$9-Channels!$N$9))-'P&L'!$C$13)/(D6*D5*(Channels!$L$9-D8*Channels!$M$9-Channels!$N$9)) | E19: =((((E6*E5*(Channels!$L$9-E8*Channels!$M$9-Channels!$N$9))-E7*E5*Channels!$P$9)-E6*E5*Channels!$R$9-E9*E6*E5*Channels!$S$9-E5*Channels!$T$9-E5*Channels!$U$9)-'P&L'!$C$8*(E6*E5*(Channels!$L$9-E8*Channels!$M$9-Channels!$N$9))-'P&L'!$C$13)/(E6*E5*(Channels!$L$9-E8*Channels!$M$9-Channels!$N$9))

Sheet Guide
A1: Guide — reading a CPG P&L
B5: The waterfall
B6: Gross Sales − Trade − Returns = NET SALES
B7: Net Sales − COGS = GROSS PROFIT (Gross Margin %)
B8: Gross Profit − fulfillment − fees − channel ad − slotting = CONTRIBUTION MARGIN (CM %)
B9: Contribution − brand marketing − sales − G&A − R&D = EBITDA (EBITDA %)
B11: Why contribution margin is the number to watch
B12: Gross margin flatters DTC and Amazon because their shelf prices are high — but those channels
B13: bleed it back through referral fees, fulfillment and customer acquisition. Contribution margin is
B14: what each channel actually leaves to cover corporate overhead. Manage the mix on contribution.
B16: Where the levers are (see the Sensitivity & tornado)
B17: • COGS — every cent off a can flows straight to EBITDA at full volume.
B18: • Price & trade — highest-leverage revenue dials, but trade is sticky once retailers expect it.
... B30: + Fibersol prebiotic fiber) as a representative premium functional beverage. Replace with your actuals.
