Workbook
Name LU_Owner: OFFSET(Lookups!$A$3,0,0,MAX(1,COUNTA(Lookups!$A$3:$A$1000)),1)
Name LU_Type: OFFSET(Lookups!$B$3,0,0,MAX(1,COUNTA(Lookups!$B$3:$B$1000)),1)
Name LU_Priority: OFFSET(Lookups!$C$3,0,0,MAX(1,COUNTA(Lookups!$C$3:$C$1000)),1)
Name LU_Status: OFFSET(Lookups!$D$3,0,0,MAX(1,COUNTA(Lookups!$D$3:$D$1000)),1)
Name LU_Warm: OFFSET(Lookups!$E$3,0,0,MAX(1,COUNTA(Lookups!$E$3:$E$1000)),1)
Name LU_Source: OFFSET(Lookups!$F$3,0,0,MAX(1,COUNTA(Lookups!$F$3:$F$1000)),1)
Name LU_Activation: OFFSET(Lookups!$G$3,0,0,MAX(1,COUNTA(Lookups!$G$3:$G$1000)),1)
Name LU_Want: OFFSET(Lookups!$H$3,0,0,MAX(1,COUNTA(Lookups!$H$3:$H$1000)),1)
Name LU_Risks: OFFSET(Lookups!$I$3,0,0,MAX(1,COUNTA(Lookups!$I$3:$I$1000)),1)
Name LU_InBC: OFFSET(Lookups!$J$3,0,0,MAX(1,COUNTA(Lookups!$J$3:$J$1000)),1)
Name LU_SKU: OFFSET(Lookups!$K$3,0,0,MAX(1,COUNTA(Lookups!$K$3:$K$1000)),1)
Name LU_Role: OFFSET(Lookups!$L$3,0,0,MAX(1,COUNTA(Lookups!$L$3:$L$1000)),1)
Name LU_City: OFFSET(Lookups!$M$3,0,0,MAX(1,COUNTA(Lookups!$M$3:$M$1000)),1)
Name LU_Neighbourhood: OFFSET(Lookups!$N$3,0,0,MAX(1,COUNTA(Lookups!$N$3:$N$1000)),1)
Name LU_EventStatus: OFFSET(Lookups!$O$3,0,0,MAX(1,COUNTA(Lookups!$O$3:$O$1000)),1)

Sheet Dashboard
A1: Organika RTD · Community Partnerships Command Centre
A2: Live overview. Every number updates on its own as the team works the type tabs. | L2: ="As of "&TEXT(TODAY(),"yyyy/mm/dd")
A4: Total Partners | C4: P1 Partners | E4: Active Conversations | G4: Activations Booked | I4: Cans Sampled to Date | K4: Cost Per Can Sampled | M4: Days Until Costco Road Show
A5: =SUM(E8:E15) | C5: =COUNTIF('Master List'!$E$3:$E$500,"P1") | E5: =COUNTIF('Master List'!$F$3:$F$500,"Outreach Sent")+COUNTIF('Master List'!$F$3:$F$500,"In Conversation")+COUNTIF('Master List'!$F$3:$F$500,"Proposal Sent")+COUNTIF('Master List'!$F$3:$F$500,"Agreed") | G5: =COUNT('Master List'!$V$3:$V$500) | I5: =24*SUM('Master List'!$X$3:$X$500) | K5: =IFERROR(SUM('Master List'!$Y$3:$Y$500)/(24*SUM('Master List'!$X$3:$X$500)),0) | M5: =MAX(0,DATE(2026,8,1)-TODAY())
A7: Pipeline by Stage | B7: Count | D7: Partners by Type | E7: Count | G7: Priority | H7: Count | J7: Budget | K7: $
A8: Open | B8: =COUNTIF('Master List'!$F$3:$F$500,"Open") | D8: Run Clubs | E8: =COUNTA('Run Clubs'!$B$3:$B$32) | G8: P1 | H8: =COUNTIF('Master List'!$E$3:$E$500,"P1") | J8: Total Budget | K8: =Budget!B14
A9: Outreach Sent | B9: =COUNTIF('Master List'!$F$3:$F$500,"Outreach Sent") | D9: Gyms & Studios | E9: =COUNTA('Gyms & Studios'!$B$3:$B$32) | G9: P2 | H9: =COUNTIF('Master List'!$E$3:$E$500,"P2") | J9: Committed | K9: =Budget!C14
A10: In Conversation | B10: =COUNTIF('Master List'!$F$3:$F$500,"In Conversation") | D10: Events & Festivals | E10: =COUNTA('Events & Festivals'!$B$3:$B$32) | G10: P3 | H10: =COUNTIF('Master List'!$E$3:$E$500,"P3") | J10: Spent | K10: =Budget!D14
A11: Proposal Sent | B11: =COUNTIF('Master List'!$F$3:$F$500,"Proposal Sent") | D11: Sports Teams & Leagues | E11: =COUNTA('Sports Teams & Leagues'!$B$3:$B$32) | J11: Remaining | K11: =Budget!E14
A12: Agreed | B12: =COUNTIF('Master List'!$F$3:$F$500,"Agreed") | D12: Campus & Student Groups | E12: =COUNTA('Campus & Student Groups'!$B$3:$B$32) | G12: Activations | H12: Count | J12: % Spent | K12: =Budget!F14
A13: Activated | B13: =COUNTIF('Master List'!$F$3:$F$500,"Activated") | D13: Wellness & Recovery | E13: =COUNTA('Wellness & Recovery'!$B$3:$B$32) | G13: Next 30 Days | H13: =COUNTIFS('Master List'!$V$3:$V$500,">="&TODAY(),'Master List'!$V$3:$V$500,"<="&TODAY()+30)
A14: Repeat Partner | B14: =COUNTIF('Master List'!$F$3:$F$500,"Repeat Partner") | D14: Ambassadors & Creators | E14: =COUNTA('Ambassadors & Creators'!$B$3:$B$32) | G14: Next 60 Days | H14: =COUNTIFS('Master List'!$V$3:$V$500,">="&TODAY(),'Master List'!$V$3:$V$500,"<="&TODAY()+60) | J14: SKU Status | K14: Requested | L14: Sampled | M14: Stocked
A15: Lost | B15: =COUNTIF('Master List'!$F$3:$F$500,"Lost") | D15: Charity & Causes | E15: =COUNTA('Charity & Causes'!$B$3:$B$32) | G15: Next 90 Days | H15: =COUNTIFS('Master List'!$V$3:$V$500,">="&TODAY(),'Master List'!$V$3:$V$500,"<="&TODAY()+90) | J15: Raspberry 4338 | K15: =COUNTIF('Master List'!$AH$3:$AH$500,"Requested") | L15: =COUNTIF('Master List'!$AH$3:$AH$500,"Sampled") | M15: =COUNTIF('Master List'!$AH$3:$AH$500,"Stocked")
A16: On Hold | B16: =COUNTIF('Master List'!$F$3:$F$500,"On Hold") | J16: Lemon Lime 4336 | K16: =COUNTIF('Master List'!$AI$3:$AI$500,"Requested") | L16: =COUNTIF('Master List'!$AI$3:$AI$500,"Sampled") | M16: =COUNTIF('Master List'!$AI$3:$AI$500,"Stocked")
G17: Region | H17: Count | J17: Pineapple Passion Fruit 4340 | K17: =COUNTIF('Master List'!$AJ$3:$AJ$500,"Requested") | L17: =COUNTIF('Master List'!$AJ$3:$AJ$500,"Sampled") | M17: =COUNTIF('Master List'!$AJ$3:$AJ$500,"Stocked")
A18: List Health | B18: Count | G18: Metro Vancouver | H18: =COUNTIF('Master List'!$C$3:$C$500,"Vancouver")+COUNTIF('Master List'!$C$3:$C$500,"Burnaby")+COUNTIF('Master List'!$C$3:$C$500,"North Vancouver")+COUNTIF('Master List'!$C$3:$C$500,"West Vancouver")+COUNTIF('Master List'!$C$3:$C$500,"Richmond")+COUNTIF('Master List'!$C$3:$C$500,"Surrey")+COUNTIF('Master List'!$C$3:$C$500,"Langley")+COUNTIF('Master List'!$C$3:$C$500,"Coquitlam")+COUNTIF('Master List'!$C$3:$C$500,"New Westminster")
A19: Overdue Next Actions | B19: =COUNTIF('Master List'!$T$3:$T$500,"<"&TODAY()) | G19: Victoria | H19: =COUNTIF('Master List'!$C$3:$C$500,"Victoria")
A20: Stale P1 Over 7 Days | B20: =COUNTIFS('Master List'!$E$3:$E$500,"P1",'Master List'!$R$3:$R$500,">7") | G20: Kelowna | H20: =COUNTIF('Master List'!$C$3:$C$500,"Kelowna")
A21: Verified Rows | B21: =COUNTIF('Master List'!$O$3:$O$500,"Verified Web")+COUNTIF('Master List'!$O$3:$O$500,"Verified Phone")+COUNTIF('Master List'!$O$3:$O$500,"Verified In Person")
A22: Pending Rows | B22: =COUNTIF('Master List'!$O$3:$O$500,"Pending")
A23: Unverified Rows | B23: =COUNTIF('Master List'!$O$3:$O$500,"Unverified")
A25: Every figure and chart refreshes on its own. To change a record, edit its type tab. The Master List, Calendar, tiles and charts all update automatically.

Sheet Activation Calendar
A1: Activation Calendar (every booked activation, soonest first)
A2: Activation Date | B2: Partner | C2: Type | D2: Owner | E2: Cases Committed | F2: Status | G2: Nearby Retail Doors
A3: =IFERROR(INDEX('Master List'!$V$3:$V$500,$I3),"") | B3: =IFERROR(INDEX('Master List'!$B$3:$B$500,$I3),"") | C3: =IFERROR(INDEX('Master List'!$A$3:$A$500,$I3),"") | D3: =IFERROR(INDEX('Master List'!$G$3:$G$500,$I3),"") | E3: =IFERROR(INDEX('Master List'!$W$3:$W$500,$I3),"") | F3: =IFERROR(INDEX('Master List'!$F$3:$F$500,$I3),"") | G3: =IFERROR(INDEX('Master List'!$AF$3:$AF$500,$I3),"") | I3: =IFERROR(MATCH(SMALL('Master List'!$AL$3:$AL$500,ROW()-2),'Master List'!$AL$3:$AL$500,0),"")
A4: =IFERROR(INDEX('Master List'!$V$3:$V$500,$I4),"") | B4: =IFERROR(INDEX('Master List'!$B$3:$B$500,$I4),"") | C4: =IFERROR(INDEX('Master List'!$A$3:$A$500,$I4),"") | D4: =IFERROR(INDEX('Master List'!$G$3:$G$500,$I4),"") | E4: =IFERROR(INDEX('Master List'!$W$3:$W$500,$I4),"") | F4: =IFERROR(INDEX('Master List'!$F$3:$F$500,$I4),"") | G4: =IFERROR(INDEX('Master List'!$AF$3:$AF$500,$I4),"") | I4: =IFERROR(MATCH(SMALL('Master List'!$AL$3:$AL$500,ROW()-2),'Master List'!$AL$3:$AL$500,0),"")
A5: =IFERROR(INDEX('Master List'!$V$3:$V$500,$I5),"") | B5: =IFERROR(INDEX('Master List'!$B$3:$B$500,$I5),"") | C5: =IFERROR(INDEX('Master List'!$A$3:$A$500,$I5),"") | D5: =IFERROR(INDEX('Master List'!$G$3:$G$500,$I5),"") | E5: =IFERROR(INDEX('Master List'!$W$3:$W$500,$I5),"") | F5: =IFERROR(INDEX('Master List'!$F$3:$F$500,$I5),"") | G5: =IFERROR(INDEX('Master List'!$AF$3:$AF$500,$I5),"") | I5: =IFERROR(MATCH(SMALL('Master List'!$AL$3:$AL$500,ROW()-2),'Master List'!$AL$3:$AL$500,0),"")
A6: =IFERROR(INDEX('Master List'!$V$3:$V$500,$I6),"") | B6: =IFERROR(INDEX('Master List'!$B$3:$B$500,$I6),"") | C6: =IFERROR(INDEX('Master List'!$A$3:$A$500,$I6),"") | D6: =IFERROR(INDEX('Master List'!$G$3:$G$500,$I6),"") | E6: =IFERROR(INDEX('Master List'!$W$3:$W$500,$I6),"") | F6: =IFERROR(INDEX('Master List'!$F$3:$F$500,$I6),"") | G6: =IFERROR(INDEX('Master List'!$AF$3:$AF$500,$I6),"") | I6: =IFERROR(MATCH(SMALL('Master List'!$AL$3:$AL$500,ROW()-2),'Master List'!$AL$3:$AL$500,0),"")
A7: =IFERROR(INDEX('Master List'!$V$3:$V$500,$I7),"") | B7: =IFERROR(INDEX('Master List'!$B$3:$B$500,$I7),"") | C7: =IFERROR(INDEX('Master List'!$A$3:$A$500,$I7),"") | D7: =IFERROR(INDEX('Master List'!$G$3:$G$500,$I7),"") | E7: =IFERROR(INDEX('Master List'!$W$3:$W$500,$I7),"") | F7: =IFERROR(INDEX('Master List'!$F$3:$F$500,$I7),"") | G7: =IFERROR(INDEX('Master List'!$AF$3:$AF$500,$I7),"") | I7: =IFERROR(MATCH(SMALL('Master List'!$AL$3:$AL$500,ROW()-2),'Master List'!$AL$3:$AL$500,0),"")
A8: =IFERROR(INDEX('Master List'!$V$3:$V$500,$I8),"") | B8: =IFERROR(INDEX('Master List'!$B$3:$B$500,$I8),"") | C8: =IFERROR(INDEX('Master List'!$A$3:$A$500,$I8),"") | D8: =IFERROR(INDEX('Master List'!$G$3:$G$500,$I8),"") | E8: =IFERROR(INDEX('Master List'!$W$3:$W$500,$I8),"") | F8: =IFERROR(INDEX('Master List'!$F$3:$F$500,$I8),"") | G8: =IFERROR(INDEX('Master List'!$AF$3:$AF$500,$I8),"") | I8: =IFERROR(MATCH(SMALL('Master List'!$AL$3:$AL$500,ROW()-2),'Master List'!$AL$3:$AL$500,0),"")
A9: =IFERROR(INDEX('Master List'!$V$3:$V$500,$I9),"") | B9: =IFERROR(INDEX('Master List'!$B$3:$B$500,$I9),"") | C9: =IFERROR(INDEX('Master List'!$A$3:$A$500,$I9),"") | D9: =IFERROR(INDEX('Master List'!$G$3:$G$500,$I9),"") | E9: =IFERROR(INDEX('Master List'!$W$3:$W$500,$I9),"") | F9: =IFERROR(INDEX('Master List'!$F$3:$F$500,$I9),"") | G9: =IFERROR(INDEX('Master List'!$AF$3:$AF$500,$I9),"") | I9: =IFERROR(MATCH(SMALL('Master List'!$AL$3:$AL$500,ROW()-2),'Master List'!$AL$3:$AL$500,0),"")
A10: =IFERROR(INDEX('Master List'!$V$3:$V$500,$I10),"") | B10: =IFERROR(INDEX('Master List'!$B$3:$B$500,$I10),"") | C10: =IFERROR(INDEX('Master List'!$A$3:$A$500,$I10),"") | D10: =IFERROR(INDEX('Master List'!$G$3:$G$500,$I10),"") | E10: =IFERROR(INDEX('Master List'!$W$3:$W$500,$I10),"") | F10: =IFERROR(INDEX('Master List'!$F$3:$F$500,$I10),"") | G10: =IFERROR(INDEX('Master List'!$AF$3:$AF$500,$I10),"") | I10: =IFERROR(MATCH(SMALL('Master List'!$AL$3:$AL$500,ROW()-2),'Master List'!$AL$3:$AL$500,0),"")
A11: =IFERROR(INDEX('Master List'!$V$3:$V$500,$I11),"") | B11: =IFERROR(INDEX('Master List'!$B$3:$B$500,$I11),"") | C11: =IFERROR(INDEX('Master List'!$A$3:$A$500,$I11),"") | D11: =IFERROR(INDEX('Master List'!$G$3:$G$500,$I11),"") | E11: =IFERROR(INDEX('Master List'!$W$3:$W$500,$I11),"") | F11: =IFERROR(INDEX('Master List'!$F$3:$F$500,$I11),"") | G11: =IFERROR(INDEX('Master List'!$AF$3:$AF$500,$I11),"") | I11: =IFERROR(MATCH(SMALL('Master List'!$AL$3:$AL$500,ROW()-2),'Master List'!$AL$3:$AL$500,0),"")
A12: =IFERROR(INDEX('Master List'!$V$3:$V$500,$I12),"") | B12: =IFERROR(INDEX('Master List'!$B$3:$B$500,$I12),"") | C12: =IFERROR(INDEX('Master List'!$A$3:$A$500,$I12),"") | D12: =IFERROR(INDEX('Master List'!$G$3:$G$500,$I12),"") | E12: =IFERROR(INDEX('Master List'!$W$3:$W$500,$I12),"") | F12: =IFERROR(INDEX('Master List'!$F$3:$F$500,$I12),"") | G12: =IFERROR(INDEX('Master List'!$AF$3:$AF$500,$I12),"") | I12: =IFERROR(MATCH(SMALL('Master List'!$AL$3:$AL$500,ROW()-2),'Master List'!$AL$3:$AL$500,0),"")
A13: =IFERROR(INDEX('Master List'!$V$3:$V$500,$I13),"") | B13: =IFERROR(INDEX('Master List'!$B$3:$B$500,$I13),"") | C13: =IFERROR(INDEX('Master List'!$A$3:$A$500,$I13),"") | D13: =IFERROR(INDEX('Master List'!$G$3:$G$500,$I13),"") | E13: =IFERROR(INDEX('Master List'!$W$3:$W$500,$I13),"") | F13: =IFERROR(INDEX('Master List'!$F$3:$F$500,$I13),"") | G13: =IFERROR(INDEX('Master List'!$AF$3:$AF$500,$I13),"") | I13: =IFERROR(MATCH(SMALL('Master List'!$AL$3:$AL$500,ROW()-2),'Master List'!$AL$3:$AL$500,0),"")
A14: =IFERROR(INDEX('Master List'!$V$3:$V$500,$I14),"") | B14: =IFERROR(INDEX('Master List'!$B$3:$B$500,$I14),"") | C14: =IFERROR(INDEX('Master List'!$A$3:$A$500,$I14),"") | D14: =IFERROR(INDEX('Master List'!$G$3:$G$500,$I14),"") | E14: =IFERROR(INDEX('Master List'!$W$3:$W$500,$I14),"") | F14: =IFERROR(INDEX('Master List'!$F$3:$F$500,$I14),"") | G14: =IFERROR(INDEX('Master List'!$AF$3:$AF$500,$I14),"") | I14: =IFERROR(MATCH(SMALL('Master List'!$AL$3:$AL$500,ROW()-2),'Master List'!$AL$3:$AL$500,0),"")
... A122: =IFERROR(INDEX('Master List'!$V$3:$V$500,$I122),"") | B122: =IFERROR(INDEX('Master List'!$B$3:$B$500,$I122),"") | C122: =IFERROR(INDEX('Master List'!$A$3:$A$500,$I122),"") | D122: =IFERROR(INDEX('Master List'!$G$3:$G$500,$I122),"") | E122: =IFERROR(INDEX('Master List'!$W$3:$W$500,$I122),"") | F122: =IFERROR(INDEX('Master List'!$F$3:$F$500,$I122),"") | G122: =IFERROR(INDEX('Master List'!$AF$3:$AF$500,$I122),"") | I122: =IFERROR(MATCH(SMALL('Master List'!$AL$3:$AL$500,ROW()-2),'Master List'!$AL$3:$AL$500,0),"")

Sheet Master List
A1: Master List (read only, auto updates from the type tabs)
A2: Partnership Type | B2: Partner Name | C2: City | D2: Neighbourhood | E2: Priority | F2: Status | G2: Primary Owner | H2: Contact Name | I2: Role | J2: Contact Email | K2: Contact Phone | L2: Instagram or Website | M2: Audience Size | N2: Audience Source | O2: Source | P2: Warm | Q2: Last Contacted | R2: Days Since Activity | S2: Next Action | T2: Next Action Date | U2: Activation Type | V2: Activation Date | W2: Cases Committed | X2: Cases Delivered | Y2: Cost ($) | Z2: Cost Per Can | AA2: Contra Value ($) | AB2: Deliverables Promised | AC2: Deliverables Received | AD2: What They Want | AE2: Risks | AF2: Nearby Retail Doors | AG2: In BC Tracker? | AH2: Raspberry 4338 | AI2: Lemon Lime 4336 | AJ2: Pineapple Passion Fruit 4340 | AK2: Notes
A3: =IF('Run Clubs'!B3="","","Run Clubs") | B3: =IF('Run Clubs'!B3="","",'Run Clubs'!B3) | C3: =IF('Run Clubs'!D3="","",'Run Clubs'!D3) | D3: =IF('Run Clubs'!E3="","",'Run Clubs'!E3) | E3: =IF('Run Clubs'!F3="","",'Run Clubs'!F3) | F3: =IF('Run Clubs'!G3="","",'Run Clubs'!G3) | G3: =IF('Run Clubs'!H3="","",'Run Clubs'!H3) | H3: =IF('Run Clubs'!I3="","",'Run Clubs'!I3) | I3: =IF('Run Clubs'!J3="","",'Run Clubs'!J3) | J3: =IF('Run Clubs'!K3="","",'Run Clubs'!K3) | ... AK3: =IF('Run Clubs'!AL3="","",'Run Clubs'!AL3) | AL3: =IF(V3="","",V3+ROW()/100000)
A4: =IF('Run Clubs'!B4="","","Run Clubs") | B4: =IF('Run Clubs'!B4="","",'Run Clubs'!B4) | C4: =IF('Run Clubs'!D4="","",'Run Clubs'!D4) | D4: =IF('Run Clubs'!E4="","",'Run Clubs'!E4) | E4: =IF('Run Clubs'!F4="","",'Run Clubs'!F4) | F4: =IF('Run Clubs'!G4="","",'Run Clubs'!G4) | G4: =IF('Run Clubs'!H4="","",'Run Clubs'!H4) | H4: =IF('Run Clubs'!I4="","",'Run Clubs'!I4) | I4: =IF('Run Clubs'!J4="","",'Run Clubs'!J4) | J4: =IF('Run Clubs'!K4="","",'Run Clubs'!K4) | ... AK4: =IF('Run Clubs'!AL4="","",'Run Clubs'!AL4) | AL4: =IF(V4="","",V4+ROW()/100000)
A5: =IF('Run Clubs'!B5="","","Run Clubs") | B5: =IF('Run Clubs'!B5="","",'Run Clubs'!B5) | C5: =IF('Run Clubs'!D5="","",'Run Clubs'!D5) | D5: =IF('Run Clubs'!E5="","",'Run Clubs'!E5) | E5: =IF('Run Clubs'!F5="","",'Run Clubs'!F5) | F5: =IF('Run Clubs'!G5="","",'Run Clubs'!G5) | G5: =IF('Run Clubs'!H5="","",'Run Clubs'!H5) | H5: =IF('Run Clubs'!I5="","",'Run Clubs'!I5) | I5: =IF('Run Clubs'!J5="","",'Run Clubs'!J5) | J5: =IF('Run Clubs'!K5="","",'Run Clubs'!K5) | ... AK5: =IF('Run Clubs'!AL5="","",'Run Clubs'!AL5) | AL5: =IF(V5="","",V5+ROW()/100000)
A6: =IF('Run Clubs'!B6="","","Run Clubs") | B6: =IF('Run Clubs'!B6="","",'Run Clubs'!B6) | C6: =IF('Run Clubs'!D6="","",'Run Clubs'!D6) | D6: =IF('Run Clubs'!E6="","",'Run Clubs'!E6) | E6: =IF('Run Clubs'!F6="","",'Run Clubs'!F6) | F6: =IF('Run Clubs'!G6="","",'Run Clubs'!G6) | G6: =IF('Run Clubs'!H6="","",'Run Clubs'!H6) | H6: =IF('Run Clubs'!I6="","",'Run Clubs'!I6) | I6: =IF('Run Clubs'!J6="","",'Run Clubs'!J6) | J6: =IF('Run Clubs'!K6="","",'Run Clubs'!K6) | ... AK6: =IF('Run Clubs'!AL6="","",'Run Clubs'!AL6) | AL6: =IF(V6="","",V6+ROW()/100000)
A7: =IF('Run Clubs'!B7="","","Run Clubs") | B7: =IF('Run Clubs'!B7="","",'Run Clubs'!B7) | C7: =IF('Run Clubs'!D7="","",'Run Clubs'!D7) | D7: =IF('Run Clubs'!E7="","",'Run Clubs'!E7) | E7: =IF('Run Clubs'!F7="","",'Run Clubs'!F7) | F7: =IF('Run Clubs'!G7="","",'Run Clubs'!G7) | G7: =IF('Run Clubs'!H7="","",'Run Clubs'!H7) | H7: =IF('Run Clubs'!I7="","",'Run Clubs'!I7) | I7: =IF('Run Clubs'!J7="","",'Run Clubs'!J7) | J7: =IF('Run Clubs'!K7="","",'Run Clubs'!K7) | ... AK7: =IF('Run Clubs'!AL7="","",'Run Clubs'!AL7) | AL7: =IF(V7="","",V7+ROW()/100000)
A8: =IF('Run Clubs'!B8="","","Run Clubs") | B8: =IF('Run Clubs'!B8="","",'Run Clubs'!B8) | C8: =IF('Run Clubs'!D8="","",'Run Clubs'!D8) | D8: =IF('Run Clubs'!E8="","",'Run Clubs'!E8) | E8: =IF('Run Clubs'!F8="","",'Run Clubs'!F8) | F8: =IF('Run Clubs'!G8="","",'Run Clubs'!G8) | G8: =IF('Run Clubs'!H8="","",'Run Clubs'!H8) | H8: =IF('Run Clubs'!I8="","",'Run Clubs'!I8) | I8: =IF('Run Clubs'!J8="","",'Run Clubs'!J8) | J8: =IF('Run Clubs'!K8="","",'Run Clubs'!K8) | ... AK8: =IF('Run Clubs'!AL8="","",'Run Clubs'!AL8) | AL8: =IF(V8="","",V8+ROW()/100000)
A9: =IF('Run Clubs'!B9="","","Run Clubs") | B9: =IF('Run Clubs'!B9="","",'Run Clubs'!B9) | C9: =IF('Run Clubs'!D9="","",'Run Clubs'!D9) | D9: =IF('Run Clubs'!E9="","",'Run Clubs'!E9) | E9: =IF('Run Clubs'!F9="","",'Run Clubs'!F9) | F9: =IF('Run Clubs'!G9="","",'Run Clubs'!G9) | G9: =IF('Run Clubs'!H9="","",'Run Clubs'!H9) | H9: =IF('Run Clubs'!I9="","",'Run Clubs'!I9) | I9: =IF('Run Clubs'!J9="","",'Run Clubs'!J9) | J9: =IF('Run Clubs'!K9="","",'Run Clubs'!K9) | ... AK9: =IF('Run Clubs'!AL9="","",'Run Clubs'!AL9) | AL9: =IF(V9="","",V9+ROW()/100000)
A10: =IF('Run Clubs'!B10="","","Run Clubs") | B10: =IF('Run Clubs'!B10="","",'Run Clubs'!B10) | C10: =IF('Run Clubs'!D10="","",'Run Clubs'!D10) | D10: =IF('Run Clubs'!E10="","",'Run Clubs'!E10) | E10: =IF('Run Clubs'!F10="","",'Run Clubs'!F10) | F10: =IF('Run Clubs'!G10="","",'Run Clubs'!G10) | G10: =IF('Run Clubs'!H10="","",'Run Clubs'!H10) | H10: =IF('Run Clubs'!I10="","",'Run Clubs'!I10) | I10: =IF('Run Clubs'!J10="","",'Run Clubs'!J10) | J10: =IF('Run Clubs'!K10="","",'Run Clubs'!K10) | ... AK10: =IF('Run Clubs'!AL10="","",'Run Clubs'!AL10) | AL10: =IF(V10="","",V10+ROW()/100000)
A11: =IF('Run Clubs'!B11="","","Run Clubs") | B11: =IF('Run Clubs'!B11="","",'Run Clubs'!B11) | C11: =IF('Run Clubs'!D11="","",'Run Clubs'!D11) | D11: =IF('Run Clubs'!E11="","",'Run Clubs'!E11) | E11: =IF('Run Clubs'!F11="","",'Run Clubs'!F11) | F11: =IF('Run Clubs'!G11="","",'Run Clubs'!G11) | G11: =IF('Run Clubs'!H11="","",'Run Clubs'!H11) | H11: =IF('Run Clubs'!I11="","",'Run Clubs'!I11) | I11: =IF('Run Clubs'!J11="","",'Run Clubs'!J11) | J11: =IF('Run Clubs'!K11="","",'Run Clubs'!K11) | ... AK11: =IF('Run Clubs'!AL11="","",'Run Clubs'!AL11) | AL11: =IF(V11="","",V11+ROW()/100000)
A12: =IF('Run Clubs'!B12="","","Run Clubs") | B12: =IF('Run Clubs'!B12="","",'Run Clubs'!B12) | C12: =IF('Run Clubs'!D12="","",'Run Clubs'!D12) | D12: =IF('Run Clubs'!E12="","",'Run Clubs'!E12) | E12: =IF('Run Clubs'!F12="","",'Run Clubs'!F12) | F12: =IF('Run Clubs'!G12="","",'Run Clubs'!G12) | G12: =IF('Run Clubs'!H12="","",'Run Clubs'!H12) | H12: =IF('Run Clubs'!I12="","",'Run Clubs'!I12) | I12: =IF('Run Clubs'!J12="","",'Run Clubs'!J12) | J12: =IF('Run Clubs'!K12="","",'Run Clubs'!K12) | ... AK12: =IF('Run Clubs'!AL12="","",'Run Clubs'!AL12) | AL12: =IF(V12="","",V12+ROW()/100000)
A13: =IF('Run Clubs'!B13="","","Run Clubs") | B13: =IF('Run Clubs'!B13="","",'Run Clubs'!B13) | C13: =IF('Run Clubs'!D13="","",'Run Clubs'!D13) | D13: =IF('Run Clubs'!E13="","",'Run Clubs'!E13) | E13: =IF('Run Clubs'!F13="","",'Run Clubs'!F13) | F13: =IF('Run Clubs'!G13="","",'Run Clubs'!G13) | G13: =IF('Run Clubs'!H13="","",'Run Clubs'!H13) | H13: =IF('Run Clubs'!I13="","",'Run Clubs'!I13) | I13: =IF('Run Clubs'!J13="","",'Run Clubs'!J13) | J13: =IF('Run Clubs'!K13="","",'Run Clubs'!K13) | ... AK13: =IF('Run Clubs'!AL13="","",'Run Clubs'!AL13) | AL13: =IF(V13="","",V13+ROW()/100000)
A14: =IF('Run Clubs'!B14="","","Run Clubs") | B14: =IF('Run Clubs'!B14="","",'Run Clubs'!B14) | C14: =IF('Run Clubs'!D14="","",'Run Clubs'!D14) | D14: =IF('Run Clubs'!E14="","",'Run Clubs'!E14) | E14: =IF('Run Clubs'!F14="","",'Run Clubs'!F14) | F14: =IF('Run Clubs'!G14="","",'Run Clubs'!G14) | G14: =IF('Run Clubs'!H14="","",'Run Clubs'!H14) | H14: =IF('Run Clubs'!I14="","",'Run Clubs'!I14) | I14: =IF('Run Clubs'!J14="","",'Run Clubs'!J14) | J14: =IF('Run Clubs'!K14="","",'Run Clubs'!K14) | ... AK14: =IF('Run Clubs'!AL14="","",'Run Clubs'!AL14) | AL14: =IF(V14="","",V14+ROW()/100000)
... A32: =IF('Run Clubs'!B32="","","Run Clubs") | B32: =IF('Run Clubs'!B32="","",'Run Clubs'!B32) | C32: =IF('Run Clubs'!D32="","",'Run Clubs'!D32) | D32: =IF('Run Clubs'!E32="","",'Run Clubs'!E32) | E32: =IF('Run Clubs'!F32="","",'Run Clubs'!F32) | F32: =IF('Run Clubs'!G32="","",'Run Clubs'!G32) | G32: =IF('Run Clubs'!H32="","",'Run Clubs'!H32) | H32: =IF('Run Clubs'!I32="","",'Run Clubs'!I32) | I32: =IF('Run Clubs'!J32="","",'Run Clubs'!J32) | J32: =IF('Run Clubs'!K32="","",'Run Clubs'!K32) | ... AK32: =IF('Run Clubs'!AL32="","",'Run Clubs'!AL32) | AL32: =IF(V32="","",V32+ROW()/100000)
A33: =IF('Gyms & Studios'!B3="","","Gyms & Studios") | B33: =IF('Gyms & Studios'!B3="","",'Gyms & Studios'!B3) | C33: =IF('Gyms & Studios'!D3="","",'Gyms & Studios'!D3) | D33: =IF('Gyms & Studios'!E3="","",'Gyms & Studios'!E3) | E33: =IF('Gyms & Studios'!F3="","",'Gyms & Studios'!F3) | F33: =IF('Gyms & Studios'!G3="","",'Gyms & Studios'!G3) | G33: =IF('Gyms & Studios'!H3="","",'Gyms & Studios'!H3) | H33: =IF('Gyms & Studios'!I3="","",'Gyms & Studios'!I3) | I33: =IF('Gyms & Studios'!J3="","",'Gyms & Studios'!J3) | J33: =IF('Gyms & Studios'!K3="","",'Gyms & Studios'!K3) | ... AK33: =IF('Gyms & Studios'!AL3="","",'Gyms & Studios'!AL3) | AL33: =IF(V33="","",V33+ROW()/100000)
A34: =IF('Gyms & Studios'!B4="","","Gyms & Studios") | B34: =IF('Gyms & Studios'!B4="","",'Gyms & Studios'!B4) | C34: =IF('Gyms & Studios'!D4="","",'Gyms & Studios'!D4) | D34: =IF('Gyms & Studios'!E4="","",'Gyms & Studios'!E4) | E34: =IF('Gyms & Studios'!F4="","",'Gyms & Studios'!F4) | F34: =IF('Gyms & Studios'!G4="","",'Gyms & Studios'!G4) | G34: =IF('Gyms & Studios'!H4="","",'Gyms & Studios'!H4) | H34: =IF('Gyms & Studios'!I4="","",'Gyms & Studios'!I4) | I34: =IF('Gyms & Studios'!J4="","",'Gyms & Studios'!J4) | J34: =IF('Gyms & Studios'!K4="","",'Gyms & Studios'!K4) | ... AK34: =IF('Gyms & Studios'!AL4="","",'Gyms & Studios'!AL4) | AL34: =IF(V34="","",V34+ROW()/100000)
A35: =IF('Gyms & Studios'!B5="","","Gyms & Studios") | B35: =IF('Gyms & Studios'!B5="","",'Gyms & Studios'!B5) | C35: =IF('Gyms & Studios'!D5="","",'Gyms & Studios'!D5) | D35: =IF('Gyms & Studios'!E5="","",'Gyms & Studios'!E5) | E35: =IF('Gyms & Studios'!F5="","",'Gyms & Studios'!F5) | F35: =IF('Gyms & Studios'!G5="","",'Gyms & Studios'!G5) | G35: =IF('Gyms & Studios'!H5="","",'Gyms & Studios'!H5) | H35: =IF('Gyms & Studios'!I5="","",'Gyms & Studios'!I5) | I35: =IF('Gyms & Studios'!J5="","",'Gyms & Studios'!J5) | J35: =IF('Gyms & Studios'!K5="","",'Gyms & Studios'!K5) | ... AK35: =IF('Gyms & Studios'!AL5="","",'Gyms & Studios'!AL5) | AL35: =IF(V35="","",V35+ROW()/100000)
A36: =IF('Gyms & Studios'!B6="","","Gyms & Studios") | B36: =IF('Gyms & Studios'!B6="","",'Gyms & Studios'!B6) | C36: =IF('Gyms & Studios'!D6="","",'Gyms & Studios'!D6) | D36: =IF('Gyms & Studios'!E6="","",'Gyms & Studios'!E6) | E36: =IF('Gyms & Studios'!F6="","",'Gyms & Studios'!F6) | F36: =IF('Gyms & Studios'!G6="","",'Gyms & Studios'!G6) | G36: =IF('Gyms & Studios'!H6="","",'Gyms & Studios'!H6) | H36: =IF('Gyms & Studios'!I6="","",'Gyms & Studios'!I6) | I36: =IF('Gyms & Studios'!J6="","",'Gyms & Studios'!J6) | J36: =IF('Gyms & Studios'!K6="","",'Gyms & Studios'!K6) | ... AK36: =IF('Gyms & Studios'!AL6="","",'Gyms & Studios'!AL6) | AL36: =IF(V36="","",V36+ROW()/100000)
A37: =IF('Gyms & Studios'!B7="","","Gyms & Studios") | B37: =IF('Gyms & Studios'!B7="","",'Gyms & Studios'!B7) | C37: =IF('Gyms & Studios'!D7="","",'Gyms & Studios'!D7) | D37: =IF('Gyms & Studios'!E7="","",'Gyms & Studios'!E7) | E37: =IF('Gyms & Studios'!F7="","",'Gyms & Studios'!F7) | F37: =IF('Gyms & Studios'!G7="","",'Gyms & Studios'!G7) | G37: =IF('Gyms & Studios'!H7="","",'Gyms & Studios'!H7) | H37: =IF('Gyms & Studios'!I7="","",'Gyms & Studios'!I7) | I37: =IF('Gyms & Studios'!J7="","",'Gyms & Studios'!J7) | J37: =IF('Gyms & Studios'!K7="","",'Gyms & Studios'!K7) | ... AK37: =IF('Gyms & Studios'!AL7="","",'Gyms & Studios'!AL7) | AL37: =IF(V37="","",V37+ROW()/100000)
A38: =IF('Gyms & Studios'!B8="","","Gyms & Studios") | B38: =IF('Gyms & Studios'!B8="","",'Gyms & Studios'!B8) | C38: =IF('Gyms & Studios'!D8="","",'Gyms & Studios'!D8) | D38: =IF('Gyms & Studios'!E8="","",'Gyms & Studios'!E8) | E38: =IF('Gyms & Studios'!F8="","",'Gyms & Studios'!F8) | F38: =IF('Gyms & Studios'!G8="","",'Gyms & Studios'!G8) | G38: =IF('Gyms & Studios'!H8="","",'Gyms & Studios'!H8) | H38: =IF('Gyms & Studios'!I8="","",'Gyms & Studios'!I8) | I38: =IF('Gyms & Studios'!J8="","",'Gyms & Studios'!J8) | J38: =IF('Gyms & Studios'!K8="","",'Gyms & Studios'!K8) | ... AK38: =IF('Gyms & Studios'!AL8="","",'Gyms & Studios'!AL8) | AL38: =IF(V38="","",V38+ROW()/100000)
A39: =IF('Gyms & Studios'!B9="","","Gyms & Studios") | B39: =IF('Gyms & Studios'!B9="","",'Gyms & Studios'!B9) | C39: =IF('Gyms & Studios'!D9="","",'Gyms & Studios'!D9) | D39: =IF('Gyms & Studios'!E9="","",'Gyms & Studios'!E9) | E39: =IF('Gyms & Studios'!F9="","",'Gyms & Studios'!F9) | F39: =IF('Gyms & Studios'!G9="","",'Gyms & Studios'!G9) | G39: =IF('Gyms & Studios'!H9="","",'Gyms & Studios'!H9) | H39: =IF('Gyms & Studios'!I9="","",'Gyms & Studios'!I9) | I39: =IF('Gyms & Studios'!J9="","",'Gyms & Studios'!J9) | J39: =IF('Gyms & Studios'!K9="","",'Gyms & Studios'!K9) | ... AK39: =IF('Gyms & Studios'!AL9="","",'Gyms & Studios'!AL9) | AL39: =IF(V39="","",V39+ROW()/100000)
A40: =IF('Gyms & Studios'!B10="","","Gyms & Studios") | B40: =IF('Gyms & Studios'!B10="","",'Gyms & Studios'!B10) | C40: =IF('Gyms & Studios'!D10="","",'Gyms & Studios'!D10) | D40: =IF('Gyms & Studios'!E10="","",'Gyms & Studios'!E10) | E40: =IF('Gyms & Studios'!F10="","",'Gyms & Studios'!F10) | F40: =IF('Gyms & Studios'!G10="","",'Gyms & Studios'!G10) | G40: =IF('Gyms & Studios'!H10="","",'Gyms & Studios'!H10) | H40: =IF('Gyms & Studios'!I10="","",'Gyms & Studios'!I10) | I40: =IF('Gyms & Studios'!J10="","",'Gyms & Studios'!J10) | J40: =IF('Gyms & Studios'!K10="","",'Gyms & Studios'!K10) | ... AK40: =IF('Gyms & Studios'!AL10="","",'Gyms & Studios'!AL10) | AL40: =IF(V40="","",V40+ROW()/100000)
A41: =IF('Gyms & Studios'!B11="","","Gyms & Studios") | B41: =IF('Gyms & Studios'!B11="","",'Gyms & Studios'!B11) | C41: =IF('Gyms & Studios'!D11="","",'Gyms & Studios'!D11) | D41: =IF('Gyms & Studios'!E11="","",'Gyms & Studios'!E11) | E41: =IF('Gyms & Studios'!F11="","",'Gyms & Studios'!F11) | F41: =IF('Gyms & Studios'!G11="","",'Gyms & Studios'!G11) | G41: =IF('Gyms & Studios'!H11="","",'Gyms & Studios'!H11) | H41: =IF('Gyms & Studios'!I11="","",'Gyms & Studios'!I11) | I41: =IF('Gyms & Studios'!J11="","",'Gyms & Studios'!J11) | J41: =IF('Gyms & Studios'!K11="","",'Gyms & Studios'!K11) | ... AK41: =IF('Gyms & Studios'!AL11="","",'Gyms & Studios'!AL11) | AL41: =IF(V41="","",V41+ROW()/100000)
A42: =IF('Gyms & Studios'!B12="","","Gyms & Studios") | B42: =IF('Gyms & Studios'!B12="","",'Gyms & Studios'!B12) | C42: =IF('Gyms & Studios'!D12="","",'Gyms & Studios'!D12) | D42: =IF('Gyms & Studios'!E12="","",'Gyms & Studios'!E12) | E42: =IF('Gyms & Studios'!F12="","",'Gyms & Studios'!F12) | F42: =IF('Gyms & Studios'!G12="","",'Gyms & Studios'!G12) | G42: =IF('Gyms & Studios'!H12="","",'Gyms & Studios'!H12) | H42: =IF('Gyms & Studios'!I12="","",'Gyms & Studios'!I12) | I42: =IF('Gyms & Studios'!J12="","",'Gyms & Studios'!J12) | J42: =IF('Gyms & Studios'!K12="","",'Gyms & Studios'!K12) | ... AK42: =IF('Gyms & Studios'!AL12="","",'Gyms & Studios'!AL12) | AL42: =IF(V42="","",V42+ROW()/100000)
A43: =IF('Gyms & Studios'!B13="","","Gyms & Studios") | B43: =IF('Gyms & Studios'!B13="","",'Gyms & Studios'!B13) | C43: =IF('Gyms & Studios'!D13="","",'Gyms & Studios'!D13) | D43: =IF('Gyms & Studios'!E13="","",'Gyms & Studios'!E13) | E43: =IF('Gyms & Studios'!F13="","",'Gyms & Studios'!F13) | F43: =IF('Gyms & Studios'!G13="","",'Gyms & Studios'!G13) | G43: =IF('Gyms & Studios'!H13="","",'Gyms & Studios'!H13) | H43: =IF('Gyms & Studios'!I13="","",'Gyms & Studios'!I13) | I43: =IF('Gyms & Studios'!J13="","",'Gyms & Studios'!J13) | J43: =IF('Gyms & Studios'!K13="","",'Gyms & Studios'!K13) | ... AK43: =IF('Gyms & Studios'!AL13="","",'Gyms & Studios'!AL13) | AL43: =IF(V43="","",V43+ROW()/100000)
A44: =IF('Gyms & Studios'!B14="","","Gyms & Studios") | B44: =IF('Gyms & Studios'!B14="","",'Gyms & Studios'!B14) | C44: =IF('Gyms & Studios'!D14="","",'Gyms & Studios'!D14) | D44: =IF('Gyms & Studios'!E14="","",'Gyms & Studios'!E14) | E44: =IF('Gyms & Studios'!F14="","",'Gyms & Studios'!F14) | F44: =IF('Gyms & Studios'!G14="","",'Gyms & Studios'!G14) | G44: =IF('Gyms & Studios'!H14="","",'Gyms & Studios'!H14) | H44: =IF('Gyms & Studios'!I14="","",'Gyms & Studios'!I14) | I44: =IF('Gyms & Studios'!J14="","",'Gyms & Studios'!J14) | J44: =IF('Gyms & Studios'!K14="","",'Gyms & Studios'!K14) | ... AK44: =IF('Gyms & Studios'!AL14="","",'Gyms & Studios'!AL14) | AL44: =IF(V44="","",V44+ROW()/100000)
... A62: =IF('Gyms & Studios'!B32="","","Gyms & Studios") | B62: =IF('Gyms & Studios'!B32="","",'Gyms & Studios'!B32) | C62: =IF('Gyms & Studios'!D32="","",'Gyms & Studios'!D32) | D62: =IF('Gyms & Studios'!E32="","",'Gyms & Studios'!E32) | E62: =IF('Gyms & Studios'!F32="","",'Gyms & Studios'!F32) | F62: =IF('Gyms & Studios'!G32="","",'Gyms & Studios'!G32) | G62: =IF('Gyms & Studios'!H32="","",'Gyms & Studios'!H32) | H62: =IF('Gyms & Studios'!I32="","",'Gyms & Studios'!I32) | I62: =IF('Gyms & Studios'!J32="","",'Gyms & Studios'!J32) | J62: =IF('Gyms & Studios'!K32="","",'Gyms & Studios'!K32) | ... AK62: =IF('Gyms & Studios'!AL32="","",'Gyms & Studios'!AL32) | AL62: =IF(V62="","",V62+ROW()/100000)
A63: =IF('Events & Festivals'!B3="","","Events & Festivals") | B63: =IF('Events & Festivals'!B3="","",'Events & Festivals'!B3) | C63: =IF('Events & Festivals'!D3="","",'Events & Festivals'!D3) | D63: =IF('Events & Festivals'!E3="","",'Events & Festivals'!E3) | E63: =IF('Events & Festivals'!F3="","",'Events & Festivals'!F3) | F63: =IF('Events & Festivals'!G3="","",'Events & Festivals'!G3) | G63: =IF('Events & Festivals'!H3="","",'Events & Festivals'!H3) | H63: =IF('Events & Festivals'!I3="","",'Events & Festivals'!I3) | I63: =IF('Events & Festivals'!J3="","",'Events & Festivals'!J3) | J63: =IF('Events & Festivals'!K3="","",'Events & Festivals'!K3) | ... AK63: =IF('Events & Festivals'!AL3="","",'Events & Festivals'!AL3) | AL63: =IF(V63="","",V63+ROW()/100000)
A64: =IF('Events & Festivals'!B4="","","Events & Festivals") | B64: =IF('Events & Festivals'!B4="","",'Events & Festivals'!B4) | C64: =IF('Events & Festivals'!D4="","",'Events & Festivals'!D4) | D64: =IF('Events & Festivals'!E4="","",'Events & Festivals'!E4) | E64: =IF('Events & Festivals'!F4="","",'Events & Festivals'!F4) | F64: =IF('Events & Festivals'!G4="","",'Events & Festivals'!G4) | G64: =IF('Events & Festivals'!H4="","",'Events & Festivals'!H4) | H64: =IF('Events & Festivals'!I4="","",'Events & Festivals'!I4) | I64: =IF('Events & Festivals'!J4="","",'Events & Festivals'!J4) | J64: =IF('Events & Festivals'!K4="","",'Events & Festivals'!K4) | ... AK64: =IF('Events & Festivals'!AL4="","",'Events & Festivals'!AL4) | AL64: =IF(V64="","",V64+ROW()/100000)
A65: =IF('Events & Festivals'!B5="","","Events & Festivals") | B65: =IF('Events & Festivals'!B5="","",'Events & Festivals'!B5) | C65: =IF('Events & Festivals'!D5="","",'Events & Festivals'!D5) | D65: =IF('Events & Festivals'!E5="","",'Events & Festivals'!E5) | E65: =IF('Events & Festivals'!F5="","",'Events & Festivals'!F5) | F65: =IF('Events & Festivals'!G5="","",'Events & Festivals'!G5) | G65: =IF('Events & Festivals'!H5="","",'Events & Festivals'!H5) | H65: =IF('Events & Festivals'!I5="","",'Events & Festivals'!I5) | I65: =IF('Events & Festivals'!J5="","",'Events & Festivals'!J5) | J65: =IF('Events & Festivals'!K5="","",'Events & Festivals'!K5) | ... AK65: =IF('Events & Festivals'!AL5="","",'Events & Festivals'!AL5) | AL65: =IF(V65="","",V65+ROW()/100000)
A66: =IF('Events & Festivals'!B6="","","Events & Festivals") | B66: =IF('Events & Festivals'!B6="","",'Events & Festivals'!B6) | C66: =IF('Events & Festivals'!D6="","",'Events & Festivals'!D6) | D66: =IF('Events & Festivals'!E6="","",'Events & Festivals'!E6) | E66: =IF('Events & Festivals'!F6="","",'Events & Festivals'!F6) | F66: =IF('Events & Festivals'!G6="","",'Events & Festivals'!G6) | G66: =IF('Events & Festivals'!H6="","",'Events & Festivals'!H6) | H66: =IF('Events & Festivals'!I6="","",'Events & Festivals'!I6) | I66: =IF('Events & Festivals'!J6="","",'Events & Festivals'!J6) | J66: =IF('Events & Festivals'!K6="","",'Events & Festivals'!K6) | ... AK66: =IF('Events & Festivals'!AL6="","",'Events & Festivals'!AL6) | AL66: =IF(V66="","",V66+ROW()/100000)
A67: =IF('Events & Festivals'!B7="","","Events & Festivals") | B67: =IF('Events & Festivals'!B7="","",'Events & Festivals'!B7) | C67: =IF('Events & Festivals'!D7="","",'Events & Festivals'!D7) | D67: =IF('Events & Festivals'!E7="","",'Events & Festivals'!E7) | E67: =IF('Events & Festivals'!F7="","",'Events & Festivals'!F7) | F67: =IF('Events & Festivals'!G7="","",'Events & Festivals'!G7) | G67: =IF('Events & Festivals'!H7="","",'Events & Festivals'!H7) | H67: =IF('Events & Festivals'!I7="","",'Events & Festivals'!I7) | I67: =IF('Events & Festivals'!J7="","",'Events & Festivals'!J7) | J67: =IF('Events & Festivals'!K7="","",'Events & Festivals'!K7) | ... AK67: =IF('Events & Festivals'!AL7="","",'Events & Festivals'!AL7) | AL67: =IF(V67="","",V67+ROW()/100000)
A68: =IF('Events & Festivals'!B8="","","Events & Festivals") | B68: =IF('Events & Festivals'!B8="","",'Events & Festivals'!B8) | C68: =IF('Events & Festivals'!D8="","",'Events & Festivals'!D8) | D68: =IF('Events & Festivals'!E8="","",'Events & Festivals'!E8) | E68: =IF('Events & Festivals'!F8="","",'Events & Festivals'!F8) | F68: =IF('Events & Festivals'!G8="","",'Events & Festivals'!G8) | G68: =IF('Events & Festivals'!H8="","",'Events & Festivals'!H8) | H68: =IF('Events & Festivals'!I8="","",'Events & Festivals'!I8) | I68: =IF('Events & Festivals'!J8="","",'Events & Festivals'!J8) | J68: =IF('Events & Festivals'!K8="","",'Events & Festivals'!K8) | ... AK68: =IF('Events & Festivals'!AL8="","",'Events & Festivals'!AL8) | AL68: =IF(V68="","",V68+ROW()/100000)
A69: =IF('Events & Festivals'!B9="","","Events & Festivals") | B69: =IF('Events & Festivals'!B9="","",'Events & Festivals'!B9) | C69: =IF('Events & Festivals'!D9="","",'Events & Festivals'!D9) | D69: =IF('Events & Festivals'!E9="","",'Events & Festivals'!E9) | E69: =IF('Events & Festivals'!F9="","",'Events & Festivals'!F9) | F69: =IF('Events & Festivals'!G9="","",'Events & Festivals'!G9) | G69: =IF('Events & Festivals'!H9="","",'Events & Festivals'!H9) | H69: =IF('Events & Festivals'!I9="","",'Events & Festivals'!I9) | I69: =IF('Events & Festivals'!J9="","",'Events & Festivals'!J9) | J69: =IF('Events & Festivals'!K9="","",'Events & Festivals'!K9) | ... AK69: =IF('Events & Festivals'!AL9="","",'Events & Festivals'!AL9) | AL69: =IF(V69="","",V69+ROW()/100000)
A70: =IF('Events & Festivals'!B10="","","Events & Festivals") | B70: =IF('Events & Festivals'!B10="","",'Events & Festivals'!B10) | C70: =IF('Events & Festivals'!D10="","",'Events & Festivals'!D10) | D70: =IF('Events & Festivals'!E10="","",'Events & Festivals'!E10) | E70: =IF('Events & Festivals'!F10="","",'Events & Festivals'!F10) | F70: =IF('Events & Festivals'!G10="","",'Events & Festivals'!G10) | G70: =IF('Events & Festivals'!H10="","",'Events & Festivals'!H10) | H70: =IF('Events & Festivals'!I10="","",'Events & Festivals'!I10) | I70: =IF('Events & Festivals'!J10="","",'Events & Festivals'!J10) | J70: =IF('Events & Festivals'!K10="","",'Events & Festivals'!K10) | ... AK70: =IF('Events & Festivals'!AL10="","",'Events & Festivals'!AL10) | AL70: =IF(V70="","",V70+ROW()/100000)
A71: =IF('Events & Festivals'!B11="","","Events & Festivals") | B71: =IF('Events & Festivals'!B11="","",'Events & Festivals'!B11) | C71: =IF('Events & Festivals'!D11="","",'Events & Festivals'!D11) | D71: =IF('Events & Festivals'!E11="","",'Events & Festivals'!E11) | E71: =IF('Events & Festivals'!F11="","",'Events & Festivals'!F11) | F71: =IF('Events & Festivals'!G11="","",'Events & Festivals'!G11) | G71: =IF('Events & Festivals'!H11="","",'Events & Festivals'!H11) | H71: =IF('Events & Festivals'!I11="","",'Events & Festivals'!I11) | I71: =IF('Events & Festivals'!J11="","",'Events & Festivals'!J11) | J71: =IF('Events & Festivals'!K11="","",'Events & Festivals'!K11) | ... AK71: =IF('Events & Festivals'!AL11="","",'Events & Festivals'!AL11) | AL71: =IF(V71="","",V71+ROW()/100000)
A72: =IF('Events & Festivals'!B12="","","Events & Festivals") | B72: =IF('Events & Festivals'!B12="","",'Events & Festivals'!B12) | C72: =IF('Events & Festivals'!D12="","",'Events & Festivals'!D12) | D72: =IF('Events & Festivals'!E12="","",'Events & Festivals'!E12) | E72: =IF('Events & Festivals'!F12="","",'Events & Festivals'!F12) | F72: =IF('Events & Festivals'!G12="","",'Events & Festivals'!G12) | G72: =IF('Events & Festivals'!H12="","",'Events & Festivals'!H12) | H72: =IF('Events & Festivals'!I12="","",'Events & Festivals'!I12) | I72: =IF('Events & Festivals'!J12="","",'Events & Festivals'!J12) | J72: =IF('Events & Festivals'!K12="","",'Events & Festivals'!K12) | ... AK72: =IF('Events & Festivals'!AL12="","",'Events & Festivals'!AL12) | AL72: =IF(V72="","",V72+ROW()/100000)
A73: =IF('Events & Festivals'!B13="","","Events & Festivals") | B73: =IF('Events & Festivals'!B13="","",'Events & Festivals'!B13) | C73: =IF('Events & Festivals'!D13="","",'Events & Festivals'!D13) | D73: =IF('Events & Festivals'!E13="","",'Events & Festivals'!E13) | E73: =IF('Events & Festivals'!F13="","",'Events & Festivals'!F13) | F73: =IF('Events & Festivals'!G13="","",'Events & Festivals'!G13) | G73: =IF('Events & Festivals'!H13="","",'Events & Festivals'!H13) | H73: =IF('Events & Festivals'!I13="","",'Events & Festivals'!I13) | I73: =IF('Events & Festivals'!J13="","",'Events & Festivals'!J13) | J73: =IF('Events & Festivals'!K13="","",'Events & Festivals'!K13) | ... AK73: =IF('Events & Festivals'!AL13="","",'Events & Festivals'!AL13) | AL73: =IF(V73="","",V73+ROW()/100000)
A74: =IF('Events & Festivals'!B14="","","Events & Festivals") | B74: =IF('Events & Festivals'!B14="","",'Events & Festivals'!B14) | C74: =IF('Events & Festivals'!D14="","",'Events & Festivals'!D14) | D74: =IF('Events & Festivals'!E14="","",'Events & Festivals'!E14) | E74: =IF('Events & Festivals'!F14="","",'Events & Festivals'!F14) | F74: =IF('Events & Festivals'!G14="","",'Events & Festivals'!G14) | G74: =IF('Events & Festivals'!H14="","",'Events & Festivals'!H14) | H74: =IF('Events & Festivals'!I14="","",'Events & Festivals'!I14) | I74: =IF('Events & Festivals'!J14="","",'Events & Festivals'!J14) | J74: =IF('Events & Festivals'!K14="","",'Events & Festivals'!K14) | ... AK74: =IF('Events & Festivals'!AL14="","",'Events & Festivals'!AL14) | AL74: =IF(V74="","",V74+ROW()/100000)
... A92: =IF('Events & Festivals'!B32="","","Events & Festivals") | B92: =IF('Events & Festivals'!B32="","",'Events & Festivals'!B32) | C92: =IF('Events & Festivals'!D32="","",'Events & Festivals'!D32) | D92: =IF('Events & Festivals'!E32="","",'Events & Festivals'!E32) | E92: =IF('Events & Festivals'!F32="","",'Events & Festivals'!F32) | F92: =IF('Events & Festivals'!G32="","",'Events & Festivals'!G32) | G92: =IF('Events & Festivals'!H32="","",'Events & Festivals'!H32) | H92: =IF('Events & Festivals'!I32="","",'Events & Festivals'!I32) | I92: =IF('Events & Festivals'!J32="","",'Events & Festivals'!J32) | J92: =IF('Events & Festivals'!K32="","",'Events & Festivals'!K32) | ... AK92: =IF('Events & Festivals'!AL32="","",'Events & Festivals'!AL32) | AL92: =IF(V92="","",V92+ROW()/100000)
A93: =IF('Sports Teams & Leagues'!B3="","","Sports Teams & Leagues") | B93: =IF('Sports Teams & Leagues'!B3="","",'Sports Teams & Leagues'!B3) | C93: =IF('Sports Teams & Leagues'!D3="","",'Sports Teams & Leagues'!D3) | D93: =IF('Sports Teams & Leagues'!E3="","",'Sports Teams & Leagues'!E3) | E93: =IF('Sports Teams & Leagues'!F3="","",'Sports Teams & Leagues'!F3) | F93: =IF('Sports Teams & Leagues'!G3="","",'Sports Teams & Leagues'!G3) | G93: =IF('Sports Teams & Leagues'!H3="","",'Sports Teams & Leagues'!H3) | H93: =IF('Sports Teams & Leagues'!I3="","",'Sports Teams & Leagues'!I3) | I93: =IF('Sports Teams & Leagues'!J3="","",'Sports Teams & Leagues'!J3) | J93: =IF('Sports Teams & Leagues'!K3="","",'Sports Teams & Leagues'!K3) | ... AK93: =IF('Sports Teams & Leagues'!AL3="","",'Sports Teams & Leagues'!AL3) | AL93: =IF(V93="","",V93+ROW()/100000)
A94: =IF('Sports Teams & Leagues'!B4="","","Sports Teams & Leagues") | B94: =IF('Sports Teams & Leagues'!B4="","",'Sports Teams & Leagues'!B4) | C94: =IF('Sports Teams & Leagues'!D4="","",'Sports Teams & Leagues'!D4) | D94: =IF('Sports Teams & Leagues'!E4="","",'Sports Teams & Leagues'!E4) | E94: =IF('Sports Teams & Leagues'!F4="","",'Sports Teams & Leagues'!F4) | F94: =IF('Sports Teams & Leagues'!G4="","",'Sports Teams & Leagues'!G4) | G94: =IF('Sports Teams & Leagues'!H4="","",'Sports Teams & Leagues'!H4) | H94: =IF('Sports Teams & Leagues'!I4="","",'Sports Teams & Leagues'!I4) | I94: =IF('Sports Teams & Leagues'!J4="","",'Sports Teams & Leagues'!J4) | J94: =IF('Sports Teams & Leagues'!K4="","",'Sports Teams & Leagues'!K4) | ... AK94: =IF('Sports Teams & Leagues'!AL4="","",'Sports Teams & Leagues'!AL4) | AL94: =IF(V94="","",V94+ROW()/100000)
A95: =IF('Sports Teams & Leagues'!B5="","","Sports Teams & Leagues") | B95: =IF('Sports Teams & Leagues'!B5="","",'Sports Teams & Leagues'!B5) | C95: =IF('Sports Teams & Leagues'!D5="","",'Sports Teams & Leagues'!D5) | D95: =IF('Sports Teams & Leagues'!E5="","",'Sports Teams & Leagues'!E5) | E95: =IF('Sports Teams & Leagues'!F5="","",'Sports Teams & Leagues'!F5) | F95: =IF('Sports Teams & Leagues'!G5="","",'Sports Teams & Leagues'!G5) | G95: =IF('Sports Teams & Leagues'!H5="","",'Sports Teams & Leagues'!H5) | H95: =IF('Sports Teams & Leagues'!I5="","",'Sports Teams & Leagues'!I5) | I95: =IF('Sports Teams & Leagues'!J5="","",'Sports Teams & Leagues'!J5) | J95: =IF('Sports Teams & Leagues'!K5="","",'Sports Teams & Leagues'!K5) | ... AK95: =IF('Sports Teams & Leagues'!AL5="","",'Sports Teams & Leagues'!AL5) | AL95: =IF(V95="","",V95+ROW()/100000)
A96: =IF('Sports Teams & Leagues'!B6="","","Sports Teams & Leagues") | B96: =IF('Sports Teams & Leagues'!B6="","",'Sports Teams & Leagues'!B6) | C96: =IF('Sports Teams & Leagues'!D6="","",'Sports Teams & Leagues'!D6) | D96: =IF('Sports Teams & Leagues'!E6="","",'Sports Teams & Leagues'!E6) | E96: =IF('Sports Teams & Leagues'!F6="","",'Sports Teams & Leagues'!F6) | F96: =IF('Sports Teams & Leagues'!G6="","",'Sports Teams & Leagues'!G6) | G96: =IF('Sports Teams & Leagues'!H6="","",'Sports Teams & Leagues'!H6) | H96: =IF('Sports Teams & Leagues'!I6="","",'Sports Teams & Leagues'!I6) | I96: =IF('Sports Teams & Leagues'!J6="","",'Sports Teams & Leagues'!J6) | J96: =IF('Sports Teams & Leagues'!K6="","",'Sports Teams & Leagues'!K6) | ... AK96: =IF('Sports Teams & Leagues'!AL6="","",'Sports Teams & Leagues'!AL6) | AL96: =IF(V96="","",V96+ROW()/100000)
A97: =IF('Sports Teams & Leagues'!B7="","","Sports Teams & Leagues") | B97: =IF('Sports Teams & Leagues'!B7="","",'Sports Teams & Leagues'!B7) | C97: =IF('Sports Teams & Leagues'!D7="","",'Sports Teams & Leagues'!D7) | D97: =IF('Sports Teams & Leagues'!E7="","",'Sports Teams & Leagues'!E7) | E97: =IF('Sports Teams & Leagues'!F7="","",'Sports Teams & Leagues'!F7) | F97: =IF('Sports Teams & Leagues'!G7="","",'Sports Teams & Leagues'!G7) | G97: =IF('Sports Teams & Leagues'!H7="","",'Sports Teams & Leagues'!H7) | H97: =IF('Sports Teams & Leagues'!I7="","",'Sports Teams & Leagues'!I7) | I97: =IF('Sports Teams & Leagues'!J7="","",'Sports Teams & Leagues'!J7) | J97: =IF('Sports Teams & Leagues'!K7="","",'Sports Teams & Leagues'!K7) | ... AK97: =IF('Sports Teams & Leagues'!AL7="","",'Sports Teams & Leagues'!AL7) | AL97: =IF(V97="","",V97+ROW()/100000)
A98: =IF('Sports Teams & Leagues'!B8="","","Sports Teams & Leagues") | B98: =IF('Sports Teams & Leagues'!B8="","",'Sports Teams & Leagues'!B8) | C98: =IF('Sports Teams & Leagues'!D8="","",'Sports Teams & Leagues'!D8) | D98: =IF('Sports Teams & Leagues'!E8="","",'Sports Teams & Leagues'!E8) | E98: =IF('Sports Teams & Leagues'!F8="","",'Sports Teams & Leagues'!F8) | F98: =IF('Sports Teams & Leagues'!G8="","",'Sports Teams & Leagues'!G8) | G98: =IF('Sports Teams & Leagues'!H8="","",'Sports Teams & Leagues'!H8) | H98: =IF('Sports Teams & Leagues'!I8="","",'Sports Teams & Leagues'!I8) | I98: =IF('Sports Teams & Leagues'!J8="","",'Sports Teams & Leagues'!J8) | J98: =IF('Sports Teams & Leagues'!K8="","",'Sports Teams & Leagues'!K8) | ... AK98: =IF('Sports Teams & Leagues'!AL8="","",'Sports Teams & Leagues'!AL8) | AL98: =IF(V98="","",V98+ROW()/100000)
A99: =IF('Sports Teams & Leagues'!B9="","","Sports Teams & Leagues") | B99: =IF('Sports Teams & Leagues'!B9="","",'Sports Teams & Leagues'!B9) | C99: =IF('Sports Teams & Leagues'!D9="","",'Sports Teams & Leagues'!D9) | D99: =IF('Sports Teams & Leagues'!E9="","",'Sports Teams & Leagues'!E9) | E99: =IF('Sports Teams & Leagues'!F9="","",'Sports Teams & Leagues'!F9) | F99: =IF('Sports Teams & Leagues'!G9="","",'Sports Teams & Leagues'!G9) | G99: =IF('Sports Teams & Leagues'!H9="","",'Sports Teams & Leagues'!H9) | H99: =IF('Sports Teams & Leagues'!I9="","",'Sports Teams & Leagues'!I9) | I99: =IF('Sports Teams & Leagues'!J9="","",'Sports Teams & Leagues'!J9) | J99: =IF('Sports Teams & Leagues'!K9="","",'Sports Teams & Leagues'!K9) | ... AK99: =IF('Sports Teams & Leagues'!AL9="","",'Sports Teams & Leagues'!AL9) | AL99: =IF(V99="","",V99+ROW()/100000)
A100: =IF('Sports Teams & Leagues'!B10="","","Sports Teams & Leagues") | B100: =IF('Sports Teams & Leagues'!B10="","",'Sports Teams & Leagues'!B10) | C100: =IF('Sports Teams & Leagues'!D10="","",'Sports Teams & Leagues'!D10) | D100: =IF('Sports Teams & Leagues'!E10="","",'Sports Teams & Leagues'!E10) | E100: =IF('Sports Teams & Leagues'!F10="","",'Sports Teams & Leagues'!F10) | F100: =IF('Sports Teams & Leagues'!G10="","",'Sports Teams & Leagues'!G10) | G100: =IF('Sports Teams & Leagues'!H10="","",'Sports Teams & Leagues'!H10) | H100: =IF('Sports Teams & Leagues'!I10="","",'Sports Teams & Leagues'!I10) | I100: =IF('Sports Teams & Leagues'!J10="","",'Sports Teams & Leagues'!J10) | J100: =IF('Sports Teams & Leagues'!K10="","",'Sports Teams & Leagues'!K10) | ... AK100: =IF('Sports Teams & Leagues'!AL10="","",'Sports Teams & Leagues'!AL10) | AL100: =IF(V100="","",V100+ROW()/100000)
A101: =IF('Sports Teams & Leagues'!B11="","","Sports Teams & Leagues") | B101: =IF('Sports Teams & Leagues'!B11="","",'Sports Teams & Leagues'!B11) | C101: =IF('Sports Teams & Leagues'!D11="","",'Sports Teams & Leagues'!D11) | D101: =IF('Sports Teams & Leagues'!E11="","",'Sports Teams & Leagues'!E11) | E101: =IF('Sports Teams & Leagues'!F11="","",'Sports Teams & Leagues'!F11) | F101: =IF('Sports Teams & Leagues'!G11="","",'Sports Teams & Leagues'!G11) | G101: =IF('Sports Teams & Leagues'!H11="","",'Sports Teams & Leagues'!H11) | H101: =IF('Sports Teams & Leagues'!I11="","",'Sports Teams & Leagues'!I11) | I101: =IF('Sports Teams & Leagues'!J11="","",'Sports Teams & Leagues'!J11) | J101: =IF('Sports Teams & Leagues'!K11="","",'Sports Teams & Leagues'!K11) | ... AK101: =IF('Sports Teams & Leagues'!AL11="","",'Sports Teams & Leagues'!AL11) | AL101: =IF(V101="","",V101+ROW()/100000)
A102: =IF('Sports Teams & Leagues'!B12="","","Sports Teams & Leagues") | B102: =IF('Sports Teams & Leagues'!B12="","",'Sports Teams & Leagues'!B12) | C102: =IF('Sports Teams & Leagues'!D12="","",'Sports Teams & Leagues'!D12) | D102: =IF('Sports Teams & Leagues'!E12="","",'Sports Teams & Leagues'!E12) | E102: =IF('Sports Teams & Leagues'!F12="","",'Sports Teams & Leagues'!F12) | F102: =IF('Sports Teams & Leagues'!G12="","",'Sports Teams & Leagues'!G12) | G102: =IF('Sports Teams & Leagues'!H12="","",'Sports Teams & Leagues'!H12) | H102: =IF('Sports Teams & Leagues'!I12="","",'Sports Teams & Leagues'!I12) | I102: =IF('Sports Teams & Leagues'!J12="","",'Sports Teams & Leagues'!J12) | J102: =IF('Sports Teams & Leagues'!K12="","",'Sports Teams & Leagues'!K12) | ... AK102: =IF('Sports Teams & Leagues'!AL12="","",'Sports Teams & Leagues'!AL12) | AL102: =IF(V102="","",V102+ROW()/100000)
A103: =IF('Sports Teams & Leagues'!B13="","","Sports Teams & Leagues") | B103: =IF('Sports Teams & Leagues'!B13="","",'Sports Teams & Leagues'!B13) | C103: =IF('Sports Teams & Leagues'!D13="","",'Sports Teams & Leagues'!D13) | D103: =IF('Sports Teams & Leagues'!E13="","",'Sports Teams & Leagues'!E13) | E103: =IF('Sports Teams & Leagues'!F13="","",'Sports Teams & Leagues'!F13) | F103: =IF('Sports Teams & Leagues'!G13="","",'Sports Teams & Leagues'!G13) | G103: =IF('Sports Teams & Leagues'!H13="","",'Sports Teams & Leagues'!H13) | H103: =IF('Sports Teams & Leagues'!I13="","",'Sports Teams & Leagues'!I13) | I103: =IF('Sports Teams & Leagues'!J13="","",'Sports Teams & Leagues'!J13) | J103: =IF('Sports Teams & Leagues'!K13="","",'Sports Teams & Leagues'!K13) | ... AK103: =IF('Sports Teams & Leagues'!AL13="","",'Sports Teams & Leagues'!AL13) | AL103: =IF(V103="","",V103+ROW()/100000)
A104: =IF('Sports Teams & Leagues'!B14="","","Sports Teams & Leagues") | B104: =IF('Sports Teams & Leagues'!B14="","",'Sports Teams & Leagues'!B14) | C104: =IF('Sports Teams & Leagues'!D14="","",'Sports Teams & Leagues'!D14) | D104: =IF('Sports Teams & Leagues'!E14="","",'Sports Teams & Leagues'!E14) | E104: =IF('Sports Teams & Leagues'!F14="","",'Sports Teams & Leagues'!F14) | F104: =IF('Sports Teams & Leagues'!G14="","",'Sports Teams & Leagues'!G14) | G104: =IF('Sports Teams & Leagues'!H14="","",'Sports Teams & Leagues'!H14) | H104: =IF('Sports Teams & Leagues'!I14="","",'Sports Teams & Leagues'!I14) | I104: =IF('Sports Teams & Leagues'!J14="","",'Sports Teams & Leagues'!J14) | J104: =IF('Sports Teams & Leagues'!K14="","",'Sports Teams & Leagues'!K14) | ... AK104: =IF('Sports Teams & Leagues'!AL14="","",'Sports Teams & Leagues'!AL14) | AL104: =IF(V104="","",V104+ROW()/100000)
... A122: =IF('Sports Teams & Leagues'!B32="","","Sports Teams & Leagues") | B122: =IF('Sports Teams & Leagues'!B32="","",'Sports Teams & Leagues'!B32) | C122: =IF('Sports Teams & Leagues'!D32="","",'Sports Teams & Leagues'!D32) | D122: =IF('Sports Teams & Leagues'!E32="","",'Sports Teams & Leagues'!E32) | E122: =IF('Sports Teams & Leagues'!F32="","",'Sports Teams & Leagues'!F32) | F122: =IF('Sports Teams & Leagues'!G32="","",'Sports Teams & Leagues'!G32) | G122: =IF('Sports Teams & Leagues'!H32="","",'Sports Teams & Leagues'!H32) | H122: =IF('Sports Teams & Leagues'!I32="","",'Sports Teams & Leagues'!I32) | I122: =IF('Sports Teams & Leagues'!J32="","",'Sports Teams & Leagues'!J32) | J122: =IF('Sports Teams & Leagues'!K32="","",'Sports Teams & Leagues'!K32) | ... AK122: =IF('Sports Teams & Leagues'!AL32="","",'Sports Teams & Leagues'!AL32) | AL122: =IF(V122="","",V122+ROW()/100000)
A123: =IF('Campus & Student Groups'!B3="","","Campus & Student Groups") | B123: =IF('Campus & Student Groups'!B3="","",'Campus & Student Groups'!B3) | C123: =IF('Campus & Student Groups'!D3="","",'Campus & Student Groups'!D3) | D123: =IF('Campus & Student Groups'!E3="","",'Campus & Student Groups'!E3) | E123: =IF('Campus & Student Groups'!F3="","",'Campus & Student Groups'!F3) | F123: =IF('Campus & Student Groups'!G3="","",'Campus & Student Groups'!G3) | G123: =IF('Campus & Student Groups'!H3="","",'Campus & Student Groups'!H3) | H123: =IF('Campus & Student Groups'!I3="","",'Campus & Student Groups'!I3) | I123: =IF('Campus & Student Groups'!J3="","",'Campus & Student Groups'!J3) | J123: =IF('Campus & Student Groups'!K3="","",'Campus & Student Groups'!K3) | ... AK123: =IF('Campus & Student Groups'!AL3="","",'Campus & Student Groups'!AL3) | AL123: =IF(V123="","",V123+ROW()/100000)
A124: =IF('Campus & Student Groups'!B4="","","Campus & Student Groups") | B124: =IF('Campus & Student Groups'!B4="","",'Campus & Student Groups'!B4) | C124: =IF('Campus & Student Groups'!D4="","",'Campus & Student Groups'!D4) | D124: =IF('Campus & Student Groups'!E4="","",'Campus & Student Groups'!E4) | E124: =IF('Campus & Student Groups'!F4="","",'Campus & Student Groups'!F4) | F124: =IF('Campus & Student Groups'!G4="","",'Campus & Student Groups'!G4) | G124: =IF('Campus & Student Groups'!H4="","",'Campus & Student Groups'!H4) | H124: =IF('Campus & Student Groups'!I4="","",'Campus & Student Groups'!I4) | I124: =IF('Campus & Student Groups'!J4="","",'Campus & Student Groups'!J4) | J124: =IF('Campus & Student Groups'!K4="","",'Campus & Student Groups'!K4) | ... AK124: =IF('Campus & Student Groups'!AL4="","",'Campus & Student Groups'!AL4) | AL124: =IF(V124="","",V124+ROW()/100000)
A125: =IF('Campus & Student Groups'!B5="","","Campus & Student Groups") | B125: =IF('Campus & Student Groups'!B5="","",'Campus & Student Groups'!B5) | C125: =IF('Campus & Student Groups'!D5="","",'Campus & Student Groups'!D5) | D125: =IF('Campus & Student Groups'!E5="","",'Campus & Student Groups'!E5) | E125: =IF('Campus & Student Groups'!F5="","",'Campus & Student Groups'!F5) | F125: =IF('Campus & Student Groups'!G5="","",'Campus & Student Groups'!G5) | G125: =IF('Campus & Student Groups'!H5="","",'Campus & Student Groups'!H5) | H125: =IF('Campus & Student Groups'!I5="","",'Campus & Student Groups'!I5) | I125: =IF('Campus & Student Groups'!J5="","",'Campus & Student Groups'!J5) | J125: =IF('Campus & Student Groups'!K5="","",'Campus & Student Groups'!K5) | ... AK125: =IF('Campus & Student Groups'!AL5="","",'Campus & Student Groups'!AL5) | AL125: =IF(V125="","",V125+ROW()/100000)
A126: =IF('Campus & Student Groups'!B6="","","Campus & Student Groups") | B126: =IF('Campus & Student Groups'!B6="","",'Campus & Student Groups'!B6) | C126: =IF('Campus & Student Groups'!D6="","",'Campus & Student Groups'!D6) | D126: =IF('Campus & Student Groups'!E6="","",'Campus & Student Groups'!E6) | E126: =IF('Campus & Student Groups'!F6="","",'Campus & Student Groups'!F6) | F126: =IF('Campus & Student Groups'!G6="","",'Campus & Student Groups'!G6) | G126: =IF('Campus & Student Groups'!H6="","",'Campus & Student Groups'!H6) | H126: =IF('Campus & Student Groups'!I6="","",'Campus & Student Groups'!I6) | I126: =IF('Campus & Student Groups'!J6="","",'Campus & Student Groups'!J6) | J126: =IF('Campus & Student Groups'!K6="","",'Campus & Student Groups'!K6) | ... AK126: =IF('Campus & Student Groups'!AL6="","",'Campus & Student Groups'!AL6) | AL126: =IF(V126="","",V126+ROW()/100000)
A127: =IF('Campus & Student Groups'!B7="","","Campus & Student Groups") | B127: =IF('Campus & Student Groups'!B7="","",'Campus & Student Groups'!B7) | C127: =IF('Campus & Student Groups'!D7="","",'Campus & Student Groups'!D7) | D127: =IF('Campus & Student Groups'!E7="","",'Campus & Student Groups'!E7) | E127: =IF('Campus & Student Groups'!F7="","",'Campus & Student Groups'!F7) | F127: =IF('Campus & Student Groups'!G7="","",'Campus & Student Groups'!G7) | G127: =IF('Campus & Student Groups'!H7="","",'Campus & Student Groups'!H7) | H127: =IF('Campus & Student Groups'!I7="","",'Campus & Student Groups'!I7) | I127: =IF('Campus & Student Groups'!J7="","",'Campus & Student Groups'!J7) | J127: =IF('Campus & Student Groups'!K7="","",'Campus & Student Groups'!K7) | ... AK127: =IF('Campus & Student Groups'!AL7="","",'Campus & Student Groups'!AL7) | AL127: =IF(V127="","",V127+ROW()/100000)
A128: =IF('Campus & Student Groups'!B8="","","Campus & Student Groups") | B128: =IF('Campus & Student Groups'!B8="","",'Campus & Student Groups'!B8) | C128: =IF('Campus & Student Groups'!D8="","",'Campus & Student Groups'!D8) | D128: =IF('Campus & Student Groups'!E8="","",'Campus & Student Groups'!E8) | E128: =IF('Campus & Student Groups'!F8="","",'Campus & Student Groups'!F8) | F128: =IF('Campus & Student Groups'!G8="","",'Campus & Student Groups'!G8) | G128: =IF('Campus & Student Groups'!H8="","",'Campus & Student Groups'!H8) | H128: =IF('Campus & Student Groups'!I8="","",'Campus & Student Groups'!I8) | I128: =IF('Campus & Student Groups'!J8="","",'Campus & Student Groups'!J8) | J128: =IF('Campus & Student Groups'!K8="","",'Campus & Student Groups'!K8) | ... AK128: =IF('Campus & Student Groups'!AL8="","",'Campus & Student Groups'!AL8) | AL128: =IF(V128="","",V128+ROW()/100000)
A129: =IF('Campus & Student Groups'!B9="","","Campus & Student Groups") | B129: =IF('Campus & Student Groups'!B9="","",'Campus & Student Groups'!B9) | C129: =IF('Campus & Student Groups'!D9="","",'Campus & Student Groups'!D9) | D129: =IF('Campus & Student Groups'!E9="","",'Campus & Student Groups'!E9) | E129: =IF('Campus & Student Groups'!F9="","",'Campus & Student Groups'!F9) | F129: =IF('Campus & Student Groups'!G9="","",'Campus & Student Groups'!G9) | G129: =IF('Campus & Student Groups'!H9="","",'Campus & Student Groups'!H9) | H129: =IF('Campus & Student Groups'!I9="","",'Campus & Student Groups'!I9) | I129: =IF('Campus & Student Groups'!J9="","",'Campus & Student Groups'!J9) | J129: =IF('Campus & Student Groups'!K9="","",'Campus & Student Groups'!K9) | ... AK129: =IF('Campus & Student Groups'!AL9="","",'Campus & Student Groups'!AL9) | AL129: =IF(V129="","",V129+ROW()/100000)
A130: =IF('Campus & Student Groups'!B10="","","Campus & Student Groups") | B130: =IF('Campus & Student Groups'!B10="","",'Campus & Student Groups'!B10) | C130: =IF('Campus & Student Groups'!D10="","",'Campus & Student Groups'!D10) | D130: =IF('Campus & Student Groups'!E10="","",'Campus & Student Groups'!E10) | E130: =IF('Campus & Student Groups'!F10="","",'Campus & Student Groups'!F10) | F130: =IF('Campus & Student Groups'!G10="","",'Campus & Student Groups'!G10) | G130: =IF('Campus & Student Groups'!H10="","",'Campus & Student Groups'!H10) | H130: =IF('Campus & Student Groups'!I10="","",'Campus & Student Groups'!I10) | I130: =IF('Campus & Student Groups'!J10="","",'Campus & Student Groups'!J10) | J130: =IF('Campus & Student Groups'!K10="","",'Campus & Student Groups'!K10) | ... AK130: =IF('Campus & Student Groups'!AL10="","",'Campus & Student Groups'!AL10) | AL130: =IF(V130="","",V130+ROW()/100000)
A131: =IF('Campus & Student Groups'!B11="","","Campus & Student Groups") | B131: =IF('Campus & Student Groups'!B11="","",'Campus & Student Groups'!B11) | C131: =IF('Campus & Student Groups'!D11="","",'Campus & Student Groups'!D11) | D131: =IF('Campus & Student Groups'!E11="","",'Campus & Student Groups'!E11) | E131: =IF('Campus & Student Groups'!F11="","",'Campus & Student Groups'!F11) | F131: =IF('Campus & Student Groups'!G11="","",'Campus & Student Groups'!G11) | G131: =IF('Campus & Student Groups'!H11="","",'Campus & Student Groups'!H11) | H131: =IF('Campus & Student Groups'!I11="","",'Campus & Student Groups'!I11) | I131: =IF('Campus & Student Groups'!J11="","",'Campus & Student Groups'!J11) | J131: =IF('Campus & Student Groups'!K11="","",'Campus & Student Groups'!K11) | ... AK131: =IF('Campus & Student Groups'!AL11="","",'Campus & Student Groups'!AL11) | AL131: =IF(V131="","",V131+ROW()/100000)
A132: =IF('Campus & Student Groups'!B12="","","Campus & Student Groups") | B132: =IF('Campus & Student Groups'!B12="","",'Campus & Student Groups'!B12) | C132: =IF('Campus & Student Groups'!D12="","",'Campus & Student Groups'!D12) | D132: =IF('Campus & Student Groups'!E12="","",'Campus & Student Groups'!E12) | E132: =IF('Campus & Student Groups'!F12="","",'Campus & Student Groups'!F12) | F132: =IF('Campus & Student Groups'!G12="","",'Campus & Student Groups'!G12) | G132: =IF('Campus & Student Groups'!H12="","",'Campus & Student Groups'!H12) | H132: =IF('Campus & Student Groups'!I12="","",'Campus & Student Groups'!I12) | I132: =IF('Campus & Student Groups'!J12="","",'Campus & Student Groups'!J12) | J132: =IF('Campus & Student Groups'!K12="","",'Campus & Student Groups'!K12) | ... AK132: =IF('Campus & Student Groups'!AL12="","",'Campus & Student Groups'!AL12) | AL132: =IF(V132="","",V132+ROW()/100000)
A133: =IF('Campus & Student Groups'!B13="","","Campus & Student Groups") | B133: =IF('Campus & Student Groups'!B13="","",'Campus & Student Groups'!B13) | C133: =IF('Campus & Student Groups'!D13="","",'Campus & Student Groups'!D13) | D133: =IF('Campus & Student Groups'!E13="","",'Campus & Student Groups'!E13) | E133: =IF('Campus & Student Groups'!F13="","",'Campus & Student Groups'!F13) | F133: =IF('Campus & Student Groups'!G13="","",'Campus & Student Groups'!G13) | G133: =IF('Campus & Student Groups'!H13="","",'Campus & Student Groups'!H13) | H133: =IF('Campus & Student Groups'!I13="","",'Campus & Student Groups'!I13) | I133: =IF('Campus & Student Groups'!J13="","",'Campus & Student Groups'!J13) | J133: =IF('Campus & Student Groups'!K13="","",'Campus & Student Groups'!K13) | ... AK133: =IF('Campus & Student Groups'!AL13="","",'Campus & Student Groups'!AL13) | AL133: =IF(V133="","",V133+ROW()/100000)
A134: =IF('Campus & Student Groups'!B14="","","Campus & Student Groups") | B134: =IF('Campus & Student Groups'!B14="","",'Campus & Student Groups'!B14) | C134: =IF('Campus & Student Groups'!D14="","",'Campus & Student Groups'!D14) | D134: =IF('Campus & Student Groups'!E14="","",'Campus & Student Groups'!E14) | E134: =IF('Campus & Student Groups'!F14="","",'Campus & Student Groups'!F14) | F134: =IF('Campus & Student Groups'!G14="","",'Campus & Student Groups'!G14) | G134: =IF('Campus & Student Groups'!H14="","",'Campus & Student Groups'!H14) | H134: =IF('Campus & Student Groups'!I14="","",'Campus & Student Groups'!I14) | I134: =IF('Campus & Student Groups'!J14="","",'Campus & Student Groups'!J14) | J134: =IF('Campus & Student Groups'!K14="","",'Campus & Student Groups'!K14) | ... AK134: =IF('Campus & Student Groups'!AL14="","",'Campus & Student Groups'!AL14) | AL134: =IF(V134="","",V134+ROW()/100000)
... A152: =IF('Campus & Student Groups'!B32="","","Campus & Student Groups") | B152: =IF('Campus & Student Groups'!B32="","",'Campus & Student Groups'!B32) | C152: =IF('Campus & Student Groups'!D32="","",'Campus & Student Groups'!D32) | D152: =IF('Campus & Student Groups'!E32="","",'Campus & Student Groups'!E32) | E152: =IF('Campus & Student Groups'!F32="","",'Campus & Student Groups'!F32) | F152: =IF('Campus & Student Groups'!G32="","",'Campus & Student Groups'!G32) | G152: =IF('Campus & Student Groups'!H32="","",'Campus & Student Groups'!H32) | H152: =IF('Campus & Student Groups'!I32="","",'Campus & Student Groups'!I32) | I152: =IF('Campus & Student Groups'!J32="","",'Campus & Student Groups'!J32) | J152: =IF('Campus & Student Groups'!K32="","",'Campus & Student Groups'!K32) | ... AK152: =IF('Campus & Student Groups'!AL32="","",'Campus & Student Groups'!AL32) | AL152: =IF(V152="","",V152+ROW()/100000)
A153: =IF('Wellness & Recovery'!B3="","","Wellness & Recovery") | B153: =IF('Wellness & Recovery'!B3="","",'Wellness & Recovery'!B3) | C153: =IF('Wellness & Recovery'!D3="","",'Wellness & Recovery'!D3) | D153: =IF('Wellness & Recovery'!E3="","",'Wellness & Recovery'!E3) | E153: =IF('Wellness & Recovery'!F3="","",'Wellness & Recovery'!F3) | F153: =IF('Wellness & Recovery'!G3="","",'Wellness & Recovery'!G3) | G153: =IF('Wellness & Recovery'!H3="","",'Wellness & Recovery'!H3) | H153: =IF('Wellness & Recovery'!I3="","",'Wellness & Recovery'!I3) | I153: =IF('Wellness & Recovery'!J3="","",'Wellness & Recovery'!J3) | J153: =IF('Wellness & Recovery'!K3="","",'Wellness & Recovery'!K3) | ... AK153: =IF('Wellness & Recovery'!AL3="","",'Wellness & Recovery'!AL3) | AL153: =IF(V153="","",V153+ROW()/100000)
A154: =IF('Wellness & Recovery'!B4="","","Wellness & Recovery") | B154: =IF('Wellness & Recovery'!B4="","",'Wellness & Recovery'!B4) | C154: =IF('Wellness & Recovery'!D4="","",'Wellness & Recovery'!D4) | D154: =IF('Wellness & Recovery'!E4="","",'Wellness & Recovery'!E4) | E154: =IF('Wellness & Recovery'!F4="","",'Wellness & Recovery'!F4) | F154: =IF('Wellness & Recovery'!G4="","",'Wellness & Recovery'!G4) | G154: =IF('Wellness & Recovery'!H4="","",'Wellness & Recovery'!H4) | H154: =IF('Wellness & Recovery'!I4="","",'Wellness & Recovery'!I4) | I154: =IF('Wellness & Recovery'!J4="","",'Wellness & Recovery'!J4) | J154: =IF('Wellness & Recovery'!K4="","",'Wellness & Recovery'!K4) | ... AK154: =IF('Wellness & Recovery'!AL4="","",'Wellness & Recovery'!AL4) | AL154: =IF(V154="","",V154+ROW()/100000)
A155: =IF('Wellness & Recovery'!B5="","","Wellness & Recovery") | B155: =IF('Wellness & Recovery'!B5="","",'Wellness & Recovery'!B5) | C155: =IF('Wellness & Recovery'!D5="","",'Wellness & Recovery'!D5) | D155: =IF('Wellness & Recovery'!E5="","",'Wellness & Recovery'!E5) | E155: =IF('Wellness & Recovery'!F5="","",'Wellness & Recovery'!F5) | F155: =IF('Wellness & Recovery'!G5="","",'Wellness & Recovery'!G5) | G155: =IF('Wellness & Recovery'!H5="","",'Wellness & Recovery'!H5) | H155: =IF('Wellness & Recovery'!I5="","",'Wellness & Recovery'!I5) | I155: =IF('Wellness & Recovery'!J5="","",'Wellness & Recovery'!J5) | J155: =IF('Wellness & Recovery'!K5="","",'Wellness & Recovery'!K5) | ... AK155: =IF('Wellness & Recovery'!AL5="","",'Wellness & Recovery'!AL5) | AL155: =IF(V155="","",V155+ROW()/100000)
A156: =IF('Wellness & Recovery'!B6="","","Wellness & Recovery") | B156: =IF('Wellness & Recovery'!B6="","",'Wellness & Recovery'!B6) | C156: =IF('Wellness & Recovery'!D6="","",'Wellness & Recovery'!D6) | D156: =IF('Wellness & Recovery'!E6="","",'Wellness & Recovery'!E6) | E156: =IF('Wellness & Recovery'!F6="","",'Wellness & Recovery'!F6) | F156: =IF('Wellness & Recovery'!G6="","",'Wellness & Recovery'!G6) | G156: =IF('Wellness & Recovery'!H6="","",'Wellness & Recovery'!H6) | H156: =IF('Wellness & Recovery'!I6="","",'Wellness & Recovery'!I6) | I156: =IF('Wellness & Recovery'!J6="","",'Wellness & Recovery'!J6) | J156: =IF('Wellness & Recovery'!K6="","",'Wellness & Recovery'!K6) | ... AK156: =IF('Wellness & Recovery'!AL6="","",'Wellness & Recovery'!AL6) | AL156: =IF(V156="","",V156+ROW()/100000)
A157: =IF('Wellness & Recovery'!B7="","","Wellness & Recovery") | B157: =IF('Wellness & Recovery'!B7="","",'Wellness & Recovery'!B7) | C157: =IF('Wellness & Recovery'!D7="","",'Wellness & Recovery'!D7) | D157: =IF('Wellness & Recovery'!E7="","",'Wellness & Recovery'!E7) | E157: =IF('Wellness & Recovery'!F7="","",'Wellness & Recovery'!F7) | F157: =IF('Wellness & Recovery'!G7="","",'Wellness & Recovery'!G7) | G157: =IF('Wellness & Recovery'!H7="","",'Wellness & Recovery'!H7) | H157: =IF('Wellness & Recovery'!I7="","",'Wellness & Recovery'!I7) | I157: =IF('Wellness & Recovery'!J7="","",'Wellness & Recovery'!J7) | J157: =IF('Wellness & Recovery'!K7="","",'Wellness & Recovery'!K7) | ... AK157: =IF('Wellness & Recovery'!AL7="","",'Wellness & Recovery'!AL7) | AL157: =IF(V157="","",V157+ROW()/100000)
A158: =IF('Wellness & Recovery'!B8="","","Wellness & Recovery") | B158: =IF('Wellness & Recovery'!B8="","",'Wellness & Recovery'!B8) | C158: =IF('Wellness & Recovery'!D8="","",'Wellness & Recovery'!D8) | D158: =IF('Wellness & Recovery'!E8="","",'Wellness & Recovery'!E8) | E158: =IF('Wellness & Recovery'!F8="","",'Wellness & Recovery'!F8) | F158: =IF('Wellness & Recovery'!G8="","",'Wellness & Recovery'!G8) | G158: =IF('Wellness & Recovery'!H8="","",'Wellness & Recovery'!H8) | H158: =IF('Wellness & Recovery'!I8="","",'Wellness & Recovery'!I8) | I158: =IF('Wellness & Recovery'!J8="","",'Wellness & Recovery'!J8) | J158: =IF('Wellness & Recovery'!K8="","",'Wellness & Recovery'!K8) | ... AK158: =IF('Wellness & Recovery'!AL8="","",'Wellness & Recovery'!AL8) | AL158: =IF(V158="","",V158+ROW()/100000)
A159: =IF('Wellness & Recovery'!B9="","","Wellness & Recovery") | B159: =IF('Wellness & Recovery'!B9="","",'Wellness & Recovery'!B9) | C159: =IF('Wellness & Recovery'!D9="","",'Wellness & Recovery'!D9) | D159: =IF('Wellness & Recovery'!E9="","",'Wellness & Recovery'!E9) | E159: =IF('Wellness & Recovery'!F9="","",'Wellness & Recovery'!F9) | F159: =IF('Wellness & Recovery'!G9="","",'Wellness & Recovery'!G9) | G159: =IF('Wellness & Recovery'!H9="","",'Wellness & Recovery'!H9) | H159: =IF('Wellness & Recovery'!I9="","",'Wellness & Recovery'!I9) | I159: =IF('Wellness & Recovery'!J9="","",'Wellness & Recovery'!J9) | J159: =IF('Wellness & Recovery'!K9="","",'Wellness & Recovery'!K9) | ... AK159: =IF('Wellness & Recovery'!AL9="","",'Wellness & Recovery'!AL9) | AL159: =IF(V159="","",V159+ROW()/100000)
A160: =IF('Wellness & Recovery'!B10="","","Wellness & Recovery") | B160: =IF('Wellness & Recovery'!B10="","",'Wellness & Recovery'!B10) | C160: =IF('Wellness & Recovery'!D10="","",'Wellness & Recovery'!D10) | D160: =IF('Wellness & Recovery'!E10="","",'Wellness & Recovery'!E10) | E160: =IF('Wellness & Recovery'!F10="","",'Wellness & Recovery'!F10) | F160: =IF('Wellness & Recovery'!G10="","",'Wellness & Recovery'!G10) | G160: =IF('Wellness & Recovery'!H10="","",'Wellness & Recovery'!H10) | H160: =IF('Wellness & Recovery'!I10="","",'Wellness & Recovery'!I10) | I160: =IF('Wellness & Recovery'!J10="","",'Wellness & Recovery'!J10) | J160: =IF('Wellness & Recovery'!K10="","",'Wellness & Recovery'!K10) | ... AK160: =IF('Wellness & Recovery'!AL10="","",'Wellness & Recovery'!AL10) | AL160: =IF(V160="","",V160+ROW()/100000)
A161: =IF('Wellness & Recovery'!B11="","","Wellness & Recovery") | B161: =IF('Wellness & Recovery'!B11="","",'Wellness & Recovery'!B11) | C161: =IF('Wellness & Recovery'!D11="","",'Wellness & Recovery'!D11) | D161: =IF('Wellness & Recovery'!E11="","",'Wellness & Recovery'!E11) | E161: =IF('Wellness & Recovery'!F11="","",'Wellness & Recovery'!F11) | F161: =IF('Wellness & Recovery'!G11="","",'Wellness & Recovery'!G11) | G161: =IF('Wellness & Recovery'!H11="","",'Wellness & Recovery'!H11) | H161: =IF('Wellness & Recovery'!I11="","",'Wellness & Recovery'!I11) | I161: =IF('Wellness & Recovery'!J11="","",'Wellness & Recovery'!J11) | J161: =IF('Wellness & Recovery'!K11="","",'Wellness & Recovery'!K11) | ... AK161: =IF('Wellness & Recovery'!AL11="","",'Wellness & Recovery'!AL11) | AL161: =IF(V161="","",V161+ROW()/100000)
A162: =IF('Wellness & Recovery'!B12="","","Wellness & Recovery") | B162: =IF('Wellness & Recovery'!B12="","",'Wellness & Recovery'!B12) | C162: =IF('Wellness & Recovery'!D12="","",'Wellness & Recovery'!D12) | D162: =IF('Wellness & Recovery'!E12="","",'Wellness & Recovery'!E12) | E162: =IF('Wellness & Recovery'!F12="","",'Wellness & Recovery'!F12) | F162: =IF('Wellness & Recovery'!G12="","",'Wellness & Recovery'!G12) | G162: =IF('Wellness & Recovery'!H12="","",'Wellness & Recovery'!H12) | H162: =IF('Wellness & Recovery'!I12="","",'Wellness & Recovery'!I12) | I162: =IF('Wellness & Recovery'!J12="","",'Wellness & Recovery'!J12) | J162: =IF('Wellness & Recovery'!K12="","",'Wellness & Recovery'!K12) | ... AK162: =IF('Wellness & Recovery'!AL12="","",'Wellness & Recovery'!AL12) | AL162: =IF(V162="","",V162+ROW()/100000)
A163: =IF('Wellness & Recovery'!B13="","","Wellness & Recovery") | B163: =IF('Wellness & Recovery'!B13="","",'Wellness & Recovery'!B13) | C163: =IF('Wellness & Recovery'!D13="","",'Wellness & Recovery'!D13) | D163: =IF('Wellness & Recovery'!E13="","",'Wellness & Recovery'!E13) | E163: =IF('Wellness & Recovery'!F13="","",'Wellness & Recovery'!F13) | F163: =IF('Wellness & Recovery'!G13="","",'Wellness & Recovery'!G13) | G163: =IF('Wellness & Recovery'!H13="","",'Wellness & Recovery'!H13) | H163: =IF('Wellness & Recovery'!I13="","",'Wellness & Recovery'!I13) | I163: =IF('Wellness & Recovery'!J13="","",'Wellness & Recovery'!J13) | J163: =IF('Wellness & Recovery'!K13="","",'Wellness & Recovery'!K13) | ... AK163: =IF('Wellness & Recovery'!AL13="","",'Wellness & Recovery'!AL13) | AL163: =IF(V163="","",V163+ROW()/100000)
A164: =IF('Wellness & Recovery'!B14="","","Wellness & Recovery") | B164: =IF('Wellness & Recovery'!B14="","",'Wellness & Recovery'!B14) | C164: =IF('Wellness & Recovery'!D14="","",'Wellness & Recovery'!D14) | D164: =IF('Wellness & Recovery'!E14="","",'Wellness & Recovery'!E14) | E164: =IF('Wellness & Recovery'!F14="","",'Wellness & Recovery'!F14) | F164: =IF('Wellness & Recovery'!G14="","",'Wellness & Recovery'!G14) | G164: =IF('Wellness & Recovery'!H14="","",'Wellness & Recovery'!H14) | H164: =IF('Wellness & Recovery'!I14="","",'Wellness & Recovery'!I14) | I164: =IF('Wellness & Recovery'!J14="","",'Wellness & Recovery'!J14) | J164: =IF('Wellness & Recovery'!K14="","",'Wellness & Recovery'!K14) | ... AK164: =IF('Wellness & Recovery'!AL14="","",'Wellness & Recovery'!AL14) | AL164: =IF(V164="","",V164+ROW()/100000)
... A182: =IF('Wellness & Recovery'!B32="","","Wellness & Recovery") | B182: =IF('Wellness & Recovery'!B32="","",'Wellness & Recovery'!B32) | C182: =IF('Wellness & Recovery'!D32="","",'Wellness & Recovery'!D32) | D182: =IF('Wellness & Recovery'!E32="","",'Wellness & Recovery'!E32) | E182: =IF('Wellness & Recovery'!F32="","",'Wellness & Recovery'!F32) | F182: =IF('Wellness & Recovery'!G32="","",'Wellness & Recovery'!G32) | G182: =IF('Wellness & Recovery'!H32="","",'Wellness & Recovery'!H32) | H182: =IF('Wellness & Recovery'!I32="","",'Wellness & Recovery'!I32) | I182: =IF('Wellness & Recovery'!J32="","",'Wellness & Recovery'!J32) | J182: =IF('Wellness & Recovery'!K32="","",'Wellness & Recovery'!K32) | ... AK182: =IF('Wellness & Recovery'!AL32="","",'Wellness & Recovery'!AL32) | AL182: =IF(V182="","",V182+ROW()/100000)
A183: =IF('Ambassadors & Creators'!B3="","","Ambassadors & Creators") | B183: =IF('Ambassadors & Creators'!B3="","",'Ambassadors & Creators'!B3) | C183: =IF('Ambassadors & Creators'!D3="","",'Ambassadors & Creators'!D3) | D183: =IF('Ambassadors & Creators'!E3="","",'Ambassadors & Creators'!E3) | E183: =IF('Ambassadors & Creators'!F3="","",'Ambassadors & Creators'!F3) | F183: =IF('Ambassadors & Creators'!G3="","",'Ambassadors & Creators'!G3) | G183: =IF('Ambassadors & Creators'!H3="","",'Ambassadors & Creators'!H3) | H183: =IF('Ambassadors & Creators'!I3="","",'Ambassadors & Creators'!I3) | I183: =IF('Ambassadors & Creators'!J3="","",'Ambassadors & Creators'!J3) | J183: =IF('Ambassadors & Creators'!K3="","",'Ambassadors & Creators'!K3) | ... AK183: =IF('Ambassadors & Creators'!AL3="","",'Ambassadors & Creators'!AL3) | AL183: =IF(V183="","",V183+ROW()/100000)
A184: =IF('Ambassadors & Creators'!B4="","","Ambassadors & Creators") | B184: =IF('Ambassadors & Creators'!B4="","",'Ambassadors & Creators'!B4) | C184: =IF('Ambassadors & Creators'!D4="","",'Ambassadors & Creators'!D4) | D184: =IF('Ambassadors & Creators'!E4="","",'Ambassadors & Creators'!E4) | E184: =IF('Ambassadors & Creators'!F4="","",'Ambassadors & Creators'!F4) | F184: =IF('Ambassadors & Creators'!G4="","",'Ambassadors & Creators'!G4) | G184: =IF('Ambassadors & Creators'!H4="","",'Ambassadors & Creators'!H4) | H184: =IF('Ambassadors & Creators'!I4="","",'Ambassadors & Creators'!I4) | I184: =IF('Ambassadors & Creators'!J4="","",'Ambassadors & Creators'!J4) | J184: =IF('Ambassadors & Creators'!K4="","",'Ambassadors & Creators'!K4) | ... AK184: =IF('Ambassadors & Creators'!AL4="","",'Ambassadors & Creators'!AL4) | AL184: =IF(V184="","",V184+ROW()/100000)
A185: =IF('Ambassadors & Creators'!B5="","","Ambassadors & Creators") | B185: =IF('Ambassadors & Creators'!B5="","",'Ambassadors & Creators'!B5) | C185: =IF('Ambassadors & Creators'!D5="","",'Ambassadors & Creators'!D5) | D185: =IF('Ambassadors & Creators'!E5="","",'Ambassadors & Creators'!E5) | E185: =IF('Ambassadors & Creators'!F5="","",'Ambassadors & Creators'!F5) | F185: =IF('Ambassadors & Creators'!G5="","",'Ambassadors & Creators'!G5) | G185: =IF('Ambassadors & Creators'!H5="","",'Ambassadors & Creators'!H5) | H185: =IF('Ambassadors & Creators'!I5="","",'Ambassadors & Creators'!I5) | I185: =IF('Ambassadors & Creators'!J5="","",'Ambassadors & Creators'!J5) | J185: =IF('Ambassadors & Creators'!K5="","",'Ambassadors & Creators'!K5) | ... AK185: =IF('Ambassadors & Creators'!AL5="","",'Ambassadors & Creators'!AL5) | AL185: =IF(V185="","",V185+ROW()/100000)
A186: =IF('Ambassadors & Creators'!B6="","","Ambassadors & Creators") | B186: =IF('Ambassadors & Creators'!B6="","",'Ambassadors & Creators'!B6) | C186: =IF('Ambassadors & Creators'!D6="","",'Ambassadors & Creators'!D6) | D186: =IF('Ambassadors & Creators'!E6="","",'Ambassadors & Creators'!E6) | E186: =IF('Ambassadors & Creators'!F6="","",'Ambassadors & Creators'!F6) | F186: =IF('Ambassadors & Creators'!G6="","",'Ambassadors & Creators'!G6) | G186: =IF('Ambassadors & Creators'!H6="","",'Ambassadors & Creators'!H6) | H186: =IF('Ambassadors & Creators'!I6="","",'Ambassadors & Creators'!I6) | I186: =IF('Ambassadors & Creators'!J6="","",'Ambassadors & Creators'!J6) | J186: =IF('Ambassadors & Creators'!K6="","",'Ambassadors & Creators'!K6) | ... AK186: =IF('Ambassadors & Creators'!AL6="","",'Ambassadors & Creators'!AL6) | AL186: =IF(V186="","",V186+ROW()/100000)
A187: =IF('Ambassadors & Creators'!B7="","","Ambassadors & Creators") | B187: =IF('Ambassadors & Creators'!B7="","",'Ambassadors & Creators'!B7) | C187: =IF('Ambassadors & Creators'!D7="","",'Ambassadors & Creators'!D7) | D187: =IF('Ambassadors & Creators'!E7="","",'Ambassadors & Creators'!E7) | E187: =IF('Ambassadors & Creators'!F7="","",'Ambassadors & Creators'!F7) | F187: =IF('Ambassadors & Creators'!G7="","",'Ambassadors & Creators'!G7) | G187: =IF('Ambassadors & Creators'!H7="","",'Ambassadors & Creators'!H7) | H187: =IF('Ambassadors & Creators'!I7="","",'Ambassadors & Creators'!I7) | I187: =IF('Ambassadors & Creators'!J7="","",'Ambassadors & Creators'!J7) | J187: =IF('Ambassadors & Creators'!K7="","",'Ambassadors & Creators'!K7) | ... AK187: =IF('Ambassadors & Creators'!AL7="","",'Ambassadors & Creators'!AL7) | AL187: =IF(V187="","",V187+ROW()/100000)
A188: =IF('Ambassadors & Creators'!B8="","","Ambassadors & Creators") | B188: =IF('Ambassadors & Creators'!B8="","",'Ambassadors & Creators'!B8) | C188: =IF('Ambassadors & Creators'!D8="","",'Ambassadors & Creators'!D8) | D188: =IF('Ambassadors & Creators'!E8="","",'Ambassadors & Creators'!E8) | E188: =IF('Ambassadors & Creators'!F8="","",'Ambassadors & Creators'!F8) | F188: =IF('Ambassadors & Creators'!G8="","",'Ambassadors & Creators'!G8) | G188: =IF('Ambassadors & Creators'!H8="","",'Ambassadors & Creators'!H8) | H188: =IF('Ambassadors & Creators'!I8="","",'Ambassadors & Creators'!I8) | I188: =IF('Ambassadors & Creators'!J8="","",'Ambassadors & Creators'!J8) | J188: =IF('Ambassadors & Creators'!K8="","",'Ambassadors & Creators'!K8) | ... AK188: =IF('Ambassadors & Creators'!AL8="","",'Ambassadors & Creators'!AL8) | AL188: =IF(V188="","",V188+ROW()/100000)
A189: =IF('Ambassadors & Creators'!B9="","","Ambassadors & Creators") | B189: =IF('Ambassadors & Creators'!B9="","",'Ambassadors & Creators'!B9) | C189: =IF('Ambassadors & Creators'!D9="","",'Ambassadors & Creators'!D9) | D189: =IF('Ambassadors & Creators'!E9="","",'Ambassadors & Creators'!E9) | E189: =IF('Ambassadors & Creators'!F9="","",'Ambassadors & Creators'!F9) | F189: =IF('Ambassadors & Creators'!G9="","",'Ambassadors & Creators'!G9) | G189: =IF('Ambassadors & Creators'!H9="","",'Ambassadors & Creators'!H9) | H189: =IF('Ambassadors & Creators'!I9="","",'Ambassadors & Creators'!I9) | I189: =IF('Ambassadors & Creators'!J9="","",'Ambassadors & Creators'!J9) | J189: =IF('Ambassadors & Creators'!K9="","",'Ambassadors & Creators'!K9) | ... AK189: =IF('Ambassadors & Creators'!AL9="","",'Ambassadors & Creators'!AL9) | AL189: =IF(V189="","",V189+ROW()/100000)
A190: =IF('Ambassadors & Creators'!B10="","","Ambassadors & Creators") | B190: =IF('Ambassadors & Creators'!B10="","",'Ambassadors & Creators'!B10) | C190: =IF('Ambassadors & Creators'!D10="","",'Ambassadors & Creators'!D10) | D190: =IF('Ambassadors & Creators'!E10="","",'Ambassadors & Creators'!E10) | E190: =IF('Ambassadors & Creators'!F10="","",'Ambassadors & Creators'!F10) | F190: =IF('Ambassadors & Creators'!G10="","",'Ambassadors & Creators'!G10) | G190: =IF('Ambassadors & Creators'!H10="","",'Ambassadors & Creators'!H10) | H190: =IF('Ambassadors & Creators'!I10="","",'Ambassadors & Creators'!I10) | I190: =IF('Ambassadors & Creators'!J10="","",'Ambassadors & Creators'!J10) | J190: =IF('Ambassadors & Creators'!K10="","",'Ambassadors & Creators'!K10) | ... AK190: =IF('Ambassadors & Creators'!AL10="","",'Ambassadors & Creators'!AL10) | AL190: =IF(V190="","",V190+ROW()/100000)
A191: =IF('Ambassadors & Creators'!B11="","","Ambassadors & Creators") | B191: =IF('Ambassadors & Creators'!B11="","",'Ambassadors & Creators'!B11) | C191: =IF('Ambassadors & Creators'!D11="","",'Ambassadors & Creators'!D11) | D191: =IF('Ambassadors & Creators'!E11="","",'Ambassadors & Creators'!E11) | E191: =IF('Ambassadors & Creators'!F11="","",'Ambassadors & Creators'!F11) | F191: =IF('Ambassadors & Creators'!G11="","",'Ambassadors & Creators'!G11) | G191: =IF('Ambassadors & Creators'!H11="","",'Ambassadors & Creators'!H11) | H191: =IF('Ambassadors & Creators'!I11="","",'Ambassadors & Creators'!I11) | I191: =IF('Ambassadors & Creators'!J11="","",'Ambassadors & Creators'!J11) | J191: =IF('Ambassadors & Creators'!K11="","",'Ambassadors & Creators'!K11) | ... AK191: =IF('Ambassadors & Creators'!AL11="","",'Ambassadors & Creators'!AL11) | AL191: =IF(V191="","",V191+ROW()/100000)
A192: =IF('Ambassadors & Creators'!B12="","","Ambassadors & Creators") | B192: =IF('Ambassadors & Creators'!B12="","",'Ambassadors & Creators'!B12) | C192: =IF('Ambassadors & Creators'!D12="","",'Ambassadors & Creators'!D12) | D192: =IF('Ambassadors & Creators'!E12="","",'Ambassadors & Creators'!E12) | E192: =IF('Ambassadors & Creators'!F12="","",'Ambassadors & Creators'!F12) | F192: =IF('Ambassadors & Creators'!G12="","",'Ambassadors & Creators'!G12) | G192: =IF('Ambassadors & Creators'!H12="","",'Ambassadors & Creators'!H12) | H192: =IF('Ambassadors & Creators'!I12="","",'Ambassadors & Creators'!I12) | I192: =IF('Ambassadors & Creators'!J12="","",'Ambassadors & Creators'!J12) | J192: =IF('Ambassadors & Creators'!K12="","",'Ambassadors & Creators'!K12) | ... AK192: =IF('Ambassadors & Creators'!AL12="","",'Ambassadors & Creators'!AL12) | AL192: =IF(V192="","",V192+ROW()/100000)
A193: =IF('Ambassadors & Creators'!B13="","","Ambassadors & Creators") | B193: =IF('Ambassadors & Creators'!B13="","",'Ambassadors & Creators'!B13) | C193: =IF('Ambassadors & Creators'!D13="","",'Ambassadors & Creators'!D13) | D193: =IF('Ambassadors & Creators'!E13="","",'Ambassadors & Creators'!E13) | E193: =IF('Ambassadors & Creators'!F13="","",'Ambassadors & Creators'!F13) | F193: =IF('Ambassadors & Creators'!G13="","",'Ambassadors & Creators'!G13) | G193: =IF('Ambassadors & Creators'!H13="","",'Ambassadors & Creators'!H13) | H193: =IF('Ambassadors & Creators'!I13="","",'Ambassadors & Creators'!I13) | I193: =IF('Ambassadors & Creators'!J13="","",'Ambassadors & Creators'!J13) | J193: =IF('Ambassadors & Creators'!K13="","",'Ambassadors & Creators'!K13) | ... AK193: =IF('Ambassadors & Creators'!AL13="","",'Ambassadors & Creators'!AL13) | AL193: =IF(V193="","",V193+ROW()/100000)
A194: =IF('Ambassadors & Creators'!B14="","","Ambassadors & Creators") | B194: =IF('Ambassadors & Creators'!B14="","",'Ambassadors & Creators'!B14) | C194: =IF('Ambassadors & Creators'!D14="","",'Ambassadors & Creators'!D14) | D194: =IF('Ambassadors & Creators'!E14="","",'Ambassadors & Creators'!E14) | E194: =IF('Ambassadors & Creators'!F14="","",'Ambassadors & Creators'!F14) | F194: =IF('Ambassadors & Creators'!G14="","",'Ambassadors & Creators'!G14) | G194: =IF('Ambassadors & Creators'!H14="","",'Ambassadors & Creators'!H14) | H194: =IF('Ambassadors & Creators'!I14="","",'Ambassadors & Creators'!I14) | I194: =IF('Ambassadors & Creators'!J14="","",'Ambassadors & Creators'!J14) | J194: =IF('Ambassadors & Creators'!K14="","",'Ambassadors & Creators'!K14) | ... AK194: =IF('Ambassadors & Creators'!AL14="","",'Ambassadors & Creators'!AL14) | AL194: =IF(V194="","",V194+ROW()/100000)
... A212: =IF('Ambassadors & Creators'!B32="","","Ambassadors & Creators") | B212: =IF('Ambassadors & Creators'!B32="","",'Ambassadors & Creators'!B32) | C212: =IF('Ambassadors & Creators'!D32="","",'Ambassadors & Creators'!D32) | D212: =IF('Ambassadors & Creators'!E32="","",'Ambassadors & Creators'!E32) | E212: =IF('Ambassadors & Creators'!F32="","",'Ambassadors & Creators'!F32) | F212: =IF('Ambassadors & Creators'!G32="","",'Ambassadors & Creators'!G32) | G212: =IF('Ambassadors & Creators'!H32="","",'Ambassadors & Creators'!H32) | H212: =IF('Ambassadors & Creators'!I32="","",'Ambassadors & Creators'!I32) | I212: =IF('Ambassadors & Creators'!J32="","",'Ambassadors & Creators'!J32) | J212: =IF('Ambassadors & Creators'!K32="","",'Ambassadors & Creators'!K32) | ... AK212: =IF('Ambassadors & Creators'!AL32="","",'Ambassadors & Creators'!AL32) | AL212: =IF(V212="","",V212+ROW()/100000)
A213: =IF('Charity & Causes'!B3="","","Charity & Causes") | B213: =IF('Charity & Causes'!B3="","",'Charity & Causes'!B3) | C213: =IF('Charity & Causes'!D3="","",'Charity & Causes'!D3) | D213: =IF('Charity & Causes'!E3="","",'Charity & Causes'!E3) | E213: =IF('Charity & Causes'!F3="","",'Charity & Causes'!F3) | F213: =IF('Charity & Causes'!G3="","",'Charity & Causes'!G3) | G213: =IF('Charity & Causes'!H3="","",'Charity & Causes'!H3) | H213: =IF('Charity & Causes'!I3="","",'Charity & Causes'!I3) | I213: =IF('Charity & Causes'!J3="","",'Charity & Causes'!J3) | J213: =IF('Charity & Causes'!K3="","",'Charity & Causes'!K3) | ... AK213: =IF('Charity & Causes'!AL3="","",'Charity & Causes'!AL3) | AL213: =IF(V213="","",V213+ROW()/100000)
A214: =IF('Charity & Causes'!B4="","","Charity & Causes") | B214: =IF('Charity & Causes'!B4="","",'Charity & Causes'!B4) | C214: =IF('Charity & Causes'!D4="","",'Charity & Causes'!D4) | D214: =IF('Charity & Causes'!E4="","",'Charity & Causes'!E4) | E214: =IF('Charity & Causes'!F4="","",'Charity & Causes'!F4) | F214: =IF('Charity & Causes'!G4="","",'Charity & Causes'!G4) | G214: =IF('Charity & Causes'!H4="","",'Charity & Causes'!H4) | H214: =IF('Charity & Causes'!I4="","",'Charity & Causes'!I4) | I214: =IF('Charity & Causes'!J4="","",'Charity & Causes'!J4) | J214: =IF('Charity & Causes'!K4="","",'Charity & Causes'!K4) | ... AK214: =IF('Charity & Causes'!AL4="","",'Charity & Causes'!AL4) | AL214: =IF(V214="","",V214+ROW()/100000)
A215: =IF('Charity & Causes'!B5="","","Charity & Causes") | B215: =IF('Charity & Causes'!B5="","",'Charity & Causes'!B5) | C215: =IF('Charity & Causes'!D5="","",'Charity & Causes'!D5) | D215: =IF('Charity & Causes'!E5="","",'Charity & Causes'!E5) | E215: =IF('Charity & Causes'!F5="","",'Charity & Causes'!F5) | F215: =IF('Charity & Causes'!G5="","",'Charity & Causes'!G5) | G215: =IF('Charity & Causes'!H5="","",'Charity & Causes'!H5) | H215: =IF('Charity & Causes'!I5="","",'Charity & Causes'!I5) | I215: =IF('Charity & Causes'!J5="","",'Charity & Causes'!J5) | J215: =IF('Charity & Causes'!K5="","",'Charity & Causes'!K5) | ... AK215: =IF('Charity & Causes'!AL5="","",'Charity & Causes'!AL5) | AL215: =IF(V215="","",V215+ROW()/100000)
A216: =IF('Charity & Causes'!B6="","","Charity & Causes") | B216: =IF('Charity & Causes'!B6="","",'Charity & Causes'!B6) | C216: =IF('Charity & Causes'!D6="","",'Charity & Causes'!D6) | D216: =IF('Charity & Causes'!E6="","",'Charity & Causes'!E6) | E216: =IF('Charity & Causes'!F6="","",'Charity & Causes'!F6) | F216: =IF('Charity & Causes'!G6="","",'Charity & Causes'!G6) | G216: =IF('Charity & Causes'!H6="","",'Charity & Causes'!H6) | H216: =IF('Charity & Causes'!I6="","",'Charity & Causes'!I6) | I216: =IF('Charity & Causes'!J6="","",'Charity & Causes'!J6) | J216: =IF('Charity & Causes'!K6="","",'Charity & Causes'!K6) | ... AK216: =IF('Charity & Causes'!AL6="","",'Charity & Causes'!AL6) | AL216: =IF(V216="","",V216+ROW()/100000)
A217: =IF('Charity & Causes'!B7="","","Charity & Causes") | B217: =IF('Charity & Causes'!B7="","",'Charity & Causes'!B7) | C217: =IF('Charity & Causes'!D7="","",'Charity & Causes'!D7) | D217: =IF('Charity & Causes'!E7="","",'Charity & Causes'!E7) | E217: =IF('Charity & Causes'!F7="","",'Charity & Causes'!F7) | F217: =IF('Charity & Causes'!G7="","",'Charity & Causes'!G7) | G217: =IF('Charity & Causes'!H7="","",'Charity & Causes'!H7) | H217: =IF('Charity & Causes'!I7="","",'Charity & Causes'!I7) | I217: =IF('Charity & Causes'!J7="","",'Charity & Causes'!J7) | J217: =IF('Charity & Causes'!K7="","",'Charity & Causes'!K7) | ... AK217: =IF('Charity & Causes'!AL7="","",'Charity & Causes'!AL7) | AL217: =IF(V217="","",V217+ROW()/100000)
A218: =IF('Charity & Causes'!B8="","","Charity & Causes") | B218: =IF('Charity & Causes'!B8="","",'Charity & Causes'!B8) | C218: =IF('Charity & Causes'!D8="","",'Charity & Causes'!D8) | D218: =IF('Charity & Causes'!E8="","",'Charity & Causes'!E8) | E218: =IF('Charity & Causes'!F8="","",'Charity & Causes'!F8) | F218: =IF('Charity & Causes'!G8="","",'Charity & Causes'!G8) | G218: =IF('Charity & Causes'!H8="","",'Charity & Causes'!H8) | H218: =IF('Charity & Causes'!I8="","",'Charity & Causes'!I8) | I218: =IF('Charity & Causes'!J8="","",'Charity & Causes'!J8) | J218: =IF('Charity & Causes'!K8="","",'Charity & Causes'!K8) | ... AK218: =IF('Charity & Causes'!AL8="","",'Charity & Causes'!AL8) | AL218: =IF(V218="","",V218+ROW()/100000)
A219: =IF('Charity & Causes'!B9="","","Charity & Causes") | B219: =IF('Charity & Causes'!B9="","",'Charity & Causes'!B9) | C219: =IF('Charity & Causes'!D9="","",'Charity & Causes'!D9) | D219: =IF('Charity & Causes'!E9="","",'Charity & Causes'!E9) | E219: =IF('Charity & Causes'!F9="","",'Charity & Causes'!F9) | F219: =IF('Charity & Causes'!G9="","",'Charity & Causes'!G9) | G219: =IF('Charity & Causes'!H9="","",'Charity & Causes'!H9) | H219: =IF('Charity & Causes'!I9="","",'Charity & Causes'!I9) | I219: =IF('Charity & Causes'!J9="","",'Charity & Causes'!J9) | J219: =IF('Charity & Causes'!K9="","",'Charity & Causes'!K9) | ... AK219: =IF('Charity & Causes'!AL9="","",'Charity & Causes'!AL9) | AL219: =IF(V219="","",V219+ROW()/100000)
...

Sheet Type Summary
A1: Type Summary
A2: Partnership Type | B2: Target (draft) | C2: Partners | D2: P1 | E2: P2 | F2: P3 | G2: In Conversation | H2: Agreed | I2: Activated | J2: Cases Committed | K2: % to Target
A3: Run Clubs | B3: 10 | C3: =COUNTA('Run Clubs'!$B$3:$B$32) | D3: =COUNTIF('Run Clubs'!$F$3:$F$32,"P1") | E3: =COUNTIF('Run Clubs'!$F$3:$F$32,"P2") | F3: =COUNTIF('Run Clubs'!$F$3:$F$32,"P3") | G3: =COUNTIF('Run Clubs'!$G$3:$G$32,"In Conversation") | H3: =COUNTIF('Run Clubs'!$G$3:$G$32,"Agreed") | I3: =COUNTIF('Run Clubs'!$G$3:$G$32,"Activated")+COUNTIF('Run Clubs'!$G$3:$G$32,"Repeat Partner") | J3: =SUM('Run Clubs'!$X$3:$X$32) | K3: =IFERROR(C3/B3,0)
A4: Gyms & Studios | B4: 10 | C4: =COUNTA('Gyms & Studios'!$B$3:$B$32) | D4: =COUNTIF('Gyms & Studios'!$F$3:$F$32,"P1") | E4: =COUNTIF('Gyms & Studios'!$F$3:$F$32,"P2") | F4: =COUNTIF('Gyms & Studios'!$F$3:$F$32,"P3") | G4: =COUNTIF('Gyms & Studios'!$G$3:$G$32,"In Conversation") | H4: =COUNTIF('Gyms & Studios'!$G$3:$G$32,"Agreed") | I4: =COUNTIF('Gyms & Studios'!$G$3:$G$32,"Activated")+COUNTIF('Gyms & Studios'!$G$3:$G$32,"Repeat Partner") | J4: =SUM('Gyms & Studios'!$X$3:$X$32) | K4: =IFERROR(C4/B4,0)
A5: Events & Festivals | B5: 8 | C5: =COUNTA('Events & Festivals'!$B$3:$B$32) | D5: =COUNTIF('Events & Festivals'!$F$3:$F$32,"P1") | E5: =COUNTIF('Events & Festivals'!$F$3:$F$32,"P2") | F5: =COUNTIF('Events & Festivals'!$F$3:$F$32,"P3") | G5: =COUNTIF('Events & Festivals'!$G$3:$G$32,"In Conversation") | H5: =COUNTIF('Events & Festivals'!$G$3:$G$32,"Agreed") | I5: =COUNTIF('Events & Festivals'!$G$3:$G$32,"Activated")+COUNTIF('Events & Festivals'!$G$3:$G$32,"Repeat Partner") | J5: =SUM('Events & Festivals'!$X$3:$X$32) | K5: =IFERROR(C5/B5,0)
A6: Sports Teams & Leagues | B6: 6 | C6: =COUNTA('Sports Teams & Leagues'!$B$3:$B$32) | D6: =COUNTIF('Sports Teams & Leagues'!$F$3:$F$32,"P1") | E6: =COUNTIF('Sports Teams & Leagues'!$F$3:$F$32,"P2") | F6: =COUNTIF('Sports Teams & Leagues'!$F$3:$F$32,"P3") | G6: =COUNTIF('Sports Teams & Leagues'!$G$3:$G$32,"In Conversation") | H6: =COUNTIF('Sports Teams & Leagues'!$G$3:$G$32,"Agreed") | I6: =COUNTIF('Sports Teams & Leagues'!$G$3:$G$32,"Activated")+COUNTIF('Sports Teams & Leagues'!$G$3:$G$32,"Repeat Partner") | J6: =SUM('Sports Teams & Leagues'!$X$3:$X$32) | K6: =IFERROR(C6/B6,0)
A7: Campus & Student Groups | B7: 6 | C7: =COUNTA('Campus & Student Groups'!$B$3:$B$32) | D7: =COUNTIF('Campus & Student Groups'!$F$3:$F$32,"P1") | E7: =COUNTIF('Campus & Student Groups'!$F$3:$F$32,"P2") | F7: =COUNTIF('Campus & Student Groups'!$F$3:$F$32,"P3") | G7: =COUNTIF('Campus & Student Groups'!$G$3:$G$32,"In Conversation") | H7: =COUNTIF('Campus & Student Groups'!$G$3:$G$32,"Agreed") | I7: =COUNTIF('Campus & Student Groups'!$G$3:$G$32,"Activated")+COUNTIF('Campus & Student Groups'!$G$3:$G$32,"Repeat Partner") | J7: =SUM('Campus & Student Groups'!$X$3:$X$32) | K7: =IFERROR(C7/B7,0)
A8: Wellness & Recovery | B8: 6 | C8: =COUNTA('Wellness & Recovery'!$B$3:$B$32) | D8: =COUNTIF('Wellness & Recovery'!$F$3:$F$32,"P1") | E8: =COUNTIF('Wellness & Recovery'!$F$3:$F$32,"P2") | F8: =COUNTIF('Wellness & Recovery'!$F$3:$F$32,"P3") | G8: =COUNTIF('Wellness & Recovery'!$G$3:$G$32,"In Conversation") | H8: =COUNTIF('Wellness & Recovery'!$G$3:$G$32,"Agreed") | I8: =COUNTIF('Wellness & Recovery'!$G$3:$G$32,"Activated")+COUNTIF('Wellness & Recovery'!$G$3:$G$32,"Repeat Partner") | J8: =SUM('Wellness & Recovery'!$X$3:$X$32) | K8: =IFERROR(C8/B8,0)
A9: Ambassadors & Creators | B9: 8 | C9: =COUNTA('Ambassadors & Creators'!$B$3:$B$32) | D9: =COUNTIF('Ambassadors & Creators'!$F$3:$F$32,"P1") | E9: =COUNTIF('Ambassadors & Creators'!$F$3:$F$32,"P2") | F9: =COUNTIF('Ambassadors & Creators'!$F$3:$F$32,"P3") | G9: =COUNTIF('Ambassadors & Creators'!$G$3:$G$32,"In Conversation") | H9: =COUNTIF('Ambassadors & Creators'!$G$3:$G$32,"Agreed") | I9: =COUNTIF('Ambassadors & Creators'!$G$3:$G$32,"Activated")+COUNTIF('Ambassadors & Creators'!$G$3:$G$32,"Repeat Partner") | J9: =SUM('Ambassadors & Creators'!$X$3:$X$32) | K9: =IFERROR(C9/B9,0)
A10: Charity & Causes | B10: 4 | C10: =COUNTA('Charity & Causes'!$B$3:$B$32) | D10: =COUNTIF('Charity & Causes'!$F$3:$F$32,"P1") | E10: =COUNTIF('Charity & Causes'!$F$3:$F$32,"P2") | F10: =COUNTIF('Charity & Causes'!$F$3:$F$32,"P3") | G10: =COUNTIF('Charity & Causes'!$G$3:$G$32,"In Conversation") | H10: =COUNTIF('Charity & Causes'!$G$3:$G$32,"Agreed") | I10: =COUNTIF('Charity & Causes'!$G$3:$G$32,"Activated")+COUNTIF('Charity & Causes'!$G$3:$G$32,"Repeat Partner") | J10: =SUM('Charity & Causes'!$X$3:$X$32) | K10: =IFERROR(C10/B10,0)
A11: Total | B11: =SUM(B3:B10) | C11: =SUM(C3:C10) | D11: =SUM(D3:D10) | E11: =SUM(E3:E10) | F11: =SUM(F3:F10) | G11: =SUM(G3:G10) | H11: =SUM(H3:H10) | I11: =SUM(I3:I10) | J11: =SUM(J3:J10) | K11: =IFERROR(C11/B11,0)
A13: Targets are a starting draft for Louis to confirm. Edit the Target column any time.

Sheet Budget
A1: Budget
A2: Partnership Type | B2: Total Budget ($) | C2: Committed ($) | D2: Spent ($) | E2: Remaining ($) | F2: % Spent
A3: Run Clubs | B3: 0 | C3: 0 | D3: =SUM('Run Clubs'!$Z$3:$Z$32) | E3: =B3-D3 | F3: =IFERROR(D3/B3,0)
A4: Gyms & Studios | B4: 0 | C4: 0 | D4: =SUM('Gyms & Studios'!$Z$3:$Z$32) | E4: =B4-D4 | F4: =IFERROR(D4/B4,0)
A5: Events & Festivals | B5: 0 | C5: 0 | D5: =SUM('Events & Festivals'!$Z$3:$Z$32) | E5: =B5-D5 | F5: =IFERROR(D5/B5,0)
A6: Sports Teams & Leagues | B6: 0 | C6: 0 | D6: =SUM('Sports Teams & Leagues'!$Z$3:$Z$32) | E6: =B6-D6 | F6: =IFERROR(D6/B6,0)
A7: Campus & Student Groups | B7: 0 | C7: 0 | D7: =SUM('Campus & Student Groups'!$Z$3:$Z$32) | E7: =B7-D7 | F7: =IFERROR(D7/B7,0)
A8: Wellness & Recovery | B8: 0 | C8: 0 | D8: =SUM('Wellness & Recovery'!$Z$3:$Z$32) | E8: =B8-D8 | F8: =IFERROR(D8/B8,0)
A9: Ambassadors & Creators | B9: 0 | C9: 0 | D9: =SUM('Ambassadors & Creators'!$Z$3:$Z$32) | E9: =B9-D9 | F9: =IFERROR(D9/B9,0)
A10: Charity & Causes | B10: 0 | C10: 0 | D10: =SUM('Charity & Causes'!$Z$3:$Z$32) | E10: =B10-D10 | F10: =IFERROR(D10/B10,0)
A11: Total | B11: =SUM(B3:B10) | C11: =SUM(C3:C10) | D11: =SUM(D3:D10) | E11: =SUM(E3:E10) | F11: =IFERROR(D11/B11,0)
A13: Total Budget and Committed are yours to set and start at zero. Spent rolls up the Cost column from each type tab.

Sheet Run Clubs
A1: Run Clubs
A2: # | B2: Partner Name | C2: Partnership Type | D2: City | E2: Neighbourhood | F2: Priority | G2: Status | H2: Primary Owner | I2: Contact Name | J2: Role | K2: Contact Email | L2: Contact Phone | M2: Instagram or Website | N2: Audience Size | O2: Audience Source | P2: Source | Q2: Warm | R2: Last Contacted | S2: Days Since Activity | T2: Next Action | U2: Next Action Date | V2: Activation Type | W2: Activation Date | X2: Cases Committed | Y2: Cases Delivered | Z2: Cost ($) | AA2: Cost Per Can | AB2: Contra Value ($) | AC2: Deliverables Promised | AD2: Deliverables Received | AE2: What They Want | AF2: Risks | AG2: Nearby Retail Doors | AH2: In BC Tracker? | AI2: Raspberry 4338 | AJ2: Lemon Lime 4336 | AK2: Pineapple Passion Fruit 4340 | AL2: Notes
A3: =IF($B3="","",ROW()-2) | B3: East Van Run Crew | C3: =IF($B3="","","Run Clubs") | D3: Vancouver | E3: East Vancouver | F3: P1 | G3: Open | H3: Maddie | M3: @eastvanruncrew | N3: 11,000 IG | O3: Instagram @eastvanruncrew follower count, web search 2026 | P3: Verified Web | Q3: Cold | S3: =IF(ISBLANK(R3),"",TODAY()-R3) | AA3: =IF(OR($Z3="",$Y3="",$Y3=0),"",$Z3/($Y3*24)) | AH3: No | AL3: Monday night runs starting from a rotating East Van brewery.
A4: =IF($B4="","",ROW()-2) | B4: Social Run Club YVR | C4: =IF($B4="","","Run Clubs") | D4: Vancouver | E4: Yaletown | F4: P1 | G4: Open | H4: Maddie | M4: @socialrunclub.yvr | N4: 12,000 IG | O4: Instagram @socialrunclub.yvr follower count, web search 2026 | P4: Verified Web | Q4: Cold | S4: =IF(ISBLANK(R4),"",TODAY()-R4) | AA4: =IF(OR($Z4="",$Y4="",$Y4=0),"",$Z4/($Y4*24)) | AH4: No | AL4: Saturday 9:30am Form Focus run that ends with a coffee social.
A5: =IF($B5="","",ROW()-2) | B5: Slow Girls Run Club | C5: =IF($B5="","","Run Clubs") | D5: Vancouver | E5: Downtown | F5: P1 | G5: Open | H5: Maddie | M5: @slowgirlsrunclub | N5: 9,400 IG | O5: Instagram @slowgirlsrunclub follower count, web search 2026 | P5: Verified Web | Q5: Cold | S5: =IF(ISBLANK(R5),"",TODAY()-R5) | AA5: =IF(OR($Z5="",$Y5="",$Y5=0),"",$Z5/($Y5*24)) | AH5: No | AL5: Saturday 8am Social Saturdays 5km. Women focused community.
A6: =IF($B6="","",ROW()-2) | B6: One Run Club | C6: =IF($B6="","","Run Clubs") | D6: Vancouver | E6: West End | F6: P2 | G6: Open | H6: Maddie | M6: @onerunclubvan | N6: 7,950 IG | O6: Instagram @onerunclubvan follower count, web search 2026. About 1,536 active members on Heylo | P6: Verified Web | Q6: Cold | S6: =IF(ISBLANK(R6),"",TODAY()-R6) | AA6: =IF(OR($Z6="",$Y6="",$Y6=0),"",$Z6/($Y6*24)) | AH6: No | AL6: Wednesday 6:30pm run with a social wrap at English Bay.
A7: =IF($B7="","",ROW()-2) | B7: Striderz Run Club | C7: =IF($B7="","","Run Clubs") | D7: Vancouver | E7: Olympic Village | F7: P2 | G7: Open | H7: Maddie | M7: @striderzrunclub | N7: 1,120 IG | O7: Instagram @striderzrunclub follower count, web search 2026 | P7: Verified Web | Q7: Cold | S7: =IF(ISBLANK(R7),"",TODAY()-R7) | AA7: =IF(OR($Z7="",$Y7="",$Y7=0),"",$Z7/($Y7*24)) | AH7: No | AL7: Free Sunday 8:30am social run from Athletes Way, all paces regroup.
A8: =IF($B8="","",ROW()-2) | B8: North Shore Women's Trail Running Club | C8: =IF($B8="","","Run Clubs") | D8: North Vancouver | E8: Lynn Valley | F8: P2 | G8: Open | H8: Maddie | M8: @northshore__runclub | N8: 2,930 IG | O8: Instagram @northshore__runclub follower count, web search 2026 | P8: Verified Web | Q8: Cold | S8: =IF(ISBLANK(R8),"",TODAY()-R8) | AA8: =IF(OR($Z8="",$Y8="",$Y8=0),"",$Z8/($Y8*24)) | AH8: No | AL8: Trail runs meeting at the End of the Line General Store.
A9: =IF($B9="","",ROW()-2) | B9: North Burnaby Runners | C9: =IF($B9="","","Run Clubs") | D9: Burnaby | E9: North Burnaby | F9: P2 | G9: Open | H9: Maddie | M9: @northburnabyrunners | N9: 2,370 IG | O9: Instagram @northburnabyrunners follower count, web search 2026 | P9: Verified Web | Q9: Cold | S9: =IF(ISBLANK(R9),"",TODAY()-R9) | AA9: =IF(OR($Z9="",$Y9="",$Y9=0),"",$Z9/($Y9*24)) | AH9: No | AL9: Wednesday 6:30pm social run from Dageraad Brewing.
A10: =IF($B10="","",ROW()-2) | B10: Flight Crew Run Club | C10: =IF($B10="","","Run Clubs") | D10: Vancouver | E10: Kitsilano | F10: P2 | G10: Open | H10: Maddie | M10: @flightcrewrunclub | N10: TBD | P10: Verified Web | Q10: Cold | S10: =IF(ISBLANK(R10),"",TODAY()-R10) | AA10: =IF(OR($Z10="",$Y10="",$Y10=0),"",$Z10/($Y10*24)) | AH10: No | AL10: Thursday 6:15pm Kitsilano road run with 3km, 5km and 10km options. Run by Vancouver Running Company.
A11: =IF($B11="","",ROW()-2) | B11: Capital City Run Crew | C11: =IF($B11="","","Run Clubs") | D11: Victoria | E11: Downtown | F11: P2 | G11: Open | H11: Maddie | M11: @capitalcityruncrew | N11: 2,820 IG | O11: Instagram @capitalcityruncrew follower count, web search 2026 | P11: Verified Web | Q11: Cold | S11: =IF(ISBLANK(R11),"",TODAY()-R11) | AA11: =IF(OR($Z11="",$Y11="",$Y11=0),"",$Z11/($Y11*24)) | AH11: No | AL11: Thursday evening downtown run.
A12: =IF($B12="","",ROW()-2) | B12: Kelowna Running Club | C12: =IF($B12="","","Run Clubs") | D12: Kelowna | E12: Waterfront Park | F12: P3 | G12: Open | H12: Maddie | M12: @kelownarunningclub | N12: 990 IG | O12: Instagram @kelownarunningclub follower count, web search 2026 | P12: Verified Web | Q12: Cold | S12: =IF(ISBLANK(R12),"",TODAY()-R12) | AA12: =IF(OR($Z12="",$Y12="",$Y12=0),"",$Z12/($Y12*24)) | AH12: No | AL12: Saturday long runs from rotating spots plus Tuesday speed work. 2026 schedule on the club site.
A13: =IF($B13="","",ROW()-2) | C13: =IF($B13="","","Run Clubs") | S13: =IF(ISBLANK(R13),"",TODAY()-R13) | AA13: =IF(OR($Z13="",$Y13="",$Y13=0),"",$Z13/($Y13*24))
A14: =IF($B14="","",ROW()-2) | C14: =IF($B14="","","Run Clubs") | S14: =IF(ISBLANK(R14),"",TODAY()-R14) | AA14: =IF(OR($Z14="",$Y14="",$Y14=0),"",$Z14/($Y14*24))
A15: =IF($B15="","",ROW()-2) | C15: =IF($B15="","","Run Clubs") | S15: =IF(ISBLANK(R15),"",TODAY()-R15) | AA15: =IF(OR($Z15="",$Y15="",$Y15=0),"",$Z15/($Y15*24))
A16: =IF($B16="","",ROW()-2) | C16: =IF($B16="","","Run Clubs") | S16: =IF(ISBLANK(R16),"",TODAY()-R16) | AA16: =IF(OR($Z16="",$Y16="",$Y16=0),"",$Z16/($Y16*24))
A17: =IF($B17="","",ROW()-2) | C17: =IF($B17="","","Run Clubs") | S17: =IF(ISBLANK(R17),"",TODAY()-R17) | AA17: =IF(OR($Z17="",$Y17="",$Y17=0),"",$Z17/($Y17*24))
A18: =IF($B18="","",ROW()-2) | C18: =IF($B18="","","Run Clubs") | S18: =IF(ISBLANK(R18),"",TODAY()-R18) | AA18: =IF(OR($Z18="",$Y18="",$Y18=0),"",$Z18/($Y18*24))
A19: =IF($B19="","",ROW()-2) | C19: =IF($B19="","","Run Clubs") | S19: =IF(ISBLANK(R19),"",TODAY()-R19) | AA19: =IF(OR($Z19="",$Y19="",$Y19=0),"",$Z19/($Y19*24))
A20: =IF($B20="","",ROW()-2) | C20: =IF($B20="","","Run Clubs") | S20: =IF(ISBLANK(R20),"",TODAY()-R20) | AA20: =IF(OR($Z20="",$Y20="",$Y20=0),"",$Z20/($Y20*24))
A21: =IF($B21="","",ROW()-2) | C21: =IF($B21="","","Run Clubs") | S21: =IF(ISBLANK(R21),"",TODAY()-R21) | AA21: =IF(OR($Z21="",$Y21="",$Y21=0),"",$Z21/($Y21*24))
A22: =IF($B22="","",ROW()-2) | C22: =IF($B22="","","Run Clubs") | S22: =IF(ISBLANK(R22),"",TODAY()-R22) | AA22: =IF(OR($Z22="",$Y22="",$Y22=0),"",$Z22/($Y22*24))
A23: =IF($B23="","",ROW()-2) | C23: =IF($B23="","","Run Clubs") | S23: =IF(ISBLANK(R23),"",TODAY()-R23) | AA23: =IF(OR($Z23="",$Y23="",$Y23=0),"",$Z23/($Y23*24))
A24: =IF($B24="","",ROW()-2) | C24: =IF($B24="","","Run Clubs") | S24: =IF(ISBLANK(R24),"",TODAY()-R24) | AA24: =IF(OR($Z24="",$Y24="",$Y24=0),"",$Z24/($Y24*24))
... A32: =IF($B32="","",ROW()-2) | C32: =IF($B32="","","Run Clubs") | S32: =IF(ISBLANK(R32),"",TODAY()-R32) | AA32: =IF(OR($Z32="",$Y32="",$Y32=0),"",$Z32/($Y32*24))

Sheet Gyms & Studios
A1: Gyms & Studios
A2: # | B2: Partner Name | C2: Partnership Type | D2: City | E2: Neighbourhood | F2: Priority | G2: Status | H2: Primary Owner | I2: Contact Name | J2: Role | K2: Contact Email | L2: Contact Phone | M2: Instagram or Website | N2: Audience Size | O2: Audience Source | P2: Source | Q2: Warm | R2: Last Contacted | S2: Days Since Activity | T2: Next Action | U2: Next Action Date | V2: Activation Type | W2: Activation Date | X2: Cases Committed | Y2: Cases Delivered | Z2: Cost ($) | AA2: Cost Per Can | AB2: Contra Value ($) | AC2: Deliverables Promised | AD2: Deliverables Received | AE2: What They Want | AF2: Risks | AG2: Nearby Retail Doors | AH2: In BC Tracker? | AI2: Raspberry 4338 | AJ2: Lemon Lime 4336 | AK2: Pineapple Passion Fruit 4340 | AL2: Notes
A3: =IF($B3="","",ROW()-2) | B3: RIDE Cycle Club | C3: =IF($B3="","","Gyms & Studios") | D3: Vancouver | E3: Yaletown | F3: P1 | G3: Open | H3: Maddie | M3: @ridecycleclub | N3: 23,000 IG | O3: Instagram @ridecycleclub follower count, web search 2026. Account covers Vancouver and Toronto | P3: Verified Web | Q3: Cold | S3: =IF(ISBLANK(R3),"",TODAY()-R3) | AA3: =IF(OR($Z3="",$Y3="",$Y3=0),"",$Z3/($Y3*24)) | AH3: No | AL3: Spin studio on Hamilton Street, part of a multi city brand.
A4: =IF($B4="","",ROW()-2) | B4: The Hive Bouldering Gym | C4: =IF($B4="","","Gyms & Studios") | D4: Vancouver | E4: Strathcona | F4: P1 | G4: Open | H4: Maddie | M4: @hiveclimbing | N4: 21,000 IG | O4: Instagram @hiveclimbing follower count, web search 2026. Brand account, several BC sites | P4: Verified Web | Q4: Cold | S4: =IF(ISBLANK(R4),"",TODAY()-R4) | AA4: =IF(OR($Z4="",$Y4="",$Y4=0),"",$Z4/($Y4*24)) | AH4: No | AL4: Bouldering gym on Industrial Avenue, brand has several BC locations.
A5: =IF($B5="","",ROW()-2) | B5: Progression Bouldering | C5: =IF($B5="","","Gyms & Studios") | D5: Vancouver | E5: Mount Pleasant | F5: P1 | G5: Open | H5: Maddie | M5: @progressionbouldering | N5: 9,700 IG | O5: Instagram @progressionbouldering follower count, web search 2026 | P5: Verified Web | Q5: Cold | S5: =IF(ISBLANK(R5),"",TODAY()-R5) | AA5: =IF(OR($Z5="",$Y5="",$Y5=0),"",$Z5/($Y5*24)) | AH5: No | AL5: 18,000 sq ft bouldering gym with a licensed cafe on site.
A6: =IF($B6="","",ROW()-2) | B6: Tantra Fitness | C6: =IF($B6="","","Gyms & Studios") | D6: Vancouver | E6: Kitsilano | F6: P2 | G6: Open | H6: Maddie | M6: @tantrafitness | N6: 17,000 IG | O6: Instagram @tantrafitness follower count, web search 2026 (single snippet, reverify) | P6: Pending | Q6: Cold | S6: =IF(ISBLANK(R6),"",TODAY()-R6) | AA6: =IF(OR($Z6="",$Y6="",$Y6=0),"",$Z6/($Y6*24)) | AH6: No | AL6: Pole and aerial fitness across three Vancouver locations.
A7: =IF($B7="","",ROW()-2) | B7: 604 Athletics | C7: =IF($B7="","","Gyms & Studios") | D7: Vancouver | E7: Mount Pleasant | F7: P2 | G7: Open | H7: Maddie | M7: @604_athletics | N7: 6,100 IG | O7: Instagram @604_athletics follower count, web search 2026 (single snippet, reverify) | P7: Pending | Q7: Cold | S7: =IF(ISBLANK(R7),"",TODAY()-R7) | AA7: =IF(OR($Z7="",$Y7="",$Y7=0),"",$Z7/($Y7*24)) | AH7: No | AL7: CrossFit box on Main Street, runs HYROX prep classes.
A8: =IF($B8="","",ROW()-2) | B8: FAR Studio | C8: =IF($B8="","","Gyms & Studios") | D8: Vancouver | E8: Gastown | F8: P2 | G8: Open | H8: Maddie | M8: @farstudiogym | N8: 2,450 IG | O8: Instagram @farstudiogym follower count, web search 2026 (single snippet, reverify) | P8: Pending | Q8: Cold | S8: =IF(ISBLANK(R8),"",TODAY()-R8) | AA8: =IF(OR($Z8="",$Y8="",$Y8=0),"",$Z8/($Y8*24)) | AH8: No | AL8: Kickboxing and strength studio on Powell Street.
A9: =IF($B9="","",ROW()-2) | B9: The Lab Victoria | C9: =IF($B9="","","Gyms & Studios") | D9: Victoria | E9: Downtown | F9: P2 | G9: Open | H9: Maddie | M9: @thelabvictoria | N9: 3,500 IG | O9: Instagram @thelabvictoria follower count, web search 2026 (single snippet, reverify) | P9: Pending | Q9: Cold | S9: =IF(ISBLANK(R9),"",TODAY()-R9) | AA9: =IF(OR($Z9="",$Y9="",$Y9=0),"",$Z9/($Y9*24)) | AH9: No | AL9: Yoga and pilates studio on Fort Street.
A10: =IF($B10="","",ROW()-2) | B10: CrossFit BC | C10: =IF($B10="","","Gyms & Studios") | D10: Vancouver | E10: Olympic Village | F10: P3 | G10: Open | H10: Maddie | M10: @crossfitbc | N10: TBD | P10: Verified Web | Q10: Cold | S10: =IF(ISBLANK(R10),"",TODAY()-R10) | AA10: =IF(OR($Z10="",$Y10="",$Y10=0),"",$Z10/($Y10*24)) | AH10: No | AL10: CrossFit box on East 1st Avenue.
A11: =IF($B11="","",ROW()-2) | B11: CrossFit Zone | C11: =IF($B11="","","Gyms & Studios") | D11: Victoria | E11: Downtown | F11: P3 | G11: Open | H11: Maddie | M11: @crossfit_zone_ | N11: TBD | P11: Verified Web | Q11: Cold | S11: =IF(ISBLANK(R11),"",TODAY()-R11) | AA11: =IF(OR($Z11="",$Y11="",$Y11=0),"",$Z11/($Y11*24)) | AH11: No | AL11: One of the oldest CrossFit boxes in Victoria, operating since 2008.
A12: =IF($B12="","",ROW()-2) | B12: CrossFit Okanagan | C12: =IF($B12="","","Gyms & Studios") | D12: Kelowna | E12: Kelowna | F12: P3 | G12: Open | H12: Maddie | M12: @crossfitokanagan | N12: 4,700 IG | O12: Instagram @crossfitokanagan follower count, web search 2026 (single snippet, reverify) | P12: Pending | Q12: Cold | S12: =IF(ISBLANK(R12),"",TODAY()-R12) | AA12: =IF(OR($Z12="",$Y12="",$Y12=0),"",$Z12/($Y12*24)) | AH12: No | AL12: CrossFit box, also runs a ForeverFit 55 plus program.
A13: =IF($B13="","",ROW()-2) | C13: =IF($B13="","","Gyms & Studios") | S13: =IF(ISBLANK(R13),"",TODAY()-R13) | AA13: =IF(OR($Z13="",$Y13="",$Y13=0),"",$Z13/($Y13*24))
A14: =IF($B14="","",ROW()-2) | C14: =IF($B14="","","Gyms & Studios") | S14: =IF(ISBLANK(R14),"",TODAY()-R14) | AA14: =IF(OR($Z14="",$Y14="",$Y14=0),"",$Z14/($Y14*24))
A15: =IF($B15="","",ROW()-2) | C15: =IF($B15="","","Gyms & Studios") | S15: =IF(ISBLANK(R15),"",TODAY()-R15) | AA15: =IF(OR($Z15="",$Y15="",$Y15=0),"",$Z15/($Y15*24))
A16: =IF($B16="","",ROW()-2) | C16: =IF($B16="","","Gyms & Studios") | S16: =IF(ISBLANK(R16),"",TODAY()-R16) | AA16: =IF(OR($Z16="",$Y16="",$Y16=0),"",$Z16/($Y16*24))
A17: =IF($B17="","",ROW()-2) | C17: =IF($B17="","","Gyms & Studios") | S17: =IF(ISBLANK(R17),"",TODAY()-R17) | AA17: =IF(OR($Z17="",$Y17="",$Y17=0),"",$Z17/($Y17*24))
A18: =IF($B18="","",ROW()-2) | C18: =IF($B18="","","Gyms & Studios") | S18: =IF(ISBLANK(R18),"",TODAY()-R18) | AA18: =IF(OR($Z18="",$Y18="",$Y18=0),"",$Z18/($Y18*24))
A19: =IF($B19="","",ROW()-2) | C19: =IF($B19="","","Gyms & Studios") | S19: =IF(ISBLANK(R19),"",TODAY()-R19) | AA19: =IF(OR($Z19="",$Y19="",$Y19=0),"",$Z19/($Y19*24))
A20: =IF($B20="","",ROW()-2) | C20: =IF($B20="","","Gyms & Studios") | S20: =IF(ISBLANK(R20),"",TODAY()-R20) | AA20: =IF(OR($Z20="",$Y20="",$Y20=0),"",$Z20/($Y20*24))
A21: =IF($B21="","",ROW()-2) | C21: =IF($B21="","","Gyms & Studios") | S21: =IF(ISBLANK(R21),"",TODAY()-R21) | AA21: =IF(OR($Z21="",$Y21="",$Y21=0),"",$Z21/($Y21*24))
A22: =IF($B22="","",ROW()-2) | C22: =IF($B22="","","Gyms & Studios") | S22: =IF(ISBLANK(R22),"",TODAY()-R22) | AA22: =IF(OR($Z22="",$Y22="",$Y22=0),"",$Z22/($Y22*24))
A23: =IF($B23="","",ROW()-2) | C23: =IF($B23="","","Gyms & Studios") | S23: =IF(ISBLANK(R23),"",TODAY()-R23) | AA23: =IF(OR($Z23="",$Y23="",$Y23=0),"",$Z23/($Y23*24))
A24: =IF($B24="","",ROW()-2) | C24: =IF($B24="","","Gyms & Studios") | S24: =IF(ISBLANK(R24),"",TODAY()-R24) | AA24: =IF(OR($Z24="",$Y24="",$Y24=0),"",$Z24/($Y24*24))
... A32: =IF($B32="","",ROW()-2) | C32: =IF($B32="","","Gyms & Studios") | S32: =IF(ISBLANK(R32),"",TODAY()-R32) | AA32: =IF(OR($Z32="",$Y32="",$Y32=0),"",$Z32/($Y32*24))

Sheet Events & Festivals
A1: Events & Festivals
A2: # | B2: Partner Name | C2: Partnership Type | D2: City | E2: Neighbourhood | F2: Priority | G2: Status | H2: Primary Owner | I2: Contact Name | J2: Role | K2: Contact Email | L2: Contact Phone | M2: Instagram or Website | N2: Audience Size | O2: Audience Source | P2: Source | Q2: Warm | R2: Last Contacted | S2: Days Since Activity | T2: Next Action | U2: Next Action Date | V2: Activation Type | W2: Activation Date | X2: Cases Committed | Y2: Cases Delivered | Z2: Cost ($) | AA2: Cost Per Can | AB2: Contra Value ($) | AC2: Deliverables Promised | AD2: Deliverables Received | AE2: What They Want | AF2: Risks | AG2: Nearby Retail Doors | AH2: In BC Tracker? | AI2: Raspberry 4338 | AJ2: Lemon Lime 4336 | AK2: Pineapple Passion Fruit 4340 | AL2: Notes
A3: =IF($B3="","",ROW()-2) | B3: Richmond Night Market | C3: =IF($B3="","","Events & Festivals") | D3: Richmond | E3: Bridgeport | F3: P1 | G3: Open | H3: Maddie | M3: richmondnightmarket.com | N3: 1,000,000+ per year | O3: vancouversbestplaces and official market materials, over a million visitors annually | P3: Verified Web | Q3: Cold | S3: =IF(ISBLANK(R3),"",TODAY()-R3) | AA3: =IF(OR($Z3="",$Y3="",$Y3=0),"",$Z3/($Y3*24)) | AH3: No | AL3: Runs Apr 24 to Sep 20 2026, Friday to Sunday evenings, near Bridgeport station.
A4: =IF($B4="","",ROW()-2) | B4: Vancouver Pride Parade and Festival | C4: =IF($B4="","","Events & Festivals") | D4: Vancouver | E4: West End | F4: P1 | G4: Open | H4: Maddie | M4: @vancouverpride | N4: 600,000+ attendees (press estimate) | O4: misterbandb and Destination Vancouver listings cite 600,000 plus, press estimate not official | P4: Verified Web | Q4: Cold | S4: =IF(ISBLANK(R4),"",TODAY()-R4) | AA4: =IF(OR($Z4="",$Y4="",$Y4=0),"",$Z4/($Y4*24)) | AH4: No | AL4: Pride week Jul 25 to Aug 2 2026, main parade Sunday Aug 2 ending at Sunset Beach.
A5: =IF($B5="","",ROW()-2) | B5: Concord Pacific Dragon Boat Summer Regatta | C5: =IF($B5="","","Events & Festivals") | D5: Vancouver | E5: False Creek | F5: P1 | G5: Open | H5: Maddie | M5: dragonboatbc.ca | N5: TBD | P5: Verified Web | Q5: Cold | S5: =IF(ISBLANK(R5),"",TODAY()-R5) | AA5: =IF(OR($Z5="",$Y5="",$Y5=0),"",$Z5/($Y5*24)) | AH5: No | AL5: One day regatta Aug 22 2026 at False Creek. Downsized for 2026 due to the FIFA security cordon, full festival returns 2027.
A6: =IF($B6="","",ROW()-2) | B6: Italian Day on The Drive | C6: =IF($B6="","","Events & Festivals") | D6: Vancouver | E6: Commercial Drive | F6: P2 | G6: Open | H6: Maddie | M6: @italiandayonthedrive | N6: 300,000 (press estimate) | O6: Vancouver Is Awesome 2026 coverage cites 300,000, press estimate not official | P6: Verified Web | Q6: Cold | S6: =IF(ISBLANK(R6),"",TODAY()-R6) | AA6: =IF(OR($Z6="",$Y6="",$Y6=0),"",$Z6/($Y6*24)) | AH6: No | AL6: Sunday Jun 14 2026, noon to 8pm, 14 blocks of Commercial Drive.
A7: =IF($B7="","",ROW()-2) | B7: Khatsahlano Street Party | C7: =IF($B7="","","Events & Festivals") | D7: Vancouver | E7: Kitsilano | F7: P2 | G7: Open | H7: Maddie | M7: @khatsahlano | N7: TBD | P7: Verified Web | Q7: Cold | S7: =IF(ISBLANK(R7),"",TODAY()-R7) | AA7: =IF(OR($Z7="",$Y7="",$Y7=0),"",$Z7/($Y7*24)) | AH7: No | AL7: Saturday Jul 11 2026 on West 4th Ave, 10 blocks, free street festival.
A8: =IF($B8="","",ROW()-2) | B8: Summer Lights in English Bay | C8: =IF($B8="","","Events & Festivals") | D8: Vancouver | E8: West End | F8: P2 | G8: Open | H8: Maddie | M8: vancouver.ca | N8: TBD | P8: Verified Web | Q8: Cold | S8: =IF(ISBLANK(R8),"",TODAY()-R8) | AA8: =IF(OR($Z8="",$Y8="",$Y8=0),"",$Z8/($Y8*24)) | AH8: No | AL8: Friday Jul 31 2026 fireworks at English Bay, BC Day long weekend. City replacement for Celebration of Light.
A9: =IF($B9="","",ROW()-2) | B9: Canada Dry Victoria Dragon Boat Festival | C9: =IF($B9="","","Events & Festivals") | D9: Victoria | E9: Inner Harbour | F9: P2 | G9: Open | H9: Maddie | M9: victoriadragonboatfestival.com | N9: TBD | P9: Verified Web | Q9: Cold | S9: =IF(ISBLANK(R9),"",TODAY()-R9) | AA9: =IF(OR($Z9="",$Y9="",$Y9=0),"",$Z9/($Y9*24)) | AH9: No | AL9: Saturday Jun 20 2026 at the Inner Harbour, more than 30 teams. Moved to June for 2026 only, back to August in 2027.
A10: =IF($B10="","",ROW()-2) | B10: Kelowna Wine Country Half Marathon | C10: =IF($B10="","","Events & Festivals") | D10: Kelowna | E10: Waterfront Park | F10: P2 | G10: Open | H10: Maddie | M10: kelownamarathon.ca | N10: 1,800 runners (cap) | O10: Event materials note registration normally limited to about 1,800 runners, confirm on site | P10: Verified Web | Q10: Cold | S10: =IF(ISBLANK(R10),"",TODAY()-R10) | AA10: =IF(OR($Z10="",$Y10="",$Y10=0),"",$Z10/($Y10*24)) | AH10: No | AL10: Saturday Jun 13 2026, finish at Waterfront Park with a post run festival.
A11: =IF($B11="","",ROW()-2) | C11: =IF($B11="","","Events & Festivals") | S11: =IF(ISBLANK(R11),"",TODAY()-R11) | AA11: =IF(OR($Z11="",$Y11="",$Y11=0),"",$Z11/($Y11*24))
A12: =IF($B12="","",ROW()-2) | C12: =IF($B12="","","Events & Festivals") | S12: =IF(ISBLANK(R12),"",TODAY()-R12) | AA12: =IF(OR($Z12="",$Y12="",$Y12=0),"",$Z12/($Y12*24))
A13: =IF($B13="","",ROW()-2) | C13: =IF($B13="","","Events & Festivals") | S13: =IF(ISBLANK(R13),"",TODAY()-R13) | AA13: =IF(OR($Z13="",$Y13="",$Y13=0),"",$Z13/($Y13*24))
A14: =IF($B14="","",ROW()-2) | C14: =IF($B14="","","Events & Festivals") | S14: =IF(ISBLANK(R14),"",TODAY()-R14) | AA14: =IF(OR($Z14="",$Y14="",$Y14=0),"",$Z14/($Y14*24))
A15: =IF($B15="","",ROW()-2) | C15: =IF($B15="","","Events & Festivals") | S15: =IF(ISBLANK(R15),"",TODAY()-R15) | AA15: =IF(OR($Z15="",$Y15="",$Y15=0),"",$Z15/($Y15*24))
A16: =IF($B16="","",ROW()-2) | C16: =IF($B16="","","Events & Festivals") | S16: =IF(ISBLANK(R16),"",TODAY()-R16) | AA16: =IF(OR($Z16="",$Y16="",$Y16=0),"",$Z16/($Y16*24))
A17: =IF($B17="","",ROW()-2) | C17: =IF($B17="","","Events & Festivals") | S17: =IF(ISBLANK(R17),"",TODAY()-R17) | AA17: =IF(OR($Z17="",$Y17="",$Y17=0),"",$Z17/($Y17*24))
A18: =IF($B18="","",ROW()-2) | C18: =IF($B18="","","Events & Festivals") | S18: =IF(ISBLANK(R18),"",TODAY()-R18) | AA18: =IF(OR($Z18="",$Y18="",$Y18=0),"",$Z18/($Y18*24))
A19: =IF($B19="","",ROW()-2) | C19: =IF($B19="","","Events & Festivals") | S19: =IF(ISBLANK(R19),"",TODAY()-R19) | AA19: =IF(OR($Z19="",$Y19="",$Y19=0),"",$Z19/($Y19*24))
A20: =IF($B20="","",ROW()-2) | C20: =IF($B20="","","Events & Festivals") | S20: =IF(ISBLANK(R20),"",TODAY()-R20) | AA20: =IF(OR($Z20="",$Y20="",$Y20=0),"",$Z20/($Y20*24))
A21: =IF($B21="","",ROW()-2) | C21: =IF($B21="","","Events & Festivals") | S21: =IF(ISBLANK(R21),"",TODAY()-R21) | AA21: =IF(OR($Z21="",$Y21="",$Y21=0),"",$Z21/($Y21*24))
A22: =IF($B22="","",ROW()-2) | C22: =IF($B22="","","Events & Festivals") | S22: =IF(ISBLANK(R22),"",TODAY()-R22) | AA22: =IF(OR($Z22="",$Y22="",$Y22=0),"",$Z22/($Y22*24))
... A32: =IF($B32="","",ROW()-2) | C32: =IF($B32="","","Events & Festivals") | S32: =IF(ISBLANK(R32),"",TODAY()-R32) | AA32: =IF(OR($Z32="",$Y32="",$Y32=0),"",$Z32/($Y32*24))

Sheet Sports Teams & Leagues
A1: Sports Teams & Leagues
A2: # | B2: Partner Name | C2: Partnership Type | D2: City | E2: Neighbourhood | F2: Priority | G2: Status | H2: Primary Owner | I2: Contact Name | J2: Role | K2: Contact Email | L2: Contact Phone | M2: Instagram or Website | N2: Audience Size | O2: Audience Source | P2: Source | Q2: Warm | R2: Last Contacted | S2: Days Since Activity | T2: Next Action | U2: Next Action Date | V2: Activation Type | W2: Activation Date | X2: Cases Committed | Y2: Cases Delivered | Z2: Cost ($) | AA2: Cost Per Can | AB2: Contra Value ($) | AC2: Deliverables Promised | AD2: Deliverables Received | AE2: What They Want | AF2: Risks | AG2: Nearby Retail Doors | AH2: In BC Tracker? | AI2: Raspberry 4338 | AJ2: Lemon Lime 4336 | AK2: Pineapple Passion Fruit 4340 | AL2: Notes
A3: =IF($B3="","",ROW()-2) | B3: Urban Rec Vancouver | C3: =IF($B3="","","Sports Teams & Leagues") | D3: Vancouver | E3: Mount Pleasant | F3: P1 | G3: Open | H3: Maddie | M3: @urbanrec | N3: 56,000 members (self stated) | O3: Urban Rec Vancouver website states over 56,000 members, brand self stated figure | P3: Verified Web | Q3: Cold | S3: =IF(ISBLANK(R3),"",TODAY()-R3) | AA3: =IF(OR($Z3="",$Y3="",$Y3=0),"",$Z3/($Y3*24)) | AH3: No | AL3: Largest sport and social club in Western Canada. Leagues across Vancouver, Richmond and Burnaby.
A4: =IF($B4="","",ROW()-2) | B4: Vancouver Dodgeball League | C4: =IF($B4="","","Sports Teams & Leagues") | D4: Vancouver | E4: Multiple | F4: P2 | G4: Open | H4: Maddie | M4: @vdldodgeball | N4: 2,000+ players, 260+ teams | O4: VDL sources describe over 260 teams and 2,000 plus players at peak | P4: Verified Web | Q4: Cold | S4: =IF(ISBLANK(R4),"",TODAY()-R4) | AA4: =IF(OR($Z4="",$Y4="",$Y4=0),"",$Z4/($Y4*24)) | AH4: No | AL4: Non profit dodgeball league playing in school and community gyms.
A5: =IF($B5="","",ROW()-2) | B5: Vancouver Pickleball Association | C5: =IF($B5="","","Sports Teams & Leagues") | D5: Vancouver | E5: Multiple | F5: P2 | G5: Open | H5: Maddie | M5: @vancouverpickleballassociation | N5: TBD | P5: Verified Web | Q5: Cold | S5: =IF(ISBLANK(R5),"",TODAY()-R5) | AA5: =IF(OR($Z5="",$Y5="",$Y5=0),"",$Z5/($Y5*24)) | AH5: No | AL5: Box league runs Apr to Sep 2026 across community centres and outdoor courts.
A6: =IF($B6="","",ROW()-2) | B6: False Creek Racing Canoe Club | C6: =IF($B6="","","Sports Teams & Leagues") | D6: Vancouver | E6: Granville Island | F6: P2 | G6: Open | H6: Maddie | M6: @falsecreekcanoeclub | N6: TBD | P6: Verified Web | Q6: Cold | S6: =IF(ISBLANK(R6),"",TODAY()-R6) | AA6: =IF(OR($Z6="",$Y6="",$Y6=0),"",$Z6/($Y6*24)) | AH6: No | AL6: Dragon boat, outrigger and sprint paddling club based on Granville Island.
A7: =IF($B7="","",ROW()-2) | B7: Victoria Sport and Social Club | C7: =IF($B7="","","Sports Teams & Leagues") | D7: Victoria | E7: Multiple | F7: P2 | G7: Open | H7: Maddie | M7: @vicsportnsocial | N7: TBD | P7: Verified Web | Q7: Cold | S7: =IF(ISBLANK(R7),"",TODAY()-R7) | AA7: =IF(OR($Z7="",$Y7="",$Y7=0),"",$Z7/($Y7*24)) | AH7: No | AL7: Mixed adult leagues, 9 plus sports running for summer 2026.
A8: =IF($B8="","",ROW()-2) | B8: Pickleball Kelowna Club | C8: =IF($B8="","","Sports Teams & Leagues") | D8: Kelowna | E8: Parkinson Rec Centre | F8: P2 | G8: Open | H8: Maddie | M8: @pickleballkelownaclub | N8: 700 members | O8: Instagram @pickleballkelownaclub states the club is home to 700 members | P8: Verified Web | Q8: Cold | S8: =IF(ISBLANK(R8),"",TODAY()-R8) | AA8: =IF(OR($Z8="",$Y8="",$Y8=0),"",$Z8/($Y8*24)) | AH8: No | AL8: Plays on 12 fenced outdoor courts, May to Sep season, hosts the Kelowna Open.
A9: =IF($B9="","",ROW()-2) | C9: =IF($B9="","","Sports Teams & Leagues") | S9: =IF(ISBLANK(R9),"",TODAY()-R9) | AA9: =IF(OR($Z9="",$Y9="",$Y9=0),"",$Z9/($Y9*24))
A10: =IF($B10="","",ROW()-2) | C10: =IF($B10="","","Sports Teams & Leagues") | S10: =IF(ISBLANK(R10),"",TODAY()-R10) | AA10: =IF(OR($Z10="",$Y10="",$Y10=0),"",$Z10/($Y10*24))
A11: =IF($B11="","",ROW()-2) | C11: =IF($B11="","","Sports Teams & Leagues") | S11: =IF(ISBLANK(R11),"",TODAY()-R11) | AA11: =IF(OR($Z11="",$Y11="",$Y11=0),"",$Z11/($Y11*24))
A12: =IF($B12="","",ROW()-2) | C12: =IF($B12="","","Sports Teams & Leagues") | S12: =IF(ISBLANK(R12),"",TODAY()-R12) | AA12: =IF(OR($Z12="",$Y12="",$Y12=0),"",$Z12/($Y12*24))
A13: =IF($B13="","",ROW()-2) | C13: =IF($B13="","","Sports Teams & Leagues") | S13: =IF(ISBLANK(R13),"",TODAY()-R13) | AA13: =IF(OR($Z13="",$Y13="",$Y13=0),"",$Z13/($Y13*24))
A14: =IF($B14="","",ROW()-2) | C14: =IF($B14="","","Sports Teams & Leagues") | S14: =IF(ISBLANK(R14),"",TODAY()-R14) | AA14: =IF(OR($Z14="",$Y14="",$Y14=0),"",$Z14/($Y14*24))
A15: =IF($B15="","",ROW()-2) | C15: =IF($B15="","","Sports Teams & Leagues") | S15: =IF(ISBLANK(R15),"",TODAY()-R15) | AA15: =IF(OR($Z15="",$Y15="",$Y15=0),"",$Z15/($Y15*24))
A16: =IF($B16="","",ROW()-2) | C16: =IF($B16="","","Sports Teams & Leagues") | S16: =IF(ISBLANK(R16),"",TODAY()-R16) | AA16: =IF(OR($Z16="",$Y16="",$Y16=0),"",$Z16/($Y16*24))
A17: =IF($B17="","",ROW()-2) | C17: =IF($B17="","","Sports Teams & Leagues") | S17: =IF(ISBLANK(R17),"",TODAY()-R17) | AA17: =IF(OR($Z17="",$Y17="",$Y17=0),"",$Z17/($Y17*24))
A18: =IF($B18="","",ROW()-2) | C18: =IF($B18="","","Sports Teams & Leagues") | S18: =IF(ISBLANK(R18),"",TODAY()-R18) | AA18: =IF(OR($Z18="",$Y18="",$Y18=0),"",$Z18/($Y18*24))
A19: =IF($B19="","",ROW()-2) | C19: =IF($B19="","","Sports Teams & Leagues") | S19: =IF(ISBLANK(R19),"",TODAY()-R19) | AA19: =IF(OR($Z19="",$Y19="",$Y19=0),"",$Z19/($Y19*24))
A20: =IF($B20="","",ROW()-2) | C20: =IF($B20="","","Sports Teams & Leagues") | S20: =IF(ISBLANK(R20),"",TODAY()-R20) | AA20: =IF(OR($Z20="",$Y20="",$Y20=0),"",$Z20/($Y20*24))
... A32: =IF($B32="","",ROW()-2) | C32: =IF($B32="","","Sports Teams & Leagues") | S32: =IF(ISBLANK(R32),"",TODAY()-R32) | AA32: =IF(OR($Z32="",$Y32="",$Y32=0),"",$Z32/($Y32*24))

Sheet Campus & Student Groups
A1: Campus & Student Groups
A2: # | B2: Partner Name | C2: Partnership Type | D2: City | E2: Neighbourhood | F2: Priority | G2: Status | H2: Primary Owner | I2: Contact Name | J2: Role | K2: Contact Email | L2: Contact Phone | M2: Instagram or Website | N2: Audience Size | O2: Audience Source | P2: Source | Q2: Warm | R2: Last Contacted | S2: Days Since Activity | T2: Next Action | U2: Next Action Date | V2: Activation Type | W2: Activation Date | X2: Cases Committed | Y2: Cases Delivered | Z2: Cost ($) | AA2: Cost Per Can | AB2: Contra Value ($) | AC2: Deliverables Promised | AD2: Deliverables Received | AE2: What They Want | AF2: Risks | AG2: Nearby Retail Doors | AH2: In BC Tracker? | AI2: Raspberry 4338 | AJ2: Lemon Lime 4336 | AK2: Pineapple Passion Fruit 4340 | AL2: Notes
A3: =IF($B3="","",ROW()-2) | B3: UBC Thunderbirds Athletics | C3: =IF($B3="","","Campus & Student Groups") | D3: Vancouver | E3: UBC | F3: P1 | G3: Open | H3: Maddie | M3: @ubctbirds | N3: 33,000 IG | O3: Instagram @ubctbirds follower count, web search 2026. 26 varsity teams per gothunderbirds.ca | P3: Verified Web | Q3: Cold | S3: =IF(ISBLANK(R3),"",TODAY()-R3) | AA3: =IF(OR($Z3="",$Y3="",$Y3=0),"",$Z3/($Y3*24)) | AH3: No | AL3: 26 varsity teams across 15 sports at the Point Grey campus.
A4: =IF($B4="","",ROW()-2) | B4: AMS of UBC | C4: =IF($B4="","","Campus & Student Groups") | D4: Vancouver | E4: UBC | F4: P1 | G4: Open | H4: Maddie | M4: ams.ubc.ca | N4: 60,000 students | O4: AMS represents more than 60,000 students per ams.ubc.ca, operates 200 plus clubs | P4: Verified Web | Q4: Cold | S4: =IF(ISBLANK(R4),"",TODAY()-R4) | AA4: =IF(OR($Z4="",$Y4="",$Y4=0),"",$Z4/($Y4*24)) | AH4: No | AL4: Student society running the Nest student union building and 200 plus clubs.
A5: =IF($B5="","",ROW()-2) | B5: SFU Recreation | C5: =IF($B5="","","Campus & Student Groups") | D5: Burnaby | E5: Burnaby Mountain | F5: P2 | G5: Open | H5: Maddie | M5: @sfurecreation | N5: 4,500 IG | O5: Instagram @sfurecreation follower count, web search 2026 | P5: Verified Web | Q5: Cold | S5: =IF(ISBLANK(R5),"",TODAY()-R5) | AA5: =IF(OR($Z5="",$Y5="",$Y5=0),"",$Z5/($Y5*24)) | AH5: No | AL5: Intramural leagues open to students, staff and faculty.
A6: =IF($B6="","",ROW()-2) | B6: UVic Vikes Recreation | C6: =IF($B6="","","Campus & Student Groups") | D6: Victoria | E6: UVic | F6: P2 | G6: Open | H6: Maddie | M6: vikesrec.ca | N6: 22,000 students | O6: UVic enrolment over 22,000 students per uvic.ca, Vikes Recreation open to all students | P6: Verified Web | Q6: Cold | S6: =IF(ISBLANK(R6),"",TODAY()-R6) | AA6: =IF(OR($Z6="",$Y6="",$Y6=0),"",$Z6/($Y6*24)) | AH6: No | AL6: Campus recreation programs based at the CARSA centre.
A7: =IF($B7="","",ROW()-2) | B7: Students' Union Okanagan of UBC | C7: =IF($B7="","","Campus & Student Groups") | D7: Kelowna | E7: UBC Okanagan | F7: P2 | G7: Open | H7: Maddie | M7: @suo_ubc | N7: 12,000 students | O7: SUO represents over 12,000 students per suo.ca | P7: Verified Web | Q7: Cold | S7: =IF(ISBLANK(R7),"",TODAY()-R7) | AA7: =IF(OR($Z7="",$Y7="",$Y7=0),"",$Z7/($Y7*24)) | AH7: No | AL7: Runs The Well student pub and The Green Bean cafe. New recreation facility broke ground May 2026.
A8: =IF($B8="","",ROW()-2) | B8: Camosun College Student Society | C8: =IF($B8="","","Campus & Student Groups") | D8: Victoria | E8: Lansdowne | F8: P3 | G8: Open | H8: Maddie | M8: camosunstudent.org | N8: 9,000+ students | O8: CCSS represents the 9,000 plus students of Camosun College per camosunstudent.org | P8: Verified Web | Q8: Cold | S8: =IF(ISBLANK(R8),"",TODAY()-R8) | AA8: =IF(OR($Z8="",$Y8="",$Y8=0),"",$Z8/($Y8*24)) | AH8: No | AL8: Student society across the Lansdowne and Interurban campuses.
A9: =IF($B9="","",ROW()-2) | C9: =IF($B9="","","Campus & Student Groups") | S9: =IF(ISBLANK(R9),"",TODAY()-R9) | AA9: =IF(OR($Z9="",$Y9="",$Y9=0),"",$Z9/($Y9*24))
A10: =IF($B10="","",ROW()-2) | C10: =IF($B10="","","Campus & Student Groups") | S10: =IF(ISBLANK(R10),"",TODAY()-R10) | AA10: =IF(OR($Z10="",$Y10="",$Y10=0),"",$Z10/($Y10*24))
A11: =IF($B11="","",ROW()-2) | C11: =IF($B11="","","Campus & Student Groups") | S11: =IF(ISBLANK(R11),"",TODAY()-R11) | AA11: =IF(OR($Z11="",$Y11="",$Y11=0),"",$Z11/($Y11*24))
A12: =IF($B12="","",ROW()-2) | C12: =IF($B12="","","Campus & Student Groups") | S12: =IF(ISBLANK(R12),"",TODAY()-R12) | AA12: =IF(OR($Z12="",$Y12="",$Y12=0),"",$Z12/($Y12*24))
A13: =IF($B13="","",ROW()-2) | C13: =IF($B13="","","Campus & Student Groups") | S13: =IF(ISBLANK(R13),"",TODAY()-R13) | AA13: =IF(OR($Z13="",$Y13="",$Y13=0),"",$Z13/($Y13*24))
A14: =IF($B14="","",ROW()-2) | C14: =IF($B14="","","Campus & Student Groups") | S14: =IF(ISBLANK(R14),"",TODAY()-R14) | AA14: =IF(OR($Z14="",$Y14="",$Y14=0),"",$Z14/($Y14*24))
A15: =IF($B15="","",ROW()-2) | C15: =IF($B15="","","Campus & Student Groups") | S15: =IF(ISBLANK(R15),"",TODAY()-R15) | AA15: =IF(OR($Z15="",$Y15="",$Y15=0),"",$Z15/($Y15*24))
A16: =IF($B16="","",ROW()-2) | C16: =IF($B16="","","Campus & Student Groups") | S16: =IF(ISBLANK(R16),"",TODAY()-R16) | AA16: =IF(OR($Z16="",$Y16="",$Y16=0),"",$Z16/($Y16*24))
A17: =IF($B17="","",ROW()-2) | C17: =IF($B17="","","Campus & Student Groups") | S17: =IF(ISBLANK(R17),"",TODAY()-R17) | AA17: =IF(OR($Z17="",$Y17="",$Y17=0),"",$Z17/($Y17*24))
A18: =IF($B18="","",ROW()-2) | C18: =IF($B18="","","Campus & Student Groups") | S18: =IF(ISBLANK(R18),"",TODAY()-R18) | AA18: =IF(OR($Z18="",$Y18="",$Y18=0),"",$Z18/($Y18*24))
A19: =IF($B19="","",ROW()-2) | C19: =IF($B19="","","Campus & Student Groups") | S19: =IF(ISBLANK(R19),"",TODAY()-R19) | AA19: =IF(OR($Z19="",$Y19="",$Y19=0),"",$Z19/($Y19*24))
A20: =IF($B20="","",ROW()-2) | C20: =IF($B20="","","Campus & Student Groups") | S20: =IF(ISBLANK(R20),"",TODAY()-R20) | AA20: =IF(OR($Z20="",$Y20="",$Y20=0),"",$Z20/($Y20*24))
... A32: =IF($B32="","",ROW()-2) | C32: =IF($B32="","","Campus & Student Groups") | S32: =IF(ISBLANK(R32),"",TODAY()-R32) | AA32: =IF(OR($Z32="",$Y32="",$Y32=0),"",$Z32/($Y32*24))

Sheet Wellness & Recovery
A1: Wellness & Recovery
A2: # | B2: Partner Name | C2: Partnership Type | D2: City | E2: Neighbourhood | F2: Priority | G2: Status | H2: Primary Owner | I2: Contact Name | J2: Role | K2: Contact Email | L2: Contact Phone | M2: Instagram or Website | N2: Audience Size | O2: Audience Source | P2: Source | Q2: Warm | R2: Last Contacted | S2: Days Since Activity | T2: Next Action | U2: Next Action Date | V2: Activation Type | W2: Activation Date | X2: Cases Committed | Y2: Cases Delivered | Z2: Cost ($) | AA2: Cost Per Can | AB2: Contra Value ($) | AC2: Deliverables Promised | AD2: Deliverables Received | AE2: What They Want | AF2: Risks | AG2: Nearby Retail Doors | AH2: In BC Tracker? | AI2: Raspberry 4338 | AJ2: Lemon Lime 4336 | AK2: Pineapple Passion Fruit 4340 | AL2: Notes
A3: =IF($B3="","",ROW()-2) | B3: Tevah Wellness | C3: =IF($B3="","","Wellness & Recovery") | D3: Vancouver | E3: Yaletown | F3: P1 | G3: Open | H3: Maddie | N3: TBD | P3: Verified Web | Q3: Cold | S3: =IF(ISBLANK(R3),"",TODAY()-R3) | AA3: =IF(OR($Z3="",$Y3="",$Y3=0),"",$Z3/($Y3*24)) | AH3: Yes | AL3: Imported from the BC Tracker Community tab so it is tracked once. Sauna and recovery. Address 955 Pacific Blvd.
A4: =IF($B4="","",ROW()-2) | B4: HAVN Saunas | C4: =IF($B4="","","Wellness & Recovery") | D4: Victoria | E4: Inner Harbour | F4: P1 | G4: Open | H4: Maddie | M4: @havn.saunas | N4: 34,000 IG | O4: Instagram @havn.saunas follower count, web search 2026 | P4: Verified Web | Q4: Cold | S4: =IF(ISBLANK(R4),"",TODAY()-R4) | AA4: =IF(OR($Z4="",$Y4="",$Y4=0),"",$Z4/($Y4*24)) | AH4: No | AL4: Floating sauna barge on the Inner Harbour with cold plunge circuits.
A5: =IF($B5="","",ROW()-2) | B5: Kolm Kontrast Nordic Spa | C5: =IF($B5="","","Wellness & Recovery") | D5: Vancouver | E5: Cambie Village | F5: P1 | G5: Open | H5: Maddie | M5: @kolmkontrast | N5: 12,000 IG | O5: Instagram @kolmkontrast follower count, web search 2026 | P5: Verified Web | Q5: Cold | S5: =IF(ISBLANK(R5),"",TODAY()-R5) | AA5: =IF(OR($Z5="",$Y5="",$Y5=0),"",$Z5/($Y5*24)) | AH5: No | AL5: Nordic spa at 525 W 8th Ave with heat and cold cycles.
A6: =IF($B6="","",ROW()-2) | B6: RITUAL Nordic Spa | C6: =IF($B6="","","Wellness & Recovery") | D6: Victoria | E6: Harris Green | F6: P2 | G6: Open | H6: Maddie | M6: @ritualnordicspa | N6: 9,400 IG | O6: Instagram @ritualnordicspa follower count, web search 2026 | P6: Verified Web | Q6: Cold | S6: =IF(ISBLANK(R6),"",TODAY()-R6) | AA6: =IF(OR($Z6="",$Y6="",$Y6=0),"",$Z6/($Y6*24)) | AH6: No | AL6: Nordic spa with an onsite cafe and salt lounge.
A7: =IF($B7="","",ROW()-2) | B7: Float House Vancouver | C7: =IF($B7="","","Wellness & Recovery") | D7: Vancouver | E7: Gastown | F7: P2 | G7: Open | H7: Maddie | M7: @float_house | N7: 9,000 IG | O7: Instagram @float_house follower count, web search 2026 | P7: Verified Web | Q7: Cold | S7: =IF(ISBLANK(R7),"",TODAY()-R7) | AA7: =IF(OR($Z7="",$Y7="",$Y7=0),"",$Z7/($Y7*24)) | AH7: No | AL7: Float and cold plunge studio at 70 W Cordova St.
A8: =IF($B8="","",ROW()-2) | B8: Regen Recovery | C8: =IF($B8="","","Wellness & Recovery") | D8: Vancouver | E8: Downtown | F8: P2 | G8: Open | H8: Maddie | M8: @regenrecovery | N8: 3,900 IG | O8: Instagram @regenrecovery follower count, web search 2026 | P8: Verified Web | Q8: Cold | S8: =IF(ISBLANK(R8),"",TODAY()-R8) | AA8: =IF(OR($Z8="",$Y8="",$Y8=0),"",$Z8/($Y8*24)) | AH8: No | AL8: Recovery lounge with sauna, cold plunge and IV services.
A9: =IF($B9="","",ROW()-2) | B9: BioShack | C9: =IF($B9="","","Wellness & Recovery") | D9: Kelowna | E9: Kelowna | F9: P3 | G9: Open | H9: Maddie | M9: @bioshack | N9: TBD | P9: Verified Web | Q9: Cold | S9: =IF(ISBLANK(R9),"",TODAY()-R9) | AA9: =IF(OR($Z9="",$Y9="",$Y9=0),"",$Z9/($Y9*24)) | AH9: No | AL9: Self led contrast therapy suite located at Sweat Studios.
A10: =IF($B10="","",ROW()-2) | C10: =IF($B10="","","Wellness & Recovery") | S10: =IF(ISBLANK(R10),"",TODAY()-R10) | AA10: =IF(OR($Z10="",$Y10="",$Y10=0),"",$Z10/($Y10*24))
A11: =IF($B11="","",ROW()-2) | C11: =IF($B11="","","Wellness & Recovery") | S11: =IF(ISBLANK(R11),"",TODAY()-R11) | AA11: =IF(OR($Z11="",$Y11="",$Y11=0),"",$Z11/($Y11*24))
A12: =IF($B12="","",ROW()-2) | C12: =IF($B12="","","Wellness & Recovery") | S12: =IF(ISBLANK(R12),"",TODAY()-R12) | AA12: =IF(OR($Z12="",$Y12="",$Y12=0),"",$Z12/($Y12*24))
A13: =IF($B13="","",ROW()-2) | C13: =IF($B13="","","Wellness & Recovery") | S13: =IF(ISBLANK(R13),"",TODAY()-R13) | AA13: =IF(OR($Z13="",$Y13="",$Y13=0),"",$Z13/($Y13*24))
A14: =IF($B14="","",ROW()-2) | C14: =IF($B14="","","Wellness & Recovery") | S14: =IF(ISBLANK(R14),"",TODAY()-R14) | AA14: =IF(OR($Z14="",$Y14="",$Y14=0),"",$Z14/($Y14*24))
A15: =IF($B15="","",ROW()-2) | C15: =IF($B15="","","Wellness & Recovery") | S15: =IF(ISBLANK(R15),"",TODAY()-R15) | AA15: =IF(OR($Z15="",$Y15="",$Y15=0),"",$Z15/($Y15*24))
A16: =IF($B16="","",ROW()-2) | C16: =IF($B16="","","Wellness & Recovery") | S16: =IF(ISBLANK(R16),"",TODAY()-R16) | AA16: =IF(OR($Z16="",$Y16="",$Y16=0),"",$Z16/($Y16*24))
A17: =IF($B17="","",ROW()-2) | C17: =IF($B17="","","Wellness & Recovery") | S17: =IF(ISBLANK(R17),"",TODAY()-R17) | AA17: =IF(OR($Z17="",$Y17="",$Y17=0),"",$Z17/($Y17*24))
A18: =IF($B18="","",ROW()-2) | C18: =IF($B18="","","Wellness & Recovery") | S18: =IF(ISBLANK(R18),"",TODAY()-R18) | AA18: =IF(OR($Z18="",$Y18="",$Y18=0),"",$Z18/($Y18*24))
A19: =IF($B19="","",ROW()-2) | C19: =IF($B19="","","Wellness & Recovery") | S19: =IF(ISBLANK(R19),"",TODAY()-R19) | AA19: =IF(OR($Z19="",$Y19="",$Y19=0),"",$Z19/($Y19*24))
A20: =IF($B20="","",ROW()-2) | C20: =IF($B20="","","Wellness & Recovery") | S20: =IF(ISBLANK(R20),"",TODAY()-R20) | AA20: =IF(OR($Z20="",$Y20="",$Y20=0),"",$Z20/($Y20*24))
A21: =IF($B21="","",ROW()-2) | C21: =IF($B21="","","Wellness & Recovery") | S21: =IF(ISBLANK(R21),"",TODAY()-R21) | AA21: =IF(OR($Z21="",$Y21="",$Y21=0),"",$Z21/($Y21*24))
... A32: =IF($B32="","",ROW()-2) | C32: =IF($B32="","","Wellness & Recovery") | S32: =IF(ISBLANK(R32),"",TODAY()-R32) | AA32: =IF(OR($Z32="",$Y32="",$Y32=0),"",$Z32/($Y32*24))

Sheet Ambassadors & Creators
A1: Ambassadors & Creators
A2: # | B2: Partner Name | C2: Partnership Type | D2: City | E2: Neighbourhood | F2: Priority | G2: Status | H2: Primary Owner | I2: Contact Name | J2: Role | K2: Contact Email | L2: Contact Phone | M2: Instagram or Website | N2: Audience Size | O2: Audience Source | P2: Source | Q2: Warm | R2: Last Contacted | S2: Days Since Activity | T2: Next Action | U2: Next Action Date | V2: Activation Type | W2: Activation Date | X2: Cases Committed | Y2: Cases Delivered | Z2: Cost ($) | AA2: Cost Per Can | AB2: Contra Value ($) | AC2: Deliverables Promised | AD2: Deliverables Received | AE2: What They Want | AF2: Risks | AG2: Nearby Retail Doors | AH2: In BC Tracker? | AI2: Raspberry 4338 | AJ2: Lemon Lime 4336 | AK2: Pineapple Passion Fruit 4340 | AL2: Notes
A3: =IF($B3="","",ROW()-2) | B3: Angela Liguori | C3: =IF($B3="","","Ambassadors & Creators") | D3: Vancouver | F3: P1 | G3: Open | H3: Maddie | M3: @angelaliggs | N3: 908,000 IG | O3: Instagram @angelaliggs follower count, web search 2026 | P3: Verified Web | Q3: Cold | S3: =IF(ISBLANK(R3),"",TODAY()-R3) | AA3: =IF(OR($Z3="",$Y3="",$Y3=0),"",$Z3/($Y3*24)) | AH3: No | AL3: Outdoor and hiking creator covering BC trails.
A4: =IF($B4="","",ROW()-2) | B4: Bailey Campbell | C4: =IF($B4="","","Ambassadors & Creators") | D4: Kelowna | F4: P1 | G4: Open | H4: Maddie | M4: @basicswithbails | N4: 641,000 IG | O4: Instagram @basicswithbails follower count, web search 2026. A tracker listed 394,700, reverify | P4: Verified Web | Q4: Cold | S4: =IF(ISBLANK(R4),"",TODAY()-R4) | AA4: =IF(OR($Z4="",$Y4="",$Y4=0),"",$Z4/($Y4*24)) | AH4: No | AL4: Kelowna Foodie. Recipe and lifestyle content.
A5: =IF($B5="","",ROW()-2) | B5: Twin Coast | C5: =IF($B5="","","Ambassadors & Creators") | D5: Vancouver | F5: P1 | G5: Open | H5: Maddie | M5: @twincoast | N5: 537,000 IG | O5: Instagram @twincoast follower count, web search 2026. Also large on TikTok and YouTube | P5: Verified Web | Q5: Cold | S5: =IF(ISBLANK(R5),"",TODAY()-R5) | AA5: =IF(OR($Z5="",$Y5="",$Y5=0),"",$Z5/($Y5*24)) | AH5: No | AL5: Twin sisters, plant based recipe creators with a cookbook brand.
A6: =IF($B6="","",ROW()-2) | B6: Vancouver Dietitians | C6: =IF($B6="","","Ambassadors & Creators") | D6: Vancouver | E6: South Granville | F6: P2 | G6: Open | H6: Maddie | M6: @vancouverdietitians | N6: 64,000 IG | O6: Instagram @vancouverdietitians follower count, web search 2026 | P6: Verified Web | Q6: Cold | S6: =IF(ISBLANK(R6),"",TODAY()-R6) | AA6: =IF(OR($Z6="",$Y6="",$Y6=0),"",$Z6/($Y6*24)) | AH6: No | AL6: Registered dietitian duo with a South Granville clinic.
A7: =IF($B7="","",ROW()-2) | B7: Cam Lee | C7: =IF($B7="","","Ambassadors & Creators") | D7: Vancouver | F7: P2 | G7: Open | H7: Maddie | M7: @camleeyoga | N7: 47,000 IG | O7: Instagram @camleeyoga follower count, web search 2026 | P7: Verified Web | Q7: Cold | S7: =IF(ISBLANK(R7),"",TODAY()-R7) | AA7: =IF(OR($Z7="",$Y7="",$Y7=0),"",$Z7/($Y7*24)) | AH7: No | AL7: Yoga and wellness creator.
A8: =IF($B8="","",ROW()-2) | B8: Caroline Doucet | C8: =IF($B8="","","Ambassadors & Creators") | D8: Vancouver | F8: P2 | G8: Open | H8: Maddie | M8: @nourishedbycaroline | N8: 38,000 IG | O8: Instagram @nourishedbycaroline follower count, web search 2026 | P8: Verified Web | Q8: Cold | S8: =IF(ISBLANK(R8),"",TODAY()-R8) | AA8: =IF(OR($Z8="",$Y8="",$Y8=0),"",$Z8/($Y8*24)) | AH8: No | AL8: Registered dietitian, plant based recipes, non diet approach.
A9: =IF($B9="","",ROW()-2) | B9: Trudy Leung | C9: =IF($B9="","","Ambassadors & Creators") | D9: Vancouver | F9: P2 | G9: Open | H9: Maddie | M9: @missvancityfoodie | N9: 37,000 IG | O9: Instagram @missvancityfoodie follower count, web search 2026 | P9: Verified Web | Q9: Cold | S9: =IF(ISBLANK(R9),"",TODAY()-R9) | AA9: =IF(OR($Z9="",$Y9="",$Y9=0),"",$Z9/($Y9*24)) | AH9: No | AL9: Miss Vancity Foodie. Local food and lifestyle content.
A10: =IF($B10="","",ROW()-2) | B10: Hilary Ann Yang | C10: =IF($B10="","","Ambassadors & Creators") | D10: Vancouver | F10: P2 | G10: Open | H10: Maddie | M10: @thehilaryann | N10: 31,000 IG | O10: Instagram @thehilaryann follower count, web search 2026 | P10: Verified Web | Q10: Cold | S10: =IF(ISBLANK(R10),"",TODAY()-R10) | AA10: =IF(OR($Z10="",$Y10="",$Y10=0),"",$Z10/($Y10*24)) | AH10: No | AL10: Trail running creator tied to Squamish, runs a women's trail running community.
A11: =IF($B11="","",ROW()-2) | C11: =IF($B11="","","Ambassadors & Creators") | S11: =IF(ISBLANK(R11),"",TODAY()-R11) | AA11: =IF(OR($Z11="",$Y11="",$Y11=0),"",$Z11/($Y11*24))
A12: =IF($B12="","",ROW()-2) | C12: =IF($B12="","","Ambassadors & Creators") | S12: =IF(ISBLANK(R12),"",TODAY()-R12) | AA12: =IF(OR($Z12="",$Y12="",$Y12=0),"",$Z12/($Y12*24))
A13: =IF($B13="","",ROW()-2) | C13: =IF($B13="","","Ambassadors & Creators") | S13: =IF(ISBLANK(R13),"",TODAY()-R13) | AA13: =IF(OR($Z13="",$Y13="",$Y13=0),"",$Z13/($Y13*24))
A14: =IF($B14="","",ROW()-2) | C14: =IF($B14="","","Ambassadors & Creators") | S14: =IF(ISBLANK(R14),"",TODAY()-R14) | AA14: =IF(OR($Z14="",$Y14="",$Y14=0),"",$Z14/($Y14*24))
A15: =IF($B15="","",ROW()-2) | C15: =IF($B15="","","Ambassadors & Creators") | S15: =IF(ISBLANK(R15),"",TODAY()-R15) | AA15: =IF(OR($Z15="",$Y15="",$Y15=0),"",$Z15/($Y15*24))
A16: =IF($B16="","",ROW()-2) | C16: =IF($B16="","","Ambassadors & Creators") | S16: =IF(ISBLANK(R16),"",TODAY()-R16) | AA16: =IF(OR($Z16="",$Y16="",$Y16=0),"",$Z16/($Y16*24))
A17: =IF($B17="","",ROW()-2) | C17: =IF($B17="","","Ambassadors & Creators") | S17: =IF(ISBLANK(R17),"",TODAY()-R17) | AA17: =IF(OR($Z17="",$Y17="",$Y17=0),"",$Z17/($Y17*24))
A18: =IF($B18="","",ROW()-2) | C18: =IF($B18="","","Ambassadors & Creators") | S18: =IF(ISBLANK(R18),"",TODAY()-R18) | AA18: =IF(OR($Z18="",$Y18="",$Y18=0),"",$Z18/($Y18*24))
A19: =IF($B19="","",ROW()-2) | C19: =IF($B19="","","Ambassadors & Creators") | S19: =IF(ISBLANK(R19),"",TODAY()-R19) | AA19: =IF(OR($Z19="",$Y19="",$Y19=0),"",$Z19/($Y19*24))
A20: =IF($B20="","",ROW()-2) | C20: =IF($B20="","","Ambassadors & Creators") | S20: =IF(ISBLANK(R20),"",TODAY()-R20) | AA20: =IF(OR($Z20="",$Y20="",$Y20=0),"",$Z20/($Y20*24))
A21: =IF($B21="","",ROW()-2) | C21: =IF($B21="","","Ambassadors & Creators") | S21: =IF(ISBLANK(R21),"",TODAY()-R21) | AA21: =IF(OR($Z21="",$Y21="",$Y21=0),"",$Z21/($Y21*24))
A22: =IF($B22="","",ROW()-2) | C22: =IF($B22="","","Ambassadors & Creators") | S22: =IF(ISBLANK(R22),"",TODAY()-R22) | AA22: =IF(OR($Z22="",$Y22="",$Y22=0),"",$Z22/($Y22*24))
... A32: =IF($B32="","",ROW()-2) | C32: =IF($B32="","","Ambassadors & Creators") | S32: =IF(ISBLANK(R32),"",TODAY()-R32) | AA32: =IF(OR($Z32="",$Y32="",$Y32=0),"",$Z32/($Y32*24))

Sheet Charity & Causes
A1: Charity & Causes
A2: # | B2: Partner Name | C2: Partnership Type | D2: City | E2: Neighbourhood | F2: Priority | G2: Status | H2: Primary Owner | I2: Contact Name | J2: Role | K2: Contact Email | L2: Contact Phone | M2: Instagram or Website | N2: Audience Size | O2: Audience Source | P2: Source | Q2: Warm | R2: Last Contacted | S2: Days Since Activity | T2: Next Action | U2: Next Action Date | V2: Activation Type | W2: Activation Date | X2: Cases Committed | Y2: Cases Delivered | Z2: Cost ($) | AA2: Cost Per Can | AB2: Contra Value ($) | AC2: Deliverables Promised | AD2: Deliverables Received | AE2: What They Want | AF2: Risks | AG2: Nearby Retail Doors | AH2: In BC Tracker? | AI2: Raspberry 4338 | AJ2: Lemon Lime 4336 | AK2: Pineapple Passion Fruit 4340 | AL2: Notes
A3: =IF($B3="","",ROW()-2) | B3: BC Children's Hospital Foundation | C3: =IF($B3="","","Charity & Causes") | D3: Vancouver | E3: Queen Elizabeth Park | F3: P1 | G3: Open | H3: Maddie | M3: fundraise.bcchf.ca | N3: 10,000 runners target 2026 | O3: runguides and BCCHF pages, 2026 aims to welcome more than 10,000 runners | P3: Verified Web | Q3: Cold | S3: =IF(ISBLANK(R3),"",TODAY()-R3) | AA3: =IF(OR($Z3="",$Y3="",$Y3=0),"",$Z3/($Y3*24)) | AH3: No | AL3: Hosts RBC Race for the Kids, Jun 8 2026 at Queen Elizabeth Park. 5k plus 2k fun run and a family carnival.
A4: =IF($B4="","",ROW()-2) | B4: Greater Vancouver Food Bank | C4: =IF($B4="","","Charity & Causes") | D4: Burnaby | E4: Swangard Stadium | F4: P2 | G4: Open | H4: Maddie | M4: foodbank.bc.ca | N4: TBD | P4: Verified Web | Q4: Cold | S4: =IF(ISBLANK(R4),"",TODAY()-R4) | AA4: =IF(OR($Z4="",$Y4="",$Y4=0),"",$Z4/($Y4*24)) | AH4: No | AL4: Hosts Foodstock, Jun 23 2026 at Swangard Stadium. A 19 plus outdoor music and food festival.
A5: =IF($B5="","",ROW()-2) | B5: Backpack Buddies | C5: =IF($B5="","","Charity & Causes") | D5: Vancouver | E5: Multiple | F5: P2 | G5: Open | H5: Maddie | M5: @backpackbuddiesbc | N5: 4,347 IG, 6,800 kids weekly | O5: Web search, 4,347 Instagram followers and over 6,800 kids reached weekly, 1.8 million meals in 2025 and 2026 | P5: Verified Web | Q5: Cold | S5: =IF(ISBLANK(R5),"",TODAY()-R5) | AA5: =IF(OR($Z5="",$Y5="",$Y5=0),"",$Z5/($Y5*24)) | AH5: No | AL5: Hosts the Birdies and Buddies golf tournament Jun 8 2026. School food programs across 83 BC communities.
A6: =IF($B6="","",ROW()-2) | B6: Victoria Hospice | C6: =IF($B6="","","Charity & Causes") | D6: Victoria | E6: Oak Bay | F6: P3 | G6: Open | H6: Maddie | M6: victoriahospice.org | N6: TBD | P6: Verified Web | Q6: Cold | S6: =IF(ISBLANK(R6),"",TODAY()-R6) | AA6: =IF(OR($Z6="",$Y6="",$Y6=0),"",$Z6/($Y6*24)) | AH6: No | AL6: Hosts Hike for Hospice, May 3 2026 at Willows Beach. A Goddess Run charity of choice.
A7: =IF($B7="","",ROW()-2) | B7: Wild One Run for Youth Mental Health | C7: =IF($B7="","","Charity & Causes") | D7: Kelowna | E7: Wilden | F7: P3 | G7: Open | H7: Maddie | M7: wildonerun.ca | N7: TBD | P7: Verified Web | Q7: Cold | S7: =IF(ISBLANK(R7),"",TODAY()-R7) | AA7: =IF(OR($Z7="",$Y7="",$Y7=0),"",$Z7/($Y7*24)) | AH7: No | AL7: Trail run and walk Oct 3 2026 on the Wilden trails. Proceeds to Foundry Kelowna.
A8: =IF($B8="","",ROW()-2) | C8: =IF($B8="","","Charity & Causes") | S8: =IF(ISBLANK(R8),"",TODAY()-R8) | AA8: =IF(OR($Z8="",$Y8="",$Y8=0),"",$Z8/($Y8*24))
A9: =IF($B9="","",ROW()-2) | C9: =IF($B9="","","Charity & Causes") | S9: =IF(ISBLANK(R9),"",TODAY()-R9) | AA9: =IF(OR($Z9="",$Y9="",$Y9=0),"",$Z9/($Y9*24))
A10: =IF($B10="","",ROW()-2) | C10: =IF($B10="","","Charity & Causes") | S10: =IF(ISBLANK(R10),"",TODAY()-R10) | AA10: =IF(OR($Z10="",$Y10="",$Y10=0),"",$Z10/($Y10*24))
A11: =IF($B11="","",ROW()-2) | C11: =IF($B11="","","Charity & Causes") | S11: =IF(ISBLANK(R11),"",TODAY()-R11) | AA11: =IF(OR($Z11="",$Y11="",$Y11=0),"",$Z11/($Y11*24))
A12: =IF($B12="","",ROW()-2) | C12: =IF($B12="","","Charity & Causes") | S12: =IF(ISBLANK(R12),"",TODAY()-R12) | AA12: =IF(OR($Z12="",$Y12="",$Y12=0),"",$Z12/($Y12*24))
A13: =IF($B13="","",ROW()-2) | C13: =IF($B13="","","Charity & Causes") | S13: =IF(ISBLANK(R13),"",TODAY()-R13) | AA13: =IF(OR($Z13="",$Y13="",$Y13=0),"",$Z13/($Y13*24))
A14: =IF($B14="","",ROW()-2) | C14: =IF($B14="","","Charity & Causes") | S14: =IF(ISBLANK(R14),"",TODAY()-R14) | AA14: =IF(OR($Z14="",$Y14="",$Y14=0),"",$Z14/($Y14*24))
A15: =IF($B15="","",ROW()-2) | C15: =IF($B15="","","Charity & Causes") | S15: =IF(ISBLANK(R15),"",TODAY()-R15) | AA15: =IF(OR($Z15="",$Y15="",$Y15=0),"",$Z15/($Y15*24))
A16: =IF($B16="","",ROW()-2) | C16: =IF($B16="","","Charity & Causes") | S16: =IF(ISBLANK(R16),"",TODAY()-R16) | AA16: =IF(OR($Z16="",$Y16="",$Y16=0),"",$Z16/($Y16*24))
A17: =IF($B17="","",ROW()-2) | C17: =IF($B17="","","Charity & Causes") | S17: =IF(ISBLANK(R17),"",TODAY()-R17) | AA17: =IF(OR($Z17="",$Y17="",$Y17=0),"",$Z17/($Y17*24))
A18: =IF($B18="","",ROW()-2) | C18: =IF($B18="","","Charity & Causes") | S18: =IF(ISBLANK(R18),"",TODAY()-R18) | AA18: =IF(OR($Z18="",$Y18="",$Y18=0),"",$Z18/($Y18*24))
A19: =IF($B19="","",ROW()-2) | C19: =IF($B19="","","Charity & Causes") | S19: =IF(ISBLANK(R19),"",TODAY()-R19) | AA19: =IF(OR($Z19="",$Y19="",$Y19=0),"",$Z19/($Y19*24))
... A32: =IF($B32="","",ROW()-2) | C32: =IF($B32="","","Charity & Causes") | S32: =IF(ISBLANK(R32),"",TODAY()-R32) | AA32: =IF(OR($Z32="",$Y32="",$Y32=0),"",$Z32/($Y32*24))

Sheet Suggested Events
A1: Suggested Events
A2: # | B2: Event | C2: City | D2: Venue or Neighbourhood | E2: Expected Window | F2: Audience Size | G2: Audience Source | H2: Source | I2: Priority | J2: Event Status | K2: Owner | L2: Why It Fits | M2: Next Step | N2: Notes
A3: =IF($B3="","",ROW()-2)
A4: =IF($B4="","",ROW()-2)
A5: =IF($B5="","",ROW()-2)
A6: =IF($B6="","",ROW()-2)
A7: =IF($B7="","",ROW()-2)
A8: =IF($B8="","",ROW()-2)
A9: =IF($B9="","",ROW()-2)
A10: =IF($B10="","",ROW()-2)
A11: =IF($B11="","",ROW()-2)
A12: =IF($B12="","",ROW()-2)
A13: =IF($B13="","",ROW()-2)
A14: =IF($B14="","",ROW()-2)
... A32: =IF($B32="","",ROW()-2)
A34: Idea parking lot for events farther down the line. It starts empty on purpose. When an idea is approved, add it as a partner row on the Events & Festivals tab and book the activation there. Nothing on this tab feeds the Master List or the Calendar.

Sheet Lookups
A1: Lookups : edit any column here to update the dropdowns across the file.
A2: Owner | B2: Partnership Type | C2: Priority | D2: Status | E2: Warm | F2: Source | G2: Activation Type | H2: What They Want | I2: Risks | J2: In BC Tracker | K2: SKU Status | L2: Role | M2: City | N2: Neighbourhood | O2: Event Status
A3: Maddie | B3: Run Clubs | C3: P1 | D3: Open | E3: Warm | F3: Verified Web | G3: Sampling | H3: Free Product | I3: Competitor Locked In | J3: Yes | K3: Requested | L3: Owner or Founder | M3: Vancouver | N3: Cambie Village | O3: Idea
B4: Gyms & Studios | C4: P2 | D4: Outreach Sent | E4: Cold | F4: Verified Phone | G4: Event Booth | H4: Sampling Budget | I4: Audience Mismatch | J4: No | K4: Sampled | L4: Director | M4: Burnaby | N4: Coal Harbour | O4: Scoping
B5: Events & Festivals | C5: P3 | D5: In Conversation | E5: Past Contact | F5: Verified In Person | G5: Sponsorship | H5: Sponsorship Fee | I5: High Fee | K5: Stocked | L5: Manager | M5: North Vancouver | N5: Commercial Drive | O5: Approved
B6: Sports Teams & Leagues | D6: Proposal Sent | E6: Unknown | F6: Pending | G6: Ambassador | H6: Social Posts From Us | I6: Slow To Respond | L6: General Manager | M6: West Vancouver | N6: Downtown | O6: Moved To Events Tab
B7: Campus & Student Groups | D7: Agreed | F7: Unverified | G7: Contra Product | H7: Co Branded Giveaway | I7: One Off Only | L7: Marketing Lead | M7: Richmond | N7: Dunbar | O7: Passed
B8: Wellness & Recovery | D8: Activated | G8: Co Branded Content | H8: Discount Code | I8: Logistics | L8: Community Manager | M8: Surrey | N8: East Vancouver
B9: Ambassadors & Creators | D9: Repeat Partner | G9: Hydration Station | H9: Long Term Deal | L9: Events Lead | M9: Langley | N9: Fairview
B10: Charity & Causes | D10: Lost | L10: Coach | M10: Coquitlam | N10: False Creek
D11: On Hold | L11: Run Lead | M11: New Westminster | N11: Gastown
L12: Studio Owner | M12: Victoria | N12: Granville Island
L13: Coordinator | M13: Kelowna | N13: Harris Green
L14: President | M14: Nanaimo | N14: Inner Harbour
L15: Board Member | M15: Online | N15: Jericho Beach
L16: Sponsorship Lead | N16: Kitsilano
L17: Athletic Director | N17: Lansdowne
L18: Creator | N18: Lower Lonsdale
N19: Lynn Valley
N20: Main Street
N21: Mount Pleasant
N22: Multiple
N23: North Burnaby
N24: Oak Bay
N25: Olympic Village
N26: Parkinson Rec Centre
N27: Queen Elizabeth Park
N28: South Granville
N29: Strathcona
N30: Swangard Stadium
... N40: Yaletown

Sheet Sales Team
A1: Sales Team
A2: Rep | B2: Email | C2: Cell | D2: Region | E2: Role on This File | F2: On Owner Dropdown?
A3: Maddie | B3: TBD verify | C3: TBD verify | D3: BC | E3: Community partnerships owner per Louis | F3: Yes
A5: Maddie runs this file. To add a rep later, add a row here and add the name to the Owner column on the Lookups tab so it appears on the Primary Owner menu.

Sheet Guide
A1: Guide · How to Use This Workbook
A2: A quick reference for the team. You only ever type into the type tabs or pick from a drop down menu.
A4: The boundary rule, BC Tracker or this file
A5: If it sells cans on a shelf it lives in the BC Tracker. If it samples, sponsors, or creates content it lives here.
A6: A partner can live in both files. Use the In BC Tracker column to flag any partner that also sits in the BC Tracker.
A7: This file is the sister to the BC Tracker. That file tracks retail doors. This file tracks community partnerships and activations.
A9: Nothing is proposed in advance
A10: Every partner row carries research facts only: who they are, where they are, audience and source.
A11: Activation Type, Activation Date, cases and budget all start blank. They only fill when the team books something real.
A12: The Activation Calendar starts empty for the same reason. Enter an Activation Date on a type tab and the row appears there on its own, soonest first.
A14: How to use it, 3 steps
A15: 1. Open your type tab at the bottom (the green tabs). Each tab is one partnership type.
... A26: The Source tag on every row
A27: Verified Web | B27: Confirmed on an official site or public Instagram in 2026.
A28: Pending | B28: The partner is real but a detail such as a follower count rests on a single source. Reverify before outreach.
A29: Unverified | B29: Heard of secondhand and not yet confirmed. Treat as a lead only.
A30: Audience numbers came from public sources. Anything that could not be verified is left blank or TBD and sits on the gap list.
A32: The three SKUs we track
A33: Raspberry is SKU 4338. Lemon Lime is SKU 4336. Pineapple Passion Fruit is SKU 4340. 355ml cans.
A34: Each SKU column takes blank, Requested, Sampled, or Stocked.
A36: Which tabs do what
A37: Dashboard | B37: Live executive overview. Totals, pipeline, list health, activations, budget, SKU status. Read only.
A38: Activation Calendar | B38: Every booked activation in date order, soonest first. Starts empty, fills itself. Read only.
A39: Master List | B39: Every partner from every type tab in one place. Read only, updates on its own.
A40: Type Summary | B40: Targets versus actuals per type with % to target. Targets are a draft for Louis to confirm. Read only.
A41: Budget | B41: Budget per type. You can fill Total Budget and Committed. Spent rolls up from the type tabs.
A42: Type tabs | B42: Where the team works. One tab per partnership type. Fully editable.
A43: Suggested Events | B43: Idea parking lot for future events. Starts empty. Approved ideas move onto the Events & Festivals tab.
A44: Lookups | B44: The lists behind every drop down. Add a value here and it appears in the menus.
A45: Sales Team | B45: Maddie owns this file. Add reps here and on the Lookups Owner column to grow the menu.
A47: What each column means
A48: Partner Name | B48: The run club, studio, event, team, group, space, creator or cause being pursued.
A49: Partnership Type | B49: Which of the eight types this partner belongs to. Fills itself when a name is entered.
A50: City and Neighbourhood | B50: Where the partner is based. Metro Vancouver first, then Victoria and Kelowna.
A51: Priority | B51: P1 chase first, P2, or P3.
A52: Status | B52: Where the partnership sits, from Open through Activated and Repeat Partner.
A53: Primary Owner | B53: The rep responsible. Maddie to start, drawn from the Sales Team tab.
A54: Audience Size and Source | B54: Approximate reach and exactly where that number came from.
A55: Source | B55: Verified Web, Pending or Unverified. How sure we are the row is real.
A56: Warm | B56: Warm, Cold, Past Contact or Unknown relationship.
A57: Last Contacted and Days Since Activity | B57: The most recent contact date and how many days have passed.
A58: Next Action and Date | B58: The next step and when it is due.
A59: Activation Type | B59: Sampling, Event Booth, Sponsorship, Ambassador, Contra Product, Co Branded Content or Hydration Station. Pick when you book.
... A67: Raspberry, Lemon Lime, Pineapple | B67: The sampling status of each flavour at that partner.
A69: Version
A70: 2026 06 v1 | B70: First build. 60 researched partners, live Dashboard, Activation Calendar, read only Master List, eight type tabs.
A71: 2026 06 v2 | B71: Cleared every proposed activation so the team books real ones. Maddie set as the single owner. Added the empty Suggested Events tab, List Health on the Dashboard and % to Target on the Type Summary.
A72: 2026 06 v3 | B72: Polish pass. Live Dashboard charts, clickable Instagram and website links, a region rollup, soft row banding for readability, a date stamp and clean print layout on every tab.
