Workbook

Sheet ReadMe
A1: Organika — Vietnam Landed Cost & Margin Model
A2: Companion to the Vietnam market entry package. Model only — replace every blue/yellow input with real figures before use.
A4: HOW TO USE
A5: 1 | B5: Open the Controls tab and set FX, duty scenario, freight, and the margin stack. Everything downstream recalculates.
A6: 2 | B6: On Controls, set the export FOB ratio, or replace it with real export prices. LandedCost derives FOB from real Canadian retail.
A7: 3 | B7: SKU Economics shows each line's shelf price vs the real Vietnamese comparable band and a Lead/Flag/Support call.
A8: 4 | B8: Channel Economics shows what the brand nets per unit across Shopee, TikTok Shop, Lazada and chain pharmacy.
A9: 5 | B9: Scenarios compares CPTPP 0% vs MFN 15% duty and tests FX sensitivity on the hero SKU.
A11: CELL LEGEND
A12: Blue text | B12: A hardcoded input or scenario lever you can change.
A13: Yellow fill | B13: A key assumption or a placeholder you must replace with a real figure.
A14: Black text | B14: A formula. Do not overwrite; it recalculates from inputs.
A15: Green text | B15: A link to another tab.
A17: SOURCES & CONFIDENCE
A18: FX | B18: USD/VND ~26,200, CAD/VND ~18,450 (OFX, exchange-rates.org, Oct 2026 — MEDIUM). Editable on Controls.
A19: Duty | B19: HS 2106.90.99: MFN 15%, CPTPP 0% with Form CPTPP C/O (VN customs brokers; Decrees 115/2022 & 13/2025, 2025-26 — MEDIUM-HIGH).
A20: VAT | B20: 8% through 31 Dec 2026, reverts to 10% in 2027 (Resolution 204/2025 — HIGH).
A21: Margins | B21: Distributor 35-60% on landed, retail 15-30%+ (Asia Pro 2026 — LOW-MEDIUM). Confirm with Kat Vietnam.
A22: Comparable bands | B22: Real Vietnamese shelf prices, primer Ch6.2/6.5 (2025-26 listings — MEDIUM).
A23: Platform take | B23: Shopee ~21%, TikTok ~18%, Lazada ~15% all-in (primer Ch6.4, 2025-26 — MEDIUM-HIGH).
A24: FOB costs | B24: Enter real COGS per SKU on LandedCost (column L) and your margin and trade targets on Controls (B22, B23): FOB then = COGS/(1-margin-trade). Until all are entered, FOB falls back to Canadian retail x 40% (LOW).
A25: Channel check | B25: Optional: enter your account's actual channel multiple (shelf / brand price) on Controls B26 and B27 to add a second lens on SKU_Economics. Blank by default.
A26: Confidentiality | B26: Template with public inputs only. Once you enter real COGS, margin targets or channel multiples, treat your copy as internal and never share it with a distributor.

Sheet Controls
A1: Controls — set once, drives every tab
A3: Foreign exchange
A4: CAD to VND | B4: 18450 | D4: input
A5: USD to VND | B5: 26200 | D5: input
A7: Import & tax
A8: Freight+insurance per unit (VND) | B8: 11800 | D8: input
A9: Duty rate (0=CPTPP, 0.15=MFN) | B9: 0 | D9: input
A10: VAT rate | B10: 0.08 | D10: input
A12: Margin stack
A13: Distributor markup on landed | B13: 0.45 | D13: input
A14: Retail margin (% of shelf) | B14: 0.3 | D14: input
A16: Registration amortization
A17: Reg + consultant per SKU (VND) | B17: 70000000 | D17: input
A18: Units per SKU per year (amort base) | B18: 20000 | D18: input
A20: Export pricing
A21: Export FOB as % of Canadian retail (fallback) | B21: 0.4 | D21: input
A22: Target contribution margin | D22: input
A23: Trade spend | D23: input
A25: Channel calibration
A26: Channel multiple, low (shelf / brand price) | D26: input
A27: Channel multiple, high | D27: input
A29: Once real COGS, margins or multiples are entered, treat your copy as internal. Never share it with a distributor.

Sheet LandedCost
A1: Landed cost per unit (CIF + duty), by SKU
A3: SKU | B3: Role | C3: Canadian retail (CAD) | D3: FOB (CAD) | E3: FOB (VND) | F3: Freight (VND) | G3: CIF (VND) | H3: Duty (VND) | I3: Landed (VND) | J3: Reg amort (VND) | K3: Landed+Reg (VND) | L3: COGS (CAD) — enter real | M3: Pack factor (1 = Canadian pack)
A4: Enhanced Collagen (250g) | B4: Credential flag | C4: 29.99 | D4: =IF(AND(N(L4)>0,N(Controls!$B$22)+N(Controls!$B$23)>0,N(Controls!$B$22)+N(Controls!$B$23)<1),L4/(1-Controls!$B$22-Controls!$B$23),C4*Controls!$B$21)*M4 -> 11.996 | E4: =D4*Controls!$B$4 -> 221326.2 | F4: =Controls!$B$8 -> 11800 | G4: =E4+F4 -> 233126.2 | H4: =G4*Controls!$B$9 -> 0 | I4: =G4+H4 -> 233126.2 | J4: =Controls!$B$17/Controls!$B$18 -> 3500 | K4: =I4+J4 -> 236626.2 | M4: 1
A5: Magnesium bisglycinate (120 caps) | B5: Lead SKU | C5: 27.99 | D5: =IF(AND(N(L5)>0,N(Controls!$B$22)+N(Controls!$B$23)>0,N(Controls!$B$22)+N(Controls!$B$23)<1),L5/(1-Controls!$B$22-Controls!$B$23),C5*Controls!$B$21)*M5 -> 11.196 | E5: =D5*Controls!$B$4 -> 206566.2 | F5: =Controls!$B$8 -> 11800 | G5: =E5+F5 -> 218366.2 | H5: =G5*Controls!$B$9 -> 0 | I5: =G5+H5 -> 218366.2 | J5: =Controls!$B$17/Controls!$B$18 -> 3500 | K5: =I5+J5 -> 221866.2 | M5: 1
A6: Greens: Digest & Renew (340g) | B6: Lead SKU | C6: 43.49 | D6: =IF(AND(N(L6)>0,N(Controls!$B$22)+N(Controls!$B$23)>0,N(Controls!$B$22)+N(Controls!$B$23)<1),L6/(1-Controls!$B$22-Controls!$B$23),C6*Controls!$B$21)*M6 -> 17.396 | E6: =D6*Controls!$B$4 -> 320956.2 | F6: =Controls!$B$8 -> 11800 | G6: =E6+F6 -> 332756.2 | H6: =G6*Controls!$B$9 -> 0 | I6: =G6+H6 -> 332756.2 | J6: =Controls!$B$17/Controls!$B$18 -> 3500 | K6: =I6+J6 -> 336256.2 | M6: 1
A7: Fibre: Whole Psyllium (454g) | B7: Range filler | C7: 25.99 | D7: =IF(AND(N(L7)>0,N(Controls!$B$22)+N(Controls!$B$23)>0,N(Controls!$B$22)+N(Controls!$B$23)<1),L7/(1-Controls!$B$22-Controls!$B$23),C7*Controls!$B$21)*M7 -> 10.396 | E7: =D7*Controls!$B$4 -> 191806.2 | F7: =Controls!$B$8 -> 11800 | G7: =E7+F7 -> 203606.2 | H7: =G7*Controls!$B$9 -> 0 | I7: =G7+H7 -> 203606.2 | J7: =Controls!$B$17/Controls!$B$18 -> 3500 | K7: =I7+J7 -> 207106.2 | M7: 1
A8: Probiotics | B8: Support | C8: 35 | D8: =IF(AND(N(L8)>0,N(Controls!$B$22)+N(Controls!$B$23)>0,N(Controls!$B$22)+N(Controls!$B$23)<1),L8/(1-Controls!$B$22-Controls!$B$23),C8*Controls!$B$21)*M8 -> 14 | E8: =D8*Controls!$B$4 -> 258300 | F8: =Controls!$B$8 -> 11800 | G8: =E8+F8 -> 270100 | H8: =G8*Controls!$B$9 -> 0 | I8: =G8+H8 -> 270100 | J8: =Controls!$B$17/Controls!$B$18 -> 3500 | K8: =I8+J8 -> 273600 | M8: 1
A9: Vitamin C / dailies | B9: Range filler | C9: 15 | D9: =IF(AND(N(L9)>0,N(Controls!$B$22)+N(Controls!$B$23)>0,N(Controls!$B$22)+N(Controls!$B$23)<1),L9/(1-Controls!$B$22-Controls!$B$23),C9*Controls!$B$21)*M9 -> 6 | E9: =D9*Controls!$B$4 -> 110700 | F9: =Controls!$B$8 -> 11800 | G9: =E9+F9 -> 122500 | H9: =G9*Controls!$B$9 -> 0 | I9: =G9+H9 -> 122500 | J9: =Controls!$B$17/Controls!$B$18 -> 3500 | K9: =I9+J9 -> 126000 | M9: 1
A11: FOB: COGS/(1-margin-trade) when real COGS (column L) and margin targets (Controls) are entered, else Canadian retail x fallback ratio. Canadian retail = real 2026 shelf prices (hover). Yellow = placeholder or required input.

Sheet SKU_Economics
A1: SKU economics — shelf price vs the real Vietnamese shelf
A2: Two lenses: the modeled margin stack (columns B to K) and an optional channel multiple you enter on Controls B26 and B27 (columns M to O). Trust the stricter one once real COGS and markups are in.
A3: SKU | B3: Landed+Reg (VND) | C3: To distributor (VND) | D3: Pre-VAT shelf (VND) | E3: Shelf (VND) | F3: Shelf (USD) | G3: Shelf (CAD) | H3: FOB multiple | I3: Comparable band low (VND) | J3: Comparable band high (VND) | K3: Position (model stack) | L3: Max FOB to hit band midpoint (CAD) | M3: Shelf at channel multiple low (VND) | N3: Shelf at channel multiple high (VND) | O3: Position at channel multiples
A4: Enhanced Collagen (250g) | B4: =LandedCost!K4 -> 236626.2 | C4: =B4*(1+Controls!$B$13) -> 343107.99 | D4: =C4/(1-Controls!$B$14) -> 490154.27 | E4: =D4*(1+Controls!$B$10) -> 529366.61 | F4: =E4/Controls!$B$5 -> 20.204833 | G4: =E4/Controls!$B$4 -> 28.691957 | H4: =E4/LandedCost!E4 -> 2.3917937 | I4: 650000 | J4: 850000 | K4: =IF(E4<I4,"Below band — room to price up",IF(E4>J4,"Above band — promo-room risk","Within band")) -> Below band — room to price up | L4: =(((I4+J4)/2/((1+Controls!$B$13)/(1-Controls!$B$14)*(1+Controls!$B$10))-Controls!$B$17/Controls!$B$18)/(1+Controls!$B$9)-Controls!$B$8)/Controls!$B$4 -> 17.341411 | M4: =IF(N(Controls!$B$26)>0,LandedCost!E4*Controls!$B$26,"") | N4: =IF(N(Controls!$B$27)>0,LandedCost!E4*Controls!$B$27,"") | O4: =IF(OR(M4="",N4=""),"Enter channel multiples",IF(N4<I4,"Below band",IF(M4>J4,"Above band at both multiples",IF(AND(M4>=I4,N4<=J4),"In band at both","Straddles band")))) -> Enter channel multiples
A5: Magnesium bisglycinate (120 caps) | B5: =LandedCost!K5 -> 221866.2 | C5: =B5*(1+Controls!$B$13) -> 321705.99 | D5: =C5/(1-Controls!$B$14) -> 459579.99 | E5: =D5*(1+Controls!$B$10) -> 496346.38 | F5: =E5/Controls!$B$5 -> 18.944518 | G5: =E5/Controls!$B$4 -> 26.902243 | H5: =E5/LandedCost!E5 -> 2.4028441 | I5: 220000 | J5: 500000 | K5: =IF(E5<I5,"Below band — room to price up",IF(E5>J5,"Above band — promo-room risk","Within band")) -> Within band | L5: =(((I5+J5)/2/((1+Controls!$B$13)/(1-Controls!$B$14)*(1+Controls!$B$10))-Controls!$B$17/Controls!$B$18)/(1+Controls!$B$9)-Controls!$B$8)/Controls!$B$4 -> 7.892658 | M5: =IF(N(Controls!$B$26)>0,LandedCost!E5*Controls!$B$26,"") | N5: =IF(N(Controls!$B$27)>0,LandedCost!E5*Controls!$B$27,"") | O5: =IF(OR(M5="",N5=""),"Enter channel multiples",IF(N5<I5,"Below band",IF(M5>J5,"Above band at both multiples",IF(AND(M5>=I5,N5<=J5),"In band at both","Straddles band")))) -> Enter channel multiples
A6: Greens: Digest & Renew (340g) | B6: =LandedCost!K6 -> 336256.2 | C6: =B6*(1+Controls!$B$13) -> 487571.49 | D6: =C6/(1-Controls!$B$14) -> 696530.7 | E6: =D6*(1+Controls!$B$10) -> 752253.16 | F6: =E6/Controls!$B$5 -> 28.711953 | G6: =E6/Controls!$B$4 -> 40.772529 | H6: =E6/LandedCost!E6 -> 2.3437876 | I6: 350000 | J6: 600000 | K6: =IF(E6<I6,"Below band — room to price up",IF(E6>J6,"Above band — promo-room risk","Within band")) -> Above band — promo-room risk | L6: =(((I6+J6)/2/((1+Controls!$B$13)/(1-Controls!$B$14)*(1+Controls!$B$10))-Controls!$B$17/Controls!$B$18)/(1+Controls!$B$9)-Controls!$B$8)/Controls!$B$4 -> 10.678829 | M6: =IF(N(Controls!$B$26)>0,LandedCost!E6*Controls!$B$26,"") | N6: =IF(N(Controls!$B$27)>0,LandedCost!E6*Controls!$B$27,"") | O6: =IF(OR(M6="",N6=""),"Enter channel multiples",IF(N6<I6,"Below band",IF(M6>J6,"Above band at both multiples",IF(AND(M6>=I6,N6<=J6),"In band at both","Straddles band")))) -> Enter channel multiples
A7: Fibre: Whole Psyllium (454g) | B7: =LandedCost!K7 -> 207106.2 | C7: =B7*(1+Controls!$B$13) -> 300303.99 | D7: =C7/(1-Controls!$B$14) -> 429005.7 | E7: =D7*(1+Controls!$B$10) -> 463326.16 | F7: =E7/Controls!$B$5 -> 17.684204 | G7: =E7/Controls!$B$4 -> 25.112529 | H7: =E7/LandedCost!E7 -> 2.4155953 | I7: 250000 | J7: 400000 | K7: =IF(E7<I7,"Below band — room to price up",IF(E7>J7,"Above band — promo-room risk","Within band")) -> Above band — promo-room risk | L7: =(((I7+J7)/2/((1+Controls!$B$13)/(1-Controls!$B$14)*(1+Controls!$B$10))-Controls!$B$17/Controls!$B$18)/(1+Controls!$B$9)-Controls!$B$8)/Controls!$B$4 -> 7.044693 | M7: =IF(N(Controls!$B$26)>0,LandedCost!E7*Controls!$B$26,"") | N7: =IF(N(Controls!$B$27)>0,LandedCost!E7*Controls!$B$27,"") | O7: =IF(OR(M7="",N7=""),"Enter channel multiples",IF(N7<I7,"Below band",IF(M7>J7,"Above band at both multiples",IF(AND(M7>=I7,N7<=J7),"In band at both","Straddles band")))) -> Enter channel multiples
A8: Probiotics | B8: =LandedCost!K8 -> 273600 | C8: =B8*(1+Controls!$B$13) -> 396720 | D8: =C8/(1-Controls!$B$14) -> 566742.86 | E8: =D8*(1+Controls!$B$10) -> 612082.29 | F8: =E8/Controls!$B$5 -> 23.361919 | G8: =E8/Controls!$B$4 -> 33.175192 | H8: =E8/LandedCost!E8 -> 2.3696565 | I8: 350000 | J8: 550000 | K8: =IF(E8<I8,"Below band — room to price up",IF(E8>J8,"Above band — promo-room risk","Within band")) -> Above band — promo-room risk | L8: =(((I8+J8)/2/((1+Controls!$B$13)/(1-Controls!$B$14)*(1+Controls!$B$10))-Controls!$B$17/Controls!$B$18)/(1+Controls!$B$9)-Controls!$B$8)/Controls!$B$4 -> 10.07314 | M8: =IF(N(Controls!$B$26)>0,LandedCost!E8*Controls!$B$26,"") | N8: =IF(N(Controls!$B$27)>0,LandedCost!E8*Controls!$B$27,"") | O8: =IF(OR(M8="",N8=""),"Enter channel multiples",IF(N8<I8,"Below band",IF(M8>J8,"Above band at both multiples",IF(AND(M8>=I8,N8<=J8),"In band at both","Straddles band")))) -> Enter channel multiples
A9: Vitamin C / dailies | B9: =LandedCost!K9 -> 126000 | C9: =B9*(1+Controls!$B$13) -> 182700 | D9: =C9/(1-Controls!$B$14) -> 261000 | E9: =D9*(1+Controls!$B$10) -> 281880 | F9: =E9/Controls!$B$5 -> 10.758779 | G9: =E9/Controls!$B$4 -> 15.278049 | H9: =E9/LandedCost!E9 -> 2.5463415 | I9: 60000 | J9: 150000 | K9: =IF(E9<I9,"Below band — room to price up",IF(E9>J9,"Above band — promo-room risk","Within band")) -> Above band — promo-room risk | L9: =(((I9+J9)/2/((1+Controls!$B$13)/(1-Controls!$B$14)*(1+Controls!$B$10))-Controls!$B$17/Controls!$B$18)/(1+Controls!$B$9)-Controls!$B$8)/Controls!$B$4 -> 1.7146269 | M9: =IF(N(Controls!$B$26)>0,LandedCost!E9*Controls!$B$26,"") | N9: =IF(N(Controls!$B$27)>0,LandedCost!E9*Controls!$B$27,"") | O9: =IF(OR(M9="",N9=""),"Enter channel multiples",IF(N9<I9,"Below band",IF(M9>J9,"Above band at both multiples",IF(AND(M9>=I9,N9<=J9),"In band at both","Straddles band")))) -> Enter channel multiples

Sheet Channels
A1: Channel economics — what the brand nets per unit
A2: For the hero SKU at its modeled shelf price. Edit take rates (blue) to your real terms.
A4: Shelf price (hero SKU, from SKU_Economics) | B4: =SKU_Economics!E4 -> 529366.61
A6: Channel | B6: Platform take % | C6: Affiliate/KOC % | D6: Voucher/co-fund % | E6: Total deductions % | F6: Net to seller (VND) | G6: Net vs landed+reg (VND) | H6: Net margin %
A7: Shopee Mall | B7: 0.21 | C7: 0.15 | D7: 0.07 | E7: =B7+C7+D7 -> 0.43 | F7: =$B$4*(1-E7) -> 301738.97 | G7: =F7-LandedCost!K4 -> 65112.769 | H7: =IF(F7=0,0,G7/F7) -> 0.21579171
A8: TikTok Shop Mall | B8: 0.18 | C8: 0.18 | D8: 0.05 | E8: =B8+C8+D8 -> 0.41 | F8: =$B$4*(1-E8) -> 312326.3 | G8: =F8-LandedCost!K4 -> 75700.102 | H8: =IF(F8=0,0,G8/F8) -> 0.24237505
A9: Lazada / LazMall | B9: 0.15 | C9: 0.05 | D9: 0.03 | E9: =B9+C9+D9 -> 0.23 | F9: =$B$4*(1-E9) -> 407612.29 | G9: =F9-LandedCost!K4 -> 170986.09 | H9: =IF(F9=0,0,G9/F9) -> 0.41948218
A10: Chain pharmacy (no platform) | B10: 0 | C10: 0 | D10: 0 | E10: =B10+C10+D10 -> 0 | F10: =$B$4*(1-E10) -> 529366.61 | G10: =F10-LandedCost!K4 -> 292740.41 | H10: =IF(F10=0,0,G10/F10) -> 0.55300128
A12: Chain pharmacy: platform take is zero but the retail margin already sits inside the shelf price (SKU_Economics). Net here is the brand/distributor side.

Sheet Scenarios
A1: Scenarios — duty and FX sensitivity (hero SKU) | H1: hero FOB CAD | I1: =LandedCost!D4 -> 11.996
A3: Duty scenario comparison (hero SKU shelf price)
A4: Scenario | B4: Duty rate | C4: Landed (VND) | D4: Shelf (VND) | E4: Shelf (CAD) | F4: FOB multiple
A5: CPTPP 0% (with C/O) | B5: 0 | C5: =(LandedCost!E4+Controls!$B$8)*(1+B5)+Controls!$B$17/Controls!$B$18 -> 236626.2 | D5: =(C5*(1+Controls!$B$13)/(1-Controls!$B$14))*(1+Controls!$B$10) -> 529366.61 | E5: =D5/Controls!$B$4 -> 28.691957 | F5: =D5/LandedCost!E4 -> 2.3917937
A6: MFN 15% (no C/O) | B6: 0.15 | C6: =(LandedCost!E4+Controls!$B$8)*(1+B6)+Controls!$B$17/Controls!$B$18 -> 271595.13 | D6: =(C6*(1+Controls!$B$13)/(1-Controls!$B$14))*(1+Controls!$B$10) -> 607597.11 | E6: =D6/Controls!$B$4 -> 32.932092 | F6: =D6/LandedCost!E4 -> 2.7452561
A7: Medical-nutrition 7% | B7: 0.07 | C7: =(LandedCost!E4+Controls!$B$8)*(1+B7)+Controls!$B$17/Controls!$B$18 -> 252945.03 | D7: =(C7*(1+Controls!$B$13)/(1-Controls!$B$14))*(1+Controls!$B$10) -> 565874.18 | E7: =D7/Controls!$B$4 -> 30.670687 | F7: =D7/LandedCost!E4 -> 2.5567428
A10: FX sensitivity — CPTPP shelf price at different CAD/VND
A11: CAD to VND | B11: Shelf (VND) | C11: Shelf (CAD)
A12: 17500 | B12: =((LandedCost!D4*A12+Controls!$B$8)+Controls!$B$17/Controls!$B$18)*(1+Controls!$B$13)/(1-Controls!$B$14)*(1+Controls!$B$10) -> 503871.69 | C12: =B12/A12 -> 28.792668
A13: 18000 | B13: =((LandedCost!D4*A13+Controls!$B$8)+Controls!$B$17/Controls!$B$18)*(1+Controls!$B$13)/(1-Controls!$B$14)*(1+Controls!$B$10) -> 517290.07 | C13: =B13/A13 -> 28.738337
A14: 18450 | B14: =((LandedCost!D4*A14+Controls!$B$8)+Controls!$B$17/Controls!$B$18)*(1+Controls!$B$13)/(1-Controls!$B$14)*(1+Controls!$B$10) -> 529366.61 | C14: =B14/A14 -> 28.691957
A15: 19000 | B15: =((LandedCost!D4*A15+Controls!$B$8)+Controls!$B$17/Controls!$B$18)*(1+Controls!$B$13)/(1-Controls!$B$14)*(1+Controls!$B$10) -> 544126.83 | C15: =B15/A15 -> 28.638254
A16: 19500 | B16: =((LandedCost!D4*A16+Controls!$B$8)+Controls!$B$17/Controls!$B$18)*(1+Controls!$B$13)/(1-Controls!$B$14)*(1+Controls!$B$10) -> 557545.22 | C16: =B16/A16 -> 28.592062
