Workbook

Sheet ReadMe
A1: Vietnam partner scorecard
A2: Score the existing partner's renewal plan and any new distributor side by side, on evidence. Internal only.
A4: HOW TO USE
A5: 1 | B5: After each meeting, enter a 1 to 5 score per criterion on the Scorecard tab (yellow cells). Leave blank what you have not verified.
A6: 2 | B6: Write the evidence behind each score on the Evidence tab. A score without evidence is an opinion; keep opinions out of this file.
A7: 3 | B7: Two criteria are must-pass gates (Registration terms, Financial strength). Any score below 3 on either fails the gate, whatever the total.
A8: 4 | B8: Weights are editable on the Criteria tab and must total 100%. The weighted score averages only the criteria you have scored.
A9: 5 | B9: Use the Questions tab in the meeting: each criterion lists the evidence to request.
A11: SCORING SCALE
A12: 5 | B12: Proven with documents or references
A13: 4 | B13: Strong, partly evidenced
A14: 3 | B14: Adequate, or promised in writing
A15: 2 | B15: Weak, or promised verbally only
A16: 1 | B16: Absent or a red flag
A18: CELL LEGEND
A19: Yellow fill | B19: Input: a score or a weight
A20: Blue text | B20: Hardcoded input
A21: Black text | B21: Formula; do not overwrite
A23: CONFIDENTIALITY
A24: Internal | B24: Do not share outside Organika. Never show a candidate its own or another candidate's scores.
A25: Example column | B25: The Example column on the Scorecard is illustrative only, to show the format. It is not a real candidate.

Sheet Scorecard
A1: Scorecard
A2: Scores 1 to 5. Blank = not yet verified. Gate rows decide first; totals rank only gate passers.
A4: # | B4: Criterion | C4: Weight | D4: Must pass | E4: Existing partner (renewal plan) | F4: Candidate A | G4: Candidate B | H4: Candidate C | I4: Candidate D | J4: Example (illustrative)
A5: 1 | B5: Pharmacy chain access | C5: =Criteria!C4 -> 0.15 | D5: =Criteria!D4 -> 0 | J5: 4
A6: 2 | B6: Independent pharmacy reach | C6: =Criteria!C5 -> 0.1 | D6: =Criteria!D5 -> 0 | J6: 3
A7: 3 | B7: Official ecommerce capability | C7: =Criteria!C6 -> 0.12 | D7: =Criteria!D6 -> 0 | J7: 2
A8: 4 | B8: Registration terms | C8: =Criteria!C7 -> 0.15 | D8: =Criteria!D7 -> YES | J8: 4
A9: 5 | B9: Marketing investment and execution | C9: =Criteria!C8 -> 0.1 | D9: =Criteria!D8 -> 0 | J9: 3
A10: 6 | B10: Portfolio fit and conflicts | C10: =Criteria!C9 -> 0.1 | D10: =Criteria!D9 -> 0 | J10: 5
A11: 7 | B11: Financial strength and payment record | C11: =Criteria!C10 -> 0.1 | D11: =Criteria!D10 -> YES | J11: 4
A12: 8 | B12: Authenticity and price discipline | C12: =Criteria!C11 -> 0.08 | D12: =Criteria!D11 -> 0 | J12: 2
A13: 9 | B13: Commitment and focus | C13: =Criteria!C12 -> 0.1 | D13: =Criteria!D12 -> 0 | J13: 4
B15: Criteria scored | E15: =COUNT(E5:E13)&" of 9" -> 0 of 9 | F15: =COUNT(F5:F13)&" of 9" -> 0 of 9 | G15: =COUNT(G5:G13)&" of 9" -> 0 of 9 | H15: =COUNT(H5:H13)&" of 9" -> 0 of 9 | I15: =COUNT(I5:I13)&" of 9" -> 0 of 9 | J15: =COUNT(J5:J13)&" of 9" -> 9 of 9
B16: Weighted score (out of 5) | E16: =IF(COUNT(E5:E13)=0,"",SUMPRODUCT(E5:E13,$C$5:$C$13)/SUMPRODUCT(--(E5:E13<>""),$C$5:$C$13)) | F16: =IF(COUNT(F5:F13)=0,"",SUMPRODUCT(F5:F13,$C$5:$C$13)/SUMPRODUCT(--(F5:F13<>""),$C$5:$C$13)) | G16: =IF(COUNT(G5:G13)=0,"",SUMPRODUCT(G5:G13,$C$5:$C$13)/SUMPRODUCT(--(G5:G13<>""),$C$5:$C$13)) | H16: =IF(COUNT(H5:H13)=0,"",SUMPRODUCT(H5:H13,$C$5:$C$13)/SUMPRODUCT(--(H5:H13<>""),$C$5:$C$13)) | I16: =IF(COUNT(I5:I13)=0,"",SUMPRODUCT(I5:I13,$C$5:$C$13)/SUMPRODUCT(--(I5:I13<>""),$C$5:$C$13)) | J16: =IF(COUNT(J5:J13)=0,"",SUMPRODUCT(J5:J13,$C$5:$C$13)/SUMPRODUCT(--(J5:J13<>""),$C$5:$C$13)) -> 3.5
B17: Gate | E17: =IF(COUNT(E5:E13)=0,"",IF(OR(AND(ISNUMBER(E8),E8<3),AND(ISNUMBER(E11),E11<3)),"FAILS GATE",IF(OR(ISBLANK(E8),ISBLANK(E11)),"Gate not yet scored","Passes gate"))) | F17: =IF(COUNT(F5:F13)=0,"",IF(OR(AND(ISNUMBER(F8),F8<3),AND(ISNUMBER(F11),F11<3)),"FAILS GATE",IF(OR(ISBLANK(F8),ISBLANK(F11)),"Gate not yet scored","Passes gate"))) | G17: =IF(COUNT(G5:G13)=0,"",IF(OR(AND(ISNUMBER(G8),G8<3),AND(ISNUMBER(G11),G11<3)),"FAILS GATE",IF(OR(ISBLANK(G8),ISBLANK(G11)),"Gate not yet scored","Passes gate"))) | H17: =IF(COUNT(H5:H13)=0,"",IF(OR(AND(ISNUMBER(H8),H8<3),AND(ISNUMBER(H11),H11<3)),"FAILS GATE",IF(OR(ISBLANK(H8),ISBLANK(H11)),"Gate not yet scored","Passes gate"))) | I17: =IF(COUNT(I5:I13)=0,"",IF(OR(AND(ISNUMBER(I8),I8<3),AND(ISNUMBER(I11),I11<3)),"FAILS GATE",IF(OR(ISBLANK(I8),ISBLANK(I11)),"Gate not yet scored","Passes gate"))) | J17: =IF(COUNT(J5:J13)=0,"",IF(OR(AND(ISNUMBER(J8),J8<3),AND(ISNUMBER(J11),J11<3)),"FAILS GATE",IF(OR(ISBLANK(J8),ISBLANK(J11)),"Gate not yet scored","Passes gate"))) -> Passes gate
B18: Rank (gate passers) | E18: =IF(ISNUMBER(E20),RANK(E20,$E$20:$I$20),"") | F18: =IF(ISNUMBER(F20),RANK(F20,$E$20:$I$20),"") | G18: =IF(ISNUMBER(G20),RANK(G20,$E$20:$I$20),"") | H18: =IF(ISNUMBER(H20),RANK(H20,$E$20:$I$20),"") | I18: =IF(ISNUMBER(I20),RANK(I20,$E$20:$I$20),"") | J18: n/a
B20: Helper: score if gate passed | E20: =IF(E17="Passes gate",E16,"") | F20: =IF(F17="Passes gate",F16,"") | G20: =IF(G17="Passes gate",G16,"") | H20: =IF(H17="Passes gate",H16,"") | I20: =IF(I17="Passes gate",I16,"")

Sheet Criteria
A1: Criteria and weights
A3: # | B3: Criterion | C3: Weight | D3: Must pass | E3: What a 5 looks like | F3: What a 1 looks like | G3: Primer anchor
A4: 1 | B4: Pharmacy chain access | C4: 0.15 | E4: Lists supplements at Long Chau and Pharmacity today, with named buyer contacts | F4: No chain listings; independents only | G4: Ch2.1, Ch8.1
A5: 2 | B5: Independent pharmacy reach | C5: 0.1 | E5: National rep force covering Hapulico and Tô Hiến Thành hubs and tier 2 cities | F5: One city, no reps | G5: Ch2.6
A6: 3 | B6: Official ecommerce capability | C6: 0.12 | E6: Runs official Shopee Mall and TikTok Shop stores for other brands, with livestream experience | F6: No official stores | G6: Ch2.7–2.9
A7: 4 | B7: Registration terms | C7: 0.15 | D7: YES | E7: Agrees in writing that Organika (or an independent agent) holds registrations, with a handover clause | F7: Insists on holding registrations with no handover | G7: Ch5.3, Ch8.2
A8: 5 | B8: Marketing investment and execution | C8: 0.1 | E8: Funds and runs pharmacist education and compliant KOC programs; shows dossier matched ad approvals | F8: No marketing capability | G8: Ch4 W4, Ch5.4
A9: 6 | B9: Portfolio fit and conflicts | C9: 0.1 | E9: No competing collagen or magnesium brand; complementary categories | F9: Carries a direct competitor in lead SKUs | G9: Ch3
A10: 7 | B10: Financial strength and payment record | C10: 0.1 | D10: YES | E10: Pays to terms on deposit or L/C; trade references check out | F10: Late payments, no references | G10: Ch8.1
A11: 8 | B11: Authenticity and price discipline | C11: 0.08 | E11: QR or GS1 authenticity program; enforces a price ladder; acts on grey market | F11: No authenticity controls | G11: Ch4 W2, F9
A12: 9 | B12: Commitment and focus | C12: 0.1 | E12: Names one accountable brand owner; agrees quarterly reviews and volume milestones | F12: Organika would be a filler line | G12: Ch8.2, Ch4 W4
B13: Total (must be 100%) | C13: =SUM(C4:C12) -> 1 | D13: =IF(ROUND(C13,4)=1,"OK","Weights must total 100%") -> OK

Sheet Evidence
A1: Evidence log
A2: One line per fact. Source and date for each. Facts only: no opinions about people.
A4: Date | B4: Candidate | C4: Criterion | D4: Evidence (fact, not opinion) | E4: Source / document | F4: Verified?

Sheet Questions
A1: Meeting questions, by criterion
A2: Ask for the evidence, not the claim. Rehearse the objection drill in the primer (Ch8.6) alongside these.
A4: Criterion | B4: Question | C4: Answer heard | D4: Evidence requested
A5: Pharmacy chain access | B5: Which supplement brands do you list at Long Chau and Pharmacity today, and since when?
A6: Pharmacy chain access | B6: Who are your buyer contacts there, and what did the last listing take?
A7: Independent pharmacy reach | B7: How many reps, in which regions? Which wholesale hubs do you supply?
A8: Official ecommerce capability | B8: Which brands do you run official Shopee and TikTok stores for? Can we see the stores?
A9: Official ecommerce capability | B9: Have you cleared TikTok Shop restricted category approval for supplements?
A10: Registration terms | B10: Will you agree in writing that Organika or an independent agent holds the registrations, with a handover clause?
A11: Registration terms | B11: Which consultant do you use, and what turnaround are you seeing on new TPBVSK dossiers right now?
A12: Registration terms | B12: How will dossiers in progress transition when the new food safety law takes effect?
A13: Marketing investment and execution | B13: What pharmacist education or KOC programs have you run, and how did you get the ad content approved?
A14: Marketing investment and execution | B14: What would you co invest at launch?
A15: Portfolio fit and conflicts | B15: Which collagen and magnesium brands do you carry or plan to carry?
A16: Financial strength and payment record | B16: What payment terms do you run with other principals? Can you share two trade references?
... A18: Commitment and focus | B18: Who would own Organika day to day? What volume milestones would you commit to for exclusivity?
