Workbook

Sheet Dashboard
B2: Commercial Control Tower
B3: Claude Cowork Commercial OS v4 · one workbook per project
B4: Set the project name in cell D4 → | D4: [Project]
B6: Health at a glance
B7: Open actions | C7: =COUNTIFS('Action Tracker'!F:F,"<>Done",'Action Tracker'!F:F,"<>Dropped",'Action Tracker'!B:B,"<>")-1
B8: Overdue actions | C8: =COUNTIFS('Action Tracker'!G:G,"<"&TODAY(),'Action Tracker'!F:F,"<>Done",'Action Tracker'!F:F,"<>Dropped")
B9: P0 / P1 open | C9: =COUNTIFS('Action Tracker'!E:E,"P0",'Action Tracker'!F:F,"<>Done")+COUNTIFS('Action Tracker'!E:E,"P1",'Action Tracker'!F:F,"<>Done")
B10: Actions missing owner | C10: =COUNTIFS('Action Tracker'!C:C,"",'Action Tracker'!B:B,"<>")-1
B11: Actions missing due date | C11: =COUNTIFS('Action Tracker'!G:G,"",'Action Tracker'!B:B,"<>")-1
B12: Open customer asks | C12: =COUNTIFS('Customer Asks'!G:G,"<>Done",'Customer Asks'!G:G,"<>Dropped",'Customer Asks'!B:B,"<>")-1
B13: Live risks (High) | C13: =COUNTIFS('Risk Register'!C:C,"High",'Risk Register'!G:G,"<>Done")
B14: Open decisions to revisit | C14: =COUNTIF('Decision Log'!G:G,"Revisit")
B15: Deck backlog open | C15: =COUNTIFS('Deck Backlog'!G:G,"<>Done",'Deck Backlog'!B:B,"<>")-1
B16: Meetings unprocessed | C16: =COUNTIF('Meeting Queue'!E:E,"No")+COUNTIF('Meeting Queue'!E:E,"Partial")
B18: The rule that matters
B19: No summary is finished until the parts that matter have landed here.
B21: Tabs: Action Tracker · Decision Log · Risk Register · Customer Asks · Deck Backlog · Meeting Queue · File Index
B22: Update in review-copy mode by default. Never mark Done without evidence.

Sheet Action Tracker
A1: ID | B1: Action | C1: Owner | D1: Priority | E1: Type | F1: Status | G1: Due Date | H1: Created | I1: Source Meeting | J1: Notes / Evidence
A2: A-001 | B2: Send Costco buyer the revised pack architecture options | C2: Louis | D2: P1 | E2: Customer-facing | F2: In Progress | G2: =TODAY()+3 | H2: =TODAY()-1 | I2: Costco JBP prep | J2: Buyer asked for 2 vs 3 pack options with landed cost
A3: A-002 | B3: Confirm item setup timing with supply planning | D3: P0 | E3: Internal | F3: Open | G3: =TODAY()+1 | H3: =TODAY()-1 | I3: Costco JBP prep | J3: MISSING OWNER — assign before it slips
A4: A-003 | B4: Update forecast file with committed promo weeks | C4: Teresa | D4: P2 | E4: Internal | F4: Waiting | G4: =TODAY()-2 | H4: =TODAY()-5 | I4: Weekly sync | J4: OVERDUE example — waiting on promo calendar sign-off

Sheet Decision Log
A1: ID | B1: Decision | C1: Date | D1: Owner | E1: Rationale | F1: Source | G1: Status | H1: Notes
A2: D-001 | B2: Lead with 3-pack architecture for Costco line review | C2: =TODAY()-1 | D2: Aaron | E2: Better landed cost story and cleaner shelf block | F2: Costco JBP prep | G2: Decided | H2: Revisit if buyer pushes on price gap

Sheet Risk Register
A1: ID | B1: Risk | C1: Severity | D1: Likelihood | E1: Mitigation | F1: Owner | G1: Status | H1: Review Date | I1: Notes
A2: R-001 | B2: Item setup may miss the Costco reset window | C2: High | D2: Medium | E2: Lock setup timing with supply planning this week | F2: Louis | G2: Open | H2: =TODAY()+7 | I2: Tied to A-002

Sheet Customer Asks
A1: ID | B1: Ask | C1: Requested By | D1: Date | E1: Internal Owner | F1: Internal Action Needed | G1: Status | H1: Due | I1: Notes
A2: C-001 | B2: Two vs three pack options with landed cost | C2: Costco buyer | D2: =TODAY()-1 | E2: Louis | F2: Build costed pack-architecture comparison | G2: Open | H2: =TODAY()+3 | I2: Feeds A-001

Sheet Deck Backlog
A1: ID | B1: Slide / Section | C1: Current State | D1: Needed Change | E1: Why It Matters | F1: Priority | G1: Status | H1: Notes
A2: K-001 | B2: Pack architecture | C2: Shows 2-pack only | D2: Add 3-pack option + landed cost | E2: Buyer asked; changes the margin story | F2: P1 | G2: Open | H2: After A-001 lands

Sheet Meeting Queue
A1: ID | B1: Meeting | C1: Date | D1: Artifacts | E1: Processed? | F1: Summary File | G1: Notes
A2: M-001 | B2: Costco JBP prep | C2: =TODAY()-1 | D2: Transcript + notes + agenda | E2: Yes | F2: YYYY-MM-DD - Costco - Meeting Summary - JBP prep | G2: One queue entry per meeting
A3: M-002 | B3: Weekly internal sync | C3: =TODAY() | D3: Recording | E3: No | G3: Awaiting Meeting Inbox Processor

Sheet File Index
A1: Type | B1: File Name | C1: Status | D1: Location | E1: Last Updated | F1: Notes
A2: Deck | B2: Costco Line Review vX.pptx | C2: Approved (source of truth) | D2: /04 Decks | E2: =TODAY()-3 | F2: The one Claude should read first
A3: Deck | B3: REVIEW - Costco Line Review.pptx | C3: Review copy | D3: /04 Decks | E3: =TODAY()-1 | F3: Working edits only
A4: Workbook | B4: Commercial_Control_Tower_Template_v2.xlsx | C4: Approved (source of truth) | D4: /02 Control Tower | E4: =TODAY() | F4: This file
A5: Forecast | B5: Costco Forecast vX.xlsx | C5: Approved (source of truth) | D5: /05 Workbooks | E5: =TODAY()-4
